Workbook

Sheet AMD Financials
A1: Income Statement ($mm)
A3: Line Item | B3: Q1 2016 | C3: Q2 2016 | D3: Q3 2016 | E3: Q4 2016 | F3: Q1 2017 | G3: Q2 2017 | H3: Q3 2017 | I3: Q4 2017 | J3: Q1 2018 | K3: Q2 2018 | L3: Q3 2018 | M3: Q4 2018 | N3: Q1 2019 | O3: Q2 2019 | P3: Q3 2019 | Q3: Q4 2019 | R3: Q1 2020 | S3: Q2 2020 | T3: Q3 2020 | U3: Q4 2020 | V3: Q1 2021 | W3: Q2 2021 | X3: Q3 2021 | Y3: Q4 2021 | Z3: Q1 2022 | AA3: Q2 2022 | AB3: Q3 2022 | AC3: Q4 2022 | AD3: Q1 2023 | AE3: Q2 2023 | AF3: Q3 2023 | AG3: Q4 2023 | AH3: Q1 2024 | AI3: Q2 2024 | AJ3: Q3 2024 | AK3: Q4 2024 | AL3: Q1 2025 | AM3: Q2 2025 | AN3: Q3 2025 | AO3: Q4 2025
A4: Revenue | B4: 832 | C4: 1027 | D4: 1307 | E4: 1106 | F4: 1178 | G4: 1151 | H4: 1584 | I4: 1340 | J4: 1647 | K4: 1756 | L4: 1653 | M4: 1419 | N4: 1272 | O4: 1531 | P4: 1801 | Q4: 2127 | R4: 1786 | S4: 1932 | T4: 2801 | U4: 3244 | V4: 3445 | W4: 3850 | X4: 4313 | Y4: 4826 | Z4: 5887 | AA4: 6550 | AB4: 5565 | AC4: 5599 | AD4: 5353 | AE4: 5359 | AF4: 5800 | AG4: 6168 | AH4: 5473 | AI4: 5835 | AJ4: 6819 | AK4: 7658 | AL4: 7438 | AM4: 7685 | AN4: 9246 | AO4: 10270
A5: Cost of Revenue | B5: 563 | C5: 708 | D5: 908 | E5: 1095 | F5: 800 | G5: 765 | H5: 1013 | I5: 888 | J5: 1050 | K5: 1104 | L5: 992 | M5: 837 | N5: 751 | O5: 910 | P5: 1024 | Q5: 1178 | R5: 968 | S5: 1084 | T5: 1571 | U5: 1793 | V5: 1858 | W5: 2020 | X5: 2227 | Y5: 2400 | Z5: 2883 | AA5: 3115 | AB5: 2799 | AC5: 2753 | AD5: 2689 | AE5: 2704 | AF5: 2843 | AG5: 3042 | AH5: 2683 | AI5: 2740 | AJ5: 3167 | AK5: 3524 | AL5: 3451 | AM5: 4366 | AN5: 4206 | AO5: 4433
A6: Gross Profit | B6: =B4-B5 -> 269 | C6: =C4-C5 -> 319 | D6: =D4-D5 -> 399 | E6: =E4-E5 -> 11 | F6: =F4-F5 -> 378 | G6: =G4-G5 -> 386 | H6: =H4-H5 -> 571 | I6: =I4-I5 -> 452 | ... AO6: =AO4-AO5 -> 5837
A7: SG&A | B7: 105 | C7: 117 | D7: 117 | E7: 121 | F7: 123 | G7: 127 | H7: 132 | I7: 134 | J7: 134 | K7: 142 | L7: 148 | M7: 138 | N7: 170 | O7: 189 | P7: 185 | Q7: 206 | R7: 199 | S7: 215 | T7: 273 | U7: 308 | V7: 319 | W7: 341 | X7: 368 | Y7: 445 | Z7: 597 | AA7: 592 | AB7: 557 | AC7: 590 | AD7: 585 | AE7: 547 | AF7: 576 | AG7: 644 | AH7: 607 | AI7: 640 | AJ7: 707 | AK7: 781 | AL7: 886 | AM7: 955 | AN7: 1069 | AO7: 1198
A8: Research & Development | B8: 242 | C8: 243 | D8: 259 | E8: 264 | F8: 271 | G8: 285 | H8: 320 | I8: 320 | J8: 343 | K8: 357 | L8: 363 | M8: 371 | N8: 373 | O8: 373 | P8: 406 | Q8: 395 | R8: 442 | S8: 460 | T8: 508 | U8: 573 | V8: 610 | W8: 659 | X8: 765 | Y8: 811 | Z8: 1060 | AA8: 1300 | AB8: 1279 | AC8: 1366 | AD8: 1411 | AE8: 1443 | AF8: 1507 | AG8: 1511 | AH8: 1525 | AI8: 1583 | AJ8: 1636 | AK8: 1712 | AL8: 1728 | AM8: 1894 | AN8: 2139 | AO8: 2330
A9: Amortization of Goodwill & Intangibles | B9: 0 | C9: 0 | D9: 0 | E9: 0 | F9: 0 | G9: 0 | H9: 0 | I9: 0 | J9: 0 | K9: 0 | L9: 0 | M9: 0 | N9: 0 | O9: 0 | P9: 0 | Q9: 0 | R9: 0 | S9: 0 | T9: 0 | U9: 0 | V9: 0 | W9: 0 | X9: 0 | Y9: 0 | Z9: 479 | AA9: 1023 | AB9: 1002 | AC9: 1044 | AD9: 823 | AE9: 693 | AF9: 660 | AG9: 635 | AH9: 622 | AI9: 603 | AJ9: 585 | AK9: 584 | AL9: 567 | AM9: 568 | AN9: 562 | AO9: 557
A10: Other Operating Expenses | B10: -7 | C10: -26 | D10: -24 | E10: -31 | F10: -27 | G10: -25 | H10: 0 | I10: 0 | J10: 0 | K10: 0 | L10: 0 | M10: 0 | N10: -60 | O10: 0 | P10: 0 | Q10: 0 | R10: 0 | S10: 0 | T10: 0 | U10: 0 | V10: -4 | W10: -1 | X10: -3 | Y10: -4 | Z10: -83 | AA10: -6 | AB10: -8 | AC10: -5 | AD10: -10 | AE10: -8 | AF10: -10 | AG10: -6 | AH10: 0 | AI10: 0 | AJ10: 0 | AK10: 0 | AL10: 0 | AM10: 0 | AN10: 0 | AO10: 0
A11: Operating Income | B11: =B6-B7-B8-B9-B10 -> -71 | C11: =C6-C7-C8-C9-C10 -> -15 | D11: =D6-D7-D8-D9-D10 -> 47 | E11: =E6-E7-E8-E9-E10 -> -343 | F11: =F6-F7-F8-F9-F10 -> 11 | G11: =G6-G7-G8-G9-G10 -> -1 | H11: =H6-H7-H8-H9-H10 -> 119 | I11: =I6-I7-I8-I9-I10 -> -2 | ... AO11: =AO6-AO7-AO8-AO9-AO10 -> 1752
A12: Interest Expense | B12: -40 | C12: -41 | D12: -41 | E12: -34 | F12: -32 | G12: -32 | H12: -31 | I12: -31 | J12: -31 | K12: -31 | L12: -30 | M12: -29 | N12: -27 | O12: -25 | P12: -24 | Q12: -18 | R12: -13 | S12: -14 | T12: -11 | U12: -9 | V12: -9 | W12: -10 | X12: -7 | Y12: -8 | Z12: -13 | AA12: -25 | AB12: -31 | AC12: -19 | AD12: -25 | AE12: -28 | AF12: -26 | AG12: -27 | AH12: -25 | AI12: -25 | AJ12: -23 | AK12: -19 | AL12: -20 | AM12: -38 | AN12: -37 | AO12: -36
A13: Interest & Investment Income | B13: 0 | C13: 0 | D13: 0 | E13: 2 | F13: 0 | G13: 0 | H13: 0 | I13: 6 | J13: 0 | K13: 0 | L13: 0 | M13: 18 | N13: 0 | O13: 0 | P13: 0 | Q13: 15 | R13: 0 | S13: 0 | T13: 0 | U13: 8 | V13: 0 | W13: 0 | X13: 0 | Y13: 8 | Z13: 0 | AA13: 0 | AB13: 22 | AC13: 32 | AD13: 0 | AE13: 0 | AF13: 0 | AG13: 206 | AH13: 0 | AI13: 0 | AJ13: 0 | AK13: 182 | AL13: 0 | AM13: 0 | AN13: 0 | AO13: 215
A14: Earnings From Equity Investments | B14: 0 | C14: -3 | D14: -5 | E14: -2 | F14: -2 | G14: -3 | H14: -2 | I14: 0 | J14: -1 | K14: -1 | L14: 0 | M14: 0 | N14: -1 | O14: 0 | P14: 1 | Q14: 0 | R14: 0 | S14: 1 | T14: 1 | U14: 3 | V14: 2 | W14: 2 | X14: 2 | Y14: 0 | Z14: 3 | AA14: 4 | AB14: 4 | AC14: 3 | AD14: 1 | AE14: 6 | AF14: 3 | AG14: 6 | AH14: 7 | AI14: 7 | AJ14: 7 | AK14: 12 | AL14: 7 | AM14: 8 | AN14: 10 | AO14: 1
A15: Currency Exchange Gain (Loss) | B15: 0 | C15: 2 | D15: 0 | E15: 1 | F15: 0 | G15: -1 | H15: -2 | I15: 0 | J15: -2 | K15: 0 | L15: 0 | M15: -1 | N15: 0 | O15: 0 | P15: 0 | Q15: 0 | R15: 0 | S15: 0 | T15: 0 | U15: 0 | V15: 0 | W15: 0 | X15: 0 | Y15: 0 | Z15: 0 | AA15: 0 | AB15: 0 | AC15: 0 | AD15: 0 | AE15: 0 | AF15: 0 | AG15: 0 | AH15: 0 | AI15: 0 | AJ15: 0 | AK15: 0 | AL15: 0 | AM15: 0 | AN15: 0 | AO15: 0
A16: Other Non Operating Income (Expenses) | B16: 0 | C16: -2 | D16: -2 | E16: 1 | F16: 2 | G16: 1 | H16: -1 | I16: -4 | J16: 4 | K16: 1 | L16: 0 | M16: -8 | N16: 1 | O16: 3 | P16: 0 | Q16: -12 | R16: 4 | S16: 1 | T16: -59 | U16: 51 | V16: 3 | W16: 0 | X16: 2 | Y16: 0 | Z16: 2 | AA16: -4 | AB16: 0 | AC16: 5 | AD16: 43 | AE16: 46 | AF16: 59 | AG16: -156 | AH16: 53 | AI16: 55 | AJ16: 36 | AK16: -147 | AL16: 39 | AM16: 98 | AN16: 82 | AO16: 509
A17: Merger & Restructuring Charges | B17: 3 | C17: 7 | D17: 0 | E17: 0 | F17: 0 | G17: 0 | H17: 0 | I17: 0 | J17: 0 | K17: 0 | L17: 0 | M17: 0 | N17: 0 | O17: 0 | P17: 0 | Q17: 0 | R17: 0 | S17: 0 | T17: 0 | U17: 0 | V17: 0 | W17: 0 | X17: -8 | Y17: 33 | Z17: 0 | AA17: 0 | AB17: 0 | AC17: 0 | AD17: 0 | AE17: 0 | AF17: 0 | AG17: 0 | AH17: 0 | AI17: 0 | AJ17: 0 | AK17: -186 | AL17: 0 | AM17: -36 | AN17: 0 | AO17: 0
A18: Gain (Loss) on Sale of Investments | B18: 0 | C18: 150 | D18: 0 | E18: -4 | F18: -3 | G18: 0 | H18: 0 | I18: 3 | J18: 0 | K18: 0 | L18: 0 | M18: 0 | N18: 0 | O18: 0 | P18: 0 | Q18: 0 | R18: 0 | S18: 0 | T18: 60 | U18: -58 | V18: -8 | W18: 0 | X18: 60 | Y18: -4 | Z18: -44 | AA18: 0 | AB18: 0 | AC18: -5 | AD18: 0 | AE18: 0 | AF18: 0 | AG18: -1 | AH18: 0 | AI18: 0 | AJ18: 0 | AK18: 2 | AL18: 0 | AM18: 0 | AN18: 0 | AO18: -366
A19: Asset Writedown | B19: 0 | C19: 0 | D19: 0 | E19: 0 | F19: 0 | G19: 0 | H19: 0 | I19: 0 | J19: 0 | K19: 0 | L19: 0 | M19: -45 | N19: 0 | O19: 0 | P19: 0 | Q19: 0 | R19: 0 | S19: 0 | T19: 0 | U19: 0 | V19: 0 | W19: 0 | X19: 0 | Y19: 0 | Z19: 0 | AA19: 0 | AB19: 0 | AC19: 0 | AD19: 0 | AE19: 0 | AF19: 0 | AG19: 0 | AH19: 0 | AI19: 0 | AJ19: 0 | AK19: 0 | AL19: 0 | AM19: 0 | AN19: 0 | AO19: 0
A20: Other Unusual Items | B20: 0 | C20: 0 | D20: -401 | E20: 333 | F20: -4 | G20: -3 | H20: 0 | I20: -3 | J20: -1 | K20: 0 | L20: -6 | M20: -5 | N20: -8 | O20: 0 | P20: -36 | Q20: -128 | R20: 0 | S20: 0 | T20: -38 | U20: -16 | V20: -6 | W20: 0 | X20: 0 | Y20: 0 | Z20: 0 | AA20: 0 | AB20: 0 | AC20: 0 | AD20: 0 | AE20: 0 | AF20: 0 | AG20: 0 | AH20: 0 | AI20: 0 | AJ20: 0 | AK20: 0 | AL20: 0 | AM20: 0 | AN20: 0 | AO20: 0
A21: Pretax Income | B21: =SUM(B11:B20) -> -108 | C21: =SUM(C11:C20) -> 98 | D21: =SUM(D11:D20) -> -402 | E21: =SUM(E11:E20) -> -46 | F21: =SUM(F11:F20) -> -28 | G21: =SUM(G11:G20) -> -39 | H21: =SUM(H11:H20) -> 83 | I21: =SUM(I11:I20) -> -31 | ... AO21: =SUM(AO11:AO20) -> 2075
A22: Income Tax Expense | B22: 1 | C22: 29 | D22: 4 | E22: 5 | F22: 5 | G22: 3 | H22: 22 | I22: -12 | J22: 8 | K22: 6 | L22: 12 | M22: -35 | N22: -13 | O22: 2 | P22: 7 | Q22: 35 | R22: 6 | S22: 4 | T22: 12 | U22: -1232 | V22: 89 | W22: 113 | X22: 82 | Y22: 229 | Z22: 113 | AA22: 54 | AB22: -135 | AC22: -154 | AD22: 13 | AE22: -23 | AF22: -39 | AG22: -297 | AH22: -52 | AI22: 41 | AJ22: -27 | AK22: 419 | AL22: 123 | AM22: -834 | AN22: 153 | AO22: 455
A23: Earnings From Discontinued Operations | B23: 0 | C23: 0 | D23: 0 | E23: 0 | F23: 0 | G23: 0 | H23: 0 | I23: 0 | J23: 0 | K23: 0 | L23: 0 | M23: 0 | N23: 0 | O23: 0 | P23: 0 | Q23: 0 | R23: 0 | S23: 0 | T23: 0 | U23: 0 | V23: 0 | W23: 0 | X23: 0 | Y23: 0 | Z23: 0 | AA23: 0 | AB23: 0 | AC23: 0 | AD23: 0 | AE23: 0 | AF23: 0 | AG23: 0 | AH23: 0 | AI23: 0 | AJ23: 0 | AK23: 0 | AL23: 0 | AM23: 104 | AN23: 71 | AO23: -109
A24: Net Income | B24: =B21-B22+B23 -> -109 | C24: =C21-C22+C23 -> 69 | D24: =D21-D22+D23 -> -406 | E24: =E21-E22+E23 -> -51 | F24: =F21-F22+F23 -> -33 | G24: =G21-G22+G23 -> -42 | H24: =H21-H22+H23 -> 61 | I24: =I21-I22+I23 -> -19 | ... AO24: =AO21-AO22+AO23 -> 1511
A25: Shares Outstanding (Basic) | B25: 793 | C25: 794 | D25: 815 | E25: 931 | F25: 939 | G25: 945 | H25: 957 | I25: 965 | J25: 968 | K25: 972 | L25: 987 | M25: 1002 | N25: 1044 | O25: 1084 | P25: 1097 | Q25: 1140 | R25: 1170 | S25: 1174 | T25: 1184 | U25: 1205 | V25: 1213 | W25: 1216 | X25: 1214 | Y25: 1208 | Z25: 1393 | AA25: 1618 | AB25: 1615 | AC25: 1613 | AD25: 1611 | AE25: 1612 | AF25: 1616 | AG25: 1616 | AH25: 1617 | AI25: 1618 | AJ25: 1620 | AK25: 1623 | AL25: 1620 | AM25: 1623 | AN25: 1626 | AO25: 1630
A26: Shares Outstanding (Diluted) | B26: 793 | C26: 821 | D26: 815 | E26: 931 | F26: 939 | G26: 945 | H26: 1042 | I26: 1037 | J26: 1039 | K26: 1147 | L26: 1076 | M26: 1079 | N26: 1094 | O26: 1109 | P26: 1117 | Q26: 1188 | R26: 1224 | S26: 1227 | T26: 1215 | U26: 1226 | V26: 1231 | W26: 1232 | X26: 1230 | Y26: 1222 | Z26: 1410 | AA26: 1632 | AB26: 1625 | AC26: 1618 | AD26: 1611 | AE26: 1627 | AF26: 1629 | AG26: 1628 | AH26: 1639 | AI26: 1637 | AJ26: 1636 | AK26: 1634 | AL26: 1626 | AM26: 1630 | AN26: 1641 | AO26: 1649
A27: EPS (Basic) | B27: =B$24/B25 -> -0.13745271 | C27: =C$24/C25 -> 0.086901763 | D27: =D$24/D25 -> -0.49815951 | E27: =E$24/E25 -> -0.054779807 | F27: =F$24/F25 -> -0.03514377 | G27: =G$24/G25 -> -0.044444444 | H27: =H$24/H25 -> 0.063740857 | I27: =I$24/I25 -> -0.019689119 | ... AO27: =AO$24/AO25 -> 0.92699387
A28: EPS (Diluted) | B28: =B$24/B26 -> -0.13745271 | C28: =C$24/C26 -> 0.084043849 | D28: =D$24/D26 -> -0.49815951 | E28: =E$24/E26 -> -0.054779807 | F28: =F$24/F26 -> -0.03514377 | G28: =G$24/G26 -> -0.044444444 | H28: =H$24/H26 -> 0.058541267 | I28: =I$24/I26 -> -0.018322083 | ... AO28: =AO$24/AO26 -> 0.91631292
A29: EBITDA | B29: =B31+B30 -> -45 | C29: =C31+C30 -> -8 | D29: =D31+D30 -> 56 | E29: =E31+E30 -> -340 | F29: =F31+F30 -> 18 | G29: =G31+G30 -> 9 | H29: =H31+H30 -> 155 | I29: =I31+I30 -> 37 | ... AO29: =AO31+AO30 -> 3060
A30: D&A For EBITDA | B30: =B84 -> 33 | C30: =C84 -> 33 | D30: =D84 -> 33 | E30: =E84 -> 34 | F30: =F84 -> 34 | G30: =G84 -> 35 | H30: =H84 -> 36 | I30: =I84 -> 39 | ... AO30: =AO84 -> 751
A31: EBIT | B31: =B11+B10+B9 -> -78 | C31: =C11+C10+C9 -> -41 | D31: =D11+D10+D9 -> 23 | E31: =E11+E10+E9 -> -374 | F31: =F11+F10+F9 -> -16 | G31: =G11+G10+G9 -> -26 | H31: =H11+H10+H9 -> 119 | I31: =I11+I10+I9 -> -2 | ... AO31: =AO11+AO10+AO9 -> 2309
A32: Normalized NI | B32: =B31+B12-B22 -> -119 | C32: =C31+C12-C22 -> -111 | D32: =D31+D12-D22 -> -22 | E32: =E31+E12-E22 -> -413 | F32: =F31+F12-F22 -> -53 | G32: =G31+G12-G22 -> -61 | H32: =H31+H12-H22 -> 66 | I32: =I31+I12-I22 -> -21 | ... AO32: =AO31+AO12-AO22 -> 1818
A33: Normalized EPS | B33: =B32/B26 -> -0.15006305 | C33: =C32/C26 -> -0.13520097 | D33: =D32/D26 -> -0.026993865 | E33: =E32/E26 -> -0.44360902 | F33: =F32/F26 -> -0.056443024 | G33: =G32/G26 -> -0.064550265 | H33: =H32/H26 -> 0.063339731 | I33: =I32/I26 -> -0.020250723 | ... AO33: =AO32/AO26 -> 1.1024864
A36: Balance Sheet ($mm)
A38: Line Item | B38: Q1 2016 | C38: Q2 2016 | D38: Q3 2016 | E38: Q4 2016 | F38: Q1 2017 | G38: Q2 2017 | H38: Q3 2017 | I38: Q4 2017 | J38: Q1 2018 | K38: Q2 2018 | L38: Q3 2018 | M38: Q4 2018 | N38: Q1 2019 | O38: Q2 2019 | P38: Q3 2019 | Q38: Q4 2019 | R38: Q1 2020 | S38: Q2 2020 | T38: Q3 2020 | U38: Q4 2020 | V38: Q1 2021 | W38: Q2 2021 | X38: Q3 2021 | Y38: Q4 2021 | Z38: Q1 2022 | AA38: Q2 2022 | AB38: Q3 2022 | AC38: Q4 2022 | AD38: Q1 2023 | AE38: Q2 2023 | AF38: Q3 2023 | AG38: Q4 2023 | AH38: Q1 2024 | AI38: Q2 2024 | AJ38: Q3 2024 | AK38: Q4 2024 | AL38: Q1 2025 | AM38: Q2 2025 | AN38: Q3 2025 | AO38: Q4 2025
A39: Cash & Equivalents | B39: 716 | C39: 957 | D39: 1258 | E39: 1264 | F39: 722 | G39: 760 | H39: 879 | I39: 1185 | J39: 1045 | K39: 948 | L39: 1046 | M39: 1078 | N39: 978 | O39: 963 | P39: 1156 | Q39: 1466 | R39: 1330 | S39: 1775 | T39: 1296 | U39: 1595 | V39: 1763 | W39: 2623 | X39: 2440 | Y39: 2535 | Z39: 4740 | AA39: 4964 | AB39: 3398 | AC39: 4835 | AD39: 3825 | AE39: 3841 | AF39: 3561 | AG39: 3933 | AH39: 4190 | AI39: 4113 | AJ39: 3897 | AK39: 3787 | AL39: 6049 | AM39: 4442 | AN39: 4808 | AO39: 5539
A40: Short-Term Investments | B40: 0 | C40: 0 | D40: 0 | E40: 0 | F40: 221 | G40: 84 | H40: 0 | I40: 0 | J40: 0 | K40: 35 | L40: 10 | M40: 78 | N40: 216 | O40: 165 | P40: 53 | Q40: 37 | R40: 55 | S40: 0 | T40: 475 | U40: 695 | V40: 1353 | W40: 1170 | X40: 1168 | Y40: 1073 | Z40: 1792 | AA40: 1028 | AB40: 2193 | AC40: 1020 | AD40: 2114 | AE40: 2444 | AF40: 2224 | AG40: 1840 | AH40: 1845 | AI40: 1227 | AJ40: 647 | AK40: 1345 | AL40: 1261 | AM40: 1425 | AN40: 2435 | AO40: 5013
A41: Cash & Short-Term Investments | B41: =SUM(B39:B40) -> 716 | C41: =SUM(C39:C40) -> 957 | D41: =SUM(D39:D40) -> 1258 | E41: =SUM(E39:E40) -> 1264 | F41: =SUM(F39:F40) -> 943 | G41: =SUM(G39:G40) -> 844 | H41: =SUM(H39:H40) -> 879 | I41: =SUM(I39:I40) -> 1185 | ... AO41: =SUM(AO39:AO40) -> 10552
A42: Receivables | B42: 508 | C42: 671 | D42: 640 | E42: 311 | F42: 514 | G42: 616 | H42: 776 | I42: 457 | J42: 745 | K42: 1118 | L42: 1245 | M42: 1251 | N42: 1279 | O42: 1363 | P42: 1410 | Q42: 1879 | R42: 1695 | S42: 1799 | T42: 2138 | U42: 2076 | V42: 2185 | W42: 2026 | X42: 2229 | Y42: 2708 | Z42: 3681 | AA42: 4053 | AB42: 4340 | AC42: 4128 | AD42: 4042 | AE42: 4314 | AF42: 5055 | AG42: 5385 | AH42: 5069 | AI42: 5773 | AJ42: 7270 | AK42: 6192 | AL42: 6286 | AM42: 5686 | AN42: 6513 | AO42: 6315
A43: Inventory | B43: 675 | C43: 743 | D43: 772 | E43: 751 | F43: 839 | G43: 833 | H43: 794 | I43: 694 | J43: 715 | K43: 750 | L43: 738 | M43: 845 | N43: 955 | O43: 1015 | P43: 1040 | Q43: 982 | R43: 1056 | S43: 1324 | T43: 1292 | U43: 1399 | V43: 1653 | W43: 1765 | X43: 1902 | Y43: 1955 | Z43: 2880 | AA43: 3048 | AB43: 4088 | AC43: 3771 | AD43: 5102 | AE43: 5409 | AF43: 5358 | AG43: 4351 | AH43: 4652 | AI43: 4991 | AJ43: 5374 | AK43: 5734 | AL43: 6416 | AM43: 6677 | AN43: 7313 | AO43: 7920
A44: Prepaid Expenses | B44: 75 | C44: 80 | D44: 76 | E44: 95 | F44: 84 | G44: 76 | H44: 93 | I44: 107 | J44: 78 | K44: 93 | L44: 75 | M44: 277 | N44: 77 | O44: 235 | P44: 242 | Q44: 225 | R44: 246 | S44: 207 | T44: 295 | U44: 378 | V44: 243 | W44: 234 | X44: 249 | Y44: 312 | Z44: 0 | AA44: 0 | AB44: 0 | AC44: 1265 | AD44: 0 | AE44: 0 | AF44: 0 | AG44: 0 | AH44: 1328 | AI44: 1361 | AJ44: 1547 | AK44: 1967 | AL44: 0 | AM44: 0 | AN44: 0 | AO44: 2143
A45: Restricted Cash | B45: 0 | C45: 0 | D45: 0 | E45: 0 | F45: 0 | G45: 0 | H45: 0 | I45: 3 | J45: 3 | K45: 5 | L45: 5 | M45: 5 | N45: 5 | O45: 5 | P45: 5 | Q45: 4 | R45: 4 | S45: 4 | T45: 4 | U45: 0 | V45: 0 | W45: 0 | X45: 0 | Y45: 0 | Z45: 0 | AA45: 0 | AB45: 0 | AC45: 0 | AD45: 0 | AE45: 0 | AF45: 0 | AG45: 0 | AH45: 0 | AI45: 0 | AJ45: 0 | AK45: 24 | AL45: 0 | AM45: 0 | AN45: 0 | AO45: 17
A46: Other Current Assets | B46: 252 | C46: 55 | D46: 78 | E46: 109 | F46: 118 | G46: 142 | H46: 157 | I46: 188 | J46: 165 | K46: 150 | L46: 195 | M46: 6 | N46: 167 | O46: 8 | P46: 6 | Q46: 4 | R46: 4 | S46: 0 | T46: 0 | U46: 0 | V46: 0 | W46: 0 | X46: 0 | Y46: 0 | Z46: 276 | AA46: 369 | AB46: 401 | AC46: 0 | AD46: 575 | AE46: 497 | AF46: 490 | AG46: 1259 | AH46: 0 | AI46: 0 | AJ46: 0 | AK46: 0 | AL46: 1583 | AM46: 6289 | AN46: 5931 | AO46: 0
A47: Total Current Assets | B47: =SUM(B41:B46) -> 2226 | C47: =SUM(C41:C46) -> 2506 | D47: =SUM(D41:D46) -> 2824 | E47: =SUM(E41:E46) -> 2530 | F47: =SUM(F41:F46) -> 2498 | G47: =SUM(G41:G46) -> 2511 | H47: =SUM(H41:H46) -> 2699 | I47: =SUM(I41:I46) -> 2634 | ... AO47: =SUM(AO41:AO46) -> 26947
A48: Property, Plant & Equipment | B48: 176 | C48: 169 | D48: 161 | E48: 164 | F48: 180 | G48: 200 | H48: 236 | I48: 261 | J48: 290 | K48: 295 | L48: 318 | M48: 348 | N48: 591 | O48: 670 | P48: 658 | Q48: 705 | R48: 761 | S48: 800 | T48: 810 | U48: 849 | V48: 922 | W48: 918 | X48: 1001 | Y48: 1069 | Z48: 1822 | AA48: 1923 | AB48: 1976 | AC48: 1973 | AD48: 1947 | AE48: 2002 | AF48: 2073 | AG48: 2222 | AH48: 2256 | AI48: 2301 | AJ48: 2316 | AK48: 1802 | AL48: 1921 | AM48: 2128 | AN48: 2205 | AO48: 2312
A49: Long-Term Investments | B49: 4 | C49: 72 | D49: 62 | E49: 59 | F49: 58 | G49: 58 | H49: 57 | I49: 58 | J49: 57 | K49: 57 | L49: 58 | M49: 58 | N49: 57 | O49: 58 | P49: 59 | Q49: 58 | R49: 58 | S49: 59 | T49: 60 | U49: 63 | V49: 65 | W49: 67 | X49: 69 | Y49: 69 | Z49: 72 | AA49: 76 | AB49: 80 | AC49: 100 | AD49: 237 | AE49: 236 | AF49: 244 | AG49: 100 | AH49: 262 | AI49: 358 | AJ49: 394 | AK49: 25 | AL49: 807 | AM49: 925 | AN49: 1072 | AO49: 400
A50: Goodwill | B50: 278 | C50: 289 | D50: 289 | E50: 289 | F50: 289 | G50: 289 | H50: 289 | I50: 289 | J50: 289 | K50: 289 | L50: 289 | M50: 289 | N50: 289 | O50: 289 | P50: 289 | Q50: 289 | R50: 289 | S50: 289 | T50: 289 | U50: 289 | V50: 289 | W50: 289 | X50: 289 | Y50: 289 | Z50: 23083 | AA50: 24193 | AB50: 24187 | AC50: 24177 | AD50: 24177 | AE50: 24177 | AF50: 24186 | AG50: 24262 | AH50: 24262 | AI50: 24262 | AJ50: 24839 | AK50: 24839 | AL50: 24839 | AM50: 25083 | AN50: 25083 | AO50: 25126
A51: Other Intangible Assets | B51: 245 | C51: 231 | D51: 235 | E51: 234 | F51: 222 | G51: 253 | H51: 248 | I51: 239 | J51: 308 | K51: 292 | L51: 274 | M51: 226 | N51: 222 | O51: 231 | P51: 220 | Q51: 210 | R51: 194 | S51: 174 | T51: 194 | U51: 229 | V51: 203 | W51: 204 | X51: 203 | Y51: 323 | Z51: 27348 | AA51: 26664 | AB51: 25714 | AC51: 24118 | AD51: 23291 | AE51: 22598 | AF51: 21950 | AG51: 21363 | AH51: 20741 | AI51: 20138 | AJ51: 19572 | AK51: 18930 | AL51: 18363 | AM51: 17812 | AN51: 17250 | AO51: 16705
A52: Long-Term Deferred Tax Assets | B52: 0 | C52: 0 | D52: 0 | E52: 11 | F52: 0 | G52: 0 | H52: 0 | I52: 11 | J52: 0 | K52: 0 | L52: 0 | M52: 15 | N52: 0 | O52: 0 | P52: 0 | Q52: 22 | R52: 0 | S52: 0 | T52: 0 | U52: 1245 | V52: 1162 | W52: 1090 | X52: 1036 | Y52: 931 | Z52: 32 | AA52: 32 | AB52: 32 | AC52: 58 | AD52: 67 | AE52: 68 | AF52: 76 | AG52: 366 | AH52: 433 | AI52: 617 | AJ52: 1183 | AK52: 688 | AL52: 845 | AM52: 860 | AN52: 633 | AO52: 384
A53: Other Long-Term Assets | B53: 52 | C53: 49 | D53: 45 | E53: 34 | F53: 52 | G53: 59 | H53: 57 | I53: 60 | J53: 68 | K53: 71 | L53: 94 | M53: 80 | N53: 95 | O53: 100 | P53: 115 | Q53: 147 | R53: 172 | S53: 152 | T53: 170 | U53: 144 | V53: 209 | W53: 305 | X53: 567 | Y53: 1155 | Z53: 1189 | AA53: 1152 | AB53: 1402 | AC53: 2135 | AD53: 2257 | AE53: 2381 | AF53: 2409 | AG53: 2804 | AH53: 2857 | AI53: 2745 | AJ53: 2597 | AK53: 3893 | AL53: 3180 | AM53: 3493 | AN53: 3648 | AO53: 5052
A54: Total Assets | B54: =SUM(B47:B53) -> 2981 | C54: =SUM(C47:C53) -> 3316 | D54: =SUM(D47:D53) -> 3616 | E54: =SUM(E47:E53) -> 3321 | F54: =SUM(F47:F53) -> 3299 | G54: =SUM(G47:G53) -> 3370 | H54: =SUM(H47:H53) -> 3586 | I54: =SUM(I47:I53) -> 3552 | ... AO54: =SUM(AO47:AO53) -> 76926
A55: Accounts Payable | B55: 557 | C55: 710 | D55: 866 | E55: 823 | F55: 858 | G55: 712 | H55: 916 | I55: 796 | J55: 830 | K55: 995 | L55: 1041 | M55: 1041 | N55: 930 | O55: 1029 | P55: 978 | Q55: 1201 | R55: 840 | S55: 994 | T55: 867 | U55: 546 | V55: 989 | W55: 872 | X55: 1084 | Y55: 1406 | Z55: 1681 | AA55: 1879 | AB55: 2734 | AC55: 2956 | AD55: 2871 | AE55: 3092 | AF55: 2570 | AG55: 2418 | AH55: 1856 | AI55: 2119 | AJ55: 2991 | AK55: 2466 | AL55: 2206 | AM55: 3080 | AN55: 3483 | AO55: 2929
A56: Accrued Expenses | B56: 325 | C56: 523 | D56: 341 | E56: 367 | F56: 340 | G56: 522 | H56: 406 | I56: 514 | J56: 431 | K56: 537 | L56: 643 | M56: 783 | N56: 663 | O56: 687 | P56: 794 | Q56: 1084 | R56: 1070 | S56: 1172 | T56: 1478 | U56: 1796 | V56: 1779 | W56: 1911 | X56: 2048 | Y56: 2424 | Z56: 3070 | AA56: 3074 | AB56: 3598 | AC56: 3077 | AD56: 3167 | AE56: 2971 | AF56: 3376 | AG56: 3082 | AH56: 3444 | AI56: 3629 | AJ56: 4120 | AK56: 4260 | AL56: 3876 | AM56: 4479 | AN56: 5112 | AO56: 5250
A57: Short-Term Debt | B57: 230 | C57: 226 | D57: 0 | E57: 0 | F57: 0 | G57: 42 | H57: 70 | I57: 0 | J57: 0 | K57: 0 | L57: 0 | M57: 0 | N57: 0 | O57: 0 | P57: 0 | Q57: 0 | R57: 0 | S57: 200 | T57: 0 | U57: 0 | V57: 0 | W57: 0 | X57: 0 | Y57: 0 | Z57: 0 | AA57: 0 | AB57: 0 | AC57: 0 | AD57: 0 | AE57: 0 | AF57: 0 | AG57: 0 | AH57: 0 | AI57: 0 | AJ57: 0 | AK57: 0 | AL57: 947 | AM57: 0 | AN57: 0 | AO57: 0
A58: Current Portion of Long-Term Debt | B58: 0 | C58: 0 | D58: 0 | E58: 0 | F58: 0 | G58: 0 | H58: 0 | I58: 70 | J58: 223 | K58: 223 | L58: 136 | M58: 136 | N58: 70 | O58: 0 | P58: 0 | Q58: 0 | R58: 0 | S58: 0 | T58: 0 | U58: 0 | V58: 0 | W58: 0 | X58: 312 | Y58: 312 | Z58: 312 | AA58: 312 | AB58: 0 | AC58: 0 | AD58: 0 | AE58: 753 | AF58: 752 | AG58: 751 | AH58: 750 | AI58: 0 | AJ58: 0 | AK58: 0 | AL58: 0 | AM58: 0 | AN58: 873 | AO58: 874
A59: Current Portion of Leases | B59: 0 | C59: 0 | D59: 0 | E59: 0 | F59: 0 | G59: 0 | H59: 0 | I59: 0 | J59: 0 | K59: 0 | L59: 0 | M59: 0 | N59: 38 | O59: 38 | P59: 38 | Q59: 0 | R59: 0 | S59: 0 | T59: 0 | U59: 0 | V59: 0 | W59: 104 | X59: 120 | Y59: 0 | Z59: 0 | AA59: 0 | AB59: 0 | AC59: 0 | AD59: 0 | AE59: 0 | AF59: 0 | AG59: 0 | AH59: 0 | AI59: 0 | AJ59: 0 | AK59: 0 | AL59: 0 | AM59: 0 | AN59: 0 | AO59: 159
A60: Current Income Taxes Payable | B60: 0 | C60: 0 | D60: 0 | E60: 0 | F60: 0 | G60: 0 | H60: 0 | I60: 0 | J60: 0 | K60: 0 | L60: 0 | M60: 0 | N60: 0 | O60: 0 | P60: 0 | Q60: 0 | R60: 0 | S60: 0 | T60: 0 | U60: 0 | V60: 0 | W60: 0 | X60: 0 | Y60: 0 | Z60: 0 | AA60: 0 | AB60: 0 | AC60: 0 | AD60: 0 | AE60: 635 | AF60: 769 | AG60: 0 | AH60: 0 | AI60: 0 | AJ60: 0 | AK60: 0 | AL60: 0 | AM60: 0 | AN60: 0 | AO60: 0
A61: Current Unearned Revenue | B61: 43 | C61: 42 | D61: 54 | E61: 63 | F61: 62 | G61: 72 | H61: 72 | I61: 85 | J61: 147 | K61: 67 | L61: 3 | M61: 11 | N61: 2 | O61: 1 | P61: 5 | Q61: 0 | R61: 0 | S61: 0 | T61: 0 | U61: 0 | V61: 0 | W61: 0 | X61: 0 | Y61: 0 | Z61: 0 | AA61: 0 | AB61: 0 | AC61: 0 | AD61: 0 | AE61: 0 | AF61: 0 | AG61: 0 | AH61: 0 | AI61: 0 | AJ61: 0 | AK61: 0 | AL61: 0 | AM61: 0 | AN61: 0 | AO61: 0
A62: Other Current Liabilities | B62: 173 | C62: 80 | D62: 212 | E62: 93 | F62: 112 | G62: 101 | H62: 127 | I62: 48 | J62: 66 | K62: 46 | L62: 55 | M62: 13 | N62: 61 | O62: 49 | P62: 49 | Q62: 74 | R62: 75 | S62: 68 | T62: 72 | U62: 75 | V62: 96 | W62: 5 | X62: 0 | Y62: 98 | Z62: 518 | AA62: 258 | AB62: 359 | AC62: 336 | AD62: 539 | AE62: 121 | AF62: 160 | AG62: 438 | AH62: 424 | AI62: 447 | AJ62: 389 | AK62: 555 | AL62: 674 | AM62: 2284 | AN62: 2232 | AO62: 243
A63: Total Current Liabilities | B63: =SUM(B55:B62) -> 1328 | C63: =SUM(C55:C62) -> 1581 | D63: =SUM(D55:D62) -> 1473 | E63: =SUM(E55:E62) -> 1346 | F63: =SUM(F55:F62) -> 1372 | G63: =SUM(G55:G62) -> 1449 | H63: =SUM(H55:H62) -> 1591 | I63: =SUM(I55:I62) -> 1513 | ... AO63: =SUM(AO55:AO62) -> 9455
A64: Long-Term Debt | B64: 2006 | C64: 2012 | D64: 1632 | E64: 1435 | F64: 1408 | G64: 1375 | H64: 1356 | I64: 1325 | J64: 1165 | K64: 1170 | L64: 1167 | M64: 1114 | N64: 1024 | O64: 1031 | P64: 872 | Q64: 486 | R64: 488 | S64: 490 | T64: 373 | U64: 330 | V64: 313 | W64: 313 | X64: 1 | Y64: 1 | Z64: 1475 | AA64: 2465 | AB64: 2466 | AC64: 2467 | AD64: 2467 | AE64: 1714 | AF64: 1715 | AG64: 1717 | AH64: 1718 | AI64: 1719 | AJ64: 1720 | AK64: 1721 | AL64: 3217 | AM64: 3218 | AN64: 2347 | AO64: 2348
A65: Long-Term Leases | B65: 0 | C65: 0 | D65: 0 | E65: 0 | F65: 0 | G65: 0 | H65: 0 | I65: 0 | J65: 0 | K65: 0 | L65: 0 | M65: 0 | N65: 213 | O65: 211 | P65: 201 | Q65: 199 | R65: 211 | S65: 204 | T65: 205 | U65: 201 | V65: 238 | W65: 240 | X65: 269 | Y65: 348 | Z65: 370 | AA65: 422 | AB65: 424 | AC65: 396 | AD65: 381 | AE65: 393 | AF65: 395 | AG65: 535 | AH65: 530 | AI65: 526 | AJ65: 518 | AK65: 491 | AL65: 567 | AM65: 668 | AN65: 650 | AO65: 625
A66: Long-Term Unearned Revenue | B66: 17 | C66: 16 | D66: 14 | E66: 0 | F66: 0 | G66: 0 | H66: 0 | I66: 0 | J66: 0 | K66: 0 | L66: 0 | M66: 0 | N66: 0 | O66: 0 | P66: 0 | Q66: 0 | R66: 0 | S66: 0 | T66: 0 | U66: 0 | V66: 0 | W66: 0 | X66: 0 | Y66: 0 | Z66: 0 | AA66: 0 | AB66: 0 | AC66: 0 | AD66: 0 | AE66: 0 | AF66: 0 | AG66: 0 | AH66: 0 | AI66: 0 | AJ66: 0 | AK66: 0 | AL66: 0 | AM66: 0 | AN66: 0 | AO66: 0
A67: Long-Term Deferred Tax Liabilities | B67: 0 | C67: 12 | D67: 11 | E67: 11 | F67: 0 | G67: 0 | H67: 0 | I67: 11 | J67: 0 | K67: 0 | L67: 0 | M67: 11 | N67: 0 | O67: 0 | P67: 0 | Q67: 11 | R67: 0 | S67: 0 | T67: 0 | U67: 11 | V67: 0 | W67: 0 | X67: 0 | Y67: 12 | Z67: 3109 | AA67: 2805 | AB67: 2078 | AC67: 1934 | AD67: 1641 | AE67: 1365 | AF67: 1152 | AG67: 1202 | AH67: 1199 | AI67: 1192 | AJ67: 1162 | AK67: 349 | AL67: 343 | AM67: 341 | AN67: 326 | AO67: 313
A68: Other Long-Term Liabilities | B68: 133 | C68: 108 | D68: 101 | E68: 113 | F68: 110 | G68: 129 | H68: 119 | I68: 107 | J68: 186 | K68: 186 | L68: 177 | M68: 181 | N68: 142 | O68: 155 | P68: 140 | Q68: 146 | R68: 143 | S68: 150 | T68: 161 | U68: 166 | V68: 155 | W68: 181 | X68: 183 | Y68: 321 | Z68: 1047 | AA68: 1118 | AB68: 1610 | AC68: 1664 | AD68: 1874 | AE68: 1787 | AF68: 1767 | AG68: 1850 | AH68: 1776 | AI68: 1716 | AJ68: 1751 | AK68: 1816 | AL68: 1839 | AM68: 1085 | AN68: 1078 | AO68: 1186
A69: Total Liabilities | B69: =SUM(B63:B68) -> 3484 | C69: =SUM(C63:C68) -> 3729 | D69: =SUM(D63:D68) -> 3231 | E69: =SUM(E63:E68) -> 2905 | F69: =SUM(F63:F68) -> 2890 | G69: =SUM(G63:G68) -> 2953 | H69: =SUM(H63:H68) -> 3066 | I69: =SUM(I63:I68) -> 2956 | ... AO69: =SUM(AO63:AO68) -> 13927
A70: Common Stock | B70: 8 | C70: 8 | D70: 9 | E70: 9 | F70: 9 | G70: 9 | H70: 10 | I70: 9 | J70: 10 | K70: 10 | L70: 10 | M70: 10 | N70: 11 | O70: 11 | P70: 11 | Q70: 12 | R70: 12 | S70: 12 | T70: 12 | U70: 12 | V70: 12 | W70: 12 | X70: 12 | Y70: 12 | Z70: 16 | AA70: 16 | AB70: 16 | AC70: 16 | AD70: 16 | AE70: 16 | AF70: 17 | AG70: 17 | AH70: 17 | AI70: 17 | AJ70: 17 | AK70: 17 | AL70: 17 | AM70: 17 | AN70: 17 | AO70: 17
A71: Additional Paid-In Capital | B71: 7033 | C71: 7053 | D71: 8258 | E71: 8334 | F71: 8379 | G71: 8405 | H71: 8437 | I71: 8464 | J71: 8502 | K71: 8564 | L71: 8666 | M71: 8750 | N71: 9246 | O71: 9325 | P71: 9490 | Q71: 9963 | R71: 10026 | S71: 10127 | T71: 10362 | U71: 10544 | V71: 10658 | W71: 10795 | X71: 10905 | Y71: 11069 | Z71: 56925 | AA71: 57297 | AB71: 57581 | AC71: 58005 | AD71: 58331 | AE71: 58825 | AF71: 59182 | AG71: 59676 | AH71: 60053 | AI71: 60542 | AJ71: 60896 | AK71: 61362 | AL71: 61730 | AM71: 62228 | AN71: 62657 | AO71: 63365
A72: Retained Earnings | B72: -7415 | C72: -7346 | D72: -7752 | E72: -7803 | F72: -7876 | G72: -7892 | H72: -7821 | I72: -7775 | J72: -7692 | K72: -7576 | L72: -7474 | M72: -7436 | N72: -7420 | O72: -7385 | P72: -7265 | Q72: -7095 | R72: -6933 | S72: -6776 | T72: -6386 | U72: -4605 | V72: -4058 | W72: -3348 | X72: -2425 | Y72: -1451 | Z72: -665 | AA72: -218 | AB72: -152 | AC72: -131 | AD72: -270 | AE72: -243 | AF72: 56 | AG72: 723 | AH72: 846 | AI72: 1111 | AJ72: 1882 | AK72: 2364 | AL72: 3073 | AM72: 3945 | AN72: 5188 | AO72: 6699
A73: Treasury Stock | B73: -123 | C73: -125 | D73: -127 | E73: -119 | F73: -99 | G73: -105 | H73: -108 | I73: -108 | J73: -108 | K73: -109 | L73: -67 | M73: -50 | N73: -48 | O73: -50 | P73: -53 | Q73: -53 | R73: -54 | S73: -54 | T73: -126 | U73: -131 | V73: -141 | W73: -401 | X73: -1356 | Y73: -2130 | Z73: -941 | AA73: -1893 | AB73: -2815 | AC73: -3099 | AD73: -3362 | AE73: -3430 | AF73: -4235 | AG73: -4514 | AH73: -4690 | AI73: -5103 | AJ73: -5812 | AK73: -6106 | AL73: -6899 | AM73: -6535 | AN73: -7059 | AO73: -7079
A74: Comprehensive Income & Other | B74: -6 | C74: -3 | D74: -3 | E74: -5 | F74: -4 | G74: 0 | H74: 2 | I74: 6 | J74: 3 | K74: -10 | L74: -10 | M74: -8 | N74: -1 | O74: 0 | P74: -7 | Q74: 0 | R74: -14 | S74: -4 | T74: 5 | U74: 17 | V74: 6 | W74: 7 | X74: 0 | Y74: -3 | Z74: -2 | AA74: -33 | AB74: -88 | AC74: -41 | AD74: -21 | AE74: -32 | AF74: -50 | AG74: -10 | AH74: -28 | AI74: -29 | AJ74: 2 | AK74: -69 | AL74: -40 | AM74: 10 | AN74: -13 | AO74: -3
A75: Shareholders' Equity | B75: =SUM(B70:B74) -> -503 | C75: =SUM(C70:C74) -> -413 | D75: =SUM(D70:D74) -> 385 | E75: =SUM(E70:E74) -> 416 | F75: =SUM(F70:F74) -> 409 | G75: =SUM(G70:G74) -> 417 | H75: =SUM(H70:H74) -> 520 | I75: =SUM(I70:I74) -> 596 | ... AO75: =SUM(AO70:AO74) -> 62999
A76: Total Liabilities & Equity | B76: =B75+B69 -> 2981 | C76: =C75+C69 -> 3316 | D76: =D75+D69 -> 3616 | E76: =E75+E69 -> 3321 | F76: =F75+F69 -> 3299 | G76: =G75+G69 -> 3370 | H76: =H75+H69 -> 3586 | I76: =I75+I69 -> 3552 | ... AO76: =AO75+AO69 -> 76926
A77: Balance | B77: =B76-B54 -> 0 | C77: =C76-C54 -> 0 | D77: =D76-D54 -> 0 | E77: =E76-E54 -> 0 | F77: =F76-F54 -> 0 | G77: =G76-G54 -> 0 | H77: =H76-H54 -> 0 | I77: =I76-I54 -> 0 | ... AO77: =AO76-AO54 -> 0
A80: Cash Flow Statement ($mm)
A82: Line Item | B82: Q1 2016 | C82: Q2 2016 | D82: Q3 2016 | E82: Q4 2016 | F82: Q1 2017 | G82: Q2 2017 | H82: Q3 2017 | I82: Q4 2017 | J82: Q1 2018 | K82: Q2 2018 | L82: Q3 2018 | M82: Q4 2018 | N82: Q1 2019 | O82: Q2 2019 | P82: Q3 2019 | Q82: Q4 2019 | R82: Q1 2020 | S82: Q2 2020 | T82: Q3 2020 | U82: Q4 2020 | V82: Q1 2021 | W82: Q2 2021 | X82: Q3 2021 | Y82: Q4 2021 | Z82: Q1 2022 | AA82: Q2 2022 | AB82: Q3 2022 | AC82: Q4 2022 | AD82: Q1 2023 | AE82: Q2 2023 | AF82: Q3 2023 | AG82: Q4 2023 | AH82: Q1 2024 | AI82: Q2 2024 | AJ82: Q3 2024 | AK82: Q4 2024 | AL82: Q1 2025 | AM82: Q2 2025 | AN82: Q3 2025 | AO82: Q4 2025
A83: Net Income | B83: -109 | C83: 69 | D83: -406 | E83: -51 | F83: -33 | G83: -42 | H83: 61 | I83: -19 | J83: 81 | K83: 116 | L83: 102 | M83: 38 | N83: 16 | O83: 35 | P83: 120 | Q83: 170 | R83: 162 | S83: 157 | T83: 390 | U83: 1781 | V83: 555 | W83: 710 | X83: 923 | Y83: 974 | Z83: 786 | AA83: 447 | AB83: 66 | AC83: 21 | AD83: -139 | AE83: 27 | AF83: 299 | AG83: 667 | AH83: 123 | AI83: 265 | AJ83: 771 | AK83: 482 | AL83: 709 | AM83: 872 | AN83: 1243 | AO83: 1511
A84: Depreciation & Amortization | B84: 33 | C84: 33 | D84: 33 | E84: 34 | F84: 34 | G84: 35 | H84: 36 | I84: 39 | J84: 44 | K84: 42 | L84: 41 | M84: 43 | N84: 55 | O84: 61 | P84: 69 | Q84: 73 | R84: 78 | S84: 82 | T84: 93 | U84: 101 | V84: 107 | W84: 110 | X84: 112 | Y84: 134 | Z84: 628 | AA84: 1201 | AB84: 1188 | AC84: 507 | AD84: 1006 | AE84: 873 | AF84: 848 | AG84: 824 | AH84: 784 | AI84: 769 | AJ84: 756 | AK84: 755 | AL84: 742 | AM84: 757 | AN84: 754 | AO84: 751
A85: Other Amortization | B85: 0 | C85: 0 | D85: 0 | E85: 21 | F85: 9 | G85: 9 | H85: 9 | I85: 9 | J85: 10 | K85: 10 | L85: 9 | M85: 9 | N85: 9 | O85: 9 | P85: 7 | Q85: 5 | R85: 4 | S85: 4 | T85: 4 | U85: 2 | V85: 0 | W85: 0 | X85: 0 | Y85: 5 | Z85: 0 | AA85: 0 | AB85: 0 | AC85: 738 | AD85: 0 | AE85: 0 | AF85: 0 | AG85: 0 | AH85: 0 | AI85: 0 | AJ85: 0 | AK85: 0 | AL85: 0 | AM85: 0 | AN85: 0 | AO85: 0
A86: Loss (Gain) From Sale of Assets | B86: 0 | C86: 0 | D86: 0 | E86: 0 | F86: 0 | G86: 0 | H86: 0 | I86: 0 | J86: 0 | K86: 0 | L86: 0 | M86: 27 | N86: 6 | O86: 2 | P86: 26 | Q86: 8 | R86: 18 | S86: 8 | T86: 2 | U86: 5 | V86: 8 | W86: 11 | X86: 0 | Y86: 15 | Z86: 15 | AA86: 0 | AB86: 0 | AC86: 1 | AD86: 0 | AE86: 0 | AF86: 0 | AG86: 0 | AH86: 0 | AI86: 0 | AJ86: 0 | AK86: 0 | AL86: 0 | AM86: 0 | AN86: 0 | AO86: 0
A87: Asset Writedown & Restructuring Costs | B87: 0 | C87: 0 | D87: 0 | E87: 0 | F87: 0 | G87: 0 | H87: 0 | I87: 0 | J87: 0 | K87: 0 | L87: 0 | M87: 45 | N87: 0 | O87: 0 | P87: 0 | Q87: 0 | R87: 0 | S87: 0 | T87: 0 | U87: 0 | V87: 0 | W87: 0 | X87: 0 | Y87: 0 | Z87: 0 | AA87: 0 | AB87: 0 | AC87: 0 | AD87: 0 | AE87: 0 | AF87: 0 | AG87: 0 | AH87: 0 | AI87: 0 | AJ87: 0 | AK87: 0 | AL87: 0 | AM87: 0 | AN87: 0 | AO87: 0
A88: Loss (Gain) From Sale of Investments | B88: 0 | C88: -150 | D88: 4 | E88: 0 | F88: 0 | G88: 0 | H88: 0 | I88: -3 | J88: 0 | K88: 0 | L88: 0 | M88: 0 | N88: 0 | O88: 0 | P88: 0 | Q88: 0 | R88: 0 | S88: 0 | T88: 0 | U88: -2 | V88: 0 | W88: 0 | X88: 0 | Y88: 0 | Z88: 0 | AA88: 0 | AB88: 0 | AC88: 0 | AD88: 0 | AE88: 0 | AF88: 0 | AG88: 0 | AH88: 0 | AI88: 0 | AJ88: 0 | AK88: 0 | AL88: 0 | AM88: 0 | AN88: 0 | AO88: -341
A89: Loss (Gain) on Equity Investments | B89: 0 | C89: 0 | D89: 0 | E89: 0 | F89: 0 | G89: 0 | H89: 0 | I89: 0 | J89: 0 | K89: 0 | L89: 0 | M89: 0 | N89: 0 | O89: 0 | P89: 0 | Q89: 0 | R89: 0 | S89: 0 | T89: -1 | U89: 1 | V89: 8 | W89: 0 | X89: -60 | Y89: -4 | Z89: 44 | AA89: 10 | AB89: 3 | AC89: 5 | AD89: 0 | AE89: 0 | AF89: 0 | AG89: 0 | AH89: 0 | AI89: 0 | AJ89: 0 | AK89: 0 | AL89: 0 | AM89: 0 | AN89: 0 | AO89: 0
A90: Stock-Based Compensation | B90: 16 | C90: 18 | D90: 23 | E90: 29 | F90: 23 | G90: 24 | H90: 29 | I90: 21 | J90: 32 | K90: 33 | L90: 36 | M90: 36 | N90: 41 | O90: 45 | P90: 54 | Q90: 57 | R90: 59 | S90: 60 | T90: 76 | U90: 79 | V90: 85 | W90: 83 | X90: 99 | Y90: 112 | Z90: 199 | AA90: 292 | AB90: 275 | AC90: 315 | AD90: 309 | AE90: 348 | AF90: 353 | AG90: 374 | AH90: 371 | AI90: 346 | AJ90: 351 | AK90: 339 | AL90: 364 | AM90: 369 | AN90: 419 | AO90: 486
A91: Other Operating Activities | B91: -1 | C91: 12 | D91: 308 | E91: -6 | F91: 9 | G91: -1 | H91: 8 | I91: -1 | J91: 2 | K91: -2 | L91: 9 | M91: -2 | N91: 7 | O91: -3 | P91: 31 | Q91: 132 | R91: 3 | S91: 5 | T91: 43 | U91: -1212 | V91: 78 | W91: 72 | X91: 56 | Y91: 102 | Z91: -255 | AA91: -182 | AB91: -713 | AC91: -180 | AD91: -303 | AE91: -287 | AF91: -241 | AG91: -242 | AH91: 3 | AI91: -179 | AJ91: -590 | AK91: -207 | AL91: -128 | AM91: -1000 | AN91: 80 | AO91: 1283
A92: Change in Accounts Receivable | B92: 26 | C92: -164 | D92: 31 | E92: 329 | F92: -395 | G92: -43 | H92: -89 | I92: 424 | J92: -295 | K92: -398 | L92: -110 | M92: -3 | N92: -5 | O92: -93 | P92: -60 | Q92: -465 | R92: 168 | S92: -104 | T92: -351 | U92: 68 | V92: -112 | W92: 158 | X92: -204 | Y92: -482 | Z92: -672 | AA92: -344 | AB92: -285 | AC92: 210 | AD92: 86 | AE92: -272 | AF92: -743 | AG92: -410 | AH92: 913 | AI92: -661 | AJ92: -2213 | AK92: 96 | AL92: 748 | AM92: 330 | AN92: -1085 | AO92: -114
A93: Change in Inventory | B93: 3 | C93: -69 | D93: -28 | E93: 21 | F93: 76 | G93: -43 | H93: -28 | I93: -8 | J93: -21 | K93: -35 | L93: 12 | M93: -107 | N93: -110 | O93: -60 | P93: -25 | Q93: 58 | R93: -74 | S93: -268 | T93: 32 | U93: -107 | V93: -254 | W93: -112 | X93: -138 | Y93: -52 | Z93: -26 | AA93: -248 | AB93: -723 | AC93: -404 | AD93: -464 | AE93: -332 | AF93: 122 | AG93: 94 | AH93: -368 | AI93: -342 | AJ93: -386 | AK93: -362 | AL93: -682 | AM93: -261 | AN93: -636 | AO93: -610
A94: Change in Accounts Payable | B94: -27 | C94: 280 | D94: -102 | E94: -93 | F94: 60 | G94: -62 | H94: 13 | I94: -5 | J94: 39 | K94: 98 | L94: 65 | M94: 91 | N94: -208 | O94: 21 | P94: 8 | Q94: 332 | R94: -369 | S94: 168 | T94: -31 | U94: -281 | V94: 466 | W94: -120 | X94: 180 | Y94: 275 | Z94: 4 | AA94: 24 | AB94: 783 | AC94: 120 | AD94: 73 | AE94: 236 | AF94: -547 | AG94: -181 | AH94: -561 | AI94: 262 | AJ94: 873 | AK94: -571 | AL94: -289 | AM94: 836 | AN94: 451 | AO94: -588
A95: Change in Other Net Operating Assets | B95: 17 | C95: -114 | D95: 166 | E95: -96 | F95: -82 | G95: 41 | H95: 30 | I95: -133 | J95: 1 | K95: 81 | L95: -88 | M95: -57 | N95: -24 | O95: 13 | P95: 4 | Q95: 72 | R95: -114 | S95: 131 | T95: 82 | U95: 119 | V95: -43 | W95: 40 | X95: -119 | Y95: -257 | Z95: 272 | AA95: -162 | AB95: 371 | AC95: -766 | AD95: -82 | AE95: -214 | AF95: 330 | AG95: -745 | AH95: -744 | AI95: 133 | AJ95: 1066 | AK95: 767 | AL95: -525 | AM95: -441 | AN95: 562 | AO95: -74
A96: Operating Cash Flow | B96: =SUM(B83:B95) -> -42 | C96: =SUM(C83:C95) -> -85 | D96: =SUM(D83:D95) -> 29 | E96: =SUM(E83:E95) -> 188 | F96: =SUM(F83:F95) -> -299 | G96: =SUM(G83:G95) -> -82 | H96: =SUM(H83:H95) -> 69 | I96: =SUM(I83:I95) -> 324 | ... AO96: =SUM(AO83:AO95) -> 2304
A97: Capital Expenditures | B97: -26 | C97: -21 | D97: -9 | E97: -21 | F97: -23 | G97: -12 | H97: -34 | I97: -44 | J97: -46 | K97: -43 | L97: -33 | M97: -41 | N97: -62 | O97: -58 | P97: -55 | Q97: -42 | R97: -55 | S97: -91 | T97: -74 | U97: -74 | V97: -66 | W97: -64 | X97: -85 | Y97: -86 | Z97: -71 | AA97: -132 | AB97: -123 | AC97: -124 | AD97: -158 | AE97: -125 | AF97: -124 | AG97: -139 | AH97: -142 | AI97: -154 | AJ97: -132 | AK97: -208 | AL97: -212 | AM97: -282 | AN97: -258 | AO97: -222
A98: Cash Acquisitions | B98: 0 | C98: 0 | D98: 0 | E98: 0 | F98: 0 | G98: 0 | H98: 0 | I98: 0 | J98: 0 | K98: 0 | L98: 0 | M98: 0 | N98: 0 | O98: 0 | P98: 0 | Q98: 0 | R98: 0 | S98: 0 | T98: 0 | U98: 0 | V98: 0 | W98: 0 | X98: 0 | Y98: 0 | Z98: 2366 | AA98: -1558 | AB98: 0 | AC98: 14 | AD98: 0 | AE98: 0 | AF98: -14 | AG98: -117 | AH98: 0 | AI98: 0 | AJ98: -548 | AK98: 0 | AL98: 0 | AM98: -1716 | AN98: 0 | AO98: -44
A99: Investment in Securities | B99: 0 | C99: 351 | D99: -5 | E99: -4 | F99: -221 | G99: 137 | H99: 84 | I99: 1 | J99: 0 | K99: -35 | L99: 25 | M99: -68 | N99: -138 | O99: 51 | P99: 112 | Q99: 16 | R99: -18 | S99: 55 | T99: -475 | U99: -220 | V99: -658 | W99: 183 | X99: 2 | Y99: 95 | Z99: 864 | AA99: 765 | AB99: -1164 | AC99: 1178 | AD99: -1085 | AE99: -312 | AF99: 250 | AG99: 401 | AH99: 6 | AI99: 539 | AJ99: 559 | AK99: -906 | AL99: -145 | AM99: -278 | AN99: -1071 | AO99: -2633
A100: Other Investing Activities | B100: 0 | C100: -1 | D100: 4 | E100: -1 | F100: -2 | G100: -1 | H100: 1 | I100: 60 | J100: 21 | K100: 10 | L100: 19 | M100: 21 | N100: 27 | O100: 0 | P100: 0 | Q100: 0 | R100: 0 | S100: 0 | T100: 0 | U100: 0 | V100: 2 | W100: 0 | X100: 0 | Y100: -9 | Z100: -1 | AA100: -3 | AB100: -11 | AC100: -1 | AD100: 6 | AE100: -1 | AF100: -10 | AG100: 5 | AH100: 1 | AI100: 1 | AJ100: -17 | AK100: -100 | AL100: 0 | AM100: -22 | AN100: -8 | AO100: 1358
A101: Investing Cash Flow | B101: =SUM(B97:B100) -> -26 | C101: =SUM(C97:C100) -> 329 | D101: =SUM(D97:D100) -> -10 | E101: =SUM(E97:E100) -> -26 | F101: =SUM(F97:F100) -> -246 | G101: =SUM(G97:G100) -> 124 | H101: =SUM(H97:H100) -> 51 | I101: =SUM(I97:I100) -> 17 | ... AO101: =SUM(AO97:AO100) -> -1541
A102: Short-Term Debt Issued | B102: 0 | C102: 0 | D102: 0 | E102: 0 | F102: 0 | G102: 0 | H102: 0 | I102: 0 | J102: 0 | K102: 0 | L102: 0 | M102: 0 | N102: 0 | O102: 0 | P102: 0 | Q102: 0 | R102: 0 | S102: 0 | T102: 0 | U102: 0 | V102: 0 | W102: 0 | X102: 0 | Y102: 0 | Z102: 0 | AA102: 0 | AB102: 0 | AC102: 0 | AD102: 0 | AE102: 0 | AF102: 0 | AG102: 0 | AH102: 0 | AI102: 0 | AJ102: 0 | AK102: 0 | AL102: 947 | AM102: 0 | AN102: 0 | AO102: 0
A103: Long-Term Debt Issued | B103: 0 | C103: 0 | D103: 0 | E103: 0 | F103: 0 | G103: 0 | H103: 0 | I103: 0 | J103: 0 | K103: 0 | L103: 0 | M103: 0 | N103: 0 | O103: 0 | P103: 0 | Q103: 0 | R103: 0 | S103: 0 | T103: 0 | U103: 0 | V103: 0 | W103: 0 | X103: 0 | Y103: 0 | Z103: 0 | AA103: 0 | AB103: 0 | AC103: 0 | AD103: 0 | AE103: 0 | AF103: 0 | AG103: 0 | AH103: 0 | AI103: 0 | AJ103: 0 | AK103: 0 | AL103: 1494 | AM103: 0 | AN103: 0 | AO103: 0
A104: Total Debt Issued | B104: 0 | C104: 0 | D104: 681 | E104: 101 | F104: 0 | G104: 42 | H104: 28 | I104: 0 | J104: 0 | K104: 0 | L104: 0 | M104: 0 | N104: 0 | O104: 0 | P104: 0 | Q104: 0 | R104: 0 | S104: 200 | T104: 0 | U104: 0 | V104: 0 | W104: 0 | X104: 0 | Y104: 0 | Z104: 0 | AA104: 991 | AB104: 0 | AC104: 0 | AD104: 0 | AE104: 0 | AF104: 0 | AG104: 0 | AH104: 0 | AI104: 0 | AJ104: 0 | AK104: 0 | AL104: 2441 | AM104: 0 | AN104: 0 | AO104: 0
A105: Long-Term Debt Repaid | B105: 0 | C105: 0 | D105: 0 | E105: 0 | F105: 0 | G105: 0 | H105: 0 | I105: 0 | J105: -14 | K105: 0 | L105: 0 | M105: 0 | N105: -164 | O105: 0 | P105: 0 | Q105: 0 | R105: 0 | S105: 0 | T105: 0 | U105: 0 | V105: 0 | W105: 0 | X105: 0 | Y105: 0 | Z105: 0 | AA105: 0 | AB105: 0 | AC105: 0 | AD105: 0 | AE105: 0 | AF105: 0 | AG105: 0 | AH105: 0 | AI105: 0 | AJ105: 0 | AK105: 0 | AL105: 0 | AM105: -950 | AN105: 0 | AO105: 0
A106: Total Debt Repaid | B106: 0 | C106: -4 | D106: -1074 | E106: -265 | F106: 0 | G106: -42 | H106: -28 | I106: -40 | J106: -14 | K106: -1 | L106: 0 | M106: -26 | N106: -164 | O106: -70 | P106: -97 | Q106: -142 | R106: 0 | S106: 0 | T106: -200 | U106: 0 | V106: 0 | W106: 0 | X106: 0 | Y106: 0 | Z106: 0 | AA106: 0 | AB106: -312 | AC106: 0 | AD106: 0 | AE106: 0 | AF106: 0 | AG106: 0 | AH106: 0 | AI106: -750 | AJ106: 0 | AK106: 0 | AL106: 0 | AM106: -950 | AN106: 0 | AO106: 0
A107: Net Debt Issued (Repaid) | B107: =SUM(B102:B106) -> 0 | C107: =SUM(C102:C106) -> -4 | D107: =SUM(D102:D106) -> -393 | E107: =SUM(E102:E106) -> -164 | F107: =SUM(F102:F106) -> 0 | G107: =SUM(G102:G106) -> 0 | H107: =SUM(H102:H106) -> 0 | I107: =SUM(I102:I106) -> -40 | ... AO107: =SUM(AO102:AO106) -> 0
...

Sheet Key Metrics
B2: AMD | C2: 215
B3: Shares | C3: ='AMD Financials'!AO26 -> 1649
B4: MC | C4: =C3*C2 -> 354535
B5: Cash | C5: ='AMD Financials'!AO41 -> 10552
B6: Debt | C6: =SUM('AMD Financials'!AO57,'AMD Financials'!AO58,'AMD Financials'!AO59,'AMD Financials'!AO64,'AMD Financials'!AO65) -> 4006
B7: EV | C7: =C4-C5+C6 -> 347989
B8: EPS Yield | C8: =SUM('AMD Financials'!AL33:AO33)/'Key Metrics'!C2 -> 0.016912746
B9: EBIT Yield | C9: =SUM('AMD Financials'!AL31:AO31)/'Key Metrics'!C7 -> 0.017195946
B10: EBITDA Yield | C10: =SUM('AMD Financials'!AL29:AO29)/'Key Metrics'!C7 -> 0.025828403
B11: FCF Yield | C11: =SUM('AMD Financials'!AL114:AO114)/'Key Metrics'!C2 -> 0.011003157
