Workbook

Sheet IS - Quarterly
A1: AeroVironment, Inc. - Income Statement
A2: USD mm, except per share data
B3: Actual | AU3: Forecast
A4: Fiscal quarter end | B4: 1/31/15 | C4: 4/30/15 | D4: 8/1/15 | E4: 10/31/15 | F4: 1/30/16 | G4: 4/30/16 | H4: 7/30/16 | I4: 10/29/16 | J4: 1/28/17 | K4: 4/30/17 | L4: 7/29/17 | M4: 10/28/17 | N4: 1/27/18 | O4: 4/30/18 | P4: 7/28/18 | Q4: 10/27/18 | R4: 1/26/19 | S4: 4/30/19 | T4: 7/27/19 | U4: 10/26/19 | V4: 1/25/20 | W4: 4/30/20 | X4: 8/1/20 | Y4: 10/31/20 | Z4: 1/30/21 | AA4: 4/30/21 | AB4: 7/31/21 | AC4: 10/30/21 | AD4: 1/29/22 | AE4: 4/30/22 | AF4: 7/30/22 | AG4: 10/29/22 | AH4: 1/28/23 | AI4: 4/30/23 | AJ4: 7/29/23 | AK4: 10/28/23 | AL4: 1/27/24 | AM4: 4/30/24 | AN4: 7/27/24 | AO4: 10/26/24 | AP4: 1/25/25 | AQ4: 4/30/25 | AR4: 8/2/25 | AS4: 11/1/25 | AT4: 1/31/26 | AU4: 4/30/26 | AV4: 8/1/26 | AW4: 10/31/26 | AX4: 1/30/27 | AY4: 4/30/27 | AZ4: 7/31/27 | BA4: 10/30/27 | BB4: 1/29/28
A5: Revenue
A6: Product sales | B6: 56.308 | C6: 63.034 | D6: 26.639 | E6: 49.492 | F6: 53.305 | G6: 60.04 | H6: 15.737 | I6: 29.35 | J6: 36.746 | K6: 111.505 | L6: 18.78 | M6: 48.42 | N6: 39.447 | O6: 85.065 | P6: 55.313 | Q6: 47.056 | R6: 50.024 | S6: 59.696 | T6: 65.839 | U6: 57.386 | V6: 36.432 | W6: 97.101 | X6: 58.357 | Y6: 65.528 | Z6: 58.348 | AA6: 96.655 | AB6: 53.116 | AC6: 70.998 | AD6: 42.599 | AE6: 73.97 | AF6: 57.974 | AG6: 62.343 | AH6: 91.216 | AI6: 141.529 | AJ6: 119.471 | AK6: 145.779 | AL6: 155.923 | AM6: 164.598 | AN6: 159.504 | AO6: 151.231 | AP6: 139.753 | AQ6: 242.234 | AR6: 313.533 | AS6: 325.037 | AT6: 277.814 | AU6: ='KPI Rev by Type'!AA6 -> 395.32932 | AV6: ='KPI Rev by Type'!AB6 -> 376.2396 | AW6: ='KPI Rev by Type'!AC6 -> 390.0444 | AX6: ='KPI Rev by Type'!AD6 -> 333.3768 | AY6: ='KPI Rev by Type'!AE6 -> 474.39519 | AZ6: ='KPI Rev by Type'!AF6 -> 425.15075 | BA6: ='KPI Rev by Type'!AG6 -> 440.75017 | BB6: ='KPI Rev by Type'!AH6 -> 376.71578
A7: Contract services | B7: 12.089 | C7: 23.437 | D7: 20.411 | E7: 15.239 | F7: 14.255 | G7: 24.717 | H7: 20.481 | I7: 20.766 | J7: 16.417 | K7: 13.871 | L7: 15.581 | M7: 17.381 | N7: 15.186 | O7: 28.564 | P7: 22.73 | Q7: 25.923 | R7: 25.298 | S7: 28.234 | T7: 21.072 | U7: 25.885 | V7: 25.459 | W7: 38.122 | X7: 29.093 | Y7: 27.137 | Z7: 20.434 | AA7: 39.36 | AB7: 47.893 | AC7: 51.01 | AD7: 47.494 | AE7: 58.652 | AF7: 50.542 | AG7: 49.241 | AH7: 43.179 | AI7: 44.512 | AJ7: 32.876 | AK7: 35.037 | AL7: 30.655 | AM7: 32.381 | AN7: 29.979 | AO7: 37.227 | AP7: 27.883 | AQ7: 32.816 | AR7: 141.143 | AS7: 147.471 | AT7: 130.231 | AU7: ='KPI Rev by Type'!AA7 -> 169.43053 | AV7: ='KPI Rev by Type'!AB7 -> 151.02301 | AW7: ='KPI Rev by Type'!AC7 -> 157.79397 | AX7: ='KPI Rev by Type'!AD7 -> 139.34717 | AY7: ='KPI Rev by Type'!AE7 -> 181.29067 | AZ7: ='KPI Rev by Type'!AF7 -> 160.08439 | BA7: ='KPI Rev by Type'!AG7 -> 167.26161 | BB7: ='KPI Rev by Type'!AH7 -> 147.708
A8: Total revenue | B8: =SUM(B6,B7) -> 68.397 | C8: =SUM(C6,C7) -> 86.471 | D8: =SUM(D6,D7) -> 47.05 | E8: =SUM(E6,E7) -> 64.731 | F8: =SUM(F6,F7) -> 67.56 | G8: =SUM(G6,G7) -> 84.757 | H8: =SUM(H6,H7) -> 36.218 | I8: =SUM(I6,I7) -> 50.116 | ... AT8: =SUM(AT6,AT7) -> 408.045 | AU8: =SUM(AU6:AU7) -> 564.75985 | AV8: =SUM(AV6:AV7) -> 527.26261 | AW8: =SUM(AW6:AW7) -> 547.83837 | AX8: =SUM(AX6:AX7) -> 472.72397 | AY8: =SUM(AY6:AY7) -> 655.68585 | AZ8: =SUM(AZ6:AZ7) -> 585.23514 | BA8: =SUM(BA6:BA7) -> 608.01178 | BB8: =SUM(BB6:BB7) -> 524.42378
A9: Cost of Sales
A10: Product sales | B10: 32.901 | C10: 27.357 | D10: 16.765 | E10: 24.802 | F10: 31.91 | G10: 32.51 | H10: 15.222 | I10: 19.197 | J10: 23.641 | K10: 57.453 | L10: 15.972 | M10: 25.196 | N10: 24.87 | O10: 43.355 | P10: 29.811 | Q10: 26.567 | R10: 26.78 | S10: 30.331 | T10: 30.408 | U10: 30.802 | V10: 21.034 | W10: 56.887 | X10: 32.084 | Y10: 34.209 | Z10: 35.746 | AA10: 47.675 | AB10: 32.59 | AC10: 38.937 | AD10: 29.294 | AE10: 39.775 | AF10: 32.899 | AG10: 39.445 | AH10: 54.866 | AI10: 76.209 | AJ10: 61.608 | AK10: 79.032 | AL10: 99.486 | AM10: 100.048 | AN10: 85.519 | AO10: 87.052 | AP10: 81.001 | AQ10: 150.775 | AR10: 230.687 | AS10: 241.397 | AT10: 199.973 | AU10: =AU6*(1-Assumptions!$D$43) -> 276.73053 | AV10: =AV6*(1-Assumptions!$E$43) -> 259.60532 | AW10: =AW6*(1-Assumptions!$F$43) -> 269.13064 | AX10: =AX6*(1-Assumptions!$G$43) -> 230.02999 | AY10: =AY6*(1-Assumptions!$H$43) -> 327.33268 | AZ10: =AZ6*(1-Assumptions!$I$43) -> 286.97675 | BA10: =BA6*(1-Assumptions!$J$43) -> 297.50637 | BB10: =BB6*(1-Assumptions!$K$43) -> 254.28315
A11: Contract services | B11: 8.503 | C11: 13.764 | D11: 14.262 | E11: 8.396 | F11: 9.025 | G11: 14.325 | H11: 14.313 | I11: 13.502 | J11: 10.171 | K11: 9.207 | L11: 9.691 | M11: 10.462 | N11: 11.513 | O11: 19.68 | P11: 15.643 | Q11: 18.013 | R11: 18.15 | S11: 20.576 | T11: 15.231 | U11: 17.303 | V11: 17.361 | W11: 25.168 | X11: 19.955 | Y11: 17.605 | Z11: 14.395 | AA11: 28.685 | AB11: 39.696 | AC11: 40.616 | AD11: 39.363 | AE11: 44.225 | AF11: 41.903 | AG11: 46.249 | AH11: 34.019 | AI11: 41.432 | AJ11: 25.079 | AK11: 26.434 | AL11: 19.805 | AM11: 21.297 | AN11: 22.497 | AO11: 27.768 | AP11: 23.436 | AQ11: 23.943 | AR11: 128.871 | AS11: 127.006 | AT11: 109.278 | AU11: =AU7*(1-Assumptions!$D$44) -> 141.47449 | AV11: =AV7*(1-Assumptions!$E$44) -> 124.59398 | AW11: =AW7*(1-Assumptions!$F$44) -> 130.18003 | AX11: =AX7*(1-Assumptions!$G$44) -> 114.96142 | AY11: =AY7*(1-Assumptions!$H$44) -> 149.5648 | AZ11: =AZ7*(1-Assumptions!$I$44) -> 130.46878 | BA11: =BA7*(1-Assumptions!$J$44) -> 136.31821 | BB11: =BB7*(1-Assumptions!$K$44) -> 120.38202
A12: Total cost of sales | B12: =SUM(B10,B11) -> 41.404 | C12: =SUM(C10,C11) -> 41.121 | D12: =SUM(D10,D11) -> 31.027 | E12: =SUM(E10,E11) -> 33.198 | F12: =SUM(F10,F11) -> 40.935 | G12: =SUM(G10,G11) -> 46.835 | H12: =SUM(H10,H11) -> 29.535 | I12: =SUM(I10,I11) -> 32.699 | ... BB12: =SUM(BB10,BB11) -> 374.66517
A13: Gross Profit
A14: Product sales gross profit | B14: =B6-B10 -> 23.407 | C14: =C6-C10 -> 35.677 | D14: =D6-D10 -> 9.874 | E14: =E6-E10 -> 24.69 | F14: =F6-F10 -> 21.395 | G14: =G6-G10 -> 27.53 | H14: =H6-H10 -> 0.515 | I14: =I6-I10 -> 10.153 | ... BB14: =BB6-BB10 -> 122.43263
A15: Contract services gross profit | B15: =B7-B11 -> 3.586 | C15: =C7-C11 -> 9.673 | D15: =D7-D11 -> 6.149 | E15: =E7-E11 -> 6.843 | F15: =F7-F11 -> 5.23 | G15: =G7-G11 -> 10.392 | H15: =H7-H11 -> 6.168 | I15: =I7-I11 -> 7.264 | ... BB15: =BB7-BB11 -> 27.32598
A16: Gross profit | B16: =B8-B12 -> 26.993 | C16: =C8-C12 -> 45.35 | D16: =D8-D12 -> 16.023 | E16: =E8-E12 -> 31.533 | F16: =F8-F12 -> 26.625 | G16: =G8-G12 -> 37.922 | H16: =H8-H12 -> 6.683 | I16: =I8-I12 -> 17.417 | ... BB16: =BB8-BB12 -> 149.75861
A17: Operating Expenses
A18: Selling, general and administrative | B18: 13.268 | C18: 15.622 | D18: 15.256 | E18: 14.733 | F18: 13.313 | G18: 16.775 | H18: 13.663 | I18: 13.387 | J18: 12.788 | K18: 16.699 | L18: 11.287 | M18: 12.768 | N18: 11.484 | O18: 15.287 | P18: 11.956 | Q18: 13.646 | R18: 14.464 | S18: 20.277 | T18: 13.668 | U18: 16.255 | V18: 13.223 | W18: 16.344 | X18: 12.011 | Y18: 14.977 | Z18: 15.652 | AA18: 24.841 | AB18: 27.128 | AC18: 24.819 | AD18: 22.549 | AE18: 21.938 | AF18: 21.943 | AG18: 23.613 | AH18: 24.746 | AI18: 61.603 | AJ18: 23.827 | AK18: 28.147 | AL18: 27.826 | AM18: 34.62 | AN18: 33.795 | AO18: 37.916 | AP18: 43.788 | AQ18: 43.254 | AR18: 131.276 | AS18: 98.336 | AT18: 99.414 | AU18: =AU8*Assumptions!$D$45 -> 112.95197 | AV18: =AV8*Assumptions!$E$45 -> 97.543583 | AW18: =AW8*Assumptions!$F$45 -> 101.3501 | AX18: =AX8*Assumptions!$G$45 -> 87.453934 | AY18: =AY8*Assumptions!$H$45 -> 121.30188 | AZ18: =AZ8*Assumptions!$I$45 -> 99.489974 | BA18: =BA8*Assumptions!$J$45 -> 103.362 | BB18: =BB8*Assumptions!$K$45 -> 89.152043
A19: Research and development | B19: 8.577 | C19: 22.259 | D19: 9.831 | E19: 9.897 | F19: 8.247 | G19: 14.316 | H19: 8.6 | I19: 8.517 | J19: 7.988 | K19: 7.937 | L19: 5.542 | M19: 6.844 | N19: 6.607 | O19: 7.44 | P19: 6.435 | Q19: 8.109 | R19: 8.087 | S19: 11.603 | T19: 8.709 | U19: 10.858 | V19: 11.381 | W19: 15.529 | X19: 11.103 | Y19: 11.976 | Z19: 13.631 | AA19: 17.054 | AB19: 13.708 | AC19: 14.297 | AD19: 13.013 | AE19: 13.671 | AF19: 15.045 | AG19: 16.591 | AH19: 16.157 | AI19: 16.462 | AJ19: 15.466 | AK19: 22.025 | AL19: 25.127 | AM19: 35.069 | AN19: 24.613 | AO19: 28.716 | AP19: 22.498 | AQ19: 24.902 | AR19: 33.114 | AS19: 35.993 | AT19: 27.112 | AU19: =AU8*Assumptions!$D$46 -> 36.70939 | AV19: =AV8*Assumptions!$E$46 -> 34.27207 | AW19: =AW8*Assumptions!$F$46 -> 35.609494 | AX19: =AX8*Assumptions!$G$46 -> 30.727058 | AY19: =AY8*Assumptions!$H$46 -> 42.619581 | AZ19: =AZ8*Assumptions!$I$46 -> 38.040284 | BA19: =BA8*Assumptions!$J$46 -> 39.520766 | BB19: =BB8*Assumptions!$K$46 -> 34.087546
A20: Impairment of goodwill | AQ20: 18.359 | AT20: 240.708 | AU20: =Assumptions!$D$47 -> 0 | AV20: =Assumptions!$E$47 -> 0 | AW20: =Assumptions!$F$47 -> 0 | AX20: =Assumptions!$G$47 -> 0 | AY20: =Assumptions!$H$47 -> 0 | AZ20: =Assumptions!$I$47 -> 0 | BA20: =Assumptions!$J$47 -> 0 | BB20: =Assumptions!$K$47 -> 0
A21: Other operating expense, net | AI21: 156.017 | AU21: =Assumptions!$D$48 -> 0 | AV21: =Assumptions!$E$48 -> 0 | AW21: =Assumptions!$F$48 -> 0 | AX21: =Assumptions!$G$48 -> 0 | AY21: =Assumptions!$H$48 -> 0 | AZ21: =Assumptions!$I$48 -> 0 | BA21: =Assumptions!$J$48 -> 0 | BB21: =Assumptions!$K$48 -> 0
A22: Total operating expenses | B22: =SUM(B18,B19,B20,B21) -> 21.845 | C22: =SUM(C18,C19,C20,C21) -> 37.881 | D22: =SUM(D18,D19,D20,D21) -> 25.087 | E22: =SUM(E18,E19,E20,E21) -> 24.63 | F22: =SUM(F18,F19,F20,F21) -> 21.56 | G22: =SUM(G18,G19,G20,G21) -> 31.091 | H22: =SUM(H18,H19,H20,H21) -> 22.263 | I22: =SUM(I18,I19,I20,I21) -> 21.904 | ... BB22: =SUM(BB18,BB19,BB20,BB21) -> 123.23959
A23: Operating income | B23: =B16-B22 -> 5.148 | C23: =C16-C22 -> 7.469 | D23: =D16-D22 -> -9.064 | E23: =E16-E22 -> 6.903 | F23: =F16-F22 -> 5.065 | G23: =G16-G22 -> 6.831 | H23: =H16-H22 -> -15.58 | I23: =I16-I22 -> -4.487 | ... BB23: =BB16-BB22 -> 26.519021
A24: Other Income / Expense
A25: Interest income (expense), net | B25: 0.224 | C25: 0.253 | D25: 0.224 | E25: 0.268 | F25: 0.181 | G25: 0.359 | H25: 0.375 | I25: 0.397 | J25: 0.39 | K25: 0.456 | L25: 0.512 | M25: 0.432 | N25: 0.545 | O25: 0.751 | P25: 0.906 | Q25: 1.068 | R25: 1.272 | S25: 1.426 | T25: 1.329 | U25: 1.266 | V25: 1.122 | W25: 1.111 | X25: 0.208 | Y25: 0.115 | Z25: 0.094 | AA25: -1.035 | AB25: -1.275 | AC25: -1.379 | AD25: -1.51 | AE25: -1.276 | AF25: -1.603 | AG25: -2.309 | AH25: -2.81 | AI25: -2.646 | AJ25: -2.008 | AK25: -1.95 | AL25: -0.114 | AM25: -0.148 | AN25: -0.239 | AO25: -0.69 | AP25: -0.248 | AQ25: -1.011 | AR25: -17.415 | AS25: 4.669 | AT25: 3.696 | AU25: =Assumptions!$D$49 -> 2 | AV25: =Assumptions!$E$49 -> 2 | AW25: =Assumptions!$F$49 -> 2 | AX25: =Assumptions!$G$49 -> 2 | AY25: =Assumptions!$H$49 -> 2 | AZ25: =Assumptions!$I$49 -> 2 | BA25: =Assumptions!$J$49 -> 2 | BB25: =Assumptions!$K$49 -> 2
A26: Other income (expense), net | B26: -0.284 | C26: -0.727 | D26: -2.389 | E26: -0.192 | F26: -0.215 | G26: 0.097 | H26: -0.3 | I26: -0.13 | J26: -0.038 | K26: 0.529 | L26: 0.004 | M26: -0.055 | N26: -0.108 | O26: 0.11 | P26: 8.388 | Q26: 1.291 | R26: 0.962 | S26: 1.339 | T26: 0.355 | U26: 0.157 | V26: 0.12 | W26: 0.075 | X26: 0.033 | Y26: 0.072 | Z26: -0.037 | AA26: -8.398 | AB26: -0.346 | AC26: -10.048 | AD26: 0.034 | AE26: 0.047 | AF26: -0.406 | AG26: 0.81 | AH26: -2.587 | AI26: 1.837 | AJ26: -1.129 | AK26: -2.858 | AL26: 1.004 | AM26: -1.39 | AN26: -0.234 | AO26: 0.016 | AP26: 0.976 | AQ26: 0.299 | AR26: 2.361 | AS26: 4.951 | AT26: -0.4 | AU26: =Assumptions!$D$50 -> 0 | AV26: =Assumptions!$E$50 -> 0 | AW26: =Assumptions!$F$50 -> 0 | AX26: =Assumptions!$G$50 -> 0 | AY26: =Assumptions!$H$50 -> 0 | AZ26: =Assumptions!$I$50 -> 0 | BA26: =Assumptions!$J$50 -> 0 | BB26: =Assumptions!$K$50 -> 0
A27: Other income (expense) / source adjustment | AE27: 6.497 | AU27: 0 | AV27: 0 | AW27: 0 | AX27: 0 | AY27: 0 | AZ27: 0 | BA27: 0 | BB27: 0
A28: Total other income (expense), net | B28: =SUM(B25,B26,B27) -> -0.06 | C28: =SUM(C25,C26,C27) -> -0.474 | D28: =SUM(D25,D26,D27) -> -2.165 | E28: =SUM(E25,E26,E27) -> 0.076 | F28: =SUM(F25,F26,F27) -> -0.034 | G28: =SUM(G25,G26,G27) -> 0.456 | H28: =SUM(H25,H26,H27) -> 0.075 | I28: =SUM(I25,I26,I27) -> 0.267 | ... BB28: =SUM(BB25,BB26,BB27) -> 2
A29: Income before income taxes | B29: =B23+B28 -> 5.088 | C29: =C23+C28 -> 6.995 | D29: =D23+D28 -> -11.229 | E29: =E23+E28 -> 6.979 | F29: =F23+F28 -> 5.031 | G29: =G23+G28 -> 7.287 | H29: =H23+H28 -> -15.505 | I29: =I23+I28 -> -4.22 | ... BB29: =BB23+BB28 -> 28.519021
A30: Provision for income taxes | B30: 2.763 | C30: -0.085 | D30: -4.248 | E30: 2.56 | F30: -1.133 | G30: 1.923 | H30: -3.863 | I30: -0.048 | J30: 1.102 | K30: 4.561 | L30: -3.221 | M30: 3.358 | N30: 0.834 | O30: 8.829 | P30: 2.567 | Q30: 1.211 | R30: 0.946 | S30: -0.083 | T30: 2.133 | U30: 1.108 | V30: -0.038 | W30: 2.645 | X30: 1.207 | Y30: 2.491 | Z30: -0.924 | AA30: -2.235 | AB30: -0.957 | AC30: -9.511 | AD30: -15.396 | AE30: 15.495 | AF30: 2.606 | AG30: -10.457 | AH30: -0.531 | AI30: -6.281 | AJ30: 1.314 | AK30: 1.137 | AL30: 1.259 | AM30: -1.819 | AN30: 1.485 | AO30: -0.221 | AP30: -0.605 | AQ30: 0.223 | AR30: -15.169 | AS30: -2.305 | AT30: -21.616 | AU30: =AU29*Assumptions!$D$52 -> -0.18810956 | AV30: =AV29*Assumptions!$E$52 -> 2.2521005 | AW30: =AW29*Assumptions!$F$52 -> 2.3065798 | AX30: =AX29*Assumptions!$G$52 -> 1.9637669 | AY30: =AY29*Assumptions!$H$52 -> 2.8673749 | AZ30: =AZ29*Assumptions!$I$52 -> 5.4840891 | BA30: =BA29*Assumptions!$J$52 -> 5.661754 | BB30: =BB29*Assumptions!$K$52 -> 4.8482335
A31: Equity method investment income (loss), net of tax | J31: -0.008 | K31: 0 | N31: -0.418 | O31: -0.865 | P31: -0.602 | Q31: -0.752 | R31: -0.717 | S31: -1.873 | T31: -1.347 | U31: -0.863 | V31: -1.2 | W31: -2.077 | X31: -1.288 | Y31: -9.522 | Z31: -0.081 | AA31: 0.41 | AB31: -1.141 | AC31: 1.133 | AD31: 0.171 | AE31: 4.426 | AF31: -0.5 | AG31: -1.273 | AH31: -0.417 | AI31: -0.263 | AJ31: -0.021 | AK31: -1.393 | AL31: -0.08 | AM31: -0.18 | AN31: 0.065 | AO31: 0.99 | AQ31: 3.782 | AR31: 1.787 | AS31: 1.196 | AT31: -0.295 | AU31: =Assumptions!$D$51 -> 0 | AV31: =Assumptions!$E$51 -> 0 | AW31: =Assumptions!$F$51 -> 0 | AX31: =Assumptions!$G$51 -> 0 | AY31: =Assumptions!$H$51 -> 0 | AZ31: =Assumptions!$I$51 -> 0 | BA31: =Assumptions!$J$51 -> 0 | BB31: =Assumptions!$K$51 -> 0
A32: Net income from continuing operations | B32: =B29-B30+B31 -> 2.325 | C32: =C29-C30+C31 -> 7.08 | D32: =D29-D30+D31 -> -6.981 | E32: =E29-E30+E31 -> 4.419 | F32: =F29-F30+F31 -> 6.164 | G32: =G29-G30+G31 -> 5.364 | H32: =H29-H30+H31 -> -11.642 | I32: =I29-I30+I31 -> -4.172 | ... BB32: =BB29-BB30+BB31 -> 23.670787
A33: Discontinued operations, net of tax | L33: -1.488 | M33: -0.033 | N33: -0.129 | O33: -2.237 | P33: 6.993 | Q33: -0.99 | R33: -0.062 | S33: -0.415 | AU33: 0 | AV33: 0 | AW33: 0 | AX33: 0 | AY33: 0 | AZ33: 0 | BA33: 0 | BB33: 0
A34: Net income | B34: =B32+B33 -> 2.325 | C34: =C32+C33 -> 7.08 | D34: =D32+D33 -> -6.981 | E34: =E32+E33 -> 4.419 | F34: =F32+F33 -> 6.164 | G34: =G32+G33 -> 5.364 | H34: =H32+H33 -> -11.642 | I34: =I32+I33 -> -4.172 | ... BB34: =BB32+BB33 -> 23.670787
A35: Net income attributable to noncontrolling interest | K35: 0.022 | L35: 0.023 | M35: 0.206 | N35: 0.009 | O35: -0.022 | P35: 0.014 | Q35: 0.007 | R35: 0.019 | S35: -0.021 | T35: 0.011 | U35: -0.004 | V35: 0.02 | W35: -0.023 | X35: 0.037 | Y35: 0.022 | Z35: -0.047 | AA35: -0.026 | AB35: -0.063 | AC35: -0.031 | AD35: 0.045 | AE35: 0.046 | AF35: -0.006 | AG35: -0.039 | AI35: 0 | AU35: =Assumptions!$D$55 -> 0 | AV35: =Assumptions!$E$55 -> 0 | AW35: =Assumptions!$F$55 -> 0 | AX35: =Assumptions!$G$55 -> 0 | AY35: =Assumptions!$H$55 -> 0 | AZ35: =Assumptions!$I$55 -> 0 | BA35: =Assumptions!$J$55 -> 0 | BB35: =Assumptions!$K$55 -> 0
A36: Net income attributable to AeroVironment, Inc. | B36: =B34+B35 -> 2.325 | C36: =C34+C35 -> 7.08 | D36: =D34+D35 -> -6.981 | E36: =E34+E35 -> 4.419 | F36: =F34+F35 -> 6.164 | G36: =G34+G35 -> 5.364 | H36: =H34+H35 -> -11.642 | I36: =I34+I35 -> -4.172 | ... BB36: =BB34+BB35 -> 23.670787
A37: Per Share Data
A38: Weighted average shares outstanding - basic | B38: 22.8905 | C38: 22.9052 | D38: 22.9475 | E38: 22.986 | F38: 22.8905 | G38: 22.9215 | H38: 22.9566 | I38: 23.0491 | J38: 23.083 | K38: 23.1466 | L38: 23.3363 | M38: 23.4779 | N38: 23.5156 | O38: 23.5519 | P38: 23.5746 | Q38: 23.6674 | R38: 23.6877 | S38: 23.718 | T38: 23.7452 | U38: 23.8044 | V38: 23.8211 | W38: 23.8496 | X38: 23.893 | Y38: 23.937 | Z38: 23.9428 | AA38: 24.4343 | AB38: 24.6202 | AC38: 24.6416 | AD38: 24.711 | AE38: 24.7689 | AF38: 24.8042 | AG38: 24.9009 | AH38: 25.0124 | AI38: 25.451 | AJ38: 26.0883 | AK38: 26.8658 | AL38: 27.9076 | AM38: 27.9163 | AN38: 27.9597 | AO38: 28.01 | AP38: 28.0319 | AQ38: 28.0686 | AR38: 46.8824 | AS38: 49.7233 | AT38: 49.7414 | AU38: =Assumptions!$D$54 -> 49.8 | AV38: =Assumptions!$E$54 -> 49.9 | AW38: =Assumptions!$F$54 -> 50 | AX38: =Assumptions!$G$54 -> 50.1 | AY38: =Assumptions!$H$54 -> 50.2 | AZ38: =Assumptions!$I$54 -> 50.3 | BA38: =Assumptions!$J$54 -> 50.4 | BB38: =Assumptions!$K$54 -> 50.5
A39: Weighted average shares outstanding - diluted | B39: 23.1094 | C39: 23.1483 | D39: 22.9475 | E39: 23.1485 | F39: 23.0838 | G39: 23.1435 | H39: 22.9566 | I39: 23.0491 | J39: 23.083 | K39: 23.3714 | L39: 23.3363 | M39: 23.833 | N39: 23.5156 | O39: 23.9169 | P39: 24.0103 | Q39: 24.0988 | R39: 24.0818 | S39: 24.0947 | T39: 24.0699 | U39: 24.0618 | V39: 23.8211 | W39: 24.1338 | X39: 24.1862 | Y39: 24.1969 | Z39: 24.2609 | AA39: 24.7799 | AB39: 24.6202 | AC39: 24.8859 | AD39: 24.8796 | AE39: 24.9362 | AF39: 24.8042 | AG39: 24.9009 | AH39: 25.0124 | AI39: 25.451 | AJ39: 26.179 | AK39: 26.9568 | AL39: 28.0441 | AM39: 28.0967 | AN39: 28.2818 | AO39: 28.1456 | AP39: 28.0319 | AQ39: 28.265 | AR39: 46.8824 | AS39: 49.7233 | AT39: 49.7414 | AU39: =Assumptions!$D$53 -> 50 | AV39: =Assumptions!$E$53 -> 50.1 | AW39: =Assumptions!$F$53 -> 50.2 | AX39: =Assumptions!$G$53 -> 50.3 | AY39: =Assumptions!$H$53 -> 50.4 | AZ39: =Assumptions!$I$53 -> 50.5 | BA39: =Assumptions!$J$53 -> 50.6 | BB39: =Assumptions!$K$53 -> 50.7
A40: Basic EPS | B40: =IF(B38=0,"",B36/B38) -> 0.10157052 | C40: =IF(C38=0,"",C36/C38) -> 0.30910012 | D40: =IF(D38=0,"",D36/D38) -> -0.30421615 | E40: =IF(E38=0,"",E36/E38) -> 0.19224745 | F40: =IF(F38=0,"",F36/F38) -> 0.26928202 | G40: =IF(G38=0,"",G36/G38) -> 0.2340161 | H40: =IF(H38=0,"",H36/H38) -> -0.50713085 | I40: =IF(I38=0,"",I36/I38) -> -0.1810049 | ... BB40: =IF(BB38=0,"",BB36/BB38) -> 0.46872846
A41: Diluted EPS | B41: =IF(B39=0,"",B36/B39) -> 0.10060841 | C41: =IF(C39=0,"",C36/C39) -> 0.30585399 | D41: =IF(D39=0,"",D36/D39) -> -0.30421615 | E41: =IF(E39=0,"",E36/E39) -> 0.1908979 | F41: =IF(F39=0,"",F36/F39) -> 0.26702709 | G41: =IF(G39=0,"",G36/G39) -> 0.23177134 | H41: =IF(H39=0,"",H36/H39) -> -0.50713085 | I41: =IF(I39=0,"",I36/I39) -> -0.1810049 | ... BB41: =IF(BB39=0,"",BB36/BB39) -> 0.46687943

Sheet BS - Quarterly
A1: AeroVironment, Inc. - Balance Sheet
A2: USD mm
A4: Fiscal quarter end | B4: 1/31/15 | C4: 4/30/15 | D4: 8/1/15 | E4: 10/31/15 | F4: 1/30/16 | G4: 4/30/16 | H4: 7/30/16 | I4: 10/29/16 | J4: 1/28/17 | K4: 4/30/17 | L4: 7/29/17 | M4: 10/28/17 | N4: 1/27/18 | O4: 4/30/18 | P4: 7/28/18 | Q4: 10/27/18 | R4: 1/26/19 | S4: 4/30/19 | T4: 7/27/19 | U4: 10/26/19 | V4: 1/25/20 | W4: 4/30/20 | X4: 8/1/20 | Y4: 10/31/20 | Z4: 1/30/21 | AA4: 4/30/21 | AB4: 7/31/21 | AC4: 10/30/21 | AD4: 1/29/22 | AE4: 4/30/22 | AF4: 7/30/22 | AG4: 10/29/22 | AH4: 1/28/23 | AI4: 4/30/23 | AJ4: 7/29/23 | AK4: 10/28/23 | AL4: 1/27/24 | AM4: 4/30/24 | AN4: 7/27/24 | AO4: 10/26/24 | AP4: 1/25/25 | AQ4: 4/30/25 | AR4: 8/2/25 | AS4: 11/1/25 | AT4: 1/31/26
A5: Assets
A6: Cash and cash equivalents | B6: 125.977 | C6: 143.41 | D6: 146.45 | E6: 128.032 | F6: 122.706 | G6: 124.287 | H6: 122.313 | I6: 88.876 | J6: 73.278 | K6: 79.904 | L6: 117.473 | M6: 117.109 | N6: 112.304 | O6: 143.517 | P6: 170.788 | Q6: 151.255 | R6: 149.369 | S6: 172.708 | T6: 137.094 | U6: 130.742 | V6: 131.496 | W6: 255.142 | X6: 246.839 | Y6: 280.099 | Z6: 324.543 | AA6: 148.741 | AB6: 93.924 | AC6: 104.77 | AD6: 82.528 | AE6: 77.231 | AF6: 93.183 | AG6: 101.417 | AH6: 78.276 | AI6: 132.859 | AJ6: 105.871 | AK6: 100.908 | AL6: 107.694 | AM6: 73.301 | AN6: 81.162 | AO6: 68.96 | AP6: 47 | AQ6: 40.862 | AR6: 685.803 | AS6: 359.434 | AT6: 289.878
A7: Short-term investments | B7: 77.581 | C7: 85.381 | D7: 71.018 | E7: 77.967 | F7: 97.69 | G7: 103.404 | H7: 101.802 | I7: 118.208 | J7: 121.095 | K7: 119.971 | L7: 107.831 | M7: 110.751 | N7: 109.543 | O7: 113.649 | P7: 118.303 | Q7: 138.536 | R7: 144.815 | S7: 150.487 | T7: 163.634 | U7: 161.635 | V7: 148.502 | W7: 47.507 | X7: 71.334 | Y7: 67.137 | Z7: 48.499 | AA7: 31.971 | AB7: 17.953 | AC7: 6.311 | AD7: 3.969 | AE7: 24.716 | AF7: 12.655 | AH7: 0 | AS7: 229.046 | AT7: 297.259
A8: Accounts receivable, net | B8: 37.834 | C8: 33.607 | D8: 28.205 | E8: 42.746 | F8: 38.991 | G8: 56.045 | H8: 32.635 | I8: 26.102 | J8: 23.121 | K8: 68.719 | L8: 30.685 | M8: 35.106 | N8: 25.69 | O8: 56.813 | P8: 13.802 | Q8: 34.639 | R8: 34.064 | S8: 31.051 | T8: 42.724 | U8: 40.564 | V8: 27.936 | W8: 73.66 | X8: 43.357 | Y8: 30.701 | Z8: 26.621 | AA8: 62.647 | AB8: 45.764 | AC8: 26.552 | AD8: 41.739 | AE8: 60.17 | AF8: 52.062 | AG8: 31.664 | AH8: 52.871 | AI8: 87.633 | AJ8: 79.214 | AK8: 73.865 | AL8: 53.236 | AM8: 70.305 | AN8: 35.487 | AO8: 73.935 | AP8: 81.231 | AQ8: 101.967 | AR8: 198.293 | AS8: 232.342 | AT8: 201.046
A9: Unbilled receivables and retentions | B9: 8.345 | C9: 17.356 | D9: 13.998 | E9: 11.798 | F9: 10.44 | G9: 18.899 | H9: 14.493 | I9: 16.87 | J9: 14.82 | K9: 14.12 | L9: 10.753 | M9: 13.494 | N9: 24.961 | O9: 16.872 | P9: 59.87 | Q9: 45.654 | R9: 51.632 | S9: 53.047 | T9: 47.935 | U9: 62.397 | V9: 77.411 | W9: 75.837 | X9: 73.791 | Y9: 70.573 | Z9: 61.084 | AA9: 71.632 | AB9: 87.131 | AC9: 119.031 | AD9: 97.993 | AE9: 104.194 | AF9: 89.397 | AG9: 92.457 | AH9: 109.289 | AI9: 105.653 | AJ9: 107.258 | AK9: 141.812 | AL9: 148.588 | AM9: 199.474 | AN9: 219.766 | AO9: 204.18 | AP9: 229.651 | AQ9: 290.009 | AR9: 463.87 | AS9: 513.486 | AT9: 528.557
A10: Inventories, net | B10: 48.799 | C10: 39.414 | D10: 43.921 | E10: 48.336 | F10: 46.434 | G10: 37.486 | H10: 44.105 | I10: 55.168 | J10: 68.806 | K10: 40.908 | L10: 72.017 | M10: 76.039 | N10: 77.327 | O10: 37.425 | P10: 42.244 | Q10: 46.096 | R10: 50.379 | S10: 54.056 | T10: 56.336 | U10: 52.769 | V10: 65.156 | W10: 45.535 | X10: 45.53 | Y10: 51.779 | Z10: 53.104 | AA10: 71.646 | AB10: 84.852 | AC10: 81.944 | AD10: 89.616 | AE10: 90.629 | AF10: 98.603 | AG10: 109.81 | AH10: 125.942 | AI10: 138.814 | AJ10: 175.396 | AK10: 181.767 | AL10: 161.384 | AM10: 150.168 | AN10: 143.835 | AO10: 139.698 | AP10: 147.973 | AQ10: 144.09 | AR10: 232.888 | AS10: 259.213 | AT10: 299.277
A11: Deferred income taxes | B11: 5.217 | C11: 5.265 | D11: 5.062 | E11: 5.05 | F11: 5.247
A12: Income taxes receivable | B12: 1.94 | D12: 5.569 | E12: 2.836 | F12: 3.901 | H12: 4.25 | I12: 3.957 | J12: 2.487 | L12: 2.969 | N12: 0.292 | S12: 0.821 | AB12: 0.322 | AC12: 11.708 | AD12: 26.578 | AE12: 0.442 | AG12: 8.94 | AH12: 9.18 | AK12: 5.735 | AL12: 8.081 | AN12: 0.338 | AO12: 9.628 | AP12: 15.112 | AQ12: 0.622 | AR12: 20.778 | AS12: 26.446 | AT12: 43.031
A13: Current assets of discontinued operations | K13: 24.93 | O13: 25.668
A14: Prepaid expenses and other current assets | B14: 4.203 | C14: 4.599 | D14: 3.958 | E14: 4.555 | F14: 4.219 | G14: 4.15 | H14: 4.167 | I14: 4.706 | J14: 5.341 | K14: 5.533 | L14: 5.266 | M14: 5.175 | N14: 5.138 | O14: 5.103 | P14: 5.196 | Q14: 5.732 | R14: 6.616 | S14: 7.418 | T14: 7.606 | U14: 8.045 | V14: 6.833 | W14: 6.246 | X14: 5.941 | Y14: 7.31 | Z14: 7.693 | AA14: 15.001 | AB14: 14.972 | AC14: 13.761 | AD14: 12.099 | AE14: 11.527 | AF14: 11.368 | AG14: 13.244 | AH14: 15.323 | AI14: 12.043 | AJ14: 13.949 | AK14: 19.958 | AL14: 21.708 | AM14: 22.333 | AN14: 19.758 | AO14: 18.444 | AP14: 22.919 | AQ14: 28.966 | AR14: 37.707 | AS14: 46.49 | AT14: 45.199
A15: Total current assets | B15: =SUM(B6,B7,B8,B9,B10,B11,B12,B13,B14) -> 309.896 | C15: =SUM(C6,C7,C8,C9,C10,C11,C12,C13,C14) -> 329.032 | D15: =SUM(D6,D7,D8,D9,D10,D11,D12,D13,D14) -> 318.181 | E15: =SUM(E6,E7,E8,E9,E10,E11,E12,E13,E14) -> 321.32 | F15: =SUM(F6,F7,F8,F9,F10,F11,F12,F13,F14) -> 329.628 | G15: =SUM(G6,G7,G8,G9,G10,G11,G12,G13,G14) -> 344.271 | H15: =SUM(H6,H7,H8,H9,H10,H11,H12,H13,H14) -> 323.765 | I15: =SUM(I6,I7,I8,I9,I10,I11,I12,I13,I14) -> 313.887 | ... AT15: =SUM(AT6,AT7,AT8,AT9,AT10,AT11,AT12,AT13,AT14) -> 1704.247
A16: Long-term investments | B16: 54.575 | C16: 46.769 | D16: 44.727 | E16: 37.715 | F16: 38.175 | G16: 33.859 | H16: 33.097 | I16: 42.559 | J16: 43.749 | K16: 42.096 | L16: 35.844 | M16: 33.024 | N16: 38.822 | O16: 40.656 | P16: 36.712 | Q16: 30.459 | R16: 27.954 | S16: 9.386 | T16: 4.887 | U16: 13.478 | V16: 26.409 | W16: 15.03 | X16: 20.338 | Y16: 20.976 | Z16: 11.222 | AA16: 12.156 | AB16: 10.165 | AC16: 11.971 | AD16: 12.388 | AE16: 15.433 | AF16: 17.707 | AG16: 22.462 | AH16: 19.319 | AI16: 23.613 | AJ16: 22.578 | AK16: 20.611 | AL16: 21.282 | AM16: 20.96 | AN16: 21.887 | AO16: 22.942 | AP16: 25.522 | AQ16: 31.627 | AR16: 36.267 | AS16: 80.97 | AT16: 61.659
A17: Property and equipment, net | B17: 16.143 | C17: 13.499 | D17: 13.023 | E17: 13.579 | F17: 14.313 | G17: 16.762 | H17: 16.91 | I17: 17.445 | J17: 18.41 | K17: 15.962 | L17: 20.317 | M17: 21.614 | N17: 21.626 | O17: 19.219 | P17: 19.347 | Q17: 20.46 | R17: 20.542 | S17: 16.905 | T17: 17.747 | U17: 20.571 | V17: 19.877 | W17: 21.694 | X17: 22.907 | Y17: 22.868 | Z17: 22.92 | AA17: 58.896 | AB17: 66.563 | AC17: 68.217 | AD17: 65.377 | AE17: 62.296 | AF17: 61.862 | AG17: 52.415 | AH17: 45.388 | AI17: 39.795 | AJ17: 39.77 | AK17: 43.772 | AL17: 45.053 | AM17: 46.602 | AN17: 48.071 | AO17: 49.681 | AP17: 49.587 | AQ17: 50.704 | AR17: 148.807 | AS17: 155.383 | AT17: 158.867
A18: Operating lease right-of-use assets | T18: 9.917 | U18: 8.902 | V18: 9.472 | W18: 8.793 | X18: 13.612 | Y18: 12.363 | Z18: 11.281 | AA18: 22.902 | AB18: 27.649 | AC18: 22.902 | AD18: 24.848 | AE18: 26.769 | AF18: 25.385 | AG18: 25.58 | AH18: 28.336 | AI18: 27.363 | AJ18: 25.742 | AK18: 30.632 | AL18: 28.904 | AM18: 41.303 | AN18: 28.283 | AO18: 32.502 | AP18: 31.696 | AQ18: 61.46 | AR18: 98.514 | AS18: 94.291 | AT18: 91.81
A19: Deferred income taxes | B19: 4.638 | C19: 7.426 | D19: 6.671 | E19: 6.725 | F19: 6.72 | G19: 15.016 | H19: 15.104 | I19: 15.409 | J19: 15.779 | K19: 15.089 | L19: 15.646 | M19: 16.113 | N19: 14.837 | O19: 11.494 | P19: 11.8 | Q19: 12.108 | R19: 12.708 | S19: 6.685 | T19: 7.699 | U19: 8.019 | V19: 8.296 | W19: 4.928 | X19: 5.262 | Y19: 5.546 | Z19: 5.821 | AA19: 2.061 | AB19: 2.534 | AC19: 2.9 | AD19: 3.258 | AE19: 7.29 | AF19: 7.671 | AG19: 8.098 | AH19: 8.54 | AI19: 27.206 | AJ19: 27.633 | AK19: 20.78 | AL19: 21.378 | AM19: 30.033 | AN19: 41.303 | AO19: 41.303 | AP19: 41.303 | AQ19: 31.879
A20: Intangibles, net | S20: 0.459 | T20: 16.727 | U20: 15.952 | V20: 14.357 | W20: 13.637 | X20: 12.928 | Y20: 12.213 | Z20: 11.552 | AA20: 106.268 | AB20: 117.855 | AC20: 110.62 | AD20: 103.825 | AE20: 97.224 | AF20: 91.009 | AG20: 88.66 | AH20: 83.442 | AI20: 43.577 | AJ20: 40.54 | AK20: 82.848 | AL20: 77.597 | AM20: 72.224 | AN20: 67.521 | AO20: 62.703 | AP20: 57.78 | AQ20: 48.711 | AR20: 1118.85 | AS20: 971.787 | AT20: 925.925
A21: Goodwill | T21: 8.08 | U21: 8.08 | V21: 6.34 | W21: 6.34 | X21: 6.34 | Y21: 6.34 | Z21: 6.34 | AA21: 314.205 | AB21: 335.029 | AC21: 335.888 | AD21: 335.164 | AE21: 334.347 | AF21: 333.791 | AG21: 334.963 | AH21: 336.555 | AI21: 180.801 | AJ21: 180.797 | AK21: 274.781 | AL21: 275.189 | AM21: 275.652 | AN21: 275.932 | AO21: 275.827 | AP21: 275.289 | AQ21: 256.781 | AR21: 2539.56 | AS21: 2623.67 | AT21: 2372.31
A22: Other assets | B22: 1.219 | C22: 0.741 | D22: 0.672 | E22: 0.69 | F22: 0.653 | G22: 0.75 | H22: 0.658 | I22: 0.598 | J22: 0.57 | K22: 2.01 | L22: 1.938 | M22: 0.838 | N22: 2.305 | O22: 3.002 | P22: 2.299 | Q22: 1.628 | R22: 0.884 | S22: 5.821 | T22: 14.196 | U22: 13.339 | V22: 16.995 | W22: 10.605 | X22: 9.64 | Y22: 0.102 | Z22: 0.312 | AA22: 10.44 | AB22: 3.84 | AC22: 6.276 | AD22: 5.881 | AE22: 1.932 | AF22: 1.961 | AG22: 1.972 | AH22: 8.741 | AI22: 5.22 | AJ22: 7.312 | AK22: 9.231 | AL22: 10.205 | AM22: 13.505 | AN22: 15.826 | AO22: 19.282 | AP22: 23.08 | AQ22: 32.889 | AR22: 42.702 | AS22: 45.909 | AT22: 49.414
A23: Long-term assets of discontinued operations | K23: 3.258
A24: Other assets / source adjustment | AC24: 2.456
A25: Total assets | B25: =SUM(B15,B16,B17,B18,B19,B20,B21,B22,B23,B24) -> 386.471 | C25: =SUM(C15,C16,C17,C18,C19,C20,C21,C22,C23,C24) -> 397.467 | D25: =SUM(D15,D16,D17,D18,D19,D20,D21,D22,D23,D24) -> 383.274 | E25: =SUM(E15,E16,E17,E18,E19,E20,E21,E22,E23,E24) -> 380.029 | F25: =SUM(F15,F16,F17,F18,F19,F20,F21,F22,F23,F24) -> 389.489 | G25: =SUM(G15,G16,G17,G18,G19,G20,G21,G22,G23,G24) -> 410.658 | H25: =SUM(H15,H16,H17,H18,H19,H20,H21,H22,H23,H24) -> 389.534 | I25: =SUM(I15,I16,I17,I18,I19,I20,I21,I22,I23,I24) -> 389.898 | ... AT25: =SUM(AT15,AT16,AT17,AT18,AT19,AT20,AT21,AT22,AT23,AT24) -> 5364.232
A26: Liabilities
A27: Accounts payable | B27: 16.215 | C27: 19.243 | D27: 12.944 | E27: 11.59 | F27: 9.786 | G27: 17.712 | H27: 10.529 | I27: 18.662 | J27: 13.792 | K27: 15.896 | L27: 13.966 | M27: 15.724 | N27: 13.249 | O27: 21.34 | P27: 12.939 | Q27: 14.149 | R27: 11.629 | S27: 15.972 | T27: 11.45 | U27: 11.022 | V27: 14.269 | W27: 19.859 | X27: 11.74 | Y27: 14.225 | Z27: 15.837 | AA27: 24.841 | AB27: 18.046 | AC27: 21.443 | AD27: 15.118 | AE27: 19.244 | AF27: 21.945 | AG27: 26.317 | AH27: 26.42 | AI27: 31.355 | AJ27: 28.824 | AK27: 28.834 | AL27: 26.969 | AM27: 48.298 | AN27: 43.596 | AO27: 40.646 | AP27: 48.766 | AQ27: 72.462 | AR27: 91.133 | AS27: 119.531 | AT27: 109.633
A28: Wages and related accruals | B28: 12.968 | C28: 13.395 | D28: 10.438 | E28: 10.503 | F28: 13.463 | G28: 13.973 | H28: 9.934 | I28: 10.021 | J28: 10.967 | K28: 10.947 | L28: 10.608 | M28: 10.415 | N28: 15.09 | O28: 16.851 | P28: 10.624 | Q28: 11.071 | R28: 14.363 | S28: 18.507 | T28: 12.085 | U28: 13.218 | V28: 17.636 | W28: 23.972 | X28: 13.025 | Y28: 18.737 | Z28: 20.081 | AA28: 28.068 | AB28: 20.067 | AC28: 21.697 | AD28: 21.207 | AE28: 25.398 | AF28: 17.403 | AG28: 25.049 | AH28: 27.135 | AI28: 35.637 | AJ28: 16.875 | AK28: 26.671 | AL28: 28.443 | AM28: 44.312 | AN28: 20.413 | AO28: 31.594 | AP28: 36.55 | AQ28: 44.253 | AR28: 73.752 | AS28: 79.294 | AT28: 75.765
A29: Customer advances | B29: 4.213 | C29: 4.235 | D29: 4.259 | E29: 3.835 | F29: 3.213 | G29: 2.544 | H29: 2.416 | I29: 3.72 | J29: 5.456 | K29: 2.057 | L29: 4.593 | M29: 3.921 | N29: 3.555 | O29: 3.564 | P29: 1.627 | Q29: 2.449 | R29: 2.875 | S29: 2.962 | T29: 3.268 | U29: 2.55 | V29: 10.633 | W29: 7.899 | X29: 5.725 | Y29: 2.957 | Z29: 4.279 | AA29: 7.183 | AB29: 9.117 | AC29: 10.322 | AD29: 6.864 | AE29: 8.968 | AF29: 10.258 | AG29: 7.074 | AH29: 22.553 | AI29: 16.645 | AJ29: 19.94 | AK29: 20.44 | AL29: 17.536 | AM29: 11.192 | AN29: 10.993 | AO29: 10.64 | AP29: 12.064 | AQ29: 15.952 | AR29: 61.269 | AS29: 71.167 | AT29: 67.543
A30: Current portion of long-term debt | AA30: 10 | AB30: 10 | AC30: 10 | AD30: 10 | AE30: 10 | AF30: 10 | AG30: 10 | AH30: 10 | AI30: 7.5 | AJ30: 10 | AK30: 5 | AL30: 7.5 | AM30: 10 | AN30: 10
A31: Current operating lease liabilities | T31: 2.771 | U31: 2.29 | V31: 2.083 | W31: 3.38 | X31: 4.478 | Y31: 4.03 | Z31: 4.403 | AA31: 6.154 | AB31: 6.747 | AC31: 6.44 | AD31: 6.15 | AE31: 6.819 | AF31: 7.029 | AG31: 7.564 | AH31: 7.794 | AI31: 8.229 | AJ31: 8.272 | AK31: 8.818 | AL31: 8.934 | AM31: 9.841 | AN31: 9.428 | AO31: 9.591 | AP31: 9.365 | AQ31: 10.479 | AR31: 16.759 | AS31: 14.829 | AT31: 15.569
A32: Income taxes payable | C32: 0.692 | G32: 0.943 | K32: 1.418 | M32: 0.35 | O32: 4.085 | P32: 8.898 | Q32: 4.851 | R32: 4.857 | T32: 1.367 | U32: 2.57 | V32: 2.809 | W32: 1.065 | X32: 2.62 | Y32: 3.018 | Z32: 2.37 | AA32: 0.861 | AB32: 0.549 | AC32: 0.214 | AD32: 0.247 | AE32: 0.759 | AF32: 2.962 | AG32: 0.026 | AH32: 0.026 | AI32: 2.342 | AJ32: 4.058 | AK32: 0.595 | AL32: 0.797 | AM32: 4.162 | AN32: 5.597 | AO32: 0.028 | AP32: 0.025 | AQ32: 0.356 | AS32: 0.215 | AT32: 0.32
A33: Other current liabilities | B33: 10.264 | C33: 9.17 | D33: 8.757 | E33: 5.669 | F33: 6.408 | G33: 11.173 | H33: 12.708 | I33: 6.997 | J33: 7.753 | K33: 8.444 | L33: 8.53 | M33: 7.441 | N33: 8.651 | O33: 6.954 | P33: 6.664 | Q33: 6.971 | R33: 8.062 | S33: 7.425 | T33: 12.167 | U33: 13.141 | V33: 13.046 | W33: 10.778 | X33: 8.735 | Y33: 10.511 | Z33: 9.158 | AA33: 19.078 | AB33: 18.134 | AC33: 31.313 | AD33: 27.897 | AE33: 30.203 | AF33: 26.279 | AG33: 27.824 | AH33: 22.469 | AI33: 19.626 | AJ33: 19.22 | AK33: 18.946 | AL33: 17.352 | AM33: 17.074 | AN33: 17.331 | AO33: 19.112 | AP33: 22.138 | AQ33: 28.659 | AR33: 32.017 | AS33: 42.991 | AT33: 40.489
A34: Current liabilities of discontinued operations | K34: 9.301 | O34: 9.294
A35: Total current liabilities | B35: =SUM(B27,B28,B29,B30,B31,B32,B33,B34) -> 43.66 | C35: =SUM(C27,C28,C29,C30,C31,C32,C33,C34) -> 46.735 | D35: =SUM(D27,D28,D29,D30,D31,D32,D33,D34) -> 36.398 | E35: =SUM(E27,E28,E29,E30,E31,E32,E33,E34) -> 31.597 | F35: =SUM(F27,F28,F29,F30,F31,F32,F33,F34) -> 32.87 | G35: =SUM(G27,G28,G29,G30,G31,G32,G33,G34) -> 46.345 | H35: =SUM(H27,H28,H29,H30,H31,H32,H33,H34) -> 35.587 | I35: =SUM(I27,I28,I29,I30,I31,I32,I33,I34) -> 39.4 | ... AT35: =SUM(AT27,AT28,AT29,AT30,AT31,AT32,AT33,AT34) -> 309.319
A36: Deferred rent | B36: 1.336 | C36: 1.381 | D36: 1.33 | E36: 1.266 | F36: 1.223 | G36: 1.714 | H36: 1.864 | I36: 1.82 | J36: 1.769 | K36: 1.719 | L36: 1.673 | M36: 1.637 | N36: 1.589 | O36: 1.536 | P36: 1.476 | Q36: 1.478 | R36: 1.352 | S36: 1.173
A37: Capital lease obligations - net of current portion | F37: 0.388 | G37: 0.449 | H37: 0.357 | I37: 0.276 | J37: 0.218 | K37: 0.161 | L37: 0.104 | M37: 0.05 | N37: 0.007
A38: Long-term debt | AA38: 187.512 | AB38: 185.141 | AC38: 182.769 | AD38: 180.398 | AE38: 177.84 | AF38: 175.481 | AG38: 155.622 | AH38: 155.763 | AI38: 125.904 | AJ38: 118.537 | AK38: 73.678 | AL38: 31.292 | AM38: 17.092 | AN38: 6.788 | AO38: 15 | AP38: 25 | AQ38: 30 | AR38: 725.703 | AS38: 726.793 | AT38: 727.877
A39: Non-current operating lease liabilities | T39: 7.597 | U39: 6.843 | V39: 7.556 | W39: 6.833 | X39: 10.344 | Y39: 9.422 | Z39: 8.426 | AA39: 19.103 | AB39: 23.048 | AC39: 21.665 | AD39: 20.678 | AE39: 21.915 | AF39: 20.371 | AG39: 20.043 | AH39: 22.63 | AI39: 21.189 | AJ39: 19.454 | AK39: 23.727 | AL39: 21.978 | AM39: 22.745 | AN39: 21.086 | AO39: 25.69 | AP39: 24.82 | AQ39: 23.812 | AR39: 87.246 | AS39: 84.313 | AT39: 82.567
A40: Other non-current liabilities | G40: 0.184 | H40: 0.184 | I40: 0.193 | J40: 0.193 | K40: 0.184 | L40: 0.184 | M40: 0.184 | N40: 0.184 | O40: 0.622 | P40: 0.958 | Q40: 1.306 | R40: 0.16 | S40: 0.15 | T40: 2.298 | U40: 2.422 | V40: 0.25 | W40: 0.25 | X40: 0.243 | Y40: 0.243 | Z40: 0.243 | AA40: 10.141 | AB40: 10.336 | AC40: 10.302 | AD40: 5.273 | AE40: 0.768 | AF40: 0.759 | AG40: 0.748 | AH40: 0.742 | AI40: 0.746 | AJ40: 1.901 | AK40: 1.898 | AL40: 2.105 | AM40: 2.132 | AN40: 2.123 | AO40: 2.114 | AP40: 2.106 | AQ40: 2.026 | AR40: 2.016 | AS40: 2.003 | AT40: 1.995
A41: Liability for uncertain tax positions | B41: 0.645 | C41: 0.439 | D41: 0.439 | E41: 0.439 | F41: 0.439 | G41: 0.441 | H41: 0.062 | I41: 0.062 | J41: 0.062 | K41: 0.064 | L41: 0.064 | M41: 0.064 | N41: 0.064 | O41: 0.049 | P41: 0.049 | Q41: 0.049 | R41: 0.049 | S41: 0.051 | T41: 0.051 | U41: 0.051 | V41: 0.051 | W41: 1.017 | X41: 1.017 | Y41: 1.017 | Z41: 1.017 | AA41: 3.518 | AB41: 3.518 | AC41: 3.518 | AD41: 3.518 | AE41: 1.45 | AF41: 1.45 | AG41: 1.45 | AH41: 1.45 | AI41: 2.705 | AJ41: 2.705 | AK41: 2.705 | AL41: 2.705 | AM41: 5.603 | AN41: 5.603 | AO41: 5.603 | AP41: 5.603 | AQ41: 6.061 | AR41: 6.061 | AS41: 6.061 | AT41: 6.061
A42: Deferred income taxes | K42: 0.116 | L42: 0.079 | M42: 0.067 | N42: 0.067 | O42: 0.067 | P42: 0.067 | Q42: 0.067 | R42: 0.067 | S42: 0.029 | T42: 0.029 | U42: 0.029 | V42: 0.029 | AB42: 5.533 | AC42: 5.39 | AD42: 5.198 | AE42: 2.626 | AF42: 2.547 | AG42: 2.482 | AH42: 2.707 | AI42: 1.729 | AJ42: 1.729 | AK42: 1.658 | AL42: 1.703 | AM42: 0.664 | AN42: 0.673 | AO42: 0.67 | AP42: 0.651 | AR42: 101.002 | AS42: 73.188 | AT42: 51.497
A43: Total liabilities | B43: =SUM(B35,B36,B37,B38,B39,B40,B41,B42) -> 45.641 | C43: =SUM(C35,C36,C37,C38,C39,C40,C41,C42) -> 48.555 | D43: =SUM(D35,D36,D37,D38,D39,D40,D41,D42) -> 38.167 | E43: =SUM(E35,E36,E37,E38,E39,E40,E41,E42) -> 33.302 | F43: =SUM(F35,F36,F37,F38,F39,F40,F41,F42) -> 34.92 | G43: =SUM(G35,G36,G37,G38,G39,G40,G41,G42) -> 49.133 | H43: =SUM(H35,H36,H37,H38,H39,H40,H41,H42) -> 38.054 | I43: =SUM(I35,I36,I37,I38,I39,I40,I41,I42) -> 41.751 | ... AT43: =SUM(AT35,AT36,AT37,AT38,AT39,AT40,AT41,AT42) -> 1179.316
A44: Stockholders' Equity
A45: Common stock | B45: 0.002 | C45: 0.002 | D45: 0.002 | E45: 0.002 | F45: 0.002 | G45: 0.002 | H45: 0.002 | I45: 0.002 | J45: 0.002 | K45: 0.002 | L45: 0.002 | M45: 0.002 | N45: 0.002 | O45: 0.002 | P45: 0.002 | Q45: 0.002 | R45: 0.002 | S45: 0.002 | T45: 0.002 | U45: 0.002 | V45: 0.002 | W45: 0.002 | X45: 0.002 | Y45: 0.002 | Z45: 0.002 | AA45: 0.002 | AB45: 0.002 | AC45: 0.002 | AD45: 0.002 | AE45: 0.002 | AF45: 0.002 | AG45: 0.004 | AH45: 0.004 | AI45: 0.004 | AJ45: 0.004 | AK45: 0.004 | AL45: 0.004 | AM45: 0.004 | AN45: 0.004 | AO45: 0.004 | AP45: 0.004 | AQ45: 0.004 | AR45: 0.006 | AS45: 0.006 | AT45: 0.006
A46: Additional paid-in capital | B46: 147.374 | C46: 148.293 | D46: 150.337 | E46: 151.269 | F46: 152.942 | G46: 154.274 | H46: 155.853 | I46: 156.667 | J46: 157.96 | K46: 162.15 | L46: 165.359 | M46: 166.993 | N46: 168.735 | O46: 170.139 | P46: 170.789 | Q46: 171.867 | R46: 174.891 | S46: 176.216 | T46: 177.207 | U46: 178.55 | V46: 180.051 | W46: 181.481 | X46: 181.406 | Y46: 183.298 | Z46: 184.366 | AA46: 260.327 | AB46: 261.192 | AC46: 261.612 | AD46: 265.885 | AE46: 267.248 | AF46: 268.641 | AG46: 283.789 | AH46: 295.07 | AI46: 384.397 | AJ46: 386.14 | AK46: 589.047 | AL46: 593.228 | AM46: 597.646 | AN46: 598.735 | AO46: 604.225 | AP46: 609.606 | AQ46: 618.711 | AR46: 4226.01 | AS46: 4234.46 | AT46: 4244.42
A47: Accumulated other comprehensive loss | B47: -1.441 | C47: -1.358 | D47: -0.226 | E47: -0.201 | F47: -0.194 | G47: -0.201 | H47: -0.183 | I47: -0.158 | J47: -0.169 | K47: -0.127 | L47: -0.125 | M47: -0.098 | N47: -0.025 | O47: -0.021 | P47: 0.016 | Q47: 0.005 | R47: 0.004 | S47: 0.002 | T47: 0.171 | U47: 0.181 | V47: 0.069 | W47: 0.328 | X47: 0.351 | Y47: 0.342 | Z47: 0.347 | AA47: 0.343 | AB47: -0.394 | AC47: -1.677 | AD47: -3.434 | AE47: -6.514 | AF47: -7.558 | AG47: -8.48 | AH47: -5.055 | AI47: -4.452 | AJ47: -4.515 | AK47: -6.077 | AL47: -4.888 | AM47: -5.592 | AN47: -5.054 | AO47: -5.228 | AP47: -6.197 | AQ47: -6.514 | AR47: -5.875 | AS47: -6.222 | AT47: -5.514
A48: Retained earnings | B48: 194.895 | C48: 201.975 | D48: 194.994 | E48: 195.657 | F48: 201.821 | G48: 207.45 | H48: 195.808 | I48: 191.636 | J48: 189.453 | K48: 219.929 | L48: 215.486 | M48: 222.504 | N48: 221.676 | O48: 238.913 | P48: 266.243 | Q48: 272.3 | R48: 280.669 | S48: 286.351 | T48: 304.126 | U48: 311.627 | V48: 310.619 | W48: 328.09 | X48: 338.17 | Y48: 340.264 | Z48: 340.475 | AA48: 351.421 | AB48: 337.44 | AC48: 339.965 | AD48: 339.975 | AE48: 347.233 | AF48: 338.838 | AG48: 332.17 | AH48: 331.494 | AI48: 171.021 | AJ48: 192.916 | AK48: 210.756 | AL48: 224.641 | AM48: 230.687 | AN48: 251.853 | AO48: 259.396 | AP48: 257.642 | AQ48: 274.306 | AR48: 206.936 | AS48: 189.833 | AT48: -53.99
A49: Total stockholders' equity | B49: =SUM(B45,B46,B47,B48) -> 340.83 | C49: =SUM(C45,C46,C47,C48) -> 348.912 | D49: =SUM(D45,D46,D47,D48) -> 345.107 | E49: =SUM(E45,E46,E47,E48) -> 346.727 | F49: =SUM(F45,F46,F47,F48) -> 354.571 | G49: =SUM(G45,G46,G47,G48) -> 361.525 | H49: =SUM(H45,H46,H47,H48) -> 351.48 | I49: =SUM(I45,I46,I47,I48) -> 348.147 | ... AT49: =SUM(AT45,AT46,AT47,AT48) -> 4184.922
A50: Noncontrolling interest | K50: 0.239 | L50: 0.216 | M50: 0.009 | N50: 0.001 | O50: 0.023 | P50: 0.009 | Q50: 0.002 | R50: -0.017 | S50: 0.004 | T50: -0.007 | U50: -0.003 | V50: -0.023 | X50: -0.037 | Y50: -0.059 | Z50: -0.012 | AA50: 0.014 | AB50: 0.077 | AC50: 0.332 | AD50: 0.287 | AE50: 0.241 | AF50: 0.247
A51: Total equity | B51: =SUM(B49,B50) -> 340.83 | C51: =SUM(C49,C50) -> 348.912 | D51: =SUM(D49,D50) -> 345.107 | E51: =SUM(E49,E50) -> 346.727 | F51: =SUM(F49,F50) -> 354.571 | G51: =SUM(G49,G50) -> 361.525 | H51: =SUM(H49,H50) -> 351.48 | I51: =SUM(I49,I50) -> 348.147 | ... AT51: =SUM(AT49,AT50) -> 4184.922
A52: Total liabilities and stockholders' equity | B52: =SUM(B43,B51) -> 386.471 | C52: =SUM(C43,C51) -> 397.467 | D52: =SUM(D43,D51) -> 383.274 | E52: =SUM(E43,E51) -> 380.029 | F52: =SUM(F43,F51) -> 389.491 | G52: =SUM(G43,G51) -> 410.658 | H52: =SUM(H43,H51) -> 389.534 | I52: =SUM(I43,I51) -> 389.898 | ... AT52: =SUM(AT43,AT51) -> 5364.238

Sheet CF - Quarterly
A1: AeroVironment, Inc. - Cash Flow Statement
A2: USD mm
A4: Fiscal quarter end | B4: 4/30/15 | C4: 8/1/15 | D4: 10/31/15 | E4: 1/30/16 | F4: 4/30/16 | G4: 7/30/16 | H4: 10/29/16 | I4: 1/28/17 | J4: 4/30/17 | K4: 7/29/17 | L4: 10/28/17 | M4: 1/27/18 | N4: 4/30/18 | O4: 7/28/18 | P4: 10/27/18 | Q4: 1/26/19 | R4: 4/30/19 | S4: 7/27/19 | T4: 10/26/19 | U4: 1/25/20 | V4: 4/30/20 | W4: 8/1/20 | X4: 10/31/20 | Y4: 1/30/21 | Z4: 4/30/21 | AA4: 7/31/21 | AB4: 10/30/21 | AC4: 1/29/22 | AD4: 4/30/22 | AE4: 7/30/22 | AF4: 10/29/22 | AG4: 1/28/23 | AH4: 4/30/23 | AI4: 7/29/23 | AJ4: 10/28/23 | AK4: 1/27/24 | AL4: 4/30/24 | AM4: 7/27/24 | AN4: 10/26/24 | AO4: 1/25/25 | AP4: 4/30/25 | AQ4: 8/2/25 | AR4: 11/1/25 | AS4: 1/31/26
A5: Operating Activities
A6: Net income | B6: 7.08 | C6: -6.981 | D6: 4.419 | E6: 6.164 | F6: 5.364 | G6: -11.642 | H6: -4.172 | I6: -2.183 | J6: 30.454 | K6: -5.882 | L6: 7.517 | M6: -0.785 | N6: 16.797 | O6: 27.316 | P6: 6.05 | Q6: 8.35 | R6: 5.703 | S6: 17.099 | T6: 7.505 | U6: -1.028 | V6: 17.494 | W6: 10.043 | X6: 2.072 | Y6: 0.258 | Z6: 10.972 | AA6: -13.918 | AB6: 2.556 | AC6: -0.035 | AD6: 7.212 | AE6: -8.389 | AF6: -6.629 | AG6: -0.676 | AH6: -160.473 | AI6: 21.895 | AJ6: 17.84 | AK6: 13.885 | AL6: 6.046 | AM6: 21.166 | AN6: 7.543 | AO6: -1.754 | AP6: 16.664 | AQ6: -67.37 | AR6: -17.103 | AS6: -156.551
A7: Gain on sale of business, net of tax | K7: 1.488 | L7: -1.488 | O7: -8.843 | P7: 0.391 | Q7: 0
A8: Loss from discontinued operations, net of tax | L8: 1.521 | M8: 0.129 | N8: -1.65 | O8: 1.05 | P8: 1.399 | Q8: 0.062 | R8: 0.453
A9: Net income from continuing operations | K9: -4.394 | L9: 7.55 | M9: -0.656 | O9: 20.323 | P9: 7.04 | Q9: 8.412 | R9: 6.118
A10: Depreciation and amortization | B10: 1.998 | C10: 1.402 | D10: 1.363 | E10: 1.782 | F10: 1.527 | G10: 1.653 | H10: 1.748 | I10: 1.787 | J10: 1.866 | K10: 1.406 | L10: 1.378 | M10: 1.493 | N10: 1.705 | O10: 1.746 | P10: 1.838 | Q10: 1.946 | R10: 2.139 | S10: 2.079 | T10: 2.407 | U10: 2.621 | V10: 2.781 | W10: 2.779 | X10: 2.914 | Y10: 2.957 | Z10: 10.612 | AA10: 13.654 | AB10: 16.365 | AC10: 17.418 | AD10: 13.388 | AE10: 14 | AF10: 18.275 | AG10: 15.834 | AH10: 51.89 | AI10: 6.951 | AJ10: 8.436 | AK10: 9.582 | AL10: 10.78 | AM10: 8.852 | AN10: 9.002 | AO10: 9.29 | AP10: 13.854 | AQ10: 90.254 | AR10: 58.073 | AS10: 54.633
A11: Equity method investment loss (income), net | B11: 0.088 | C11: 0.065 | D11: 0.057 | E11: 0.126 | F11: -0.11 | G11: 0.072 | H11: 0.039 | I11: 0.008 | K11: 0.009 | M11: 0.418 | O11: 0.602 | P11: 0.752 | Q11: 0.717 | S11: 1.347 | T11: 0.863 | U11: 1.2 | W11: 1.288 | X11: 5.405 | Y11: 0.081 | AA11: 1.141 | AB11: -1.661 | AC11: -0.279 | AE11: 0.5 | AF11: 1.273 | AG11: 0.417 | AI11: 0.021 | AJ11: 1.393 | AK11: 0.08 | AL11: 0.18 | AM11: -0.065 | AN11: -0.5275 | AO11: 0 | AP11: -3.782 | AQ11: -1.787 | AR11: -1.4915 | AS11: 0.295
A12: Impairment of available-for-sale securities | C12: 2.186 | D12: 0 | E12: 0 | F12: 0
A13: Impairment of goodwill | AP13: 18.359
A14: Loss on deconsolidation of previously controlled subsidiary | AF14: 0.0945 | AG14: -0.001 | AH14: 0.6
A15: Amortization of debt issuance costs | Y15: 0 | Z15: 10.481 | AA15: 0.129 | AB15: 0.129 | AC15: 0.128 | AD15: 0.403 | AE15: 0.211 | AF15: 0.211 | AG15: 0.212 | AH15: 0.211 | AI15: 0.214 | AJ15: 0.21 | AK15: 0.214 | AL15: 0.351 | AM15: 0.266 | AN15: 0.781 | AO15: 0.074 | AP15: 0.074 | AQ15: 7.829 | AR15: 1.225 | AS15: 1.219
A16: Realized gain from sale of available-for-sale investments | U16: -0.002 | V16: -0.178 | W16: -0.011 | X16: 0 | Y16: 0 | Z16: 0.156
A17: Impairment of long-lived assets | G17: 0.171 | H17: -0.171 | I17: 0 | J17: 0.046 | K17: 0.209 | L17: 0.046 | M17: 0 | N17: 0
A18: Provision for credit losses | B18: -0.005 | C18: -0.147 | D18: -0.084 | E18: -0.021 | F18: 0.074 | G18: 0.226 | H18: -0.107 | I18: -0.004 | J18: -0.069 | K18: -0.106 | L18: 1.031 | M18: 0.159 | N18: 0.037 | O18: -0.048 | P18: 0.021 | Q18: -0.006 | R18: -0.006 | S18: 0.011 | T18: 0.003 | U18: -0.016 | V18: 0.39 | W18: -0.136 | X18: -0.02 | Y18: 0.011 | Z18: 0.031 | AA18: -0.02 | AB18: -0.015 | AC18: 0.015 | AD18: 0.014 | AE18: 0.023 | AF18: -0.004 | AG18: -0.014 | AH18: 0.094 | AI18: -0.015 | AJ18: 0.019 | AK18: -0.071 | AL18: 0.071 | AM18: -0.101 | AN18: 0.034 | AO18: -0.097 | AP18: 0.207 | AQ18: 0.173 | AR18: 1.805 | AS18: -0.111
A19: Foreign currency transaction loss (gain), net | C19: 0.058 | D19: 0.005 | E19: 0 | G19: -0.069 | H19: 0.338 | I19: 0.003 | J19: 0.012 | L19: -0.108 | M19: 0.072 | O19: -0.306 | P19: -0.308 | T19: -0.669 | U19: -0.277 | W19: 0.001 | X19: 0.001 | Y19: -0.001 | AA19: 0.019 | AB19: 0.011 | AE19: -0.044 | AF19: -0.0295 | AH19: -2.995 | AI19: 0.132 | AJ19: -0.092 | AK19: 0.238 | AM19: 0.142 | AN19: -0.11 | AO19: 0.2295 | AP19: 0.2295 | AQ19: 0.161 | AR19: 0.054
A20: Impairment of intangible assets and goodwill | L20: 0.5105 | M20: 0
A21: Loss on sale of equity securities | B21: 0.391 | C21: 0.145 | D21: 0.074 | E21: 0 | F21: 0
A22: Other non-cash expense (gain), net | R22: -0.421 | S22: 0.032 | T22: 0.049 | X22: -0.473 | Y22: 0 | AA22: 0.048 | AB22: 0.109 | AC22: 0.283 | AE22: 0.153 | AF22: 0.412 | AG22: 0.37 | AH22: 1.06 | AI22: 0.173 | AJ22: 0.158 | AK22: 0.452 | AL22: 0.533 | AM22: 0.616 | AN22: 0.578 | AO22: 0.616 | AP22: 0.796 | AQ22: 0.616 | AR22: 1.473 | AS22: 1.454
A23: Reserve for inventory excess and obsolescence | AE23: 0.22 | AF23: 2.639 | AG23: 0.928 | AH23: 4.349 | AI23: 3.33 | AJ23: 5.008 | AK23: 3.33 | AL23: 2.269 | AM23: 2.667 | AN23: -0.635 | AO23: -0.007 | AP23: 0.857 | AQ23: 1.178 | AR23: 1.501 | AS23: 2.446
A24: Non-cash lease expense | P24: -0.013 | Q24: 0.013 | R24: 3.878 | S24: -0.251 | T24: 2.506 | U24: 1.198 | V24: 1.121 | W24: 1.19 | X24: 1.203 | Y24: 1.202 | Z24: 1.555 | AA24: 1.677 | AB24: 1.681 | AC24: 1.675 | AD24: 1.781 | AE24: 1.59 | AF24: 2.185 | AG24: 2.091 | AH24: 2.182 | AI24: 2.184 | AJ24: 2.302 | AK24: 2.437 | AL24: 3.477 | AM24: 2.43 | AN24: 2.55 | AO24: 2.399 | AP24: 2.784 | AQ24: 6.85 | AR24: 5.805 | AS24: 6.234
A25: Unrealized loss (gain) on available-for-sale equity securities, net | AF25: -0.464 | AG25: 0.53 | AH25: 0.53 | AI25: 1.013 | AJ25: 2.45 | AL25: 1.233 | AM25: 0.321 | AN25: -0.054 | AO25: -1.454 | AP25: 1.01 | AQ25: -2.702 | AR25: -6.156 | AS25: 1.412
A26: Deferred income taxes | B26: -3.18 | C26: 0.203 | D26: 0.012 | E26: -0.197 | F26: -2.93 | G26: 0.992 | H26: -1.321 | I26: -0.369 | J26: 0.646 | K26: -0.597 | L26: -0.497 | M26: 1.268 | N26: 3.66 | P26: 1.2585 | Q26: -3.731 | R26: 6.006 | S26: -0.349 | T26: 3.333 | U26: -3.93 | V26: -1.332 | W26: 0.002 | X26: -0.623 | Y26: -0.276 | Z26: -0.797 | AA26: -0.472 | AB26: -0.368 | AC26: -0.355 | AD26: -6.087 | AE26: -0.381 | AF26: -0.427 | AG26: -0.442 | AH26: -17.411 | AI26: -0.427 | AJ26: -0.579 | AK26: -0.598 | AL26: -21.846 | AP26: -20.157 | AQ26: -0.001
A27: Change in fair value of conversion feature of convertible bonds | B27: 0
A28: Stock-based compensation | B28: 1.054 | C28: 1.039 | D28: 1.043 | E28: 1.088 | F28: 1.392 | G28: 0.022 | H28: 1.791 | I28: 0.923 | J28: 0.973 | K28: 1.326 | L28: 1.209 | M28: 1.291 | N28: 1.254 | O28: 1.287 | P28: -1.287 | Q28: 5.599 | R28: 1.386 | S28: 1.566 | T28: -1.641 | U28: 4.826 | V28: 6.298 | W28: -0.339 | X28: 3.848 | Y28: 1.245 | Z28: 2.178 | AA28: 0.09 | AB28: 2.252 | AC28: 1.615 | AD28: 4.433 | AE28: 2.217 | AF28: 2.185 | AG28: 2.706 | AH28: 3.657 | AI28: 3.204 | AJ28: 5.04 | AK28: 4.181 | AL28: 4.644 | AM28: 4.536 | AN28: 5.601 | AO28: 5.381 | AP28: 5.943 | AQ28: 11.429 | AR28: 8.566 | AS28: 8.07
A29: Tax benefit from stock-based compensation | B29: 0.22 | C29: 0.101 | D29: 0 | E29: 0.106 | F29: -0.141 | G29: -0.007 | H29: 0.029 | I29: 0
A30: Loss (gain) on disposition of property and equipment | F30: 0.032 | G30: 0.661 | H30: -0.0035 | I30: 0.044 | J30: 0 | L30: 0.0075 | M30: 0 | P30: -0.459 | Q30: 0.51 | S30: -0.075 | T30: -0.909 | U30: -0.307 | W30: 1.595 | X30: 0.001 | Y30: 0 | AA30: 1.922 | AB30: 1.114 | AC30: 2.027 | AE30: 0.485 | AF30: 0.34 | AG30: 0.368 | AH30: 0.304 | AI30: 0.116 | AJ30: 0.02 | AK30: -0.021 | AL30: 0.506 | AM30: 0.143 | AN30: 0.058 | AO30: 0.055 | AP30: 0.055 | AQ30: 0.048 | AR30: 0.546
A31: Accounts receivable | B31: 4.232 | C31: 5.549 | D31: -14.457 | E31: 3.856 | F31: -17.208 | G31: 23.019 | H31: 6.543 | I31: 2.991 | J31: -51.18 | K31: 43.819 | L31: -5.137 | M31: 9.01 | N31: -37.801 | O31: 43.189 | P31: -20.928 | Q31: 0.556 | R31: 3.004 | S31: -11.557 | T31: 2.157 | U31: 12.645 | V31: -46.114 | W31: 30.439 | X31: 12.676 | Y31: 4.069 | Z31: -30.007 | AA31: 17.914 | AB31: 19.22 | AC31: -15.233 | AD31: -18.817 | AE31: 8.053 | AF31: 19.959 | AG31: -21.165 | AH31: -34.27 | AI31: 8.207 | AJ31: 7.346 | AK31: 20.834 | AL31: -17.179 | AM31: 34.993 | AN31: -1.75 | AP31: -20.666 | AQ31: -15.693 | AR31: -25.7595
A32: Unbilled receivables and retentions | B32: -9.011 | C32: 3.358 | D32: 2.2 | E32: 1.358 | F32: -8.471 | G32: 4.406 | H32: -2.377 | I32: 2.05 | J32: 0.7 | K32: 6.234 | L32: -5.634 | M32: -12.668 | N32: 14.321 | O32: -42.998 | P32: 14.216 | Q32: -5.978 | R32: -1.415 | S32: 5.112 | T32: -14.462 | U32: -15.014 | V32: 1.574 | W32: 2.046 | X32: 3.218 | Y32: 9.489 | Z32: -6.372 | AA32: -14.684 | AB32: -31.935 | AC32: 21.022 | AD32: -6.286 | AE32: 14.754 | AF32: -3.058 | AG32: -16.794 | AH32: 3.652 | AI32: -1.603 | AJ32: -33.572 | AK32: -6.775 | AL32: -50.9 | AM32: -20.274 | AN32: -2.342 | AP32: -60.342 | AQ32: -74.51 | AR32: -62.0735
A33: Inventories | B33: 9.385 | C33: -4.507 | D33: -4.415 | E33: 1.902 | F33: 8.948 | G33: -6.619 | H33: -11.063 | I33: -13.638 | J33: 8.73 | K33: -10.224 | L33: -3.548 | M33: -1.536 | N33: 16.5 | O33: -4.819 | P33: -3.852 | Q33: -4.283 | R33: -3.677 | S33: -1.946 | T33: 3.567 | U33: -12.387 | V33: 19.621 | W33: 0.005 | X33: -6.249 | Y33: -1.325 | Z33: 2.39 | AA33: -6.058 | AB33: -4.017 | AC33: -11.515 | AD33: -7.841 | AE33: -11.927 | AF33: -12.129 | AG33: -16.416 | AH33: -18.735 | AI33: -40.004 | AJ33: -9.325 | AK33: 17.428 | AL33: 8.856 | AM33: 3.867 | AN33: 3.7425 | AP33: 4.133 | AQ33: -12.704 | AR33: -24.68
A34: Income taxes receivable | B34: 1.94 | C34: -5.569 | D34: 2.682 | E34: -1.065 | G34: -4.25 | H34: 0.293 | I34: 1.47 | J34: 2.487 | K34: -3.385 | L34: 3.078 | M34: -0.292 | N34: 0.72 | Q34: 0 | R34: -0.821 | S34: 0.821 | T34: 0 | U34: 0 | AA34: -0.326 | AB34: -10.341 | AC34: -15.541 | AD34: 25.766 | AE34: 0.442 | AF34: -8.981 | AG34: -0.849 | AH34: 9.246 | AJ34: -5.735 | AK34: -2.279 | AL34: 8.014 | AM34: -0.336 | AN34: -4.818 | AP34: 14.148 | AQ34: -16.39 | AR34: -11.115
A35: Prepaid expenses and other assets | C35: 0.71 | D35: -0.591 | E35: 0.336 | F35: 0.062 | G35: -0.017 | H35: -0.538 | I35: -0.635 | J35: -0.294 | K35: 0.358 | L35: 0.055 | M35: 0.004 | N35: -0.278 | O35: -0.133 | P35: -0.698 | Q35: -0.96 | R35: -0.61 | S35: -0.616 | T35: -0.435 | U35: 1.267 | V35: 0.615 | W35: 0.324 | X35: -1.353 | Y35: -0.593 | Z35: -4.482 | AA35: 0.481 | AB35: -0.209 | AC35: 1.517 | AD35: -6.323 | AE35: 0.046 | AF35: -1.163 | AG35: -1.997 | AH35: -0.707 | AI35: -4.401 | AJ35: -8.319 | AK35: -3.176 | AL35: -4.383 | AM35: -0.814 | AN35: -1.1235 | AP35: -11.696 | AQ35: -1.749 | AR35: -6.3735
A36: Accounts payable | B36: 3.028 | C36: -6.299 | D36: -1.354 | E36: -1.804 | F36: 6.752 | G36: -6.336 | H36: 7.749 | I36: -4.583 | J36: 6.013 | K36: -5.504 | L36: 2.532 | M36: -1.479 | N36: 10.187 | O36: -9.893 | P36: 1.052 | Q36: -1.804 | R36: 3.591 | S36: -5.11 | T36: 0.064 | U36: 3.745 | V36: 4.428 | W36: -7.338 | X36: 2.31 | Y36: 1.682 | Z36: 5.911 | AA36: -7.997 | AB36: 4.41 | AC36: -6.643 | AD36: 3.676 | AE36: 3.323 | AF36: 3.5 | AG36: 0.966 | AH36: 4.749 | AI36: -2.78 | AJ36: -3.325 | AK36: -3.898 | AL36: 22.971 | AM36: -4.976 | AN36: -3.812 | AP36: 23.69 | AQ36: -29.625 | AR36: -3.886
A37: Other liabilities | B37: -0.089 | C37: -3.766 | D37: -3.651 | E37: 2.671 | F37: 6.267 | G37: -3.594 | H37: -4.339 | I37: 3.423 | J37: 3.564 | K37: -4.306 | L37: 0.081 | M37: 4.8 | N37: 8.649 | O37: -3.797 | P37: -2.387 | Q37: 3.586 | R37: 6.441 | S37: -4.524 | T37: -0.059 | U37: 12.53 | V37: 0.233 | W37: -15.004 | X37: 4.248 | Y37: 1.238 | Z37: 15.73 | AA37: -9.283 | AB37: 18.925 | AC37: -15.449 | AD37: 4.311 | AE37: -9.519 | AF37: 0.855 | AG37: 8.507 | AH37: -2.478 | AI37: -15.272 | AJ37: 2.421 | AK37: -2.47 | AL37: 12.489 | AM37: -25.081 | AN37: -10.208 | AP37: 13.337 | AQ37: -19.734 | AR37: -1.053
A38: Amortization of debt securities | B38: 1.144 | C38: 1.149 | D38: 0.997 | E38: 0.94 | F38: 0.789 | H38: 0.6295 | I38: 0.568 | J38: 0.655 | K38: 0.474 | L38: 0.423 | M38: 0.353 | N38: 0.174 | O38: -0.115 | P38: 0.115 | Q38: -0.941 | R38: -0.565 | S38: -0.527 | T38: 0.527 | U38: 0 | V38: -1.423 | W38: -0.043 | X38: 0.031 | Y38: 0.155 | Z38: 0.166 | AA38: 0.379 | AB38: -0.266 | AC38: 0.004 | AD38: 0.125 | AE38: 0.13 | AF38: -0.005 | AG38: 0 | AR38: -0.1005 | AS38: -0.46
A39: Other operating activities / source adjustment | B39: 3.922 | D39: 0.095 | F39: 3.903 | G39: 0.069 | H39: -0.104 | J39: -0.678 | K39: 4.394 | L39: -5.852 | M39: 0.257 | N39: 3.725 | O39: -19.525 | P39: -6.5795 | Q39: -7.808 | R39: -11.155 | U39: 0.076 | V39: 4.523 | X39: 2.543 | Y39: 0.177 | Z39: -10.954 | AB39: -6 | AC39: -0.486 | AD39: -2.197 | AF39: -2.994 | AG39: 2.294 | AH39: 157.144 | AJ39: -0.224 | AK39: -0.818 | AL39: 0.215 | AN39: -8.1515 | AO39: -40.4955 | AP39: 0.2385 | AR39: 35.6595 | AS39: 76.252
A40: Net cash provided by operating activities | B40: =SUM(B6,B7,B8,B9,B10,B11,B12,B13,B14,B15,B16,B17,B18,B19,B20,B21,B22,B23,B24,B25,B26,B27,B28,B29,B30,B31,B32,B33,B34,B35,B36,B37,B38,B39) -> 22.197 | C40: =SUM(C6,C7,C8,C9,C10,C11,C12,C13,C14,C15,C16,C17,C18,C19,C20,C21,C22,C23,C24,C25,C26,C27,C28,C29,C30,C31,C32,C33,C34,C35,C36,C37,C38,C39) -> -11.304 | D40: =SUM(D6,D7,D8,D9,D10,D11,D12,D13,D14,D15,D16,D17,D18,D19,D20,D21,D22,D23,D24,D25,D26,D27,D28,D29,D30,D31,D32,D33,D34,D35,D36,D37,D38,D39) -> -11.605 | E40: =SUM(E6,E7,E8,E9,E10,E11,E12,E13,E14,E15,E16,E17,E18,E19,E20,E21,E22,E23,E24,E25,E26,E27,E28,E29,E30,E31,E32,E33,E34,E35,E36,E37,E38,E39) -> 17.242 | F40: =SUM(F6,F7,F8,F9,F10,F11,F12,F13,F14,F15,F16,F17,F18,F19,F20,F21,F22,F23,F24,F25,F26,F27,F28,F29,F30,F31,F32,F33,F34,F35,F36,F37,F38,F39) -> 6.25 | G40: =SUM(G6,G7,G8,G9,G10,G11,G12,G13,G14,G15,G16,G17,G18,G19,G20,G21,G22,G23,G24,G25,G26,G27,G28,G29,G30,G31,G32,G33,G34,G35,G36,G37,G38,G39) -> -1.243 | H40: =SUM(H6,H7,H8,H9,H10,H11,H12,H13,H14,H15,H16,H17,H18,H19,H20,H21,H22,H23,H24,H25,H26,H27,H28,H29,H30,H31,H32,H33,H34,H35,H36,H37,H38,H39) -> -5.036 | I40: =SUM(I6,I7,I8,I9,I10,I11,I12,I13,I14,I15,I16,I17,I18,I19,I20,I21,I22,I23,I24,I25,I26,I27,I28,I29,I30,I31,I32,I33,I34,I35,I36,I37,I38,I39) -> -8.145 | ... AS40: =SUM(AS6,AS7,AS8,AS9,AS10,AS11,AS12,AS13,AS14,AS15,AS16,AS17,AS18,AS19,AS20,AS21,AS22,AS23,AS24,AS25,AS26,AS27,AS28,AS29,AS30,AS31,AS32,AS33,AS34,AS35,AS36,AS37,AS38,AS39) -> -5.107
A41: Investing Activities
A42: Acquisition of property and equipment | B42: -2.953 | C42: -0.906 | D42: -1.898 | E42: -1.455 | F42: -2.57 | G42: -2.634 | H42: -1.88 | I42: -3.072 | J42: -2.276 | K42: -2.705 | L42: -2.75 | M42: -2.258 | N42: -1.85 | O42: -1.423 | P42: -2.712 | Q42: -2.671 | R42: -2.09 | S42: -1.902 | T42: -4.948 | U42: -1.654 | V42: -2.716 | W42: -4.067 | X42: -1.985 | Y42: -2.42 | Z42: -2.791 | AA42: -5.428 | AB42: -7.719 | AC42: -3.917 | AD42: -5.225 | AE42: -5.393 | AF42: -2.194 | AG42: -2.529 | AH42: -4.752 | AI42: -3.632 | AJ42: -6.472 | AK42: -3.797 | AL42: -9.082 | AM42: -5.43 | AN42: -5.017 | AO42: -3.845 | AP42: -8.524 | AQ42: -22.728 | AR42: -10.809 | AS42: -12.597
A43: Contributions in equity method investments | B43: -0.11 | C43: -0.085 | D43: -0.101 | E43: -0.109 | F43: 0 | N43: -1.407 | Q43: 0 | R43: -7.598 | S43: -4.569 | T43: 0 | U43: -4.982 | V43: -4.947 | W43: -1.173 | X43: 0 | Y43: -0.977 | Z43: -0.525 | AA43: -2.692 | AB43: -3.553 | AC43: -0.639 | AD43: 0 | AE43: -2.774 | AF43: 0 | AG43: 0 | AH43: -3.004 | AJ43: -1.875 | AK43: 0 | AL43: -1.199 | AM43: -1.183 | AN43: 0 | AO43: -1.126 | AP43: -3.365 | AR43: -2.123 | AS43: -1.12
A44: Equity security investments | AF44: -2.55 | AG44: 0 | AH44: 0
A45: Purchase of available-for-sale investments | S45: -2.693 | T45: 2.693 | U45: -59.297 | V45: -47.31 | W45: -69.961 | X45: -46.984 | Y45: -8.699 | Z45: 0 | AC45: -2.987 | AD45: -20.895 | AE45: -1.326 | AF45: 0 | AG45: 0 | AH45: 0 | AR45: -132.108 | AS45: -70.968
A46: Other | AB46: 0.112 | AC46: 0.001 | AD46: -0.001
A47: Acquisition of capitalized software to be sold | AQ47: -9.34 | AR47: -3.926 | AS47: -4.009
A48: Business acquisitions, net of cash acquired | S48: -18.641 | T48: 0 | U48: 0 | V48: 0 | Y48: 0 | Z48: -385.614 | AA48: -46.15 | AB48: 0 | AC48: 0 | AD48: 0 | AF48: -2.5525 | AG48: 0 | AH48: 0 | AJ48: -12.078 | AK48: 0 | AL48: -0.001 | AQ48: -844.58 | AR48: 0 | AS48: -0.006
A49: Proceeds from sale of business | O49: 31.994 | P49: 0 | Q49: 0 | R49: 0
A50: Acquisition of intangible assets | B50: 0 | AJ50: -0.75 | AK50: 0 | AL50: 0
A51: Proceeds from sale of property and equipment | G51: 0.007 | H51: 0 | I51: 0 | Q51: 0 | R51: 260.918 | S51: 0.081 | T51: 0 | U51: 0 | V51: 0
A52: Redemptions of held-to-maturity investments | B52: 7.28 | C52: 37.507 | D52: 18.34 | E52: 11.555 | F52: 17.031 | G52: 28.82 | H52: 25.141 | I52: 39.247 | J52: 28.314 | K52: 59.28 | L52: 46.478 | M52: 58.055 | N52: 63.85 | O52: 78.909 | P52: 74.12 | Q52: 38.426 | R52: 69.463 | S52: 65.035 | T52: 94.804 | U52: 7.078 | V52: 19
A53: Purchases of held-to-maturity investments | B53: -9.39 | C53: -22.97 | D53: -20.102 | E53: -32.668 | F53: -19.214 | G53: -27.487 | H53: -51.565 | I53: -43.926 | J53: -26.013 | K53: -41.806 | L53: -46.957 | M53: -62.977 | N53: -69.94 | O53: -81.646 | P53: -87.756 | Q53: -41.718 | R53: -56.002 | S53: -70.463 | T53: -98.685 | U53: 6.631 | V53: -14.24
A54: Proceeds from deconsolidation, net of cash deconsolidated | AF54: -0.3175 | AG54: 0 | AH54: 0
A55: Redemption of available-for-sale investments | B55: 0.583 | C55: 0.217 | D55: 0.77 | E55: 0 | F55: 0 | G55: 0.4 | H55: 0 | I55: 0 | J55: 0 | K55: 0.45 | L55: 0 | M55: 0 | N55: 0 | O55: 2.25 | P55: 0 | Q55: 0 | R55: -2.25 | T55: -4.947 | U55: 46.097 | V55: 159.742 | W55: 41.727 | X55: 50.499 | Y55: 37.84 | Z55: -255.71 | AA55: 17.925 | AB55: 12.606 | AC55: 5.32 | AD55: 0 | AE55: 19.28 | AF55: 6.665 | AG55: 0 | AH55: 0.114
A56: Other investing activities / source adjustment | F56: 0.08 | J56: 0.408 | L56: -0.314 | M56: -1.86 | R56: -258.668 | Z56: 272.069 | AB56: 0.112 | AD56: 10.842 | AF56: -5.42 | AH56: -0.25 | AJ56: -12.828 | AR56: -132.107 | AS56: 21.5
A57: Net cash provided by investing activities | B57: =SUM(B42,B43,B44,B45,B46,B47,B48,B49,B50,B51,B52,B53,B54,B55,B56) -> -4.59 | C57: =SUM(C42,C43,C44,C45,C46,C47,C48,C49,C50,C51,C52,C53,C54,C55,C56) -> 13.763 | D57: =SUM(D42,D43,D44,D45,D46,D47,D48,D49,D50,D51,D52,D53,D54,D55,D56) -> -2.991 | E57: =SUM(E42,E43,E44,E45,E46,E47,E48,E49,E50,E51,E52,E53,E54,E55,E56) -> -22.677 | F57: =SUM(F42,F43,F44,F45,F46,F47,F48,F49,F50,F51,F52,F53,F54,F55,F56) -> -4.673 | G57: =SUM(G42,G43,G44,G45,G46,G47,G48,G49,G50,G51,G52,G53,G54,G55,G56) -> -0.894 | H57: =SUM(H42,H43,H44,H45,H46,H47,H48,H49,H50,H51,H52,H53,H54,H55,H56) -> -28.304 | I57: =SUM(I42,I43,I44,I45,I46,I47,I48,I49,I50,I51,I52,I53,I54,I55,I56) -> -7.751 | ... AS57: =SUM(AS42,AS43,AS44,AS45,AS46,AS47,AS48,AS49,AS50,AS51,AS52,AS53,AS54,AS55,AS56) -> -67.2
A58: Financing Activities
A59: Purchase and retirement of common stock | D59: -1.878 | E59: 0 | F59: 0
A60: Principal payments of capital lease obligations | D60: -0.029 | E60: -0.312 | F60: -0.131 | G60: -0.095 | H60: -0.097 | I60: -0.099 | J60: -0.099 | K60: -0.092 | L60: -0.081 | M60: -0.058 | N60: -0.057 | O60: -0.057 | P60: -0.054 | Q60: -0.043 | R60: -0.007
A61: Excess tax benefit from stock-based compensation | B61: -0.181 | C61: 0.095
A62: Principal payments of term loan | AA62: -2.5 | AB62: -2.5 | AC62: -2.5 | AD62: -2.5 | AE62: -2.5 | AF62: -20 | AG62: 0 | AH62: -32.5 | AI62: -5 | AJ62: -50 | AK62: -40 | AL62: -12 | AM62: -10.5 | AN62: -17.5 | AO62: 0 | AP62: 0 | AQ62: -700 | AR62: 0 | AS62: 0
A63: Proceeds from long-term debt | AN63: 15 | AO63: -15 | AQ63: 693.202 | AR63: 0 | AS63: 0
A64: Principal payments of revolver | AO64: 0 | AP64: -10 | AQ64: -265 | AR64: 0 | AS64: 0
A65: Holdback and retention payments for business acquisition | Y65: -1.492 | Z65: 0 | AA65: -5.991 | AB65: 0 | AC65: 0 | AD65: -1.823 | AJ65: -0.15 | AK65: -0.2 | AL65: 0 | AP65: 0
A66: Payment of contingent consideration | AL66: -0.02
A67: Proceeds from revolver, net of creditor costs | AO67: 25 | AP67: 15 | AQ67: 233.939 | AR67: 0 | AS67: 0
A68: Proceeds from shares issued, net of underwriter costs | AF68: 5.889 | AG68: 8.326 | AH68: 84.545 | AJ68: 44.2185 | AK68: 0 | AL68: 0 | AQ68: 968.515 | AR68: 0 | AS68: 0
A69: Proceeds from convertible debt, net of underwriter costs | AQ69: 726.944 | AR69: 0 | AS69: 0
A70: Payment of debt issuance costs | AG70: -0.853 | AH70: 0.853 | AI70: -0.009 | AJ70: 0.001 | AK70: -0.029 | AL70: 0 | AN70: -0.9 | AO70: -0.156 | AP70: -0.095 | AQ70: -2.445 | AR70: 0 | AS70: 0
A71: Payment of equity issuance costs | AO71: -0.365 | AP71: -2.531 | AQ71: -1.388 | AR71: 0 | AS71: 0
A72: Tax withholding payment related to net settlement of equity awards | B72: 0 | C72: -0.029 | D72: 0.029 | E72: -0.029 | F72: 0 | I72: 0 | J72: -0.005 | K72: -0.212 | L72: -0.101 | M72: -0.076 | N72: -0.008 | O72: -0.819 | P72: -0.156 | Q72: -0.058 | R72: -0.061 | S72: -0.668 | T72: -0.075 | U72: -0.266 | V72: 1.009 | W72: -1.756 | X72: -0.022 | Y72: -0.177 | Z72: -0.037 | AA72: -1.176 | AB72: 0 | AC72: 0 | AD72: -0.069 | AE72: -0.824 | AF72: -0.029 | AG72: 0 | AH72: -1.933 | AI72: -1.298 | AJ72: -0.072 | AK72: 0 | AL72: -0.226 | AM72: -3.953 | AN72: -0.111 | AO72: 0 | AP72: -0.083 | AQ72: -10.786 | AR72: -0.114 | AS72: 0
A73: Employee stock purchase plan contributions | AO73: 0 | AP73: 1.91 | AQ73: 2.467 | AR73: 0 | AS73: 1.888
A74: Exercise of stock options | B74: 0.007 | C74: 0.515 | D74: 0.029 | E74: 0.482 | F74: 0.096 | G74: 0.258 | H74: 0 | I74: 0.397 | J74: 3.21 | K74: 1.64 | L74: 0.524 | M74: 0.527 | N74: 0.014 | O74: 0.067 | P74: 0.004 | Q74: 0 | R74: 0 | S74: 0.093 | T74: 0 | U74: 0 | V74: 0.007 | W74: 0.086 | X74: 0 | Y74: 0 | Z74: 1.436 | AA74: 0.119 | AB74: 0 | AC74: 2.657 | AD74: 0 | AF74: 0.341 | AG74: 0.186 | AH74: 2.299 | AM74: 0.506 | AN74: 0 | AO74: 0 | AP74: 1.335
A75: Other | AA75: -0.008 | AB75: -0.008 | AC75: -0.007 | AD75: -0.008 | AE75: -0.007 | AF75: -0.007 | AG75: -0.007 | AH75: -0.099 | AI75: -0.008 | AJ75: -0.007 | AK75: -0.004 | AL75: -0.005 | AM75: -0.007 | AN75: -0.006 | AO75: -0.006 | AP75: -0.004 | AQ75: -0.005 | AR75: -0.004 | AS75: -0.003
A76: Other financing activities / source adjustment | D76: -1.973 | V76: -1.93 | Z76: 196.122 | AD76: -0.293 | AF76: 6.23 | AG76: 0.853 | AH76: 0.071 | AJ76: 43.8685 | AK76: -1.932 | AO76: -0.39
A77: Net cash provided by financing activities | B77: =SUM(B59,B60,B61,B62,B63,B64,B65,B66,B67,B68,B69,B70,B71,B72,B73,B74,B75,B76) -> -0.174 | C77: =SUM(C59,C60,C61,C62,C63,C64,C65,C66,C67,C68,C69,C70,C71,C72,C73,C74,C75,C76) -> 0.581 | D77: =SUM(D59,D60,D61,D62,D63,D64,D65,D66,D67,D68,D69,D70,D71,D72,D73,D74,D75,D76) -> -3.822 | E77: =SUM(E59,E60,E61,E62,E63,E64,E65,E66,E67,E68,E69,E70,E71,E72,E73,E74,E75,E76) -> 0.141 | F77: =SUM(F59,F60,F61,F62,F63,F64,F65,F66,F67,F68,F69,F70,F71,F72,F73,F74,F75,F76) -> -0.035 | G77: =SUM(G59,G60,G61,G62,G63,G64,G65,G66,G67,G68,G69,G70,G71,G72,G73,G74,G75,G76) -> 0.163 | H77: =SUM(H59,H60,H61,H62,H63,H64,H65,H66,H67,H68,H69,H70,H71,H72,H73,H74,H75,H76) -> -0.097 | I77: =SUM(I59,I60,I61,I62,I63,I64,I65,I66,I67,I68,I69,I70,I71,I72,I73,I74,I75,I76) -> 0.298 | ... AS77: =SUM(AS59,AS60,AS61,AS62,AS63,AS64,AS65,AS66,AS67,AS68,AS69,AS70,AS71,AS72,AS73,AS74,AS75,AS76) -> 1.885
A78: Discontinued Operations and FX
A79: Operating activities of discontinued operations | K79: -4.037 | L79: -1.838 | M79: 2.159 | P79: -7.188 | Q79: -0.062 | R79: -0.436
A80: Investing activities of discontinued operations | K80: -0.268 | L80: -0.314 | M80: -0.155 | N80: -0.482 | P80: -0.452 | Q80: 0 | R80: 0.021
A81: Discontinued operations / source adjustment | O81: -7.04 | P81: 7.04
A82: Net cash provided by discontinued operations | B82: =SUM(B79,B80,B81) -> 0 | C82: =SUM(C79,C80,C81) -> 0 | D82: =SUM(D79,D80,D81) -> 0 | E82: =SUM(E79,E80,E81) -> 0 | F82: =SUM(F79,F80,F81) -> 0 | G82: =SUM(G79,G80,G81) -> 0 | H82: =SUM(H79,H80,H81) -> 0 | I82: =SUM(I79,I80,I81) -> 0 | ... AS82: =SUM(AS79,AS80,AS81) -> 0
A83: Effects of currency translation on cash and cash equivalents | AA83: -0.111 | AB83: -0.164 | AC83: -0.338 | AD83: -0.706 | AE83: -0.391 | AF83: 0.134 | AG83: 0.952 | AH83: -0.298 | AI83: 0.021 | AJ83: -0.291 | AK83: 0.193 | AL83: -0.207 | AM83: 0.077 | AN83: -0.026 | AO83: -0.309 | AP83: 0.483 | AQ83: -0.128 | AR83: -0.094 | AS83: 0.866
A84: Net change in cash / source adjustment | AE84: -6 | AF84: 6
A85: Net change in cash, cash equivalents and restricted cash | B85: =SUM(B40,B57,B77,B82,B83,B84) -> 17.433 | C85: =SUM(C40,C57,C77,C82,C83,C84) -> 3.04 | D85: =SUM(D40,D57,D77,D82,D83,D84) -> -18.418 | E85: =SUM(E40,E57,E77,E82,E83,E84) -> -5.294 | F85: =SUM(F40,F57,F77,F82,F83,F84) -> 1.542 | G85: =SUM(G40,G57,G77,G82,G83,G84) -> -1.974 | H85: =SUM(H40,H57,H77,H82,H83,H84) -> -33.437 | I85: =SUM(I40,I57,I77,I82,I83,I84) -> -15.598 | ... AS85: =SUM(AS40,AS57,AS77,AS82,AS83,AS84) -> -69.556
A86: Cash, cash equivalents and restricted cash at beginning of period | K86: 79.904 | M86: 143.517 | O86: 143.517 | P86: 143.517 | Q86: 172.708 | R86: 149.369 | S86: 172.708 | T86: 172.708 | U86: 135.742 | V86: 136.496 | W86: 255.142 | X86: 255.142 | Y86: 157.063 | Z86: 324.543 | AA86: 157.063 | AB86: 157.063 | AC86: 77.231 | AD86: 84.351 | AE86: 77.231 | AF86: 77.231 | AG86: 101.417 | AH86: 85.214
A87: Ending cash / source adjustment | J87: 72.44 | L87: 144.195 | N87: 115.397 | P87: 27.271 | Q87: -21.453 | T87: -30.614 | X87: -8.303 | Y87: 123.036 | AB87: -61.316 | AC87: 29.362 | AF87: 15.952
A88: Cash, cash equivalents and restricted cash at end of period | B88: =IF(COUNTA(B86,B85,B87)=0,"",SUM(B86,B85,B87)) -> 17.433 | C88: =IF(COUNTA(C86,C85,C87)=0,"",SUM(C86,C85,C87)) -> 3.04 | D88: =IF(COUNTA(D86,D85,D87)=0,"",SUM(D86,D85,D87)) -> -18.418 | E88: =IF(COUNTA(E86,E85,E87)=0,"",SUM(E86,E85,E87)) -> -5.294 | F88: =IF(COUNTA(F86,F85,F87)=0,"",SUM(F86,F85,F87)) -> 1.542 | G88: =IF(COUNTA(G86,G85,G87)=0,"",SUM(G86,G85,G87)) -> -1.974 | H88: =IF(COUNTA(H86,H85,H87)=0,"",SUM(H86,H85,H87)) -> -33.437 | I88: =IF(COUNTA(I86,I85,I87)=0,"",SUM(I86,I85,I87)) -> -15.598 | ... AS88: =IF(COUNTA(AS86,AS85,AS87)=0,"",SUM(AS86,AS85,AS87)) -> -69.556

Sheet Ratios - Quarterly
A1: AeroVironment, Inc. - Ratios
A2: USD mm for market value rows; ratios and percentages as shown
A4: Fiscal quarter end | B4: 1/31/15 | C4: 4/30/15 | D4: 8/1/15 | E4: 10/31/15 | F4: 1/30/16 | G4: 4/30/16 | H4: 7/30/16 | I4: 10/29/16 | J4: 1/28/17 | K4: 4/30/17 | L4: 7/29/17 | M4: 10/28/17 | N4: 1/27/18 | O4: 4/30/18 | P4: 7/28/18 | Q4: 10/27/18 | R4: 1/26/19 | S4: 4/30/19 | T4: 7/27/19 | U4: 10/26/19 | V4: 1/25/20 | W4: 4/30/20 | X4: 8/1/20 | Y4: 10/31/20 | Z4: 1/30/21 | AA4: 4/30/21 | AB4: 7/31/21 | AC4: 10/30/21 | AD4: 1/29/22 | AE4: 4/30/22 | AF4: 7/30/22 | AG4: 10/29/22 | AH4: 1/28/23 | AI4: 4/30/23 | AJ4: 7/29/23 | AK4: 10/28/23 | AL4: 1/27/24 | AM4: 4/30/24 | AN4: 7/27/24 | AO4: 10/26/24 | AP4: 1/25/25 | AQ4: 4/30/25 | AR4: 8/2/25 | AS4: 11/1/25 | AT4: 1/31/26 | AU4: TTM
A5: Valuation and Operating Ratios
A6: Market Cap | B6: 597.037 | C6: 596.855 | D6: 613.209 | E6: 537.962 | F6: 595.888 | G6: 674.635 | H6: 663.249 | I6: 553.681 | J6: 608.932 | K6: 675.121 | L6: 899.971 | M6: 1226.2 | N6: 1271.08 | O6: 1303.03 | P6: 1724.63 | Q6: 2152.36 | R6: 1883.48 | S6: 1641.76 | T6: 1300.76 | U6: 1362.43 | V6: 1629.99 | W6: 1450.07 | X6: 1845.2 | Y6: 1840.58 | Z6: 2766.27 | AA6: 2734.67 | AB6: 2508.47 | AC6: 2210.45 | AD6: 1339.93 | AE6: 2004.09 | AF6: 2165.18 | AG6: 2267.71 | AH6: 2238.39 | AI6: 2639.78 | AJ6: 2498.54 | AK6: 3205.48 | AL6: 3435.5 | AM6: 4495.6 | AN6: 4902.85 | AO6: 6230.54 | AP6: 5089.66 | AQ6: 4283.09 | AR6: 12985.9 | AS6: 18470.4 | AT6: 13901.3 | AU6: 6950.4213
A7: Enterprise Value | B7: 393.479 | C7: 368.064 | D7: 395.741 | E7: 331.963 | F7: 375.88 | G7: 447.393 | H7: 439.491 | I7: 346.873 | J7: 414.777 | K7: 475.646 | L7: 674.987 | M7: 998.4 | N7: 1049.25 | O7: 1045.88 | P7: 1435.55 | Q7: 1862.57 | R7: 1589.28 | S7: 1318.57 | T7: 1010.4 | U7: 1079.18 | V7: 1359.61 | W7: 1157.64 | X7: 1541.82 | Y7: 1506.74 | Z7: 2406.04 | AA7: 2776.74 | AB7: 2621.61 | AC7: 2320.57 | AD7: 1470.95 | AE7: 2118.96 | AF7: 2272.47 | AG7: 2359.52 | AH7: 2356.3 | AI7: 2669.74 | AJ7: 2548.93 | AK7: 3215.8 | AL7: 3397.51 | AM7: 4481.98 | AN7: 4868.99 | AO7: 6211.86 | AP7: 5101.84 | AQ7: 4306.52 | AR7: 13129.8 | AS7: 18707.9 | AT7: 14140.2 | AU7: 7189.2973
A8: Last Close Price | B8: 25.59 | C8: 25.6 | D8: 26.06 | E8: 23.07 | F8: 25.51 | G8: 28.88 | H8: 28.35 | I8: 23.69 | J8: 25.96 | K8: 28.57 | L8: 37.75 | M8: 51.38 | N8: 53.17 | O8: 54.5 | P8: 72.09 | Q8: 89.95 | R8: 78.7 | S8: 68.56 | T8: 54.22 | U8: 56.79 | V8: 67.93 | W8: 60.26 | X8: 76.55 | Y8: 76.36 | Z8: 114.77 | AA8: 110.37 | AB8: 101.1 | AC8: 89.11 | AD8: 53.78 | AE8: 80.32 | AF8: 86.64 | AG8: 90.14 | AH8: 88.6 | AI8: 100.69 | AJ8: 95.03 | AK8: 113.93 | AL8: 122.1 | AM8: 159.79 | AN8: 173.82 | AO8: 220.9 | AP8: 180.36 | AQ8: 151.52 | AR8: 260.07 | AS8: 369.91 | AT8: 278.39 | AU8: 137.95
A9: PE Ratio | C9: 196.923 | E9: 76.9 | F9: 54.2766 | G9: 74.0513 | H9: 157.5 | K9: 51.0179 | L9: 54.7101 | M9: 43.1765 | N9: 42.536 | O9: 59.8901 | P9: 33.8451 | Q9: 43.665 | R9: 32.2541 | S9: 34.802 | T9: 34.9806 | U9: 35.2733 | V9: 55.6803 | W9: 35.2398 | X9: 54.2908 | Y9: 64.1681 | Z9: 92.5565 | AA9: 114.969 | AF9: 1732.8 | AM9: 73.2982 | AN9: 81.6056 | AO9: 126.954 | AP9: 152.847 | AQ9: 97.7548
A10: PS Ratio | C10: 2.30092 | E10: 2.01749 | F10: 2.24176 | G10: 2.88629 | H10: 2.61878 | I10: 2.32005 | J10: 2.71537 | K10: 2.89621 | L10: 3.42174 | M10: 4.3997 | N10: 4.53682 | O10: 4.85436 | P10: 5.52579 | Q10: 6.7412 | R10: 5.5401 | S10: 5.22397 | T10: 4.02536 | U10: 4.08605 | V10: 5.09366 | W10: 3.94797 | X10: 5.01639 | Y10: 4.87921 | Z10: 7.01884 | AA10: 6.92476 | AB10: 6.14113 | AC10: 5.04883 | AD10: 2.98343 | AE10: 4.49617 | AF10: 4.77714 | AG10: 5.12112 | AH10: 4.59518 | AI10: 4.88363 | AJ10: 4.27564 | AK10: 4.90436 | AL10: 4.86764 | AM10: 6.27247 | AN10: 6.5037 | AO10: 8.18195 | AP10: 6.85424 | AQ10: 5.21929 | AR10: 11.9595 | AS10: 13.4833 | AT10: 8.63287 | AU10: 4.31628
A11: PB Ratio | B11: 1.75172 | C11: 1.71062 | D11: 1.77687 | E11: 1.55154 | F11: 1.68059 | G11: 1.86608 | H11: 1.88702 | I11: 1.59037 | J11: 1.75361 | K11: 1.76755 | L11: 2.36385 | M11: 3.14894 | N11: 3.25595 | O11: 3.18563 | P11: 3.94608 | Q11: 4.84575 | R11: 4.13438 | S11: 3.5492 | T11: 2.70145 | U11: 2.77842 | V11: 3.32148 | W11: 2.84384 | X11: 3.54895 | Y11: 3.51319 | Z11: 5.26717 | AA11: 4.46774 | AB11: 4.19309 | AC11: 3.68468 | AD11: 2.22422 | AE11: 3.29636 | AF11: 3.6091 | AG11: 3.73296 | AH11: 3.60152 | AI11: 4.79115 | AJ11: 4.34873 | AK11: 4.0385 | AL11: 4.22578 | AM11: 5.46415 | AN11: 5.7985 | AO11: 7.25834 | AP11: 5.91096 | AQ11: 4.83143 | AR11: 2.93329 | AS11: 4.18064 | AT11: 3.32177 | AU11: 1.60525
A12: P/TBV Ratio | B12: 1.735 | C12: 1.698 | D12: 1.733 | E12: 1.54 | F12: 1.661 | G12: 1.849 | H12: 1.852 | I12: 1.568 | J12: 1.726 | K12: 1.748 | L12: 2.314 | M12: 3.145 | N12: 3.203 | O12: 3.187 | P12: 3.96 | Q12: 4.88 | R12: 4.16 | S12: 3.575 | T12: 2.858 | U12: 2.93 | V12: 3.443 | W12: 2.968 | X12: 3.698 | Y12: 3.656 | Z12: 5.489 | AA12: 14.273 | AB12: 17.124 | AC12: 14.457 | AD12: 8.187 | AE12: 11.354 | AF12: 12.272 | AG12: 12.208 | AH12: 10.997 | AI12: 7.847 | AJ12: 7.043 | AK12: 7.042 | AL12: 7.441 | AM12: 9.454 | AN12: 9.791 | AO12: 11.96 | AP12: 9.576 | AQ12: 7.371 | AR12: 15.862 | AS12: 22.359 | AT12: 15.617 | AU12: 6.792
A13: P/FCF Ratio | C13: 17.4856 | F13: 64.1705 | H13: 322.749 | I13: 64.0687 | L13: 146.814 | M13: 81.9051 | N13: 49.328 | O13: 21.6202 | P13: 41.7911 | Q13: 62.8389 | R13: 51.9711 | S13: 90.9561 | T13: 83.1264 | U13: 66.1469 | V13: 66.4731 | W13: 104.495 | X13: 52.0656 | Y13: 28.1654 | Z13: 35.5538 | AA13: 36.332 | AB13: 78.9747 | AC13: 354.409 | AG13: 253.971 | AH13: 318.95 | AL13: 314.865 | AN13: 136.478 | AO13: 147.416
A14: P/OCF Ratio | C14: 15.1436 | F14: 36.1188 | G14: 111.565 | H14: 62.4999 | I14: 32.2264 | L14: 56.0276 | M14: 47.5751 | N14: 35.5478 | O14: 18.6594 | P14: 34.8066 | Q14: 50.6497 | R14: 41.9512 | S14: 60.9277 | T14: 51.9827 | U14: 42.3009 | V14: 46.4186 | W14: 57.7788 | X14: 37.7922 | Y14: 24.2914 | Z14: 31.0841 | AA14: 31.603 | AB14: 56.5137 | AC14: 89.8739 | AF14: 100.365 | AG14: 88.3821 | AH14: 100.111 | AI14: 231.56 | AL14: 116.205 | AM14: 293.984 | AN14: 80.7652 | AO14: 94.9907
A15: EV/Revenue | C15: 1.41892 | E15: 1.24494 | F15: 1.41408 | G15: 1.91408 | H15: 1.73529 | I15: 1.45348 | J15: 1.84959 | K15: 2.04048 | L15: 2.56634 | M15: 3.58233 | N15: 3.74502 | O15: 3.89638 | P15: 4.59956 | Q15: 5.83358 | R15: 4.67473 | S15: 4.1956 | T15: 3.12679 | U15: 3.23656 | V15: 4.24873 | W15: 3.15179 | X15: 4.1916 | Y15: 3.99422 | Z15: 6.10484 | AA15: 7.03129 | AB15: 6.4181 | AC15: 5.30036 | AD15: 3.27515 | AE15: 4.75388 | AF15: 5.01386 | AG15: 5.32845 | AH15: 4.83724 | AI15: 4.93906 | AJ15: 4.36187 | AK15: 4.92014 | AL15: 4.81382 | AM15: 6.25346 | AN15: 6.45878 | AO15: 8.15742 | AP15: 6.87065 | AQ15: 5.24784 | AR15: 12.0921 | AS15: 13.6567 | AT15: 8.78122 | AU15: 4.46463
A16: EV/EBITDA | C16: 35.4589 | E16: 31.7486 | F16: 22.2177 | G16: 13.2911 | H16: 46.0489 | K16: 109.9 | L16: 754.176 | M16: 199.202 | N16: 23.3249 | O16: 28.7267 | P16: 24.2997 | Q16: 33.4693 | R16: 24.9163 | S16: 31.7765 | T16: 37.5654 | U16: 30.3832 | V16: 38.7507 | W16: 13.9705 | X16: 51.6868 | Y16: 41.6433 | Z16: 41.2849 | AA16: 34.5645 | AB16: 39.2456 | AC16: 33.2975 | AD16: 20.8146 | AE16: 41.5987 | AF16: 37.7971 | AG16: 53.1663 | AH16: 38.2958 | AM16: 41.6645 | AN16: 45.862 | AO16: 70.1429 | AP16: 72.0121 | AQ16: 52.6515 | AR16: 185.282 | AS16: 226.2 | AU16: 47.55927
A17: EV/EBIT | C17: 182.753 | E17: 31.7486 | F17: 36.2363 | G17: 15.0102 | H17: 136.53 | N17: 27.0139 | O17: 34.3747 | P17: 27.2117 | Q17: 38.1143 | R17: 28.104 | S17: 38.9809 | T17: 53.4742 | U17: 40.0468 | V17: 52.6163 | W17: 15.8635 | X17: 80.1277 | Y17: 60.0605 | Z17: 51.3585 | AA17: 45.4659 | AB17: 71.5056 | AC17: 88.8972 | AD17: 116.557 | AH17: 73634.5 | AM17: 62.4022 | AN17: 71.0636 | AO17: 123.388 | AP17: 154.963 | AQ17: 105.565
A18: EV/FCF | C18: 10.7829 | F18: 40.4781 | H18: 213.864 | I18: 40.1381 | L18: 110.112 | M18: 66.6889 | N18: 40.7189 | O18: 17.3536 | P18: 34.7861 | Q18: 54.3784 | R18: 43.8532 | S18: 73.0508 | T18: 64.5703 | U18: 52.395 | V18: 55.4466 | W18: 83.4214 | X18: 43.505 | Y18: 23.0568 | Z18: 30.924 | AA18: 36.8909 | AB18: 82.5366 | AC18: 372.065 | AG18: 264.254 | AH18: 335.751 | AL18: 311.383 | AN18: 135.536 | AO18: 146.974
A19: Debt/Equity | B19: 0 | C19: 0 | D19: 0 | E19: 0 | F19: 0.00109428 | G19: 0.00124196 | H19: 0.00101571 | I19: 0.000792769 | J19: 0.000627797 | K19: 0.000421253 | L19: 0.00027301 | M19: 0.000128399 | N19: 1.79308e-05 | O19: 0 | P19: 0 | Q19: 0 | R19: 0 | S19: 0 | T19: 0.0157778 | U19: 0.0139551 | V19: 0.0153978 | W19: 0.0134006 | X19: 0.0198964 | Y19: 0.0179862 | Z19: 0.0160441 | AA19: 0.337547 | AB19: 0.347958 | AC19: 0.340591 | AD19: 0.333617 | AE19: 0.328431 | AF19: 0.326328 | AG19: 0.289169 | AH19: 0.28703 | AI19: 0.266971 | AJ19: 0.240174 | AK19: 0.122718 | AL19: 0.065524 | AM19: 0.0484196 | AN19: 0.032966 | AO19: 0.0474023 | AP19: 0.0578593 | AQ19: 0.0607012 | AR19: 0.183631 | AS19: 0.183588 | AT19: 0.193658 | AU19: 0.193658
A20: Debt/EBITDA | F20: 0.057 | G20: 0.054 | J20: 0.602 | K20: 0.004 | M20: 0.004 | N20: 0.004 | T20: 0.494 | U20: 0.873 | V20: 6.371 | W20: 0.424 | X20: 0.983 | Y20: 0.8 | Z20: 5.542 | AA20: 7.852 | AB20: 145.968 | AC20: 11.21 | AD20: 65.986 | AE20: 8.203 | AF20: 19.847 | AG20: 48.783 | AH20: 9.598 | AJ20: 4.69 | AK20: 3.309 | AL20: 2.915 | AM20: 3.568 | AN20: 1.482 | AO20: 3.141 | AP20: 9.541 | AQ20: 2.323 | AR20: 39.544 | AS20: 29.658
A21: Debt/FCF | F21: 0.025 | G21: 0.122 | K21: 0.098 | L21: 0.005 | M21: 0.026 | T21: 8.562 | V21: 1.755 | W21: 1.396 | X21: 0.651 | Y21: 0.452 | Z21: 0.715 | AA21: 46.614 | AC21: 52.081 | AE21: 25.99 | AF21: 20.286 | AG21: 13.951 | AL21: 1.43 | AN21: 2.064
A22: Net Debt/Equity | B22: -0.597 | C22: -0.656 | D22: -0.63 | E22: -0.594 | F22: -0.62 | G22: -0.629 | H22: -0.637 | I22: -0.594 | J22: -0.559 | K22: -0.523 | L22: -0.592 | M22: -0.585 | N22: -0.568 | O22: -0.629 | P22: -0.661 | Q22: -0.652 | R22: -0.646 | S22: -0.699 | T22: -0.603 | U22: -0.578 | V22: -0.551 | W22: -0.574 | X22: -0.583 | Y22: -0.637 | Z22: -0.686 | AA22: 0.069 | AB22: 0.189 | AC22: 0.183 | AD22: 0.217 | AE22: 0.189 | AF22: 0.178 | AG22: 0.151 | AH22: 0.19 | AI22: 0.054 | AJ22: 0.088 | AK22: 0.013 | AL22: -0.047 | AM22: -0.017 | AN22: -0.04 | AO22: -0.022 | AP22: 0.014 | AQ22: 0.026 | AR22: 0.033 | AS22: 0.054 | AT22: 0.057 | AU22: 0.057
A23: Net Debt/EBITDA | B23: -39.541 | C23: -24.167 | D23: 28.383 | E23: -24.921 | F23: -32.132 | G23: -27.189 | H23: 16.066 | I23: 75.505 | J23: -536.34 | K23: -5.565 | L23: 33.487 | M23: -19.129 | N23: -134.286 | O23: -8.696 | P23: -18.132 | Q23: -34.165 | R23: -30.059 | S23: -44.383 | T23: -13.844 | U23: -27.079 | V23: -178.691 | W23: -12.146 | X23: -20.121 | Y23: -19.854 | Z23: -155.6 | AA23: 1.482 | AB23: 73.367 | AC23: 5.572 | AD23: 39.711 | AE23: 4.342 | AF23: 9.98 | AG23: 23.179 | AH23: 5.768 | AI23: -0.263 | AJ23: 1.512 | AK23: 0.307 | AL23: -1.588 | AM23: -0.815 | AN23: -1.061 | AO23: -1.167 | AP23: 1.964 | AQ23: 0.847 | AR23: 6.858 | AS23: 8.527 | AT23: -1.117 | AU23: -1.74
A24: Net Debt/FCF | C24: -11.889 | D24: 17.811 | E24: 15.256 | F24: -13.964 | G24: -61.751 | H24: 57.714 | I24: 29.903 | J24: 17.309 | K24: -121.112 | L24: -9.958 | M24: -118.343 | N24: 528.19 | O24: -7.114 | P24: -80.014 | Q24: 56.922 | R24: -187.498 | S24: -17.996 | T24: -239.769 | U24: 1994.676 | V24: -49.219 | W24: -39.978 | X24: -13.32 | Y24: -11.213 | Z24: -20.069 | AA24: 8.8 | AB24: -5.453 | AC24: 25.888 | AD24: -5.505 | AE24: 13.756 | AF24: 10.2 | AG24: 6.629 | AH24: -4.595 | AI24: -13.917 | AJ24: -2.435 | AK24: -0.688 | AL24: -0.779 | AM24: 0.656 | AN24: -1.477 | AO24: 2.157 | AP24: -0.412 | AQ24: -2.666 | AR24: -0.983 | AS24: -4.248 | AT24: -13.493 | AU24: -1.044
A25: Asset Turnover | B25: 0.176978 | C25: 0.217555 | D25: 0.122758 | E25: 0.170332 | F25: 0.174132 | G25: 0.209762 | H25: 0.0937309 | I25: 0.130184 | J25: 0.136851 | K25: 0.297396 | L25: 0.0848134 | M25: 0.160655 | N25: 0.133202 | O25: 0.250859 | P25: 0.173217 | Q25: 0.159372 | R25: 0.161668 | S25: 0.179036 | T25: 0.171263 | U25: 0.161525 | V25: 0.116991 | W25: 0.247254 | X25: 0.157227 | Y25: 0.163647 | Z25: 0.137004 | AA25: 0.179733 | AB25: 0.135913 | AC25: 0.161246 | AD25: 0.120425 | AE25: 0.143938 | AF25: 0.120226 | AG25: 0.122823 | AH25: 0.147164 | AI25: 0.213991 | AJ25: 0.176869 | AK25: 0.190495 | AL25: 0.196243 | AM25: 0.214057 | AN25: 0.207627 | AO25: 0.186059 | AP25: 0.165285 | AQ25: 0.257486 | AR25: 0.137298 | AS25: 0.141946 | AT25: 0.127268 | AU25: 0.127268
A26: Inventory Turnover | B26: 0.84846 | C26: 1.04331 | D26: 0.706427 | E26: 0.686817 | F26: 0.859681 | G26: 1.21808 | H26: 0.671052 | I26: 0.63184 | J26: 0.58681 | K26: 1.70209 | L26: 0.442001 | M26: 0.543538 | N26: 0.497944 | O26: 1.60941 | P26: 0.795617 | Q26: 0.730012 | R26: 0.703647 | S26: 1.11295 | T26: 0.925928 | U26: 0.973145 | V26: 0.664647 | W26: 1.64784 | X26: 1.02171 | Y26: 0.9912 | Z26: 0.847979 | AA26: 1.30328 | AB26: 1.10883 | AC26: 1.18982 | AD26: 0.962122 | AE26: 1.03528 | AF26: 0.815481 | AG26: 0.893791 | AH26: 0.824697 | AI26: 1.02545 | AJ26: 0.632754 | AK26: 0.723418 | AL26: 0.830353 | AM26: 0.83981 | AN26: 0.676726 | AO26: 0.714355 | AP26: 0.675188 | AQ26: 1.18752 | AR26: 1.90887 | AS26: 1.84704 | AT26: 1.3829 | AU26: 4.34002
A27: Quick Ratio | B27: 5.72004 | C27: 5.98596 | D27: 7.13421 | E27: 8.24581 | F27: 8.20891 | G27: 6.53005 | H27: 7.62197 | I27: 6.3466 | J27: 6.11868 | K27: 5.88215 | L27: 7.07595 | M27: 7.3039 | N27: 6.72088 | O27: 5.32874 | P27: 8.90172 | Q27: 9.37135 | R27: 9.09108 | S27: 9.07799 | T27: 9.07922 | U27: 8.82628 | V27: 6.37187 | W27: 6.75319 | X27: 9.39751 | Y27: 8.38681 | Z27: 8.20886 | AA27: 3.27485 | AB27: 2.96119 | AC27: 2.53048 | AD27: 2.58598 | AE27: 2.62657 | AF27: 2.57934 | AG27: 2.17168 | AH27: 2.06565 | AI27: 2.68799 | AJ27: 2.72736 | AK27: 2.89637 | AL27: 2.87841 | AM27: 2.36805 | AN27: 2.86657 | AO27: 3.10968 | AP27: 2.77626 | AQ27: 2.51415 | AR27: 4.90294 | AS27: 4.06768 | AT27: 4.2569 | AU27: 4.2569
A28: Current Ratio | B28: 7.09794 | C28: 7.04038 | D28: 8.74172 | E28: 10.1693 | F28: 10.0283 | G28: 7.42844 | H28: 9.09784 | I28: 7.96668 | J28: 8.13706 | K28: 7.3671 | L28: 9.20482 | M28: 9.44953 | N28: 8.76199 | O28: 6.42712 | P28: 10.0658 | Q28: 10.6838 | R28: 10.4551 | S28: 10.4665 | T28: 10.5625 | U28: 10.184 | V28: 7.56224 | W28: 7.52658 | X28: 10.5086 | Y28: 9.49173 | Z28: 9.29205 | AA28: 4.17568 | AB28: 4.17273 | AC28: 3.58948 | AD28: 4.05247 | AE28: 3.63848 | AF28: 3.72635 | AG28: 3.44264 | AH28: 3.35817 | AI28: 3.93131 | AJ28: 4.49382 | AK28: 4.79438 | AL28: 4.65625 | AM28: 3.5587 | AN28: 4.26342 | AO28: 4.61285 | AP28: 4.21918 | AQ28: 3.52296 | AR28: 5.96275 | AS28: 5.08024 | AT28: 5.50967 | AU28: 5.50967
A29: Return on Equity (ROE) | B29: 0.00682158 | C29: 0.0202916 | D29: -0.0202285 | E29: 0.0127449 | F29: 0.0177279 | G29: 0.0151006 | H29: -0.0334258 | I29: -0.0120079 | J29: -0.00622099 | K29: 0.0818778 | L29: -0.0119986 | M29: 0.020473 | N29: -0.00177866 | O29: 0.0481113 | P29: 0.0496897 | Q29: 0.0168909 | R29: 0.019888 | S29: 0.0140381 | T29: 0.0372301 | U29: 0.0160615 | V29: -0.00217275 | W29: 0.0365233 | X29: 0.0200581 | Y29: 0.00408596 | Z29: 0.000620142 | AA29: 0.0195578 | AB29: -0.0248934 | AC29: 0.00454771 | AD29: -6.20626e-05 | AE29: 0.00117183 | AF29: -0.0139993 | AG29: -0.0109777 | AH29: -0.00110437 | AI29: -0.276873 | AJ29: 0.0372771 | AK29: 0.0254637 | AL29: 0.0193587 | AM29: 0.00880241 | AN29: 0.0298095 | AO29: 0.00913126 | AP29: -0.00209553 | AQ29: 0.0194986 | AR29: -0.0255547 | AS29: -0.00648273 | AT29: -0.0966406 | AU29: -0.0966406
A30: Return on Assets (ROA) | B30: 0.00608692 | C30: 0.0190198 | D30: -0.0147024 | E30: 0.0115014 | F30: 0.0159947 | G30: 0.0124445 | H30: -0.0302748 | I30: -0.0115231 | J30: -0.00740767 | K30: 0.0701893 | L30: -0.0115806 | M30: 0.0177964 | N30: -0.00142869 | O30: 0.0420275 | P30: 0.0279786 | Q30: 0.0123797 | R30: 0.0151283 | S30: 0.0106158 | T30: 0.0331041 | U30: 0.0136113 | V30: -0.00201977 | W30: 0.0338902 | X30: 0.0197369 | Y30: 0.0111451 | Z30: 0.000577475 | AA30: 0.0294719 | AB30: -0.0152501 | AC30: -0.00162174 | AD30: -4.2827e-05 | AE30: 0.00062296 | AF30: -0.00526185 | AG30: -0.00611289 | AH30: 0.00282538 | AI30: -0.183395 | AJ30: 0.0288779 | AK30: 0.0249365 | AL30: 0.0138231 | AM30: 0.00924053 | AN30: 0.0236105 | AO30: 0.0071256 | AP30: -0.00226311 | AQ30: 0.0127639 | AR30: -0.0170737 | AS30: -0.00800127 | AT30: -0.0769074 | AU30: -0.0769074
A31: Return on Invested Capital (ROIC) | B31: 0.0153023 | C31: 0.0555709 | D31: -0.0395652 | E31: 0.0287677 | F31: 0.0414296 | G31: 0.0350016 | H31: -0.0814136 | I31: -0.0289868 | J31: -0.0183193 | K31: 0.165742 | L31: -0.0297118 | M31: 0.0442573 | N31: -0.00333907 | O31: 0.0991902 | P31: 0.0744652 | Q31: 0.0326905 | R31: 0.0390009 | S31: 0.0316722 | T31: 0.0888795 | U31: 0.0351351 | V31: -0.00501687 | W31: 0.0951356 | X31: 0.0493157 | Y31: 0.02897 | Z31: 0.00154735 | AA31: 0.0477881 | AB31: -0.022817 | AC31: -0.00250711 | AD31: -6.64405e-05 | AE31: 0.000784907 | AF31: -0.00629042 | AG31: -0.00735573 | AH31: 0.00328312 | AI31: -0.229027 | AJ31: 0.0348877 | AK31: 0.0297882 | AL31: 0.0163608 | AM31: 0.0115324 | AN31: 0.0281942 | AO31: 0.00835271 | AP31: -0.00264889 | AQ31: 0.0150414 | AR31: -0.0200952 | AS31: -0.00929803 | AT31: -0.0895428 | AU31: -0.0895428
A32: Return on Capital Employed (ROCE) | B32: 0.015017 | C32: 0.0212955 | D32: -0.0261304 | E32: 0.0198116 | F32: 0.0144832 | G32: 0.0191065 | H32: -0.044462 | I32: -0.0128396 | J32: -0.0040362 | K32: 0.0908795 | L32: -0.0220655 | M32: 0.0283889 | N32: 0.000428694 | O32: 0.0700381 | P32: 0.0345177 | Q32: 0.0158476 | R32: 0.0184608 | S32: 0.0117513 | T32: 0.0405871 | U32: 0.0170114 | V32: -0.00231852 | W32: 0.0433716 | X32: 0.0240418 | Y32: 0.026876 | Z32: -0.00124242 | AA32: 0.0263037 | AB32: -0.0178475 | AC32: 0.00491605 | AD32: -0.0208865 | AE32: 0.0158194 | AF32: -0.0040254 | AG32: -0.0177625 | AH32: 0.00567859 | AI32: -0.21857 | AJ32: 0.0347014 | AK32: 0.0298809 | AL32: 0.017089 | AM32: 0.00755293 | AN32: 0.0288115 | AO32: 0.00776344 | AP32: -0.00344531 | AQ32: 0.0151886 | AR32: -0.0222349 | AS32: -0.00972159 | AT32: -0.0898672 | AU32: -0.0898672
A33: Earnings Yield | B33: 0 | C33: 0.00507813 | D33: 0 | E33: 0.0130039 | F33: 0.0184241 | G33: 0.0135042 | H33: 0.00634921 | K33: 0.019601 | L33: 0.0182781 | M33: 0.0231608 | N33: 0.0235095 | O33: 0.0166972 | P33: 0.0295464 | Q33: 0.0229016 | R33: 0.0310038 | S33: 0.028734 | T33: 0.0285872 | U33: 0.0283501 | V33: 0.0179597 | W33: 0.028377 | X33: 0.0184193 | Y33: 0.0155841 | Z33: 0.0108042 | AA33: 0.00869802 | AF33: 0.000577101 | AM33: 0.0136429 | AN33: 0.0122541 | AO33: 0.00787687 | AP33: 0.00654247 | AQ33: 0.0102297
A34: Free Cash Flow Yield | B34: 0 | C34: 0.0571898 | D34: 0 | E34: 0 | F34: 0.0155835 | H34: 0.00309838 | I34: 0.0156083 | L34: 0.00681133 | M34: 0.0122093 | N34: 0.0202725 | O34: 0.0462531 | P34: 0.0239286 | Q34: 0.0159137 | R34: 0.0192415 | S34: 0.0109943 | T34: 0.0120299 | U34: 0.0151179 | V34: 0.0150437 | W34: 0.00956985 | X34: 0.0192065 | Y34: 0.0355046 | Z34: 0.0281264 | AA34: 0.027524 | AB34: 0.0126623 | AC34: 0.0028216 | AG34: 0.00393746 | AH34: 0.00313529 | AL34: 0.00317596 | AN34: 0.00732717 | AO34: 0.00678352
A35: Buyback Yield | F35: 0.0011077743 | G35: 0.00020735864 | H35: -0.00039655736 | I35: 0.0042940147 | J35: 3.4656339e-05 | K35: -0.0098472573 | L35: -0.016539906 | M35: -0.034010005 | N35: -0.018741065 | O35: -0.023340493 | P35: -0.028882042 | Q35: -0.011152604 | R35: -0.024077634 | S35: -0.0074340738 | T35: -0.002482268 | U35: 0.0015353462 | V35: 0.010825603 | W35: -0.0016227635 | X35: -0.0048317608 | Y35: -0.0056147088 | Z35: -0.018462623 | AA35: -0.026771582 | AB35: -0.017944117 | AC35: -0.028474722 | AD35: -0.025501939 | AE35: -0.0063075315 | AF35: -0.007473538 | AG35: -0.00060275096 | AH35: -0.0053377064 | AI35: -0.020644685 | AJ35: -0.055426097 | AK35: -0.082563281 | AL35: -0.12120788 | AM35: -0.10395269 | AN35: -0.080323924 | AO35: -0.04410019 | AP35: 0.00043502911 | AQ35: -0.0059900273 | AR35: -0.65768798 | AS35: -0.76664559 | AT35: -0.77445696 | AU35: -0.54789
A36: Total Return | F36: 0.0011077743 | G36: 0.00020735864 | H36: -0.00039655736 | I36: 0.0042940147 | J36: 3.4656339e-05 | K36: -0.0098472573 | L36: -0.016539906 | M36: -0.034010005 | N36: -0.018741065 | O36: -0.023340493 | P36: -0.028882042 | Q36: -0.011152604 | R36: -0.024077634 | S36: -0.0074340738 | T36: -0.002482268 | U36: 0.0015353462 | V36: 0.010825603 | W36: -0.0016227635 | X36: -0.0048317608 | Y36: -0.0056147088 | Z36: -0.018462623 | AA36: -0.026771582 | AB36: -0.017944117 | AC36: -0.028474722 | AD36: -0.025501939 | AE36: -0.0063075315 | AF36: -0.007473538 | AG36: -0.00060275096 | AH36: -0.0053377064 | AI36: -0.020644685 | AJ36: -0.055426097 | AK36: -0.082563281 | AL36: -0.12120788 | AM36: -0.10395269 | AN36: -0.080323924 | AO36: -0.04410019 | AP36: 0.00043502911 | AQ36: -0.0059900273 | AR36: -0.65768798 | AS36: -0.76664559 | AT36: -0.77445696 | AU36: -0.54789

Sheet KPI Rev by Segment
A1: AeroVironment, Inc. - KPI Rev by Segment
A2: USD mm
B3: Actual | AA3: Forecast
A4: Fiscal quarter end | B4: 1/25/20 | C4: 4/30/20 | D4: 8/1/20 | E4: 10/31/20 | F4: 1/30/21 | G4: 4/30/21 | H4: 7/31/21 | I4: 10/30/21 | J4: 1/29/22 | K4: 4/30/22 | L4: 7/30/22 | M4: 10/29/22 | N4: 1/28/23 | O4: 4/30/23 | P4: 7/29/23 | Q4: 10/28/23 | R4: 1/27/24 | S4: 4/30/24 | T4: 7/27/24 | U4: 10/26/24 | V4: 1/25/25 | W4: 4/30/25 | X4: 8/2/25 | Y4: 11/1/25 | Z4: 1/31/26 | AA4: 4/30/26 | AB4: 8/1/26 | AC4: 10/31/26 | AD4: 1/30/27 | AE4: 4/30/27 | AF4: 7/31/27 | AG4: 10/30/27 | AH4: 1/29/28
A5: Key Performance Indicators
A6: Autonomous Systems and Space (AxS) Revenue | T6: 189.483 | U6: 188.458 | V6: 167.636 | X6: 285.324 | Y6: 301.573 | Z6: 278.744 | AA6: =Z6*(1+Assumptions!$D$5) -> 412.54112 | AB6: =IF(X6<>"",X6*(1+Assumptions!$E$5),IF(AA6<>"",AA6*(1+Assumptions!$E$5),"")) -> 336.68232 | AC6: =IF(Y6<>"",Y6*(1+Assumptions!$F$5),IF(AB6<>"",AB6*(1+Assumptions!$F$5),"")) -> 355.85614 | AD6: =IF(Z6<>"",Z6*(1+Assumptions!$G$5),IF(AC6<>"",AC6*(1+Assumptions!$G$5),"")) -> 328.91792 | AE6: =IF(AA6<>"",AA6*(1+Assumptions!$H$5),IF(AD6<>"",AD6*(1+Assumptions!$H$5),"")) -> 486.79852 | AF6: =IF(AB6<>"",AB6*(1+Assumptions!$I$5),IF(AE6<>"",AE6*(1+Assumptions!$I$5),"")) -> 377.0842 | AG6: =IF(AC6<>"",AC6*(1+Assumptions!$J$5),IF(AF6<>"",AF6*(1+Assumptions!$J$5),"")) -> 398.55888 | AH6: =IF(AD6<>"",AD6*(1+Assumptions!$K$5),IF(AG6<>"",AG6*(1+Assumptions!$K$5),"")) -> 368.38807
A7: Cyber and Directed Energy (SCDE) Revenue | X7: 169.352 | Y7: 170.935 | Z7: 129.301 | AA7: =Z7*(1+Assumptions!$D$6) -> 152.57518 | AB7: =IF(X7<>"",X7*(1+Assumptions!$E$6),IF(AA7<>"",AA7*(1+Assumptions!$E$6),"")) -> 177.8196 | AC7: =IF(Y7<>"",Y7*(1+Assumptions!$F$6),IF(AB7<>"",AB7*(1+Assumptions!$F$6),"")) -> 179.48175 | AD7: =IF(Z7<>"",Z7*(1+Assumptions!$G$6),IF(AC7<>"",AC7*(1+Assumptions!$G$6),"")) -> 135.76605 | AE7: =IF(AA7<>"",AA7*(1+Assumptions!$H$6),IF(AD7<>"",AD7*(1+Assumptions!$H$6),"")) -> 160.20394 | AF7: =IF(AB7<>"",AB7*(1+Assumptions!$I$6),IF(AE7<>"",AE7*(1+Assumptions!$I$6),"")) -> 188.48878 | AG7: =IF(AC7<>"",AC7*(1+Assumptions!$J$6),IF(AF7<>"",AF7*(1+Assumptions!$J$6),"")) -> 190.25065 | AH7: =IF(AD7<>"",AD7*(1+Assumptions!$K$6),IF(AG7<>"",AG7*(1+Assumptions!$K$6),"")) -> 143.91201
A8: Other / not disclosed revenue | B8: 61.891 | C8: 135.223 | D8: 87.45 | E8: 92.665 | F8: 78.782 | G8: 136.015 | H8: 101.009 | I8: 122.008 | J8: 90.093 | K8: 132.622 | L8: 108.516 | M8: 111.584 | N8: 134.395 | O8: 186.041 | P8: 152.347 | Q8: 180.816 | R8: 186.578 | S8: 196.979 | W8: 275.05 | AA8: =Z8*(1+Assumptions!$D$7) -> 0 | AB8: =IF(X8<>"",X8*(1+Assumptions!$E$7),IF(AA8<>"",AA8*(1+Assumptions!$E$7),"")) -> 0 | AC8: =IF(Y8<>"",Y8*(1+Assumptions!$F$7),IF(AB8<>"",AB8*(1+Assumptions!$F$7),"")) -> 0 | AD8: =IF(Z8<>"",Z8*(1+Assumptions!$G$7),IF(AC8<>"",AC8*(1+Assumptions!$G$7),"")) -> 0 | AE8: =IF(AA8<>"",AA8*(1+Assumptions!$H$7),IF(AD8<>"",AD8*(1+Assumptions!$H$7),"")) -> 0 | AF8: =IF(AB8<>"",AB8*(1+Assumptions!$I$7),IF(AE8<>"",AE8*(1+Assumptions!$I$7),"")) -> 0 | AG8: =IF(AC8<>"",AC8*(1+Assumptions!$J$7),IF(AF8<>"",AF8*(1+Assumptions!$J$7),"")) -> 0 | AH8: =IF(AD8<>"",AD8*(1+Assumptions!$K$7),IF(AG8<>"",AG8*(1+Assumptions!$K$7),"")) -> 0
A9: Revenue (total) | B9: =SUM(B6,B7,B8) -> 61.891 | C9: =SUM(C6,C7,C8) -> 135.223 | D9: =SUM(D6,D7,D8) -> 87.45 | E9: =SUM(E6,E7,E8) -> 92.665 | F9: =SUM(F6,F7,F8) -> 78.782 | G9: =SUM(G6,G7,G8) -> 136.015 | H9: =SUM(H6,H7,H8) -> 101.009 | I9: =SUM(I6,I7,I8) -> 122.008 | ... AH9: =SUM(AH6,AH7,AH8) -> 512.30008

Sheet KPI Rev by Geography
A1: AeroVironment, Inc. - KPI Rev by Geography
A2: USD mm
B3: Actual | AA3: Forecast
A4: Fiscal quarter end | B4: 1/25/20 | C4: 4/30/20 | D4: 8/1/20 | E4: 10/31/20 | F4: 1/30/21 | G4: 4/30/21 | H4: 7/31/21 | I4: 10/30/21 | J4: 1/29/22 | K4: 4/30/22 | L4: 7/30/22 | M4: 10/29/22 | N4: 1/28/23 | O4: 4/30/23 | P4: 7/29/23 | Q4: 10/28/23 | R4: 1/27/24 | S4: 4/30/24 | T4: 7/27/24 | U4: 10/26/24 | V4: 1/25/25 | W4: 4/30/25 | X4: 8/2/25 | Y4: 11/1/25 | Z4: 1/31/26 | AA4: 4/30/26 | AB4: 8/1/26 | AC4: 10/31/26 | AD4: 1/30/27 | AE4: 4/30/27 | AF4: 7/31/27 | AG4: 10/30/27 | AH4: 1/29/28
A5: Key Performance Indicators
A6: Domestic Revenue | B6: 27.626 | C6: 84.647 | D6: 53.43 | E6: 46.398 | F6: 51.062 | G6: 91.008 | H6: 68.388 | I6: 68.663 | J6: 56.48 | K6: 68.727 | L6: 50.103 | M6: 67.657 | N6: 55.955 | O6: 77.293 | P6: 58.126 | Q6: 69.975 | R6: 62.865 | S6: 85.282 | T6: 66.998 | U6: 86.958 | V6: 104.097 | W6: 132.691 | X6: 347.035 | Y6: 360.703 | Z6: 226.11 | AA6: =Z6*(1+Assumptions!$D$8) -> 339.165 | AB6: =IF(X6<>"",X6*(1+Assumptions!$E$8),IF(AA6<>"",AA6*(1+Assumptions!$E$8),"")) -> 402.5606 | AC6: =IF(Y6<>"",Y6*(1+Assumptions!$F$8),IF(AB6<>"",AB6*(1+Assumptions!$F$8),"")) -> 418.41548 | AD6: =IF(Z6<>"",Z6*(1+Assumptions!$G$8),IF(AC6<>"",AC6*(1+Assumptions!$G$8),"")) -> 262.2876 | AE6: =IF(AA6<>"",AA6*(1+Assumptions!$H$8),IF(AD6<>"",AD6*(1+Assumptions!$H$8),"")) -> 393.4314 | AF6: =IF(AB6<>"",AB6*(1+Assumptions!$I$8),IF(AE6<>"",AE6*(1+Assumptions!$I$8),"")) -> 450.86787 | AG6: =IF(AC6<>"",AC6*(1+Assumptions!$J$8),IF(AF6<>"",AF6*(1+Assumptions!$J$8),"")) -> 468.62534 | AH6: =IF(AD6<>"",AD6*(1+Assumptions!$K$8),IF(AG6<>"",AG6*(1+Assumptions!$K$8),"")) -> 293.76211
A7: International Revenue | B7: 34.265 | C7: 50.576 | D7: 34.02 | E7: 46.267 | F7: 27.72 | G7: 45.007 | H7: 32.621 | I7: 53.345 | J7: 33.613 | K7: 63.895 | L7: 58.413 | M7: 43.927 | N7: 78.44 | O7: 108.748 | P7: 94.221 | Q7: 110.841 | R7: 123.713 | S7: 111.697 | T7: 122.485 | U7: 101.5 | V7: 63.539 | W7: 142.359 | X7: 107.641 | Y7: 111.805 | Z7: 181.935 | AA7: =Z7*(1+Assumptions!$D$9) -> 225.5994 | AB7: =IF(X7<>"",X7*(1+Assumptions!$E$9),IF(AA7<>"",AA7*(1+Assumptions!$E$9),"")) -> 124.86356 | AC7: =IF(Y7<>"",Y7*(1+Assumptions!$F$9),IF(AB7<>"",AB7*(1+Assumptions!$F$9),"")) -> 129.6938 | AD7: =IF(Z7<>"",Z7*(1+Assumptions!$G$9),IF(AC7<>"",AC7*(1+Assumptions!$G$9),"")) -> 211.0446 | AE7: =IF(AA7<>"",AA7*(1+Assumptions!$H$9),IF(AD7<>"",AD7*(1+Assumptions!$H$9),"")) -> 261.6953 | AF7: =IF(AB7<>"",AB7*(1+Assumptions!$I$9),IF(AE7<>"",AE7*(1+Assumptions!$I$9),"")) -> 139.84719 | AG7: =IF(AC7<>"",AC7*(1+Assumptions!$J$9),IF(AF7<>"",AF7*(1+Assumptions!$J$9),"")) -> 145.25706 | AH7: =IF(AD7<>"",AD7*(1+Assumptions!$K$9),IF(AG7<>"",AG7*(1+Assumptions!$K$9),"")) -> 236.36995
A8: Revenue (total) | B8: =SUM(B6,B7) -> 61.891 | C8: =SUM(C6,C7) -> 135.223 | D8: =SUM(D6,D7) -> 87.45 | E8: =SUM(E6,E7) -> 92.665 | F8: =SUM(F6,F7) -> 78.782 | G8: =SUM(G6,G7) -> 136.015 | H8: =SUM(H6,H7) -> 101.009 | I8: =SUM(I6,I7) -> 122.008 | ... AH8: =SUM(AH6,AH7) -> 530.13206

Sheet KPI Rev by Bus Unit
A1: AeroVironment, Inc. - KPI Rev by Bus Unit
A2: USD mm
B3: Actual | AA3: Forecast
A4: Fiscal quarter end | B4: 1/25/20 | C4: 4/30/20 | D4: 8/1/20 | E4: 10/31/20 | F4: 1/30/21 | G4: 4/30/21 | H4: 7/31/21 | I4: 10/30/21 | J4: 1/29/22 | K4: 4/30/22 | L4: 7/30/22 | M4: 10/29/22 | N4: 1/28/23 | O4: 4/30/23 | P4: 7/29/23 | Q4: 10/28/23 | R4: 1/27/24 | S4: 4/30/24 | T4: 7/27/24 | U4: 10/26/24 | V4: 1/25/25 | W4: 4/30/25 | X4: 8/2/25 | Y4: 11/1/25 | Z4: 1/31/26 | AA4: 4/30/26 | AB4: 8/1/26 | AC4: 10/31/26 | AD4: 1/30/27 | AE4: 4/30/27 | AF4: 7/31/27 | AG4: 10/30/27 | AH4: 1/29/28
A5: Key Performance Indicators
A6: Unmanned Systems (UMS) Revenue | L6: 67.774 | M6: 61.634 | N6: 92.329 | O6: 122.172 | P6: 98.207 | Q6: 132.773 | R6: 113.29 | S6: 103.736 | T6: 119.976 | U6: 85.416 | V6: 63.75 | W6: 112.636 | AA6: =Z6*(1+Assumptions!$D$10) -> 0 | AB6: =IF(X6<>"",X6*(1+Assumptions!$E$10),IF(AA6<>"",AA6*(1+Assumptions!$E$10),"")) -> 0 | AC6: =IF(Y6<>"",Y6*(1+Assumptions!$F$10),IF(AB6<>"",AB6*(1+Assumptions!$F$10),"")) -> 0 | AD6: =IF(Z6<>"",Z6*(1+Assumptions!$G$10),IF(AC6<>"",AC6*(1+Assumptions!$G$10),"")) -> 0 | AE6: =IF(AA6<>"",AA6*(1+Assumptions!$H$10),IF(AD6<>"",AD6*(1+Assumptions!$H$10),"")) -> 0 | AF6: =IF(AB6<>"",AB6*(1+Assumptions!$I$10),IF(AE6<>"",AE6*(1+Assumptions!$I$10),"")) -> 0 | AG6: =IF(AC6<>"",AC6*(1+Assumptions!$J$10),IF(AF6<>"",AF6*(1+Assumptions!$J$10),"")) -> 0 | AH6: =IF(AD6<>"",AD6*(1+Assumptions!$K$10),IF(AG6<>"",AG6*(1+Assumptions!$K$10),"")) -> 0
A7: Loitering Munitions Systems (LMS) Revenue | L7: 23.012 | M7: 31.101 | N7: 24.015 | O7: 42.497 | P7: 30.917 | Q7: 30.249 | R7: 57.658 | S7: 73.763 | T7: 51.973 | U7: 77.715 | V7: 83.941 | W7: 138.348 | AA7: =Z7*(1+Assumptions!$D$11) -> 0 | AB7: =IF(X7<>"",X7*(1+Assumptions!$E$11),IF(AA7<>"",AA7*(1+Assumptions!$E$11),"")) -> 0 | AC7: =IF(Y7<>"",Y7*(1+Assumptions!$F$11),IF(AB7<>"",AB7*(1+Assumptions!$F$11),"")) -> 0 | AD7: =IF(Z7<>"",Z7*(1+Assumptions!$G$11),IF(AC7<>"",AC7*(1+Assumptions!$G$11),"")) -> 0 | AE7: =IF(AA7<>"",AA7*(1+Assumptions!$H$11),IF(AD7<>"",AD7*(1+Assumptions!$H$11),"")) -> 0 | AF7: =IF(AB7<>"",AB7*(1+Assumptions!$I$11),IF(AE7<>"",AE7*(1+Assumptions!$I$11),"")) -> 0 | AG7: =IF(AC7<>"",AC7*(1+Assumptions!$J$11),IF(AF7<>"",AF7*(1+Assumptions!$J$11),"")) -> 0 | AH7: =IF(AD7<>"",AD7*(1+Assumptions!$K$11),IF(AG7<>"",AG7*(1+Assumptions!$K$11),"")) -> 0
A8: MacCready Works (MW) Revenue | L8: 17.73 | M8: 18.849 | N8: 18.051 | O8: 21.372 | P8: 23.223 | Q8: 17.794 | R8: 15.63 | S8: 19.48 | T8: 17.534 | U8: 25.327 | V8: 19.945 | W8: 24.066 | AA8: =Z8*(1+Assumptions!$D$12) -> 0 | AB8: =IF(X8<>"",X8*(1+Assumptions!$E$12),IF(AA8<>"",AA8*(1+Assumptions!$E$12),"")) -> 0 | AC8: =IF(Y8<>"",Y8*(1+Assumptions!$F$12),IF(AB8<>"",AB8*(1+Assumptions!$F$12),"")) -> 0 | AD8: =IF(Z8<>"",Z8*(1+Assumptions!$G$12),IF(AC8<>"",AC8*(1+Assumptions!$G$12),"")) -> 0 | AE8: =IF(AA8<>"",AA8*(1+Assumptions!$H$12),IF(AD8<>"",AD8*(1+Assumptions!$H$12),"")) -> 0 | AF8: =IF(AB8<>"",AB8*(1+Assumptions!$I$12),IF(AE8<>"",AE8*(1+Assumptions!$I$12),"")) -> 0 | AG8: =IF(AC8<>"",AC8*(1+Assumptions!$J$12),IF(AF8<>"",AF8*(1+Assumptions!$J$12),"")) -> 0 | AH8: =IF(AD8<>"",AD8*(1+Assumptions!$K$12),IF(AG8<>"",AG8*(1+Assumptions!$K$12),"")) -> 0
A9: Other / not disclosed revenue | B9: 61.891 | C9: 135.223 | D9: 87.45 | E9: 92.665 | F9: 78.782 | G9: 136.015 | H9: 101.009 | I9: 122.008 | J9: 90.093 | K9: 132.622 | X9: 454.676 | Y9: 472.508 | Z9: 408.045 | AA9: =Z9*(1+Assumptions!$D$13) -> 565.14233 | AB9: =IF(X9<>"",X9*(1+Assumptions!$E$13),IF(AA9<>"",AA9*(1+Assumptions!$E$13),"")) -> 527.42416 | AC9: =IF(Y9<>"",Y9*(1+Assumptions!$F$13),IF(AB9<>"",AB9*(1+Assumptions!$F$13),"")) -> 548.10928 | AD9: =IF(Z9<>"",Z9*(1+Assumptions!$G$13),IF(AC9<>"",AC9*(1+Assumptions!$G$13),"")) -> 473.3322 | AE9: =IF(AA9<>"",AA9*(1+Assumptions!$H$13),IF(AD9<>"",AD9*(1+Assumptions!$H$13),"")) -> 655.5651 | AF9: =IF(AB9<>"",AB9*(1+Assumptions!$I$13),IF(AE9<>"",AE9*(1+Assumptions!$I$13),"")) -> 590.71506 | AG9: =IF(AC9<>"",AC9*(1+Assumptions!$J$13),IF(AF9<>"",AF9*(1+Assumptions!$J$13),"")) -> 613.88239 | AH9: =IF(AD9<>"",AD9*(1+Assumptions!$K$13),IF(AG9<>"",AG9*(1+Assumptions!$K$13),"")) -> 530.13206
A10: Revenue (total) | B10: =SUM(B6,B7,B8,B9) -> 61.891 | C10: =SUM(C6,C7,C8,C9) -> 135.223 | D10: =SUM(D6,D7,D8,D9) -> 87.45 | E10: =SUM(E6,E7,E8,E9) -> 92.665 | F10: =SUM(F6,F7,F8,F9) -> 78.782 | G10: =SUM(G6,G7,G8,G9) -> 136.015 | H10: =SUM(H6,H7,H8,H9) -> 101.009 | I10: =SUM(I6,I7,I8,I9) -> 122.008 | ... AH10: =SUM(AH6,AH7,AH8,AH9) -> 530.13206

Sheet KPI Rev by Product
A1: AeroVironment, Inc. - KPI Rev by Product
A2: USD mm
B3: Actual | AA3: Forecast
A4: Fiscal quarter end | B4: 1/25/20 | C4: 4/30/20 | D4: 8/1/20 | E4: 10/31/20 | F4: 1/30/21 | G4: 4/30/21 | H4: 7/31/21 | I4: 10/30/21 | J4: 1/29/22 | K4: 4/30/22 | L4: 7/30/22 | M4: 10/29/22 | N4: 1/28/23 | O4: 4/30/23 | P4: 7/29/23 | Q4: 10/28/23 | R4: 1/27/24 | S4: 4/30/24 | T4: 7/27/24 | U4: 10/26/24 | V4: 1/25/25 | W4: 4/30/25 | X4: 8/2/25 | Y4: 11/1/25 | Z4: 1/31/26 | AA4: 4/30/26 | AB4: 8/1/26 | AC4: 10/31/26 | AD4: 1/30/27 | AE4: 4/30/27 | AF4: 7/31/27 | AG4: 10/30/27 | AH4: 1/29/28
A5: Key Performance Indicators
A6: Small Unmanned Aircraft Systems (SUAS) Revenue | B6: 36.965 | C6: 63.02 | D6: 56.202 | E6: 58.265 | F6: 50.536 | G6: 70.851 | H6: 39.924 | I6: 54.714 | J6: 24.366 | K6: 59.198 | L6: 43.256 | M6: 26.681 | N6: 69.376 | O6: 94.595 | AA6: =Z6*(1+Assumptions!$D$14) -> 0 | AB6: =IF(X6<>"",X6*(1+Assumptions!$E$14),IF(AA6<>"",AA6*(1+Assumptions!$E$14),"")) -> 0 | AC6: =IF(Y6<>"",Y6*(1+Assumptions!$F$14),IF(AB6<>"",AB6*(1+Assumptions!$F$14),"")) -> 0 | AD6: =IF(Z6<>"",Z6*(1+Assumptions!$G$14),IF(AC6<>"",AC6*(1+Assumptions!$G$14),"")) -> 0 | AE6: =IF(AA6<>"",AA6*(1+Assumptions!$H$14),IF(AD6<>"",AD6*(1+Assumptions!$H$14),"")) -> 0 | AF6: =IF(AB6<>"",AB6*(1+Assumptions!$I$14),IF(AE6<>"",AE6*(1+Assumptions!$I$14),"")) -> 0 | AG6: =IF(AC6<>"",AC6*(1+Assumptions!$J$14),IF(AF6<>"",AF6*(1+Assumptions!$J$14),"")) -> 0 | AH6: =IF(AD6<>"",AD6*(1+Assumptions!$K$14),IF(AG6<>"",AG6*(1+Assumptions!$K$14),"")) -> 0
A7: Tactical Missile Systems (TMS) Revenue | B7: 7.908 | C7: 42.362 | D7: 9.534 | E7: 18.961 | F7: 19.598 | G7: 39.175 | H7: 19.176 | I7: 18.418 | J7: 18.603 | K7: 20.217 | L7: 23.011 | M7: 31.101 | N7: 24.015 | O7: 42.497 | AA7: =Z7*(1+Assumptions!$D$15) -> 0 | AB7: =IF(X7<>"",X7*(1+Assumptions!$E$15),IF(AA7<>"",AA7*(1+Assumptions!$E$15),"")) -> 0 | AC7: =IF(Y7<>"",Y7*(1+Assumptions!$F$15),IF(AB7<>"",AB7*(1+Assumptions!$F$15),"")) -> 0 | AD7: =IF(Z7<>"",Z7*(1+Assumptions!$G$15),IF(AC7<>"",AC7*(1+Assumptions!$G$15),"")) -> 0 | AE7: =IF(AA7<>"",AA7*(1+Assumptions!$H$15),IF(AD7<>"",AD7*(1+Assumptions!$H$15),"")) -> 0 | AF7: =IF(AB7<>"",AB7*(1+Assumptions!$I$15),IF(AE7<>"",AE7*(1+Assumptions!$I$15),"")) -> 0 | AG7: =IF(AC7<>"",AC7*(1+Assumptions!$J$15),IF(AF7<>"",AF7*(1+Assumptions!$J$15),"")) -> 0 | AH7: =IF(AD7<>"",AD7*(1+Assumptions!$K$15),IF(AG7<>"",AG7*(1+Assumptions!$K$15),"")) -> 0
A8: Medium Unmanned Aircraft Systems (MUAS) Revenue | G8: 15.837 | H8: 22.379 | I8: 26.525 | J8: 21.168 | K8: 23.083 | L8: 19.262 | M8: 27.281 | N8: 15.405 | O8: 8.379 | AA8: =Z8*(1+Assumptions!$D$16) -> 0 | AB8: =IF(X8<>"",X8*(1+Assumptions!$E$16),IF(AA8<>"",AA8*(1+Assumptions!$E$16),"")) -> 0 | AC8: =IF(Y8<>"",Y8*(1+Assumptions!$F$16),IF(AB8<>"",AB8*(1+Assumptions!$F$16),"")) -> 0 | AD8: =IF(Z8<>"",Z8*(1+Assumptions!$G$16),IF(AC8<>"",AC8*(1+Assumptions!$G$16),"")) -> 0 | AE8: =IF(AA8<>"",AA8*(1+Assumptions!$H$16),IF(AD8<>"",AD8*(1+Assumptions!$H$16),"")) -> 0 | AF8: =IF(AB8<>"",AB8*(1+Assumptions!$I$16),IF(AE8<>"",AE8*(1+Assumptions!$I$16),"")) -> 0 | AG8: =IF(AC8<>"",AC8*(1+Assumptions!$J$16),IF(AF8<>"",AF8*(1+Assumptions!$J$16),"")) -> 0 | AH8: =IF(AD8<>"",AD8*(1+Assumptions!$K$16),IF(AG8<>"",AG8*(1+Assumptions!$K$16),"")) -> 0
A9: High Altitude Pseudo-Satellite Unmanned Aircraft Systems (HAPS) Revenue | B9: 11.762 | C9: 23.374 | D9: 16.386 | E9: 11.452 | F9: 7.48 | G9: 7.108 | H9: 10.352 | I9: 10.342 | J9: 9.543 | K9: 13.088 | L9: 10.215 | M9: 9.066 | N9: 8.938 | AA9: =Z9*(1+Assumptions!$D$17) -> 0 | AB9: =IF(X9<>"",X9*(1+Assumptions!$E$17),IF(AA9<>"",AA9*(1+Assumptions!$E$17),"")) -> 0 | AC9: =IF(Y9<>"",Y9*(1+Assumptions!$F$17),IF(AB9<>"",AB9*(1+Assumptions!$F$17),"")) -> 0 | AD9: =IF(Z9<>"",Z9*(1+Assumptions!$G$17),IF(AC9<>"",AC9*(1+Assumptions!$G$17),"")) -> 0 | AE9: =IF(AA9<>"",AA9*(1+Assumptions!$H$17),IF(AD9<>"",AD9*(1+Assumptions!$H$17),"")) -> 0 | AF9: =IF(AB9<>"",AB9*(1+Assumptions!$I$17),IF(AE9<>"",AE9*(1+Assumptions!$I$17),"")) -> 0 | AG9: =IF(AC9<>"",AC9*(1+Assumptions!$J$17),IF(AF9<>"",AF9*(1+Assumptions!$J$17),"")) -> 0 | AH9: =IF(AD9<>"",AD9*(1+Assumptions!$K$17),IF(AG9<>"",AG9*(1+Assumptions!$K$17),"")) -> 0
A10: Other Segment Revenue | B10: 5.256 | C10: 6.467 | D10: 5.328 | E10: 3.987 | F10: 1.168 | G10: 3.044 | H10: 9.178 | I10: 12.009 | J10: 16.413 | K10: 17.035 | L10: 12.772 | M10: 17.455 | N10: 16.661 | AA10: =Z10*(1+Assumptions!$D$18) -> 0 | AB10: =IF(X10<>"",X10*(1+Assumptions!$E$18),IF(AA10<>"",AA10*(1+Assumptions!$E$18),"")) -> 0 | AC10: =IF(Y10<>"",Y10*(1+Assumptions!$F$18),IF(AB10<>"",AB10*(1+Assumptions!$F$18),"")) -> 0 | AD10: =IF(Z10<>"",Z10*(1+Assumptions!$G$18),IF(AC10<>"",AC10*(1+Assumptions!$G$18),"")) -> 0 | AE10: =IF(AA10<>"",AA10*(1+Assumptions!$H$18),IF(AD10<>"",AD10*(1+Assumptions!$H$18),"")) -> 0 | AF10: =IF(AB10<>"",AB10*(1+Assumptions!$I$18),IF(AE10<>"",AE10*(1+Assumptions!$I$18),"")) -> 0 | AG10: =IF(AC10<>"",AC10*(1+Assumptions!$J$18),IF(AF10<>"",AF10*(1+Assumptions!$J$18),"")) -> 0 | AH10: =IF(AD10<>"",AD10*(1+Assumptions!$K$18),IF(AG10<>"",AG10*(1+Assumptions!$K$18),"")) -> 0
A11: All Other Segment Revenue | B11: 17.018 | C11: 29.841 | D11: 21.714 | E11: 15.439 | F11: 8.648 | G11: 10.152 | H11: 19.53 | I11: 22.351 | J11: 25.956 | K11: 30.124 | L11: 22.987 | M11: 26.521 | N11: 25.599 | O11: 40.57 | AA11: =Z11*(1+Assumptions!$D$19) -> 0 | AB11: =IF(X11<>"",X11*(1+Assumptions!$E$19),IF(AA11<>"",AA11*(1+Assumptions!$E$19),"")) -> 0 | AC11: =IF(Y11<>"",Y11*(1+Assumptions!$F$19),IF(AB11<>"",AB11*(1+Assumptions!$F$19),"")) -> 0 | AD11: =IF(Z11<>"",Z11*(1+Assumptions!$G$19),IF(AC11<>"",AC11*(1+Assumptions!$G$19),"")) -> 0 | AE11: =IF(AA11<>"",AA11*(1+Assumptions!$H$19),IF(AD11<>"",AD11*(1+Assumptions!$H$19),"")) -> 0 | AF11: =IF(AB11<>"",AB11*(1+Assumptions!$I$19),IF(AE11<>"",AE11*(1+Assumptions!$I$19),"")) -> 0 | AG11: =IF(AC11<>"",AC11*(1+Assumptions!$J$19),IF(AF11<>"",AF11*(1+Assumptions!$J$19),"")) -> 0 | AH11: =IF(AD11<>"",AD11*(1+Assumptions!$K$19),IF(AG11<>"",AG11*(1+Assumptions!$K$19),"")) -> 0
A12: Other / not disclosed revenue | B12: -17.018 | C12: -29.841 | D12: -21.714 | E12: -15.439 | F12: -8.648 | G12: -10.152 | H12: -19.53 | I12: -22.351 | J12: -25.956 | K12: -30.123 | L12: -22.987 | M12: -26.521 | N12: -25.599 | P12: 152.347 | Q12: 180.816 | R12: 186.578 | S12: 196.979 | T12: 189.483 | U12: 188.458 | V12: 167.636 | W12: 275.05 | X12: 454.676 | Y12: 472.508 | Z12: 408.045 | AA12: =Z12*(1+Assumptions!$D$20) -> 565.14233 | AB12: =IF(X12<>"",X12*(1+Assumptions!$E$20),IF(AA12<>"",AA12*(1+Assumptions!$E$20),"")) -> 527.42416 | AC12: =IF(Y12<>"",Y12*(1+Assumptions!$F$20),IF(AB12<>"",AB12*(1+Assumptions!$F$20),"")) -> 548.10928 | AD12: =IF(Z12<>"",Z12*(1+Assumptions!$G$20),IF(AC12<>"",AC12*(1+Assumptions!$G$20),"")) -> 473.3322 | AE12: =IF(AA12<>"",AA12*(1+Assumptions!$H$20),IF(AD12<>"",AD12*(1+Assumptions!$H$20),"")) -> 655.5651 | AF12: =IF(AB12<>"",AB12*(1+Assumptions!$I$20),IF(AE12<>"",AE12*(1+Assumptions!$I$20),"")) -> 590.71506 | AG12: =IF(AC12<>"",AC12*(1+Assumptions!$J$20),IF(AF12<>"",AF12*(1+Assumptions!$J$20),"")) -> 613.88239 | AH12: =IF(AD12<>"",AD12*(1+Assumptions!$K$20),IF(AG12<>"",AG12*(1+Assumptions!$K$20),"")) -> 530.13206
A13: Revenue (total) | B13: =SUM(B6,B7,B8,B9,B10,B11,B12) -> 61.891 | C13: =SUM(C6,C7,C8,C9,C10,C11,C12) -> 135.223 | D13: =SUM(D6,D7,D8,D9,D10,D11,D12) -> 87.45 | E13: =SUM(E6,E7,E8,E9,E10,E11,E12) -> 92.665 | F13: =SUM(F6,F7,F8,F9,F10,F11,F12) -> 78.782 | G13: =SUM(G6,G7,G8,G9,G10,G11,G12) -> 136.015 | H13: =SUM(H6,H7,H8,H9,H10,H11,H12) -> 101.009 | I13: =SUM(I6,I7,I8,I9,I10,I11,I12) -> 122.008 | ... AH13: =SUM(AH6,AH7,AH8,AH9,AH10,AH11,AH12) -> 530.13206

Sheet KPI Rev by Type
A1: AeroVironment, Inc. - KPI Rev by Type
A2: USD mm
B3: Actual | AA3: Forecast
A4: Fiscal quarter end | B4: 1/25/20 | C4: 4/30/20 | D4: 8/1/20 | E4: 10/31/20 | F4: 1/30/21 | G4: 4/30/21 | H4: 7/31/21 | I4: 10/30/21 | J4: 1/29/22 | K4: 4/30/22 | L4: 7/30/22 | M4: 10/29/22 | N4: 1/28/23 | O4: 4/30/23 | P4: 7/29/23 | Q4: 10/28/23 | R4: 1/27/24 | S4: 4/30/24 | T4: 7/27/24 | U4: 10/26/24 | V4: 1/25/25 | W4: 4/30/25 | X4: 8/2/25 | Y4: 11/1/25 | Z4: 1/31/26 | AA4: 4/30/26 | AB4: 8/1/26 | AC4: 10/31/26 | AD4: 1/30/27 | AE4: 4/30/27 | AF4: 7/31/27 | AG4: 10/30/27 | AH4: 1/29/28
A5: Key Performance Indicators
A6: Product Sales | B6: 36.432 | C6: 97.101 | D6: 58.357 | E6: 65.528 | F6: 58.348 | G6: 96.655 | H6: 53.116 | I6: 70.998 | J6: 42.599 | K6: 73.97 | L6: 57.974 | M6: 62.343 | N6: 91.216 | O6: 141.529 | P6: 119.471 | Q6: 145.779 | R6: 155.923 | S6: 164.598 | T6: 159.504 | U6: 151.231 | V6: 139.753 | W6: 242.234 | X6: 313.533 | Y6: 325.037 | Z6: 277.814 | AA6: =Z6*(1+Assumptions!$D$21) -> 395.32932 | AB6: =IF(X6<>"",X6*(1+Assumptions!$E$21),IF(AA6<>"",AA6*(1+Assumptions!$E$21),"")) -> 376.2396 | AC6: =IF(Y6<>"",Y6*(1+Assumptions!$F$21),IF(AB6<>"",AB6*(1+Assumptions!$F$21),"")) -> 390.0444 | AD6: =IF(Z6<>"",Z6*(1+Assumptions!$G$21),IF(AC6<>"",AC6*(1+Assumptions!$G$21),"")) -> 333.3768 | AE6: =IF(AA6<>"",AA6*(1+Assumptions!$H$21),IF(AD6<>"",AD6*(1+Assumptions!$H$21),"")) -> 474.39519 | AF6: =IF(AB6<>"",AB6*(1+Assumptions!$I$21),IF(AE6<>"",AE6*(1+Assumptions!$I$21),"")) -> 425.15075 | AG6: =IF(AC6<>"",AC6*(1+Assumptions!$J$21),IF(AF6<>"",AF6*(1+Assumptions!$J$21),"")) -> 440.75017 | AH6: =IF(AD6<>"",AD6*(1+Assumptions!$K$21),IF(AG6<>"",AG6*(1+Assumptions!$K$21),"")) -> 376.71578
A7: Contract Services Revenue | B7: 25.459 | C7: 38.122 | D7: 29.093 | E7: 27.137 | F7: 20.434 | G7: 39.36 | H7: 47.893 | I7: 51.01 | J7: 47.494 | K7: 58.652 | L7: 50.542 | M7: 49.241 | N7: 43.179 | O7: 44.512 | P7: 32.876 | Q7: 35.037 | R7: 30.655 | S7: 32.381 | T7: 29.979 | U7: 37.227 | V7: 27.883 | W7: 32.816 | X7: 141.143 | Y7: 147.471 | Z7: 130.231 | AA7: =Z7*(1+Assumptions!$D$22) -> 169.43053 | AB7: =IF(X7<>"",X7*(1+Assumptions!$E$22),IF(AA7<>"",AA7*(1+Assumptions!$E$22),"")) -> 151.02301 | AC7: =IF(Y7<>"",Y7*(1+Assumptions!$F$22),IF(AB7<>"",AB7*(1+Assumptions!$F$22),"")) -> 157.79397 | AD7: =IF(Z7<>"",Z7*(1+Assumptions!$G$22),IF(AC7<>"",AC7*(1+Assumptions!$G$22),"")) -> 139.34717 | AE7: =IF(AA7<>"",AA7*(1+Assumptions!$H$22),IF(AD7<>"",AD7*(1+Assumptions!$H$22),"")) -> 181.29067 | AF7: =IF(AB7<>"",AB7*(1+Assumptions!$I$22),IF(AE7<>"",AE7*(1+Assumptions!$I$22),"")) -> 160.08439 | AG7: =IF(AC7<>"",AC7*(1+Assumptions!$J$22),IF(AF7<>"",AF7*(1+Assumptions!$J$22),"")) -> 167.26161 | AH7: =IF(AD7<>"",AD7*(1+Assumptions!$K$22),IF(AG7<>"",AG7*(1+Assumptions!$K$22),"")) -> 147.708
A8: Revenue | B8: 61.891 | C8: 135.223 | D8: 87.45 | E8: 92.665 | F8: 78.782 | G8: 136.015 | H8: 101.009 | I8: 122.008 | J8: 90.093 | K8: 132.622 | L8: 108.516 | M8: 111.584 | N8: 134.395 | O8: 186.041 | P8: 152.347 | Q8: 180.816 | R8: 186.578 | S8: 196.979 | T8: 189.483 | U8: 188.458 | V8: 167.636 | W8: 275.05 | X8: 454.676 | Y8: 472.508 | Z8: 408.045 | AA8: =SUM(AA6,AA7) -> 564.75985 | AB8: =SUM(AB6,AB7) -> 527.26261 | AC8: =SUM(AC6,AC7) -> 547.83837 | AD8: =SUM(AD6,AD7) -> 472.72397 | AE8: =SUM(AE6,AE7) -> 655.68585 | AF8: =SUM(AF6,AF7) -> 585.23514 | AG8: =SUM(AG6,AG7) -> 608.01178 | AH8: =SUM(AH6,AH7) -> 524.42378

Sheet KPI Rev by Contract
A1: AeroVironment, Inc. - KPI Rev by Contract
A2: USD mm
B3: Actual | AA3: Forecast
A4: Fiscal quarter end | B4: 1/25/20 | C4: 4/30/20 | D4: 8/1/20 | E4: 10/31/20 | F4: 1/30/21 | G4: 4/30/21 | H4: 7/31/21 | I4: 10/30/21 | J4: 1/29/22 | K4: 4/30/22 | L4: 7/30/22 | M4: 10/29/22 | N4: 1/28/23 | O4: 4/30/23 | P4: 7/29/23 | Q4: 10/28/23 | R4: 1/27/24 | S4: 4/30/24 | T4: 7/27/24 | U4: 10/26/24 | V4: 1/25/25 | W4: 4/30/25 | X4: 8/2/25 | Y4: 11/1/25 | Z4: 1/31/26 | AA4: 4/30/26 | AB4: 8/1/26 | AC4: 10/31/26 | AD4: 1/30/27 | AE4: 4/30/27 | AF4: 7/31/27 | AG4: 10/30/27 | AH4: 1/29/28
A5: Key Performance Indicators
A6: Firm Fixed Price (FFP) Revenue | B6: 40.145 | C6: 101.31 | D6: 60.875 | E6: 68.425 | F6: 61.23 | G6: 116.883 | H6: 80.766 | I6: 98.393 | J6: 66.639 | K6: 100.294 | L6: 80.829 | M6: 85.236 | N6: 109.119 | O6: 155.363 | P6: 129.942 | Q6: 159.879 | R6: 167.256 | S6: 177.189 | T6: 171.869 | U6: 168.752 | V6: 148.768 | W6: 256.802 | X6: 298.977 | Y6: 301.508 | Z6: 280.369 | AA6: =Z6*(1+Assumptions!$D$23) -> 420.5535 | AB6: =IF(X6<>"",X6*(1+Assumptions!$E$23),IF(AA6<>"",AA6*(1+Assumptions!$E$23),"")) -> 346.81332 | AC6: =IF(Y6<>"",Y6*(1+Assumptions!$F$23),IF(AB6<>"",AB6*(1+Assumptions!$F$23),"")) -> 349.74928 | AD6: =IF(Z6<>"",Z6*(1+Assumptions!$G$23),IF(AC6<>"",AC6*(1+Assumptions!$G$23),"")) -> 325.22804 | AE6: =IF(AA6<>"",AA6*(1+Assumptions!$H$23),IF(AD6<>"",AD6*(1+Assumptions!$H$23),"")) -> 487.84206 | AF6: =IF(AB6<>"",AB6*(1+Assumptions!$I$23),IF(AE6<>"",AE6*(1+Assumptions!$I$23),"")) -> 388.43092 | AG6: =IF(AC6<>"",AC6*(1+Assumptions!$J$23),IF(AF6<>"",AF6*(1+Assumptions!$J$23),"")) -> 391.71919 | AH6: =IF(AD6<>"",AD6*(1+Assumptions!$K$23),IF(AG6<>"",AG6*(1+Assumptions!$K$23),"")) -> 364.2554
A7: Cost Plus Fixed Fee (CPFF) Revenue | B7: 20.863 | C7: 33.792 | D7: 26.569 | E7: 24.23 | F7: 17.53 | G7: 18.39 | H7: 19.117 | I7: 21.594 | J7: 21.788 | K7: 30.929 | L7: 26.455 | M7: 25.013 | N7: 24.115 | O7: 28.861 | P7: 21.293 | Q7: 19.802 | R7: 17.925 | S7: 18.013 | T7: 16.231 | U7: 18.81 | V7: 17.372 | W7: 15.573 | X7: 118.928 | Y7: 131.35 | Z7: 95.802 | AA7: =Z7*(1+Assumptions!$D$24) -> 107.29824 | AB7: =IF(X7<>"",X7*(1+Assumptions!$E$24),IF(AA7<>"",AA7*(1+Assumptions!$E$24),"")) -> 130.8208 | AC7: =IF(Y7<>"",Y7*(1+Assumptions!$F$24),IF(AB7<>"",AB7*(1+Assumptions!$F$24),"")) -> 144.485 | AD7: =IF(Z7<>"",Z7*(1+Assumptions!$G$24),IF(AC7<>"",AC7*(1+Assumptions!$G$24),"")) -> 105.3822 | AE7: =IF(AA7<>"",AA7*(1+Assumptions!$H$24),IF(AD7<>"",AD7*(1+Assumptions!$H$24),"")) -> 118.02806 | AF7: =IF(AB7<>"",AB7*(1+Assumptions!$I$24),IF(AE7<>"",AE7*(1+Assumptions!$I$24),"")) -> 143.90288 | AG7: =IF(AC7<>"",AC7*(1+Assumptions!$J$24),IF(AF7<>"",AF7*(1+Assumptions!$J$24),"")) -> 158.9335 | AH7: =IF(AD7<>"",AD7*(1+Assumptions!$K$24),IF(AG7<>"",AG7*(1+Assumptions!$K$24),"")) -> 115.92042
A8: Time and Materials (T&M) Revenue | B8: 0.883 | C8: 0.121 | D8: 0.006 | E8: 0.01 | F8: 0.022 | G8: 0.742 | H8: 1.126 | I8: 2.021 | J8: 1.666 | K8: 1.399 | L8: 1.232 | M8: 1.335 | N8: 1.161 | O8: 1.817 | P8: 1.112 | Q8: 1.135 | R8: 1.397 | S8: 1.777 | T8: 1.383 | U8: 0.896 | V8: 1.496 | W8: 2.675 | X8: 36.771 | Y8: 39.65 | Z8: 31.874 | AA8: =Z8*(1+Assumptions!$D$25) -> 35.69888 | AB8: =IF(X8<>"",X8*(1+Assumptions!$E$25),IF(AA8<>"",AA8*(1+Assumptions!$E$25),"")) -> 41.91894 | AC8: =IF(Y8<>"",Y8*(1+Assumptions!$F$25),IF(AB8<>"",AB8*(1+Assumptions!$F$25),"")) -> 45.201 | AD8: =IF(Z8<>"",Z8*(1+Assumptions!$G$25),IF(AC8<>"",AC8*(1+Assumptions!$G$25),"")) -> 36.33636 | AE8: =IF(AA8<>"",AA8*(1+Assumptions!$H$25),IF(AD8<>"",AD8*(1+Assumptions!$H$25),"")) -> 40.696723 | AF8: =IF(AB8<>"",AB8*(1+Assumptions!$I$25),IF(AE8<>"",AE8*(1+Assumptions!$I$25),"")) -> 46.949213 | AG8: =IF(AC8<>"",AC8*(1+Assumptions!$J$25),IF(AF8<>"",AF8*(1+Assumptions!$J$25),"")) -> 50.62512 | AH8: =IF(AD8<>"",AD8*(1+Assumptions!$K$25),IF(AG8<>"",AG8*(1+Assumptions!$K$25),"")) -> 40.696723
A9: Revenue (total) | B9: =SUM(B6,B7,B8) -> 61.891 | C9: =SUM(C6,C7,C8) -> 135.223 | D9: =SUM(D6,D7,D8) -> 87.45 | E9: =SUM(E6,E7,E8) -> 92.665 | F9: =SUM(F6,F7,F8) -> 78.782 | G9: =SUM(G6,G7,G8) -> 136.015 | H9: =SUM(H6,H7,H8) -> 101.009 | I9: =SUM(I6,I7,I8) -> 122.008 | ... AH9: =SUM(AH6,AH7,AH8) -> 520.87255

Sheet KPI GP by Bus Unit
A1: AeroVironment, Inc. - KPI GP by Bus Unit
A2: USD mm
A4: Fiscal quarter end | B4: 1/25/20 | C4: 4/30/20 | D4: 8/1/20 | E4: 10/31/20 | F4: 1/30/21 | G4: 4/30/21 | H4: 7/31/21 | I4: 10/30/21 | J4: 1/29/22 | K4: 4/30/22 | L4: 7/30/22 | M4: 10/29/22 | N4: 1/28/23 | O4: 4/30/23 | P4: 7/29/23 | Q4: 10/28/23 | R4: 1/27/24 | S4: 4/30/24 | T4: 7/27/24 | U4: 10/26/24 | V4: 1/25/25 | W4: 4/30/25 | X4: 8/2/25 | Y4: 11/1/25 | Z4: 1/31/26
A5: Key Performance Indicators
A6: Unmanned Systems (UMS) Gross Margin | P6: 50.426 | Q6: 65.613 | R6: 50.05 | S6: 44.435 | T6: 67.233 | U6: 41.363 | V6: 29.418 | W6: 49.112
A7: Loitering Munitions Systems (LMS) Gross Margin | P7: 12.323 | Q7: 9.345 | R7: 17.98 | S7: 28.576 | T7: 13.272 | U7: 30.157 | V7: 33.008 | W7: 52.117
A8: MacCready Works (MW) Gross Margin | P8: 5.308 | Q8: 3.604 | R8: 3.294 | S8: 6.526 | T8: 4.675 | U8: 5.838 | V8: 4.476 | W8: 7.372
A9: Gross Profit | B9: 23.496 | C9: 53.168 | D9: 35.411 | E9: 40.851 | F9: 28.641 | G9: 59.655 | H9: 28.723 | I9: 42.455 | J9: 21.436 | K9: 48.622 | L9: 33.714 | M9: 25.89 | N9: 45.51 | O9: 68.4 | P9: 65.66 | Q9: 75.35 | R9: 67.287 | S9: 75.634 | T9: 81.467 | U9: 73.638 | V9: 63.199 | W9: 100.332 | X9: 95.118 | Y9: 104.105 | Z9: 98.794

Sheet KPI GP by Product
A1: AeroVironment, Inc. - KPI GP by Product
A2: USD mm
A4: Fiscal quarter end | B4: 1/25/20 | C4: 4/30/20 | D4: 8/1/20 | E4: 10/31/20 | F4: 1/30/21 | G4: 4/30/21 | H4: 7/31/21 | I4: 10/30/21 | J4: 1/29/22 | K4: 4/30/22 | L4: 7/30/22 | M4: 10/29/22 | N4: 1/28/23 | O4: 4/30/23 | P4: 7/29/23 | Q4: 10/28/23 | R4: 1/27/24 | S4: 4/30/24 | T4: 7/27/24 | U4: 10/26/24 | V4: 1/25/25 | W4: 4/30/25 | X4: 8/2/25 | Y4: 11/1/25 | Z4: 1/31/26
A5: Key Performance Indicators
A6: Small Unmanned Aircraft Systems (SUAS) Gross Margin | D6: 27.483 | E6: 29.695 | F6: 22.017 | G6: 39.867 | H6: 16.92 | I6: 27.754 | J6: 8.656 | K6: 30.429 | L6: 21.296 | M6: 12.319 | N6: 32.937 | O6: 54.819
A7: Tactical Missile Systems (TMS) Gross Margin | D7: 1.92 | E7: 5.943 | F7: 4.889 | G7: 13.924 | H7: 5.989 | I7: 6.222 | J7: 5.209 | K7: 7.065 | L7: 7.746 | M7: 12.636 | N7: 7.841 | O7: 14.513
A8: Medium Unmanned Aircraft Systems (MUAS) Gross Margin | G8: 2.965 | H8: 3.181 | I8: 2.223 | J8: 0.335 | K8: 0.416 | L8: -1.073 | M8: -6.884 | N8: -2.008 | O8: -14.39
A9: High Altitude Pseudo-Satellite Unmanned Aircraft Systems (HAPS) Gross Margin | G9: 3.461 | H9: 3.174 | I9: 3.944 | J9: 3.173 | K9: 5.242 | L9: 3.324 | M9: 3.001 | N9: 2.733
A10: Other Segment Gross Margin | G10: -0.562 | H10: -0.541 | I10: 2.312 | J10: 4.063 | K10: 5.469 | L10: 2.421 | M10: 4.818 | N10: 4.007
A11: All Other Segment Gross Margin | D11: 6.008 | E11: 5.213 | F11: 1.735 | G11: 2.899 | H11: 2.633 | I11: 6.256 | J11: 7.236 | K11: 10.712 | L11: 5.745 | M11: 7.819 | N11: 6.74 | O11: 13.458
A12: Gross Profit | B12: 23.496 | C12: 53.168 | D12: 35.411 | E12: 40.851 | F12: 28.641 | G12: 59.655 | H12: 28.723 | I12: 42.455 | J12: 21.436 | K12: 48.622 | L12: 33.714 | M12: 25.89 | N12: 45.51 | O12: 68.4 | P12: 65.66 | Q12: 75.35 | R12: 67.287 | S12: 75.634 | T12: 81.467 | U12: 73.638 | V12: 63.199 | W12: 100.332 | X12: 95.118 | Y12: 104.105 | Z12: 98.794

Sheet KPI Adj EBITDA
A1: AeroVironment, Inc. - KPI Adj EBITDA
A2: USD mm
A4: Fiscal quarter end | B4: 1/25/20 | C4: 4/30/20 | D4: 8/1/20 | E4: 10/31/20 | F4: 1/30/21 | G4: 4/30/21 | H4: 7/31/21 | I4: 10/30/21 | J4: 1/29/22 | K4: 4/30/22 | L4: 7/30/22 | M4: 10/29/22 | N4: 1/28/23 | O4: 4/30/23 | P4: 7/29/23 | Q4: 10/28/23 | R4: 1/27/24 | S4: 4/30/24 | T4: 7/27/24 | U4: 10/26/24 | V4: 1/25/25 | W4: 4/30/25 | X4: 8/2/25 | Y4: 11/1/25 | Z4: 1/31/26
A5: Key Performance Indicators
A6: Autonomous Systems and Space (AxS) Adjusted EBITDA | T6: 37.188 | U6: 25.862 | V6: 21.766 | X6: 52.393 | Y6: 51.438 | Z6: 46.167
A7: Cyber and Directed Energy (SCDE) Adjusted EBITDA | X7: 4.162 | Y7: -6.48 | Z7: -1.691
A8: Operating Income | B8: -1.108 | C8: 21.295 | D8: 12.297 | E8: 13.898 | F8: -0.642 | G8: 17.76 | H8: -12.113 | I8: 3.339 | J8: -14.126 | K8: 13.013 | L8: -3.274 | M8: -14.314 | N8: 4.607 | O8: -165.682 | P8: 26.367 | Q8: 25.178 | R8: 14.334 | S8: 5.945 | T8: 23.059 | U8: 7.006 | V8: -3.087 | W8: 13.817 | X8: -69.272 | Y8: -30.224 | Z8: -268.44

Sheet KPI Adj Op Inc
A1: AeroVironment, Inc. - KPI Adj Op Inc
A2: USD mm
A4: Fiscal quarter end | B4: 1/25/20 | C4: 4/30/20 | D4: 8/1/20 | E4: 10/31/20 | F4: 1/30/21 | G4: 4/30/21 | H4: 7/31/21 | I4: 10/30/21 | J4: 1/29/22 | K4: 4/30/22 | L4: 7/30/22 | M4: 10/29/22 | N4: 1/28/23 | O4: 4/30/23 | P4: 7/29/23 | Q4: 10/28/23 | R4: 1/27/24 | S4: 4/30/24 | T4: 7/27/24 | U4: 10/26/24 | V4: 1/25/25 | W4: 4/30/25 | X4: 8/2/25 | Y4: 11/1/25 | Z4: 1/31/26
A5: Key Performance Indicators
A6: Unmanned Systems (UMS) Adjusted Income From Operations | L6: 2.951 | M6: -9.528 | N6: 11.792 | O6: 25.354 | P6: 25.024 | Q6: 38.603 | R6: 20.417 | S6: 9.078
A7: Loitering Munitions Systems (LMS) Adjusted Income From Operations | L7: -1.031 | M7: 2.004 | N7: -0.129 | O7: 7.229 | P7: 4.91 | Q7: -1.122 | R7: 7.562 | S7: 12.712
A8: MacCready Works (MW) Adjusted Income From Operations | L8: 2.102 | M8: 1.621 | N8: 0.376 | O8: -0.435 | P8: 0.272 | Q8: -6.797 | R8: -8.103 | S8: -10.078
A9: Operating Income | B9: -1.108 | C9: 21.295 | D9: 12.297 | E9: 13.898 | F9: -0.642 | G9: 17.76 | H9: -12.113 | I9: 3.339 | J9: -14.126 | K9: 13.013 | L9: -3.274 | M9: -14.314 | N9: 4.607 | O9: -165.682 | P9: 26.367 | Q9: 25.178 | R9: 14.334 | S9: 5.945 | T9: 23.059 | U9: 7.006 | V9: -3.087 | W9: 13.817 | X9: -69.272 | Y9: -30.224 | Z9: -268.44

Sheet KPI Funded Backlog
A1: AeroVironment, Inc. - KPI Funded Backlog
A2: USD mm
A4: Fiscal quarter end | B4: 1/25/20 | C4: 4/30/20 | D4: 8/1/20 | E4: 10/31/20 | F4: 1/30/21 | G4: 4/30/21 | H4: 7/31/21 | I4: 10/30/21 | J4: 1/29/22 | K4: 4/30/22 | L4: 7/30/22 | M4: 10/29/22 | N4: 1/28/23 | O4: 4/30/23 | P4: 7/29/23 | Q4: 10/28/23 | R4: 1/27/24 | S4: 4/30/24 | T4: 7/27/24 | U4: 10/26/24 | V4: 1/25/25 | W4: 4/30/25 | X4: 8/2/25 | Y4: 11/1/25 | Z4: 1/31/26
A5: Key Performance Indicators
A6: Funded Backlog | B6: 126 | C6: 208.1 | D6: 154.4 | E6: 130.6 | F6: 103.9 | G6: 211.8 | H6: 257.7 | I6: 252 | J6: 226.3 | K6: 210.8 | L6: 203.9 | M6: 293.1 | N6: 413.9 | O6: 424.1 | P6: 539.7 | Q6: 487 | R6: 462.8 | S6: 400.2 | T6: 372.9 | U6: 467.1 | V6: 763.5 | W6: 726.6 | X6: 1066.4 | Y6: 1092.5 | Z6: 1120.7

Sheet Assumptions
A1: AeroVironment, Inc. - Sales Forecast Assumptions
A2: Hardcoded growth inputs in blue. Q4 FY2026 (4/30/26) is SEQUENTIAL off Q3 FY2026 and calibrated to the FY2026 revenue guidance midpoint of $1.90B; the year-ago quarter (4/30/25) predates the BlueHalo acquisition (closed 5/1/25), so year-over-year growth is invalid across that boundary. FY2027-FY2028 use year-over-year growth off clean post-BlueHalo comparables. Income statement revenue is driven by the KPI Rev by Type tab; other KPI cuts are independent cross-checks.
A4: KPI Sheet | B4: Revenue Driver | C4: Formula Logic | D4: 4/30/26 | E4: 8/1/26 | F4: 10/31/26 | G4: 1/30/27 | H4: 4/30/27 | I4: 7/31/27 | J4: 10/30/27 | K4: 1/29/28
A5: KPI Rev by Segment | B5: Autonomous Systems and Space (AxS) Revenue | C5: YoY growth / sequential fallback | D5: 0.48 | E5: 0.18 | F5: 0.18 | G5: 0.18 | H5: 0.18 | I5: 0.12 | J5: 0.12 | K5: 0.12
A6: KPI Rev by Segment | B6: Cyber and Directed Energy (SCDE) Revenue | C6: YoY growth / sequential fallback | D6: 0.18 | E6: 0.05 | F6: 0.05 | G6: 0.05 | H6: 0.05 | I6: 0.06 | J6: 0.06 | K6: 0.06
A7: KPI Rev by Segment | B7: Other / not disclosed revenue | C7: YoY growth / sequential fallback | D7: 0 | E7: 0 | F7: 0 | G7: 0 | H7: 0 | I7: 0 | J7: 0 | K7: 0
A8: KPI Rev by Geography | B8: Domestic Revenue | C8: YoY growth / sequential fallback | D8: 0.5 | E8: 0.16 | F8: 0.16 | G8: 0.16 | H8: 0.16 | I8: 0.12 | J8: 0.12 | K8: 0.12
A9: KPI Rev by Geography | B9: International Revenue | C9: YoY growth / sequential fallback | D9: 0.24 | E9: 0.16 | F9: 0.16 | G9: 0.16 | H9: 0.16 | I9: 0.12 | J9: 0.12 | K9: 0.12
A10: KPI Rev by Bus Unit | B10: Unmanned Systems (UMS) Revenue | C10: YoY growth / sequential fallback | D10: 0 | E10: 0 | F10: 0 | G10: 0 | H10: 0 | I10: 0 | J10: 0 | K10: 0
A11: KPI Rev by Bus Unit | B11: Loitering Munitions Systems (LMS) Revenue | C11: YoY growth / sequential fallback | D11: 0 | E11: 0 | F11: 0 | G11: 0 | H11: 0 | I11: 0 | J11: 0 | K11: 0
A12: KPI Rev by Bus Unit | B12: MacCready Works (MW) Revenue | C12: YoY growth / sequential fallback | D12: 0 | E12: 0 | F12: 0 | G12: 0 | H12: 0 | I12: 0 | J12: 0 | K12: 0
A13: KPI Rev by Bus Unit | B13: Other / not disclosed revenue | C13: YoY growth / sequential fallback | D13: 0.385 | E13: 0.16 | F13: 0.16 | G13: 0.16 | H13: 0.16 | I13: 0.12 | J13: 0.12 | K13: 0.12
A14: KPI Rev by Product | B14: Small Unmanned Aircraft Systems (SUAS) Revenue | C14: YoY growth / sequential fallback | D14: 0 | E14: 0 | F14: 0 | G14: 0 | H14: 0 | I14: 0 | J14: 0 | K14: 0
A15: KPI Rev by Product | B15: Tactical Missile Systems (TMS) Revenue | C15: YoY growth / sequential fallback | D15: 0 | E15: 0 | F15: 0 | G15: 0 | H15: 0 | I15: 0 | J15: 0 | K15: 0
A16: KPI Rev by Product | B16: Medium Unmanned Aircraft Systems (MUAS) Revenue | C16: YoY growth / sequential fallback | D16: 0 | E16: 0 | F16: 0 | G16: 0 | H16: 0 | I16: 0 | J16: 0 | K16: 0
... A25: KPI Rev by Contract | B25: Time and Materials (T&M) Revenue | C25: YoY growth / sequential fallback | D25: 0.12 | E25: 0.14 | F25: 0.14 | G25: 0.14 | H25: 0.14 | I25: 0.12 | J25: 0.12 | K25: 0.12
A28: FY2026 Guidance Bridge (USD mm)
A29: 9M FY2026 revenue (actual) | D29: =SUM('IS - Quarterly'!AR8:AT8) -> 1335.229
A30: Q4 FY2026 revenue (model, anchored) | D30: ='IS - Quarterly'!AU8 -> 564.75985
A31: FY2026 revenue (model) | D31: =D29+D30 -> 1899.9889
A32: FY2026 guidance - low | D32: 1850
A33: FY2026 guidance - midpoint | D33: 1900
A34: FY2026 guidance - high | D34: 1950
A35: Model vs guidance midpoint | D35: =D31/D33-1 -> -5.8668421e-06
A37: FY2027 revenue (model) | D37: =SUM('IS - Quarterly'!AV8:AY8) -> 2203.5108
A38: FY2027 growth vs FY2026 model | D38: =D37/D31-1 -> 0.15974933
A41: Income Statement Drivers - Probable / Base Case (GAAP)
D42: 4/30/26 | E42: 8/1/26 | F42: 10/31/26 | G42: 1/30/27 | H42: 4/30/27 | I42: 7/31/27 | J42: 10/30/27 | K42: 1/29/28
A43: Product gross margin % | D43: 0.3 | E43: 0.31 | F43: 0.31 | G43: 0.31 | H43: 0.31 | I43: 0.325 | J43: 0.325 | K43: 0.325
A44: Contract services gross margin % | D44: 0.165 | E44: 0.175 | F44: 0.175 | G44: 0.175 | H44: 0.175 | I44: 0.185 | J44: 0.185 | K44: 0.185
A45: SG&A % of revenue | D45: 0.2 | E45: 0.185 | F45: 0.185 | G45: 0.185 | H45: 0.185 | I45: 0.17 | J45: 0.17 | K45: 0.17
A46: R&D % of revenue | D46: 0.065 | E46: 0.065 | F46: 0.065 | G46: 0.065 | H46: 0.065 | I46: 0.065 | J46: 0.065 | K46: 0.065
A47: Goodwill impairment ($mm) | D47: 0 | E47: 0 | F47: 0 | G47: 0 | H47: 0 | I47: 0 | J47: 0 | K47: 0
A48: Other operating expense, net ($mm) | D48: 0 | E48: 0 | F48: 0 | G48: 0 | H48: 0 | I48: 0 | J48: 0 | K48: 0
A49: Net interest income/(expense) ($mm) | D49: 2 | E49: 2 | F49: 2 | G49: 2 | H49: 2 | I49: 2 | J49: 2 | K49: 2
A50: Other income/(expense), net ($mm) | D50: 0 | E50: 0 | F50: 0 | G50: 0 | H50: 0 | I50: 0 | J50: 0 | K50: 0
A51: Equity method income/(loss) ($mm) | D51: 0 | E51: 0 | F51: 0 | G51: 0 | H51: 0 | I51: 0 | J51: 0 | K51: 0
A52: Effective tax rate % | D52: 0.17 | E52: 0.17 | F52: 0.17 | G52: 0.17 | H52: 0.17 | I52: 0.17 | J52: 0.17 | K52: 0.17
A53: Diluted shares (mm) | D53: 50 | E53: 50.1 | F53: 50.2 | G53: 50.3 | H53: 50.4 | I53: 50.5 | J53: 50.6 | K53: 50.7
A54: Basic shares (mm) | D54: 49.8 | E54: 49.9 | F54: 50 | G54: 50.1 | H54: 50.2 | I54: 50.3 | J54: 50.4 | K54: 50.5
A55: Noncontrolling interest ($mm) | D55: 0 | E55: 0 | F55: 0 | G55: 0 | H55: 0 | I55: 0 | J55: 0 | K55: 0
A57: Forecast P&L Summary (model, GAAP)
A58: FY2026 operating income | D58: =SUM('IS - Quarterly'!AR23:AU23) -> -371.04253
A59: FY2026 net income (AVAV) | D59: =SUM('IS - Quarterly'!AR36:AU36) -> -329.21442
A60: FY2026 diluted EPS | D60: =SUM('IS - Quarterly'!AR36:AU36)/AVERAGE('IS - Quarterly'!AR39:AU39) -> -6.7067844
A61: FY2027 operating income | D61: =SUM('IS - Quarterly'!AV23:AY23) -> 47.234248
A62: FY2027 operating margin | D62: =D61/D37 -> 0.021435905
A63: FY2027 net income (AVAV) | D63: =SUM('IS - Quarterly'!AV36:AY36) -> 45.844426
A64: FY2027 diluted EPS | D64: =SUM('IS - Quarterly'!AV36:AY36)/AVERAGE('IS - Quarterly'!AV39:AY39) -> 0.91232688
A66: Damodaran Possible / Plausible / Probable Screen
A67: Driver | B67: Possible (range) | C67: Plausible (range) | D67: Probable (used) | E67: Basis
A68: Product gross margin | B68: 26% - 38% | C68: 29% - 34% | D68: 30% - 32.5% | E68: Q3 FY26 GAAP 28%; scale + commercialization, capped below legacy 40%+
A69: Contract services gross margin | B69: 10% - 22% | C69: 15% - 19% | D69: 16.5% - 18.5% | E69: Q3 FY26 GAAP 16%; integration matures, SCAR drag laps
A70: SG&A % of revenue | B70: 16% - 26% | C70: 17% - 21% | D70: 20% to 17% (declining) | E70: GAAP carries intangible amortization; operating leverage
A71: R&D % of revenue | B71: 5% - 9% | C71: 6% - 7.5% | D71: 6.5% | E71: Management guide 6-7%
A72: Effective tax rate | B72: 10% - 23% | C72: 15% - 20% | D72: 17% | E72: Defense peer norm; R&D credits
A73: Net interest / quarter | B73: ($8) - +$6 | C73: ($2) - +$5 | D73: +$2 | E73: Low-coupon converts vs cash+investments; recent +$4
A74: Diluted shares | B74: 49.7 - 55.0 | C74: 50.0 - 51.0 | D74: 50.0 - 50.7 | E74: Post-raise base; SBC creep; no buyback
A75: Goodwill impairment | B75: $0 - >$150 | C75: $0 | D75: $0 | E75: Base case excludes non-recurring; SCAR already impaired
A76: Total revenue FY26 | B76: $1.80 - $2.00B | C76: $1.85 - $1.95B | D76: $1.90B | E76: Company guidance midpoint (see bridge above)
A77: Total revenue FY27 | B77: $2.00 - $2.45B | C77: $2.10 - $2.30B | D77: $2.20B | E77: Backlog $1.1B, book-to-bill 1.6, capacity adds; pre-guidance
