Workbook

Sheet Dashboard
A1: AWS 7-Year Forecast Summary -- Capacity-Driven
A3: Model Output | B3: Value | D3: Sanity Check | E3: 2025A | F3: 2026E | G3: 2027E | H3: 2032E
A4: 2026E Sales | B4: =AWS!E4 -> 162028.37 | D4: Energized GW | E4: =AWS!D6 -> 23.1 | F4: =AWS!E6 -> 29.084252 | G4: =AWS!F6 -> 35.815021 | H4: =AWS!K6 -> 63.007329
A5: 2032E Sales | B5: =AWS!K4 -> 351013.83 | D5: Revenue Growth | E5: =AWS!D5 -> 0.1968184 | F5: =AWS!E5 -> 0.25871717 | G5: =AWS!F5 -> 0.23142315 | H5: =AWS!K5 -> 0.081891939
A6: 2026E EBIT | B6: =AWS!E10 -> 47007.051 | D6: EBIT Margin | E6: =AWS!D11 -> 0.35429015 | F6: =AWS!E11 -> 0.29011618 | G6: =AWS!F11 -> 0.24973179 | H6: =AWS!K11 -> 0.26025347
A7: 2032E EBIT | B7: =AWS!K10 -> 91352.568 | D7: Capex / Sales | E7: =AWS!D14/AWS!D4 -> 0.74962905 | F7: =AWS!E14/AWS!E4 -> 0.93810733 | G7: =AWS!F14/AWS!F4 -> 0.87708095 | H7: =AWS!K14/AWS!K4 -> 0.35326243
A8: 2026E FCF | B8: =AWS!E19 -> -79693.008 | D8: FCF Margin | E8: =AWS!D20 -> -0.31702327 | F8: =AWS!E20 -> -0.49184602 | G8: =AWS!F20 -> -0.41577521 | H8: =AWS!K20 -> 0.1323844
A9: 2032E FCF | B9: =AWS!K19 -> 46468.755
A10: 2026E Capex | B10: =AWS!E14 -> 152000
A12: Interpretation
A13: Causation runs forward and every unit is anchored to disclosed 2025 data. Capex builds gigawatts of power at $25.4B per GW, the actual 2025 build cost ($96.5B of AWS capex for 3.8 GW). Energized capacity times revenue per GW of $5,571mm (the 2025 figure) gives revenue, so growth comes from capacity, not a chosen rate. 2026 capex anchors to Amazon guided $200B times a 76% AWS share. EBIT equals revenue times EBITDA margin minus a depreciation schedule built on the 5-year server life Amazon adopted in 2025, which is why EBIT margin compresses into the low 20s during the ramp and recovers as capex normalizes. This runs below management 35% margin framing because it forces the shorter-life depreciation through EBIT.

Sheet AWS Assumptions
A1: AWS Value-Driven Assumptions (capacity-anchored)
A3: Metric | B3: 2023A | C3: 2024A | D3: 2025A | E3: 2026E | F3: 2027E | G3: 2028E | H3: 2029E | I3: 2030E | J3: 2031E | K3: 2032E
A4: Revenue per GW ($mm/yr) | D4: 5571 | E4: 5571 | F4: 5571 | G4: 5571 | H4: 5571 | I4: 5571 | J4: 5571 | K4: 5571
A5: Capex per GW ($mm/GW) | D5: 25394 | E5: 25400 | F5: 26000 | G5: 26000 | H5: 26000 | I5: 26000 | J5: 26000 | K5: 26000
A6: EBITDA Margin | D6: 0.521 | E6: 0.52 | F6: 0.525 | G6: 0.53 | H6: 0.535 | I6: 0.54 | J6: 0.545 | K6: 0.55
A7: D&A on Prior-Year Net PPE | E7: 0.14 | F7: 0.14 | G7: 0.14 | H7: 0.14 | I7: 0.14 | J7: 0.14 | K7: 0.14
A8: D&A on Current-Year Capex | E8: 0.07 | F8: 0.07 | G8: 0.07 | H8: 0.07 | I8: 0.07 | J8: 0.07 | K8: 0.07
A9: Tax Rate | B9: 0.24 | C9: 0.24 | D9: 0.24 | E9: 0.24 | F9: 0.24 | G9: 0.24 | H9: 0.24 | I9: 0.24 | J9: 0.24 | K9: 0.24
A10: NOWC / Sales | B10: 0.02 | C10: 0.02 | D10: 0.02 | E10: 0.02 | F10: 0.02 | G10: 0.02 | H10: 0.022 | I10: 0.024 | J10: 0.025 | K10: 0.025
A12: Capex Build
A13: Amazon Total Company Capex ($mm) | E13: 200000
A14: AWS Allocation Share | E14: 0.76
A15: AWS Capex ($mm) | E15: =E13*E14 -> 152000 | F15: 175000 | G15: 165000 | H15: 150000 | I15: 138000 | J15: 130000 | K15: 124000
A17: Key Input | B17: Value | C17: Source / Comment | D17: Tag
A18: Revenue method | B18: Energized GW x revenue per GW | C18: Revenue equals operational power capacity times revenue per gigawatt. Capacity is the binding constraint AWS discloses. | D18: Inference
A19: Energized GW end-2025 | B19: 23.1 GW | C19: Derived: AWS added 3.8 GW in 2025 and revenue rose from $107.6B to $128.7B, which pins the installed energized base. | D19: Inference
A20: Revenue per GW | B20: $5,571mm/GW/yr | C20: 2025 AWS revenue / energized GW. Held flat, so revenue growth comes only from added capacity, not price. | D20: Inference
A21: Capex per GW | B21: $25,394mm/GW | C21: 2025 AWS capex $96.5B / 3.8 GW added. The all-in build cost of a gigawatt including land, power, and silicon. | D21: Fact
A22: 2025 AWS capex | B22: $96,496mm | C22: AWS net property and equipment additions, 2025. 73% of Amazon total capex of $131.8B. | D22: Fact
A23: 2026 total capex | B23: $200,000mm | C23: Amazon 2026 company-wide capex guidance from the Feb 2026 earnings call. | D23: Guidance
A24: AWS share 2026 | B24: 76% | C24: Jassy: 2026 capex is predominantly AWS. 2025 share was 73%. | D24: Estimate
A25: Out-year AWS capex | B25: $175B to $124B | C25: Tapers as the buildout matures. Out-years are unguided and carry the most uncertainty. | D25: Estimate
A26: Server useful life | B26: 5 years | C26: Amazon cut server and networking life from 6 to 5 years effective Jan 1, 2025, raising depreciation. | D26: Fact
A27: D&A schedule | B27: 14% prior PPE + 7% current capex | C27: Ties 2025 actual D&A of $21.45B. Current-capex rate lifted from 6% to reflect the 5-year server life. | D27: Inference
A28: EBITDA margin | B28: 52.1% in 2025 | C28: (AWS EBIT + D&A) / revenue. EBIT margin falls out after the depreciation schedule. | D28: Fact
A29: Capacity check | B29: Doubles by ~2030 | C29: Capex-implied build reaches 36 GW by end-2027 (+55%), short of Jassy double-by-2027. Model is conservative vs guidance. | D29: Inference

Sheet AWS
A1: AWS Segment Operating Model -- Capacity-Driven ($mm) | L1: Source Notes
E2: =1-YEARFRAC(DATE(2025,12,31), DATE(2026,6,18), 1) -> 0.5369863 | F2: =E2+1 -> 1.5369863 | G2: =F2+1 -> 2.5369863 | H2: =G2+1 -> 3.5369863 | I2: =H2+1 -> 4.5369863 | J2: =I2+1 -> 5.5369863 | K2: =J2+1 -> 6.5369863 | L2: Revenue = energized power capacity (GW) x revenue per GW. Capacity is the disclosed binding constraint.
A3: Metric | B3: 2023A | C3: 2024A | D3: 2025A | E3: 2026E | F3: 2027E | G3: 2028E | H3: 2029E | I3: 2030E | J3: 2031E | K3: 2032E | L3: Q1 2026 AWS sales grew 28%, used to support 2026 revenue growth assumption.
A4: Sales | B4: 90757 | C4: 107556 | D4: 128725 | E4: =E6*'AWS Assumptions'!E4 -> 162028.37 | F4: =F6*'AWS Assumptions'!F4 -> 199525.48 | G4: =G6*'AWS Assumptions'!G4 -> 234879.91 | H4: =H6*'AWS Assumptions'!H4 -> 267020.29 | I4: =I6*'AWS Assumptions'!I4 -> 296589.44 | J4: =J6*'AWS Assumptions'!J4 -> 324444.44 | K4: =K6*'AWS Assumptions'!K4 -> 351013.83 | L4: Energized GW end-2025 (23.1) derived from the disclosed 3.8 GW added and the 2024-2025 revenue step.
A5: % Growth | C5: =C4/B4-1 -> 0.18509867 | D5: =D4/C4-1 -> 0.1968184 | E5: =E4/D4-1 -> 0.25871717 | F5: =F4/E4-1 -> 0.23142315 | G5: =G4/F4-1 -> 0.17719252 | H5: =H4/G4-1 -> 0.13683752 | I5: =I4/H4-1 -> 0.11073748 | J5: =J4/I4-1 -> 0.093917705 | K5: =K4/J4-1 -> 0.081891939
A6: Energized Power Capacity (GW) | B6: 16.4 | C6: 19.4 | D6: 23.1 | E6: =D6+E7 -> 29.084252 | F6: =E6+F7 -> 35.815021 | G6: =F6+G7 -> 42.161175 | H6: =G6+H7 -> 47.930406 | I6: =H6+I7 -> 53.238098 | J6: =I6+J7 -> 58.238098 | K6: =J6+K7 -> 63.007329 | L6: GW added = capex / capex per GW. 2025 build cost = $96.5B / 3.8 GW = $25.4B per GW.
A7: GW Added in Year | C7: 3 | D7: 3.8 | E7: =E14/E15 -> 5.984252 | F7: =F14/F15 -> 6.7307692 | G7: =G14/G15 -> 6.3461538 | H7: =H14/H15 -> 5.7692308 | I7: =I14/I15 -> 5.3076923 | J7: =J14/J15 -> 5 | K7: =K14/K15 -> 4.7692308
A8: Revenue per GW ($mm) | D8: ='AWS Assumptions'!D4 -> 5571 | E8: ='AWS Assumptions'!E4 -> 5571 | F8: ='AWS Assumptions'!F4 -> 5571 | G8: ='AWS Assumptions'!G4 -> 5571 | H8: ='AWS Assumptions'!H4 -> 5571 | I8: ='AWS Assumptions'!I4 -> 5571 | J8: ='AWS Assumptions'!J4 -> 5571 | K8: ='AWS Assumptions'!K4 -> 5571 | L8: 2026 capex = Amazon $200B guidance x 76% AWS share. Out-years taper and are unguided.
A9: EBITDA Margin | D9: ='AWS Assumptions'!D6 -> 0.521 | E9: ='AWS Assumptions'!E6 -> 0.52 | F9: ='AWS Assumptions'!F6 -> 0.525 | G9: ='AWS Assumptions'!G6 -> 0.53 | H9: ='AWS Assumptions'!H6 -> 0.535 | I9: ='AWS Assumptions'!I6 -> 0.54 | J9: ='AWS Assumptions'!J6 -> 0.545 | K9: ='AWS Assumptions'!K6 -> 0.55
A10: EBIT | B10: 24631 | C10: 39834 | D10: 45606 | E10: =E4*'AWS Assumptions'!E6-E13 -> 47007.051 | F10: =F4*'AWS Assumptions'!F6-F13 -> 49827.857 | G10: =G4*'AWS Assumptions'!G6-G13 -> 53452.551 | H10: =H4*'AWS Assumptions'!H6-H13 -> 59716.789 | I10: =I4*'AWS Assumptions'!I6-I13 -> 68498.702 | J10: =J4*'AWS Assumptions'!J6-J13 -> 79234.968 | K10: =K4*'AWS Assumptions'!K6-K13 -> 91352.568 | L10: EBIT = revenue x EBITDA margin minus D&A. The 5-year server life makes D&A heavier than the prior model.
A11: EBIT Margin | B11: =B10/B4 -> 0.27139504 | C11: =C10/C4 -> 0.37035591 | D11: =D10/D4 -> 0.35429015 | E11: =E10/E4 -> 0.29011618 | F11: =F10/F4 -> 0.24973179 | G11: =G10/G4 -> 0.22757396 | H11: =H10/H4 -> 0.22364139 | I11: =I10/I4 -> 0.23095462 | ... K11: =K10/K4 -> 0.26025347
A12: NOPAT | B12: =B10*(1-'AWS Assumptions'!B9) -> 18719.56 | C12: =C10*(1-'AWS Assumptions'!C9) -> 30273.84 | D12: =D10*(1-'AWS Assumptions'!D9) -> 34660.56 | E12: =E10*(1-'AWS Assumptions'!E9) -> 35725.359 | F12: =F10*(1-'AWS Assumptions'!F9) -> 37869.171 | G12: =G10*(1-'AWS Assumptions'!G9) -> 40623.939 | H12: =H10*(1-'AWS Assumptions'!H9) -> 45384.759 | I12: =I10*(1-'AWS Assumptions'!I9) -> 52059.014 | ... K12: =K10*(1-'AWS Assumptions'!K9) -> 69427.951 | L12: Historical AWS sales, EBIT, D&A, PPE, capex from Amazon 2025 10-K.
A13: D&A | B13: 12531 | C13: 13320 | D13: 21450 | E13: ='AWS Assumptions'!E7*D16+'AWS Assumptions'!E8*E14 -> 37247.7 | F13: ='AWS Assumptions'!F7*E16+'AWS Assumptions'!F8*F14 -> 54923.022 | G13: ='AWS Assumptions'!G7*F16+'AWS Assumptions'!G8*G14 -> 71033.799 | H13: ='AWS Assumptions'!H7*G16+'AWS Assumptions'!H8*H14 -> 83139.067 | I13: ='AWS Assumptions'!I7*H16+'AWS Assumptions'!I8*I14 -> 91659.598 | J13: ='AWS Assumptions'!J7*I16+'AWS Assumptions'!J8*J14 -> 97587.254 | K13: ='AWS Assumptions'!K7*J16+'AWS Assumptions'!K8*K14 -> 101705.04
A14: Capex ($mm) | B14: 24843 | C14: 53267 | D14: 96496 | E14: ='AWS Assumptions'!E15 -> 152000 | F14: ='AWS Assumptions'!F15 -> 175000 | G14: ='AWS Assumptions'!G15 -> 165000 | H14: ='AWS Assumptions'!H15 -> 150000 | I14: ='AWS Assumptions'!I15 -> 138000 | J14: ='AWS Assumptions'!J15 -> 130000 | K14: ='AWS Assumptions'!K15 -> 124000
A15: Capex per GW ($mm) | C15: =C14/C7 -> 17755.667 | D15: =D14/D7 -> 25393.684 | E15: ='AWS Assumptions'!E5 -> 25400 | F15: ='AWS Assumptions'!F5 -> 26000 | G15: ='AWS Assumptions'!G5 -> 26000 | H15: ='AWS Assumptions'!H5 -> 26000 | I15: ='AWS Assumptions'!I5 -> 26000 | J15: ='AWS Assumptions'!J5 -> 26000 | K15: ='AWS Assumptions'!K5 -> 26000
A16: Net PPE | B16: 72701 | C16: 110683 | D16: 190055 | E16: =D16+E14-E13 -> 304807.3 | F16: =E16+F14-F13 -> 424884.28 | G16: =F16+G14-G13 -> 518850.48 | H16: =G16+H14-H13 -> 585711.41 | I16: =H16+I14-I13 -> 632051.81 | J16: =I16+J14-J13 -> 664464.56 | K16: =J16+K14-K13 -> 686759.52
A17: NOWC | B17: =B4*'AWS Assumptions'!B10 -> 1815.14 | C17: =C4*'AWS Assumptions'!C10 -> 2151.12 | D17: =D4*'AWS Assumptions'!D10 -> 2574.5 | E17: =E4*'AWS Assumptions'!E10 -> 3240.5674 | F17: =F4*'AWS Assumptions'!F10 -> 3990.5097 | G17: =G4*'AWS Assumptions'!G10 -> 4697.5981 | H17: =H4*'AWS Assumptions'!H10 -> 5874.4464 | I17: =I4*'AWS Assumptions'!I10 -> 7118.1467 | ... K17: =K4*'AWS Assumptions'!K10 -> 8775.3457
A18: Investment in NOWC | C18: =C17-B17 -> 335.98 | D18: =D17-C17 -> 423.38 | E18: =E17-D17 -> 666.06735 | F18: =F17-E17 -> 749.94231 | G18: =G17-F17 -> 707.08846 | H18: =H17-G17 -> 1176.8483 | I18: =I17-H17 -> 1243.7003 | J18: =J17-I17 -> 992.96444 | K18: =K17-J17 -> 664.23462
A19: Unlevered FCF | B19: =B12+B13-B14 -> 6407.56 | C19: =C12+C13-C14-C18 -> -10009.14 | D19: =D12+D13-D14-D18 -> -40808.82 | E19: =E12+E13-E14-E18 -> -79693.008 | F19: =F12+F13-F14-F18 -> -82957.749 | G19: =G12+G13-G14-G18 -> -54049.351 | H19: =H12+H13-H14-H18 -> -22653.022 | I19: =I12+I13-I14-I18 -> 4474.9112 | J19: =J12+J13-J14-J18 -> 26812.865 | K19: =K12+K13-K14-K18 -> 46468.755
A20: FCF Margin | B20: =B19/B4 -> 0.070601276 | C20: =C19/C4 -> -0.093059801 | D20: =D19/D4 -> -0.31702327 | E20: =E19/E4 -> -0.49184602 | F20: =F19/F4 -> -0.41577521 | G20: =G19/G4 -> -0.23011483 | H20: =H19/H4 -> -0.084836332 | I20: =I19/I4 -> 0.015087898 | ... K20: =K19/K4 -> 0.1323844
A21: Disc FCF | E21: =E19/(1+$B$23)^E2 -> -76089.145 | F21: =F19/(1+$B$23)^F2 -> -72666.283 | G21: =G19/(1+$B$23)^G2 -> -43435.014 | H21: =H19/(1+$B$23)^H2 -> -16701.256 | I21: =I19/(1+$B$23)^I2 -> 3026.7804 | J21: =J19/(1+$B$23)^J2 -> 16638.464 | K21: =K19/(1+$B$23)^K2 -> 26454.803
A23: Disc | B23: 0.09
A24: EV/EBIT Exit | B24: 18
A25: Disc TV | B25: =(B24*K10)/(1+B23)^K2 -> 936131.28
A26: EV | B26: =B25+SUM(E21:K21) -> 773359.63

Sheet Online Retail
A1: Amazon Online Retail Ecosystem Forecast ($mm)
E2: =1-YEARFRAC(DATE(2025,12,31), DATE(2026,6,18), 1) -> 0.5369863 | F2: =E2+1 -> 1.5369863 | G2: =F2+1 -> 2.5369863 | H2: =G2+1 -> 3.5369863 | I2: =H2+1 -> 4.5369863 | J2: =I2+1 -> 5.5369863 | K2: =J2+1 -> 6.5369863
A3: Metric | B3: 2023A | C3: 2024A | D3: 2025A | E3: 2026E | F3: 2027E | G3: 2028E | H3: 2029E | I3: 2030E | J3: 2031E | K3: 2032E
A4: Online Stores Revenue | B4: 231872 | C4: 247029 | D4: 269287 | E4: =D4*(1+E42) -> 289483.52 | F4: =E4*(1+F42) -> 309747.37 | G4: =F4*(1+G42) -> 329880.95 | H4: =G4*(1+H42) -> 349673.81 | I4: =H4*(1+I42) -> 368905.87 | J4: =I4*(1+J42) -> 387351.16 | K4: =J4*(1+K42) -> 404781.96
A5: Third-Party Seller Services | B5: 140053 | C5: 156146 | D5: 172162 | E5: =D5*(1+E43) -> 191099.82 | F5: =E5*(1+F43) -> 210209.8 | G5: =F5*(1+G43) -> 229128.68 | H5: =G5*(1+H43) -> 247458.98 | I5: =H5*(1+I43) -> 264781.11 | J5: =I5*(1+J43) -> 281991.88 | K5: =J5*(1+K43) -> 298911.39
A6: Advertising Services | B6: 46906 | C6: 56214 | D6: 68635 | E6: =D6*(1+E44) -> 80646.125 | F6: =E6*(1+F44) -> 92743.044 | G6: =F6*(1+G44) -> 104799.64 | H6: =G6*(1+H44) -> 116327.6 | I6: =H6*(1+I44) -> 126797.08 | J6: =I6*(1+J44) -> 136940.85 | K6: =J6*(1+K44) -> 146526.71
A7: Subscription Services | B7: 40209 | C7: 44374 | D7: 49619 | E7: =D7*(1+E45) -> 54084.71 | F7: =E7*(1+F45) -> 58411.487 | G7: =F7*(1+G45) -> 62500.291 | H7: =G7*(1+H45) -> 66562.81 | I7: =H7*(1+I45) -> 70556.578 | J7: =I7*(1+J45) -> 74437.19 | K7: =J7*(1+K45) -> 78159.05
A8: Total Online Retail Revenue | B8: =SUM(B4:B7) -> 459040 | C8: =SUM(C4:C7) -> 503763 | D8: =SUM(D4:D7) -> 559703 | E8: =SUM(E4:E7) -> 615314.18 | F8: =SUM(F4:F7) -> 671111.7 | G8: =SUM(G4:G7) -> 726309.57 | H8: =SUM(H4:H7) -> 780023.2 | I8: =SUM(I4:I7) -> 831040.64 | ... K8: =SUM(K4:K7) -> 928379.11
A9: % Growth | C9: =C8/B8-1 -> 0.097427239 | D9: =D8/C8-1 -> 0.11104428 | E9: =E8/D8-1 -> 0.099358374 | F9: =F8/E8-1 -> 0.090681356 | G9: =G8/F8-1 -> 0.082248396 | H9: =H8/G8-1 -> 0.073954184 | I9: =I8/H8-1 -> 0.06540503 | J9: =J8/I8-1 -> 0.059781004 | K9: =K8/J8-1 -> 0.054112517
A10: EBIT Margin, Segment Proxy | B10: =B11/B8 -> 0.026622952 | C10: =C11/C8 -> 0.057088353 | D10: =D11/D8 -> 0.061405781 | E10: =E46 -> 0.065 | F10: =F46 -> 0.07 | G10: =G46 -> 0.074 | H10: =H46 -> 0.077 | I10: =I46 -> 0.079 | J10: =J46 -> 0.081 | K10: =K46 -> 0.083
A11: EBIT, Segment Proxy | B11: 12221 | C11: 28759 | D11: 34369 | E11: =E8*E10 -> 39995.422 | F11: =F8*F10 -> 46977.819 | G11: =G8*G10 -> 53746.908 | H11: =H8*H10 -> 60061.786 | I11: =I8*I10 -> 65652.21 | J11: =J8*J10 -> 71338.408 | K11: =K8*K10 -> 77055.467
A12: Tax Rate | B12: =B47 -> 0.24 | C12: =C47 -> 0.24 | D12: =D47 -> 0.24 | E12: =E47 -> 0.24 | F12: =F47 -> 0.24 | G12: =G47 -> 0.24 | H12: =H47 -> 0.24 | I12: =I47 -> 0.24 | ... K12: =K47 -> 0.24
A13: NOPAT | B13: =B11*(1-B12) -> 9287.96 | C13: =C11*(1-C12) -> 21856.84 | D13: =D11*(1-D12) -> 26120.44 | E13: =E11*(1-E12) -> 30396.52 | F13: =F11*(1-F12) -> 35703.143 | G13: =G11*(1-G12) -> 40847.65 | H13: =H11*(1-H12) -> 45646.957 | I13: =I11*(1-I12) -> 49895.68 | ... K13: =K11*(1-K12) -> 58562.155
A14: D&A / Sales | B14: =B48 -> 0.035 | C14: =C48 -> 0.033 | D14: =D48 -> 0.032 | E14: =E48 -> 0.031 | F14: =F48 -> 0.03 | G14: =G48 -> 0.029 | H14: =H48 -> 0.028 | I14: =I48 -> 0.027 | ... K14: =K48 -> 0.025
A15: D&A | B15: =B8*B14 -> 16066.4 | C15: =C8*C14 -> 16624.179 | D15: =D8*D14 -> 17910.496 | E15: =E8*E14 -> 19074.74 | F15: =F8*F14 -> 20133.351 | G15: =G8*G14 -> 21062.977 | H15: =H8*H14 -> 21840.65 | I15: =I8*I14 -> 22438.097 | ... K15: =K8*K14 -> 23209.478
A16: Capex / Sales | B16: =B49 -> 0.05 | C16: =C49 -> 0.045 | D16: =D49 -> 0.04 | E16: =E49 -> 0.038 | F16: =F49 -> 0.036 | G16: =G49 -> 0.034 | H16: =H49 -> 0.033 | I16: =I49 -> 0.032 | ... K16: =K49 -> 0.03
A17: Capex | B17: =B8*B16 -> 22952 | C17: =C8*C16 -> 22669.335 | D17: =D8*D16 -> 22388.12 | E17: =E8*E16 -> 23381.939 | F17: =F8*F16 -> 24160.021 | G17: =G8*G16 -> 24694.525 | H17: =H8*H16 -> 25740.765 | I17: =I8*I16 -> 26593.3 | ... K17: =K8*K16 -> 27851.373
A18: NOWC / Sales | B18: =B50 -> -0.055 | C18: =C50 -> -0.054 | D18: =D50 -> -0.053 | E18: =E50 -> -0.052 | F18: =F50 -> -0.051 | G18: =G50 -> -0.05 | H18: =H50 -> -0.049 | I18: =I50 -> -0.048 | ... K18: =K50 -> -0.046
A19: NOWC | B19: =B8*B18 -> -25247.2 | C19: =C8*C18 -> -27203.202 | D19: =D8*D18 -> -29664.259 | E19: =E8*E18 -> -31996.337 | F19: =F8*F18 -> -34226.697 | G19: =G8*G18 -> -36315.478 | H19: =H8*H18 -> -38221.137 | I19: =I8*I18 -> -39889.951 | ... K19: =K8*K18 -> -42705.439
A20: Investment in NOWC | B20: 0 | C20: =C19-B19 -> -1956.002 | D20: =D19-C19 -> -2461.057 | E20: =E19-D19 -> -2332.0784 | F20: =F19-E19 -> -2230.3596 | G20: =G19-F19 -> -2088.7814 | H20: =H19-G19 -> -1905.6584 | I20: =I19-H19 -> -1668.8139 | J20: =J19-I19 -> -1503.9402 | K20: =K19-J19 -> -1311.5485
A21: Unlevered FCF | B21: =B13+B15-B17-B20 -> 2402.36 | C21: =C13+C15-C17-C20 -> 17767.686 | D21: =D13+D15-D17-D20 -> 24103.873 | E21: =E13+E15-E17-E20 -> 28421.4 | F21: =F13+F15-F17-F20 -> 33906.832 | G21: =G13+G15-G17-G20 -> 39304.883 | H21: =H13+H15-H17-H20 -> 43652.5 | I21: =I13+I15-I17-I20 -> 47409.291 | ... K21: =K13+K15-K17-K20 -> 55231.807
A22: FCF Margin | B22: =B21/B8 -> 0.0052334437 | C22: =C21/C8 -> 0.035269931 | D22: =D21/D8 -> 0.04306547 | E22: =E21/E8 -> 0.046190061 | F22: =F21/F8 -> 0.050523381 | G22: =G21/G8 -> 0.054115883 | H22: =H21/H8 -> 0.055963079 | I22: =I21/I8 -> 0.057048101 | ... K22: =K21/K8 -> 0.059492729
A23: Disc FCF | E23: =E21/(1+$B$25)^E2 -> 27270.768 | F23: =F21/(1+$B$25)^F2 -> 30124.189 | G23: =G21/(1+$B$25)^G2 -> 32333.365 | H23: =H21/(1+$B$25)^H2 -> 33249.855 | I23: =I21/(1+$B$25)^I2 -> 33436.463 | J23: =J21/(1+$B$25)^J2 -> 33511.882 | K23: =K21/(1+$B$25)^K2 -> 33396.321
A25: Disc | B25: 0.08
A26: EV/EBIT Exit | B26: 14
A27: Disc TV | B27: =(B26*K11)/(1+B25)^K2 -> 652290.21
A28: EV | B28: =B27+SUM(E23:K23) -> 875613.05
A41: Forecast Assumptions
A42: Online Stores Growth | E42: 0.075 | F42: 0.07 | G42: 0.065 | H42: 0.06 | I42: 0.055 | J42: 0.05 | K42: 0.045
A43: Third-Party Seller Services Growth | E43: 0.11 | F43: 0.1 | G43: 0.09 | H43: 0.08 | I43: 0.07 | J43: 0.065 | K43: 0.06
A44: Advertising Services Growth | E44: 0.175 | F44: 0.15 | G44: 0.13 | H44: 0.11 | I44: 0.09 | J44: 0.08 | K44: 0.07
A45: Subscription Services Growth | E45: 0.09 | F45: 0.08 | G45: 0.07 | H45: 0.065 | I45: 0.06 | J45: 0.055 | K45: 0.05
A46: EBIT Margin, Segment Proxy | E46: 0.065 | F46: 0.07 | G46: 0.074 | H46: 0.077 | I46: 0.079 | J46: 0.081 | K46: 0.083
A47: Tax Rate | B47: 0.24 | C47: 0.24 | D47: 0.24 | E47: 0.24 | F47: 0.24 | G47: 0.24 | H47: 0.24 | I47: 0.24 | J47: 0.24 | K47: 0.24
A48: D&A / Sales | B48: 0.035 | C48: 0.033 | D48: 0.032 | E48: 0.031 | F48: 0.03 | G48: 0.029 | H48: 0.028 | I48: 0.027 | J48: 0.026 | K48: 0.025
A49: Capex / Sales | B49: 0.05 | C49: 0.045 | D49: 0.04 | E49: 0.038 | F49: 0.036 | G49: 0.034 | H49: 0.033 | I49: 0.032 | J49: 0.031 | K49: 0.03
A50: NOWC / Sales | B50: -0.055 | C50: -0.054 | D50: -0.053 | E50: -0.052 | F50: -0.051 | G50: -0.05 | H50: -0.049 | I50: -0.048 | J50: -0.047 | K50: -0.046
