Workbook

Sheet 00 Control
A1: Cerebras Full Operating Model Template
A2: Units | B2: all values in $mm except operational drivers
B3: 2026 | C3: 2027 | D3: 2028 | E3: 2029 | F3: 2030 | G3: 2031
A4: Model Start Year | B4: 2026
A5: Model End Year | B5: 2031
A6: Tax Rate | B6: 0.21 | C6: 0.21 | D6: 0.21 | E6: 0.21 | F6: 0.21 | G6: 0.21
A7: Discount Rate | B7: 0.12 | C7: 0.12 | D7: 0.12 | E7: 0.12 | F7: 0.12 | G7: 0.12
A8: Terminal Growth Rate | B8: 0.03 | C8: 0.03 | D8: 0.03 | E8: 0.03 | F8: 0.03 | G8: 0.03
A9: Terminal EV / EBIT Multiple | B9: 20 | C9: 20 | D9: 20 | E9: 20 | F9: 20 | G9: 20
A10: Cash | B10: 1336.909 | C10: 1336.909 | D10: 1336.909 | E10: 1336.909 | F10: 1336.909 | G10: 1336.909
A11: Debt | B11: 261.822 | C11: 261.822 | D11: 261.822 | E11: 261.822 | F11: 261.822 | G11: 261.822
A12: Diluted Shares | B12: 190 | C12: 190 | D12: 190 | E12: 190 | F12: 190 | G12: 190
A13: Use Perpetuity TV? 1=yes | B13: 0 | C13: 0 | D13: 0 | E13: 0 | F13: 0 | G13: 0
A14: Scenario Selected | B14: 1 | C14: Base case = 1, downside = 2, upside = 3
A15: Notes | B15: Blue font = input. Green font = linked formula. Black font = calculation.

Sheet 01 Dashboard
A1: Dashboard
A2: Units | B2: summary
B3: 2026 | C3: 2027 | D3: 2028 | E3: 2029 | F3: 2030 | G3: 2031
A4: Metric | B4: 2031 | D4: Revenue | E4: Gross Profit | F4: EBIT | G4: FCF
A5: Revenue | B5: ='21 Income Statement'!G4 | D5: ='21 Income Statement'!G4 | E5: ='21 Income Statement'!G6 | F5: ='21 Income Statement'!G9 | G5: ='23 Cash Flow'!G10
A6: Gross Profit | B6: ='21 Income Statement'!G6
A7: Gross Margin | B7: ='21 Income Statement'!G7
A8: EBIT | B8: ='21 Income Statement'!G9
A9: EBIT Margin | B9: ='21 Income Statement'!G10
A10: Free Cash Flow | B10: ='23 Cash Flow'!G10
A11: Installed Base | B11: ='03 Revenue Build'!G8
A12: Enterprise Value | B12: ='24 DCF Valuation'!G14
A13: Equity Value | B13: ='24 DCF Valuation'!G17
A14: Implied Share Price | B14: ='24 DCF Valuation'!G19
A15: Check Status | B15: ='25 Checks'!G8

Sheet 02 Scenario Manager
A1: Scenario Manager
A2: Units | B2: scenario toggles and growth drivers
B3: 2026 | C3: 2027 | D3: 2028 | E3: 2029 | F3: 2030 | G3: 2031
A4: Downside Units Growth | B4: 0 | C4: 0 | D4: 0 | E4: 0 | F4: 0 | G4: 0
A5: Base Units Growth | B5: 0.45 | C5: 0.444 | D5: 0.37 | E5: 0.26 | F5: 0.189 | G5: 0.173
A6: Upside Units Growth | B6: 0 | C6: 0 | D6: 0 | E6: 0 | F6: 0 | G6: 0
A7: Downside ASP Growth | B7: 0 | C7: 0 | D7: 0 | E7: 0 | F7: 0 | G7: 0
A8: Base ASP Growth | B8: 0 | C8: 0.019 | D8: 0 | E8: 0.019 | F8: 0.019 | G8: 0.018
A9: Upside ASP Growth | B9: 0 | C9: 0 | D9: 0 | E9: 0 | F9: 0 | G9: 0
A10: Downside Cloud Rev / Installed CS3 Growth | B10: 0 | C10: 0 | D10: 0 | E10: 0 | F10: 0 | G10: 0
A11: Base Cloud Rev / Installed CS3 Growth | B11: 0 | C11: 0 | D11: 0 | E11: 0 | F11: 0 | G11: 0
A12: Upside Cloud Rev / Installed CS3 Growth | B12: 0 | C12: 0 | D12: 0 | E12: 0 | F12: 0 | G12: 0
A13: Downside Gross Margin Stress | B13: 0 | C13: 0 | D13: 0 | E13: 0 | F13: 0 | G13: 0
A14: Base Gross Margin Stress | B14: 0 | C14: 0 | D14: 0 | E14: 0 | F14: 0 | G14: 0
A15: Upside Gross Margin Stress | B15: 0 | C15: 0 | D15: 0 | E15: 0 | F15: 0 | G15: 0

Sheet 03 Revenue Build
A1: Revenue Build
A2: Units | B2: $mm except units
B3: 2026 | C3: 2027 | D3: 2028 | E3: 2029 | F3: 2030 | G3: 2031
A4: CS3 Systems Sold | B4: ='05 CS3 Systems'!B6 | C4: ='05 CS3 Systems'!C6 | D4: ='05 CS3 Systems'!D6 | E4: ='05 CS3 Systems'!E6 | F4: ='05 CS3 Systems'!F6 | G4: ='05 CS3 Systems'!G6
A5: Average Selling Price / CS3 | B5: ='05 CS3 Systems'!B8 | C5: ='05 CS3 Systems'!C8 | D5: ='05 CS3 Systems'!D8 | E5: ='05 CS3 Systems'!E8 | F5: ='05 CS3 Systems'!F8 | G5: ='05 CS3 Systems'!G8
A6: Hardware Revenue | B6: =B4*B5 | C6: =C4*C5 | D6: =D4*D5 | E6: =E4*E5 | F6: =F4*F5 | G6: =G4*G5
A7: Beginning Installed Base | B7: 285 | C7: =B8 | D7: =C8 | E7: =D8 | F7: =E8 | G7: =F8
A8: Ending Installed Base | B8: =B7+B4 | C8: =C7+C4 | D8: =D7+D4 | E8: =E7+E4 | F8: =F7+F4 | G8: =G7+G4
A9: Cloud Revenue | B9: ='07 Cloud Revenue'!B8 | C9: ='07 Cloud Revenue'!C8 | D9: ='07 Cloud Revenue'!D8 | E9: ='07 Cloud Revenue'!E8 | F9: ='07 Cloud Revenue'!F8 | G9: ='07 Cloud Revenue'!G8
A10: Services Revenue | B10: ='08 Services Support'!B7 | C10: ='08 Services Support'!C7 | D10: ='08 Services Support'!D7 | E10: ='08 Services Support'!E7 | F10: ='08 Services Support'!F7 | G10: ='08 Services Support'!G7
A11: Total Revenue | B11: =SUM(B6,B9,B10) | C11: =SUM(C6,C9,C10) | D11: =SUM(D6,D9,D10) | E11: =SUM(E6,E9,E10) | F11: =SUM(F6,F9,F10) | G11: =SUM(G6,G9,G10)

Sheet 04 Installed Base
A1: Installed Base and Utilization
A2: Units | B2: units and %
B3: 2026 | C3: 2027 | D3: 2028 | E3: 2029 | F3: 2030 | G3: 2031
A4: Beginning CS3 Installed Base | B4: 285 | C4: =B7 | D4: =C7 | E4: =D7 | F4: =E7 | G4: =F7
A5: New CS3 Systems | B5: ='05 CS3 Systems'!B6 | C5: ='05 CS3 Systems'!C6 | D5: ='05 CS3 Systems'!D6 | E5: ='05 CS3 Systems'!E6 | F5: ='05 CS3 Systems'!F6 | G5: ='05 CS3 Systems'!G6
A6: Retired CS3 Systems | B6: 0 | C6: 0 | D6: 0 | E6: 0 | F6: 0 | G6: 0
A7: Ending CS3 Installed Base | B7: =B4+B5-B6 | C7: =C4+C5-C6 | D7: =D4+D5-D6 | E7: =E4+E5-E6 | F7: =F4+F5-F6 | G7: =G4+G5-G6
A8: Average Installed Base | B8: =AVERAGE(B4,B7) | C8: =AVERAGE(C4,C7) | D8: =AVERAGE(D4,D7) | E8: =AVERAGE(E4,E7) | F8: =AVERAGE(F4,F7) | G8: =AVERAGE(G4,G7)
A9: Cloud Utilization | B9: 0.105 | C9: 0.105 | D9: 0.105 | E9: 0.105 | F9: 0.105 | G9: 0.105
A10: Revenue / Active Cloud System | B10: 4.58 | C10: 4.3 | D10: 4.02 | E10: 3.79 | F10: 3.55 | G10: 3.34

Sheet 05 CS3 Systems
A1: CS3 Systems Build
A2: Units | B2: units and $mm
B3: 2026 | C3: 2027 | D3: 2028 | E3: 2029 | F3: 2030 | G3: 2031
A4: Clusters Sold | B4: ='06 CS3 Clusters'!B9 | C4: ='06 CS3 Clusters'!C9 | D4: ='06 CS3 Clusters'!D9 | E4: ='06 CS3 Clusters'!E9 | F4: ='06 CS3 Clusters'!F9 | G4: ='06 CS3 Clusters'!G9
A5: CS3 per Cluster | B5: 11.5 | C5: 11.5 | D5: 11.7 | E5: 12 | F5: 11.8 | G5: 12
A6: CS3 Systems Sold | B6: =B4*B5 | C6: =C4*C5 | D6: =D4*D5 | E6: =E4*E5 | F6: =F4*F5 | G6: =G4*G5
A7: Unit Growth | B7: 0 | C7: =IFERROR(C6/B6-1,0) | D7: =IFERROR(D6/C6-1,0) | E7: =IFERROR(E6/D6-1,0) | F7: =IFERROR(F6/E6-1,0) | G7: =IFERROR(G6/F6-1,0)
A8: ASP per CS3 | B8: 2.6 | C8: 2.65 | D8: 2.65 | E8: 2.7 | F8: 2.75 | G8: 2.8
A9: ASP Growth | B9: 0 | C9: =IFERROR(C8/B8-1,0) | D9: =IFERROR(D8/C8-1,0) | E9: =IFERROR(E8/D8-1,0) | F9: =IFERROR(F8/E8-1,0) | G9: =IFERROR(G8/F8-1,0)
A10: Hardware Revenue | B10: =B6*B8 | C10: =C6*C8 | D10: =D6*D8 | E10: =E6*E8 | F10: =F6*F8 | G10: =G6*G8

Sheet 06 CS3 Clusters
A1: CS3 Cluster Demand Build
A2: Units | B2: units
B3: 2026 | C3: 2027 | D3: 2028 | E3: 2029 | F3: 2030 | G3: 2031
A4: Enterprise AI Clusters | B4: 8 | C4: 12 | D4: 16 | E4: 20 | F4: 24 | G4: 28
A5: National Lab / Research Clusters | B5: 2 | C5: 3 | D5: 4 | E5: 5 | F5: 6 | G5: 7
A6: Sovereign AI Clusters | B6: 5 | C6: 7 | D6: 9 | E6: 11 | F6: 13 | G6: 15
A7: Hyperscaler Clusters | B7: 2 | C7: 3 | D7: 4 | E7: 5 | F7: 6 | G7: 7
A8: Other Clusters | B8: 1 | C8: 1 | D8: 2 | E8: 2 | F8: 3 | G8: 3
A9: Total Clusters | B9: =SUM(B4:B8) | C9: =SUM(C4:C8) | D9: =SUM(D4:D8) | E9: =SUM(E4:E8) | F9: =SUM(F4:F8) | G9: =SUM(G4:G8)

Sheet 07 Cloud Revenue
A1: Cloud Revenue Build
A2: Units | B2: $mm except utilization
B3: 2026 | C3: 2027 | D3: 2028 | E3: 2029 | F3: 2030 | G3: 2031
A4: Average Installed Base | B4: ='04 Installed Base'!B8 | C4: ='04 Installed Base'!C8 | D4: ='04 Installed Base'!D8 | E4: ='04 Installed Base'!E8 | F4: ='04 Installed Base'!F8 | G4: ='04 Installed Base'!G8
A5: Cloud Utilization | B5: ='04 Installed Base'!B9 | C5: ='04 Installed Base'!C9 | D5: ='04 Installed Base'!D9 | E5: ='04 Installed Base'!E9 | F5: ='04 Installed Base'!F9 | G5: ='04 Installed Base'!G9
A6: Active Cloud Systems | B6: =B4*B5 | C6: =C4*C5 | D6: =D4*D5 | E6: =E4*E5 | F6: =F4*F5 | G6: =G4*G5
A7: Revenue / Active Cloud System | B7: ='04 Installed Base'!B10 | C7: ='04 Installed Base'!C10 | D7: ='04 Installed Base'!D10 | E7: ='04 Installed Base'!E10 | F7: ='04 Installed Base'!F10 | G7: ='04 Installed Base'!G10
A8: Cloud Revenue | B8: =B6*B7 | C8: =C6*C7 | D8: =D6*D7 | E8: =E6*E7 | F8: =F6*F7 | G8: =G6*G7
A9: Cloud Revenue Growth | B9: =0 | C9: =IFERROR(C8/B8-1,0) | D9: =IFERROR(D8/C8-1,0) | E9: =IFERROR(E8/D8-1,0) | F9: =IFERROR(F8/E8-1,0) | G9: =IFERROR(G8/F8-1,0)
A10: Cloud Gross Margin | B10: 0.33 | C10: 0.36 | D10: 0.39 | E10: 0.41 | F10: 0.43 | G10: 0.45

Sheet 08 Services Support
A1: Services and Support Revenue
A2: Units | B2: $mm
B3: 2026 | C3: 2027 | D3: 2028 | E3: 2029 | F3: 2030 | G3: 2031
A4: Hardware Revenue | B4: ='03 Revenue Build'!B6 | C4: ='03 Revenue Build'!C6 | D4: ='03 Revenue Build'!D6 | E4: ='03 Revenue Build'!E6 | F4: ='03 Revenue Build'!F6 | G4: ='03 Revenue Build'!G6
A5: Service Attach Rate | B5: 0.85 | C5: 0.85 | D5: 0.85 | E5: 0.85 | F5: 0.85 | G5: 0.85
A6: Annual Service Fee % of ASP | B6: 0.12 | C6: 0.104 | D6: 0.096 | E6: 0.091 | F6: 0.091 | G6: 0.089
A7: Service Revenue | B7: =B4*B5*B6 | C7: =C4*C5*C6 | D7: =D4*D5*D6 | E7: =E4*E5*E6 | F7: =F4*F5*F6 | G7: =G4*G5*G6
A8: Support Cost % of Service Revenue | B8: 0.4 | C8: 0.4 | D8: 0.4 | E8: 0.4 | F8: 0.4 | G8: 0.4
A9: Support Cost | B9: =B7*B8 | C9: =C7*C8 | D9: =D7*D8 | E9: =E7*E8 | F9: =F7*F8 | G9: =G7*G8
A10: Service Gross Profit | B10: =B7-B9 | C10: =C7-C9 | D10: =D7-D9 | E10: =E7-E9 | F10: =F7-F9 | G10: =G7-G9

Sheet 09 Wafer Die
A1: Wafer and Die Build
A2: Units | B2: units and $mm
B3: 2026 | C3: 2027 | D3: 2028 | E3: 2029 | F3: 2030 | G3: 2031
A4: CS3 Systems Sold | B4: ='03 Revenue Build'!B4 | C4: ='03 Revenue Build'!C4 | D4: ='03 Revenue Build'!D4 | E4: ='03 Revenue Build'!E4 | F4: ='03 Revenue Build'!F4 | G4: ='03 Revenue Build'!G4
A5: Wafers per CS3 | B5: 1 | C5: 1 | D5: 1 | E5: 1 | F5: 1 | G5: 1
A6: Gross Wafers Required | B6: =B4*B5 | C6: =C4*C5 | D6: =D4*D5 | E6: =E4*E5 | F6: =F4*F5 | G6: =G4*G5
A7: Wafer Cost per Wafer | B7: 0.4176 | C7: 0.4277 | D7: 0.4275 | E7: 0.4279 | F7: 0.4281 | G7: 0.429
A8: Gross Wafer Cost | B8: =B6*B7 | C8: =C6*C7 | D8: =D6*D7 | E8: =E6*E7 | F8: =F6*F7 | G8: =G6*G7
A9: Yield | B9: 0.72 | C9: 0.74 | D9: 0.75 | E9: 0.76 | F9: 0.77 | G9: 0.78
A10: Net Wafer Cost (total) | B10: =B8/B9 | C10: =C8/C9 | D10: =D8/D9 | E10: =E8/E9 | F10: =F8/F9 | G10: =G8/G9
A11: Chip Design Allocation / CS3 | B11: 0.12 | C11: 0.112 | D11: 0.105 | E11: 0.099 | F11: 0.094 | G11: 0.09
A12: Design Allocation (total) | B12: =B11*B4 | C12: =C11*C4 | D12: =D11*D4 | E12: =E11*E4 | F12: =F11*F4 | G12: =G11*G4
A13: Total Wafer and Die Cost | B13: =B10+B12 | C13: =C10+C12 | D13: =D10+D12 | E13: =E10+E12 | F13: =F10+F12 | G13: =G10+G12

Sheet 10 Yield Packaging
A1: Yield and Packaging Build
A2: Units | B2: $mm
B3: 2026 | C3: 2027 | D3: 2028 | E3: 2029 | F3: 2030 | G3: 2031
A4: CS3 Systems Sold | B4: ='03 Revenue Build'!B4 | C4: ='03 Revenue Build'!C4 | D4: ='03 Revenue Build'!D4 | E4: ='03 Revenue Build'!E4 | F4: ='03 Revenue Build'!F4 | G4: ='03 Revenue Build'!G4
A5: Advanced Packaging Cost / CS3 | B5: 0.1 | C5: 0.097 | D5: 0.094 | E5: 0.091 | F5: 0.088 | G5: 0.085
A6: Test Cost / CS3 | B6: 0.05 | C6: 0.048 | D6: 0.046 | E6: 0.044 | F6: 0.042 | G6: 0.04
A7: Scrap / Rework % of Hardware Revenue | B7: 0.005 | C7: 0.005 | D7: 0.005 | E7: 0.005 | F7: 0.005 | G7: 0.005
A8: Packaging Cost | B8: =B4*B5 | C8: =C4*C5 | D8: =D4*D5 | E8: =E4*E5 | F8: =F4*F5 | G8: =G4*G5
A9: Test Cost | B9: =B4*B6 | C9: =C4*C6 | D9: =D4*D6 | E9: =E4*E6 | F9: =F4*F6 | G9: =G4*G6
A10: Scrap / Rework Cost | B10: ='03 Revenue Build'!B6*B7 | C10: ='03 Revenue Build'!C6*C7 | D10: ='03 Revenue Build'!D6*D7 | E10: ='03 Revenue Build'!E6*E7 | F10: ='03 Revenue Build'!F6*F7 | G10: ='03 Revenue Build'!G6*G7
A11: Total Packaging and Test Cost | B11: =SUM(B8:B10) | C11: =SUM(C8:C10) | D11: =SUM(D8:D10) | E11: =SUM(E8:E10) | F11: =SUM(F8:F10) | G11: =SUM(G8:G10)

Sheet 11 MemoryX
A1: MemoryX Build
A2: Units | B2: $mm
B3: 2026 | C3: 2027 | D3: 2028 | E3: 2029 | F3: 2030 | G3: 2031
A4: CS3 Systems Sold | B4: ='03 Revenue Build'!B4 | C4: ='03 Revenue Build'!C4 | D4: ='03 Revenue Build'!D4 | E4: ='03 Revenue Build'!E4 | F4: ='03 Revenue Build'!F4 | G4: ='03 Revenue Build'!G4
A5: MemoryX Modules / CS3 | B5: 6 | C5: 6 | D5: 6 | E5: 6 | F5: 6 | G5: 6
A6: Cost / Module | B6: 0.019 | C6: 0.0184 | D6: 0.0178 | E6: 0.0172 | F6: 0.0166 | G6: 0.016
A7: Yield / Scrap Factor | B7: 0.05 | C7: 0.05 | D7: 0.05 | E7: 0.05 | F7: 0.05 | G7: 0.05
A8: Gross MemoryX Cost | B8: =B4*B5*B6 | C8: =C4*C5*C6 | D8: =D4*D5*D6 | E8: =E4*E5*E6 | F8: =F4*F5*F6 | G8: =G4*G5*G6
A9: Net MemoryX Cost | B9: =B8*(1+B7) | C9: =C8*(1+C7) | D9: =D8*(1+D7) | E9: =E8*(1+E7) | F9: =F8*(1+F7) | G9: =G8*(1+G7)

Sheet 12 SwarmX
A1: SwarmX Interconnect Build
A2: Units | B2: $mm
B3: 2026 | C3: 2027 | D3: 2028 | E3: 2029 | F3: 2030 | G3: 2031
A4: CS3 Systems Sold | B4: ='03 Revenue Build'!B4 | C4: ='03 Revenue Build'!C4 | D4: ='03 Revenue Build'!D4 | E4: ='03 Revenue Build'!E4 | F4: ='03 Revenue Build'!F4 | G4: ='03 Revenue Build'!G4
A5: SwarmX Units / CS3 | B5: 4 | C5: 4 | D5: 4 | E5: 4 | F5: 4 | G5: 4
A6: Cost / SwarmX Unit | B6: 0.02 | C6: 0.0192 | D6: 0.0184 | E6: 0.0176 | F6: 0.0168 | G6: 0.016
A7: Network Switch Cost / CS3 | B7: 0.06 | C7: 0.057 | D7: 0.054 | E7: 0.051 | F7: 0.048 | G7: 0.045
A8: Cables and Optics / CS3 | B8: 0.04 | C8: 0.038 | D8: 0.036 | E8: 0.034 | F8: 0.032 | G8: 0.03
A9: SwarmX Cost | B9: =B4*B5*B6 | C9: =C4*C5*C6 | D9: =D4*D5*D6 | E9: =E4*E5*E6 | F9: =F4*F5*F6 | G9: =G4*G5*G6
A10: Network Hardware Cost | B10: =B4*(B7+B8) | C10: =C4*(C7+C8) | D10: =D4*(D7+D8) | E10: =E4*(E7+E8) | F10: =F4*(F7+F8) | G10: =G4*(G7+G8)
A11: Total SwarmX Cost | B11: =SUM(B9:B10) | C11: =SUM(C9:C10) | D11: =SUM(D9:D10) | E11: =SUM(E9:E10) | F11: =SUM(F9:F10) | G11: =SUM(G9:G10)

Sheet 13 Hardware Other
A1: x86, Cooling, Power and Other Hardware
A2: Units | B2: $mm
B3: 2026 | C3: 2027 | D3: 2028 | E3: 2029 | F3: 2030 | G3: 2031
A4: CS3 Systems Sold | B4: ='03 Revenue Build'!B4 | C4: ='03 Revenue Build'!C4 | D4: ='03 Revenue Build'!D4 | E4: ='03 Revenue Build'!E4 | F4: ='03 Revenue Build'!F4 | G4: ='03 Revenue Build'!G4
A5: x86 Server Cost / CS3 | B5: 0.05 | C5: 0.048 | D5: 0.046 | E5: 0.044 | F5: 0.042 | G5: 0.04
A6: Cooling Cost / CS3 | B6: 0.04 | C6: 0.038 | D6: 0.036 | E6: 0.034 | F6: 0.032 | G6: 0.03
A7: Power Delivery Cost / CS3 | B7: 0.04 | C7: 0.038 | D7: 0.036 | E7: 0.034 | F7: 0.032 | G7: 0.03
A8: Rack / Chassis Cost / CS3 | B8: 0.03 | C8: 0.029 | D8: 0.028 | E8: 0.027 | F8: 0.026 | G8: 0.025
A9: Management Hardware / CS3 | B9: 0.02 | C9: 0.019 | D9: 0.018 | E9: 0.017 | F9: 0.016 | G9: 0.015
A10: Other Cost / CS3 | B10: 0.02 | C10: 0.019 | D10: 0.018 | E10: 0.017 | F10: 0.016 | G10: 0.015
A11: Total Other Hardware Cost | B11: =B4*SUM(B5:B10) | C11: =C4*SUM(C5:C10) | D11: =D4*SUM(D5:D10) | E11: =E4*SUM(E5:E10) | F11: =F4*SUM(F5:F10) | G11: =G4*SUM(G5:G10)

Sheet 14 COGS
A1: Cost of Goods Sold Build
A2: Units | B2: $mm
B3: 2026 | C3: 2027 | D3: 2028 | E3: 2029 | F3: 2030 | G3: 2031
A4: Hardware Revenue | B4: ='03 Revenue Build'!B6 | C4: ='03 Revenue Build'!C6 | D4: ='03 Revenue Build'!D6 | E4: ='03 Revenue Build'!E6 | F4: ='03 Revenue Build'!F6 | G4: ='03 Revenue Build'!G6
A5: Wafer and Die | B5: ='09 Wafer Die'!B13 | C5: ='09 Wafer Die'!C13 | D5: ='09 Wafer Die'!D13 | E5: ='09 Wafer Die'!E13 | F5: ='09 Wafer Die'!F13 | G5: ='09 Wafer Die'!G13
A6: Packaging and Test | B6: ='10 Yield Packaging'!B11 | C6: ='10 Yield Packaging'!C11 | D6: ='10 Yield Packaging'!D11 | E6: ='10 Yield Packaging'!E11 | F6: ='10 Yield Packaging'!F11 | G6: ='10 Yield Packaging'!G11
A7: MemoryX | B7: ='11 MemoryX'!B9 | C7: ='11 MemoryX'!C9 | D7: ='11 MemoryX'!D9 | E7: ='11 MemoryX'!E9 | F7: ='11 MemoryX'!F9 | G7: ='11 MemoryX'!G9
A8: SwarmX | B8: ='12 SwarmX'!B11 | C8: ='12 SwarmX'!C11 | D8: ='12 SwarmX'!D11 | E8: ='12 SwarmX'!E11 | F8: ='12 SwarmX'!F11 | G8: ='12 SwarmX'!G11
A9: Other Hardware | B9: ='13 Hardware Other'!B11 | C9: ='13 Hardware Other'!C11 | D9: ='13 Hardware Other'!D11 | E9: ='13 Hardware Other'!E11 | F9: ='13 Hardware Other'!F11 | G9: ='13 Hardware Other'!G11
A10: Direct Labor / CS3 | B10: 0.04 | C10: 0.038 | D10: 0.036 | E10: 0.034 | F10: 0.032 | G10: 0.03
A11: Mfg Overhead / CS3 | B11: 0.05 | C11: 0.048 | D11: 0.046 | E11: 0.044 | F11: 0.042 | G11: 0.04
A12: Warranty % Hardware Rev | B12: 0.015 | C12: 0.015 | D12: 0.015 | E12: 0.015 | F12: 0.015 | G12: 0.015
A13: Freight / CS3 | B13: 0.012 | C13: 0.011 | D13: 0.01 | E13: 0.01 | F13: 0.009 | G13: 0.009
A14: Hardware COGS | B14: =SUM(B5:B9)+'03 Revenue Build'!B4*(B10+B11+B13)+B4*B12 | C14: =SUM(C5:C9)+'03 Revenue Build'!C4*(C10+C11+C13)+C4*C12 | D14: =SUM(D5:D9)+'03 Revenue Build'!D4*(D10+D11+D13)+D4*D12 | E14: =SUM(E5:E9)+'03 Revenue Build'!E4*(E10+E11+E13)+E4*E12 | F14: =SUM(F5:F9)+'03 Revenue Build'!F4*(F10+F11+F13)+F4*F12 | G14: =SUM(G5:G9)+'03 Revenue Build'!G4*(G10+G11+G13)+G4*G12
A15: Cloud COGS | B15: ='07 Cloud Revenue'!B8*(1-'07 Cloud Revenue'!B10) | C15: ='07 Cloud Revenue'!C8*(1-'07 Cloud Revenue'!C10) | D15: ='07 Cloud Revenue'!D8*(1-'07 Cloud Revenue'!D10) | E15: ='07 Cloud Revenue'!E8*(1-'07 Cloud Revenue'!E10) | F15: ='07 Cloud Revenue'!F8*(1-'07 Cloud Revenue'!F10) | G15: ='07 Cloud Revenue'!G8*(1-'07 Cloud Revenue'!G10)
A16: Service COGS | B16: ='08 Services Support'!B9 | C16: ='08 Services Support'!C9 | D16: ='08 Services Support'!D9 | E16: ='08 Services Support'!E9 | F16: ='08 Services Support'!F9 | G16: ='08 Services Support'!G9
A17: Total COGS | B17: =B14+B15+B16 | C17: =C14+C15+C16 | D17: =D14+D15+D16 | E17: =E14+E15+E16 | F17: =F14+F15+F16 | G17: =G14+G15+G16
A18: Gross Profit | B18: ='03 Revenue Build'!B11-B17 | C18: ='03 Revenue Build'!C11-C17 | D18: ='03 Revenue Build'!D11-D17 | E18: ='03 Revenue Build'!E11-E17 | F18: ='03 Revenue Build'!F11-F17 | G18: ='03 Revenue Build'!G11-G17
A19: Gross Margin % | B19: =IFERROR(B18/'03 Revenue Build'!B11,0) | C19: =IFERROR(C18/'03 Revenue Build'!C11,0) | D19: =IFERROR(D18/'03 Revenue Build'!D11,0) | E19: =IFERROR(E18/'03 Revenue Build'!E11,0) | F19: =IFERROR(F18/'03 Revenue Build'!F11,0) | G19: =IFERROR(G18/'03 Revenue Build'!G11,0)

Sheet 15 Headcount
A1: Headcount Build
A2: Units | B2: employees and $mm
B3: 2026 | C3: 2027 | D3: 2028 | E3: 2029 | F3: 2030 | G3: 2031
A4: Engineering HC | B4: 620 | C4: 760 | D4: 910 | E4: 1060 | F4: 1210 | G4: 1360
A5: Manufacturing HC | B5: 120 | C5: 150 | D5: 185 | E5: 220 | F5: 255 | G5: 290
A6: Sales HC | B6: 110 | C6: 140 | D6: 175 | E6: 210 | F6: 245 | G6: 280
A7: G&A HC | B7: 90 | C7: 110 | D7: 135 | E7: 160 | F7: 185 | G7: 210
A8: Total HC | B8: =SUM(B4:B7) | C8: =SUM(C4:C7) | D8: =SUM(D4:D7) | E8: =SUM(E4:E7) | F8: =SUM(F4:F7) | G8: =SUM(G4:G7)
A9: Avg Comp / Engineering | B9: 0.26 | C9: 0.26 | D9: 0.26 | E9: 0.26 | F9: 0.26 | G9: 0.26
A10: Avg Comp / Manufacturing | B10: 0.15 | C10: 0.15 | D10: 0.15 | E10: 0.15 | F10: 0.15 | G10: 0.15
A11: Avg Comp / Sales | B11: 0.24 | C11: 0.24 | D11: 0.24 | E11: 0.24 | F11: 0.24 | G11: 0.24
A12: Avg Comp / G&A | B12: 0.23 | C12: 0.23 | D12: 0.23 | E12: 0.23 | F12: 0.23 | G12: 0.23
A13: Cash Compensation | B13: =B4*B9+B5*B10+B6*B11+B7*B12 | C13: =C4*C9+C5*C10+C6*C11+C7*C12 | D13: =D4*D9+D5*D10+D6*D11+D7*D12 | E13: =E4*E9+E5*E10+E6*E11+E7*E12 | F13: =F4*F9+F5*F10+F6*F11+F7*F12 | G13: =G4*G9+G5*G10+G6*G11+G7*G12
A14: Stock Based Compensation % Revenue | B14: 0.09 | C14: 0.08 | D14: 0.07 | E14: 0.065 | F14: 0.06 | G14: 0.055
A15: Stock Based Compensation | B15: ='03 Revenue Build'!B11*B14 | C15: ='03 Revenue Build'!C11*C14 | D15: ='03 Revenue Build'!D11*D14 | E15: ='03 Revenue Build'!E11*E14 | F15: ='03 Revenue Build'!F11*F14 | G15: ='03 Revenue Build'!G11*G14

Sheet 16 R&D Teams
A1: Research and Development by Team
A2: Units | B2: $mm
B3: 2026 | C3: 2027 | D3: 2028 | E3: 2029 | F3: 2030 | G3: 2031
A4: Chip Design | B4: 95 | C4: 112 | D4: 130 | E4: 150 | F4: 170 | G4: 192
A5: Compiler | B5: 34 | C5: 41 | D5: 48 | E5: 56 | F5: 64 | G5: 72
A6: Software Platform | B6: 55 | C6: 66 | D6: 78 | E6: 92 | F6: 106 | G6: 120
A7: MemoryX | B7: 16 | C7: 19 | D7: 22 | E7: 25 | F7: 28 | G7: 31
A8: SwarmX | B8: 16 | C8: 19 | D8: 22 | E8: 25 | F8: 28 | G8: 31
A9: Cooling | B9: 10 | C9: 12 | D9: 14 | E9: 16 | F9: 18 | G9: 20
A10: Power Delivery | B10: 10 | C10: 12 | D10: 14 | E10: 16 | F10: 18 | G10: 20
A11: AI Model / Customer Engineering | B11: 40 | C11: 50 | D11: 62 | E11: 76 | F11: 90 | G11: 105
A12: Other R&D | B12: 24 | C12: 29 | D12: 35 | E12: 44 | F12: 53 | G12: 64
A13: Total R&D | B13: =SUM(B4:B12) | C13: =SUM(C4:C12) | D13: =SUM(D4:D12) | E13: =SUM(E4:E12) | F13: =SUM(F4:F12) | G13: =SUM(G4:G12)
A14: R&D % Revenue | B14: =IFERROR(B13/'03 Revenue Build'!B11,0) | C14: =IFERROR(C13/'03 Revenue Build'!C11,0) | D14: =IFERROR(D13/'03 Revenue Build'!D11,0) | E14: =IFERROR(E13/'03 Revenue Build'!E11,0) | F14: =IFERROR(F13/'03 Revenue Build'!F11,0) | G14: =IFERROR(G13/'03 Revenue Build'!G11,0)

Sheet 17 OpEx
A1: Operating Expense Build
A2: Units | B2: $mm
B3: 2026 | C3: 2027 | D3: 2028 | E3: 2029 | F3: 2030 | G3: 2031
A4: Revenue | B4: ='03 Revenue Build'!B11 | C4: ='03 Revenue Build'!C11 | D4: ='03 Revenue Build'!D11 | E4: ='03 Revenue Build'!E11 | F4: ='03 Revenue Build'!F11 | G4: ='03 Revenue Build'!G11
A5: R&D | B5: ='16 R&D Teams'!B13 | C5: ='16 R&D Teams'!C13 | D5: ='16 R&D Teams'!D13 | E5: ='16 R&D Teams'!E13 | F5: ='16 R&D Teams'!F13 | G5: ='16 R&D Teams'!G13
A6: Sales and Marketing | B6: 70 | C6: 88 | D6: 108 | E6: 130 | F6: 155 | G6: 180
A7: General and Administrative | B7: 55 | C7: 66 | D7: 78 | E7: 92 | F7: 110 | G7: 130
A8: Facilities | B8: 12 | C8: 15 | D8: 18 | E8: 22 | F8: 26 | G8: 30
A9: Other OpEx | B9: 8 | C9: 10 | D9: 12 | E9: 14 | F9: 16 | G9: 18
A10: Stock Based Compensation | B10: ='15 Headcount'!B15 | C10: ='15 Headcount'!C15 | D10: ='15 Headcount'!D15 | E10: ='15 Headcount'!E15 | F10: ='15 Headcount'!F15 | G10: ='15 Headcount'!G15
A11: Total OpEx | B11: =SUM(B5:B10) | C11: =SUM(C5:C10) | D11: =SUM(D5:D10) | E11: =SUM(E5:E10) | F11: =SUM(F5:F10) | G11: =SUM(G5:G10)
A12: OpEx % Revenue | B12: =IFERROR(B11/B4,0) | C12: =IFERROR(C11/C4,0) | D12: =IFERROR(D11/D4,0) | E12: =IFERROR(E11/E4,0) | F12: =IFERROR(F11/F4,0) | G12: =IFERROR(G11/G4,0)

Sheet 18 CapEx
A1: Capital Expenditure Build
A2: Units | B2: $mm
B3: 2026 | C3: 2027 | D3: 2028 | E3: 2029 | F3: 2030 | G3: 2031
A4: Revenue | B4: ='03 Revenue Build'!B11 | C4: ='03 Revenue Build'!C11 | D4: ='03 Revenue Build'!D11 | E4: ='03 Revenue Build'!E11 | F4: ='03 Revenue Build'!F11 | G4: ='03 Revenue Build'!G11
A5: Manufacturing CapEx % Revenue | B5: 0.05 | C5: 0.045 | D5: 0.04 | E5: 0.035 | F5: 0.03 | G5: 0.028
A6: Cloud Infrastructure CapEx % Cloud Revenue | B6: 1.2 | C6: 0.9 | D6: 0.7 | E6: 0.55 | F6: 0.45 | G6: 0.4
A7: Facilities CapEx | B7: 40 | C7: 45 | D7: 50 | E7: 55 | F7: 60 | G7: 65
A8: Capitalized Software | B8: 20 | C8: 24 | D8: 28 | E8: 32 | F8: 36 | G8: 40
A9: Other CapEx | B9: 15 | C9: 18 | D9: 20 | E9: 22 | F9: 24 | G9: 26
A10: Total CapEx | B10: =B4*B5+'07 Cloud Revenue'!B8*B6+SUM(B7:B9) | C10: =C4*C5+'07 Cloud Revenue'!C8*C6+SUM(C7:C9) | D10: =D4*D5+'07 Cloud Revenue'!D8*D6+SUM(D7:D9) | E10: =E4*E5+'07 Cloud Revenue'!E8*E6+SUM(E7:E9) | F10: =F4*F5+'07 Cloud Revenue'!F8*F6+SUM(F7:F9) | G10: =G4*G5+'07 Cloud Revenue'!G8*G6+SUM(G7:G9)

Sheet 19 Depreciation
A1: Depreciation Schedule
A2: Units | B2: $mm
B3: 2026 | C3: 2027 | D3: 2028 | E3: 2029 | F3: 2030 | G3: 2031
A4: Beginning PP&E | B4: 686.346 | C4: =B8 | D4: =C8 | E4: =D8 | F4: =E8 | G4: =F8
A5: CapEx | B5: ='18 CapEx'!B10 | C5: ='18 CapEx'!C10 | D5: ='18 CapEx'!D10 | E5: ='18 CapEx'!E10 | F5: ='18 CapEx'!F10 | G5: ='18 CapEx'!G10
A6: Depreciation Rate | B6: 0.18 | C6: 0.18 | D6: 0.18 | E6: 0.18 | F6: 0.18 | G6: 0.18
A7: Depreciation | B7: =AVERAGE(B4,B4+B5)*B6 | C7: =AVERAGE(C4,C4+C5)*C6 | D7: =AVERAGE(D4,D4+D5)*D6 | E7: =AVERAGE(E4,E4+E5)*E6 | F7: =AVERAGE(F4,F4+F5)*F6 | G7: =AVERAGE(G4,G4+G5)*G6
A8: Ending PP&E | B8: =B4+B5-B7 | C8: =C4+C5-C7 | D8: =D4+D5-D7 | E8: =E4+E5-E7 | F8: =F4+F5-F7 | G8: =G4+G5-G7

Sheet 20 Working Capital
A1: Net Operating Working Capital
A2: Units | B2: $mm
B3: 2026 | C3: 2027 | D3: 2028 | E3: 2029 | F3: 2030 | G3: 2031
A4: Revenue | B4: ='03 Revenue Build'!B11 | C4: ='03 Revenue Build'!C11 | D4: ='03 Revenue Build'!D11 | E4: ='03 Revenue Build'!E11 | F4: ='03 Revenue Build'!F11 | G4: ='03 Revenue Build'!G11
A5: Days Sales Outstanding | B5: 40 | C5: 40 | D5: 40 | E5: 40 | F5: 40 | G5: 40
A6: Accounts Receivable | B6: =B4/365*B5 | C6: =C4/365*C5 | D6: =D4/365*D5 | E6: =E4/365*E5 | F6: =F4/365*F5 | G6: =G4/365*G5
A7: Inventory Days | B7: 70 | C7: 68 | D7: 66 | E7: 64 | F7: 62 | G7: 60
A8: Inventory | B8: ='14 COGS'!B18/365*B7 | C8: ='14 COGS'!C18/365*C7 | D8: ='14 COGS'!D18/365*D7 | E8: ='14 COGS'!E18/365*E7 | F8: ='14 COGS'!F18/365*F7 | G8: ='14 COGS'!G18/365*G7
A9: Days Payable Outstanding | B9: 55 | C9: 55 | D9: 55 | E9: 55 | F9: 55 | G9: 55
A10: Accounts Payable | B10: ='14 COGS'!B18/365*B9 | C10: ='14 COGS'!C18/365*C9 | D10: ='14 COGS'!D18/365*D9 | E10: ='14 COGS'!E18/365*E9 | F10: ='14 COGS'!F18/365*F9 | G10: ='14 COGS'!G18/365*G9
A11: Deferred Revenue % Revenue | B11: 0.25 | C11: 0.24 | D11: 0.23 | E11: 0.22 | F11: 0.21 | G11: 0.2
A12: Deferred Revenue | B12: =B4*B11 | C12: =C4*C11 | D12: =D4*D11 | E12: =E4*E11 | F12: =F4*F11 | G12: =G4*G11
A13: Net Operating Working Capital | B13: =B6+B8-B10-B12 | C13: =C6+C8-C10-C12 | D13: =D6+D8-D10-D12 | E13: =E6+E8-E10-E12 | F13: =F6+F8-F10-F12 | G13: =G6+G8-G10-G12
A14: Change in NOWC | B14: =B13-$B$15 | C14: =C13-B13 | D14: =D13-C13 | E14: =E13-D13 | F14: =F13-E13 | G14: =G13-F13
A15: FY2025 NOWC (actual, seed) | B15: -101.477

Sheet 21 Income Statement
A1: Income Statement
A2: Units | B2: $mm
B3: 2026 | C3: 2027 | D3: 2028 | E3: 2029 | F3: 2030 | G3: 2031
A4: Revenue | B4: ='03 Revenue Build'!B11 | C4: ='03 Revenue Build'!C11 | D4: ='03 Revenue Build'!D11 | E4: ='03 Revenue Build'!E11 | F4: ='03 Revenue Build'!F11 | G4: ='03 Revenue Build'!G11
A5: COGS | B5: ='14 COGS'!B17 | C5: ='14 COGS'!C17 | D5: ='14 COGS'!D17 | E5: ='14 COGS'!E17 | F5: ='14 COGS'!F17 | G5: ='14 COGS'!G17
A6: Gross Profit | B6: =B4-B5 | C6: =C4-C5 | D6: =D4-D5 | E6: =E4-E5 | F6: =F4-F5 | G6: =G4-G5
A7: Gross Margin | B7: =IFERROR(B6/B4,0) | C7: =IFERROR(C6/C4,0) | D7: =IFERROR(D6/D4,0) | E7: =IFERROR(E6/E4,0) | F7: =IFERROR(F6/F4,0) | G7: =IFERROR(G6/G4,0)
A8: Operating Expenses | B8: ='17 OpEx'!B11 | C8: ='17 OpEx'!C11 | D8: ='17 OpEx'!D11 | E8: ='17 OpEx'!E11 | F8: ='17 OpEx'!F11 | G8: ='17 OpEx'!G11
A9: EBIT | B9: =B6-B8 | C9: =C6-C8 | D9: =D6-D8 | E9: =E6-E8 | F9: =F6-F8 | G9: =G6-G8
A10: EBIT Margin | B10: =IFERROR(B9/B4,0) | C10: =IFERROR(C9/C4,0) | D10: =IFERROR(D9/D4,0) | E10: =IFERROR(E9/E4,0) | F10: =IFERROR(F9/F4,0) | G10: =IFERROR(G9/G4,0)
A11: Taxes | B11: =MAX(0,B9*'00 Control'!B6) | C11: =MAX(0,C9*'00 Control'!C6) | D11: =MAX(0,D9*'00 Control'!D6) | E11: =MAX(0,E9*'00 Control'!E6) | F11: =MAX(0,F9*'00 Control'!F6) | G11: =MAX(0,G9*'00 Control'!G6)
A12: NOPAT | B12: =B9-B11 | C12: =C9-C11 | D12: =D9-D11 | E12: =E9-E11 | F12: =F9-F11 | G12: =G9-G11
A13: NOPAT Margin | B13: =IFERROR(B12/B4,0) | C13: =IFERROR(C12/C4,0) | D13: =IFERROR(D12/D4,0) | E13: =IFERROR(E12/E4,0) | F13: =IFERROR(F12/F4,0) | G13: =IFERROR(G12/G4,0)

Sheet 22 Balance Sheet
A1: Balance Sheet Support
A2: Units | B2: $mm
B3: 2026 | C3: 2027 | D3: 2028 | E3: 2029 | F3: 2030 | G3: 2031
A4: Cash | B4: ='00 Control'!B10 | C4: ='00 Control'!C10 | D4: ='00 Control'!D10 | E4: ='00 Control'!E10 | F4: ='00 Control'!F10 | G4: ='00 Control'!G10
A5: Accounts Receivable | B5: ='20 Working Capital'!B6 | C5: ='20 Working Capital'!C6 | D5: ='20 Working Capital'!D6 | E5: ='20 Working Capital'!E6 | F5: ='20 Working Capital'!F6 | G5: ='20 Working Capital'!G6
A6: Inventory | B6: ='20 Working Capital'!B8 | C6: ='20 Working Capital'!C8 | D6: ='20 Working Capital'!D8 | E6: ='20 Working Capital'!E8 | F6: ='20 Working Capital'!F8 | G6: ='20 Working Capital'!G8
A7: PP&E | B7: ='19 Depreciation'!B8 | C7: ='19 Depreciation'!C8 | D7: ='19 Depreciation'!D8 | E7: ='19 Depreciation'!E8 | F7: ='19 Depreciation'!F8 | G7: ='19 Depreciation'!G8
A8: Total Assets | B8: =SUM(B4:B7) | C8: =SUM(C4:C7) | D8: =SUM(D4:D7) | E8: =SUM(E4:E7) | F8: =SUM(F4:F7) | G8: =SUM(G4:G7)
A9: Accounts Payable | B9: ='20 Working Capital'!B10 | C9: ='20 Working Capital'!C10 | D9: ='20 Working Capital'!D10 | E9: ='20 Working Capital'!E10 | F9: ='20 Working Capital'!F10 | G9: ='20 Working Capital'!G10
A10: Deferred Revenue | B10: ='20 Working Capital'!B12 | C10: ='20 Working Capital'!C12 | D10: ='20 Working Capital'!D12 | E10: ='20 Working Capital'!E12 | F10: ='20 Working Capital'!F12 | G10: ='20 Working Capital'!G12
A11: Debt | B11: ='00 Control'!B11 | C11: ='00 Control'!C11 | D11: ='00 Control'!D11 | E11: ='00 Control'!E11 | F11: ='00 Control'!F11 | G11: ='00 Control'!G11
A12: Total Liabilities | B12: =SUM(B9:B11) | C12: =SUM(C9:C11) | D12: =SUM(D9:D11) | E12: =SUM(E9:E11) | F12: =SUM(F9:F11) | G12: =SUM(G9:G11)
A13: Equity Plug | B13: =B8-B12 | C13: =C8-C12 | D13: =D8-D12 | E13: =E8-E12 | F13: =F8-F12 | G13: =G8-G12
A14: Total Liabilities + Equity | B14: =B12+B13 | C14: =C12+C13 | D14: =D12+D13 | E14: =E12+E13 | F14: =F12+F13 | G14: =G12+G13
A15: Balance Check | B15: =B8-B14 | C15: =C8-C14 | D15: =D8-D14 | E15: =E8-E14 | F15: =F8-F14 | G15: =G8-G14

Sheet 23 Cash Flow
A1: Free Cash Flow
A2: Units | B2: $mm
B3: 2026 | C3: 2027 | D3: 2028 | E3: 2029 | F3: 2030 | G3: 2031
A4: EBIT | B4: ='21 Income Statement'!B9 | C4: ='21 Income Statement'!C9 | D4: ='21 Income Statement'!D9 | E4: ='21 Income Statement'!E9 | F4: ='21 Income Statement'!F9 | G4: ='21 Income Statement'!G9
A5: Tax Rate | B5: ='00 Control'!B6 | C5: ='00 Control'!C6 | D5: ='00 Control'!D6 | E5: ='00 Control'!E6 | F5: ='00 Control'!F6 | G5: ='00 Control'!G6
A6: NOPAT | B6: ='21 Income Statement'!B12 | C6: ='21 Income Statement'!C12 | D6: ='21 Income Statement'!D12 | E6: ='21 Income Statement'!E12 | F6: ='21 Income Statement'!F12 | G6: ='21 Income Statement'!G12
A7: Depreciation | B7: ='19 Depreciation'!B7 | C7: ='19 Depreciation'!C7 | D7: ='19 Depreciation'!D7 | E7: ='19 Depreciation'!E7 | F7: ='19 Depreciation'!F7 | G7: ='19 Depreciation'!G7
A8: Capital Expenditures | B8: ='18 CapEx'!B10 | C8: ='18 CapEx'!C10 | D8: ='18 CapEx'!D10 | E8: ='18 CapEx'!E10 | F8: ='18 CapEx'!F10 | G8: ='18 CapEx'!G10
A9: Change in NOWC | B9: ='20 Working Capital'!B14 | C9: ='20 Working Capital'!C14 | D9: ='20 Working Capital'!D14 | E9: ='20 Working Capital'!E14 | F9: ='20 Working Capital'!F14 | G9: ='20 Working Capital'!G14
A10: Free Cash Flow | B10: =B6+B7-B8-B9 | C10: =C6+C7-C8-C9 | D10: =D6+D7-D8-D9 | E10: =E6+E7-E8-E9 | F10: =F6+F7-F8-F9 | G10: =G6+G7-G8-G9
A11: Cumulative FCF | B11: =B10 | C11: =B11+C10 | D11: =C11+D10 | E11: =D11+E10 | F11: =E11+F10 | G11: =F11+G10

Sheet 24 DCF Valuation
A1: DCF Valuation
A2: Units | B2: $mm except per share
B3: 2026 | C3: 2027 | D3: 2028 | E3: 2029 | F3: 2030 | G3: 2031
A4: Free Cash Flow | B4: ='23 Cash Flow'!B10 | C4: ='23 Cash Flow'!C10 | D4: ='23 Cash Flow'!D10 | E4: ='23 Cash Flow'!E10 | F4: ='23 Cash Flow'!F10 | G4: ='23 Cash Flow'!G10
A5: Discount Rate | B5: ='00 Control'!B7 | C5: ='00 Control'!C7 | D5: ='00 Control'!D7 | E5: ='00 Control'!E7 | F5: ='00 Control'!F7 | G5: ='00 Control'!G7
A6: Discount Period | B6: 1 | C6: 2 | D6: 3 | E6: 4 | F6: 5 | G6: 6
A7: Discount Factor | B7: =1/(1+B5)^B6 | C7: =1/(1+C5)^C6 | D7: =1/(1+D5)^D6 | E7: =1/(1+E5)^E6 | F7: =1/(1+F5)^F6 | G7: =1/(1+G5)^G6
A8: PV of FCF | B8: =B4*B7 | C8: =C4*C7 | D8: =D4*D7 | E8: =E4*E7 | F8: =F4*F7 | G8: =G4*G7
A9: Terminal FCF | G9: ='23 Cash Flow'!G10
A10: Perpetuity Terminal Value | G10: =IFERROR(G9*(1+'00 Control'!G8)/('00 Control'!G7-'00 Control'!G8),0)
A11: Exit Multiple Terminal Value | G11: ='21 Income Statement'!G9*'00 Control'!G9
A12: Selected Terminal Value | G12: =IF('00 Control'!G13=1,G10,G11)
A13: PV of Terminal Value | G13: =G12*G7
A14: Enterprise Value | G14: =SUM(B8:G8)+G13
A15: Cash | G15: ='00 Control'!G10
A16: Debt | G16: ='00 Control'!G11
A17: Equity Value | G17: =G14+G15-G16
A18: Diluted Shares | G18: ='00 Control'!G12
A19: Implied Share Price | G19: =IFERROR(G17/G18,0)

Sheet 25 Checks
A1: Model Checks
A2: Units | B2: check outputs
B3: 2026 | C3: 2027 | D3: 2028 | E3: 2029 | F3: 2030 | G3: 2031
A4: Balance Sheet Check | B4: ='22 Balance Sheet'!B15 | C4: ='22 Balance Sheet'!C15 | D4: ='22 Balance Sheet'!D15 | E4: ='22 Balance Sheet'!E15 | F4: ='22 Balance Sheet'!F15 | G4: ='22 Balance Sheet'!G15
A5: Revenue Tie Check | B5: ='03 Revenue Build'!B11-'21 Income Statement'!B4 | C5: ='03 Revenue Build'!C11-'21 Income Statement'!C4 | D5: ='03 Revenue Build'!D11-'21 Income Statement'!D4 | E5: ='03 Revenue Build'!E11-'21 Income Statement'!E4 | F5: ='03 Revenue Build'!F11-'21 Income Statement'!F4 | G5: ='03 Revenue Build'!G11-'21 Income Statement'!G4
A6: COGS Tie Check | B6: ='14 COGS'!B17-'21 Income Statement'!B5 | C6: ='14 COGS'!C17-'21 Income Statement'!C5 | D6: ='14 COGS'!D17-'21 Income Statement'!D5 | E6: ='14 COGS'!E17-'21 Income Statement'!E5 | F6: ='14 COGS'!F17-'21 Income Statement'!F5 | G6: ='14 COGS'!G17-'21 Income Statement'!G5
A7: FCF Tie Check | B7: ='23 Cash Flow'!B10-('23 Cash Flow'!B6+'23 Cash Flow'!B7-'23 Cash Flow'!B8-'23 Cash Flow'!B9) | C7: ='23 Cash Flow'!C10-('23 Cash Flow'!C6+'23 Cash Flow'!C7-'23 Cash Flow'!C8-'23 Cash Flow'!C9) | D7: ='23 Cash Flow'!D10-('23 Cash Flow'!D6+'23 Cash Flow'!D7-'23 Cash Flow'!D8-'23 Cash Flow'!D9) | E7: ='23 Cash Flow'!E10-('23 Cash Flow'!E6+'23 Cash Flow'!E7-'23 Cash Flow'!E8-'23 Cash Flow'!E9) | F7: ='23 Cash Flow'!F10-('23 Cash Flow'!F6+'23 Cash Flow'!F7-'23 Cash Flow'!F8-'23 Cash Flow'!F9) | G7: ='23 Cash Flow'!G10-('23 Cash Flow'!G6+'23 Cash Flow'!G7-'23 Cash Flow'!G8-'23 Cash Flow'!G9)
A8: Any Check Failed? | B8: =IF(OR(ABS(B4)>0.01,ABS(B5)>0.01,ABS(B6)>0.01,ABS(B7)>0.01),"FAIL","OK") | C8: =IF(OR(ABS(C4)>0.01,ABS(C5)>0.01,ABS(C6)>0.01,ABS(C7)>0.01),"FAIL","OK") | D8: =IF(OR(ABS(D4)>0.01,ABS(D5)>0.01,ABS(D6)>0.01,ABS(D7)>0.01),"FAIL","OK") | E8: =IF(OR(ABS(E4)>0.01,ABS(E5)>0.01,ABS(E6)>0.01,ABS(E7)>0.01),"FAIL","OK") | F8: =IF(OR(ABS(F4)>0.01,ABS(F5)>0.01,ABS(F6)>0.01,ABS(F7)>0.01),"FAIL","OK") | G8: =IF(OR(ABS(G4)>0.01,ABS(G5)>0.01,ABS(G6)>0.01,ABS(G7)>0.01),"FAIL","OK")

Sheet 26 Sources
A1: Sources and Input Log
A2: Units | B2: plain text URLs and notes
B3: 2026 | C3: 2027 | D3: 2028 | E3: 2029 | F3: 2030 | G3: 2031
A4: Sheet | B4: Line Item | C4: Source URL | D4: Source Date | E4: Notes
A5: All | B5: Historical anchor | C5: cbrs-financials.xlsx (FY24/FY25, Q1-26) | D5: 2026-06 | E5: FY25 rev $510.0mm; Q1-26 rev $193.4mm validates 2026 base
A6: 03 Revenue Build | B6: Hardware/Cloud split | C6: cbrs-metrics-annual.xlsx | D6: 2026-06 | E6: FY25 Hardware $358.4mm, Cloud&Svc $151.6mm
A7: 05 CS3 Systems | B7: ASP per CS3 ~$2.6-2.8mm | C7: Analyst estimate | D7: 2026-06 | E7: Wafer-scale CS-3 price; not disclosed by company
A8: 04/07 Cloud | B8: Installed base seed 285 | C8: Analyst estimate | D8: 2026-06 | E8: Cumulative CS-2/CS-3 fleet shipped thru FY25
A9: 06 Clusters | B9: RPO $25.0bn backlog | C9: cbrs-metrics-annual (3).xlsx | D9: 2026-06 | E9: Drives unit ramp; Customer A 62%, B 24% concentration
A10: 14 COGS | B10: Hardware GM 42%->54% | C10: Analyst est / FY25 42.9% actual | D10: 2026-06 | E10: Yield + scale; cloud GM 30%->45%
A11: 16 R&D | B11: R&D ramp, falling % rev | C11: FY25 R&D $243.3mm (48% rev) | D11: 2026-06 | E11: Grows in $ but to ~21% of revenue by 2031
A12: 15 OpEx | B12: SBC % revenue 9%->5.5% | C12: FY25 SBC $49.8mm | D12: 2026-06 | E12: Declines with scale
A13: 18 CapEx | B13: Cloud capex heavy early | C13: FY25 capex $382.7mm (75% rev) | D13: 2026-06 | E13: Cloud datacenter buildout; tapers to ~19% rev
A14: 20 WC | B14: DSO40/Inv~65/DPO55/Def25% | C14: FY25 actuals | D14: 2026-06 | E14: FY25 NOWC -$101.5mm seeded for 2026 change
A15: 00 Control | B15: Cash $1,336.9 Debt $261.8 | C15: FY25 balance sheet | D15: 2026-06 | E15: Net cash bridge for DCF; 190mm diluted shares
A16: 24 DCF | B16: 12% disc, 20x exit EBIT | C16: Assumption | D16: 2026-06 | E16: Exit-multiple TV (growth co, pre-FCF); perpetuity toggle avail
