Workbook

Sheet Dashboard
A1: Dell Reverse DCF Dashboard
A3: Metric | B3: Value | C3: Read | E3: Interpretation
A4: Current share price | B4: =Inputs!B4 -> 395.9 | C4: Market price used in reverse DCF | E4: At the current market cap, the base reverse DCF requires roughly 13.8% annual FCFE growth through FY2031 at a 9.5% cost of equity and 2.5% terminal growth.
A5: Market cap | B5: =Inputs!B5 -> 259710.4 | C5: Target equity value | E5: Implied AI revenue is highly sensitive to AI server operating margin. At 7.0% it implies about $224B of FY2031 AI server revenue, near a 39% revenue CAGR off FY2027.
A6: Required FCFE CAGR | B6: =Inputs!B16 -> 0.13760926 | C6: What the current price requires under base cost of equity and terminal growth | E6: AI growth and AI margin are drawn with a negative correlation, since Dell wins AI server volume by pricing thin. That trade-off compresses both tails versus an independent draw and lowers the share of simulations above the current price.
A7: Required FY2031 FCFE | B7: =Inputs!B17 -> 21203.433 | C7: Needed free cash flow to equity by FY2031
A8: Selected AI operating margin | B8: =Inputs!B18 -> 0.07 | C8: Margin assumption for implied AI revenue bridge
A9: Implied FY2031 AI revenue | B9: =Inputs!B33 -> 224010.11 | C9: Revenue needed at selected AI margin
A10: Implied AI revenue CAGR | B10: =Inputs!B34 -> 0.39004575 | C10: FY2027 to FY2031 AI revenue CAGR
A11: Monte Carlo median value | B11: ='Monte Carlo'!B6 -> 352.67117 | C11: Seeded simulation central case
A12: Probability above current price | B12: ='Monte Carlo'!B12 -> 0.2618 | C12: Share of simulations above current price

Sheet Inputs
A1: Dell Reverse DCF Inputs
A3: Input | B3: Value | C3: Unit | D3: Source | E3: Notes | F3: Q1 mix %
A4: Current share price | B4: 395.9 | C4: $/share | D4: S3 | E4: Live market data snapshot
A5: Equity market cap | B5: 259710.4 | C5: $mm | D5: S3 | E5: Used as target equity value
A6: Implied diluted shares | B6: =B5/B4 -> 656 | C6: mm | D6: Formula | E6: Market cap divided by price
A7: Cash and cash equivalents | B7: 11578 | C7: $mm | D7: S2 | E7: May 1 2026
A8: Core debt | B8: 16707 | C8: $mm | D8: S2 | E8: Excludes DFS related debt and other debt
A9: Core net debt | B9: =B8-B7 -> 5129 | C9: $mm | D9: Formula | E9: Core debt minus cash
A10: Core enterprise value | B10: =B5+B9 -> 264839.4 | C10: $mm | D10: Formula | E10: Equity value plus core net debt
A11: FY2027 revenue guidance midpoint | B11: 167000 | C11: $mm | D11: S1 | E11: Management guidance
A12: FY2027 AI server revenue guidance | B12: 60000 | C12: $mm | D12: S1 | E12: Management guidance
A13: Q1 adjusted free cash flow annualized | B13: 12660 | C13: $mm | D13: S1 | E13: Q1 adjusted FCF times four
A14: Cost of equity | B14: 0.095 | C14: % | D14: S4 | E14: Base case discount rate
A15: Terminal growth | B15: 0.025 | C15: % | D15: S4 | E15: Base case terminal growth
A16: Required FCFE CAGR | B16: 0.13760926 | C16: % | D16: Formula/Python solver | E16: Solver output: CAGR that sets Reverse DCF equity value equal to market cap. No closed-form inverse, set by Goal Seek. Reverse DCF check cell confirms it.
A17: Required FY2031 FCFE | B17: =B13*(1+B16)^4 -> 21203.433 | C17: $mm | D17: Formula | E17: FY2027 FCFE grown at required CAGR for four years
A18: Selected AI operating margin | B18: 0.07 | C18: % | D18: S4 | E18: Adjust to test implied AI revenue needed
A19: Traditional server and networking margin | B19: 0.1 | C19: % | D19: S4 | E19: Model assumption
A20: Storage operating margin | B20: 0.15 | C20: % | D20: S4 | E20: Model assumption
A21: CSG operating margin | B21: 0.08 | C21: % | D21: S4 | E21: Model assumption
A22: Corporate cost FY2027 | B22: -2300 | C22: $mm | D22: S4 | E22: Corporate adjustments and shared costs
A23: Corporate cost growth | B23: 0.03 | C23: % | D23: S4 | E23: Model assumption
A24: Tax rate | B24: 0.18 | C24: % | D24: S4 | E24: Model assumption
A25: FY2031 FCFE conversion | B25: 1.05 | C25: % | D25: S4 | E25: FCFE divided by normalized net income
A26: Traditional server growth | B26: 0.03 | C26: % | D26: S4 | E26: Model assumption
A27: Storage growth | B27: 0.04 | C27: % | D27: S4 | E27: Model assumption
A28: CSG growth | B28: 0.02 | C28: % | D28: S4 | E28: Model assumption
A29: FY2027 traditional server revenue | B29: =($B$11-$B$12)*F29 -> 32988.127 | C29: $mm | D29: Formula | E29: Allocated from non-AI FY2027 revenue using Q1 mix | F29: 0.30830025
A30: FY2027 storage revenue | B30: =($B$11-$B$12)*F30 -> 16735.402 | C30: $mm | D30: Formula | E30: Allocated from non-AI FY2027 revenue using Q1 mix | F30: 0.15640563
A31: FY2027 CSG revenue | B31: =($B$11-$B$12)*F31 -> 56411.512 | C31: $mm | D31: Formula | E31: Allocated from non-AI FY2027 revenue using Q1 mix | F31: 0.52721039
A32: FY2027 corporate and other revenue | B32: =($B$11-$B$12)*F32 -> 864.9585 | C32: $mm | D32: Formula | E32: Allocated from non-AI FY2027 revenue using Q1 mix | F32: 0.0080837243
A33: Implied FY2031 AI revenue needed | B33: =(B17/B25/(1-B24)-(B29*(1+B26)^4*B19+B30*(1+B27)^4*B20+B31*(1+B28)^4*B21+B22*(1+B23)^4))/B18 -> 224010.11 | C33: $mm | D33: Formula | E33: Given selected AI margin and required FY2031 FCFE
A34: Implied AI revenue CAGR needed | B34: =(B33/B12)^(1/4)-1 -> 0.39004575 | C34: % | D34: Formula | E34: Required CAGR from FY2027 to FY2031

Sheet Reverse DCF
A1: Reverse DCF, what Dell stock is pricing in
B3: FY2027 | C3: FY2028 | D3: FY2029 | E3: FY2030 | F3: FY2031 | G3: Terminal
A4: Year index | B4: 1 | C4: 2 | D4: 3 | E4: 4 | F4: 5
A5: FCFE | B5: =Inputs!$B$13 -> 12660 | C5: =B5*(1+Inputs!$B$16) -> 14402.133 | D5: =C5*(1+Inputs!$B$16) -> 16384 | E5: =D5*(1+Inputs!$B$16) -> 18638.59 | F5: =E5*(1+Inputs!$B$16) -> 21203.433
A6: Required FCFE growth | B6: =Inputs!$B$16 -> 0.13760926 | C6: =Inputs!$B$16 -> 0.13760926 | D6: =Inputs!$B$16 -> 0.13760926 | E6: =Inputs!$B$16 -> 0.13760926 | F6: =Inputs!$B$16 -> 0.13760926
A7: Discount factor | B7: =1/(1+Inputs!$B$14)^1 -> 0.91324201 | C7: =1/(1+Inputs!$B$14)^2 -> 0.83401097 | D7: =1/(1+Inputs!$B$14)^3 -> 0.76165385 | E7: =1/(1+Inputs!$B$14)^4 -> 0.69557429 | F7: =1/(1+Inputs!$B$14)^5 -> 0.63522767
A8: Present value of FCFE | B8: =B5*B7 -> 11561.644 | C8: =C5*C7 -> 12011.537 | D8: =D5*D7 -> 12478.937 | E8: =E5*E7 -> 12964.524 | F8: =F5*F7 -> 13469.007
A9: Terminal value | F9: =F5*(1+Inputs!$B$15)/(Inputs!$B$14-Inputs!$B$15) -> 310478.84
A10: Present value of terminal value | F10: =F9*F7 -> 197224.75
A12: Summary
A13: PV of explicit FCFE | B13: =SUM(B8:F8) -> 62485.65
A14: PV of terminal value | B14: =F10 -> 197224.75
A15: Equity value from DCF | B15: =SUM(B8:F8)+F10 -> 259710.4
A16: Market equity value | B16: =Inputs!$B$5 -> 259710.4
A17: Value per share | B17: =B15/Inputs!$B$6 -> 395.9
A18: Current share price | B18: =Inputs!$B$4 -> 395.9
A19: Difference to market | B19: =B17-B18 -> 0
A20: Check: DCF equity value minus market cap | B20: =B15-B16 -> 0

Sheet Segment Build
A1: Segment Build, implied AI server growth needed
A3: $mm unless noted | B3: FY2027 | C3: FY2028 | D3: FY2029 | E3: FY2030 | F3: FY2031
A5: Revenue
A6: AI optimized servers | B6: =Inputs!$B$12 -> 60000 | C6: =B6*(1+Inputs!$B$34) -> 83402.745 | D6: =C6*(1+Inputs!$B$34) -> 115933.63 | E6: =D6*(1+Inputs!$B$34) -> 161153.05 | F6: =E6*(1+Inputs!$B$34) -> 224010.11
A7: Traditional servers and networking | B7: =Inputs!$B$29 -> 32988.127 | C7: =B7*(1+Inputs!$B$26) -> 33977.771 | D7: =C7*(1+Inputs!$B$26) -> 34997.104 | E7: =D7*(1+Inputs!$B$26) -> 36047.017 | F7: =E7*(1+Inputs!$B$26) -> 37128.428
A8: Storage | B8: =Inputs!$B$30 -> 16735.402 | C8: =B8*(1+Inputs!$B$27) -> 17404.818 | D8: =C8*(1+Inputs!$B$27) -> 18101.011 | E8: =D8*(1+Inputs!$B$27) -> 18825.052 | F8: =E8*(1+Inputs!$B$27) -> 19578.054
A9: Client Solutions Group | B9: =Inputs!$B$31 -> 56411.512 | C9: =B9*(1+Inputs!$B$28) -> 57539.742 | D9: =C9*(1+Inputs!$B$28) -> 58690.537 | E9: =D9*(1+Inputs!$B$28) -> 59864.348 | F9: =E9*(1+Inputs!$B$28) -> 61061.635
A10: Corporate and other | B10: =Inputs!$B$32 -> 864.9585 | C10: =B10*(1+Inputs!$B$23) -> 890.90725 | D10: =C10*(1+Inputs!$B$23) -> 917.63447 | E10: =D10*(1+Inputs!$B$23) -> 945.16351 | F10: =E10*(1+Inputs!$B$23) -> 973.51841
A11: Total revenue | B11: =SUM(B6:B10) -> 167000 | C11: =SUM(C6:C10) -> 193215.98 | D11: =SUM(D6:D10) -> 228639.92 | E11: =SUM(E6:E10) -> 276834.63 | F11: =SUM(F6:F10) -> 342751.75
A13: Operating income
A14: AI optimized servers | B14: =B6*Inputs!$B$18 -> 4200 | C14: =C6*Inputs!$B$18 -> 5838.1922 | D14: =D6*Inputs!$B$18 -> 8115.3542 | E14: =E6*Inputs!$B$18 -> 11280.714 | F14: =F6*Inputs!$B$18 -> 15680.708
A15: Traditional servers and networking | B15: =B7*Inputs!$B$19 -> 3298.8127 | C15: =C7*Inputs!$B$19 -> 3397.7771 | D15: =D7*Inputs!$B$19 -> 3499.7104 | E15: =E7*Inputs!$B$19 -> 3604.7017 | F15: =F7*Inputs!$B$19 -> 3712.8428
A16: Storage | B16: =B8*Inputs!$B$20 -> 2510.3104 | C16: =C8*Inputs!$B$20 -> 2610.7228 | D16: =D8*Inputs!$B$20 -> 2715.1517 | E16: =E8*Inputs!$B$20 -> 2823.7577 | F16: =F8*Inputs!$B$20 -> 2936.7081
A17: Client Solutions Group | B17: =B9*Inputs!$B$21 -> 4512.921 | C17: =C9*Inputs!$B$21 -> 4603.1794 | D17: =D9*Inputs!$B$21 -> 4695.243 | E17: =E9*Inputs!$B$21 -> 4789.1478 | F17: =F9*Inputs!$B$21 -> 4884.9308
A18: Corporate cost / adjustments | B18: =Inputs!$B$22 -> -2300 | C18: =B18*(1+Inputs!$B$23) -> -2369 | D18: =C18*(1+Inputs!$B$23) -> -2440.07 | E18: =D18*(1+Inputs!$B$23) -> -2513.2721 | F18: =E18*(1+Inputs!$B$23) -> -2588.6703
A19: Total clean operating income | B19: =SUM(B14:B18) -> 12222.044 | C19: =SUM(C14:C18) -> 14080.871 | D19: =SUM(D14:D18) -> 16585.389 | E19: =SUM(E14:E18) -> 19985.049 | F19: =SUM(F14:F18) -> 24626.519
A20: Tax on clean operating income | B20: =-B19*Inputs!$B$24 -> -2199.9679 | C20: =-C19*Inputs!$B$24 -> -2534.5569 | D20: =-D19*Inputs!$B$24 -> -2985.3701 | E20: =-E19*Inputs!$B$24 -> -3597.3088 | F20: =-F19*Inputs!$B$24 -> -4432.7735
A21: Normalized net income | B21: =B19+B20 -> 10022.076 | C21: =C19+C20 -> 11546.315 | D21: =D19+D20 -> 13600.019 | E21: =E19+E20 -> 16387.74 | F21: =F19+F20 -> 20193.746
A22: FCFE conversion | B22: =Inputs!$B$13/B21 -> 1.2632113 | C22: =B22+(Inputs!$B$25-B22)*1/4 -> 1.2099085 | D22: =B22+(Inputs!$B$25-B22)*2/4 -> 1.1566057 | E22: =B22+(Inputs!$B$25-B22)*3/4 -> 1.1033028 | F22: =B22+(Inputs!$B$25-B22)*4/4 -> 1.05
A23: Free cash flow to equity | B23: =B21*B22 -> 12660 | C23: =C21*C22 -> 13969.984 | D23: =D21*D22 -> 15729.859 | E23: =E21*E22 -> 18080.64 | F23: =F21*F22 -> 21203.433

Sheet Sensitivity
A1: Sensitivity, price and AI assumptions
A3: Value per share sensitivity, FCFE CAGR vs terminal growth
A4: FCFE CAGR | B4: 0.015 | C4: 0.02 | D4: 0.025 | E4: 0.03 | F4: 0.035 | H4: AI operating margin | I4: Required FY31 AI revenue ($mm) | J4: Implied AI revenue CAGR
A5: 0 | B5: =(Inputs!$B$13/(1+Inputs!$B$14)^1+Inputs!$B$13*(1+$A5)/(1+Inputs!$B$14)^2+Inputs!$B$13*(1+$A5)^2/(1+Inputs!$B$14)^3+Inputs!$B$13*(1+$A5)^3/(1+Inputs!$B$14)^4+Inputs!$B$13*(1+$A5)^4/(1+Inputs!$B$14)^5+(Inputs!$B$13*(1+$A5)^4*(1+B$4)/(Inputs!$B$14-B$4))/(1+Inputs!$B$14)^5)/Inputs!$B$6 -> 229.63927 | C5: =(Inputs!$B$13/(1+Inputs!$B$14)^1+Inputs!$B$13*(1+$A5)/(1+Inputs!$B$14)^2+Inputs!$B$13*(1+$A5)^2/(1+Inputs!$B$14)^3+Inputs!$B$13*(1+$A5)^3/(1+Inputs!$B$14)^4+Inputs!$B$13*(1+$A5)^4/(1+Inputs!$B$14)^5+(Inputs!$B$13*(1+$A5)^4*(1+C$4)/(Inputs!$B$14-C$4))/(1+Inputs!$B$14)^5)/Inputs!$B$6 -> 240.82572 | D5: =(Inputs!$B$13/(1+Inputs!$B$14)^1+Inputs!$B$13*(1+$A5)/(1+Inputs!$B$14)^2+Inputs!$B$13*(1+$A5)^2/(1+Inputs!$B$14)^3+Inputs!$B$13*(1+$A5)^3/(1+Inputs!$B$14)^4+Inputs!$B$13*(1+$A5)^4/(1+Inputs!$B$14)^5+(Inputs!$B$13*(1+$A5)^4*(1+D$4)/(Inputs!$B$14-D$4))/(1+Inputs!$B$14)^5)/Inputs!$B$6 -> 253.61023 | E5: =(Inputs!$B$13/(1+Inputs!$B$14)^1+Inputs!$B$13*(1+$A5)/(1+Inputs!$B$14)^2+Inputs!$B$13*(1+$A5)^2/(1+Inputs!$B$14)^3+Inputs!$B$13*(1+$A5)^3/(1+Inputs!$B$14)^4+Inputs!$B$13*(1+$A5)^4/(1+Inputs!$B$14)^5+(Inputs!$B$13*(1+$A5)^4*(1+E$4)/(Inputs!$B$14-E$4))/(1+Inputs!$B$14)^5)/Inputs!$B$6 -> 268.36159 | F5: =(Inputs!$B$13/(1+Inputs!$B$14)^1+Inputs!$B$13*(1+$A5)/(1+Inputs!$B$14)^2+Inputs!$B$13*(1+$A5)^2/(1+Inputs!$B$14)^3+Inputs!$B$13*(1+$A5)^3/(1+Inputs!$B$14)^4+Inputs!$B$13*(1+$A5)^4/(1+Inputs!$B$14)^5+(Inputs!$B$13*(1+$A5)^4*(1+F$4)/(Inputs!$B$14-F$4))/(1+Inputs!$B$14)^5)/Inputs!$B$6 -> 285.5715 | H5: 0.04 | I5: =$I$19/H5 -> 392017.7 | J5: =(I5/Inputs!$B$12)^(1/4)-1 -> 0.59877963
A6: 0.05 | B6: =(Inputs!$B$13/(1+Inputs!$B$14)^1+Inputs!$B$13*(1+$A6)/(1+Inputs!$B$14)^2+Inputs!$B$13*(1+$A6)^2/(1+Inputs!$B$14)^3+Inputs!$B$13*(1+$A6)^3/(1+Inputs!$B$14)^4+Inputs!$B$13*(1+$A6)^4/(1+Inputs!$B$14)^5+(Inputs!$B$13*(1+$A6)^4*(1+B$4)/(Inputs!$B$14-B$4))/(1+Inputs!$B$14)^5)/Inputs!$B$6 -> 270.22784 | C6: =(Inputs!$B$13/(1+Inputs!$B$14)^1+Inputs!$B$13*(1+$A6)/(1+Inputs!$B$14)^2+Inputs!$B$13*(1+$A6)^2/(1+Inputs!$B$14)^3+Inputs!$B$13*(1+$A6)^3/(1+Inputs!$B$14)^4+Inputs!$B$13*(1+$A6)^4/(1+Inputs!$B$14)^5+(Inputs!$B$13*(1+$A6)^4*(1+C$4)/(Inputs!$B$14-C$4))/(1+Inputs!$B$14)^5)/Inputs!$B$6 -> 283.82504 | D6: =(Inputs!$B$13/(1+Inputs!$B$14)^1+Inputs!$B$13*(1+$A6)/(1+Inputs!$B$14)^2+Inputs!$B$13*(1+$A6)^2/(1+Inputs!$B$14)^3+Inputs!$B$13*(1+$A6)^3/(1+Inputs!$B$14)^4+Inputs!$B$13*(1+$A6)^4/(1+Inputs!$B$14)^5+(Inputs!$B$13*(1+$A6)^4*(1+D$4)/(Inputs!$B$14-D$4))/(1+Inputs!$B$14)^5)/Inputs!$B$6 -> 299.36469 | E6: =(Inputs!$B$13/(1+Inputs!$B$14)^1+Inputs!$B$13*(1+$A6)/(1+Inputs!$B$14)^2+Inputs!$B$13*(1+$A6)^2/(1+Inputs!$B$14)^3+Inputs!$B$13*(1+$A6)^3/(1+Inputs!$B$14)^4+Inputs!$B$13*(1+$A6)^4/(1+Inputs!$B$14)^5+(Inputs!$B$13*(1+$A6)^4*(1+E$4)/(Inputs!$B$14-E$4))/(1+Inputs!$B$14)^5)/Inputs!$B$6 -> 317.29506 | F6: =(Inputs!$B$13/(1+Inputs!$B$14)^1+Inputs!$B$13*(1+$A6)/(1+Inputs!$B$14)^2+Inputs!$B$13*(1+$A6)^2/(1+Inputs!$B$14)^3+Inputs!$B$13*(1+$A6)^3/(1+Inputs!$B$14)^4+Inputs!$B$13*(1+$A6)^4/(1+Inputs!$B$14)^5+(Inputs!$B$13*(1+$A6)^4*(1+F$4)/(Inputs!$B$14-F$4))/(1+Inputs!$B$14)^5)/Inputs!$B$6 -> 338.21382 | H6: 0.05 | I6: =$I$19/H6 -> 313614.16 | J6: =(I6/Inputs!$B$12)^(1/4)-1 -> 0.51203242
A7: 0.1 | B7: =(Inputs!$B$13/(1+Inputs!$B$14)^1+Inputs!$B$13*(1+$A7)/(1+Inputs!$B$14)^2+Inputs!$B$13*(1+$A7)^2/(1+Inputs!$B$14)^3+Inputs!$B$13*(1+$A7)^3/(1+Inputs!$B$14)^4+Inputs!$B$13*(1+$A7)^4/(1+Inputs!$B$14)^5+(Inputs!$B$13*(1+$A7)^4*(1+B$4)/(Inputs!$B$14-B$4))/(1+Inputs!$B$14)^5)/Inputs!$B$6 -> 316.6533 | C7: =(Inputs!$B$13/(1+Inputs!$B$14)^1+Inputs!$B$13*(1+$A7)/(1+Inputs!$B$14)^2+Inputs!$B$13*(1+$A7)^2/(1+Inputs!$B$14)^3+Inputs!$B$13*(1+$A7)^3/(1+Inputs!$B$14)^4+Inputs!$B$13*(1+$A7)^4/(1+Inputs!$B$14)^5+(Inputs!$B$13*(1+$A7)^4*(1+C$4)/(Inputs!$B$14-C$4))/(1+Inputs!$B$14)^5)/Inputs!$B$6 -> 333.03138 | D7: =(Inputs!$B$13/(1+Inputs!$B$14)^1+Inputs!$B$13*(1+$A7)/(1+Inputs!$B$14)^2+Inputs!$B$13*(1+$A7)^2/(1+Inputs!$B$14)^3+Inputs!$B$13*(1+$A7)^3/(1+Inputs!$B$14)^4+Inputs!$B$13*(1+$A7)^4/(1+Inputs!$B$14)^5+(Inputs!$B$13*(1+$A7)^4*(1+D$4)/(Inputs!$B$14-D$4))/(1+Inputs!$B$14)^5)/Inputs!$B$6 -> 351.74918 | E7: =(Inputs!$B$13/(1+Inputs!$B$14)^1+Inputs!$B$13*(1+$A7)/(1+Inputs!$B$14)^2+Inputs!$B$13*(1+$A7)^2/(1+Inputs!$B$14)^3+Inputs!$B$13*(1+$A7)^3/(1+Inputs!$B$14)^4+Inputs!$B$13*(1+$A7)^4/(1+Inputs!$B$14)^5+(Inputs!$B$13*(1+$A7)^4*(1+E$4)/(Inputs!$B$14-E$4))/(1+Inputs!$B$14)^5)/Inputs!$B$6 -> 373.34664 | F7: =(Inputs!$B$13/(1+Inputs!$B$14)^1+Inputs!$B$13*(1+$A7)/(1+Inputs!$B$14)^2+Inputs!$B$13*(1+$A7)^2/(1+Inputs!$B$14)^3+Inputs!$B$13*(1+$A7)^3/(1+Inputs!$B$14)^4+Inputs!$B$13*(1+$A7)^4/(1+Inputs!$B$14)^5+(Inputs!$B$13*(1+$A7)^4*(1+F$4)/(Inputs!$B$14-F$4))/(1+Inputs!$B$14)^5)/Inputs!$B$6 -> 398.54368 | H7: 0.06 | I7: =$I$19/H7 -> 261345.13 | J7: =(I7/Inputs!$B$12)^(1/4)-1 -> 0.44466048
A8: 0.125 | B8: =(Inputs!$B$13/(1+Inputs!$B$14)^1+Inputs!$B$13*(1+$A8)/(1+Inputs!$B$14)^2+Inputs!$B$13*(1+$A8)^2/(1+Inputs!$B$14)^3+Inputs!$B$13*(1+$A8)^3/(1+Inputs!$B$14)^4+Inputs!$B$13*(1+$A8)^4/(1+Inputs!$B$14)^5+(Inputs!$B$13*(1+$A8)^4*(1+B$4)/(Inputs!$B$14-B$4))/(1+Inputs!$B$14)^5)/Inputs!$B$6 -> 342.22614 | C8: =(Inputs!$B$13/(1+Inputs!$B$14)^1+Inputs!$B$13*(1+$A8)/(1+Inputs!$B$14)^2+Inputs!$B$13*(1+$A8)^2/(1+Inputs!$B$14)^3+Inputs!$B$13*(1+$A8)^3/(1+Inputs!$B$14)^4+Inputs!$B$13*(1+$A8)^4/(1+Inputs!$B$14)^5+(Inputs!$B$13*(1+$A8)^4*(1+C$4)/(Inputs!$B$14-C$4))/(1+Inputs!$B$14)^5)/Inputs!$B$6 -> 360.14466 | D8: =(Inputs!$B$13/(1+Inputs!$B$14)^1+Inputs!$B$13*(1+$A8)/(1+Inputs!$B$14)^2+Inputs!$B$13*(1+$A8)^2/(1+Inputs!$B$14)^3+Inputs!$B$13*(1+$A8)^3/(1+Inputs!$B$14)^4+Inputs!$B$13*(1+$A8)^4/(1+Inputs!$B$14)^5+(Inputs!$B$13*(1+$A8)^4*(1+D$4)/(Inputs!$B$14-D$4))/(1+Inputs!$B$14)^5)/Inputs!$B$6 -> 380.62298 | E8: =(Inputs!$B$13/(1+Inputs!$B$14)^1+Inputs!$B$13*(1+$A8)/(1+Inputs!$B$14)^2+Inputs!$B$13*(1+$A8)^2/(1+Inputs!$B$14)^3+Inputs!$B$13*(1+$A8)^3/(1+Inputs!$B$14)^4+Inputs!$B$13*(1+$A8)^4/(1+Inputs!$B$14)^5+(Inputs!$B$13*(1+$A8)^4*(1+E$4)/(Inputs!$B$14-E$4))/(1+Inputs!$B$14)^5)/Inputs!$B$6 -> 404.2518 | F8: =(Inputs!$B$13/(1+Inputs!$B$14)^1+Inputs!$B$13*(1+$A8)/(1+Inputs!$B$14)^2+Inputs!$B$13*(1+$A8)^2/(1+Inputs!$B$14)^3+Inputs!$B$13*(1+$A8)^3/(1+Inputs!$B$14)^4+Inputs!$B$13*(1+$A8)^4/(1+Inputs!$B$14)^5+(Inputs!$B$13*(1+$A8)^4*(1+F$4)/(Inputs!$B$14-F$4))/(1+Inputs!$B$14)^5)/Inputs!$B$6 -> 431.81876 | H8: 0.07 | I8: =$I$19/H8 -> 224010.11 | J8: =(I8/Inputs!$B$12)^(1/4)-1 -> 0.39004575
A9: 0.15 | B9: =(Inputs!$B$13/(1+Inputs!$B$14)^1+Inputs!$B$13*(1+$A9)/(1+Inputs!$B$14)^2+Inputs!$B$13*(1+$A9)^2/(1+Inputs!$B$14)^3+Inputs!$B$13*(1+$A9)^3/(1+Inputs!$B$14)^4+Inputs!$B$13*(1+$A9)^4/(1+Inputs!$B$14)^5+(Inputs!$B$13*(1+$A9)^4*(1+B$4)/(Inputs!$B$14-B$4))/(1+Inputs!$B$14)^5)/Inputs!$B$6 -> 369.46687 | C9: =(Inputs!$B$13/(1+Inputs!$B$14)^1+Inputs!$B$13*(1+$A9)/(1+Inputs!$B$14)^2+Inputs!$B$13*(1+$A9)^2/(1+Inputs!$B$14)^3+Inputs!$B$13*(1+$A9)^3/(1+Inputs!$B$14)^4+Inputs!$B$13*(1+$A9)^4/(1+Inputs!$B$14)^5+(Inputs!$B$13*(1+$A9)^4*(1+C$4)/(Inputs!$B$14-C$4))/(1+Inputs!$B$14)^5)/Inputs!$B$6 -> 389.03203 | D9: =(Inputs!$B$13/(1+Inputs!$B$14)^1+Inputs!$B$13*(1+$A9)/(1+Inputs!$B$14)^2+Inputs!$B$13*(1+$A9)^2/(1+Inputs!$B$14)^3+Inputs!$B$13*(1+$A9)^3/(1+Inputs!$B$14)^4+Inputs!$B$13*(1+$A9)^4/(1+Inputs!$B$14)^5+(Inputs!$B$13*(1+$A9)^4*(1+D$4)/(Inputs!$B$14-D$4))/(1+Inputs!$B$14)^5)/Inputs!$B$6 -> 411.39222 | E9: =(Inputs!$B$13/(1+Inputs!$B$14)^1+Inputs!$B$13*(1+$A9)/(1+Inputs!$B$14)^2+Inputs!$B$13*(1+$A9)^2/(1+Inputs!$B$14)^3+Inputs!$B$13*(1+$A9)^3/(1+Inputs!$B$14)^4+Inputs!$B$13*(1+$A9)^4/(1+Inputs!$B$14)^5+(Inputs!$B$13*(1+$A9)^4*(1+E$4)/(Inputs!$B$14-E$4))/(1+Inputs!$B$14)^5)/Inputs!$B$6 -> 437.19244 | F9: =(Inputs!$B$13/(1+Inputs!$B$14)^1+Inputs!$B$13*(1+$A9)/(1+Inputs!$B$14)^2+Inputs!$B$13*(1+$A9)^2/(1+Inputs!$B$14)^3+Inputs!$B$13*(1+$A9)^3/(1+Inputs!$B$14)^4+Inputs!$B$13*(1+$A9)^4/(1+Inputs!$B$14)^5+(Inputs!$B$13*(1+$A9)^4*(1+F$4)/(Inputs!$B$14-F$4))/(1+Inputs!$B$14)^5)/Inputs!$B$6 -> 467.29269 | H9: 0.08 | I9: =$I$19/H9 -> 196008.85 | J9: =(I9/Inputs!$B$12)^(1/4)-1 -> 0.34440806
A10: 0.175 | B10: =(Inputs!$B$13/(1+Inputs!$B$14)^1+Inputs!$B$13*(1+$A10)/(1+Inputs!$B$14)^2+Inputs!$B$13*(1+$A10)^2/(1+Inputs!$B$14)^3+Inputs!$B$13*(1+$A10)^3/(1+Inputs!$B$14)^4+Inputs!$B$13*(1+$A10)^4/(1+Inputs!$B$14)^5+(Inputs!$B$13*(1+$A10)^4*(1+B$4)/(Inputs!$B$14-B$4))/(1+Inputs!$B$14)^5)/Inputs!$B$6 -> 398.44833 | C10: =(Inputs!$B$13/(1+Inputs!$B$14)^1+Inputs!$B$13*(1+$A10)/(1+Inputs!$B$14)^2+Inputs!$B$13*(1+$A10)^2/(1+Inputs!$B$14)^3+Inputs!$B$13*(1+$A10)^3/(1+Inputs!$B$14)^4+Inputs!$B$13*(1+$A10)^4/(1+Inputs!$B$14)^5+(Inputs!$B$13*(1+$A10)^4*(1+C$4)/(Inputs!$B$14-C$4))/(1+Inputs!$B$14)^5)/Inputs!$B$6 -> 419.7711 | D10: =(Inputs!$B$13/(1+Inputs!$B$14)^1+Inputs!$B$13*(1+$A10)/(1+Inputs!$B$14)^2+Inputs!$B$13*(1+$A10)^2/(1+Inputs!$B$14)^3+Inputs!$B$13*(1+$A10)^3/(1+Inputs!$B$14)^4+Inputs!$B$13*(1+$A10)^4/(1+Inputs!$B$14)^5+(Inputs!$B$13*(1+$A10)^4*(1+D$4)/(Inputs!$B$14-D$4))/(1+Inputs!$B$14)^5)/Inputs!$B$6 -> 444.13997 | E10: =(Inputs!$B$13/(1+Inputs!$B$14)^1+Inputs!$B$13*(1+$A10)/(1+Inputs!$B$14)^2+Inputs!$B$13*(1+$A10)^2/(1+Inputs!$B$14)^3+Inputs!$B$13*(1+$A10)^3/(1+Inputs!$B$14)^4+Inputs!$B$13*(1+$A10)^4/(1+Inputs!$B$14)^5+(Inputs!$B$13*(1+$A10)^4*(1+E$4)/(Inputs!$B$14-E$4))/(1+Inputs!$B$14)^5)/Inputs!$B$6 -> 472.25791 | F10: =(Inputs!$B$13/(1+Inputs!$B$14)^1+Inputs!$B$13*(1+$A10)/(1+Inputs!$B$14)^2+Inputs!$B$13*(1+$A10)^2/(1+Inputs!$B$14)^3+Inputs!$B$13*(1+$A10)^3/(1+Inputs!$B$14)^4+Inputs!$B$13*(1+$A10)^4/(1+Inputs!$B$14)^5+(Inputs!$B$13*(1+$A10)^4*(1+F$4)/(Inputs!$B$14-F$4))/(1+Inputs!$B$14)^5)/Inputs!$B$6 -> 505.06217 | H10: 0.09 | I10: =$I$19/H10 -> 174230.09 | J10: =(I10/Inputs!$B$12)^(1/4)-1 -> 0.3053981
A11: 0.2 | B11: =(Inputs!$B$13/(1+Inputs!$B$14)^1+Inputs!$B$13*(1+$A11)/(1+Inputs!$B$14)^2+Inputs!$B$13*(1+$A11)^2/(1+Inputs!$B$14)^3+Inputs!$B$13*(1+$A11)^3/(1+Inputs!$B$14)^4+Inputs!$B$13*(1+$A11)^4/(1+Inputs!$B$14)^5+(Inputs!$B$13*(1+$A11)^4*(1+B$4)/(Inputs!$B$14-B$4))/(1+Inputs!$B$14)^5)/Inputs!$B$6 -> 429.24492 | C11: =(Inputs!$B$13/(1+Inputs!$B$14)^1+Inputs!$B$13*(1+$A11)/(1+Inputs!$B$14)^2+Inputs!$B$13*(1+$A11)^2/(1+Inputs!$B$14)^3+Inputs!$B$13*(1+$A11)^3/(1+Inputs!$B$14)^4+Inputs!$B$13*(1+$A11)^4/(1+Inputs!$B$14)^5+(Inputs!$B$13*(1+$A11)^4*(1+C$4)/(Inputs!$B$14-C$4))/(1+Inputs!$B$14)^5)/Inputs!$B$6 -> 452.44113 | D11: =(Inputs!$B$13/(1+Inputs!$B$14)^1+Inputs!$B$13*(1+$A11)/(1+Inputs!$B$14)^2+Inputs!$B$13*(1+$A11)^2/(1+Inputs!$B$14)^3+Inputs!$B$13*(1+$A11)^3/(1+Inputs!$B$14)^4+Inputs!$B$13*(1+$A11)^4/(1+Inputs!$B$14)^5+(Inputs!$B$13*(1+$A11)^4*(1+D$4)/(Inputs!$B$14-D$4))/(1+Inputs!$B$14)^5)/Inputs!$B$6 -> 478.95109 | E11: =(Inputs!$B$13/(1+Inputs!$B$14)^1+Inputs!$B$13*(1+$A11)/(1+Inputs!$B$14)^2+Inputs!$B$13*(1+$A11)^2/(1+Inputs!$B$14)^3+Inputs!$B$13*(1+$A11)^3/(1+Inputs!$B$14)^4+Inputs!$B$13*(1+$A11)^4/(1+Inputs!$B$14)^5+(Inputs!$B$13*(1+$A11)^4*(1+E$4)/(Inputs!$B$14-E$4))/(1+Inputs!$B$14)^5)/Inputs!$B$6 -> 509.53951 | F11: =(Inputs!$B$13/(1+Inputs!$B$14)^1+Inputs!$B$13*(1+$A11)/(1+Inputs!$B$14)^2+Inputs!$B$13*(1+$A11)^2/(1+Inputs!$B$14)^3+Inputs!$B$13*(1+$A11)^3/(1+Inputs!$B$14)^4+Inputs!$B$13*(1+$A11)^4/(1+Inputs!$B$14)^5+(Inputs!$B$13*(1+$A11)^4*(1+F$4)/(Inputs!$B$14-F$4))/(1+Inputs!$B$14)^5)/Inputs!$B$6 -> 545.22599 | H11: 0.1 | I11: =$I$19/H11 -> 156807.08 | J11: =(I11/Inputs!$B$12)^(1/4)-1 -> 0.27146264
A12: 0.25 | B12: =(Inputs!$B$13/(1+Inputs!$B$14)^1+Inputs!$B$13*(1+$A12)/(1+Inputs!$B$14)^2+Inputs!$B$13*(1+$A12)^2/(1+Inputs!$B$14)^3+Inputs!$B$13*(1+$A12)^3/(1+Inputs!$B$14)^4+Inputs!$B$13*(1+$A12)^4/(1+Inputs!$B$14)^5+(Inputs!$B$13*(1+$A12)^4*(1+B$4)/(Inputs!$B$14-B$4))/(1+Inputs!$B$14)^5)/Inputs!$B$6 -> 496.58901 | C12: =(Inputs!$B$13/(1+Inputs!$B$14)^1+Inputs!$B$13*(1+$A12)/(1+Inputs!$B$14)^2+Inputs!$B$13*(1+$A12)^2/(1+Inputs!$B$14)^3+Inputs!$B$13*(1+$A12)^3/(1+Inputs!$B$14)^4+Inputs!$B$13*(1+$A12)^4/(1+Inputs!$B$14)^5+(Inputs!$B$13*(1+$A12)^4*(1+C$4)/(Inputs!$B$14-C$4))/(1+Inputs!$B$14)^5)/Inputs!$B$6 -> 523.89967 | D12: =(Inputs!$B$13/(1+Inputs!$B$14)^1+Inputs!$B$13*(1+$A12)/(1+Inputs!$B$14)^2+Inputs!$B$13*(1+$A12)^2/(1+Inputs!$B$14)^3+Inputs!$B$13*(1+$A12)^3/(1+Inputs!$B$14)^4+Inputs!$B$13*(1+$A12)^4/(1+Inputs!$B$14)^5+(Inputs!$B$13*(1+$A12)^4*(1+D$4)/(Inputs!$B$14-D$4))/(1+Inputs!$B$14)^5)/Inputs!$B$6 -> 555.11185 | E12: =(Inputs!$B$13/(1+Inputs!$B$14)^1+Inputs!$B$13*(1+$A12)/(1+Inputs!$B$14)^2+Inputs!$B$13*(1+$A12)^2/(1+Inputs!$B$14)^3+Inputs!$B$13*(1+$A12)^3/(1+Inputs!$B$14)^4+Inputs!$B$13*(1+$A12)^4/(1+Inputs!$B$14)^5+(Inputs!$B$13*(1+$A12)^4*(1+E$4)/(Inputs!$B$14-E$4))/(1+Inputs!$B$14)^5)/Inputs!$B$6 -> 591.12591 | F12: =(Inputs!$B$13/(1+Inputs!$B$14)^1+Inputs!$B$13*(1+$A12)/(1+Inputs!$B$14)^2+Inputs!$B$13*(1+$A12)^2/(1+Inputs!$B$14)^3+Inputs!$B$13*(1+$A12)^3/(1+Inputs!$B$14)^4+Inputs!$B$13*(1+$A12)^4/(1+Inputs!$B$14)^5+(Inputs!$B$13*(1+$A12)^4*(1+F$4)/(Inputs!$B$14-F$4))/(1+Inputs!$B$14)^5)/Inputs!$B$6 -> 633.14231 | H12: 0.11 | I12: =$I$19/H12 -> 142551.89 | J12: =(I12/Inputs!$B$12)^(1/4)-1 -> 0.2415249
A13: 0.3 | B13: =(Inputs!$B$13/(1+Inputs!$B$14)^1+Inputs!$B$13*(1+$A13)/(1+Inputs!$B$14)^2+Inputs!$B$13*(1+$A13)^2/(1+Inputs!$B$14)^3+Inputs!$B$13*(1+$A13)^3/(1+Inputs!$B$14)^4+Inputs!$B$13*(1+$A13)^4/(1+Inputs!$B$14)^5+(Inputs!$B$13*(1+$A13)^4*(1+B$4)/(Inputs!$B$14-B$4))/(1+Inputs!$B$14)^5)/Inputs!$B$6 -> 572.12585 | C13: =(Inputs!$B$13/(1+Inputs!$B$14)^1+Inputs!$B$13*(1+$A13)/(1+Inputs!$B$14)^2+Inputs!$B$13*(1+$A13)^2/(1+Inputs!$B$14)^3+Inputs!$B$13*(1+$A13)^3/(1+Inputs!$B$14)^4+Inputs!$B$13*(1+$A13)^4/(1+Inputs!$B$14)^5+(Inputs!$B$13*(1+$A13)^4*(1+C$4)/(Inputs!$B$14-C$4))/(1+Inputs!$B$14)^5)/Inputs!$B$6 -> 604.07546 | D13: =(Inputs!$B$13/(1+Inputs!$B$14)^1+Inputs!$B$13*(1+$A13)/(1+Inputs!$B$14)^2+Inputs!$B$13*(1+$A13)^2/(1+Inputs!$B$14)^3+Inputs!$B$13*(1+$A13)^3/(1+Inputs!$B$14)^4+Inputs!$B$13*(1+$A13)^4/(1+Inputs!$B$14)^5+(Inputs!$B$13*(1+$A13)^4*(1+D$4)/(Inputs!$B$14-D$4))/(1+Inputs!$B$14)^5)/Inputs!$B$6 -> 640.5893 | E13: =(Inputs!$B$13/(1+Inputs!$B$14)^1+Inputs!$B$13*(1+$A13)/(1+Inputs!$B$14)^2+Inputs!$B$13*(1+$A13)^2/(1+Inputs!$B$14)^3+Inputs!$B$13*(1+$A13)^3/(1+Inputs!$B$14)^4+Inputs!$B$13*(1+$A13)^4/(1+Inputs!$B$14)^5+(Inputs!$B$13*(1+$A13)^4*(1+E$4)/(Inputs!$B$14-E$4))/(1+Inputs!$B$14)^5)/Inputs!$B$6 -> 682.72065 | F13: =(Inputs!$B$13/(1+Inputs!$B$14)^1+Inputs!$B$13*(1+$A13)/(1+Inputs!$B$14)^2+Inputs!$B$13*(1+$A13)^2/(1+Inputs!$B$14)^3+Inputs!$B$13*(1+$A13)^3/(1+Inputs!$B$14)^4+Inputs!$B$13*(1+$A13)^4/(1+Inputs!$B$14)^5+(Inputs!$B$13*(1+$A13)^4*(1+F$4)/(Inputs!$B$14-F$4))/(1+Inputs!$B$14)^5)/Inputs!$B$6 -> 731.8739 | H13: 0.12 | I13: =$I$19/H13 -> 130672.57 | J13: =(I13/Inputs!$B$12)^(1/4)-1 -> 0.21480982
H14: 0.13 | I14: =$I$19/H14 -> 120620.83 | J14: =(I14/Inputs!$B$12)^(1/4)-1 -> 0.19074226
H15: 0.14 | I15: =$I$19/H15 -> 112005.06 | J15: =(I15/Inputs!$B$12)^(1/4)-1 -> 0.16888449
H17: FY31 other-segment OI ($mm) | I17: =Inputs!B29*(1+Inputs!B26)^4*Inputs!B19+Inputs!B30*(1+Inputs!B27)^4*Inputs!B20+Inputs!B31*(1+Inputs!B28)^4*Inputs!B21+Inputs!B22*(1+Inputs!B23)^4 -> 8945.8113
H18: Required FY31 OI ($mm) | I18: =Inputs!B17/Inputs!B25/(1-Inputs!B24) -> 24626.519
H19: Required FY31 AI OI ($mm) | I19: =I18-I17 -> 15680.708

Sheet Monte Carlo
A1: Monte Carlo, seeded 5,000 simulations
A3: Metric | B3: Value | D3: Variable | E3: Distribution | F3: Low | G3: Mode | H3: High
A4: Simulations | B4: 5000 | D4: AI revenue CAGR | E4: Triangular | F4: 0.1 | G4: 0.3 | H4: 0.55
A5: Mean value per share | B5: =AVERAGE(N17:N5016) -> 360.6215 | D5: AI operating margin | E5: Triangular | F5: 0.04 | G5: 0.075 | H5: 0.12
A6: Median value per share | B6: =MEDIAN(N17:N5016) -> 352.67117 | D6: Traditional server growth | E6: Triangular | F6: 0 | G6: 0.03 | H6: 0.06
A7: 5th percentile | B7: =PERCENTILE(N17:N5016,0.05) -> 271.24063 | D7: Storage growth | E7: Triangular | F7: 0.01 | G7: 0.04 | H7: 0.08
A8: 25th percentile | B8: =PERCENTILE(N17:N5016,0.25) -> 314.3029 | D8: CSG growth | E8: Triangular | F8: -0.02 | G8: 0.015 | H8: 0.04
A9: 75th percentile | B9: =PERCENTILE(N17:N5016,0.75) -> 398.63063 | D9: Tax rate | E9: Triangular | F9: 0.15 | G9: 0.18 | H9: 0.23
A10: 95th percentile | B10: =PERCENTILE(N17:N5016,0.95) -> 477.27727 | D10: FCFE conversion | E10: Triangular | F10: 0.9 | G10: 1.05 | H10: 1.2
A11: Standard deviation | B11: =STDEV(N17:N5016) -> 63.568061 | D11: Cost of equity | E11: Triangular | F11: 0.085 | G11: 0.095 | H11: 0.11
A12: Probability value exceeds current price | B12: =AVERAGE(O17:O5016) -> 0.2618 | D12: Terminal growth | E12: Triangular | F12: 0.015 | G12: 0.025 | H12: 0.035
A13: Current share price | B13: =Inputs!B4 -> 395.9
D14: AI growth / margin correlation | F14: -0.5
A15: Distribution parameters and the correlation above document the seeded draw (numpy seed 42, Gaussian copula on AI growth and AI margin). Changing them requires re-running the simulation.
A16: Sim | B16: AI CAGR | C16: AI margin | D16: Trad growth | E16: Storage growth | F16: CSG growth | G16: Tax | H16: FCFE conv | I16: Cost equity | J16: Terminal growth | K16: FY31 AI rev | L16: FY31 FCFE | M16: Equity value | N16: Value / share | O16: Above current | P16: r - g | Q16: OI FY27 | R16: OI FY28 | S16: OI FY29 | T16: OI FY30 | U16: OI FY31 | V16: conv FY27 | W16: FCFE FY27 | X16: FCFE FY28 | Y16: FCFE FY29 | Z16: FCFE FY30 | AA16: FCFE FY31 | AB16: PV explicit | AC16: TV | AD16: PV TV
A17: 1 | B17: 0.34316017 | C17: 0.060230428 | D17: 0.040165862 | E17: 0.019048645 | F17: 0.0027324412 | G17: 0.17414592 | H17: 1.1541384 | I17: 0.09259729 | J17: 0.027551943 | K17: =Inputs!$B$12*(1+$B17)^4 -> 195282.11 | L17: =AA17 -> 19353.163 | M17: =AB17+AD17 -> 255311.28 | N17: =M17/Inputs!$B$6 -> 389.19402 | O17: =IF(N17>Inputs!$B$4,1,0) -> 0 | P17: =I17-J17 -> 0.065045347 | Q17: =Inputs!$B$12*(1+$B17)^0*$C17+Inputs!$B$29*(1+$D17)^0*Inputs!$B$19+Inputs!$B$30*(1+$E17)^0*Inputs!$B$20+Inputs!$B$31*(1+$F17)^0*Inputs!$B$21+Inputs!$B$22*(1+Inputs!$B$23)^0 -> 11635.87 | R17: =Inputs!$B$12*(1+$B17)^1*$C17+Inputs!$B$29*(1+$D17)^1*Inputs!$B$19+Inputs!$B$30*(1+$E17)^1*Inputs!$B$20+Inputs!$B$31*(1+$F17)^1*Inputs!$B$21+Inputs!$B$22*(1+Inputs!$B$23)^1 -> 12999.64 | S17: =Inputs!$B$12*(1+$B17)^2*$C17+Inputs!$B$29*(1+$D17)^2*Inputs!$B$19+Inputs!$B$30*(1+$E17)^2*Inputs!$B$20+Inputs!$B$31*(1+$F17)^2*Inputs!$B$21+Inputs!$B$22*(1+Inputs!$B$23)^2 -> 14793.166 | T17: =Inputs!$B$12*(1+$B17)^3*$C17+Inputs!$B$29*(1+$D17)^3*Inputs!$B$19+Inputs!$B$30*(1+$E17)^3*Inputs!$B$20+Inputs!$B$31*(1+$F17)^3*Inputs!$B$21+Inputs!$B$22*(1+Inputs!$B$23)^3 -> 17162.654 | U17: =Inputs!$B$12*(1+$B17)^4*$C17+Inputs!$B$29*(1+$D17)^4*Inputs!$B$19+Inputs!$B$30*(1+$E17)^4*Inputs!$B$20+Inputs!$B$31*(1+$F17)^4*Inputs!$B$21+Inputs!$B$22*(1+Inputs!$B$23)^4 -> 20304.428 | V17: =Inputs!$B$13/(Q17*(1-$G17)) -> 1.3174421 | W17: =Inputs!$B$13 -> 12660 | X17: =R17*(1-$G17)*($V17+($H17-$V17)*1/4) -> 13705.503 | Y17: =S17*(1-$G17)*($V17+($H17-$V17)*2/4) -> 15097.645 | Z17: =T17*(1-$G17)*($V17+($H17-$V17)*3/4) -> 16937.242 | AA17: =U17*(1-$G17)*$H17 -> 19353.163 | AB17: =W17/(1+$I17)^1+X17/(1+$I17)^2+Y17/(1+$I17)^3+Z17/(1+$I17)^4+AA17/(1+$I17)^5 -> 58957.663 | AC17: =AA17*(1+$J17)/($I17-$J17) -> 305731.01 | AD17: =AC17/(1+$I17)^5 -> 196353.61
A18: 2 | B18: 0.39037452 | C18: 0.085521545 | D18: 0.02118505 | E18: 0.064348112 | F18: 0.015969897 | G18: 0.20048671 | H18: 0.96709642 | I18: 0.088321369 | J18: 0.034474264 | K18: =Inputs!$B$12*(1+$B18)^4 -> 224222.12 | L18: =AA18 -> 21807.692 | M18: =AB18+AD18 -> 337797.59 | N18: =M18/Inputs!$B$6 -> 514.93535 | O18: =IF(N18>Inputs!$B$4,1,0) -> 1 | P18: =I18-J18 -> 0.053847105 | Q18: =Inputs!$B$12*(1+$B18)^0*$C18+Inputs!$B$29*(1+$D18)^0*Inputs!$B$19+Inputs!$B$30*(1+$E18)^0*Inputs!$B$20+Inputs!$B$31*(1+$F18)^0*Inputs!$B$21+Inputs!$B$22*(1+Inputs!$B$23)^0 -> 13153.337 | R18: =Inputs!$B$12*(1+$B18)^1*$C18+Inputs!$B$29*(1+$D18)^1*Inputs!$B$19+Inputs!$B$30*(1+$E18)^1*Inputs!$B$20+Inputs!$B$31*(1+$F18)^1*Inputs!$B$21+Inputs!$B$22*(1+Inputs!$B$23)^1 -> 15390.953 | S18: =Inputs!$B$12*(1+$B18)^2*$C18+Inputs!$B$29*(1+$D18)^2*Inputs!$B$19+Inputs!$B$30*(1+$E18)^2*Inputs!$B$20+Inputs!$B$31*(1+$F18)^2*Inputs!$B$21+Inputs!$B$22*(1+Inputs!$B$23)^2 -> 18421.494 | T18: =Inputs!$B$12*(1+$B18)^3*$C18+Inputs!$B$29*(1+$D18)^3*Inputs!$B$19+Inputs!$B$30*(1+$E18)^3*Inputs!$B$20+Inputs!$B$31*(1+$F18)^3*Inputs!$B$21+Inputs!$B$22*(1+Inputs!$B$23)^3 -> 22550.878 | U18: =Inputs!$B$12*(1+$B18)^4*$C18+Inputs!$B$29*(1+$D18)^4*Inputs!$B$19+Inputs!$B$30*(1+$E18)^4*Inputs!$B$20+Inputs!$B$31*(1+$F18)^4*Inputs!$B$21+Inputs!$B$22*(1+Inputs!$B$23)^4 -> 28204.23 | V18: =Inputs!$B$13/(Q18*(1-$G18)) -> 1.2038492 | W18: =Inputs!$B$13 -> 12660 | X18: =R18*(1-$G18)*($V18+($H18-$V18)*1/4) -> 14085.364 | Y18: =S18*(1-$G18)*($V18+($H18-$V18)*2/4) -> 15987.092 | Z18: =T18*(1-$G18)*($V18+($H18-$V18)*3/4) -> 18503.631 | AA18: =U18*(1-$G18)*$H18 -> 21807.692 | AB18: =W18/(1+$I18)^1+X18/(1+$I18)^2+Y18/(1+$I18)^3+Z18/(1+$I18)^4+AA18/(1+$I18)^5 -> 63399.389 | AC18: =AA18*(1+$J18)/($I18-$J18) -> 418954.67 | AD18: =AC18/(1+$I18)^5 -> 274398.2
A19: 3 | B19: 0.14793098 | C19: 0.07508061 | D19: 0.042042118 | E19: 0.049851967 | F19: 0.010895932 | G19: 0.19727926 | H19: 1.1639921 | I19: 0.095097156 | J19: 0.028030519 | K19: =Inputs!$B$12*(1+$B19)^4 -> 104187.2 | L19: =AA19 -> 15777.369 | M19: =AB19+AD19 -> 207293.76 | N19: =M19/Inputs!$B$6 -> 315.99658 | O19: =IF(N19>Inputs!$B$4,1,0) -> 0 | P19: =I19-J19 -> 0.067066637 | Q19: =Inputs!$B$12*(1+$B19)^0*$C19+Inputs!$B$29*(1+$D19)^0*Inputs!$B$19+Inputs!$B$30*(1+$E19)^0*Inputs!$B$20+Inputs!$B$31*(1+$F19)^0*Inputs!$B$21+Inputs!$B$22*(1+Inputs!$B$23)^0 -> 12526.881 | R19: =Inputs!$B$12*(1+$B19)^1*$C19+Inputs!$B$29*(1+$D19)^1*Inputs!$B$19+Inputs!$B$30*(1+$E19)^1*Inputs!$B$20+Inputs!$B$31*(1+$F19)^1*Inputs!$B$21+Inputs!$B$22*(1+Inputs!$B$23)^1 -> 13437.291 | S19: =Inputs!$B$12*(1+$B19)^2*$C19+Inputs!$B$29*(1+$D19)^2*Inputs!$B$19+Inputs!$B$30*(1+$E19)^2*Inputs!$B$20+Inputs!$B$31*(1+$F19)^2*Inputs!$B$21+Inputs!$B$22*(1+Inputs!$B$23)^2 -> 14456.818 | T19: =Inputs!$B$12*(1+$B19)^3*$C19+Inputs!$B$29*(1+$D19)^3*Inputs!$B$19+Inputs!$B$30*(1+$E19)^3*Inputs!$B$20+Inputs!$B$31*(1+$F19)^3*Inputs!$B$21+Inputs!$B$22*(1+Inputs!$B$23)^3 -> 15600.546 | U19: =Inputs!$B$12*(1+$B19)^4*$C19+Inputs!$B$29*(1+$D19)^4*Inputs!$B$19+Inputs!$B$30*(1+$E19)^4*Inputs!$B$20+Inputs!$B$31*(1+$F19)^4*Inputs!$B$21+Inputs!$B$22*(1+Inputs!$B$23)^4 -> 16885.739 | V19: =Inputs!$B$13/(Q19*(1-$G19)) -> 1.2590016 | W19: =Inputs!$B$13 -> 12660 | X19: =R19*(1-$G19)*($V19+($H19-$V19)*1/4) -> 13323.882 | Y19: =S19*(1-$G19)*($V19+($H19-$V19)*2/4) -> 14059.164 | Z19: =T19*(1-$G19)*($V19+($H19-$V19)*3/4) -> 14873.984 | AA19: =U19*(1-$G19)*$H19 -> 15777.369 | AB19: =W19/(1+$I19)^1+X19/(1+$I19)^2+Y19/(1+$I19)^3+Z19/(1+$I19)^4+AA19/(1+$I19)^5 -> 53736.343 | AC19: =AA19*(1+$J19)/($I19-$J19) -> 241843.3 | AD19: =AC19/(1+$I19)^5 -> 153557.42
A20: 4 | B20: 0.32521569 | C20: 0.072089336 | D20: 0.017856102 | E20: 0.047504626 | F20: 0.03733602 | G20: 0.16516251 | H20: 1.1764164 | I20: 0.10204073 | J20: 0.032063329 | K20: =Inputs!$B$12*(1+$B20)^4 -> 185053.6 | L20: =AA20 -> 22137.421 | M20: =AB20+AD20 -> 262581.94 | N20: =M20/Inputs!$B$6 -> 400.27735 | O20: =IF(N20>Inputs!$B$4,1,0) -> 1 | P20: =I20-J20 -> 0.069977397 | Q20: =Inputs!$B$12*(1+$B20)^0*$C20+Inputs!$B$29*(1+$D20)^0*Inputs!$B$19+Inputs!$B$30*(1+$E20)^0*Inputs!$B$20+Inputs!$B$31*(1+$F20)^0*Inputs!$B$21+Inputs!$B$22*(1+Inputs!$B$23)^0 -> 12347.404 | R20: =Inputs!$B$12*(1+$B20)^1*$C20+Inputs!$B$29*(1+$D20)^1*Inputs!$B$19+Inputs!$B$30*(1+$E20)^1*Inputs!$B$20+Inputs!$B$31*(1+$F20)^1*Inputs!$B$21+Inputs!$B$22*(1+Inputs!$B$23)^1 -> 14031.729 | S20: =Inputs!$B$12*(1+$B20)^2*$C20+Inputs!$B$29*(1+$D20)^2*Inputs!$B$19+Inputs!$B$30*(1+$E20)^2*Inputs!$B$20+Inputs!$B$31*(1+$F20)^2*Inputs!$B$21+Inputs!$B$22*(1+Inputs!$B$23)^2 -> 16184.464 | T20: =Inputs!$B$12*(1+$B20)^3*$C20+Inputs!$B$29*(1+$D20)^3*Inputs!$B$19+Inputs!$B$30*(1+$E20)^3*Inputs!$B$20+Inputs!$B$31*(1+$F20)^3*Inputs!$B$21+Inputs!$B$22*(1+Inputs!$B$23)^3 -> 18954.848 | U20: =Inputs!$B$12*(1+$B20)^4*$C20+Inputs!$B$29*(1+$D20)^4*Inputs!$B$19+Inputs!$B$30*(1+$E20)^4*Inputs!$B$20+Inputs!$B$31*(1+$F20)^4*Inputs!$B$21+Inputs!$B$22*(1+Inputs!$B$23)^4 -> 22540.523 | V20: =Inputs!$B$13/(Q20*(1-$G20)) -> 1.2281632 | W20: =Inputs!$B$13 -> 12660 | X20: =R20*(1-$G20)*($V20+($H20-$V20)*1/4) -> 14235.423 | Y20: =S20*(1-$G20)*($V20+($H20-$V20)*2/4) -> 16244.616 | Z20: =T20*(1-$G20)*($V20+($H20-$V20)*3/4) -> 18820.583 | AA20: =U20*(1-$G20)*$H20 -> 22137.421 | AB20: =W20/(1+$I20)^1+X20/(1+$I20)^2+Y20/(1+$I20)^3+Z20/(1+$I20)^4+AA20/(1+$I20)^5 -> 61724.763 | AC20: =AA20*(1+$J20)/($I20-$J20) -> 326494.29 | AD20: =AC20/(1+$I20)^5 -> 200857.18
A21: 5 | B21: 0.31124486 | C21: 0.065519418 | D21: 0.025437224 | E21: 0.052641816 | F21: 0.025668301 | G21: 0.18818094 | H21: 1.0594016 | I21: 0.10694915 | J21: 0.027742138 | K21: =Inputs!$B$12*(1+$B21)^4 -> 177372.56 | L21: =AA21 -> 17851.653 | M21: =AB21+AD21 -> 194179.67 | N21: =M21/Inputs!$B$6 -> 296.0056 | O21: =IF(N21>Inputs!$B$4,1,0) -> 0 | P21: =I21-J21 -> 0.079207016 | Q21: =Inputs!$B$12*(1+$B21)^0*$C21+Inputs!$B$29*(1+$D21)^0*Inputs!$B$19+Inputs!$B$30*(1+$E21)^0*Inputs!$B$20+Inputs!$B$31*(1+$F21)^0*Inputs!$B$21+Inputs!$B$22*(1+Inputs!$B$23)^0 -> 11953.209 | R21: =Inputs!$B$12*(1+$B21)^1*$C21+Inputs!$B$29*(1+$D21)^1*Inputs!$B$19+Inputs!$B$30*(1+$E21)^1*Inputs!$B$20+Inputs!$B$31*(1+$F21)^1*Inputs!$B$21+Inputs!$B$22*(1+Inputs!$B$23)^1 -> 13439.663 | S21: =Inputs!$B$12*(1+$B21)^2*$C21+Inputs!$B$29*(1+$D21)^2*Inputs!$B$19+Inputs!$B$30*(1+$E21)^2*Inputs!$B$20+Inputs!$B$31*(1+$F21)^2*Inputs!$B$21+Inputs!$B$22*(1+Inputs!$B$23)^2 -> 15316.936 | T21: =Inputs!$B$12*(1+$B21)^3*$C21+Inputs!$B$29*(1+$D21)^3*Inputs!$B$19+Inputs!$B$30*(1+$E21)^3*Inputs!$B$20+Inputs!$B$31*(1+$F21)^3*Inputs!$B$21+Inputs!$B$22*(1+Inputs!$B$23)^3 -> 17703.994 | U21: =Inputs!$B$12*(1+$B21)^4*$C21+Inputs!$B$29*(1+$D21)^4*Inputs!$B$19+Inputs!$B$30*(1+$E21)^4*Inputs!$B$20+Inputs!$B$31*(1+$F21)^4*Inputs!$B$21+Inputs!$B$22*(1+Inputs!$B$23)^4 -> 20756.713 | V21: =Inputs!$B$13/(Q21*(1-$G21)) -> 1.3046378 | W21: =Inputs!$B$13 -> 12660 | X21: =R21*(1-$G21)*($V21+($H21-$V21)*1/4) -> 13565.431 | Y21: =S21*(1-$G21)*($V21+($H21-$V21)*2/4) -> 14697.919 | Z21: =T21*(1-$G21)*($V21+($H21-$V21)*3/4) -> 16107.346 | AA21: =U21*(1-$G21)*$H21 -> 17851.653 | AB21: =W21/(1+$I21)^1+X21/(1+$I21)^2+Y21/(1+$I21)^3+Z21/(1+$I21)^4+AA21/(1+$I21)^5 -> 54812.467 | AC21: =AA21*(1+$J21)/($I21-$J21) -> 231632.21 | AD21: =AC21/(1+$I21)^5 -> 139367.21
A22: 6 | B22: 0.40395485 | C22: 0.081696885 | D22: 0.026868869 | E22: 0.034435437 | F22: 0.013234982 | G22: 0.21688912 | H22: 1.02231 | I22: 0.099399073 | J22: 0.023122647 | K22: =Inputs!$B$12*(1+$B22)^4 -> 233111.56 | L22: =AA22 -> 22219.914 | M22: =AB22+AD22 -> 247429.42 | N22: =M22/Inputs!$B$6 -> 377.17899 | O22: =IF(N22>Inputs!$B$4,1,0) -> 0 | P22: =I22-J22 -> 0.076276426 | Q22: =Inputs!$B$12*(1+$B22)^0*$C22+Inputs!$B$29*(1+$D22)^0*Inputs!$B$19+Inputs!$B$30*(1+$E22)^0*Inputs!$B$20+Inputs!$B$31*(1+$F22)^0*Inputs!$B$21+Inputs!$B$22*(1+Inputs!$B$23)^0 -> 12923.857 | R22: =Inputs!$B$12*(1+$B22)^1*$C22+Inputs!$B$29*(1+$D22)^1*Inputs!$B$19+Inputs!$B$30*(1+$E22)^1*Inputs!$B$20+Inputs!$B$31*(1+$F22)^1*Inputs!$B$21+Inputs!$B$22*(1+Inputs!$B$23)^1 -> 15069.776 | S22: =Inputs!$B$12*(1+$B22)^2*$C22+Inputs!$B$29*(1+$D22)^2*Inputs!$B$19+Inputs!$B$30*(1+$E22)^2*Inputs!$B$20+Inputs!$B$31*(1+$F22)^2*Inputs!$B$21+Inputs!$B$22*(1+Inputs!$B$23)^2 -> 18019.649 | T22: =Inputs!$B$12*(1+$B22)^3*$C22+Inputs!$B$29*(1+$D22)^3*Inputs!$B$19+Inputs!$B$30*(1+$E22)^3*Inputs!$B$20+Inputs!$B$31*(1+$F22)^3*Inputs!$B$21+Inputs!$B$22*(1+Inputs!$B$23)^3 -> 22096.704 | U22: =Inputs!$B$12*(1+$B22)^4*$C22+Inputs!$B$29*(1+$D22)^4*Inputs!$B$19+Inputs!$B$30*(1+$E22)^4*Inputs!$B$20+Inputs!$B$31*(1+$F22)^4*Inputs!$B$21+Inputs!$B$22*(1+Inputs!$B$23)^4 -> 27754.698 | V22: =Inputs!$B$13/(Q22*(1-$G22)) -> 1.2508876 | W22: =Inputs!$B$13 -> 12660 | X22: =R22*(1-$G22)*($V22+($H22-$V22)*1/4) -> 14087.728 | Y22: =S22*(1-$G22)*($V22+($H22-$V22)*2/4) -> 16038.981 | Z22: =T22*(1-$G22)*($V22+($H22-$V22)*3/4) -> 18679.062 | AA22: =U22*(1-$G22)*$H22 -> 22219.914 | AB22: =W22/(1+$I22)^1+X22/(1+$I22)^2+Y22/(1+$I22)^3+Z22/(1+$I22)^4+AA22/(1+$I22)^5 -> 61861.493 | AC22: =AA22*(1+$J22)/($I22-$J22) -> 298043.56 | AD22: =AC22/(1+$I22)^5 -> 185567.92
A23: 7 | B23: 0.3191567 | C23: 0.095059317 | D23: 0.023218932 | E23: 0.046695477 | F23: 0.023049583 | G23: 0.20729823 | H23: 0.91971193 | I23: 0.10473626 | J23: 0.029120403 | K23: =Inputs!$B$12*(1+$B23)^4 -> 181692.42 | L23: =AA23 -> 19141.833 | M23: =AB23+AD23 -> 215379.74 | N23: =M23/Inputs!$B$6 -> 328.32277 | O23: =IF(N23>Inputs!$B$4,1,0) -> 0 | P23: =I23-J23 -> 0.075615862 | Q23: =Inputs!$B$12*(1+$B23)^0*$C23+Inputs!$B$29*(1+$D23)^0*Inputs!$B$19+Inputs!$B$30*(1+$E23)^0*Inputs!$B$20+Inputs!$B$31*(1+$F23)^0*Inputs!$B$21+Inputs!$B$22*(1+Inputs!$B$23)^0 -> 13725.603 | R23: =Inputs!$B$12*(1+$B23)^1*$C23+Inputs!$B$29*(1+$D23)^1*Inputs!$B$19+Inputs!$B$30*(1+$E23)^1*Inputs!$B$20+Inputs!$B$31*(1+$F23)^1*Inputs!$B$21+Inputs!$B$22*(1+Inputs!$B$23)^1 -> 15774.768 | S23: =Inputs!$B$12*(1+$B23)^2*$C23+Inputs!$B$29*(1+$D23)^2*Inputs!$B$19+Inputs!$B$30*(1+$E23)^2*Inputs!$B$20+Inputs!$B$31*(1+$F23)^2*Inputs!$B$21+Inputs!$B$22*(1+Inputs!$B$23)^2 -> 18412.483 | T23: =Inputs!$B$12*(1+$B23)^3*$C23+Inputs!$B$29*(1+$D23)^3*Inputs!$B$19+Inputs!$B$30*(1+$E23)^3*Inputs!$B$20+Inputs!$B$31*(1+$F23)^3*Inputs!$B$21+Inputs!$B$22*(1+Inputs!$B$23)^3 -> 21824.459 | U23: =Inputs!$B$12*(1+$B23)^4*$C23+Inputs!$B$29*(1+$D23)^4*Inputs!$B$19+Inputs!$B$30*(1+$E23)^4*Inputs!$B$20+Inputs!$B$31*(1+$F23)^4*Inputs!$B$21+Inputs!$B$22*(1+Inputs!$B$23)^4 -> 26255.596 | V23: =Inputs!$B$13/(Q23*(1-$G23)) -> 1.1635698 | W23: =Inputs!$B$13 -> 12660 | X23: =R23*(1-$G23)*($V23+($H23-$V23)*1/4) -> 13787.734 | Y23: =S23*(1-$G23)*($V23+($H23-$V23)*2/4) -> 15203.382 | Z23: =T23*(1-$G23)*($V23+($H23-$V23)*3/4) -> 16965.983 | AA23: =U23*(1-$G23)*$H23 -> 19141.833 | AB23: =W23/(1+$I23)^1+X23/(1+$I23)^2+Y23/(1+$I23)^3+Z23/(1+$I23)^4+AA23/(1+$I23)^5 -> 57056.831 | AC23: =AA23*(1+$J23)/($I23-$J23) -> 260517.45 | AD23: =AC23/(1+$I23)^5 -> 158322.91
A24: 8 | B24: 0.36024325 | C24: 0.061432612 | D24: 0.0024581385 | E24: 0.056390285 | F24: -0.0014134322 | G24: 0.1913169 | H24: 0.92641449 | I24: 0.095107032 | J24: 0.026831044 | K24: =Inputs!$B$12*(1+$B24)^4 -> 205408.1 | L24: =AA24 -> 15714.092 | M24: =AB24+AD24 -> 203101.47 | N24: =M24/Inputs!$B$6 -> 309.6059 | O24: =IF(N24>Inputs!$B$4,1,0) -> 0 | P24: =I24-J24 -> 0.068275989 | Q24: =Inputs!$B$12*(1+$B24)^0*$C24+Inputs!$B$29*(1+$D24)^0*Inputs!$B$19+Inputs!$B$30*(1+$E24)^0*Inputs!$B$20+Inputs!$B$31*(1+$F24)^0*Inputs!$B$21+Inputs!$B$22*(1+Inputs!$B$23)^0 -> 11708.001 | R24: =Inputs!$B$12*(1+$B24)^1*$C24+Inputs!$B$29*(1+$D24)^1*Inputs!$B$19+Inputs!$B$30*(1+$E24)^1*Inputs!$B$20+Inputs!$B$31*(1+$F24)^1*Inputs!$B$21+Inputs!$B$22*(1+Inputs!$B$23)^1 -> 13110.129 | S24: =Inputs!$B$12*(1+$B24)^2*$C24+Inputs!$B$29*(1+$D24)^2*Inputs!$B$19+Inputs!$B$30*(1+$E24)^2*Inputs!$B$20+Inputs!$B$31*(1+$F24)^2*Inputs!$B$21+Inputs!$B$22*(1+Inputs!$B$23)^2 -> 14996.545 | T24: =Inputs!$B$12*(1+$B24)^3*$C24+Inputs!$B$29*(1+$D24)^3*Inputs!$B$19+Inputs!$B$30*(1+$E24)^3*Inputs!$B$20+Inputs!$B$31*(1+$F24)^3*Inputs!$B$21+Inputs!$B$22*(1+Inputs!$B$23)^3 -> 17539.956 | U24: =Inputs!$B$12*(1+$B24)^4*$C24+Inputs!$B$29*(1+$D24)^4*Inputs!$B$19+Inputs!$B$30*(1+$E24)^4*Inputs!$B$20+Inputs!$B$31*(1+$F24)^4*Inputs!$B$21+Inputs!$B$22*(1+Inputs!$B$23)^4 -> 20975.174 | V24: =Inputs!$B$13/(Q24*(1-$G24)) -> 1.3371268 | W24: =Inputs!$B$13 -> 12660 | X24: =R24*(1-$G24)*($V24+($H24-$V24)*1/4) -> 13087.551 | Y24: =S24*(1-$G24)*($V24+($H24-$V24)*2/4) -> 13725.495 | Z24: =T24*(1-$G24)*($V24+($H24-$V24)*3/4) -> 14596.923 | AA24: =U24*(1-$G24)*$H24 -> 15714.092 | AB24: =W24/(1+$I24)^1+X24/(1+$I24)^2+Y24/(1+$I24)^3+Z24/(1+$I24)^4+AA24/(1+$I24)^5 -> 53050.977 | AC24: =AA24*(1+$J24)/($I24-$J24) -> 236330.77 | AD24: =AC24/(1+$I24)^5 -> 150050.5
A25: 9 | B25: 0.34983099 | C25: 0.060839552 | D25: 0.020589237 | E25: 0.023770197 | F25: -0.0054075003 | G25: 0.17183722 | H25: 1.0321525 | I25: 0.093699274 | J25: 0.017571691 | K25: =Inputs!$B$12*(1+$B25)^4 -> 199190.59 | L25: =AA25 -> 17337.481 | M25: =AB25+AD25 -> 203723.91 | N25: =M25/Inputs!$B$6 -> 310.55475 | O25: =IF(N25>Inputs!$B$4,1,0) -> 0 | P25: =I25-J25 -> 0.076127583 | Q25: =Inputs!$B$12*(1+$B25)^0*$C25+Inputs!$B$29*(1+$D25)^0*Inputs!$B$19+Inputs!$B$30*(1+$E25)^0*Inputs!$B$20+Inputs!$B$31*(1+$F25)^0*Inputs!$B$21+Inputs!$B$22*(1+Inputs!$B$23)^0 -> 11672.417 | R25: =Inputs!$B$12*(1+$B25)^1*$C25+Inputs!$B$29*(1+$D25)^1*Inputs!$B$19+Inputs!$B$30*(1+$E25)^1*Inputs!$B$20+Inputs!$B$31*(1+$F25)^1*Inputs!$B$21+Inputs!$B$22*(1+Inputs!$B$23)^1 -> 12983.618 | S25: =Inputs!$B$12*(1+$B25)^2*$C25+Inputs!$B$29*(1+$D25)^2*Inputs!$B$19+Inputs!$B$30*(1+$E25)^2*Inputs!$B$20+Inputs!$B$31*(1+$F25)^2*Inputs!$B$21+Inputs!$B$22*(1+Inputs!$B$23)^2 -> 14742.436 | T25: =Inputs!$B$12*(1+$B25)^3*$C25+Inputs!$B$29*(1+$D25)^3*Inputs!$B$19+Inputs!$B$30*(1+$E25)^3*Inputs!$B$20+Inputs!$B$31*(1+$F25)^3*Inputs!$B$21+Inputs!$B$22*(1+Inputs!$B$23)^3 -> 17105.155 | U25: =Inputs!$B$12*(1+$B25)^4*$C25+Inputs!$B$29*(1+$D25)^4*Inputs!$B$19+Inputs!$B$30*(1+$E25)^4*Inputs!$B$20+Inputs!$B$31*(1+$F25)^4*Inputs!$B$21+Inputs!$B$22*(1+Inputs!$B$23)^4 -> 20282.729 | V25: =Inputs!$B$13/(Q25*(1-$G25)) -> 1.3096559 | W25: =Inputs!$B$13 -> 12660 | X25: =R25*(1-$G25)*($V25+($H25-$V25)*1/4) -> 13336.172 | Y25: =S25*(1-$G25)*($V25+($H25-$V25)*2/4) -> 14295.73 | Z25: =T25*(1-$G25)*($V25+($H25-$V25)*3/4) -> 15604.089 | AA25: =U25*(1-$G25)*$H25 -> 17337.481 | AB25: =W25/(1+$I25)^1+X25/(1+$I25)^2+Y25/(1+$I25)^3+Z25/(1+$I25)^4+AA25/(1+$I25)^5 -> 55636.093 | AC25: =AA25*(1+$J25)/($I25-$J25) -> 231744.25 | AD25: =AC25/(1+$I25)^5 -> 148087.82
A26: 10 | B26: 0.40385592 | C26: 0.069686169 | D26: 0.024653122 | E26: 0.069261624 | F26: 0.01646229 | G26: 0.17886755 | H26: 1.1011983 | I26: 0.091209373 | J26: 0.020872547 | K26: =Inputs!$B$12*(1+$B26)^4 -> 233045.87 | L26: =AA26 -> 22955.401 | M26: =AB26+AD26 -> 279764.35 | N26: =M26/Inputs!$B$6 -> 426.47005 | O26: =IF(N26>Inputs!$B$4,1,0) -> 1 | P26: =I26-J26 -> 0.070336825 | Q26: =Inputs!$B$12*(1+$B26)^0*$C26+Inputs!$B$29*(1+$D26)^0*Inputs!$B$19+Inputs!$B$30*(1+$E26)^0*Inputs!$B$20+Inputs!$B$31*(1+$F26)^0*Inputs!$B$21+Inputs!$B$22*(1+Inputs!$B$23)^0 -> 12203.214 | R26: =Inputs!$B$12*(1+$B26)^1*$C26+Inputs!$B$29*(1+$D26)^1*Inputs!$B$19+Inputs!$B$30*(1+$E26)^1*Inputs!$B$20+Inputs!$B$31*(1+$F26)^1*Inputs!$B$21+Inputs!$B$22*(1+Inputs!$B$23)^1 -> 14152.292 | S26: =Inputs!$B$12*(1+$B26)^2*$C26+Inputs!$B$29*(1+$D26)^2*Inputs!$B$19+Inputs!$B$30*(1+$E26)^2*Inputs!$B$20+Inputs!$B$31*(1+$F26)^2*Inputs!$B$21+Inputs!$B$22*(1+Inputs!$B$23)^2 -> 16796.517 | T26: =Inputs!$B$12*(1+$B26)^3*$C26+Inputs!$B$29*(1+$D26)^3*Inputs!$B$19+Inputs!$B$30*(1+$E26)^3*Inputs!$B$20+Inputs!$B$31*(1+$F26)^3*Inputs!$B$21+Inputs!$B$22*(1+Inputs!$B$23)^3 -> 20412.14 | U26: =Inputs!$B$12*(1+$B26)^4*$C26+Inputs!$B$29*(1+$D26)^4*Inputs!$B$19+Inputs!$B$30*(1+$E26)^4*Inputs!$B$20+Inputs!$B$31*(1+$F26)^4*Inputs!$B$21+Inputs!$B$22*(1+Inputs!$B$23)^4 -> 25386.692 | V26: =Inputs!$B$13/(Q26*(1-$G26)) -> 1.2634157 | W26: =Inputs!$B$13 -> 12660 | X26: =R26*(1-$G26)*($V26+($H26-$V26)*1/4) -> 14210.757 | Y26: =S26*(1-$G26)*($V26+($H26-$V26)*2/4) -> 16306.573 | Z26: =T26*(1-$G26)*($V26+($H26-$V26)*3/4) -> 19136.996 | AA26: =U26*(1-$G26)*$H26 -> 22955.401 | AB26: =W26/(1+$I26)^1+X26/(1+$I26)^2+Y26/(1+$I26)^3+Z26/(1+$I26)^4+AA26/(1+$I26)^5 -> 64420.139 | AC26: =AA26*(1+$J26)/($I26-$J26) -> 333175.95 | AD26: =AC26/(1+$I26)^5 -> 215344.21
A27: 11 | B27: 0.2959596 | C27: 0.06943802 | D27: 0.023759731 | E27: 0.062601237 | F27: 0.019755957 | G27: 0.1689963 | H27: 1.1490766 | I27: 0.096319001 | J27: 0.022228734 | K27: =Inputs!$B$12*(1+$B27)^4 -> 169245.49 | L27: =AA27 -> 19926.362 | M27: =AB27+AD27 -> 233146.59 | N27: =M27/Inputs!$B$6 -> 355.40639 | O27: =IF(N27>Inputs!$B$4,1,0) -> 0 | P27: =I27-J27 -> 0.074090266 | Q27: =Inputs!$B$12*(1+$B27)^0*$C27+Inputs!$B$29*(1+$D27)^0*Inputs!$B$19+Inputs!$B$30*(1+$E27)^0*Inputs!$B$20+Inputs!$B$31*(1+$F27)^0*Inputs!$B$21+Inputs!$B$22*(1+Inputs!$B$23)^0 -> 12188.325 | R27: =Inputs!$B$12*(1+$B27)^1*$C27+Inputs!$B$29*(1+$D27)^1*Inputs!$B$19+Inputs!$B$30*(1+$E27)^1*Inputs!$B$20+Inputs!$B$31*(1+$F27)^1*Inputs!$B$21+Inputs!$B$22*(1+Inputs!$B$23)^1 -> 13677.061 | S27: =Inputs!$B$12*(1+$B27)^2*$C27+Inputs!$B$29*(1+$D27)^2*Inputs!$B$19+Inputs!$B$30*(1+$E27)^2*Inputs!$B$20+Inputs!$B$31*(1+$F27)^2*Inputs!$B$21+Inputs!$B$22*(1+Inputs!$B$23)^2 -> 15542.121 | T27: =Inputs!$B$12*(1+$B27)^3*$C27+Inputs!$B$29*(1+$D27)^3*Inputs!$B$19+Inputs!$B$30*(1+$E27)^3*Inputs!$B$20+Inputs!$B$31*(1+$F27)^3*Inputs!$B$21+Inputs!$B$22*(1+Inputs!$B$23)^3 -> 17892.144 | U27: =Inputs!$B$12*(1+$B27)^4*$C27+Inputs!$B$29*(1+$D27)^4*Inputs!$B$19+Inputs!$B$30*(1+$E27)^4*Inputs!$B$20+Inputs!$B$31*(1+$F27)^4*Inputs!$B$21+Inputs!$B$22*(1+Inputs!$B$23)^4 -> 20867.771 | V27: =Inputs!$B$13/(Q27*(1-$G27)) -> 1.2499329 | W27: =Inputs!$B$13 -> 12660 | X27: =R27*(1-$G27)*($V27+($H27-$V27)*1/4) -> 13919.772 | Y27: =S27*(1-$G27)*($V27+($H27-$V27)*2/4) -> 15492.276 | Z27: =T27*(1-$G27)*($V27+($H27-$V27)*3/4) -> 17459.868 | AA27: =U27*(1-$G27)*$H27 -> 19926.362 | AB27: =W27/(1+$I27)^1+X27/(1+$I27)^2+Y27/(1+$I27)^3+Z27/(1+$I27)^4+AA27/(1+$I27)^5 -> 59554.382 | AC27: =AA27*(1+$J27)/($I27-$J27) -> 274925.45 | AD27: =AC27/(1+$I27)^5 -> 173592.21
A28: 12 | B28: 0.43837768 | C28: 0.065272479 | D28: 0.040353115 | E28: 0.069824182 | F28: -0.0094445027 | G28: 0.20331147 | H28: 0.98345672 | I28: 0.094040714 | J28: 0.027838489 | K28: =Inputs!$B$12*(1+$B28)^4 -> 256828.37 | L28: =AA28 -> 20114.796 | M28: =AB28+AD28 -> 258861.57 | N28: =M28/Inputs!$B$6 -> 394.60605 | O28: =IF(N28>Inputs!$B$4,1,0) -> 0 | P28: =I28-J28 -> 0.066202225 | Q28: =Inputs!$B$12*(1+$B28)^0*$C28+Inputs!$B$29*(1+$D28)^0*Inputs!$B$19+Inputs!$B$30*(1+$E28)^0*Inputs!$B$20+Inputs!$B$31*(1+$F28)^0*Inputs!$B$21+Inputs!$B$22*(1+Inputs!$B$23)^0 -> 11938.393 | R28: =Inputs!$B$12*(1+$B28)^1*$C28+Inputs!$B$29*(1+$D28)^1*Inputs!$B$19+Inputs!$B$30*(1+$E28)^1*Inputs!$B$20+Inputs!$B$31*(1+$F28)^1*Inputs!$B$21+Inputs!$B$22*(1+Inputs!$B$23)^1 -> 13852.008 | S28: =Inputs!$B$12*(1+$B28)^2*$C28+Inputs!$B$29*(1+$D28)^2*Inputs!$B$19+Inputs!$B$30*(1+$E28)^2*Inputs!$B$20+Inputs!$B$31*(1+$F28)^2*Inputs!$B$21+Inputs!$B$22*(1+Inputs!$B$23)^2 -> 16534.191 | T28: =Inputs!$B$12*(1+$B28)^3*$C28+Inputs!$B$29*(1+$D28)^3*Inputs!$B$19+Inputs!$B$30*(1+$E28)^3*Inputs!$B$20+Inputs!$B$31*(1+$F28)^3*Inputs!$B$21+Inputs!$B$22*(1+Inputs!$B$23)^3 -> 20315.88 | U28: =Inputs!$B$12*(1+$B28)^4*$C28+Inputs!$B$29*(1+$D28)^4*Inputs!$B$19+Inputs!$B$30*(1+$E28)^4*Inputs!$B$20+Inputs!$B$31*(1+$F28)^4*Inputs!$B$21+Inputs!$B$22*(1+Inputs!$B$23)^4 -> 25672.717 | V28: =Inputs!$B$13/(Q28*(1-$G28)) -> 1.331065 | W28: =Inputs!$B$13 -> 12660 | X28: =R28*(1-$G28)*($V28+($H28-$V28)*1/4) -> 13730.254 | Y28: =S28*(1-$G28)*($V28+($H28-$V28)*2/4) -> 15244.135 | Z28: =T28*(1-$G28)*($V28+($H28-$V28)*3/4) -> 17324.216 | AA28: =U28*(1-$G28)*$H28 -> 20114.796 | AB28: =W28/(1+$I28)^1+X28/(1+$I28)^2+Y28/(1+$I28)^3+Z28/(1+$I28)^4+AA28/(1+$I28)^5 -> 59610.567 | AC28: =AA28*(1+$J28)/($I28-$J28) -> 312297.09 | AD28: =AC28/(1+$I28)^5 -> 199251
... A5016: 5000 | B5016: 0.42890404 | C5016: 0.065680935 | D5016: 0.030185948 | E5016: 0.047069874 | F5016: 0.013670966 | G5016: 0.18635441 | H5016: 0.93108868 | I5016: 0.09476824 | J5016: 0.019744054 | K5016: =Inputs!$B$12*(1+$B5016)^4 -> 250128.69 | L5016: =AA5016 -> 19195.263 | M5016: =AB5016+AD5016 -> 224162.25 | N5016: =M5016/Inputs!$B$6 -> 341.71075 | O5016: =IF(N5016>Inputs!$B$4,1,0) -> 0 | P5016: =I5016-J5016 -> 0.075024186 | Q5016: =Inputs!$B$12*(1+$B5016)^0*$C5016+Inputs!$B$29*(1+$D5016)^0*Inputs!$B$19+Inputs!$B$30*(1+$E5016)^0*Inputs!$B$20+Inputs!$B$31*(1+$F5016)^0*Inputs!$B$21+Inputs!$B$22*(1+Inputs!$B$23)^0 -> 11962.9 | R5016: =Inputs!$B$12*(1+$B5016)^1*$C5016+Inputs!$B$29*(1+$D5016)^1*Inputs!$B$19+Inputs!$B$30*(1+$E5016)^1*Inputs!$B$20+Inputs!$B$31*(1+$F5016)^1*Inputs!$B$21+Inputs!$B$22*(1+Inputs!$B$23)^1 -> 13863.583 | S5016: =Inputs!$B$12*(1+$B5016)^2*$C5016+Inputs!$B$29*(1+$D5016)^2*Inputs!$B$19+Inputs!$B$30*(1+$E5016)^2*Inputs!$B$20+Inputs!$B$31*(1+$F5016)^2*Inputs!$B$21+Inputs!$B$22*(1+Inputs!$B$23)^2 -> 16496.562 | T5016: =Inputs!$B$12*(1+$B5016)^3*$C5016+Inputs!$B$29*(1+$D5016)^3*Inputs!$B$19+Inputs!$B$30*(1+$E5016)^3*Inputs!$B$20+Inputs!$B$31*(1+$F5016)^3*Inputs!$B$21+Inputs!$B$22*(1+Inputs!$B$23)^3 -> 20173.074 | U5016: =Inputs!$B$12*(1+$B5016)^4*$C5016+Inputs!$B$29*(1+$D5016)^4*Inputs!$B$19+Inputs!$B$30*(1+$E5016)^4*Inputs!$B$20+Inputs!$B$31*(1+$F5016)^4*Inputs!$B$21+Inputs!$B$22*(1+Inputs!$B$23)^4 -> 25337.733 | V5016: =Inputs!$B$13/(Q5016*(1-$G5016)) -> 1.3006545 | W5016: =Inputs!$B$13 -> 12660 | X5016: =R5016*(1-$G5016)*($V5016+($H5016-$V5016)*1/4) -> 13629.259 | Y5016: =S5016*(1-$G5016)*($V5016+($H5016-$V5016)*2/4) -> 14977.624 | Z5016: =T5016*(1-$G5016)*($V5016+($H5016-$V5016)*3/4) -> 16799.129 | AA5016: =U5016*(1-$G5016)*$H5016 -> 19195.263 | AB5016: =W5016/(1+$I5016)^1+X5016/(1+$I5016)^2+Y5016/(1+$I5016)^3+Z5016/(1+$I5016)^4+AA5016/(1+$I5016)^5 -> 58252.083 | AC5016: =AA5016*(1+$J5016)/($I5016-$J5016) -> 260905.94 | AD5016: =AC5016/(1+$I5016)^5 -> 165910.17

Sheet Chart Data
A1: Year | B1: FCFE ($B) | D1: Year | E1: AI optimized servers ($B) | F1: Traditional servers ($B) | G1: Storage ($B) | H1: CSG ($B) | I1: Total revenue ($B) | K1: Bin | L1: Count | N1: AI margin | O1: Required FY31 AI revenue ($B)
A2: FY2027 | B2: ='Reverse DCF'!B5/1000 -> 12.66 | D2: FY2027 | E2: ='Segment Build'!B6/1000 -> 60 | F2: ='Segment Build'!B7/1000 -> 32.988127 | G2: ='Segment Build'!B8/1000 -> 16.735402 | H2: ='Segment Build'!B9/1000 -> 56.411512 | I2: ='Segment Build'!B11/1000 -> 167 | K2: <$200 | L2: =COUNTIF('Monte Carlo'!$N$17:$N$5016,"<200") -> 0 | N2: =Sensitivity!H5 -> 0.04 | O2: =Sensitivity!I5 -> 392017.7
A3: FY2028 | B3: ='Reverse DCF'!C5/1000 -> 14.402133 | D3: FY2028 | E3: ='Segment Build'!C6/1000 -> 83.402745 | F3: ='Segment Build'!C7/1000 -> 33.977771 | G3: ='Segment Build'!C8/1000 -> 17.404818 | H3: ='Segment Build'!C9/1000 -> 57.539742 | I3: ='Segment Build'!C11/1000 -> 193.21598 | K3: $200-$250 | L3: =COUNTIFS('Monte Carlo'!$N$17:$N$5016,">=200",'Monte Carlo'!$N$17:$N$5016,"<250") -> 63 | N3: =Sensitivity!H6 -> 0.05 | O3: =Sensitivity!I6 -> 313614.16
A4: FY2029 | B4: ='Reverse DCF'!D5/1000 -> 16.384 | D4: FY2029 | E4: ='Segment Build'!D6/1000 -> 115.93363 | F4: ='Segment Build'!D7/1000 -> 34.997104 | G4: ='Segment Build'!D8/1000 -> 18.101011 | H4: ='Segment Build'!D9/1000 -> 58.690537 | I4: ='Segment Build'!D11/1000 -> 228.63992 | K4: $250-$300 | L4: =COUNTIFS('Monte Carlo'!$N$17:$N$5016,">=250",'Monte Carlo'!$N$17:$N$5016,"<300") -> 789 | N4: =Sensitivity!H7 -> 0.06 | O4: =Sensitivity!I7 -> 261345.13
A5: FY2030 | B5: ='Reverse DCF'!E5/1000 -> 18.63859 | D5: FY2030 | E5: ='Segment Build'!E6/1000 -> 161.15305 | F5: ='Segment Build'!E7/1000 -> 36.047017 | G5: ='Segment Build'!E8/1000 -> 18.825052 | H5: ='Segment Build'!E9/1000 -> 59.864348 | I5: ='Segment Build'!E11/1000 -> 276.83463 | K5: $300-$350 | L5: =COUNTIFS('Monte Carlo'!$N$17:$N$5016,">=300",'Monte Carlo'!$N$17:$N$5016,"<350") -> 1560 | N5: =Sensitivity!H8 -> 0.07 | O5: =Sensitivity!I8 -> 224010.11
A6: FY2031 | B6: ='Reverse DCF'!F5/1000 -> 21.203433 | D6: FY2031 | E6: ='Segment Build'!F6/1000 -> 224.01011 | F6: ='Segment Build'!F7/1000 -> 37.128428 | G6: ='Segment Build'!F8/1000 -> 19.578054 | H6: ='Segment Build'!F9/1000 -> 61.061635 | I6: ='Segment Build'!F11/1000 -> 342.75175 | K6: $350-$400 | L6: =COUNTIFS('Monte Carlo'!$N$17:$N$5016,">=350",'Monte Carlo'!$N$17:$N$5016,"<400") -> 1370 | N6: =Sensitivity!H9 -> 0.08 | O6: =Sensitivity!I9 -> 196008.85
K7: $400-$450 | L7: =COUNTIFS('Monte Carlo'!$N$17:$N$5016,">=400",'Monte Carlo'!$N$17:$N$5016,"<450") -> 764 | N7: =Sensitivity!H10 -> 0.09 | O7: =Sensitivity!I10 -> 174230.09
K8: $450-$500 | L8: =COUNTIFS('Monte Carlo'!$N$17:$N$5016,">=450",'Monte Carlo'!$N$17:$N$5016,"<500") -> 311 | N8: =Sensitivity!H11 -> 0.1 | O8: =Sensitivity!I11 -> 156807.08
K9: $500-$550 | L9: =COUNTIFS('Monte Carlo'!$N$17:$N$5016,">=500",'Monte Carlo'!$N$17:$N$5016,"<550") -> 101 | N9: =Sensitivity!H12 -> 0.11 | O9: =Sensitivity!I12 -> 142551.89
K10: $550-$600 | L10: =COUNTIFS('Monte Carlo'!$N$17:$N$5016,">=550",'Monte Carlo'!$N$17:$N$5016,"<600") -> 35 | N10: =Sensitivity!H13 -> 0.12 | O10: =Sensitivity!I13 -> 130672.57
K11: $600-$700 | L11: =COUNTIFS('Monte Carlo'!$N$17:$N$5016,">=600",'Monte Carlo'!$N$17:$N$5016,"<700") -> 7 | N11: =Sensitivity!H14 -> 0.13 | O11: =Sensitivity!I14 -> 120620.83
K12: $700-$800 | L12: =COUNTIFS('Monte Carlo'!$N$17:$N$5016,">=700",'Monte Carlo'!$N$17:$N$5016,"<800") -> 0 | N12: =Sensitivity!H15 -> 0.14 | O12: =Sensitivity!I15 -> 112005.06
K13: $800-$1000 | L13: =COUNTIFS('Monte Carlo'!$N$17:$N$5016,">=800",'Monte Carlo'!$N$17:$N$5016,"<1000") -> 0
K14: $1000+ | L14: =COUNTIF('Monte Carlo'!$N$17:$N$5016,">=1000") -> 0
