Workbook

Sheet Stress Test Log
A1: MercadoLibre (MELI) | Assumption Stress Test - changed to best-fit real-life case
A2: Source: MELI Q4 2025 8-K (filed Feb 24 2026) and Q1 2026 results (May 7 2026). Edited cells = Probable (active) case and Valuation inputs.
A4: Item | B4: Driver | C4: Old | D4: New | E4: Why (real-life anchor)
A5: BASE ANCHORS (2025A)
A6: Fintech take rate | B6: B19 | C6: 4.58% | D6: 4.54% | E6: Mercado Pago rev $12.6bn / TPV $277.8bn = 4.54%
A7: Credit portfolio | B7: B23 | C7: $13,000mm | D7: $12,500mm | E7: Reported FY25 credit book = $12.5bn (+90% YoY)
A8: REVENUE BUILD (Probable case)
A9: Active buyer growth 2026 | B9: D65 | C9: 23.0% | D9: 24.0% | E9: Q1 26 Brazil buyer growth +32% YoY, fastest in 5 yrs
A10: Commerce take rate 26-30 | B10: D70:P70 | C10: 25.0->25.4% | D10: 25.2->26.0% | E10: Mercado Ads +67% YoY, near-zero marginal cost lifts take
A11: Fintech MAU growth 26/27 | B11: D73,G73 | C11: 22%/17% | D11: 24%/18% | E11: Actual fintech MAU growth ~27-30% in 2025
A12: Fintech take rate 26-30 | B12: D78:P78 | C12: 4.55->4.48% | D12: 4.58->4.74% | E12: Monetization RISING (4.37% in 24 -> 4.54% in 25); model had it falling
A13: Credit portfolio growth | B13: D83:P83 | C13: 65->14% | D13: 80->18% | E13: Book grew 90% in 25, 87% in Q1 26; near-term too low
A14: MARGIN DRIVERS (Probable case)
A15: Gross margin 29/30 | B15: M85,P85 | C15: 43.8/44.2% | D15: 43.6/44.0% | E15: Free-shipping investment keeps COGS elevated; slower recovery
A16: SG&A % 27-30 | B16: G86:P86 | C16: 15.1->13.6% | D16: 15.2->14.0% | E16: Less operating leverage than modeled; reinvestment ongoing
A17: R&D % 28-30 | B17: J87:P87 | C17: 7.5->7.1% | D17: 7.6->7.4% | E17: Heavy AI / tech spend held higher
A18: Other opex % 26-30 | B18: D88:P88 | C18: 12.8->10.8% | D18: 12.6->11.7% | E18: Bad-debt provisions stay elevated as credit book grows 80-90%
A19: -> Op margin 2030 | B19: memo | C19: 12.7% | D19: 10.9% | E19: Recovers toward, not back to, the 2024 peak
A20: VALUATION
A21: Current share price | B21: C7 | C21: $1,650.13 | D21: $1,584 | E21: MELI close 6/23/2026
A22: WACC | B22: C8 | C22: 14.0% | D22: 13.5% | E22: Build-up (no beta): 4.4% RF + 5.0% ERP + 3.5% LatAm CRP + 0.75% co-specific = 13.65% Ke; clean WACC ~12.7%; +0.8% for un-haircut FX
A23: Terminal EV/EBIT | B23: C9 | C23: 10.0x on row27 | D23: 15.0x on op income | E23: Re-pointed to TRUE operating income (row13); row27 EBIT excluded credit provisions (~2x). 15x = ~8% implied continuing growth at 13.5%
A24: RESULT
A25: Implied value / share | B25: C13 | C25: -- | D25: $2,163 | E25: Refined case
A26: Upside to current | B26: C14 | C26: -- | D26: +37% | E26: Essentially on top of street target ~$2,217

Sheet Annual
A1: MercadoLibre, Inc. (NASDAQ: MELI) | Integrated Operating Model
A2: $ in millions, except per share data. Shares in millions. Fiscal year ends December 31. Actuals 2005-2025 | Estimates 2026E-2030E
A4: ($ in millions) | B4: 2005 | C4: 2006 | D4: 2007 | E4: 2008 | F4: 2009 | G4: 2010 | H4: 2011 | I4: 2012 | J4: 2013 | K4: 2014 | L4: 2015 | M4: 2016 | N4: 2017 | O4: 2018 | P4: 2019 | Q4: 2020 | R4: 2021 | S4: 2022 | T4: 2023 | U4: 2024 | V4: 2025 | W4: 2026E | X4: 2027E | Y4: 2028E | Z4: 2029E | AA4: 2030E
A5: INCOME STATEMENT
A6: Revenue | B6: 28.249677 | C6: 52.05889 | D6: 85.126341 | E6: 137.02262 | F6: 172.84362 | G6: 216.71571 | H6: 298.93162 | I6: 373.60149 | J6: 472.595 | K6: 556.536 | L6: 651.79 | M6: 844.396 | N6: 1216.542 | O6: 1439.653 | P6: 2296.314 | Q6: 3974 | R6: 7069 | S6: 10780 | T6: 15107 | U6: 20777 | V6: 28893 | W6: ='Assumptions (Annual)'!C21 -> 39916.237 | X6: ='Assumptions (Annual)'!D21 -> 51458.663 | Y6: ='Assumptions (Annual)'!E21 -> 63236.229 | Z6: ='Assumptions (Annual)'!F21 -> 74631.355 | AA6: ='Assumptions (Annual)'!G21 -> 85669.337
A7: Cost of Revenue | B7: 6.138732 | C7: 12.085648 | D7: 18.27294 | E7: 27.536573 | F7: 35.95805 | G7: 46.549845 | H7: 72.055835 | I7: 98.085644 | J7: 130.077 | K7: 158.978 | L7: 214.994 | M7: 307.538 | N7: 496.942 | O7: 742.645 | P7: 1194.191 | Q7: 2265 | R7: 4064 | S7: 5582 | T7: 7517 | U7: 11200 | V7: 16035 | W7: =W6*(1-'Assumptions (Annual)'!C26) -> 22951.836 | X7: =X6*(1-'Assumptions (Annual)'!D26) -> 29434.355 | Y7: =Y6*(1-'Assumptions (Annual)'!E26) -> 35918.178 | Z7: =Z6*(1-'Assumptions (Annual)'!F26) -> 42092.084 | AA7: =AA6*(1-'Assumptions (Annual)'!G26) -> 47974.829
A8: Gross Profit | B8: =B6-B7 -> 22.110945 | C8: =C6-C7 -> 39.973242 | D8: =D6-D7 -> 66.853401 | E8: =E6-E7 -> 109.48605 | F8: =F6-F7 -> 136.88557 | G8: =G6-G7 -> 170.16587 | H8: =H6-H7 -> 226.87579 | I8: =I6-I7 -> 275.51585 | ... AA8: =AA6-AA7 -> 37694.508
A9: Selling, General & Administrative | B9: 19.112863 | C9: 31.509009 | D9: 40.822205 | E9: 62.735238 | F9: 68.711331 | G9: 79.711313 | H9: 103.75384 | I9: 117.2311 | J9: 148.091 | K9: 173.991 | L9: 204.951 | M9: 243.606 | N9: 447.569 | O9: 620.217 | P9: 1031.477 | Q9: 1095 | R9: 1539 | S9: 1957 | T9: 2502 | U9: 3154 | V9: 4297 | W9: =W6*'Assumptions (Annual)'!C27 -> 6187.0167 | X9: =X6*'Assumptions (Annual)'!D27 -> 7821.7168 | Y9: =Y6*'Assumptions (Annual)'!E27 -> 9358.9618 | Z9: =Z6*'Assumptions (Annual)'!F27 -> 10746.915 | AA9: =AA6*'Assumptions (Annual)'!G27 -> 11993.707
A10: Research & Development | B10: 2.18622 | C10: 3.066304 | D10: 4.369376 | E10: 7.307008 | F10: 12.140521 | G10: 15.855992 | H10: 23.349787 | I10: 28.62688 | J10: 40.888 | K10: 53.6 | L10: 76.423 | M10: 98.479 | N10: 127.16 | O10: 146.273 | P10: 223.807 | Q10: 353 | R10: 590 | S10: 1099 | T10: 1831 | U10: 1934 | V10: 2269 | W10: =W6*'Assumptions (Annual)'!C28 -> 3113.4665 | X10: =X6*'Assumptions (Annual)'!D28 -> 3962.3171 | Y10: =Y6*'Assumptions (Annual)'!E28 -> 4805.9534 | Z10: =Z6*'Assumptions (Annual)'!F28 -> 5597.3516 | AA10: =AA6*'Assumptions (Annual)'!G28 -> 6339.5309
A11: Other Operating Expenses | B11: 0 | C11: 0 | D11: 0 | E11: 1.91987 | F11: 0 | G11: 0 | H11: 0 | I11: 0 | J11: 0 | K11: 49.496 | L11: 16.226 | M11: 13.717 | N11: 88.598 | O11: 0 | P11: 0 | Q11: 133 | R11: 435 | S11: 1073 | T11: 1050 | U11: 1858 | V11: 3091 | W11: =W6*'Assumptions (Annual)'!C29 -> 5029.4458 | X11: =X6*'Assumptions (Annual)'!D29 -> 6380.8743 | Y11: =Y6*'Assumptions (Annual)'!E29 -> 7714.8199 | Z11: =Z6*'Assumptions (Annual)'!F29 -> 8955.7626 | AA11: =AA6*'Assumptions (Annual)'!G29 -> 10023.312
A12: Total Operating Expenses | B12: =B9+B10+B11 -> 21.299083 | C12: =C9+C10+C11 -> 34.575313 | D12: =D9+D10+D11 -> 45.191581 | E12: =E9+E10+E11 -> 71.962116 | F12: =F9+F10+F11 -> 80.851852 | G12: =G9+G10+G11 -> 95.567305 | H12: =H9+H10+H11 -> 127.10362 | I12: =I9+I10+I11 -> 145.85798 | ... AA12: =AA9+AA10+AA11 -> 28356.55
A13: Operating Income | B13: =B8-B12 -> 0.811862 | C13: =C8-C12 -> 5.397929 | D13: =D8-D12 -> 21.66182 | E13: =E8-E12 -> 37.523931 | F13: =F8-F12 -> 56.033719 | G13: =G8-G12 -> 74.598563 | H13: =H8-H12 -> 99.772165 | I13: =I8-I12 -> 129.65787 | ... AA13: =AA8-AA12 -> 9337.9577
A14: Interest Expense / (Income) | B14: 0.45643 | C14: 1.743315 | D14: 2.737901 | E14: 8.442427 | F14: 13.357554 | G14: 7.601671 | H14: 3.648733 | I14: 1.138379 | J14: 2.356 | K14: 11.659 | L14: 20.391 | M14: 25.605 | N14: 26.469 | O14: 56.249 | P14: 65.876 | Q14: 107 | R14: 229 | S14: 135 | T14: 174 | U14: 165 | V14: 160 | W14: =W6*'Assumptions (Annual)'!C30+'Assumptions (Annual)'!C34*0 -> 339.28801 | X14: =X6*'Assumptions (Annual)'!D30+'Assumptions (Annual)'!D34*W110 -> 411.66931 | Y14: =Y6*'Assumptions (Annual)'!E30+'Assumptions (Annual)'!E34*X110 -> 474.27171 | Z14: =Z6*'Assumptions (Annual)'!F30+'Assumptions (Annual)'!F34*Y110 -> 522.41948 | AA14: =AA6*'Assumptions (Annual)'!G30+'Assumptions (Annual)'!G34*Z110 -> 556.85069
A15: Other Expense / (Income) | B15: -0.629342 | C15: 1.339693 | D15: 4.503528 | E15: -0.3644 | F15: -0.036633 | G15: -4.868768 | H15: -12.316442 | I15: -11.599185 | J15: -11.907 | K15: -12.912 | L15: -31.686 | M15: -29.877 | N15: -24.266 | O15: -60.279 | P15: -111.791 | Q15: -60 | R15: -20 | S15: 154 | T15: 477 | U15: 34 | V15: 199 | W15: =W6*'Assumptions (Annual)'!C31 -> 199.58118 | X15: =X6*'Assumptions (Annual)'!D31 -> 257.29332 | Y15: =Y6*'Assumptions (Annual)'!E31 -> 316.18114 | Z15: =Z6*'Assumptions (Annual)'!F31 -> 373.15677 | AA15: =AA6*'Assumptions (Annual)'!G31 -> 428.34668
A16: Pretax Income | B16: =B13-B14-B15 -> 0.984774 | C16: =C13-C14-C15 -> 2.314921 | D16: =D13-D14-D15 -> 14.420391 | E16: =E13-E14-E15 -> 29.445904 | F16: =F13-F14-F15 -> 42.712798 | G16: =G13-G14-G15 -> 71.86566 | H16: =H13-H14-H15 -> 108.43987 | I16: =I13-I14-I15 -> 140.11868 | ... AA16: =AA13-AA14-AA15 -> 8352.7603
A17: Income Tax | B17: -1.369362 | C17: 1.242838 | D17: 4.727451 | E17: 10.634243 | F17: 9.504005 | G17: 15.840641 | H17: 31.659821 | I17: 38.871379 | J17: 45.583 | K17: 49.143 | L17: 44.702 | M17: 48.962 | N17: 40.29 | O17: -28.867 | P17: 64.753 | Q17: 82 | R17: 149 | S17: 298 | T17: 569 | U17: 521 | V17: 845 | W17: =W16*'Assumptions (Annual)'!C32 -> 618.20272 | X17: =X16*'Assumptions (Annual)'!D32 -> 941.17895 | Y17: =Y16*'Assumptions (Annual)'!E32 -> 1371.1195 | Z17: =Z16*'Assumptions (Annual)'!F32 -> 1871.3812 | AA17: =AA16*'Assumptions (Annual)'!G32 -> 2464.0643
A18: Net Income | B18: =B16-B17 -> 2.354136 | C18: =C16-C17 -> 1.072083 | D18: =D16-D17 -> 9.69294 | E18: =E16-E17 -> 18.811661 | F18: =F16-F17 -> 33.208793 | G18: =G16-G17 -> 56.025019 | H18: =H16-H17 -> 76.780053 | I18: =I16-I17 -> 101.2473 | ... AA18: =AA16-AA17 -> 5888.696
A19: Preferred Dividends | B19: 0.494878 | C19: 0.494878 | D19: 0.309299 | E19: 0 | F19: 0 | G19: 0 | H19: 0 | I19: 0 | J19: 0 | K19: 0 | L19: 0 | M19: 0 | N19: 0 | O19: 0 | P19: 0 | Q19: 0 | R19: 0 | S19: 0 | T19: 0 | U19: 0 | V19: 0 | W19: ='Assumptions (Annual)'!C44 -> 0 | X19: ='Assumptions (Annual)'!D44 -> 0 | Y19: ='Assumptions (Annual)'!E44 -> 0 | Z19: ='Assumptions (Annual)'!F44 -> 0 | AA19: ='Assumptions (Annual)'!G44 -> 0
A20: Net Income to Common | B20: =B18-B19 -> 1.859258 | C20: =C18-C19 -> 0.577205 | D20: =D18-D19 -> 9.383641 | E20: =E18-E19 -> 18.811661 | F20: =F18-F19 -> 33.208793 | G20: =G18-G19 -> 56.025019 | H20: =H18-H19 -> 76.780053 | I20: =I18-I19 -> 101.2473 | ... AA20: =AA18-AA19 -> 5888.696
A22: Shares Outstanding (Basic) | B22: 13.065496 | C22: 13.149139 | D22: 25.149405 | E22: 44.239443 | F22: 44.086892 | G22: 44.124018 | H22: 44.138397 | I22: 44.147861 | J22: 44.1526 | K22: 44.153884 | L22: 44.15568 | M22: 44.157251 | N22: 44.157364 | O22: 44.529614 | P22: 48.692906 | Q22: 49.740407 | R22: 49.802993 | S22: 50.345353 | T22: 50.262302 | U22: 50.697428 | V22: 50.697299 | W22: =V22*(1+'Assumptions (Annual)'!C33) -> 50.595904 | X22: =W22*(1+'Assumptions (Annual)'!D33) -> 50.494713 | Y22: =X22*(1+'Assumptions (Annual)'!E33) -> 50.393723 | Z22: =Y22*(1+'Assumptions (Annual)'!F33) -> 50.292936 | AA22: =Z22*(1+'Assumptions (Annual)'!G33) -> 50.19235
A23: Shares Outstanding (Diluted) | B23: 13.671359 | C23: =C22 -> 13.149139 | D23: 25.478336 | E23: 44.34895 | F23: 44.144368 | G23: 44.146858 | H23: 44.151437 | I23: 44.149838 | J23: 44.1526 | K23: 44.153884 | L23: 44.15568 | M23: 44.157251 | N23: 44.157364 | O23: 44.529614 | P23: 48.692906 | Q23: 49.740407 | R23: 49.802993 | S23: 51.335621 | T23: 51.00686 | U23: 50.697428 | V23: 50.69732 | W23: =V23*(1+'Assumptions (Annual)'!C33) -> 50.595925 | X23: =W23*(1+'Assumptions (Annual)'!D33) -> 50.494734 | Y23: =X23*(1+'Assumptions (Annual)'!E33) -> 50.393744 | Z23: =Y23*(1+'Assumptions (Annual)'!F33) -> 50.292957 | AA23: =Z23*(1+'Assumptions (Annual)'!G33) -> 50.192371
A24: EPS (Basic) | B24: =IF(B22=0,"",B20/B22) -> 0.1423029 | C24: =IF(C22=0,"",C20/C22) -> 0.043896791 | D24: =IF(D22=0,"",D20/D22) -> 0.37311583 | E24: =IF(E22=0,"",E20/E22) -> 0.42522373 | F24: =IF(F22=0,"",F20/F22) -> 0.75325775 | G24: =IF(G22=0,"",G20/G22) -> 1.2697171 | H24: =IF(H22=0,"",H20/H22) -> 1.7395297 | I24: =IF(I22=0,"",I20/I22) -> 2.2933681 | ... V24: =IF(V22=0,"",V20/V22) -> 39.390659 | W24: =W20/W22 -> 29.199986 | X24: =X20/X22 -> 44.54443 | Y24: =Y20/Y22 -> 65.022846 | Z24: =Z20/Z22 -> 88.924694 | AA24: =AA20/AA22 -> 117.32258
A25: EPS (Diluted) | B25: =IF(B23=0,"",B20/B23) -> 0.13599658 | C25: =IF(C23=0,"",C20/C23) -> 0.043896791 | D25: =IF(D23=0,"",D20/D23) -> 0.36829882 | E25: =IF(E23=0,"",E20/E23) -> 0.42417376 | F25: =IF(F23=0,"",F20/F23) -> 0.75227701 | G25: =IF(G23=0,"",G20/G23) -> 1.2690602 | H25: =IF(H23=0,"",H20/H23) -> 1.7390159 | I25: =IF(I23=0,"",I20/I23) -> 2.2932654 | ... V25: =IF(V23=0,"",V20/V23) -> 39.390642 | W25: =W20/W23 -> 29.199974 | X25: =X20/X23 -> 44.544411 | Y25: =Y20/Y23 -> 65.022819 | Z25: =Z20/Z23 -> 88.924658 | AA25: =AA20/AA23 -> 117.32253
A27: EBIT | B27: =B8-B9-B10 -> 0.811862 | C27: =C8-C9-C10 -> 5.397929 | D27: =D8-D9-D10 -> 21.66182 | E27: =E8-E9-E10 -> 39.443801 | F27: =F8-F9-F10 -> 56.033719 | G27: =G8-G9-G10 -> 74.598563 | H27: =H8-H9-H10 -> 99.772165 | I27: =I8-I9-I10 -> 129.65787 | ... AA27: =AA8-AA9-AA10 -> 19361.27
A28: Normalized Earnings | B28: =B27+B14-B17-B19 -> 2.142776 | C28: =C27+C14-C17-C19 -> 5.403528 | D28: =D27+D14-D17-D19 -> 19.362971 | E28: =E27+E14-E17-E19 -> 37.251985 | F28: =F27+F14-F17-F19 -> 59.887268 | G28: =G27+G14-G17-G19 -> 66.359593 | H28: =H27+H14-H17-H19 -> 71.761077 | I28: =I27+I14-I17-I19 -> 91.924871 | ... V28: =V27+V14-V17-V19 -> 5607 | W28: =W27*(1-'Assumptions (Annual)'!C32) -> 5403.0618 | X28: =X27*(1-'Assumptions (Annual)'!D32) -> 7219.3932 | Y28: =Y27*(1-'Assumptions (Annual)'!E32) -> 9272.9606 | Z28: =Z27*(1-'Assumptions (Annual)'!F32) -> 11417.478 | AA28: =AA27*(1-'Assumptions (Annual)'!G32) -> 13649.695
A29: Normalized EPS | B29: =B28/B23 -> 0.15673467 | C29: =C28/C23 -> 0.41094158 | D29: =D28/D23 -> 0.75997785 | E29: =E28/E23 -> 0.83997445 | F29: =F28/F23 -> 1.3566231 | G29: =G28/G23 -> 1.5031555 | H29: =H28/H23 -> 1.6253396 | I29: =I28/I23 -> 2.0821112 | ... AA29: =AA28/AA23 -> 271.94761
A31: Sales Growth | C31: =C6/B6-1 -> 0.84281364 | D31: =D6/C6-1 -> 0.63519316 | E31: =E6/D6-1 -> 0.60963831 | F31: =F6/E6-1 -> 0.261424 | G31: =G6/F6-1 -> 0.25382535 | H31: =H6/G6-1 -> 0.37937218 | I31: =I6/H6-1 -> 0.24978912 | J31: =J6/I6-1 -> 0.26497085 | ... AA31: =AA6/Z6-1 -> 0.14790006
A32: Gross Margin | B32: =B8/B6 -> 0.78269727 | C32: =C8/C6 -> 0.76784661 | D32: =D8/D6 -> 0.78534329 | E32: =E8/E6 -> 0.7990363 | F32: =F8/F6 -> 0.79196195 | G32: =G8/G6 -> 0.78520318 | H32: =H8/H6 -> 0.75895546 | I32: =I8/I6 -> 0.73745918 | ... AA32: =AA8/AA6 -> 0.44
A33: EBIT Margin | B33: =B27/B6 -> 0.028738806 | C33: =C27/C6 -> 0.1036889 | D33: =D27/D6 -> 0.25446671 | E33: =E27/E6 -> 0.28786343 | F33: =F27/F6 -> 0.32418737 | G33: =G27/G6 -> 0.34422314 | H33: =H27/H6 -> 0.3337625 | I33: =I27/I6 -> 0.34704859 | ... AA33: =AA27/AA6 -> 0.226
A34: Normalized Net Margin | B34: =B28/B6 -> 0.075851345 | C34: =C28/C6 -> 0.10379645 | D34: =D28/D6 -> 0.22746157 | E34: =E28/E6 -> 0.27186741 | F34: =F28/F6 -> 0.34648237 | G34: =G28/G6 -> 0.30620573 | H34: =H28/H6 -> 0.2400585 | I34: =I28/I6 -> 0.2460506 | ... AA34: =AA28/AA6 -> 0.15933
A36: BALANCE SHEET
A37: Cash & Equivalents | B37: 8.979838 | C37: 7.143027 | D37: 15.677407 | E37: 17.474112 | F37: 49.803402 | G37: 56.830466 | H37: 67.381677 | I37: 101.489 | J37: 140.2851 | K37: 223.144 | L37: 166.881 | M37: 234.14 | N37: 388.26 | O37: 464.695 | P37: 1451.424 | Q37: 2508.224 | R37: 3648 | S37: 3363 | T37: 3848 | U37: 4699 | V37: 13537 | W37: =V37+W97 -> 17418.805 | X37: =W37+X97 -> 21094.185 | Y37: =X37+Y97 -> 25929.53 | Z37: =Y37+Z97 -> 31441.813 | AA37: =Z37+AA97 -> 38245.448
A38: Short-Term Investments | B38: 3.411266 | C38: 6.320656 | D38: 52.300007 | E38: 31.6394 | F38: 14.580185 | G38: 5.342766 | H38: 74.92862 | I38: 93.694805 | J38: 76.593214 | K38: 148.81 | L38: 202.112 | M38: 259.604 | N38: 282.841 | O38: 557.319 | P38: 1779.346 | Q38: 1626.342 | R38: 2009 | S38: 4043 | T38: 6109 | U38: 9201 | V38: 11484 | W38: =W6*'Assumptions (Annual)'!C49 -> 13571.521 | X38: =X6*'Assumptions (Annual)'!D49 -> 16981.359 | Y38: =Y6*'Assumptions (Annual)'!E49 -> 20235.593 | Z38: =Z6*'Assumptions (Annual)'!F49 -> 23135.72 | AA38: =AA6*'Assumptions (Annual)'!G49 -> 25700.801
A39: Total Cash & Short-Term Investments | B39: =B37+B38 -> 12.391104 | C39: =C37+C38 -> 13.463683 | D39: =D37+D38 -> 67.977414 | E39: =E37+E38 -> 49.113512 | F39: =F37+F38 -> 64.383587 | G39: =G37+G38 -> 62.173232 | H39: =H37+H38 -> 142.3103 | I39: =I37+I38 -> 195.18381 | ... AA39: =AA37+AA38 -> 63946.249
A40: Receivables | B40: 6.548564 | C40: 12.171715 | D40: 32.374015 | E40: 6.178808 | F40: 8.654179 | G40: 18.769691 | H40: 40.670776 | I40: 55.653528 | J40: 77.930111 | K40: 131.834 | L40: 160.374 | M40: 333.339 | N40: 549.298 | O40: 395.451 | P40: 415.415 | Q40: 912.764 | R40: 1937 | S40: 3076 | T40: 3788 | U40: 5543 | V40: 7415 | W40: =W6*'Assumptions (Annual)'!C46 -> 11974.871 | X40: =X6*'Assumptions (Annual)'!D46 -> 16466.772 | Y40: =Y6*'Assumptions (Annual)'!E46 -> 20867.955 | Z40: =Z6*'Assumptions (Annual)'!F46 -> 25374.661 | AA40: =AA6*'Assumptions (Annual)'!G46 -> 29984.268
A41: Inventory | B41: 0 | C41: 0 | D41: 0 | E41: 0 | F41: 0 | G41: 0 | H41: 0 | I41: 0 | J41: 0 | K41: 0 | L41: 0.222 | M41: 1.103 | N41: 2.549 | O41: 4.612 | P41: 8.626 | Q41: 118.14 | R41: 253 | S41: 152 | T41: 238 | U41: 296 | V41: 570 | W41: =W6*'Assumptions (Annual)'!C47 -> 997.90592 | X41: =X6*'Assumptions (Annual)'!D47 -> 1389.3839 | Y41: =Y6*'Assumptions (Annual)'!E47 -> 1833.8506 | Z41: =Z6*'Assumptions (Annual)'!F47 -> 2238.9406 | AA41: =AA6*'Assumptions (Annual)'!G47 -> 2741.4188
A42: Other Current Assets | B42: 1.159354 | C42: 3.48448 | D42: 4.622741 | E42: 5.008904 | F42: 9.09725 | G42: 20.692285 | H42: 17.264482 | I42: 24.52384 | J42: 31.355806 | K42: 28.962 | L42: 15.584 | M42: 41.275 | N42: 63.971 | O42: 89.046 | P42: 134.045 | Q42: 181.337 | R42: 328 | S42: 319 | T42: 277 | U42: 403 | V42: 567 | W42: =W6*'Assumptions (Annual)'!C48 -> 798.32474 | X42: =X6*'Assumptions (Annual)'!D48 -> 1029.1733 | Y42: =Y6*'Assumptions (Annual)'!E48 -> 1264.7246 | Z42: =Z6*'Assumptions (Annual)'!F48 -> 1492.6271 | AA42: =AA6*'Assumptions (Annual)'!G48 -> 1713.3867
A43: Total Current Assets | B43: =B39+B40+B41+B42 -> 20.099022 | C43: =C39+C40+C41+C42 -> 29.119878 | D43: =D39+D40+D41+D42 -> 104.97417 | E43: =E39+E40+E41+E42 -> 60.301224 | F43: =F39+F40+F41+F42 -> 82.135016 | G43: =G39+G40+G41+G42 -> 101.63521 | H43: =H39+H40+H41+H42 -> 200.24555 | I43: =I39+I40+I41+I42 -> 275.36118 | ... AA43: =AA39+AA40+AA41+AA42 -> 98385.322
A44: Property, Plant & Equipment | B44: 2.343623 | C44: 2.93147 | D44: 4.143204 | E44: 5.94016 | F44: 5.948276 | G44: 20.817712 | H44: 30.877719 | I44: 37.726222 | J44: 131.37191 | K44: 91.545 | L44: 81.633 | M44: 124.261 | N44: 114.837 | O44: 165.614 | P44: 444.706 | Q44: 694.898 | R44: 1268 | S44: 1649 | T44: 2149 | U44: 2478 | V44: 4504 | W44: =V44+W6*'Assumptions (Annual)'!C39-W6*'Assumptions (Annual)'!C37 -> 5901.0683 | X44: =W44+X6*'Assumptions (Annual)'!D39-X6*'Assumptions (Annual)'!D37 -> 7393.3695 | Y44: =X44+Y6*'Assumptions (Annual)'!E39-Y6*'Assumptions (Annual)'!E37 -> 8911.039 | Z44: =Y44+Z6*'Assumptions (Annual)'!F39-Z6*'Assumptions (Annual)'!F37 -> 10403.666 | AA44: =Z44+AA6*'Assumptions (Annual)'!G39-AA6*'Assumptions (Annual)'!G37 -> 11860.045
A45: Long-Term Investments | B45: 0 | C45: 0 | D45: 1.323789 | E45: 9.218153 | F45: 26.627357 | G45: 78.846281 | H45: 43.933316 | I45: 85.955584 | J45: 45.719737 | K45: 205.265 | L45: 187.621 | M45: 153.803 | N45: 34.72 | O45: 276.136 | P45: 270.422 | Q45: 182.73 | R45: 150 | S45: 354 | T45: 227 | U45: 1382 | V45: 2274 | W45: =V45*(1+'Assumptions (Annual)'!C55) -> 2455.92 | X45: =W45*(1+'Assumptions (Annual)'!D55) -> 2627.8344 | Y45: =X45*(1+'Assumptions (Annual)'!E55) -> 2785.5045 | Z45: =Y45*(1+'Assumptions (Annual)'!F55) -> 2924.7797 | AA45: =Z45*(1+'Assumptions (Annual)'!G55) -> 3071.0187
A46: Goodwill & Intangibles | B46: 20.564179 | C46: 21.342315 | D46: 23.428646 | E46: 72.911546 | F46: 64.338564 | G46: 64.637481 | H46: 68.588805 | I46: 67.645928 | J46: 61.692803 | K46: 92 | L46: 115.536 | M46: 118.074 | N46: 115.453 | O46: 107.464 | P46: 101.884 | Q46: 99.366 | R46: 193 | S46: 178 | T46: 198 | U46: 210 | V46: 196 | W46: ='Assumptions (Annual)'!C57 -> 196 | X46: ='Assumptions (Annual)'!D57 -> 196 | Y46: ='Assumptions (Annual)'!E57 -> 196 | Z46: ='Assumptions (Annual)'!F57 -> 196 | AA46: ='Assumptions (Annual)'!G57 -> 196
A47: Other Long-Term Assets | B47: 1.412949 | C47: 0.418909 | D47: 0.622991 | E47: 8.367666 | F47: 3.565436 | G47: 3.746341 | H47: 12.286041 | I47: 11.980367 | J47: 27.414089 | K47: 45.288 | L47: 73.643 | M47: 101.836 | N47: 121.258 | O47: 179.182 | P47: 175.823 | Q47: 202.531 | R47: 315 | S47: 602 | T47: 778 | U47: 984 | V47: 2120 | W47: =W6*'Assumptions (Annual)'!C53 -> 2913.8853 | X47: =X6*'Assumptions (Annual)'!D53 -> 3756.4824 | Y47: =Y6*'Assumptions (Annual)'!E53 -> 4616.2447 | Z47: =Z6*'Assumptions (Annual)'!F53 -> 5448.0889 | AA47: =AA6*'Assumptions (Annual)'!G53 -> 6253.8616
A48: Total Long-Term Assets | B48: =B44+B45+B46+B47 -> 24.320751 | C48: =C44+C45+C46+C47 -> 24.692694 | D48: =D44+D45+D46+D47 -> 29.51863 | E48: =E44+E45+E46+E47 -> 96.437525 | F48: =F44+F45+F46+F47 -> 100.47963 | G48: =G44+G45+G46+G47 -> 168.04782 | H48: =H44+H45+H46+H47 -> 155.68588 | I48: =I44+I45+I46+I47 -> 203.3081 | ... AA48: =AA44+AA45+AA46+AA47 -> 21380.925
A49: Total Assets | B49: =B43+B48 -> 44.419773 | C49: =C43+C48 -> 53.812572 | D49: =D43+D48 -> 134.4928 | E49: =E43+E48 -> 156.73875 | F49: =F43+F48 -> 182.61465 | G49: =G43+G48 -> 269.68302 | H49: =H43+H48 -> 355.93144 | I49: =I43+I48 -> 478.66928 | ... AA49: =AA43+AA48 -> 119766.25
A51: Accounts Payable | B51: 8.505247 | C51: 17.516569 | D51: 29.474551 | E51: 36.396861 | F51: 43.053044 | G51: 66.020328 | H51: 106.83696 | I51: 148.87618 | J51: 195.81208 | K51: 263.143 | L51: 308.625 | M51: 540.87 | N51: 894.257 | O51: 991.28 | P51: 1395.01 | Q51: 2757.641 | R51: 4083 | S51: 5736 | T51: 8229 | U51: 12841 | V51: 22218 | W51: =W6*'Assumptions (Annual)'!C50 -> 30735.502 | X51: =X6*'Assumptions (Annual)'!D50 -> 39880.464 | Y51: =Y6*'Assumptions (Annual)'!E50 -> 49324.258 | Z51: =Z6*'Assumptions (Annual)'!F50 -> 58212.457 | AA51: =AA6*'Assumptions (Annual)'!G50 -> 67250.429
A52: Deferred Revenue | B52: 0 | C52: 0 | D52: 0 | E52: 0 | F52: 0 | G52: 0 | H52: 0 | I52: 0 | J52: 0 | K52: 0 | L52: 0 | M52: 0 | N52: 0 | O52: 0 | P52: 0 | Q52: 0 | R52: 0 | S52: 0 | T52: 0 | U52: 0 | V52: 0 | W52: 0 | X52: 0 | Y52: 0 | Z52: 0 | AA52: 0
A53: Current Debt | B53: 0.131085 | C53: 0.097527 | D53: 9.713227 | E53: 14.963421 | F53: 3.213992 | G53: 0.100031 | H53: 0.146194 | I53: 0.08457 | J53: 13.370823 | K53: 1.642 | L53: 1.965 | M53: 11.583 | N53: 56.325 | O53: 132.949 | P53: 209.397 | Q53: 603.639 | R53: 1377 | S53: 2273 | T53: 2458 | U53: 3069 | V53: 5053 | W53: =W112+W110 -> 6985.3414 | X53: =X112+X110 -> 8747.9728 | Y53: =Y112+Y110 -> 10433.978 | Z53: =Z112+Z110 -> 11941.017 | AA53: =AA112+AA110 -> 13278.747
A54: Other Current Liabilities | B54: 2.262507 | C54: 2.046823 | D54: 2.563728 | E54: 4.949603 | F54: 14.225856 | G54: 22.274108 | H54: 11.320368 | I54: 20.570519 | J54: 14.98271 | K54: 27.838 | L54: 11.885 | M54: 24.148 | N54: 17.45 | O54: 41.995 | P54: 147.913 | Q54: 274.6 | R54: 377 | S54: 553 | T54: 576 | U54: 693 | V54: 1362 | W54: =W6*'Assumptions (Annual)'!C51 -> 1876.0631 | X54: =X6*'Assumptions (Annual)'!D51 -> 2418.5572 | Y54: =Y6*'Assumptions (Annual)'!E51 -> 2972.1027 | Z54: =Z6*'Assumptions (Annual)'!F51 -> 3507.6737 | AA54: =AA6*'Assumptions (Annual)'!G51 -> 4026.4588
A55: Total Current Liabilities | B55: =B51+B52+B53+B54 -> 10.898839 | C55: =C51+C52+C53+C54 -> 19.660919 | D55: =D51+D52+D53+D54 -> 41.751506 | E55: =E51+E52+E53+E54 -> 56.309885 | F55: =F51+F52+F53+F54 -> 60.492892 | G55: =G51+G52+G53+G54 -> 88.394467 | H55: =H51+H52+H53+H54 -> 118.30352 | I55: =I51+I52+I53+I54 -> 169.53127 | ... AA55: =AA51+AA52+AA53+AA54 -> 84555.635
A56: Long-Term Debt | B56: 12 | C56: 9 | D56: 0 | E56: 3.050061 | F56: 0 | G56: 0.188846 | H56: 0.136227 | I56: 0.059493 | J56: 2.489819 | K56: 282.184 | L56: 294.342 | M56: 301.94 | N56: 312.089 | O56: 602.228 | P56: 808.026 | Q56: 1104.477 | R56: 2605 | S56: 3141 | T56: 2875 | U56: 3781 | V56: 6339 | W56: =V56*(1+'Assumptions (Annual)'!C56) -> 7099.68 | X56: =W56*(1+'Assumptions (Annual)'!D56) -> 7809.648 | Y56: =X56*(1+'Assumptions (Annual)'!E56) -> 8434.4198 | Z56: =Y56*(1+'Assumptions (Annual)'!F56) -> 9024.8292 | AA56: =Z56*(1+'Assumptions (Annual)'!G56) -> 9566.319
A57: Other Long-Term Liabilities | B57: 0.346087 | C57: 1.803315 | D57: 1.068155 | E57: 3.954822 | F57: 7.92852 | G57: 9.38144 | H57: 14.312668 | I57: 15.264885 | J57: 18.223737 | K57: 36.253 | L57: 47.331 | M57: 60.04 | N57: 67.287 | O57: 134.367 | P57: 139.382 | Q57: 134.397 | R57: 128 | S57: 206 | T57: 403 | U57: 461 | V57: 947 | W57: =W6*'Assumptions (Annual)'!C54 -> 1317.2358 | X57: =X6*'Assumptions (Annual)'!D54 -> 1698.1359 | Y57: =Y6*'Assumptions (Annual)'!E54 -> 2086.7955 | Z57: =Z6*'Assumptions (Annual)'!F54 -> 2462.8347 | AA57: =AA6*'Assumptions (Annual)'!G54 -> 2827.0881
A58: Total Long-Term Liabilities | B58: =B56+B57 -> 12.346087 | C58: =C56+C57 -> 10.803315 | D58: =D56+D57 -> 1.068155 | E58: =E56+E57 -> 7.004883 | F58: =F56+F57 -> 7.92852 | G58: =G56+G57 -> 9.570286 | H58: =H56+H57 -> 14.448895 | I58: =I56+I57 -> 15.324378 | ... AA58: =AA56+AA57 -> 12393.407
A59: Total Liabilities | B59: =B55+B58 -> 23.244926 | C59: =C55+C58 -> 30.464234 | D59: =D55+D58 -> 42.819661 | E59: =E55+E58 -> 63.314768 | F59: =F55+F58 -> 68.421412 | G59: =G55+G58 -> 97.964753 | H59: =H55+H58 -> 132.75242 | I59: =I55+I58 -> 184.85565 | ... AA59: =AA55+AA58 -> 96949.042
A61: Shareholders' Equity | B61: -42.40682 | C61: -40.728207 | D61: 91.673139 | E61: 93.423981 | F61: 114.19324 | G61: 171.71827 | H61: 219.17902 | I61: 289.81363 | J61: 343.48361 | K61: 355.788 | L61: 339.458 | M61: 428.854 | N61: 325.779 | O61: 336.7 | P61: 1983.12 | Q61: 1651.578 | R61: 1531 | S61: 1827 | T61: 3071 | U61: 4351 | V61: 6748 | W61: =V61+W18+W80+'Assumptions (Annual)'!C41+'Assumptions (Annual)'!C42-W19+'Assumptions (Annual)'!C43 -> 8214.4783 | X61: =W61+X18+X80+'Assumptions (Annual)'!D41+'Assumptions (Annual)'!D42-X19+'Assumptions (Annual)'!D43 -> 10379.782 | Y61: =X61+Y18+Y80+'Assumptions (Annual)'!E41+'Assumptions (Annual)'!E42-Y19+'Assumptions (Annual)'!E43 -> 13388.887 | Z61: =Y61+Z18+Z80+'Assumptions (Annual)'!F41+'Assumptions (Annual)'!F42-Z19+'Assumptions (Annual)'!F43 -> 17507.485 | AA61: =Z61+AA18+AA80+'Assumptions (Annual)'!G41+'Assumptions (Annual)'!G42-AA19+'Assumptions (Annual)'!G43 -> 22817.205
A62: Total Liabilities & Equity | B62: =B59+B61 -> -19.161894 | C62: =C59+C61 -> -10.263973 | D62: =D59+D61 -> 134.4928 | E62: =E59+E61 -> 156.73875 | F62: =F59+F61 -> 182.61465 | G62: =G59+G61 -> 269.68302 | H62: =H59+H61 -> 351.93144 | I62: =I59+I61 -> 474.66928 | ... AA62: =AA59+AA61 -> 119766.25
A63: Balance Check (Assets less L&E) | B63: =B49-B62 -> 63.581667 | C63: =C49-C62 -> 64.076545 | D63: =D49-D62 -> 0 | E63: =E49-E62 -> 0 | F63: =F49-F62 -> 0 | G63: =G49-G62 -> 0 | H63: =H49-H62 -> 4 | I63: =I49-I62 -> 4 | ... AA63: =AA49-AA62 -> 0
A65: Memo:
A66: Total Debt | B66: =B53+B56 -> 12.131085 | C66: =C53+C56 -> 9.097527 | D66: =D53+D56 -> 9.713227 | E66: =E53+E56 -> 18.013482 | F66: =F53+F56 -> 3.213992 | G66: =G53+G56 -> 0.288877 | H66: =H53+H56 -> 0.282421 | I66: =I53+I56 -> 0.144063 | ... AA66: =AA53+AA56 -> 22845.066
A67: Net Cash / (Debt) | B67: =B39-B66 -> 0.260019 | C67: =C39-C66 -> 4.366156 | D67: =D39-D66 -> 58.264187 | E67: =E39-E66 -> 31.10003 | F67: =F39-F66 -> 61.169595 | G67: =G39-G66 -> 61.884355 | H67: =H39-H66 -> 142.02788 | I67: =I39-I66 -> 195.03974 | ... AA67: =AA39-AA66 -> 41101.183
A68: Working Capital | B68: =B43-B55 -> 9.200183 | C68: =C43-C55 -> 9.458959 | D68: =D43-D55 -> 63.222664 | E68: =E43-E55 -> 3.991339 | F68: =F43-F55 -> 21.642124 | G68: =G43-G55 -> 13.240741 | H68: =H43-H55 -> 81.94203 | I68: =I43-I55 -> 105.8299 | ... AA68: =AA43-AA55 -> 13829.687
A70: NOWC | B70: =B43-B39-B55-B53 -> -3.322006 | C70: =C43-C39-C55-C53 -> -4.102251 | D70: =D43-D39-D55-D53 -> -14.467977 | E70: =E43-E39-E55-E53 -> -60.085594 | F70: =F43-F39-F55-F53 -> -45.955455 | G70: =G43-G39-G55-G53 -> -49.032522 | H70: =H43-H39-H55-H53 -> -60.514461 | I70: =I43-I39-I55-I53 -> -89.438474 | ... V70: =V43-V39-V55-V53 -> -25134 | W70: =(W40+W41+W42)-(W51+W54) -> -18840.464 | X70: =(X40+X41+X42)-(X51+X54) -> -23413.692 | Y70: =(Y40+Y41+Y42)-(Y51+Y54) -> -28329.83 | Z70: =(Z40+Z41+Z42)-(Z51+Z54) -> -32613.902 | AA70: =(AA40+AA41+AA42)-(AA51+AA54) -> -36837.815
A71: Change in NOWC | C71: =C70-B70 -> -0.780245 | D71: =D70-C70 -> -10.365726 | E71: =E70-D70 -> -45.617617 | F71: =F70-E70 -> 14.130139 | G71: =G70-F70 -> -3.077067 | H71: =H70-G70 -> -11.481939 | I71: =I70-H70 -> -28.924013 | J71: =J70-I70 -> -38.812041 | ... AA71: =AA70-Z70 -> -4223.9127
A73: Operating Capital | B73: =B68+B44 -> 11.543806 | C73: =C68+C44 -> 12.390429 | D73: =D68+D44 -> 67.365868 | E73: =E68+E44 -> 9.931499 | F73: =F68+F44 -> 27.5904 | G73: =G68+G44 -> 34.058453 | H73: =H68+H44 -> 112.81975 | I73: =I68+I44 -> 143.55613 | ... V73: =V68+V44 -> 9444 | W73: =W70+W44+W46+W47 -> -9829.5102 | X73: =X70+X44+X46+X47 -> -12067.84 | Y73: =Y70+Y44+Y46+Y47 -> -14606.547 | Z73: =Z70+Z44+Z46+Z47 -> -16566.147 | AA73: =AA70+AA44+AA46+AA47 -> -18527.908
A74: Operating Asset Turnover | B74: =B6/B73 -> 2.4471718 | C74: =C6/C73 -> 4.2015406 | D74: =D6/D73 -> 1.263642 | E74: =E6/E73 -> 13.796771 | F74: =F6/F73 -> 6.264629 | G74: =G6/G73 -> 6.3630522 | H74: =H6/H73 -> 2.6496392 | I74: =I6/I73 -> 2.6024769 | ... AA74: =AA6/AA73 -> -4.6237997
A75: ROOA | B75: =B28/B73 -> 0.18562128 | C75: =C28/C73 -> 0.436105 | D75: =D28/D73 -> 0.28742999 | E75: =E28/E73 -> 3.7508925 | F75: =F28/F73 -> 2.1705835 | G75: =G28/G73 -> 1.948403 | H75: =H28/H73 -> 0.6360684 | I75: =I28/I73 -> 0.64034099 | ... AA75: =AA28/AA73 -> -0.73671
A77: CASH FLOW STATEMENT
A78: Net Income | B78: =B18 -> 2.354136 | C78: =C18 -> 1.072083 | D78: =D18 -> 9.69294 | E78: =E18 -> 18.811661 | F78: =F18 -> 33.208793 | G78: =G18 -> 56.025019 | H78: =H18 -> 76.780053 | I78: =I18 -> 101.2473 | ... AA78: =AA18 -> 5888.696
A79: Depreciation & Amortization | B79: 1.572497 | C79: 2.016939 | D79: 2.307649 | E79: 3.335673 | F79: 3.893752 | G79: 4.92165 | H79: 7.268075 | I79: 8.959293 | J79: 11.879 | K79: 16.947 | L79: 23.209 | M79: 29.022 | N79: 40.921 | O79: 45.792 | P79: 73.32 | Q79: 105 | R79: 204 | S79: 403 | T79: 524 | U79: 617 | V79: 818 | W79: =W6*'Assumptions (Annual)'!C37 -> 1197.4871 | X79: =X6*'Assumptions (Annual)'!D37 -> 1595.2186 | Y79: =Y6*'Assumptions (Annual)'!E37 -> 1960.3231 | Z79: =Z6*'Assumptions (Annual)'!F37 -> 2238.9406 | AA79: =AA6*'Assumptions (Annual)'!G37 -> 2570.0801
A80: Share-Based Compensation | B80: 0 | C80: 0.033223 | D80: 0.031443 | E80: 0.949582 | F80: 2.000283 | G80: 3.517006 | H80: 4.079265 | I80: 4.442822 | J80: 11.645 | K80: 11.852 | L80: 10.213 | M80: 22.983 | N80: 35.719 | O80: 27.525 | P80: 52.057 | Q80: 131 | R80: 89 | S80: 84 | T80: 167 | U80: 261 | V80: 303 | W80: =W6*'Assumptions (Annual)'!C38 -> 439.0786 | X80: =X6*'Assumptions (Annual)'!D38 -> 566.0453 | Y80: =Y6*'Assumptions (Annual)'!E38 -> 632.36229 | Z80: =Z6*'Assumptions (Annual)'!F38 -> 746.31355 | AA80: =AA6*'Assumptions (Annual)'!G38 -> 771.02403
A81: Other Operating Activities | B81: -0.488029 | C81: 3.036109 | D81: -4.424051 | E81: 32.682261 | F81: 10.598158 | G81: 3.432778 | H81: 1.298238 | I81: 25.241976 | J81: 1.482 | K81: 95.413 | L81: 82.159 | M81: 1.888 | N81: 178.59 | O81: 194.175 | P81: 497.713 | Q81: 947 | R81: 589 | S81: 1971 | T81: 3462 | U81: 5129 | V81: 8998 | W81: =-(W40-V40)-(W41-V41)-(W42-V42)+(W51-V51)+(W54-V54)+(W57-V57)-(W47-V47) -> 3388.8143 | X81: =-(X40-W40)-(X41-W41)-(X42-W42)+(X51-W51)+(X54-W54)+(X57-W57)-(X47-W47) -> 4111.531 | Y81: =-(Y40-X40)-(Y41-X41)-(Y42-X42)+(Y51-X51)+(Y54-X54)+(Y57-X57)-(Y47-X47) -> 4445.0359 | Z81: =-(Z40-Y40)-(Z41-Y41)-(Z42-Y42)+(Z51-Y51)+(Z54-Y54)+(Z57-Y57)-(Z47-Y47) -> 3828.2666 | AA81: =-(AA40-Z40)-(AA41-Z41)-(AA42-Z42)+(AA51-Z51)+(AA54-Z54)+(AA57-Z57)-(AA47-Z47) -> 3782.3935
A82: Operating Cash Flow | B82: =B78+B79+B80+B81 -> 3.438604 | C82: =C78+C79+C80+C81 -> 6.158354 | D82: =D78+D79+D80+D81 -> 7.607981 | E82: =E78+E79+E80+E81 -> 55.779177 | F82: =F78+F79+F80+F81 -> 49.700986 | G82: =G78+G79+G80+G81 -> 67.896453 | H82: =H78+H79+H80+H81 -> 89.425631 | I82: =I78+I79+I80+I81 -> 139.89139 | ... AA82: =AA78+AA79+AA80+AA81 -> 13012.194
A84: Capital Expenditures | B84: -1.455717 | C84: -2.097555 | D84: -3.058813 | E84: -4.904991 | F84: -3.79817 | G84: -13.214043 | H84: -18.924161 | I84: -16.747746 | J84: -113.756 | K84: -34.426 | L84: -62.53 | M84: -76.939 | N84: -74.851 | O84: -97.562 | P84: -136.798 | Q84: -247 | R84: -573 | S84: -455 | T84: -509 | U84: -860 | V84: -1343 | W84: =-W6*'Assumptions (Annual)'!C39 -> -2594.5554 | X84: =-X6*'Assumptions (Annual)'!D39 -> -3087.5198 | Y84: =-Y6*'Assumptions (Annual)'!E39 -> -3477.9926 | Z84: =-Z6*'Assumptions (Annual)'!F39 -> -3731.5677 | AA84: =-AA6*'Assumptions (Annual)'!G39 -> -4026.4588
A85: Acquisitions | B85: -12.141243 | C85: 0 | D85: 0 | E85: -39.181473 | F85: 0 | G85: 0 | H85: -5.46818 | I85: 0 | J85: -3.423 | K85: -40.814 | L85: -45.009 | M85: -7.284 | N85: -35.798 | O85: -4.195 | P85: 0 | Q85: -7 | R85: -56 | S85: 0 | T85: 0 | U85: -6 | V85: 0 | W85: ='Assumptions (Annual)'!C40 -> 0 | X85: ='Assumptions (Annual)'!D40 -> 0 | Y85: ='Assumptions (Annual)'!E40 -> 0 | Z85: ='Assumptions (Annual)'!F40 -> 0 | AA85: ='Assumptions (Annual)'!G40 -> 0
A86: Change in Investments | B86: 1.106712 | C86: -2.760134 | D86: -46.346688 | E86: 5.286163 | F86: 1.667576 | G86: -45.203528 | H86: -42.209369 | I86: -66.483782 | J86: 38.849 | K86: -246.294 | L86: -74.253 | M86: 0.411 | N86: 88.041 | O86: -570.51 | P86: -1310.92 | Q86: 2 | R86: -932 | S86: -3416 | T86: -2941 | U86: -7421 | V86: -4911 | W86: =-((W38-V38)+(W45-V45)) -> -2269.4405 | X86: =-((X38-W38)+(X45-W45)) -> -3581.7528 | Y86: =-((Y38-X38)+(Y45-X45)) -> -3411.9043 | Z86: =-((Z38-Y38)+(Z45-Y45)) -> -3039.4021 | AA86: =-((AA38-Z38)+(AA45-Z45)) -> -2711.32
A87: Other Investing Activities | B87: -0.548886 | C87: -0.346365 | D87: -0.028748 | E87: -0.058238 | F87: -0.955679 | G87: -0.41645 | H87: -0.280706 | I87: -1.390654 | J87: -0.459 | K87: -0.857 | L87: -1.746 | M87: -0.431 | N87: -0.033 | O87: -0.192 | P87: -0.072 | Q87: 0 | R87: -36 | S87: 0 | T87: 0 | U87: 0 | V87: 75 | W87: 0 | X87: 0 | Y87: 0 | Z87: 0 | AA87: 0
A88: Investing Cash Flow | B88: =B84+B85+B86+B87 -> -13.039134 | C88: =C84+C85+C86+C87 -> -5.204054 | D88: =D84+D85+D86+D87 -> -49.434249 | E88: =E84+E85+E86+E87 -> -38.858539 | F88: =F84+F85+F86+F87 -> -3.086273 | G88: =G84+G85+G86+G87 -> -58.834021 | H88: =H84+H85+H86+H87 -> -66.882416 | I88: =I84+I85+I86+I87 -> -84.622182 | ... AA88: =AA84+AA85+AA86+AA87 -> -6737.7788
A90: Dividends Paid | B90: 0 | C90: 0 | D90: 0 | E90: 0 | F90: 0 | G90: 0 | H90: -10.593206 | I90: -17.968004 | J90: -23.754 | K90: -28.303 | L90: -20.974 | M90: -24.419 | N90: -26.496 | O90: -6.624 | P90: 0 | Q90: 0 | R90: 0 | S90: 0 | T90: 0 | U90: 0 | V90: 0 | W90: ='Assumptions (Annual)'!C42 -> 0 | X90: ='Assumptions (Annual)'!D42 -> 0 | Y90: ='Assumptions (Annual)'!E42 -> 0 | Z90: ='Assumptions (Annual)'!F42 -> 0 | AA90: ='Assumptions (Annual)'!G42 -> 0
A91: Share Issuance / (Repurchase) | B91: 0.009003 | C91: 0.007107 | D91: 49.611815 | E91: -2.515134 | F91: 0.028354 | G91: 0.018199 | H91: 0.011175 | I91: 0.0057 | J91: -1.009 | K91: -1.944 | L91: -2.714 | M91: 0 | N91: 0 | O91: 0 | P91: 1866.495 | Q91: -54 | R91: 1034 | S91: -148 | T91: -356 | U91: -1 | V91: -1 | W91: ='Assumptions (Annual)'!C41 -> -250 | X91: ='Assumptions (Annual)'!D41 -> -500 | Y91: ='Assumptions (Annual)'!E41 -> -750 | Z91: ='Assumptions (Annual)'!F41 -> -1000 | AA91: ='Assumptions (Annual)'!G41 -> -1250
A92: Debt Issued / (Repaid) | B92: 12.002335 | C92: -3.002058 | D92: -0.116896 | E92: -9.137223 | F92: -15.310634 | G92: -3 | H92: 0 | I92: 0 | J92: 15.517 | K92: 322.296 | L92: -4.026 | M92: 4.751 | N92: -24.407 | O92: 631.77 | P92: 58.673 | Q92: 299 | R92: 891 | S92: 1064 | T92: 89 | U92: 1960 | V92: 2905 | W92: =(W112+W56)-(V53+V56) -> 2693.0214 | X92: =(X112+X56)-(W112+W56) -> 2472.5993 | Y92: =(Y112+Y56)-(X112+X56) -> 2310.7768 | Z92: =(Z112+Z56)-(Y112+Y56) -> 2097.4484 | AA92: =(AA112+AA56)-(Z112+Z56) -> 1879.2202
A93: Other Financing Activities | B93: 0 | C93: 0 | D93: 0.749991 | E93: 0 | F93: 0 | G93: 0 | H93: 0 | I93: 0 | J93: 0 | K93: -27.752 | L93: 0 | M93: 0 | N93: 0 | O93: -16.264 | P93: 95.844 | Q93: -3 | R93: 0 | S93: 0 | T93: 0 | U93: 0 | V93: 0 | W93: =W108 -> 0 | X93: =X108 -> 0 | Y93: =Y108 -> 0 | Z93: =Z108 -> 0 | AA93: =AA108 -> 0
A94: Financing Cash Flow | B94: =B90+B91+B92+B93 -> 12.011338 | C94: =C90+C91+C92+C93 -> -2.994951 | D94: =D90+D91+D92+D93 -> 50.24491 | E94: =E90+E91+E92+E93 -> -11.652357 | F94: =F90+F91+F92+F93 -> -15.28228 | G94: =G90+G91+G92+G93 -> -2.981801 | H94: =H90+H91+H92+H93 -> -10.582031 | I94: =I90+I91+I92+I93 -> -17.962304 | ... AA94: =AA90+AA91+AA92+AA93 -> 629.22017
A96: Effect of FX on Cash & Other | B96: -0.455328 | C96: 0.20384 | D96: 0.115738 | E96: -3.471576 | F96: 0.996857 | G96: 0.946433 | H96: -1.409973 | I96: -3.199578 | J96: -15.682 | K96: -55.84 | L96: -66.381 | M96: -19.089 | N96: -41.346 | O96: -90.895 | P96: -37.584 | Q96: -115 | R96: -153 | S96: -270 | T96: -938 | U96: -739 | V96: -3 | W96: ='Assumptions (Annual)'!C43 -> -200 | X96: ='Assumptions (Annual)'!D43 -> -150 | Y96: ='Assumptions (Annual)'!E43 -> -150 | Z96: ='Assumptions (Annual)'!F43 -> -100 | AA96: ='Assumptions (Annual)'!G43 -> -100
A97: Net Change in Cash | B97: =B82+B88+B94+B96 -> 1.95548 | C97: =C82+C88+C94+C96 -> -1.836811 | D97: =D82+D88+D94+D96 -> 8.53438 | E97: =E82+E88+E94+E96 -> 1.796705 | F97: =F82+F88+F94+F96 -> 32.32929 | G97: =G82+G88+G94+G96 -> 7.027064 | H97: =H82+H88+H94+H96 -> 10.551211 | I97: =I82+I88+I94+I96 -> 34.107325 | ... AA97: =AA82+AA88+AA94+AA96 -> 6803.635
A99: Memo:
A100: Free Cash Flow | B100: =B82+B84 -> 1.982887 | C100: =C82+C84 -> 4.060799 | D100: =D82+D84 -> 4.549168 | E100: =E82+E84 -> 50.874186 | F100: =F82+F84 -> 45.902816 | G100: =G82+G84 -> 54.68241 | H100: =H82+H84 -> 70.50147 | I100: =I82+I84 -> 123.14364 | ... AA100: =AA82+AA84 -> 8985.7348
A101: YoY Growth % | C101: =C100/B100-1 -> 1.0479225 | D101: =D100/C100-1 -> 0.12026426 | E101: =E100/D100-1 -> 10.183185 | F101: =F100/E100-1 -> -0.09771891 | G101: =G100/F100-1 -> 0.19126482 | H101: =H100/G100-1 -> 0.28928974 | I101: =I100/H100-1 -> 0.74668192 | J101: =J100/I100-1 -> -0.76647597 | ... AA101: =AA100/Z100-1 -> 0.18949602
A102: CAGR | V102: =(V100/B100)^(1/(V4-B4))-1 -> 0.53727631 | W102: =(W100/$V$100)^(1/5)-1 -> -0.18355193 | X102: =(X100/$V$100)^(1/5)-1 -> -0.12790235 | Y102: =(Y100/$V$100)^(1/5)-1 -> -0.086940507 | Z102: =(Z100/$V$100)^(1/5)-1 -> -0.068525888 | AA102: =(AA100/$V$100)^(1/5)-1 -> -0.035630676
A104: LIQUIDITY & REVOLVER
A105: Beginning cash | W105: =V37 -> 13537 | X105: =W37 -> 17418.805 | Y105: =X37 -> 21094.185 | Z105: =Y37 -> 25929.53 | AA105: =Z37 -> 31441.813
A106: Cash flow before revolver | W106: =W105+W82+W88+W90+W91+W92+W96 -> 17418.805 | X106: =X105+X82+X88+X90+X91+X92+X96 -> 21094.185 | Y106: =Y105+Y82+Y88+Y90+Y91+Y92+Y96 -> 25929.53 | Z106: =Z105+Z82+Z88+Z90+Z91+Z92+Z96 -> 31441.813 | AA106: =AA105+AA82+AA88+AA90+AA91+AA92+AA96 -> 38245.448
A107: Minimum cash balance | W107: ='Assumptions (Annual)'!C35 -> 2500 | X107: ='Assumptions (Annual)'!D35 -> 2750 | Y107: ='Assumptions (Annual)'!E35 -> 3000 | Z107: ='Assumptions (Annual)'!F35 -> 3250 | AA107: ='Assumptions (Annual)'!G35 -> 3500
A108: Revolver draw / (paydown) | W108: =IF(W106<W107,W107-W106,-MIN(W109,W106-W107)) -> 0 | X108: =IF(X106<X107,X107-X106,-MIN(X109,X106-X107)) -> 0 | Y108: =IF(Y106<Y107,Y107-Y106,-MIN(Y109,Y106-Y107)) -> 0 | Z108: =IF(Z106<Z107,Z107-Z106,-MIN(Z109,Z106-Z107)) -> 0 | AA108: =IF(AA106<AA107,AA107-AA106,-MIN(AA109,AA106-AA107)) -> 0
A109: Revolver balance, beginning | W109: =0 -> 0 | X109: =W110 -> 0 | Y109: =X110 -> 0 | Z109: =Y110 -> 0 | AA109: =Z110 -> 0
A110: Revolver balance, ending | W110: =W109+W108 -> 0 | X110: =X109+X108 -> 0 | Y110: =Y109+Y108 -> 0 | Z110: =Z109+Z108 -> 0 | AA110: =AA109+AA108 -> 0
A111: Revolver interest (memo) | W111: ='Assumptions (Annual)'!C34*W109 -> 0 | X111: ='Assumptions (Annual)'!D34*X109 -> 0 | Y111: ='Assumptions (Annual)'!E34*Y109 -> 0 | Z111: ='Assumptions (Annual)'!F34*Z109 -> 0 | AA111: ='Assumptions (Annual)'!G34*AA109 -> 0
A112: Current debt - term (ex-revolver) | W112: =W6*'Assumptions (Annual)'!C52 -> 6985.3414 | X112: =X6*'Assumptions (Annual)'!D52 -> 8747.9728 | Y112: =Y6*'Assumptions (Annual)'!E52 -> 10433.978 | Z112: =Z6*'Assumptions (Annual)'!F52 -> 11941.017 | AA112: =AA6*'Assumptions (Annual)'!G52 -> 13278.747

Sheet Quarterly
A1: MercadoLibre, Inc. (NASDAQ: MELI) | Integrated Operating Model - Quarterly
A2: $ in millions, except per share data. Shares in millions. Actuals through Q1 2026 | Estimates Q2 2026E-Q4 2027E
A4: ($ in millions) | B4: Q4'06 | C4: Q1'07 | D4: Q2'07 | E4: Q3'07 | F4: Q4'07 | G4: Q1'08 | H4: Q2'08 | I4: Q3'08 | J4: Q4'08 | K4: Q1'09 | L4: Q2'09 | M4: Q3'09 | N4: Q4'09 | O4: Q1'10 | P4: Q2'10 | Q4: Q3'10 | R4: Q4'10 | S4: Q1'11 | T4: Q2'11 | U4: Q3'11 | V4: Q4'11 | W4: Q1'12 | X4: Q2'12 | Y4: Q3'12 | Z4: Q4'12 | AA4: Q1'13 | AB4: Q2'13 | AC4: Q3'13 | AD4: Q4'13 | AE4: Q1'14 | AF4: Q2'14 | AG4: Q3'14 | AH4: Q4'14 | AI4: Q1'15 | AJ4: Q2'15 | AK4: Q3'15 | AL4: Q4'15 | AM4: Q1'16 | AN4: Q2'16 | AO4: Q3'16 | AP4: Q4'16 | AQ4: Q1'17 | AR4: Q2'17 | AS4: Q3'17 | AT4: Q4'17 | AU4: Q1'18 | AV4: Q2'18 | AW4: Q3'18 | AX4: Q4'18 | AY4: Q1'19 | AZ4: Q2'19 | BA4: Q3'19 | BB4: Q4'19 | BC4: Q1'20 | BD4: Q2'20 | BE4: Q3'20 | BF4: Q4'20 | BG4: Q1'21 | BH4: Q2'21 | BI4: Q3'21 | BJ4: Q4'21 | BK4: Q1'22 | BL4: Q2'22 | BM4: Q3'22 | BN4: Q4'22 | BO4: Q1'23 | BP4: Q2'23 | BQ4: Q3'23 | BR4: Q4'23 | BS4: Q1'24 | BT4: Q2'24 | BU4: Q3'24 | BV4: Q4'24 | BW4: Q1'25 | BX4: Q2'25 | BY4: Q3'25 | BZ4: Q4'25 | CA4: Q1'26 | CB4: Q2'26E | CC4: Q3'26E | CD4: Q4'26E | CE4: Q1'27E | CF4: Q2'27E | CG4: Q3'27E | CH4: Q4'27E
A5: INCOME STATEMENT
A6: Revenue | B6: 15.462397 | C6: 16.459337 | D6: 18.973288 | E6: 22.80013 | F6: 26.893586 | G6: 28.84073 | H6: 34.471508 | I6: 40.260643 | J6: 33.449739 | K6: 32.322501 | L6: 40.901799 | M6: 50.599276 | N6: 49.020045 | O6: 45.937774 | P6: 52.510331 | Q6: 55.951378 | R6: 62.31623 | S6: 61.459668 | T6: 69.37816 | U6: 81.628144 | V6: 86.465653 | W6: 83.736006 | X6: 88.844059 | Y6: 97.266784 | Z6: 103.75465 | AA6: 102.72575 | AB6: 112.18336 | AC6: 123.05543 | AD6: 134.63046 | AE6: 115.382 | AF6: 131.849 | AG6: 147.935 | AH6: 161.37 | AI6: 148.103 | AJ6: 154.314 | AK6: 168.641 | AL6: 180.732 | AM6: 157.63 | AN6: 199.644 | AO6: 230.847 | AP6: 256.275 | AQ6: 269.675 | AR6: 283.882 | AS6: 304.921 | AT6: 358.063 | AU6: 320.976 | AV6: 335.377 | AW6: 355.281 | AX6: 428.019 | AY6: 473.77 | AZ6: 545.242 | BA6: 603.031 | BB6: 674.271 | BC6: 652.091 | BD6: 878.369 | BE6: 1115.701 | BF6: 1327.839 | BG6: 1378 | BH6: 1703 | BI6: 1858 | BJ6: 2130 | BK6: 2248 | BL6: 2597 | BM6: 2690 | BN6: 3245 | BO6: 3186 | BP6: 3585 | BQ6: 3927 | BR6: 4409 | BS6: 4333 | BT6: 5073 | BU6: 5312 | BV6: 6059 | BW6: 5935 | BX6: 6790 | BY6: 7409 | BZ6: 8759 | CA6: 8845 | CB6: ='Assumptions (Quarterly)'!F13 -> 9130.66 | CC6: ='Assumptions (Quarterly)'!G13 -> 10109.82 | CD6: ='Assumptions (Quarterly)'!H13 -> 11654.815 | CE6: ='Assumptions (Quarterly)'!I13 -> 11500.64 | CF6: ='Assumptions (Quarterly)'!J13 -> 11593.531 | CG6: ='Assumptions (Quarterly)'!K13 -> 12625.39 | CH6: ='Assumptions (Quarterly)'!L13 -> 14281.798
A7: Cost of Revenue | B7: 3.653165 | C7: 3.487339 | D7: 3.999922 | E7: 4.882048 | F7: 5.90363 | G7: 6.018281 | H7: 6.901503 | I7: 8.153862 | J7: 6.461529 | K7: 6.633986 | L7: 8.595477 | M7: 10.390671 | N7: 10.337916 | O7: 9.893051 | P7: 11.411561 | Q7: 11.450919 | R7: 13.794314 | S7: 14.331703 | T7: 16.939118 | U7: 20.060474 | V7: 20.72454 | W7: 21.096297 | X7: 23.892881 | Y7: 25.693605 | Z7: 27.402862 | AA7: 28.649167 | AB7: 31.077211 | AC7: 34.144989 | AD7: 36.205632 | AE7: 31.54 | AF7: 36.372 | AG7: 43.402 | AH7: 47.665 | AI7: 44.708 | AJ7: 50.311 | AK7: 56.813 | AL7: 63.162 | AM7: 55.448 | AN7: 73.346 | AO7: 85.199 | AP7: 93.545 | AQ7: 100.819 | AR7: 112.328 | AS7: 129.094 | AT7: 154.701 | AU7: 158.218 | AV7: 175.629 | AW7: 185.563 | AX7: 223.235 | AY7: 236.766 | AZ7: 272.812 | BA7: 318.689 | BB7: 365.924 | BC7: 339.277 | BD7: 451.197 | BE7: 635.511 | BF7: 839.015 | BG7: 787 | BH7: 949 | BI7: 1051 | BJ7: 1277 | BK7: 1175 | BL7: 1313 | BM7: 1342 | BN7: 1752 | BO7: 1572 | BP7: 1754 | BQ7: 1832 | BR7: 2359 | BS7: 2309 | BT7: 2708 | BU7: 2873 | BV7: 3310 | BW7: 3164 | BX7: 3696 | BY7: 4200 | BZ7: 4975 | CA7: 4983 | CB7: =CB6*(1-'Assumptions (Quarterly)'!F15) -> 5113.1696 | CC7: =CC6*(1-'Assumptions (Quarterly)'!G15) -> 5641.2795 | CD7: =CD6*(1-'Assumptions (Quarterly)'!H15) -> 6468.4223 | CE7: =CE6*(1-'Assumptions (Quarterly)'!I15) -> 6440.3584 | CF7: =CF6*(1-'Assumptions (Quarterly)'!J15) -> 6457.5969 | CG7: =CG6*(1-'Assumptions (Quarterly)'!K15) -> 7007.0917 | CH7: =CH6*(1-'Assumptions (Quarterly)'!L15) -> 7883.5525
A8: Gross Profit | B8: =B6-B7 -> 11.809232 | C8: =C6-C7 -> 12.971998 | D8: =D6-D7 -> 14.973366 | E8: =E6-E7 -> 17.918082 | F8: =F6-F7 -> 20.989956 | G8: =G6-G7 -> 22.822449 | H8: =H6-H7 -> 27.570005 | I8: =I6-I7 -> 32.106781 | ... CH8: =CH6-CH7 -> 6398.2455
A9: Selling, General & Administrative | B9: 8.967412 | C9: 8.991513 | D9: 9.141326 | E9: 10.466394 | F9: 12.222972 | G9: 14.162263 | H9: 16.144958 | I9: 18.686236 | J9: 13.741782 | K9: 16.287552 | L9: 16.806893 | M9: 17.930819 | N9: 17.686067 | O9: 17.315682 | P9: 18.307737 | Q9: 20.965277 | R9: 23.122616 | S9: 22.679919 | T9: 25.368753 | U9: 25.678928 | V9: 30.026238 | W9: 30.122891 | X9: 26.932439 | Y9: 29.876191 | Z9: 30.299578 | AA9: 36.123007 | AB9: 35.896634 | AC9: 39.436793 | AD9: 36.635004 | AE9: 37.584 | AF9: 40.153 | AG9: 43.812 | AH9: 52.44 | AI9: 44.336 | AJ9: 49.727 | AK9: 49.506 | AL9: 61.382 | AM9: 49.752 | AN9: 56.178 | AO9: 65.873 | AP9: 71.802 | AQ9: 75.24 | AR9: 108.354 | AS9: 115.905 | AT9: 148.069 | AU9: 153.781 | AV9: 154.553 | AW9: 145.243 | AX9: 166.64 | AY9: 174.496 | AZ9: 230.995 | BA9: 306.772 | BB9: 319.214 | BC9: 269.073 | BD9: 254.48 | BE9: 308.32 | BF9: 263.127 | BG9: 374 | BH9: 359 | BI9: 404 | BJ9: 486 | BK9: 445 | BL9: 469 | BM9: 486 | BN9: 556 | BO9: 563 | BP9: 572 | BQ9: 637 | BR9: 730 | BS9: 664 | BT9: 729 | BU9: 871 | BV9: 890 | BW9: 854 | BX9: 1012 | BY9: 1103 | BZ9: 1328 | CA9: 1308 | CB9: =CB6*'Assumptions (Quarterly)'!F16 -> 1333.0764 | CC9: =CC6*'Assumptions (Quarterly)'!G16 -> 1465.9239 | CD9: =CD6*'Assumptions (Quarterly)'!H16 -> 1654.9837 | CE9: =CE6*'Assumptions (Quarterly)'!I16 -> 1656.0922 | CF9: =CF6*'Assumptions (Quarterly)'!J16 -> 1646.2814 | CG9: =CG6*'Assumptions (Quarterly)'!K16 -> 1780.18 | CH9: =CH6*'Assumptions (Quarterly)'!L16 -> 1970.8881
A10: Research & Development | B10: 0.814537 | C10: 0.97362 | D10: 1.029096 | E10: 1.154317 | F10: 1.212343 | G10: 1.744511 | H10: 1.73078 | I10: 1.744608 | J10: 2.088506 | K10: 2.633419 | L10: 3.087206 | M10: 3.295436 | N10: 3.12446 | O10: 3.224775 | P10: 3.976466 | Q10: 4.224476 | R10: 4.430276 | S10: 5.15689 | T10: 5.518892 | U10: 5.925019 | V10: 6.748985 | W10: 7.586074 | X10: 6.133819 | Y10: 7.983301 | Z10: 6.923686 | AA10: 9.382389 | AB10: 9.76022 | AC10: 12.074586 | AD10: 9.670805 | AE10: 12.257 | AF10: 11.741 | AG10: 13.574 | AH10: 16.028 | AI10: 17.245 | AJ10: 19.639 | AK10: 17.042 | AL10: 22.496 | AM10: 21.941 | AN10: 24.216 | AO10: 26.066 | AP10: 26.256 | AQ10: 30.302 | AR10: 30.338 | AS10: 32.38 | AT10: 34.141 | AU10: 38.396 | AV10: 33.437 | AW10: 35.478 | AX10: 38.962 | AY10: 52.369 | AZ10: 53.923 | BA10: 59.495 | BB10: 58.02 | BC10: 73.435 | BD10: 73.254 | BE10: 88.796 | BF10: 117.515 | BG10: 126 | BH10: 147 | BI10: 138 | BJ10: 179 | BK10: 234 | BL10: 262 | BM10: 278 | BN10: 325 | BO10: 381 | BP10: 368 | BQ10: 396 | BR10: 686 | BS10: 458 | BT10: 460 | BU10: 504 | BV10: 512 | BW10: 551 | BX10: 567 | BY10: 567 | BZ10: 584 | CA10: 699 | CB10: =CB6*'Assumptions (Quarterly)'!F17 -> 721.32214 | CC10: =CC6*'Assumptions (Quarterly)'!G17 -> 788.56595 | CD10: =CD6*'Assumptions (Quarterly)'!H17 -> 897.42075 | CE10: =CE6*'Assumptions (Quarterly)'!I17 -> 897.04992 | CF10: =CF6*'Assumptions (Quarterly)'!J17 -> 892.7019 | CG10: =CG6*'Assumptions (Quarterly)'!K17 -> 959.52967 | CH10: =CH6*'Assumptions (Quarterly)'!L17 -> 1071.1349
A11: Other Operating Expenses | B11: 0 | C11: 0 | D11: 0 | E11: 0 | F11: 0 | G11: 0.373473 | H11: 1.546397 | I11: 0 | J11: 0 | K11: 0 | L11: 0 | M11: 0 | N11: 0 | O11: 0 | P11: 0 | Q11: 0 | R11: 0 | S11: 0 | T11: 0 | U11: 0 | V11: 0 | W11: 0 | X11: 0 | Y11: 0 | Z11: 0 | AA11: 0 | AB11: 0 | AC11: 0 | AD11: 0 | AE11: 0 | AF11: 49.496 | AG11: 0 | AH11: 0 | AI11: 16.226 | AJ11: 0 | AK11: 0 | AL11: 0 | AM11: 0 | AN11: 13.717 | AO11: 0 | AP11: 0 | AQ11: 0 | AR11: 2.837 | AS11: 0 | AT11: 85.761 | AU11: 0 | AV11: 0 | AW11: 0 | AX11: 0 | AY11: 0 | AZ11: 0 | BA11: 0 | BB11: 0 | BC11: 0 | BD11: 0 | BE11: 0 | BF11: 133 | BG11: 0 | BH11: 82 | BI11: 105 | BJ11: 164 | BK11: 255 | BL11: 303 | BM11: 288 | BN11: 228 | BO11: 252 | BP11: 222 | BQ11: 277 | BR11: 299 | BS11: 374 | BT11: 450 | BU11: 507 | BV11: 527 | BW11: 603 | BX11: 690 | BY11: 815 | BZ11: 983 | CA11: 1244 | CB11: =CB6*'Assumptions (Quarterly)'!F18 -> 1141.3325 | CC11: =CC6*'Assumptions (Quarterly)'!G18 -> 1213.1784 | CD11: =CD6*'Assumptions (Quarterly)'!H18 -> 1340.3037 | CE11: =CE6*'Assumptions (Quarterly)'!I18 -> 1403.0781 | CF11: =CF6*'Assumptions (Quarterly)'!J18 -> 1368.0367 | CG11: =CG6*'Assumptions (Quarterly)'!K18 -> 1439.2945 | CH11: =CH6*'Assumptions (Quarterly)'!L18 -> 1570.9978
A12: Total Operating Expenses | B12: =B9+B10+B11 -> 9.781949 | C12: =C9+C10+C11 -> 9.965133 | D12: =D9+D10+D11 -> 10.170422 | E12: =E9+E10+E11 -> 11.620711 | F12: =F9+F10+F11 -> 13.435315 | G12: =G9+G10+G11 -> 16.280247 | H12: =H9+H10+H11 -> 19.422135 | I12: =I9+I10+I11 -> 20.430844 | ... CH12: =CH9+CH10+CH11 -> 4613.0208
A13: Operating Income | B13: =B8-B12 -> 2.027283 | C13: =C8-C12 -> 3.006865 | D13: =D8-D12 -> 4.802944 | E13: =E8-E12 -> 6.297371 | F13: =F8-F12 -> 7.554641 | G13: =G8-G12 -> 6.542202 | H13: =H8-H12 -> 8.14787 | I13: =I8-I12 -> 11.675937 | ... CH13: =CH8-CH12 -> 1785.2248
A14: Interest Expense / (Income) | B14: 0.465986 | C14: 0.535861 | D14: 0.451783 | E14: 0.700631 | F14: 1.049626 | G14: 1.3628 | H14: 0.958348 | I14: 1.132524 | J14: 4.988756 | K14: 2.510184 | L14: 3.334589 | M14: 3.87323 | N14: 3.639551 | O14: 2.995418 | P14: 3.355921 | Q14: 0.567969 | R14: 0.682364 | S14: 0.62895 | T14: 0.880819 | U14: 1.052865 | V14: 1.0861 | W14: 0.077317 | X14: 0.4743 | Y14: 0.31286 | Z14: 0.273902 | AA14: 0.360352 | AB14: 0.531668 | AC14: 0.487496 | AD14: 0.976484 | AE14: 1.027 | AF14: 0.778 | AG14: 4.913 | AH14: 4.941 | AI14: 4.95 | AJ14: 5.201 | AK14: 6.011 | AL14: 4.229 | AM14: 5.684 | AN14: 6.631 | AO14: 6.492 | AP14: 6.798 | AQ14: 6.471 | AR14: 6.506 | AS14: 6.709 | AT14: 6.783 | AU14: 10.734 | AV14: 13.202 | AW14: 15.869 | AX14: 16.444 | AY14: 15.559 | AZ14: 14.679 | BA14: 14.451 | BB14: 21.187 | BC14: 23.584 | BD14: 26.977 | BE14: 24.522 | BF14: 31.917 | BG14: 91 | BH14: 40 | BI14: 44 | BJ14: 54 | BK14: 56 | BL14: 73 | BM14: 92 | BN14: -86 | BO14: 34 | BP14: 49 | BQ14: 53 | BR14: 38 | BS14: 38 | BT14: 39 | BU14: 40 | BV14: 48 | BW14: 39 | BX14: 36 | BY14: 35 | BZ14: 50 | CA14: 65 | CB14: =CB6*'Assumptions (Quarterly)'!F19+'Assumptions (Quarterly)'!F23*0 -> 63.91462 | CC14: =CC6*'Assumptions (Quarterly)'!G19+'Assumptions (Quarterly)'!G23*CB93 -> 70.768739 | CD14: =CD6*'Assumptions (Quarterly)'!H19+'Assumptions (Quarterly)'!H23*CC93 -> 81.583705 | CE14: =CE6*'Assumptions (Quarterly)'!I19+'Assumptions (Quarterly)'!I23*CD93 -> 80.50448 | CF14: =CF6*'Assumptions (Quarterly)'!J19+'Assumptions (Quarterly)'!J23*CE93 -> 81.154718 | CG14: =CG6*'Assumptions (Quarterly)'!K19+'Assumptions (Quarterly)'!K23*CF93 -> 75.752342 | CH14: =CH6*'Assumptions (Quarterly)'!L19+'Assumptions (Quarterly)'!L23*CG93 -> 85.690788
A15: Other Expense / (Income) | B15: 0.056983 | C15: 0.591695 | D15: 1.939297 | E15: 1.409738 | F15: 0.562799 | G15: 0.239361 | H15: 1.779777 | I15: 2.278858 | J15: -4.662396 | K15: -2.805149 | L15: 0.744099 | M15: 2.719595 | N15: -0.695178 | O15: -1.191114 | P15: -0.88191 | Q15: -1.00768 | R15: -1.788066 | S15: -1.393457 | T15: -1.787281 | U15: -6.189972 | V15: -2.94573 | W15: -2.048902 | X15: -3.70867 | Y15: -2.527873 | Z15: -3.313741 | AA15: 2.901779 | AB15: -5.762196 | AC15: -4.448093 | AD15: -4.598487 | AE15: -6.065 | AF15: 12.398 | AG15: -9.594 | AH15: -9.65 | AI15: 4.262 | AJ15: -4.035 | AK15: -8.347 | AL15: -23.565 | AM15: -12.398 | AN15: -2.662 | AO15: -5.069 | AP15: -9.747 | AQ15: -12.82 | AR15: 11.097 | AS15: -15.822 | AT15: -6.721 | AU15: -14.796 | AV15: -22.492 | AW15: -12.56 | AX15: -10.431 | AY15: -20.775 | AZ15: -34.467 | BA15: -29.449 | BB15: -27.1 | BC15: -36.598 | BD15: -16.879 | BE15: 5.882 | BF15: -12.405 | BG15: -10 | BH15: -12 | BI15: -10 | BJ15: 12 | BK15: -28 | BL15: 15 | BM15: 6 | BN15: 161 | BO15: 61 | BP15: 148 | BQ15: 201 | BR15: 67 | BS15: 9 | BT15: 19 | BU15: -3 | BV15: 9 | BW15: 18 | BX15: 73 | BY15: 53 | BZ15: 55 | CA15: -33 | CB15: =CB6*'Assumptions (Quarterly)'!F20 -> 45.6533 | CC15: =CC6*'Assumptions (Quarterly)'!G20 -> 50.549099 | CD15: =CD6*'Assumptions (Quarterly)'!H20 -> 58.274075 | CE15: =CE6*'Assumptions (Quarterly)'!I20 -> 57.5032 | CF15: =CF6*'Assumptions (Quarterly)'!J20 -> 57.967656 | CG15: =CG6*'Assumptions (Quarterly)'!K20 -> 63.126952 | CH15: =CH6*'Assumptions (Quarterly)'!L20 -> 71.40899
A16: Pretax Income | B16: =B13-B14-B15 -> 1.504314 | C16: =C13-C14-C15 -> 1.879309 | D16: =D13-D14-D15 -> 2.411864 | E16: =E13-E14-E15 -> 4.187002 | F16: =F13-F14-F15 -> 5.942216 | G16: =G13-G14-G15 -> 4.940041 | H16: =H13-H14-H15 -> 5.409745 | I16: =I13-I14-I15 -> 8.264555 | ... CH16: =CH13-CH14-CH15 -> 1628.125
A17: Income Tax | B17: -0.340772 | C17: 0.885122 | D17: 1.820978 | E17: 1.401528 | F17: 0.619823 | G17: 2.872364 | H17: 2.46265 | I17: 2.388763 | J17: 2.910465 | K17: 1.671333 | L17: 1.653756 | M17: 2.537257 | N17: 3.641659 | O17: 4.079361 | P17: 4.666593 | Q17: 0.959454 | R17: 6.135233 | S17: 5.998029 | T17: 7.637033 | U17: 8.804905 | V17: 9.219854 | W17: 7.267719 | X17: 9.740098 | Y17: 9.885607 | Z17: 11.977954 | AA17: 7.8288 | AB17: 10.701182 | AC17: 12.075486 | AD17: 14.977533 | AE17: 8.775 | AF17: 6.506 | AG17: 18.062 | AH17: 15.8 | AI17: 14.655 | AJ17: 14.008 | AK17: 1.976 | AL17: 14.063 | AM17: 6.956 | AN17: 12.36 | AO17: 13.374 | AP17: 16.272 | AQ17: 21.145 | AR17: 7.106 | AS17: 8.989 | AT17: 3.049 | AU17: -12.438 | AV17: -7.7 | AW17: -4.234 | AX17: -4.495 | AY17: 3.491 | AZ17: -8.917 | BA17: 79.155 | BB17: -8.976 | BC17: 4.429 | BD17: 33.393 | BE17: 37.635 | BF17: 6.543 | BG17: 44 | BH17: 70 | BI17: 31 | BJ17: 4 | BK17: 46 | BL17: 39 | BM17: 69 | BN17: 144 | BO17: 122 | BP17: 210 | BQ17: 172 | BR17: 65 | BS17: 137 | BT17: 137 | BU17: 123 | BV17: 124 | BW17: 212 | BX17: 193 | BY17: 215 | BZ17: 225 | CA17: 162 | CB17: =CB16*'Assumptions (Quarterly)'!F21 -> 206.53553 | CC17: =CC16*'Assumptions (Quarterly)'!G21 -> 255.07075 | CD17: =CD16*'Assumptions (Quarterly)'!H21 -> 334.60974 | CE17: =CE16*'Assumptions (Quarterly)'!I21 -> 280.15559 | CF17: =CF16*'Assumptions (Quarterly)'!J21 -> 316.03966 | CG17: =CG16*'Assumptions (Quarterly)'!K21 -> 377.12041 | CH17: =CH16*'Assumptions (Quarterly)'!L21 -> 472.15624
A18: Net Income | B18: =B16-B17 -> 1.845086 | C18: =C16-C17 -> 0.994187 | D18: =D16-D17 -> 0.590886 | E18: =E16-E17 -> 2.785474 | F18: =F16-F17 -> 5.322393 | G18: =G16-G17 -> 2.067677 | H18: =H16-H17 -> 2.947095 | I18: =I16-I17 -> 5.875792 | ... CH18: =CH16-CH17 -> 1155.9687
A19: Preferred Dividends | B19: 0.12372 | C19: 0.123719 | D19: 0.12372 | E19: 0.06186 | F19: 0 | G19: 0 | H19: 0 | I19: 0 | J19: 0 | K19: 0 | L19: 0 | M19: 0 | N19: 0 | O19: 0 | P19: 0 | Q19: 0 | R19: 0 | S19: 0 | T19: 0 | U19: 0 | V19: 0 | W19: 0 | X19: 0 | Y19: 0 | Z19: 0 | AA19: 0 | AB19: 0 | AC19: 0 | AD19: 0 | AE19: 0 | AF19: 0 | AG19: 0 | AH19: 0 | AI19: 0 | AJ19: 0 | AK19: 0 | AL19: 0 | AM19: 0 | AN19: 0 | AO19: 0 | AP19: 0 | AQ19: 0 | AR19: 0 | AS19: 0 | AT19: 0 | AU19: 0 | AV19: 0 | AW19: 0 | AX19: 0 | AY19: 0 | AZ19: 0 | BA19: 0 | BB19: 0 | BC19: 0 | BD19: 0 | BE19: 0 | BF19: 0 | BG19: 0 | BH19: 0 | BI19: 0 | BJ19: 0 | BK19: 0 | BL19: 0 | BM19: 0 | BN19: 0 | BO19: 0 | BP19: 0 | BQ19: 0 | BR19: 0 | BS19: 0 | BT19: 0 | BU19: 0 | BV19: 0 | BW19: 0 | BX19: 0 | BY19: 0 | BZ19: 0 | CA19: 0 | CB19: ='Assumptions (Quarterly)'!F33 -> 0 | CC19: ='Assumptions (Quarterly)'!G33 -> 0 | CD19: ='Assumptions (Quarterly)'!H33 -> 0 | CE19: ='Assumptions (Quarterly)'!I33 -> 0 | CF19: ='Assumptions (Quarterly)'!J33 -> 0 | CG19: ='Assumptions (Quarterly)'!K33 -> 0 | CH19: ='Assumptions (Quarterly)'!L33 -> 0
A20: Net Income to Common | B20: =B18-B19 -> 1.721366 | C20: =C18-C19 -> 0.870468 | D20: =D18-D19 -> 0.467166 | E20: =E18-E19 -> 2.723614 | F20: =F18-F19 -> 5.322393 | G20: =G18-G19 -> 2.067677 | H20: =H18-H19 -> 2.947095 | I20: =I18-I19 -> 5.875792 | ... CH20: =CH18-CH19 -> 1155.9687
A22: Shares Outstanding (Basic) | B22: 13.199908 | C22: 13.375482 | D22: 13.575158 | E22: 27.538652 | F22: 25.149405 | G22: 44.22746 | H22: 44.238166 | I22: 44.29054 | J22: 44.189817 | K22: 44.069134 | L22: 44.078235 | M22: 44.088936 | N22: 44.110055 | O22: 44.113595 | P22: 44.121087 | Q22: 44.129762 | R22: 44.131455 | S22: 44.131383 | T22: 44.138105 | U22: 44.141925 | V22: 44.14206 | W22: 44.142076 | X22: 44.147999 | Y22: 44.150387 | Z22: 44.150942 | AA22: 44.151323 | AB22: 44.152933 | AC22: 44.152933 | AD22: 44.153194 | AE22: 44.153818 | AF22: 44.153892 | AG22: 44.153892 | AH22: 44.153935 | AI22: 44.154796 | AJ22: 44.155271 | AK22: 44.15583 | AL22: 44.156811 | AM22: 44.156961 | AN22: 44.157341 | AO22: 44.157341 | AP22: 44.157359 | AQ22: 44.157364 | AR22: 44.157364 | AS22: 44.157364 | AT22: 44.157364 | AU22: 44.157364 | AV22: 44.157364 | AW22: 44.588704 | AX22: 45.210284 | AY22: 45.980255 | AZ22: 49.318522 | BA22: 49.710723 | BB22: 49.721129 | BC22: 49.709955 | BD22: 49.709973 | BE22: 49.720854 | BF22: 49.820765 | BG22: 49.867625 | BH22: 49.822272 | BI22: 49.597157 | BJ22: 49.927892 | BK22: 50.408754 | BL22: 50.364529 | BM22: 50.325075 | BN22: 50.283973 | BO22: 50.245073 | BP22: 50.162687 | BQ22: 50.00832 | BR22: 50.63573 | BS22: 50.697442 | BT22: 50.697447 | BU22: 50.697438 | BV22: 50.697386 | BW22: 50.697375 | BX22: 50.697375 | BY22: 50.697265 | BZ22: 50.697182 | CA22: 50.697182 | CB22: =CA22*(1+'Assumptions (Quarterly)'!F22) -> 50.646485 | CC22: =CB22*(1+'Assumptions (Quarterly)'!G22) -> 50.595838 | CD22: =CC22*(1+'Assumptions (Quarterly)'!H22) -> 50.545242 | CE22: =CD22*(1+'Assumptions (Quarterly)'!I22) -> 50.494697 | CF22: =CE22*(1+'Assumptions (Quarterly)'!J22) -> 50.444203 | CG22: =CF22*(1+'Assumptions (Quarterly)'!K22) -> 50.393758 | CH22: =CG22*(1+'Assumptions (Quarterly)'!L22) -> 50.343365
A23: Shares Outstanding (Diluted) | B23: 0 | C23: 13.375482 | D23: 13.987128 | E23: 27.685028 | F23: 25.478336 | G23: 44.368011 | H23: 44.369317 | I23: 44.379682 | J23: 44.273428 | K23: 44.130866 | L23: 44.132204 | M23: 44.138031 | N23: 44.187238 | O23: 44.1497 | P23: 44.145255 | Q23: 44.151367 | R23: 44.153398 | S23: 44.147667 | T23: 44.152296 | U23: 44.151218 | V23: 44.153132 | W23: 44.147796 | X23: 44.152133 | Y23: 44.157321 | Z23: 44.138018 | AA23: 44.151357 | AB23: 44.152933 | AC23: 44.152933 | AD23: 44.153194 | AE23: 44.153818 | AF23: 44.182668 | AG23: 44.153892 | AH23: 44.153935 | AI23: 44.154796 | AJ23: 44.155271 | AK23: 44.15583 | AL23: 44.156811 | AM23: 44.156961 | AN23: 44.157341 | AO23: 44.157341 | AP23: 44.157359 | AQ23: 44.157364 | AR23: 44.157364 | AS23: 44.157364 | AT23: 44.157364 | AU23: 44.157364 | AV23: 44.157364 | AW23: 44.588704 | AX23: 45.210284 | AY23: 45.980255 | AZ23: 49.318522 | BA23: 49.710723 | BB23: 49.721129 | BC23: 49.709955 | BD23: 49.709973 | BE23: 49.720854 | BF23: 49.820765 | BG23: 49.867625 | BH23: 49.822272 | BI23: 49.597157 | BJ23: 49.927892 | BK23: 50.408754 | BL23: 50.364529 | BM23: 51.315343 | BN23: 51.274241 | BO23: 51.235341 | BP23: 51.152955 | BQ23: 50.209439 | BR23: 53.010605 | BS23: 50.697442 | BT23: 50.697447 | BU23: 50.697438 | BV23: 50.697386 | BW23: 50.697375 | BX23: 50.697375 | BY23: 50.697284 | BZ23: 50.697248 | CA23: 50.697298 | CB23: =CA23*(1+'Assumptions (Quarterly)'!F22) -> 50.646601 | CC23: =CB23*(1+'Assumptions (Quarterly)'!G22) -> 50.595954 | CD23: =CC23*(1+'Assumptions (Quarterly)'!H22) -> 50.545358 | CE23: =CD23*(1+'Assumptions (Quarterly)'!I22) -> 50.494813 | CF23: =CE23*(1+'Assumptions (Quarterly)'!J22) -> 50.444318 | CG23: =CF23*(1+'Assumptions (Quarterly)'!K22) -> 50.393874 | CH23: =CG23*(1+'Assumptions (Quarterly)'!L22) -> 50.34348
A24: EPS (Basic) | B24: =IF(B22=0,"",B20/B22) -> 0.13040742 | C24: =IF(C22=0,"",C20/C22) -> 0.065079374 | D24: =IF(D22=0,"",D20/D22) -> 0.034413301 | E24: =IF(E22=0,"",E20/E22) -> 0.0989015 | F24: =IF(F22=0,"",F20/F22) -> 0.21163097 | G24: =IF(G22=0,"",G20/G22) -> 0.046750978 | H24: =IF(H22=0,"",H20/H22) -> 0.066618833 | I24: =IF(I22=0,"",I20/I22) -> 0.13266472 | ... CA24: =IF(CA22=0,"",CA20/CA22) -> 8.2253092 | CB24: =CB20/CB22 -> 9.9840286 | CC24: =CC20/CC22 -> 12.342588 | CD24: =CD20/CD22 -> 16.207598 | CE24: =CE20/CE22 -> 13.583568 | CF24: =CF20/CF22 -> 15.338775 | CG24: =CG20/CG22 -> 18.32161 | CH24: =CH20/CH22 -> 22.96169
A25: EPS (Diluted) | B25: =IF(B23=0,"",B20/B23) | C25: =IF(C23=0,"",C20/C23) -> 0.065079374 | D25: =IF(D23=0,"",D20/D23) -> 0.033399709 | E25: =IF(E23=0,"",E20/E23) -> 0.098378589 | F25: =IF(F23=0,"",F20/F23) -> 0.20889877 | G25: =IF(G23=0,"",G20/G23) -> 0.046602878 | H25: =IF(H23=0,"",H20/H23) -> 0.066421915 | I25: =IF(I23=0,"",I20/I23) -> 0.13239824 | ... CA25: =IF(CA23=0,"",CA20/CA23) -> 8.2252904 | CB25: =CB20/CB23 -> 9.9840057 | CC25: =CC20/CC23 -> 12.342559 | CD25: =CD20/CD23 -> 16.20756 | CE25: =CE20/CE23 -> 13.583537 | CF25: =CF20/CF23 -> 15.33874 | CG25: =CG20/CG23 -> 18.321568 | CH25: =CH20/CH23 -> 22.961637
A27: BALANCE SHEET
A28: Cash & Equivalents | B28: 7.143027 | C28: 6.390163 | D28: 9.09493 | E28: 14.53598 | F28: 15.677407 | G28: 13.947927 | H28: 17.674256 | I28: 10.403585 | J28: 17.474112 | K28: 17.006309 | L28: 19.374901 | M28: 33.332506 | N28: 49.803402 | O28: 34.634299 | P28: 31.56872 | Q28: 44.4519 | R28: 56.830466 | S28: 50.968258 | T28: 44.250132 | U28: 59.083417 | V28: 67.381677 | W28: 75.874938 | X28: 87.59573 | Y28: 98.171852 | Z28: 101.489 | AA28: 122.16738 | AB28: 131.19135 | AC28: 128.09699 | AD28: 140.2851 | AE28: 131.13955 | AF28: 385.52012 | AG28: 237.50391 | AH28: 223.144 | AI28: 219.768 | AJ28: 170.391 | AK28: 173.024 | AL28: 166.881 | AM28: 144.885 | AN28: 144.016 | AO28: 187.995 | AP28: 234.14 | AQ28: 301.388 | AR28: 382.791 | AS28: 461.198 | AT28: 388.26 | AU28: 350.411 | AV28: 524.011 | AW28: 1077.73 | AX28: 464.695 | AY28: 1306.261 | AZ28: 1128.322 | BA28: 1456.965 | BB28: 1451.424 | BC28: 1265.383 | BD28: 1663.358 | BE28: 1624.129 | BF28: 2508.224 | BG28: 1188.356 | BH28: 1431.089 | BI28: 1422.561 | BJ28: 3648 | BK28: 2414 | BL28: 2253 | BM28: 2528 | BN28: 3363 | BO28: 3524 | BP28: 3824 | BQ28: 3256 | BR28: 3848 | BS28: 3818 | BT28: 3823 | BU28: 3478 | BV28: 4699 | BW28: 4498 | BX28: 6888 | BY28: 9199 | BZ28: 13537 | CA28: 15141 | CB28: =CA28+CB81 -> 16107.472 | CC28: =CB28+CC81 -> 18221.023 | CD28: =CC28+CD81 -> 21239.266 | CE28: =CD28+CE81 -> 21965.247 | CF28: =CE28+CF81 -> 23429.2 | CG28: =CF28+CG81 -> 26140.893 | CH28: =CG28+CH81 -> 29485.223
A29: Short-Term Investments | B29: 6.320656 | C29: 7.736592 | D29: 7.141477 | E29: 48.373617 | F29: 52.300007 | G29: 37.921663 | H29: 31.743124 | I29: 20.489006 | J29: 31.6394 | K29: 29.354094 | L29: 28.647386 | M29: 19.867077 | N29: 14.580185 | O29: 7.077862 | P29: 11.27962 | Q29: 6.584453 | R29: 5.342766 | S29: 3.179205 | T29: 72.384019 | U29: 67.578494 | V29: 74.92862 | W29: 82.72215 | X29: 83.016176 | Y29: 79.390492 | Z29: 93.694805 | AA29: 75.545528 | AB29: 71.299941 | AC29: 91.330179 | AD29: 76.593214 | AE29: 87.390844 | AF29: 105.22866 | AG29: 169.84359 | AH29: 148.81 | AI29: 148.052 | AJ29: 167.161 | AK29: 168.015 | AL29: 202.112 | AM29: 195.569 | AN29: 251.416 | AO29: 283.65 | AP29: 259.604 | AQ29: 276.545 | AR29: 231.455 | AS29: 227.008 | AT29: 282.841 | AU29: 281.774 | AV29: 181.498 | AW29: 157.868 | AX29: 557.319 | AY29: 1783.097 | AZ29: 1982.235 | BA29: 1902.263 | BB29: 1779.346 | BC29: 1699.744 | BD29: 2264.02 | BE29: 2426.614 | BF29: 1626.342 | BG29: 1396.676 | BH29: 1445.55 | BI29: 1814.621 | BJ29: 2009 | BK29: 3069 | BL29: 3435 | BM29: 3667 | BN29: 4043 | BO29: 4356 | BP29: 4890 | BQ29: 5656 | BR29: 6109 | BS29: 6790 | BT29: 7513 | BU29: 8759 | BV29: 9201 | BW29: 10583 | BX29: 11241 | BY29: 11525 | BZ29: 11484 | CA29: 12142 | CB29: =CB6*'Assumptions (Quarterly)'!F38 -> 12509.004 | CC29: =CC6*'Assumptions (Quarterly)'!G38 -> 13648.257 | CD29: =CD6*'Assumptions (Quarterly)'!H38 -> 15151.26 | CE29: =CE6*'Assumptions (Quarterly)'!I38 -> 14950.832 | CF29: =CF6*'Assumptions (Quarterly)'!J38 -> 14839.72 | CG29: =CG6*'Assumptions (Quarterly)'!K38 -> 15907.992 | CH29: =CH6*'Assumptions (Quarterly)'!L38 -> 17709.43
A30: Total Cash & Short-Term Investments | B30: =B28+B29 -> 13.463683 | C30: =C28+C29 -> 14.126755 | D30: =D28+D29 -> 16.236407 | E30: =E28+E29 -> 62.909597 | F30: =F28+F29 -> 67.977414 | G30: =G28+G29 -> 51.86959 | H30: =H28+H29 -> 49.41738 | I30: =I28+I29 -> 30.892591 | ... CH30: =CH28+CH29 -> 47194.653
A31: Receivables | B31: 12.171715 | C31: 12.375465 | D31: 13.353793 | E31: 19.716352 | F31: 32.374015 | G31: 28.678864 | H31: 39.60244 | I31: 40.608683 | J31: 6.178808 | K31: 6.691454 | L31: 6.430542 | M31: 7.842202 | N31: 8.654179 | O31: 10.816958 | P31: 12.403569 | Q31: 15.821176 | R31: 18.769691 | S31: 19.080174 | T31: 22.89457 | U31: 28.673498 | V31: 40.670776 | W31: 40.302502 | X31: 44.581635 | Y31: 56.246485 | Z31: 55.653528 | AA31: 61.118162 | AB31: 82.942389 | AC31: 64.489304 | AD31: 77.930111 | AE31: 84.653793 | AF31: 94.123106 | AG31: 125.71238 | AH31: 131.834 | AI31: 187.698 | AJ31: 177.094 | AK31: 242.117 | AL31: 160.374 | AM31: 240.784 | AN31: 255.492 | AO31: 257.904 | AP31: 333.339 | AQ31: 324.709 | AR31: 289.945 | AS31: 435.447 | AT31: 549.298 | AU31: 560.099 | AV31: 335.084 | AW31: 293.602 | AX31: 395.451 | AY31: 342.992 | AZ31: 473.221 | BA31: 324.379 | BB31: 415.415 | BC31: 400.863 | BD31: 689.162 | BE31: 701.293 | BF31: 912.764 | BG31: 948.485 | BH31: 1259.646 | BI31: 1498.996 | BJ31: 1937 | BK31: 2610 | BL31: 2603 | BM31: 2658 | BN31: 3076 | BO31: 2931 | BP31: 2995 | BQ31: 3536 | BR31: 3788 | BS31: 4132 | BT31: 4358 | BU31: 4801 | BV31: 5543 | BW31: 5793 | BX31: 6865 | BY31: 6946 | BZ31: 7415 | CA31: 8504 | CB31: =CB6*'Assumptions (Quarterly)'!F35 -> 8765.4336 | CC31: =CC6*'Assumptions (Quarterly)'!G35 -> 9705.427 | CD31: =CD6*'Assumptions (Quarterly)'!H35 -> 11072.074 | CE31: =CE6*'Assumptions (Quarterly)'!I35 -> 11040.614 | CF31: =CF6*'Assumptions (Quarterly)'!J35 -> 11129.79 | CG31: =CG6*'Assumptions (Quarterly)'!K35 -> 12120.375 | CH31: =CH6*'Assumptions (Quarterly)'!L35 -> 13567.708
A32: Inventory | B32: 0 | C32: 0 | D32: 0 | E32: 0 | F32: 0 | G32: 0 | H32: 0 | I32: 0 | J32: 0 | K32: 0 | L32: 0 | M32: 0 | N32: 0 | O32: 0 | P32: 0 | Q32: 0 | R32: 0 | S32: 0 | T32: 0 | U32: 0 | V32: 0 | W32: 0 | X32: 0 | Y32: 0 | Z32: 0 | AA32: 0 | AB32: 0 | AC32: 0 | AD32: 0 | AE32: 0 | AF32: 0 | AG32: 0 | AH32: 0 | AI32: 0 | AJ32: 0 | AK32: 0.135 | AL32: 0.222 | AM32: 0.42 | AN32: 0.99 | AO32: 1.388 | AP32: 1.103 | AQ32: 0.432 | AR32: 1.034 | AS32: 2.309 | AT32: 2.549 | AU32: 3.362 | AV32: 7.938 | AW32: 7.395 | AX32: 4.612 | AY32: 3.003 | AZ32: 5.95 | BA32: 10.132 | BB32: 8.626 | BC32: 12.114 | BD32: 20.831 | BE32: 46.644 | BF32: 118.14 | BG32: 131.46 | BH32: 169.449 | BI32: 226.694 | BJ32: 253 | BK32: 239 | BL32: 183 | BM32: 160 | BN32: 152 | BO32: 199 | BP32: 236 | BQ32: 246 | BR32: 238 | BS32: 223 | BT32: 257 | BU32: 322 | BV32: 296 | BW32: 358 | BX32: 434 | BY32: 532 | BZ32: 570 | CA32: 677 | CB32: =CB6*'Assumptions (Quarterly)'!F36 -> 703.06082 | CC32: =CC6*'Assumptions (Quarterly)'!G36 -> 778.45613 | CD32: =CD6*'Assumptions (Quarterly)'!H36 -> 885.76594 | CE32: =CE6*'Assumptions (Quarterly)'!I36 -> 885.54928 | CF32: =CF6*'Assumptions (Quarterly)'!J36 -> 892.7019 | CG32: =CG6*'Assumptions (Quarterly)'!K36 -> 972.15506 | CH32: =CH6*'Assumptions (Quarterly)'!L36 -> 1085.4166
A33: Other Current Assets | B33: 3.48448 | C33: 3.878033 | D33: 3.816206 | E33: 3.455271 | F33: 4.622741 | G33: 7.296034 | H33: 6.173713 | I33: 7.614242 | J33: 5.008904 | K33: 4.22251 | L33: 9.944814 | M33: 13.350809 | N33: 9.09725 | O33: 9.366018 | P33: 12.03249 | Q33: 18.57764 | R33: 20.692285 | S33: 20.996826 | T33: 19.692995 | U33: 19.155538 | V33: 17.264482 | W33: 18.299573 | X33: 18.350863 | Y33: 21.102893 | Z33: 24.52384 | AA33: 29.733988 | AB33: 27.565935 | AC33: 33.832618 | AD33: 31.355806 | AE33: 34.026946 | AF33: 29.344268 | AG33: 36.831743 | AH33: 28.962 | AI33: 32.657 | AJ33: 32.708 | AK33: 41.923 | AL33: 15.584 | AM33: 23.391 | AN33: 21.353 | AO33: 28.17 | AP33: 41.275 | AQ33: 43.318 | AR33: 52.96 | AS33: 56.194 | AT33: 63.971 | AU33: 89.914 | AV33: 76.623 | AW33: 65.084 | AX33: 89.046 | AY33: 85.1 | AZ33: 86.704 | BA33: 86.891 | BB33: 134.045 | BC33: 132.17 | BD33: 117.183 | BE33: 125.211 | BF33: 181.337 | BG33: 235.214 | BH33: 261.917 | BI33: 320.249 | BJ33: 328 | BK33: 373 | BL33: 389 | BM33: 338 | BN33: 319 | BO33: 326 | BP33: 345 | BQ33: 356 | BR33: 277 | BS33: 542 | BT33: 528 | BU33: 464 | BV33: 403 | BW33: 508 | BX33: 634 | BY33: 593 | BZ33: 567 | CA33: 659 | CB33: =CB6*'Assumptions (Quarterly)'!F37 -> 684.7995 | CC33: =CC6*'Assumptions (Quarterly)'!G37 -> 758.23649 | CD33: =CD6*'Assumptions (Quarterly)'!H37 -> 862.45631 | CE33: =CE6*'Assumptions (Quarterly)'!I37 -> 862.548 | CF33: =CF6*'Assumptions (Quarterly)'!J37 -> 869.51484 | CG33: =CG6*'Assumptions (Quarterly)'!K37 -> 946.90428 | CH33: =CH6*'Assumptions (Quarterly)'!L37 -> 1056.8531
A34: Total Current Assets | B34: =B30+B31+B32+B33 -> 29.119878 | C34: =C30+C31+C32+C33 -> 30.380253 | D34: =D30+D31+D32+D33 -> 33.406406 | E34: =E30+E31+E32+E33 -> 86.08122 | F34: =F30+F31+F32+F33 -> 104.97417 | G34: =G30+G31+G32+G33 -> 87.844488 | H34: =H30+H31+H32+H33 -> 95.193533 | I34: =I30+I31+I32+I33 -> 79.115516 | ... CH34: =CH30+CH31+CH32+CH33 -> 62904.63
A35: Property, Plant & Equipment | B35: 2.93147 | C35: 3.076521 | D35: 4.017032 | E35: 4.171087 | F35: 4.143204 | G35: 4.732349 | H35: 5.676382 | I35: 5.874868 | J35: 5.94016 | K35: 6.730431 | L35: 6.402482 | M35: 6.394512 | N35: 5.948276 | O35: 7.263001 | P35: 7.6891 | Q35: 19.062411 | R35: 20.817712 | S35: 22.672952 | T35: 31.316388 | U35: 31.351966 | V35: 30.877719 | W35: 33.117055 | X35: 35.103153 | Y35: 35.217386 | Z35: 37.726222 | AA35: 38.0172 | AB35: 80.081659 | AC35: 80.00011 | AD35: 131.37191 | AE35: 129.46493 | AF35: 83.780843 | AG35: 83.926941 | AH35: 91.545 | AI35: 75.945 | AJ35: 82.735 | AK35: 82.51 | AL35: 81.633 | AM35: 89.932 | AN35: 104.808 | AO35: 121.006 | AP35: 124.261 | AQ35: 131.968 | AR35: 130.594 | AS35: 136.101 | AT35: 114.837 | AU35: 122.859 | AV35: 113.17 | AW35: 138.417 | AX35: 165.614 | AY35: 342.455 | AZ35: 373.848 | BA35: 395.876 | BB35: 444.706 | BC35: 422.783 | BD35: 449.892 | BE35: 527.834 | BF35: 694.898 | BG35: 803.953 | BH35: 1015.25 | BI35: 1092.334 | BJ35: 1268 | BK35: 1509 | BL35: 1457 | BM35: 1532 | BN35: 1649 | BO35: 1733 | BP35: 1869 | BQ35: 1877 | BR35: 2149 | BS35: 2132 | BT35: 1993 | BU35: 2251 | BV35: 2478 | BW35: 2825 | BX35: 3463 | BY35: 4100 | BZ35: 4504 | CA35: 4815 | CB35: =CA35+CB6*'Assumptions (Quarterly)'!F28-CB6*'Assumptions (Quarterly)'!F26 -> 4961.0906 | CC35: =CB35+CC6*'Assumptions (Quarterly)'!G28-CC6*'Assumptions (Quarterly)'!G26 -> 5122.8477 | CD35: =CC35+CD6*'Assumptions (Quarterly)'!H28-CD6*'Assumptions (Quarterly)'!H26 -> 5297.6699 | CE35: =CD35+CE6*'Assumptions (Quarterly)'!I28-CE6*'Assumptions (Quarterly)'!I26 -> 5470.1795 | CF35: =CE35+CF6*'Assumptions (Quarterly)'!J28-CF6*'Assumptions (Quarterly)'!J26 -> 5632.4889 | CG35: =CF35+CG6*'Assumptions (Quarterly)'!K28-CG6*'Assumptions (Quarterly)'!K26 -> 5796.619 | CH35: =CG35+CH6*'Assumptions (Quarterly)'!L28-CH6*'Assumptions (Quarterly)'!L26 -> 5968.0006
A36: Long-Term Investments | B36: 0 | C36: 1.437402 | D36: 1.447859 | E36: 1.459271 | F36: 1.323789 | G36: 1.427431 | H36: 2.244276 | I36: 3.057065 | J36: 9.218153 | K36: 13.763469 | L36: 22.402035 | M36: 24.314404 | N36: 26.627357 | O36: 54.864792 | P36: 66.112729 | Q36: 65.852573 | R36: 78.846281 | S36: 101.82432 | T36: 50.201025 | U36: 41.002762 | V36: 43.933316 | W36: 43.084473 | X36: 49.571882 | Y36: 59.418012 | Z36: 85.955584 | AA36: 94.956562 | AB36: 59.437585 | AC36: 69.806906 | AD36: 45.719737 | AE36: 45.001998 | AF36: 52.145285 | AG36: 158.83905 | AH36: 205.265 | AI36: 190.152 | AJ36: 209.324 | AK36: 185.733 | AL36: 187.621 | AM36: 187.889 | AN36: 157.832 | AO36: 155.178 | AP36: 153.803 | AQ36: 170.352 | AR36: 186.322 | AS36: 45.55 | AT36: 34.72 | AU36: 33.41 | AV36: 11.394 | AW36: 2.823 | AX36: 276.136 | AY36: 275.432 | AZ36: 207.047 | BA36: 3.595 | BB36: 270.422 | BC36: 276.834 | BD36: 10.845 | BE36: 21.963 | BF36: 182.73 | BG36: 194.45 | BH36: 204.68 | BI36: 69.211 | BJ36: 150 | BK36: 201 | BL36: 511 | BM36: 417 | BN36: 354 | BO36: 309 | BP36: 225 | BQ36: 191 | BR36: 227 | BS36: 335 | BT36: 527 | BU36: 1382 | BV36: 1382 | BW36: 1546 | BX36: 1665 | BY36: 1718 | BZ36: 2274 | CA36: 2262 | CB36: =CA36*(1+'Assumptions (Quarterly)'!F44) -> 2318.55 | CC36: =CB36*(1+'Assumptions (Quarterly)'!G44) -> 2376.5138 | CD36: =CC36*(1+'Assumptions (Quarterly)'!H44) -> 2435.9266 | CE36: =CD36*(1+'Assumptions (Quarterly)'!I44) -> 2496.8248 | CF36: =CE36*(1+'Assumptions (Quarterly)'!J44) -> 2559.2454 | CG36: =CF36*(1+'Assumptions (Quarterly)'!K44) -> 2623.2265 | CH36: =CG36*(1+'Assumptions (Quarterly)'!L44) -> 2688.8072
A37: Goodwill & Intangibles | B37: 21.342315 | C37: 21.707341 | D37: 22.645835 | E37: 23.018001 | F37: 23.428646 | G37: 42.812153 | H37: 43.893181 | I37: 80.592075 | J37: 72.911546 | K37: 71.431003 | L37: 74.488034 | M37: 75.525514 | N37: 64.338564 | O37: 63.769288 | P37: 62.932379 | Q37: 64.790278 | R37: 64.637481 | S37: 64.459731 | T37: 65.17578 | U37: 69.571885 | V37: 68.588805 | W37: 70.562274 | X37: 68.7351 | Y37: 68.892998 | Z37: 67.645928 | AA37: 69.986076 | AB37: 66.275789 | AC37: 64.294149 | AD37: 61.692803 | AE37: 58.353034 | AF37: 95.950947 | AG37: 90.373013 | AH37: 92 | AI37: 88.378 | AJ37: 136.105 | AK37: 122.366 | AL37: 115.536 | AM37: 120.435 | AN37: 125.276 | AO37: 122.218 | AP37: 118.074 | AQ37: 122.076 | AR37: 119.477 | AS37: 119.891 | AT37: 115.453 | AU37: 116.106 | AV37: 102.893 | AW37: 107.369 | AX37: 107.464 | AY37: 107.51 | AZ37: 107.183 | BA37: 101.228 | BB37: 101.884 | BC37: 99.416 | BD37: 97.741 | BE37: 93.294 | BF37: 99.366 | BG37: 103.101 | BH37: 109.059 | BI37: 111.658 | BJ37: 193 | BK37: 205 | BL37: 180 | BM37: 176 | BN37: 178 | BO37: 184 | BP37: 188 | BQ37: 180 | BR37: 198 | BS37: 210 | BT37: 198 | BU37: 195 | BV37: 210 | BW37: 247 | BX37: 268 | BY37: 277 | BZ37: 196 | CA37: 198 | CB37: ='Assumptions (Quarterly)'!F46 -> 198 | CC37: ='Assumptions (Quarterly)'!G46 -> 198 | CD37: ='Assumptions (Quarterly)'!H46 -> 198 | CE37: ='Assumptions (Quarterly)'!I46 -> 198 | CF37: ='Assumptions (Quarterly)'!J46 -> 198 | CG37: ='Assumptions (Quarterly)'!K46 -> 198 | CH37: ='Assumptions (Quarterly)'!L46 -> 198
A38: Other Long-Term Assets | B38: 0.418909 | C38: 0.577082 | D38: 0.706186 | E38: 0.728962 | F38: 0.622991 | G38: 0.260147 | H38: 0.40884 | I38: 0.485237 | J38: 8.367666 | K38: 11.69922 | L38: 15.529518 | M38: 14.856998 | N38: 3.565436 | O38: 4.545014 | P38: 4.623123 | Q38: 5.592221 | R38: 3.746341 | S38: 3.551709 | T38: 2.611067 | U38: 8.92603 | V38: 12.286041 | W38: 12.606491 | X38: 11.597194 | Y38: 12.184434 | Z38: 11.980367 | AA38: 11.695895 | AB38: 10.787587 | AC38: 37.470985 | AD38: 27.414089 | AE38: 27.827577 | AF38: 41.871676 | AG38: 36.167992 | AH38: 45.288 | AI38: 34.133 | AJ38: 45.117 | AK38: 53.005 | AL38: 73.643 | AM38: 80.164 | AN38: 78.966 | AO38: 98.548 | AP38: 101.836 | AQ38: 112.858 | AR38: 116.86 | AS38: 134.594 | AT38: 121.258 | AU38: 161.752 | AV38: 166.83 | AW38: 168.063 | AX38: 179.182 | AY38: 202.31 | AZ38: 230.982 | BA38: 158.012 | BB38: 175.823 | BC38: 148.773 | BD38: 139.704 | BE38: 170.737 | BF38: 202.531 | BG38: 196.16 | BH38: 246.054 | BI38: 243.693 | BJ38: 315 | BK38: 403 | BL38: 436 | BM38: 486 | BN38: 602 | BO38: 639 | BP38: 671 | BQ38: 826 | BR38: 778 | BS38: 880 | BT38: 833 | BU38: 971 | BV38: 984 | BW38: 1324 | BX38: 1490 | BY38: 1801 | BZ38: 2120 | CA38: 2536 | CB38: =CB6*'Assumptions (Quarterly)'!F42 -> 2620.4994 | CC38: =CC6*'Assumptions (Quarterly)'!G42 -> 2901.5183 | CD38: =CD6*'Assumptions (Quarterly)'!H42 -> 3344.9319 | CE38: =CE6*'Assumptions (Quarterly)'!I42 -> 3300.6837 | CF38: =CF6*'Assumptions (Quarterly)'!J42 -> 3327.3435 | CG38: =CG6*'Assumptions (Quarterly)'!K42 -> 3623.487 | CH38: =CH6*'Assumptions (Quarterly)'!L42 -> 4098.876
A39: Total Long-Term Assets | B39: =B35+B36+B37+B38 -> 24.692694 | C39: =C35+C36+C37+C38 -> 26.798346 | D39: =D35+D36+D37+D38 -> 28.816912 | E39: =E35+E36+E37+E38 -> 29.377321 | F39: =F35+F36+F37+F38 -> 29.51863 | G39: =G35+G36+G37+G38 -> 49.23208 | H39: =H35+H36+H37+H38 -> 52.222679 | I39: =I35+I36+I37+I38 -> 90.009245 | ... CH39: =CH35+CH36+CH37+CH38 -> 12953.684
A40: Total Assets | B40: =B34+B39 -> 53.812572 | C40: =C34+C39 -> 57.178599 | D40: =D34+D39 -> 62.223318 | E40: =E34+E39 -> 115.45854 | F40: =F34+F39 -> 134.4928 | G40: =G34+G39 -> 137.07657 | H40: =H34+H39 -> 147.41621 | I40: =I34+I39 -> 169.12476 | ... CH40: =CH34+CH39 -> 75858.314
A42: Accounts Payable | B42: 17.516569 | C42: 18.523162 | D42: 19.217765 | E42: 23.939185 | F42: 29.474551 | G42: 32.697175 | H42: 36.478364 | I42: 42.278878 | J42: 36.396861 | K42: 38.59461 | L42: 43.93758 | M42: 51.31934 | N42: 43.053044 | O42: 46.408974 | P42: 49.797292 | Q42: 54.929348 | R42: 66.020328 | S42: 70.716898 | T42: 78.509696 | U42: 78.873056 | V42: 106.83696 | W42: 92.21449 | X42: 120.5434 | Y42: 130.02019 | Z42: 148.87618 | AA42: 164.37241 | AB42: 171.55803 | AC42: 187.36745 | AD42: 195.81208 | AE42: 201.09901 | AF42: 215.27997 | AG42: 254.492 | AH42: 263.143 | AI42: 299.753 | AJ42: 303.703 | AK42: 338.216 | AL42: 308.625 | AM42: 350.219 | AN42: 406.621 | AO42: 468.284 | AP42: 540.87 | AQ42: 590.834 | AR42: 646.723 | AS42: 784.269 | AT42: 894.257 | AU42: 938.51 | AV42: 793.89 | AW42: 836.849 | AX42: 991.28 | AY42: 1035.463 | AZ42: 1194.486 | BA42: 1170.994 | BB42: 1395.01 | BC42: 1130.178 | BD42: 1882.587 | BE42: 2117.247 | BF42: 2757.641 | BG42: 2354.038 | BH42: 2919.934 | BI42: 3193.656 | BJ42: 4083 | BK42: 4258 | BL42: 4373 | BM42: 4480 | BN42: 5736 | BO42: 5829 | BP42: 6600 | BQ42: 7202 | BR42: 8229 | BS42: 9145 | BT42: 9946 | BU42: 11175 | BV42: 12841 | BW42: 13553 | BX42: 16555 | BY42: 18519 | BZ42: 22218 | CA42: 24555 | CB42: =CB6*'Assumptions (Quarterly)'!F39 -> 25383.235 | CC42: =CC6*'Assumptions (Quarterly)'!G39 -> 28307.495 | CD42: =CD6*'Assumptions (Quarterly)'!H39 -> 32400.386 | CE42: =CE6*'Assumptions (Quarterly)'!I39 -> 32201.792 | CF42: =CF6*'Assumptions (Quarterly)'!J39 -> 32693.758 | CG42: =CG6*'Assumptions (Quarterly)'!K39 -> 35856.109 | CH42: =CH6*'Assumptions (Quarterly)'!L39 -> 40274.67
A43: Deferred Revenue | B43: 0 | C43: 0 | D43: 0 | E43: 0 | F43: 0 | G43: 0 | H43: 0 | I43: 0 | J43: 0 | K43: 0 | L43: 0 | M43: 0 | N43: 0 | O43: 0 | P43: 0 | Q43: 0 | R43: 0 | S43: 0 | T43: 0 | U43: 0 | V43: 0 | W43: 0 | X43: 0 | Y43: 0 | Z43: 0 | AA43: 0 | AB43: 0 | AC43: 0 | AD43: 0 | AE43: 0 | AF43: 0 | AG43: 0 | AH43: 0 | AI43: 0 | AJ43: 0 | AK43: 0 | AL43: 0 | AM43: 0 | AN43: 0 | AO43: 0 | AP43: 0 | AQ43: 0 | AR43: 0 | AS43: 0 | AT43: 0 | AU43: 0 | AV43: 0 | AW43: 0 | AX43: 0 | AY43: 0 | AZ43: 0 | BA43: 0 | BB43: 0 | BC43: 0 | BD43: 0 | BE43: 0 | BF43: 0 | BG43: 0 | BH43: 0 | BI43: 0 | BJ43: 0 | BK43: 0 | BL43: 0 | BM43: 0 | BN43: 0 | BO43: 0 | BP43: 0 | BQ43: 0 | BR43: 0 | BS43: 0 | BT43: 0 | BU43: 0 | BV43: 0 | BW43: 0 | BX43: 0 | BY43: 0 | BZ43: 0 | CA43: 0 | CB43: 0 | CC43: 0 | CD43: 0 | CE43: 0 | CF43: 0 | CG43: 0 | CH43: 0
A44: Current Debt | B44: 0.097527 | C44: 0.256076 | D44: 0.415647 | E44: 3.05058 | F44: 9.713227 | G44: 3.619514 | H44: 2.667192 | I44: 18.497771 | J44: 14.963421 | K44: 18.4906 | L44: 15.465001 | M44: 6.343964 | N44: 3.213992 | O44: 0 | P44: 0.056121 | Q44: 0.030905 | R44: 0.100031 | S44: 0.092513 | T44: 0.105498 | U44: 0.140107 | V44: 0.146194 | W44: 0.142687 | X44: 0.146604 | Y44: 0.124753 | Z44: 0.08457 | AA44: 0.115017 | AB44: 11.870676 | AC44: 18.909134 | AD44: 13.370823 | AE44: 7.677659 | AF44: 2.258026 | AG44: 1.548537 | AH44: 1.642 | AI44: 1.565 | AJ44: 1.499 | AK44: 4.294 | AL44: 1.965 | AM44: 3.277 | AN44: 0.782 | AO44: 6.077 | AP44: 11.583 | AQ44: 16.43 | AR44: 18.24 | AS44: 24.701 | AT44: 56.325 | AU44: 134.466 | AV44: 146.655 | AW44: 141.502 | AX44: 132.949 | AY44: 153.747 | AZ44: 176.94 | BA44: 126.349 | BB44: 209.397 | BC44: 339.533 | BD44: 616.796 | BE44: 657.784 | BF44: 603.639 | BG44: 581.804 | BH44: 660.383 | BI44: 848.812 | BJ44: 1377 | BK44: 1568 | BL44: 2033 | BM44: 2067 | BN44: 2273 | BO44: 2491 | BP44: 2452 | BQ44: 2443 | BR44: 2458 | BS44: 2409 | BT44: 2341 | BU44: 2451 | BV44: 3069 | BW44: 3853 | BX44: 4162 | BY44: 4832 | BZ44: 5053 | CA44: 5788 | CB44: =CB95+CB93 -> 5971.4516 | CC44: =CC95+CC93 -> 6611.8222 | CD44: =CD95+CD93 -> 7622.249 | CE44: =CE95+CE93 -> 7521.4186 | CF44: =CF95+CF93 -> 7582.1694 | CG44: =CG95+CG93 -> 8257.0053 | CH44: =CH95+CH93 -> 9340.2959
A45: Other Current Liabilities | B45: 2.046823 | C45: 1.983115 | D45: 5.998696 | E45: 2.037854 | F45: 2.563728 | G45: 3.38286 | H45: 4.118796 | I45: 5.760862 | J45: 4.949603 | K45: 3.655538 | L45: 10.489046 | M45: 12.011736 | N45: 14.225856 | O45: 12.247271 | P45: 15.670723 | Q45: 18.935442 | R45: 22.274108 | S45: 23.083075 | T45: 22.138218 | U45: 25.251283 | V45: 11.320368 | W45: 27.845935 | X45: 11.340572 | Y45: 13.271075 | Z45: 20.570519 | AA45: 18.241547 | AB45: 15.360454 | AC45: 13.946211 | AD45: 14.98271 | AE45: 18.063286 | AF45: 22.911069 | AG45: 26.875266 | AH45: 27.838 | AI45: 21.842 | AJ45: 40.477 | AK45: 24.801 | AL45: 11.885 | AM45: 32.832 | AN45: 14.952 | AO45: 21.952 | AP45: 24.148 | AQ45: 30.4 | AR45: 11.074 | AS45: 13.823 | AT45: 17.45 | AU45: 12.875 | AV45: 34.519 | AW45: 11.181 | AX45: 41.995 | AY45: 59.005 | AZ45: 78.083 | BA45: 87.467 | BB45: 147.913 | BC45: 106.789 | BD45: 160.396 | BE45: 232.229 | BF45: 274.6 | BG45: 269.107 | BH45: 288.973 | BI45: 244.063 | BJ45: 377 | BK45: 402 | BL45: 417 | BM45: 455 | BN45: 553 | BO45: 507 | BP45: 564 | BQ45: 661 | BR45: 576 | BS45: 702 | BT45: 627 | BU45: 687 | BV45: 693 | BW45: 659 | BX45: 1033 | BY45: 1171 | BZ45: 1362 | CA45: 1626 | CB45: =CB6*'Assumptions (Quarterly)'!F40 -> 1680.0414 | CC45: =CC6*'Assumptions (Quarterly)'!G40 -> 1860.2068 | CD45: =CD6*'Assumptions (Quarterly)'!H40 -> 2144.486 | CE45: =CE6*'Assumptions (Quarterly)'!I40 -> 2116.1178 | CF45: =CF6*'Assumptions (Quarterly)'!J40 -> 2133.2097 | CG45: =CG6*'Assumptions (Quarterly)'!K40 -> 2323.0718 | CH45: =CH6*'Assumptions (Quarterly)'!L40 -> 2627.8508
A46: Total Current Liabilities | B46: =B42+B43+B44+B45 -> 19.660919 | C46: =C42+C43+C44+C45 -> 20.762353 | D46: =D42+D43+D44+D45 -> 25.632108 | E46: =E42+E43+E44+E45 -> 29.027619 | F46: =F42+F43+F44+F45 -> 41.751506 | G46: =G42+G43+G44+G45 -> 39.699549 | H46: =H42+H43+H44+H45 -> 43.264352 | I46: =I42+I43+I44+I45 -> 66.537511 | ... CH46: =CH42+CH43+CH44+CH45 -> 52242.817
A47: Long-Term Debt | B47: 9 | C47: 9 | D47: 9 | E47: 0 | F47: 0 | G47: 0.009018 | H47: 0.005959 | I47: 0 | J47: 3.050061 | K47: 0 | L47: 0 | M47: 0 | N47: 0 | O47: 0 | P47: 0.161008 | Q47: 0.280228 | R47: 0.188846 | S47: 0.166592 | T47: 0.125721 | U47: 0.178543 | V47: 0.136227 | W47: 0.101249 | X47: 0.094093 | Y47: 0.074937 | Z47: 0.059493 | AA47: 0.046463 | AB47: 0.033977 | AC47: 0.023575 | AD47: 2.489819 | AE47: 1.812047 | AF47: 278.36278 | AG47: 282.94551 | AH47: 282.184 | AI47: 286.18 | AJ47: 286.525 | AK47: 292.726 | AL47: 294.342 | AM47: 295.683 | AN47: 296.691 | AO47: 299.472 | AP47: 301.94 | AQ47: 304.534 | AR47: 306.706 | AS47: 309.444 | AT47: 312.089 | AU47: 314.953 | AV47: 333.364 | AW47: 554.83 | AX47: 602.228 | AY47: 745.108 | AZ47: 767.225 | BA47: 782.115 | BB47: 808.026 | BC47: 785.442 | BD47: 779.488 | BE47: 807.435 | BF47: 1104.477 | BG47: 1937.162 | BH47: 2101.96 | BI47: 2277.726 | BJ47: 2605 | BK47: 3072 | BL47: 2935 | BM47: 3213 | BN47: 3141 | BO47: 3029 | BP47: 3076 | BQ47: 2797 | BR47: 2875 | BS47: 2877 | BT47: 3062 | BU47: 3873 | BV47: 3781 | BW47: 3873 | BX47: 4817 | BY47: 5045 | BZ47: 6339 | CA47: 6557 | CB47: =CA47*(1+'Assumptions (Quarterly)'!F45) -> 6786.495 | CC47: =CB47*(1+'Assumptions (Quarterly)'!G45) -> 7024.0223 | CD47: =CC47*(1+'Assumptions (Quarterly)'!H45) -> 7269.8631 | CE47: =CD47*(1+'Assumptions (Quarterly)'!I45) -> 7487.959 | CF47: =CE47*(1+'Assumptions (Quarterly)'!J45) -> 7712.5978 | CG47: =CF47*(1+'Assumptions (Quarterly)'!K45) -> 7943.9757 | CH47: =CG47*(1+'Assumptions (Quarterly)'!L45) -> 8142.5751
A48: Other Long-Term Liabilities | B48: 1.803315 | C48: 2.417652 | D48: 0.723764 | E48: 0.948406 | F48: 1.068155 | G48: 2.733187 | H48: 3.172724 | I48: 3.717399 | J48: 3.954822 | K48: 4.631162 | L48: 6.900108 | M48: 7.39903 | N48: 7.92852 | O48: 10.434277 | P48: 9.235074 | Q48: 10.397032 | R48: 9.38144 | S48: 9.56896 | T48: 10.017673 | U48: 13.046558 | V48: 14.312668 | W48: 14.585279 | X48: 14.586006 | Y48: 15.027837 | Z48: 15.264885 | AA48: 16.436933 | AB48: 17.855036 | AC48: 20.874334 | AD48: 18.223737 | AE48: 15.341309 | AF48: 30.637945 | AG48: 28.488017 | AH48: 36.253 | AI48: 36.325 | AJ48: 43.988 | AK48: 45.339 | AL48: 47.331 | AM48: 48.392 | AN48: 56.536 | AO48: 65.285 | AP48: 60.04 | AQ48: 59.204 | AR48: 69.68 | AS48: 79.899 | AT48: 67.287 | AU48: 66.016 | AV48: 56.276 | AW48: 132.237 | AX48: 134.367 | AY48: 142.091 | AZ48: 134.146 | BA48: 135.399 | BB48: 139.382 | BC48: 130.728 | BD48: 106.377 | BE48: 127.498 | BF48: 134.397 | BG48: 86.148 | BH48: 90.414 | BI48: 112.784 | BJ48: 128 | BK48: 134 | BL48: 109 | BM48: 116 | BN48: 206 | BO48: 305 | BP48: 299 | BQ48: 280 | BR48: 403 | BS48: 539 | BT48: 398 | BU48: 435 | BV48: 461 | BW48: 740 | BX48: 668 | BY48: 906 | BZ48: 947 | CA48: 1127 | CB48: =CB6*'Assumptions (Quarterly)'!F43 -> 1159.5938 | CC48: =CC6*'Assumptions (Quarterly)'!G43 -> 1283.9471 | CD48: =CD6*'Assumptions (Quarterly)'!H43 -> 1480.1615 | CE48: =CE6*'Assumptions (Quarterly)'!I43 -> 1460.5813 | CF48: =CF6*'Assumptions (Quarterly)'!J43 -> 1472.3785 | CG48: =CG6*'Assumptions (Quarterly)'!K43 -> 1603.4246 | CH48: =CH6*'Assumptions (Quarterly)'!L43 -> 1813.7883
A49: Total Long-Term Liabilities | B49: =B47+B48 -> 10.803315 | C49: =C47+C48 -> 11.417652 | D49: =D47+D48 -> 9.723764 | E49: =E47+E48 -> 0.948406 | F49: =F47+F48 -> 1.068155 | G49: =G47+G48 -> 2.742205 | H49: =H47+H48 -> 3.178683 | I49: =I47+I48 -> 3.717399 | ... CH49: =CH47+CH48 -> 9956.3634
A50: Total Liabilities | B50: =B46+B49 -> 30.464234 | C50: =C46+C49 -> 32.180005 | D50: =D46+D49 -> 35.355872 | E50: =E46+E49 -> 29.976025 | F50: =F46+F49 -> 42.819661 | G50: =G46+G49 -> 42.441754 | H50: =H46+H49 -> 46.443035 | I50: =I46+I49 -> 70.25491 | ... CH50: =CH46+CH49 -> 62199.181
A52: Shareholders' Equity | B52: -40.728207 | C52: -39.20167 | D52: -37.456538 | E52: 85.482516 | F52: 91.673139 | G52: 94.634814 | H52: 100.97318 | I52: 98.869851 | J52: 93.423981 | K52: 95.52658 | L52: 106.42798 | M52: 118.40995 | N52: 114.19324 | O52: 123.24671 | P52: 133.72151 | Q52: 156.1597 | R52: 171.71827 | S52: 183.10514 | T52: 197.62917 | U52: 204.44341 | V52: 219.17902 | W52: 237.67982 | X52: 247.84105 | Y52: 268.10576 | Z52: 289.81363 | AA52: 300.00842 | AB52: 308.90406 | AC52: 324.20054 | AD52: 343.48361 | AE52: 349.86536 | AF52: 334.51511 | AG52: 340.84929 | AH52: 355.788 | AI52: 331.118 | AJ52: 344.443 | AK52: 363.452 | AL52: 339.458 | AM52: 353.066 | AN52: 364.567 | AO52: 394.987 | AP52: 428.854 | AQ52: 482.244 | AR52: 459.015 | AS52: 406.156 | AT52: 325.779 | AU52: 252.867 | AV52: 154.737 | AW52: 341.752 | AX52: 336.7 | AY52: 2214.058 | AZ52: 2145.769 | BA52: 2038.174 | BB52: 1983.12 | BC52: 1866.567 | BD52: 1808.249 | BE52: 1746.099 | BF52: 1651.578 | BG52: -30.404 | BH52: 81.03 | BI52: 122.976 | BJ52: 1531 | BK52: 1589 | BL52: 1580 | BM52: 1631 | BN52: 1827 | BO52: 2040 | BP52: 2252 | BQ52: 2741 | BR52: 3071 | BS52: 3390 | BT52: 3656 | BU52: 4002 | BV52: 4351 | BW52: 5004 | BX52: 5713 | BY52: 6218 | BZ52: 6748 | CA52: 7281 | CB52: =CA52+CB18+CB64+'Assumptions (Quarterly)'!F30+'Assumptions (Quarterly)'!F31-CB19+'Assumptions (Quarterly)'!F32 -> 7887.0932 | CC52: =CB52+CC18+CC64+'Assumptions (Quarterly)'!G30+'Assumptions (Quarterly)'!G31-CC19+'Assumptions (Quarterly)'!G32 -> 8622.7848 | CD52: =CC52+CD18+CD64+'Assumptions (Quarterly)'!H30+'Assumptions (Quarterly)'!H31-CD19+'Assumptions (Quarterly)'!H32 -> 9570.2047 | CE52: =CD52+CE18+CE64+'Assumptions (Quarterly)'!I30+'Assumptions (Quarterly)'!I31-CE19+'Assumptions (Quarterly)'!I32 -> 10382.61 | CF52: =CE52+CF18+CF64+'Assumptions (Quarterly)'!J30+'Assumptions (Quarterly)'!J31-CF19+'Assumptions (Quarterly)'!J32 -> 11283.891 | CG52: =CF52+CG18+CG64+'Assumptions (Quarterly)'!K30+'Assumptions (Quarterly)'!K31-CG19+'Assumptions (Quarterly)'!K32 -> 12346.065 | CH52: =CG52+CH18+CH64+'Assumptions (Quarterly)'!L30+'Assumptions (Quarterly)'!L31-CH19+'Assumptions (Quarterly)'!L32 -> 13659.134
A53: Total Liabilities & Equity | B53: =B50+B52 -> -10.263973 | C53: =C50+C52 -> -7.021665 | D53: =D50+D52 -> -2.100666 | E53: =E50+E52 -> 115.45854 | F53: =F50+F52 -> 134.4928 | G53: =G50+G52 -> 137.07657 | H53: =H50+H52 -> 147.41621 | I53: =I50+I52 -> 169.12476 | ... CH53: =CH50+CH52 -> 75858.314
A54: Balance Check (Assets less L&E) | B54: =B40-B53 -> 64.076545 | C54: =C40-C53 -> 64.200264 | D54: =D40-D53 -> 64.323984 | E54: =E40-E53 -> 0 | F54: =F40-F53 -> 0 | G54: =G40-G53 -> 0 | H54: =H40-H53 -> 0 | I54: =I40-I53 -> 0 | ... CH54: =CH40-CH53 -> 0
A56: Memo:
A57: Total Debt | B57: =B44+B47 -> 9.097527 | C57: =C44+C47 -> 9.256076 | D57: =D44+D47 -> 9.415647 | E57: =E44+E47 -> 3.05058 | F57: =F44+F47 -> 9.713227 | G57: =G44+G47 -> 3.628532 | H57: =H44+H47 -> 2.673151 | I57: =I44+I47 -> 18.497771 | ... CH57: =CH44+CH47 -> 17482.871
A58: Net Cash / (Debt) | B58: =B30-B57 -> 4.366156 | C58: =C30-C57 -> 4.870679 | D58: =D30-D57 -> 6.82076 | E58: =E30-E57 -> 59.859017 | F58: =F30-F57 -> 58.264187 | G58: =G30-G57 -> 48.241058 | H58: =H30-H57 -> 46.744229 | I58: =I30-I57 -> 12.39482 | ... CH58: =CH30-CH57 -> 29711.782
A59: Working Capital | B59: =B34-B46 -> 9.458959 | C59: =C34-C46 -> 9.6179 | D59: =D34-D46 -> 7.774298 | E59: =E34-E46 -> 57.053601 | F59: =F34-F46 -> 63.222664 | G59: =G34-G46 -> 48.144939 | H59: =H34-H46 -> 51.929181 | I59: =I34-I46 -> 12.578005 | ... CH59: =CH34-CH46 -> 10661.813
A61: CASH FLOW STATEMENT
A62: Net Income | B62: =B18 -> 1.845086 | C62: =C18 -> 0.994187 | D62: =D18 -> 0.590886 | E62: =E18 -> 2.785474 | F62: =F18 -> 5.322393 | G62: =G18 -> 2.067677 | H62: =H18 -> 2.947095 | I62: =I18 -> 5.875792 | ... CH62: =CH18 -> 1155.9687
A63: Depreciation & Amortization | B63: 0.535833 | C63: 0.534556 | D63: 0.566494 | E63: 0.566868 | F63: 0.639731 | G63: 0.70745 | H63: 0.813252 | I63: 0.955148 | J63: 0.859823 | K63: 0.956491 | L63: 0.988891 | M63: 1.013895 | N63: 0.934475 | O63: 0.946873 | P63: 1.24048 | Q63: 1.406803 | R63: 1.327494 | S63: 1.541143 | T63: 1.764652 | U63: 1.943373 | V63: 2.018907 | W63: 1.966624 | X63: 2.090847 | Y63: 2.354739 | Z63: 2.547083 | AA63: 2.621339 | AB63: 2.834684 | AC63: 3.137368 | AD63: 3.285609 | AE63: 3.519 | AF63: 4.064 | AG63: 4.763 | AH63: 4.601 | AI63: 5.081 | AJ63: 5.889 | AK63: 5.986 | AL63: 6.253 | AM63: 6.252 | AN63: 6.926 | AO63: 7.52 | AP63: 8.324 | AQ63: 9.003 | AR63: 10.08 | AS63: 10.87 | AT63: 10.968 | AU63: 11.084 | AV63: 11.482 | AW63: 11.295 | AX63: 11.931 | AY63: 15.694 | AZ63: 17.281 | BA63: 19.543 | BB63: 20.802 | BC63: 21.55 | BD63: 22.652 | BE63: 28.234 | BF63: 32.564 | BG63: 38 | BH63: 47 | BI63: 52 | BJ63: 67 | BK63: 84 | BL63: 100 | BM63: 97 | BN63: 122 | BO63: 126 | BP63: 128 | BQ63: 135 | BR63: 135 | BS63: 154 | BT63: 154 | BU63: 157 | BV63: 152 | BW63: 172 | BX63: 199 | BY63: 209 | BZ63: 238 | CA63: 246 | CB63: =CB6*'Assumptions (Quarterly)'!F26 -> 264.78914 | CC63: =CC6*'Assumptions (Quarterly)'!G26 -> 293.18477 | CD63: =CD6*'Assumptions (Quarterly)'!H26 -> 337.98964 | CE63: =CE6*'Assumptions (Quarterly)'!I26 -> 333.51856 | CF63: =CF6*'Assumptions (Quarterly)'!J26 -> 336.2124 | CG63: =CG6*'Assumptions (Quarterly)'!K26 -> 378.76171 | CH63: =CH6*'Assumptions (Quarterly)'!L26 -> 428.45394
A64: Share-Based Compensation | B64: 0.009856 | C64: 0.005725 | D64: 0.007823 | E64: 0.008863 | F64: 0.009032 | G64: 0.021299 | H64: 0.027477 | I64: 0.389054 | J64: 0.511752 | K64: 0.22262 | L64: 1.252874 | M64: -0.258337 | N64: 0.783126 | O64: 0.345872 | P64: 1.207607 | Q64: 1.283056 | R64: 0.680471 | S64: 1.17071 | T64: 1.132832 | U64: 0.223952 | V64: 1.551771 | W64: 1.849633 | X64: 0.353209 | Y64: 1.135526 | Z64: 1.104454 | AA64: 1.710752 | AB64: 2.586791 | AC64: 5.699671 | AD64: 1.647786 | AE64: 0 | AF64: 0 | AG64: 0 | AH64: 11.852 | AI64: 3.327 | AJ64: 5.136 | AK64: -0.431 | AL64: 2.181 | AM64: 3.19 | AN64: 6.936 | AO64: 9.125 | AP64: 3.732 | AQ64: 9.176 | AR64: 12.892 | AS64: 6.666 | AT64: 6.985 | AU64: 15.737 | AV64: 1.055 | AW64: 10.914 | AX64: -0.181 | AY64: 13.441 | AZ64: 18.767 | BA64: 16.319 | BB64: 3.53 | BC64: 15.843 | BD64: 36.43 | BE64: 23.417 | BF64: 55.31 | BG64: 22 | BH64: 29 | BI64: 33 | BJ64: 5 | BK64: 30 | BL64: 5 | BM64: 25 | BN64: 24 | BO64: 47 | BP64: 36 | BQ64: 39 | BR64: 45 | BS64: 68 | BT64: 59 | BU64: 83 | BV64: 51 | BW64: 92 | BX64: 96 | BY64: 64 | BZ64: 51 | CA64: 96 | CB64: =CB6*'Assumptions (Quarterly)'!F27 -> 100.43726 | CC64: =CC6*'Assumptions (Quarterly)'!G27 -> 111.20802 | CD64: =CD6*'Assumptions (Quarterly)'!H27 -> 128.20297 | CE64: =CE6*'Assumptions (Quarterly)'!I27 -> 126.50704 | CF64: =CF6*'Assumptions (Quarterly)'!J27 -> 127.52884 | CG64: =CG6*'Assumptions (Quarterly)'!K27 -> 138.87929 | CH64: =CH6*'Assumptions (Quarterly)'!L27 -> 157.09978
A65: Other Operating Activities | B65: 0.106856 | C65: 0.977798 | D65: 1.852786 | E65: -0.787294 | F65: -6.467341 | G65: 4.102245 | H65: -4.118901 | I65: 2.400382 | J65: 30.298535 | K65: -1.717406 | L65: -0.747974 | M65: 3.329422 | N65: 9.734116 | O65: 0.541202 | P65: 0.515172 | Q65: -5.582932 | R65: 7.959335 | S65: -1.60051 | T65: 0.845027 | U65: 0.098108 | V65: 1.955615 | W65: -4.464685 | X65: 11.67936 | Y65: -4.31401 | Z65: 22.341309 | AA65: 8.279153 | AB65: -6.329849 | AC65: 25.565475 | AD65: -26.032338 | AE65: -6.155 | AF65: 81.81 | AG65: 12.003 | AH65: 7.755 | AI65: 28.05 | AJ65: 28.164 | AK65: -36.747 | AL65: 62.692 | AM65: -51.491 | AN65: 26.937 | AO65: 47.27 | AP65: -20.828 | AQ65: 38.06 | AR65: 93.269 | AS65: -29.127 | AT65: 76.388 | AU65: -50.908 | AV65: 142.875 | AW65: 76.816 | AX65: 25.392 | AY65: 97.372 | AZ65: -24.711 | BA65: 317.112 | BB65: 107.94 | BC65: -101.935 | BD65: 535.307 | BE65: 294.624 | BF65: 219.004 | BG65: -291 | BH65: 120 | BI65: 85 | BJ65: 675 | BK65: -412 | BL65: 679 | BM65: 473 | BN65: 1231 | BO65: 485 | BP65: 986 | BQ65: 408 | BR65: 1583 | BS65: 946 | BT65: 1138 | BU65: 963 | BV65: 2082 | BW65: 273 | BX65: 2099 | BY65: 2265 | BZ65: 4361 | CA65: 1316 | CB65: =-(CB31-CA31)-(CB32-CA32)-(CB33-CA33)+(CB42-CA42)+(CB45-CA45)+(CB48-CA48)-(CB38-CA38) -> 517.07672 | CC65: =-(CC31-CB31)-(CC32-CB32)-(CC33-CB33)+(CC42-CB42)+(CC45-CB45)+(CC48-CB48)-(CC38-CB38) -> 1858.9348 | CD65: =-(CD31-CC31)-(CD32-CC32)-(CD33-CC33)+(CD42-CC42)+(CD45-CC45)+(CD48-CC48)-(CD38-CC38) -> 2551.7932 | CE65: =-(CE31-CD31)-(CE32-CD32)-(CE33-CD33)+(CE42-CD42)+(CE45-CD45)+(CE48-CD48)-(CE38-CD38) -> -170.70908 | CF65: =-(CF31-CE31)-(CF32-CE32)-(CF33-CE33)+(CF42-CE42)+(CF45-CE45)+(CF48-CE48)-(CF38-CE38) -> 390.90036 | CG65: =-(CG31-CF31)-(CG32-CF32)-(CG33-CF33)+(CG42-CF42)+(CG45-CF45)+(CG48-CF48)-(CG38-CF38) -> 2039.688 | CH65: =-(CH31-CG31)-(CH32-CG32)-(CH33-CG33)+(CH42-CG42)+(CH45-CG45)+(CH48-CG48)-(CH38-CG38) -> 2787.7717
A66: Operating Cash Flow | B66: =B62+B63+B64+B65 -> 2.497631 | C66: =C62+C63+C64+C65 -> 2.512266 | D66: =D62+D63+D64+D65 -> 3.017989 | E66: =E62+E63+E64+E65 -> 2.573911 | F66: =F62+F63+F64+F65 -> -0.496185 | G66: =G62+G63+G64+G65 -> 6.898671 | H66: =H62+H63+H64+H65 -> -0.331077 | I66: =I62+I63+I64+I65 -> 9.620376 | ... CH66: =CH62+CH63+CH64+CH65 -> 4529.2942
A68: Capital Expenditures | B68: -0.673613 | C68: -0.574291 | D68: -1.367898 | E68: -0.119288 | F68: -0.997336 | G68: -1.139166 | H68: -1.536199 | I68: -1.193944 | J68: -1.035682 | K68: -1.720008 | L68: -0.46235 | M68: -0.767465 | N68: -0.848347 | O68: -1.396672 | P68: -2.509615 | Q68: -6.648695 | R68: -2.659061 | S68: -2.886154 | T68: -10.361262 | U68: -3.836981 | V68: -1.839764 | W68: -3.696281 | X68: -4.627624 | Y68: -3.358934 | Z68: -5.064907 | AA68: -2.861295 | AB68: -35.232028 | AC68: -38.002593 | AD68: -37.660084 | AE68: -6.966 | AF68: -7.668 | AG68: -9.812 | AH68: -9.98 | AI68: -7.315 | AJ68: -16.463 | AK68: -13.064 | AL68: -25.688 | AM68: -15.424 | AN68: -22.129 | AO68: -24.086 | AP68: -15.3 | AQ68: -12.773 | AR68: -21.725 | AS68: -17.559 | AT68: -22.794 | AU68: -22.932 | AV68: -23.586 | AW68: -23.041 | AX68: -28.003 | AY68: -32.928 | AZ68: -38.433 | BA68: -29.371 | BB68: -36.066 | BC68: -45.175 | BD68: -49.659 | BE68: -64.689 | BF68: -87.477 | BG68: -113 | BH68: -150 | BI68: -162 | BJ68: -148 | BK68: -137 | BL68: -99 | BM68: -106 | BN68: -113 | BO68: -89 | BP68: -114 | BQ68: -126 | BR68: -180 | BS68: -148 | BT68: -184 | BU68: -223 | BV68: -305 | BW68: -272 | BX68: -287 | BY68: -357 | BZ68: -427 | CA68: -271 | CB68: =-CB6*'Assumptions (Quarterly)'!F28 -> -410.8797 | CC68: =-CC6*'Assumptions (Quarterly)'!G28 -> -454.94189 | CD68: =-CD6*'Assumptions (Quarterly)'!H28 -> -512.81186 | CE68: =-CE6*'Assumptions (Quarterly)'!I28 -> -506.02816 | CF68: =-CF6*'Assumptions (Quarterly)'!J28 -> -498.52184 | CG68: =-CG6*'Assumptions (Quarterly)'!K28 -> -542.89179 | CH68: =-CH6*'Assumptions (Quarterly)'!L28 -> -599.83552
A69: Acquisitions | B69: 0 | C69: 0 | D69: 0 | E69: 0 | F69: 0 | G69: -16.824065 | H69: 0 | I69: -22.354384 | J69: -0.003024 | K69: 0 | L69: 0 | M69: 0 | N69: 0 | O69: 0 | P69: 0 | Q69: 0 | R69: 0 | S69: 0 | T69: 0 | U69: -5.46818 | V69: 0 | W69: 0 | X69: 0 | Y69: 0 | Z69: 0 | AA69: -3.224162 | AB69: 0 | AC69: 0 | AD69: -0.198838 | AE69: 0 | AF69: -32.127 | AG69: 0 | AH69: -8.687 | AI69: 0 | AJ69: -45.009 | AK69: 0 | AL69: 0 | AM69: -1.838 | AN69: -5.446 | AO69: 0 | AP69: 0 | AQ69: 0 | AR69: 0 | AS69: 0 | AT69: -35.798 | AU69: 0 | AV69: 0 | AW69: -2.281 | AX69: -1.914 | AY69: 0 | AZ69: 0 | BA69: 0 | BB69: 0 | BC69: -7.561 | BD69: 0.624 | BE69: 0 | BF69: -0.063 | BG69: 0 | BH69: 0 | BI69: -5 | BJ69: -51 | BK69: 0 | BL69: 0 | BM69: 0 | BN69: 0 | BO69: 0 | BP69: 0 | BQ69: 0 | BR69: 0 | BS69: 0 | BT69: 0 | BU69: 0 | BV69: -6 | BW69: 0 | BX69: 0 | BY69: 0 | BZ69: 0 | CA69: 0 | CB69: ='Assumptions (Quarterly)'!F29 -> 0 | CC69: ='Assumptions (Quarterly)'!G29 -> 0 | CD69: ='Assumptions (Quarterly)'!H29 -> 0 | CE69: ='Assumptions (Quarterly)'!I29 -> 0 | CF69: ='Assumptions (Quarterly)'!J29 -> 0 | CG69: ='Assumptions (Quarterly)'!K29 -> 0 | CH69: ='Assumptions (Quarterly)'!L29 -> 0
A70: Change in Investments | B70: 0.115531 | C70: -2.669171 | D70: 0.913499 | E70: -40.549478 | F70: -4.041538 | G70: 14.977998 | H70: 6.669243 | I70: 9.331976 | J70: -25.693054 | K70: -2.795175 | L70: -3.215991 | M70: 8.398758 | N70: -0.720016 | O70: -21.630901 | P70: -15.761137 | Q70: 3.199174 | R70: -11.010664 | S70: -18.246195 | T70: -11.655533 | U70: 0.861168 | V70: -13.168809 | W70: -3.075129 | X70: -15.461008 | Y70: -5.767068 | Z70: -42.180577 | AA70: 9.891804 | AB70: 27.520612 | AC70: -36.468588 | AD70: 37.905172 | AE70: -7.035 | AF70: -21.27 | AG70: -186.213 | AH70: -31.776 | AI70: 11.566 | AJ70: -36.144 | AK70: 13.073 | AL70: -62.748 | AM70: 18.05 | AN70: -11.809 | AO70: -29.183 | AP70: 23.353 | AQ70: -26.357 | AR70: 19.858 | AS70: 150.458 | AT70: -55.918 | AU70: -1.068 | AV70: 76.7 | AW70: 18.572 | AX70: -664.714 | AY70: -1227.123 | AZ70: -116.428 | BA70: 170.94 | BB70: -138.309 | BC70: -97.253 | BD70: -348.917 | BE70: -225.407 | BF70: 673.577 | BG70: 23 | BH70: 4 | BI70: -455 | BJ70: -504 | BK70: -1087 | BL70: -1237 | BM70: -558 | BN70: -534 | BO70: -449 | BP70: -554 | BQ70: -1204 | BR70: -734 | BS70: -1318 | BT70: -1901 | BU70: -2385 | BV70: -1817 | BW70: -1570 | BX70: -938 | BY70: -754 | BZ70: -1649 | CA70: -1200 | CB70: =-((CB29-CA29)+(CB36-CA36)) -> -423.5542 | CC70: =-((CC29-CB29)+(CC36-CB36)) -> -1197.2163 | CD70: =-((CD29-CC29)+(CD36-CC36)) -> -1562.4156 | CE70: =-((CE29-CD29)+(CE36-CD36)) -> 139.52934 | CF70: =-((CF29-CE29)+(CF36-CE36)) -> 48.691445 | CG70: =-((CG29-CF29)+(CG36-CF36)) -> -1132.2531 | CH70: =-((CH29-CG29)+(CH36-CG36)) -> -1867.0183
A71: Other Investing Activities | B71: -0.087575 | C71: -0.021027 | D71: 0.000848 | E71: -0.027282 | F71: 0.018713 | G71: -0.007344 | H71: -0.051754 | I71: 0.00086 | J71: 0 | K71: -0.918479 | L71: -0.034685 | M71: 0.006664 | N71: -0.009179 | O71: -0.012865 | P71: 0.000132 | Q71: -5.5e-05 | R71: -0.403662 | S71: -0.073405 | T71: -0.035418 | U71: -0.010439 | V71: -0.161444 | W71: -0.031508 | X71: -1.35923 | Y71: 0.048949 | Z71: -0.048865 | AA71: 0 | AB71: -0.012657 | AC71: 0.012657 | AD71: -0.459 | AE71: -0.144 | AF71: -1.807 | AG71: 1.408 | AH71: -0.314 | AI71: -0.942 | AJ71: -0.425 | AK71: -0.135 | AL71: -0.244 | AM71: -0.011 | AN71: -0.038 | AO71: 0 | AP71: -0.382 | AQ71: -0.017 | AR71: -0.057 | AS71: -0.01 | AT71: 0.051 | AU71: -0.097 | AV71: -0.145 | AW71: 0.025 | AX71: 0.025 | AY71: -0.034 | AZ71: 0 | BA71: -0.016 | BB71: -0.022 | BC71: -0.093 | BD71: 0.006 | BE71: -0.006 | BF71: 0.093 | BG71: -8 | BH71: -12 | BI71: -9 | BJ71: -7 | BK71: 0 | BL71: -1 | BM71: 0 | BN71: 1 | BO71: 0 | BP71: 0 | BQ71: 0 | BR71: 0 | BS71: 0 | BT71: 0 | BU71: 0 | BV71: 0 | BW71: 0 | BX71: 0 | BY71: 0 | BZ71: 75 | CA71: 0 | CB71: 0 | CC71: 0 | CD71: 0 | CE71: 0 | CF71: 0 | CG71: 0 | CH71: 0
A72: Investing Cash Flow | B72: =B68+B69+B70+B71 -> -0.645657 | C72: =C68+C69+C70+C71 -> -3.264489 | D72: =D68+D69+D70+D71 -> -0.453551 | E72: =E68+E69+E70+E71 -> -40.696048 | F72: =F68+F69+F70+F71 -> -5.020161 | G72: =G68+G69+G70+G71 -> -2.992577 | H72: =H68+H69+H70+H71 -> 5.08129 | I72: =I68+I69+I70+I71 -> -14.215492 | ... CH72: =CH68+CH69+CH70+CH71 -> -2466.8538
A74: Dividends Paid | B74: 0 | C74: 0 | D74: 0 | E74: 0 | F74: 0 | G74: 0 | H74: 0 | I74: 0 | J74: 0 | K74: 0 | L74: 0 | M74: 0 | N74: 0 | O74: 0 | P74: 0 | Q74: 0 | R74: 0 | S74: 0 | T74: -3.53051 | U74: -3.531337 | V74: -3.531359 | W74: -3.531362 | X74: -4.812036 | Y74: -4.81204 | Z74: -4.812566 | AA74: -4.812396 | AB74: -6.313869 | AC74: -6.31387 | AD74: -6.313865 | AE74: -6.314 | AF74: -7.329 | AG74: -7.294 | AH74: -7.366 | AI74: -7.33 | AJ74: -4.548 | AK74: -4.548 | AL74: -4.548 | AM74: -4.548 | AN74: -6.624 | AO74: -6.623 | AP74: -6.624 | AQ74: -6.624 | AR74: -6.623 | AS74: -6.624 | AT74: -6.625 | AU74: -6.624 | AV74: 0 | AW74: 0 | AX74: 0 | AY74: 0 | AZ74: 0 | BA74: 0 | BB74: 0 | BC74: 0 | BD74: 0 | BE74: 0 | BF74: 0 | BG74: 0 | BH74: 0 | BI74: 0 | BJ74: 0 | BK74: 0 | BL74: 0 | BM74: 0 | BN74: 0 | BO74: 0 | BP74: 0 | BQ74: 0 | BR74: 0 | BS74: 0 | BT74: 0 | BU74: 0 | BV74: 0 | BW74: 0 | BX74: 0 | BY74: 0 | BZ74: 0 | CA74: 0 | CB74: ='Assumptions (Quarterly)'!F31 -> 0 | CC74: ='Assumptions (Quarterly)'!G31 -> 0 | CD74: ='Assumptions (Quarterly)'!H31 -> 0 | CE74: ='Assumptions (Quarterly)'!I31 -> 0 | CF74: ='Assumptions (Quarterly)'!J31 -> 0 | CG74: ='Assumptions (Quarterly)'!K31 -> 0 | CH74: ='Assumptions (Quarterly)'!L31 -> 0
A75: Share Issuance / (Repurchase) | B75: 0.000709 | C75: 5e-05 | D75: 0.022838 | E75: 49.58893 | F75: -3e-06 | G75: 0.004502 | H75: 0.058352 | I75: 0.002005 | J75: -2.579993 | K75: 3e-06 | L75: 0.004001 | M75: 0.018526 | N75: 0.005824 | O75: 0.00197 | P75: 0.003479 | Q75: 0.01275 | R75: 0 | S75: 0.000885 | T75: 0.009821 | U75: 0.000469 | V75: 0 | W75: 0 | X75: 0.0024 | Y75: 0.0033 | Z75: 0 | AA75: 0.00302 | AB75: -1.012216 | AC75: 0 | AD75: 0.000196 | AE75: 0 | AF75: -1.944 | AG75: 0 | AH75: 0 | AI75: 0 | AJ75: -2.714 | AK75: 0 | AL75: 0 | AM75: 0 | AN75: 0 | AO75: 0 | AP75: 0 | AQ75: 0 | AR75: 0 | AS75: 0 | AT75: 0 | AU75: 0 | AV75: 0 | AW75: 0 | AX75: 0 | AY75: 1866.5 | AZ75: 0.715 | BA75: -0.72 | BB75: 0 | BC75: 0 | BD75: -0.72 | BE75: -38.951 | BF75: -14.329 | BG75: -25 | BH75: -117 | BI75: -298 | BJ75: 1474 | BK75: -39 | BL75: -35 | BM75: -41 | BN75: -33 | BO75: -61 | BP75: -146 | BQ75: -149 | BR75: 0 | BS75: 0 | BT75: -1 | BU75: 0 | BV75: 0 | BW75: 0 | BX75: 0 | BY75: -1 | BZ75: 0 | CA75: 0 | CB75: ='Assumptions (Quarterly)'!F30 -> 0 | CC75: ='Assumptions (Quarterly)'!G30 -> 0 | CD75: ='Assumptions (Quarterly)'!H30 -> 0 | CE75: ='Assumptions (Quarterly)'!I30 -> 0 | CF75: ='Assumptions (Quarterly)'!J30 -> 0 | CG75: ='Assumptions (Quarterly)'!K30 -> 0 | CH75: ='Assumptions (Quarterly)'!L30 -> 0
A76: Debt Issued / (Repaid) | B76: -3.003969 | C76: 0.00105 | D76: 0.00032 | E76: -6.20032 | F76: 6.082054 | G76: -6.207947 | H76: -1.416402 | I76: -2.100371 | J76: 0.587497 | K76: -0.057175 | L76: -3.13653 | M76: -9.119456 | N76: -2.997473 | O76: -3.213878 | P76: 0.219893 | Q76: 0.095283 | R76: -0.101298 | S76: 0 | T76: 0 | U76: 0 | V76: 0 | W76: 0 | X76: 0 | Y76: 0 | Z76: 0 | AA76: 0 | AB76: 0 | AC76: 13.523158 | AD76: 1.993842 | AE76: -0.582 | AF76: 327.856 | AG76: -0.583 | AH76: -4.395 | AI76: -0.139 | AJ76: -4.299 | AK76: 4.831 | AL76: -4.419 | AM76: -0.661 | AN76: -5.638 | AO76: 3.699 | AP76: 7.351 | AQ76: 1.415 | AR76: 3.416 | AS76: 4.018 | AT76: -33.256 | AU76: 76.342 | AV76: 55.431 | AW76: 599.177 | AX76: -99.18 | AY76: 9.499 | AZ76: 29.979 | BA76: 26.622 | BB76: -7.427 | BC76: 155.556 | BD76: 270.762 | BE76: 45.494 | BF76: -172.812 | BG76: -733 | BH76: 220 | BI76: 720 | BJ76: 684 | BK76: 191 | BL76: 469 | BM76: 383 | BN76: 21 | BO76: -51 | BP76: -214 | BQ76: 281 | BR76: 73 | BS76: 0 | BT76: 477 | BU76: 726 | BV76: 757 | BW76: 465 | BX76: 613 | BY76: 445 | BZ76: 1382 | CA76: 473 | CB76: =(CB95+CB47)-(CA44+CA47) -> 412.94664 | CC76: =(CC95+CC47)-(CB95+CB47) -> 877.89785 | CD76: =(CD95+CD47)-(CC95+CC47) -> 1256.2676 | CE76: =(CE95+CE47)-(CD95+CD47) -> 117.26544 | CF76: =(CF95+CF47)-(CE95+CE47) -> 285.38961 | CG76: =(CG95+CG47)-(CF95+CF47) -> 906.21386 | CH76: =(CH95+CH47)-(CG95+CG47) -> 1281.89
A77: Other Financing Activities | B77: 0 | C77: 0 | D77: 0 | E77: 0.749991 | F77: 0 | G77: 0 | H77: 0 | I77: 0 | J77: 0 | K77: 0 | L77: 0 | M77: 0 | N77: 0 | O77: 0 | P77: 0 | Q77: 0 | R77: 0 | S77: 0 | T77: 0 | U77: 0 | V77: 0 | W77: 0 | X77: 0 | Y77: 0 | Z77: 0 | AA77: 0 | AB77: 0 | AC77: 0 | AD77: 0 | AE77: 0 | AF77: -27.093 | AG77: -0.659 | AH77: 0 | AI77: 0 | AJ77: 0 | AK77: 0 | AL77: 0 | AM77: 0 | AN77: 0 | AO77: 0 | AP77: 0 | AQ77: 0 | AR77: 0 | AS77: -67.308 | AT77: 67.308 | AU77: -45.692 | AV77: 0 | AW77: -108.048 | AX77: 137.476 | AY77: 98.688 | AZ77: -89.206 | BA77: -1 | BB77: 87.362 | BC77: -1 | BD77: -105.095 | BE77: -83.682 | BF77: 186.777 | BG77: -101 | BH77: 0 | BI77: 0 | BJ77: 101 | BK77: 0 | BL77: 0 | BM77: 0 | BN77: 0 | BO77: 0 | BP77: 0 | BQ77: 0 | BR77: 0 | BS77: 0 | BT77: 0 | BU77: 0 | BV77: 0 | BW77: 0 | BX77: 0 | BY77: 0 | BZ77: 0 | CA77: 0 | CB77: =CB91 -> 0 | CC77: =CC91 -> 0 | CD77: =CD91 -> 0 | CE77: =CE91 -> 0 | CF77: =CF91 -> 0 | CG77: =CG91 -> 0 | CH77: =CH91 -> 0
A78: Financing Cash Flow | B78: =B74+B75+B76+B77 -> -3.00326 | C78: =C74+C75+C76+C77 -> 0.0011 | D78: =D74+D75+D76+D77 -> 0.023158 | E78: =E74+E75+E76+E77 -> 44.138601 | F78: =F74+F75+F76+F77 -> 6.082051 | G78: =G74+G75+G76+G77 -> -6.203445 | H78: =H74+H75+H76+H77 -> -1.35805 | I78: =I74+I75+I76+I77 -> -2.098366 | ... CH78: =CH74+CH75+CH76+CH77 -> 1281.89
A80: Effect of FX on Cash & Other | B80: 0.062932 | C80: -0.001741 | D80: 0.117171 | E80: -0.575414 | F80: 0.575722 | G80: 0.567871 | H80: 0.334166 | I80: -0.577189 | J80: -3.796424 | K80: 0.17015 | L80: 1.040577 | M80: 1.48333 | N80: -1.6972 | O80: -0.371305 | P80: 0.344447 | Q80: 0.326833 | R80: 0.646458 | S80: 0.173684 | T80: 0.291439 | U80: -1.742773 | V80: -0.132323 | W80: -0.158641 | X80: -1.524318 | Y80: -0.757433 | Z80: -0.759186 | AA80: -8.410089 | AB80: -4.996143 | AC80: 0.468195 | AD80: -2.743963 | AE80: -15.732 | AF80: -34.516 | AG80: 4.604 | AH80: -10.196 | AI80: -37.395 | AJ80: 1.573 | AK80: -11.972 | AL80: -18.587 | AM80: -5.762 | AN80: -5.842 | AO80: -2.655 | AP80: -4.83 | AQ80: 6.847 | AR80: -35.023 | AS80: -0.643 | AT80: -12.527 | AU80: -0.772 | AV80: -78.96 | AW80: -19.632 | AX80: 8.469 | AY80: -11.407 | AZ80: 7.88 | BA80: -44.704 | BB80: 10.647 | BC80: -104.864 | BD80: -19.362 | BE80: -33.298 | BF80: 42.524 | BG80: -98 | BH80: 34 | BI80: -64 | BJ80: -25 | BK80: 71 | BL80: -165 | BM80: -127 | BN80: -49 | BO80: -48 | BP80: -84 | BQ80: -311 | BR80: -495 | BS80: -76 | BT80: -268 | BU80: -63 | BV80: -332 | BW80: 145 | BX80: 85 | BY80: 19 | BZ80: -252 | CA80: 527 | CB80: ='Assumptions (Quarterly)'!F32 -> 0 | CC80: ='Assumptions (Quarterly)'!G32 -> 0 | CD80: ='Assumptions (Quarterly)'!H32 -> 0 | CE80: ='Assumptions (Quarterly)'!I32 -> 0 | CF80: ='Assumptions (Quarterly)'!J32 -> 0 | CG80: ='Assumptions (Quarterly)'!K32 -> 0 | CH80: ='Assumptions (Quarterly)'!L32 -> 0
A81: Net Change in Cash | B81: =B66+B72+B78+B80 -> -1.088354 | C81: =C66+C72+C78+C80 -> -0.752864 | D81: =D66+D72+D78+D80 -> 2.704767 | E81: =E66+E72+E78+E80 -> 5.44105 | F81: =F66+F72+F78+F80 -> 1.141427 | G81: =G66+G72+G78+G80 -> -1.72948 | H81: =H66+H72+H78+H80 -> 3.726329 | I81: =I66+I72+I78+I80 -> -7.270671 | ... CH81: =CH66+CH72+CH78+CH80 -> 3344.3303
A83: Memo:
A84: Free Cash Flow | B84: =B66+B68 -> 1.824018 | C84: =C66+C68 -> 1.937975 | D84: =D66+D68 -> 1.650091 | E84: =E66+E68 -> 2.454623 | F84: =F66+F68 -> -1.493521 | G84: =G66+G68 -> 5.759505 | H84: =H66+H68 -> -1.867276 | I84: =I66+I68 -> 8.426432 | ... CH84: =CH66+CH68 -> 3929.4587
A85: FCF YoY Growth % | F85: =F84/B84-1 -> -1.8188083 | G85: =G84/C84-1 -> 1.9719191 | H85: =H84/D84-1 -> -2.13162 | I85: =I84/E84-1 -> 2.4328824 | J85: =J84/F84-1 -> -26.815188 | K85: =K84/G84-1 -> -0.45605169 | L85: =L84/H84-1 -> -5.1296627 | M85: =M84/I84-1 -> 0.56291334 | ... CA85: =CA84/BW84-1 -> 1.3768116 | CB85: =CB84/CA84-1 -> -0.45838172 | CC85: =CC84/CB84-1 -> 1.4899403 | CD85: =CD84/CC84-1 -> 0.36644864 | CE85: =CE84/CD84-1 -> -0.85886542 | CF85: =CF84/CE84-1 -> 1.4081511 | CG85: =CG84/CF84-1 -> 1.6000573 | CH85: =CH84/CG84-1 -> 0.33758242
A87: LIQUIDITY & REVOLVER
A88: Beginning cash | CB88: =CA28 -> 15141 | CC88: =CB28 -> 16107.472 | CD88: =CC28 -> 18221.023 | CE88: =CD28 -> 21239.266 | CF88: =CE28 -> 21965.247 | CG88: =CF28 -> 23429.2 | CH88: =CG28 -> 26140.893
A89: Cash flow before revolver | CB89: =CB88+CB66+CB72+CB74+CB75+CB76+CB80 -> 16107.472 | CC89: =CC88+CC66+CC72+CC74+CC75+CC76+CC80 -> 18221.023 | CD89: =CD88+CD66+CD72+CD74+CD75+CD76+CD80 -> 21239.266 | CE89: =CE88+CE66+CE72+CE74+CE75+CE76+CE80 -> 21965.247 | CF89: =CF88+CF66+CF72+CF74+CF75+CF76+CF80 -> 23429.2 | CG89: =CG88+CG66+CG72+CG74+CG75+CG76+CG80 -> 26140.893 | CH89: =CH88+CH66+CH72+CH74+CH75+CH76+CH80 -> 29485.223
A90: Minimum cash balance | CB90: ='Assumptions (Quarterly)'!F24 -> 2000 | CC90: ='Assumptions (Quarterly)'!G24 -> 2000 | CD90: ='Assumptions (Quarterly)'!H24 -> 2000 | CE90: ='Assumptions (Quarterly)'!I24 -> 2000 | CF90: ='Assumptions (Quarterly)'!J24 -> 2000 | CG90: ='Assumptions (Quarterly)'!K24 -> 2000 | CH90: ='Assumptions (Quarterly)'!L24 -> 2000
A91: Revolver draw / (paydown) | CB91: =IF(CB89<CB90,CB90-CB89,-MIN(CB92,CB89-CB90)) -> 0 | CC91: =IF(CC89<CC90,CC90-CC89,-MIN(CC92,CC89-CC90)) -> 0 | CD91: =IF(CD89<CD90,CD90-CD89,-MIN(CD92,CD89-CD90)) -> 0 | CE91: =IF(CE89<CE90,CE90-CE89,-MIN(CE92,CE89-CE90)) -> 0 | CF91: =IF(CF89<CF90,CF90-CF89,-MIN(CF92,CF89-CF90)) -> 0 | CG91: =IF(CG89<CG90,CG90-CG89,-MIN(CG92,CG89-CG90)) -> 0 | CH91: =IF(CH89<CH90,CH90-CH89,-MIN(CH92,CH89-CH90)) -> 0
A92: Revolver balance, beginning | CB92: =0 -> 0 | CC92: =CB93 -> 0 | CD92: =CC93 -> 0 | CE92: =CD93 -> 0 | CF92: =CE93 -> 0 | CG92: =CF93 -> 0 | CH92: =CG93 -> 0
A93: Revolver balance, ending | CB93: =CB92+CB91 -> 0 | CC93: =CC92+CC91 -> 0 | CD93: =CD92+CD91 -> 0 | CE93: =CE92+CE91 -> 0 | CF93: =CF92+CF91 -> 0 | CG93: =CG92+CG91 -> 0 | CH93: =CH92+CH91 -> 0
A94: Revolver interest (memo) | CB94: ='Assumptions (Quarterly)'!F23*CB92 -> 0 | CC94: ='Assumptions (Quarterly)'!G23*CC92 -> 0 | CD94: ='Assumptions (Quarterly)'!H23*CD92 -> 0 | CE94: ='Assumptions (Quarterly)'!I23*CE92 -> 0 | CF94: ='Assumptions (Quarterly)'!J23*CF92 -> 0 | CG94: ='Assumptions (Quarterly)'!K23*CG92 -> 0 | CH94: ='Assumptions (Quarterly)'!L23*CH92 -> 0
A95: Current debt - term (ex-revolver) | CB95: =CB6*'Assumptions (Quarterly)'!F41 -> 5971.4516 | CC95: =CC6*'Assumptions (Quarterly)'!G41 -> 6611.8222 | CD95: =CD6*'Assumptions (Quarterly)'!H41 -> 7622.249 | CE95: =CE6*'Assumptions (Quarterly)'!I41 -> 7521.4186 | CF95: =CF6*'Assumptions (Quarterly)'!J41 -> 7582.1694 | CG95: =CG6*'Assumptions (Quarterly)'!K41 -> 8257.0053 | CH95: =CH6*'Assumptions (Quarterly)'!L41 -> 9340.2959

Sheet Assumptions (Annual)
A1: MercadoLibre (MELI) | Forecast Assumptions - Annual
A2: Revenue is KPI-driven. Active case (C:G) pulls the Probable scenario. Possible / Plausible / Probable matrix at H:W. $ in millions.
A3: Driver / KPI | B3: 2025A | C3: 2026E | D3: 2027E | E3: 2028E | F3: 2029E | G3: 2030E
A4: KPI / REVENUE BUILD
A5: Unique active buyers (mn) | B5: 121 | C5: =B5*(1+C6) -> 150.04 | D5: =C5*(1+D6) -> 177.0472 | E5: =D5*(1+E6) -> 201.83381 | F5: =E5*(1+F6) -> 224.03553 | G5: =F5*(1+G6) -> 244.19872
A6: active buyer growth % | C6: =D65 -> 0.24 | D6: =G65 -> 0.18 | E6: =J65 -> 0.14 | F6: =M65 -> 0.11 | G6: =P65 -> 0.09
A7: GMV per active buyer ($) | B7: 537 | C7: =B7*(1+C8) -> 579.96 | D7: =C7*(1+D8) -> 620.5572 | E7: =D7*(1+E8) -> 657.79063 | F7: =E7*(1+F8) -> 690.68016 | G7: =F7*(1+G8) -> 718.30737
A8: GMV per buyer growth % | C8: =D67 -> 0.08 | D8: =G67 -> 0.07 | E8: =J67 -> 0.06 | F8: =M67 -> 0.05 | G8: =P67 -> 0.04
A9: GMV ($mm) | B9: =B5*B7 -> 64977 | C9: =C5*C7 -> 87017.198 | D9: =D5*D7 -> 109867.91 | E9: =E5*E7 -> 132764.39 | F9: =F5*F7 -> 154736.89 | G9: =G5*G7 -> 175409.74
A10: GMV growth % (memo) | C10: =C9/B9-1 -> 0.3392 | D10: =D9/C9-1 -> 0.2626 | E10: =E9/D9-1 -> 0.2084 | F10: =F9/E9-1 -> 0.1655 | G10: =G9/F9-1 -> 0.1336
A11: Commerce take rate % | B11: 0.249 | C11: =D70 -> 0.252 | D11: =G70 -> 0.254 | E11: =J70 -> 0.256 | F11: =M70 -> 0.258 | G11: =P70 -> 0.26
A12: Commerce revenue ($mm) | B12: =B9*B11 -> 16179.273 | C12: =C9*C11 -> 21928.334 | D12: =D9*D11 -> 27906.45 | E12: =E9*E11 -> 33987.683 | F12: =F9*F11 -> 39922.119 | G12: =G9*G11 -> 45606.533
A13: Fintech MAUs (mn) | B13: 78 | C13: =B13*(1+C14) -> 96.72 | D13: =C13*(1+D14) -> 114.1296 | E13: =D13*(1+E14) -> 130.10774 | F13: =E13*(1+F14) -> 144.4196 | G13: =F13*(1+G14) -> 157.41736
A14: MAU growth % | C14: =D73 -> 0.24 | D14: =G73 -> 0.18 | E14: =J73 -> 0.14 | F14: =M73 -> 0.11 | G14: =P73 -> 0.09
A15: TPV per MAU ($) | B15: 3562 | C15: =B15*(1+C16) -> 4060.68 | D15: =C15*(1+D16) -> 4466.748 | E15: =D15*(1+E16) -> 4824.0878 | F15: =E15*(1+F16) -> 5113.5331 | G15: =F15*(1+G16) -> 5369.2098
A16: TPV per MAU growth % | C16: =D75 -> 0.14 | D16: =G75 -> 0.1 | E16: =J75 -> 0.08 | F16: =M75 -> 0.06 | G16: =P75 -> 0.05
A17: TPV ($mm) | B17: =B13*B15 -> 277836 | C17: =C13*C15 -> 392748.97 | D17: =D13*D15 -> 509788.16 | E17: =E13*E15 -> 627651.19 | F17: =F13*F15 -> 738494.39 | G17: =G13*G15 -> 845206.82
A18: TPV growth % (memo) | C18: =C17/B17-1 -> 0.4136 | D18: =D17/C17-1 -> 0.298 | E18: =E17/D17-1 -> 0.2312 | F18: =F17/E17-1 -> 0.1766 | G18: =G17/F17-1 -> 0.1445
A19: Fintech take rate % | B19: 0.0454 | C19: =D78 -> 0.0458 | D19: =G78 -> 0.0462 | E19: =J78 -> 0.0466 | F19: =M78 -> 0.047 | G19: =P78 -> 0.0474
A20: Fintech revenue ($mm) | B20: =B17*B19 -> 12613.754 | C20: =C17*C19 -> 17987.903 | D20: =D17*D19 -> 23552.213 | E20: =E17*E19 -> 29248.545 | F20: =F17*F19 -> 34709.236 | G20: =G17*G19 -> 40062.803
A21: Total revenue ($mm) | B21: =B12+B20 -> 28793.027 | C21: =C12+C20 -> 39916.237 | D21: =D12+D20 -> 51458.663 | E21: =E12+E20 -> 63236.229 | F21: =F12+F20 -> 74631.355 | G21: =G12+G20 -> 85669.337
A22: total revenue growth % (memo) | C22: =C21/B21-1 -> 0.38631608 | D22: =D21/C21-1 -> 0.2891662 | E22: =E21/D21-1 -> 0.22887429 | F22: =F21/E21-1 -> 0.18019933 | G22: =G21/F21-1 -> 0.14790006
A23: Credit portfolio ($mm, memo) | B23: 12500 | C23: =B23*(1+C24) -> 22500 | D23: =C23*(1+D24) -> 33750 | E23: =D23*(1+E24) -> 45562.5 | F23: =E23*(1+F24) -> 56953.125 | G23: =F23*(1+G24) -> 67204.688
A24: credit portfolio growth % | C24: =D83 -> 0.8 | D24: =G83 -> 0.5 | E24: =J83 -> 0.35 | F24: =M83 -> 0.25 | G24: =P83 -> 0.18
A25: MARGIN & INCOME STATEMENT DRIVERS
A26: Gross margin % | C26: =D85 -> 0.425 | D26: =G85 -> 0.428 | E26: =J85 -> 0.432 | F26: =M85 -> 0.436 | G26: =P85 -> 0.44
A27: SG&A % of revenue | C27: =D86 -> 0.155 | D27: =G86 -> 0.152 | E27: =J86 -> 0.148 | F27: =M86 -> 0.144 | G27: =P86 -> 0.14
A28: R&D % of revenue | C28: =D87 -> 0.078 | D28: =G87 -> 0.077 | E28: =J87 -> 0.076 | F28: =M87 -> 0.075 | G28: =P87 -> 0.074
A29: Other operating expense % of revenue | C29: =D88 -> 0.126 | D29: =G88 -> 0.124 | E29: =J88 -> 0.122 | F29: =M88 -> 0.12 | G29: =P88 -> 0.117
A30: Interest expense % of revenue (base) | C30: =D89 -> 0.0085 | D30: =G89 -> 0.008 | E30: =J89 -> 0.0075 | F30: =M89 -> 0.007 | G30: =P89 -> 0.0065
A31: Other expense/(income) % of revenue | C31: =D90 -> 0.005 | D31: =G90 -> 0.005 | E31: =J90 -> 0.005 | F31: =M90 -> 0.005 | G31: =P90 -> 0.005
A32: Effective tax rate % | C32: =D91 -> 0.295 | D32: =G91 -> 0.295 | E32: =J91 -> 0.295 | F32: =M91 -> 0.295 | G32: =P91 -> 0.295
A33: Diluted share count change % | C33: =D92 -> -0.002 | D33: =G92 -> -0.002 | E33: =J92 -> -0.002 | F33: =M92 -> -0.002 | G33: =P92 -> -0.002
A34: Revolver interest rate % | C34: =D93 -> 0.085 | D34: =G93 -> 0.082 | E34: =J93 -> 0.08 | F34: =M93 -> 0.078 | G34: =P93 -> 0.075
A35: Minimum cash balance ($mm) | C35: =D94 -> 2500 | D35: =G94 -> 2750 | E35: =J94 -> 3000 | F35: =M94 -> 3250 | G35: =P94 -> 3500
A36: CASH FLOW DRIVERS
A37: D&A % of revenue | C37: =D96 -> 0.03 | D37: =G96 -> 0.031 | E37: =J96 -> 0.031 | F37: =M96 -> 0.03 | G37: =P96 -> 0.03
A38: Stock-based comp % of revenue | C38: =D97 -> 0.011 | D38: =G97 -> 0.011 | E38: =J97 -> 0.01 | F38: =M97 -> 0.01 | G38: =P97 -> 0.009
A39: Capex % of revenue | C39: =D98 -> 0.065 | D39: =G98 -> 0.06 | E39: =J98 -> 0.055 | F39: =M98 -> 0.05 | G39: =P98 -> 0.047
A40: Acquisitions ($, outflow negative) | C40: =D99 -> 0 | D40: =G99 -> 0 | E40: =J99 -> 0 | F40: =M99 -> 0 | G40: =P99 -> 0
A41: Share repurchase/(issuance) ($, buyback neg) | C41: =D100 -> -250 | D41: =G100 -> -500 | E41: =J100 -> -750 | F41: =M100 -> -1000 | G41: =P100 -> -1250
A42: Dividends paid ($, outflow negative) | C42: =D101 -> 0 | D42: =G101 -> 0 | E42: =J101 -> 0 | F42: =M101 -> 0 | G42: =P101 -> 0
A43: FX effect on cash ($) | C43: =D102 -> -200 | D43: =G102 -> -150 | E43: =J102 -> -150 | F43: =M102 -> -100 | G43: =P102 -> -100
A44: Preferred dividends ($) | C44: =D103 -> 0 | D44: =G103 -> 0 | E44: =J103 -> 0 | F44: =M103 -> 0 | G44: =P103 -> 0
A45: BALANCE SHEET DRIVERS
A46: Receivables % of revenue | C46: =D105 -> 0.3 | D46: =G105 -> 0.32 | E46: =J105 -> 0.33 | F46: =M105 -> 0.34 | G46: =P105 -> 0.35
A47: Inventory % of revenue | C47: =D106 -> 0.025 | D47: =G106 -> 0.027 | E47: =J106 -> 0.029 | F47: =M106 -> 0.03 | G47: =P106 -> 0.032
A48: Other current assets % of revenue | C48: =D107 -> 0.02 | D48: =G107 -> 0.02 | E48: =J107 -> 0.02 | F48: =M107 -> 0.02 | G48: =P107 -> 0.02
A49: Short-term investments % of revenue | C49: =D108 -> 0.34 | D49: =G108 -> 0.33 | E49: =J108 -> 0.32 | F49: =M108 -> 0.31 | G49: =P108 -> 0.3
A50: Accounts payable % of revenue | C50: =D109 -> 0.77 | D50: =G109 -> 0.775 | E50: =J109 -> 0.78 | F50: =M109 -> 0.78 | G50: =P109 -> 0.785
A51: Other current liabilities % of revenue | C51: =D110 -> 0.047 | D51: =G110 -> 0.047 | E51: =J110 -> 0.047 | F51: =M110 -> 0.047 | G51: =P110 -> 0.047
A52: Current debt (term) % of revenue | C52: =D111 -> 0.175 | D52: =G111 -> 0.17 | E52: =J111 -> 0.165 | F52: =M111 -> 0.16 | G52: =P111 -> 0.155
A53: Other long-term assets % of revenue | C53: =D112 -> 0.073 | D53: =G112 -> 0.073 | E53: =J112 -> 0.073 | F53: =M112 -> 0.073 | G53: =P112 -> 0.073
A54: Other long-term liabilities % of revenue | C54: =D113 -> 0.033 | D54: =G113 -> 0.033 | E54: =J113 -> 0.033 | F54: =M113 -> 0.033 | G54: =P113 -> 0.033
A55: Long-term investments growth % | C55: =D114 -> 0.08 | D55: =G114 -> 0.07 | E55: =J114 -> 0.06 | F55: =M114 -> 0.05 | G55: =P114 -> 0.05
A56: Long-term debt growth % | C56: =D115 -> 0.12 | D56: =G115 -> 0.1 | E56: =J115 -> 0.08 | F56: =M115 -> 0.07 | G56: =P115 -> 0.06
A57: Goodwill & intangibles ($, flat) | C57: =D116 -> 196 | D57: =G116 -> 196 | E57: =J116 -> 196 | F57: =M116 -> 196 | G57: =P116 -> 196
A60: Possible / Plausible / Probable Annual Assumption Matrix
A61: Active forecast in C:G pulls from the Probable case. Possible and Plausible provide realistic upside ranges for every annual forecast cell.
A62: Metric / Driver | B62: 2026 Possible | C62: 2026 Plausible | D62: 2026 Probable | E62: 2027 Possible | F62: 2027 Plausible | G62: 2027 Probable | H62: 2028 Possible | I62: 2028 Plausible | J62: 2028 Probable | K62: 2029 Possible | L62: 2029 Plausible | M62: 2029 Probable | N62: 2030 Possible | O62: 2030 Plausible | P62: 2030 Probable
A63: KPI / REVENUE BUILD
A64: Unique active buyers (mn) | B64: =$B$5*(1+B$65) -> 154.88 | C64: =$B$5*(1+C$65) -> 151.25 | D64: =$B$5*(1+D$65) -> 150.04 | E64: =B$64*(1+E$65) -> 188.9536 | F64: =C$64*(1+F$65) -> 181.5 | G64: =D$64*(1+G$65) -> 177.0472 | H64: =E$64*(1+H$65) -> 222.96525 | I64: =F$64*(1+I$65) -> 210.54 | J64: =G$64*(1+J$65) -> 201.83381 | K64: =H$64*(1+K$65) -> 256.41004 | L64: =I$64*(1+L$65) -> 237.9102 | ... P64: =M$64*(1+P$65) -> 244.19872
A65: active buyer growth % | B65: 0.28 | C65: 0.25 | D65: 0.24 | E65: 0.22 | F65: 0.2 | G65: 0.18 | H65: 0.18 | I65: 0.16 | J65: 0.14 | K65: 0.15 | L65: 0.13 | M65: 0.11 | N65: 0.12 | O65: 0.1 | P65: 0.09
A66: GMV per active buyer ($) | B66: =$B$7*(1+B$67) -> 596.07 | C66: =$B$7*(1+C$67) -> 585.33 | D66: =$B$7*(1+D$67) -> 579.96 | E66: =B$66*(1+E$67) -> 649.7163 | F66: =C$66*(1+F$67) -> 632.1564 | G66: =D$66*(1+G$67) -> 620.5572 | H66: =E$66*(1+H$67) -> 701.6936 | I66: =F$66*(1+I$67) -> 676.40735 | J66: =G$66*(1+J$67) -> 657.79063 | K66: =H$66*(1+K$67) -> 750.81216 | L66: =I$66*(1+L$67) -> 716.99179 | ... P66: =M$66*(1+P$67) -> 718.30737
A67: GMV per buyer growth % | B67: 0.11 | C67: 0.09 | D67: 0.08 | E67: 0.09 | F67: 0.08 | G67: 0.07 | H67: 0.08 | I67: 0.07 | J67: 0.06 | K67: 0.07 | L67: 0.06 | M67: 0.05 | N67: 0.06 | O67: 0.05 | P67: 0.04
A68: GMV ($mm) | B68: =B$64*B$66 -> 92319.322 | C68: =C$64*C$66 -> 88531.163 | D68: =D$64*D$66 -> 87017.198 | E68: =E$64*E$66 -> 122766.23 | F68: =F$64*F$66 -> 114736.39 | G68: =G$64*G$66 -> 109867.91 | H68: =H$64*H$66 -> 156453.29 | I68: =I$64*I$66 -> 142410.8 | ... P68: =P$64*P$66 -> 175409.74
A69: GMV growth % (memo) | B69: =B$68/$B$9-1 -> 0.4208 | C69: =C$68/$B$9-1 -> 0.3625 | D69: =D$68/$B$9-1 -> 0.3392 | E69: =E$68/B$68-1 -> 0.3298 | F69: =F$68/C$68-1 -> 0.296 | G69: =G$68/D$68-1 -> 0.2626 | H69: =H$68/E$68-1 -> 0.2744 | I69: =I$68/F$68-1 -> 0.2412 | J69: =J$68/G$68-1 -> 0.2084 | K69: =K$68/H$68-1 -> 0.2305 | L69: =L$68/I$68-1 -> 0.1978 | ... P69: =P$68/M$68-1 -> 0.1336
A70: Commerce take rate % | B70: 0.255 | C70: 0.252 | D70: 0.252 | E70: 0.258 | F70: 0.254 | G70: 0.254 | H70: 0.261 | I70: 0.256 | J70: 0.256 | K70: 0.264 | L70: 0.258 | M70: 0.258 | N70: 0.267 | O70: 0.26 | P70: 0.26
A71: Commerce revenue ($mm) | B71: =B$68*B$70 -> 23541.427 | C71: =C$68*C$70 -> 22309.853 | D71: =D$68*D$70 -> 21928.334 | E71: =E$68*E$70 -> 31673.688 | F71: =F$68*F$70 -> 29143.042 | G71: =G$68*G$70 -> 27906.45 | H71: =H$68*H$70 -> 40834.308 | I71: =I$68*I$70 -> 36457.166 | ... P71: =P$68*P$70 -> 45606.533
A72: Fintech MAUs (mn) | B72: =$B$13*(1+B$73) -> 99.84 | C72: =$B$13*(1+C$73) -> 97.5 | D72: =$B$13*(1+D$73) -> 96.72 | E72: =B$72*(1+E$73) -> 121.8048 | F72: =C$72*(1+F$73) -> 117 | G72: =D$72*(1+G$73) -> 114.1296 | H72: =E$72*(1+H$73) -> 143.72966 | I72: =F$72*(1+I$73) -> 135.72 | J72: =G$72*(1+J$73) -> 130.10774 | K72: =H$72*(1+K$73) -> 165.28911 | L72: =I$72*(1+L$73) -> 153.3636 | ... P72: =M$72*(1+P$73) -> 157.41736
A73: MAU growth % | B73: 0.28 | C73: 0.25 | D73: 0.24 | E73: 0.22 | F73: 0.2 | G73: 0.18 | H73: 0.18 | I73: 0.16 | J73: 0.14 | K73: 0.15 | L73: 0.13 | M73: 0.11 | N73: 0.12 | O73: 0.1 | P73: 0.09
A74: TPV per MAU ($) | B74: =$B$15*(1+B$75) -> 4167.54 | C74: =$B$15*(1+C$75) -> 4096.3 | D74: =$B$15*(1+D$75) -> 4060.68 | E74: =B$74*(1+E$75) -> 4750.9956 | F74: =C$74*(1+F$75) -> 4587.856 | G74: =D$74*(1+G$75) -> 4466.748 | H74: =E$74*(1+H$75) -> 5321.1151 | I74: =F$74*(1+I$75) -> 5046.6416 | J74: =G$74*(1+J$75) -> 4824.0878 | K74: =H$74*(1+K$75) -> 5853.2266 | L74: =I$74*(1+L$75) -> 5450.3729 | ... P74: =M$74*(1+P$75) -> 5369.2098
A75: TPV per MAU growth % | B75: 0.17 | C75: 0.15 | D75: 0.14 | E75: 0.14 | F75: 0.12 | G75: 0.1 | H75: 0.12 | I75: 0.1 | J75: 0.08 | K75: 0.1 | L75: 0.08 | M75: 0.06 | N75: 0.08 | O75: 0.06 | P75: 0.05
A76: TPV ($mm) | B76: =B$72*B$74 -> 416087.19 | C76: =C$72*C$74 -> 399389.25 | D76: =D$72*D$74 -> 392748.97 | E76: =E$72*E$74 -> 578694.07 | F76: =F$72*F$74 -> 536779.15 | G76: =G$72*G$74 -> 509788.16 | H76: =H$72*H$74 -> 764802.08 | I76: =I$72*I$74 -> 684930.2 | ... P76: =P$72*P$74 -> 845206.82
A77: TPV growth % (memo) | B77: =B$76/$B$17-1 -> 0.4976 | C77: =C$76/$B$17-1 -> 0.4375 | D77: =D$76/$B$17-1 -> 0.4136 | E77: =E$76/B$76-1 -> 0.3908 | F77: =F$76/C$76-1 -> 0.344 | G77: =G$76/D$76-1 -> 0.298 | H77: =H$76/E$76-1 -> 0.3216 | I77: =I$76/F$76-1 -> 0.276 | J77: =J$76/G$76-1 -> 0.2312 | K77: =K$76/H$76-1 -> 0.265 | L77: =L$76/I$76-1 -> 0.2204 | ... P77: =P$76/M$76-1 -> 0.1445
A78: Fintech take rate % | B78: 0.0475 | C78: 0.0465 | D78: 0.0458 | E78: 0.0485 | F78: 0.047 | G78: 0.0462 | H78: 0.0495 | I78: 0.0473 | J78: 0.0466 | K78: 0.05 | L78: 0.0475 | M78: 0.047 | N78: 0.0505 | O78: 0.0478 | P78: 0.0474
A79: Fintech revenue ($mm) | B79: =B$76*B$78 -> 19764.142 | C79: =C$76*C$78 -> 18571.6 | D79: =D$76*D$78 -> 17987.903 | E79: =E$76*E$78 -> 28066.662 | F79: =F$76*F$78 -> 25228.62 | G79: =G$76*G$78 -> 23552.213 | H79: =H$76*H$78 -> 37857.703 | I79: =I$76*I$78 -> 32397.198 | ... P79: =P$76*P$78 -> 40062.803
A80: Total revenue ($mm) | B80: =B$71+B$79 -> 43305.569 | C80: =C$71+C$79 -> 40881.453 | D80: =D$71+D$79 -> 39916.237 | E80: =E$71+E$79 -> 59740.351 | F80: =F$71+F$79 -> 54371.662 | G80: =G$71+G$79 -> 51458.663 | H80: =H$71+H$79 -> 78692.011 | I80: =I$71+I$79 -> 68854.364 | ... P80: =P$71+P$79 -> 85669.337
A81: total revenue growth % (memo) | B81: =B$80/$B$21-1 -> 0.50402971 | C81: =C$80/$B$21-1 -> 0.41983865 | D81: =D$80/$B$21-1 -> 0.38631608 | E81: =E$80/B$80-1 -> 0.37950736 | F81: =F$80/C$80-1 -> 0.32998361 | G81: =G$80/D$80-1 -> 0.2891662 | H81: =H$80/E$80-1 -> 0.31723384 | I81: =I$80/F$80-1 -> 0.26636489 | J81: =J$80/G$80-1 -> 0.22887429 | K81: =K$80/H$80-1 -> 0.26058406 | L81: =L$80/I$80-1 -> 0.21581649 | ... P81: =P$80/M$80-1 -> 0.14790006
A82: Credit portfolio ($mm, memo) | B82: =$B$23*(1+B$83) -> 23125 | C82: =$B$23*(1+C$83) -> 21875 | D82: =$B$23*(1+D$83) -> 22500 | E82: =B$82*(1+E$83) -> 35843.75 | F82: =C$82*(1+F$83) -> 31718.75 | G82: =D$82*(1+G$83) -> 33750 | H82: =E$82*(1+H$83) -> 50181.25 | I82: =F$82*(1+I$83) -> 41868.75 | J82: =G$82*(1+J$83) -> 45562.5 | K82: =H$82*(1+K$83) -> 65235.625 | L82: =I$82*(1+L$83) -> 51917.25 | ... P82: =M$82*(1+P$83) -> 67204.688
A83: credit portfolio growth % | B83: 0.85 | C83: 0.75 | D83: 0.8 | E83: 0.55 | F83: 0.45 | G83: 0.5 | H83: 0.4 | I83: 0.32 | J83: 0.35 | K83: 0.3 | L83: 0.24 | M83: 0.25 | N83: 0.22 | O83: 0.18 | P83: 0.18
A84: MARGIN & INCOME STATEMENT DRIVERS
A85: Gross margin % | B85: 0.435 | C85: 0.43 | D85: 0.425 | E85: 0.442 | F85: 0.435 | G85: 0.428 | H85: 0.45 | I85: 0.44 | J85: 0.432 | K85: 0.458 | L85: 0.445 | M85: 0.436 | N85: 0.465 | O85: 0.45 | P85: 0.44
A86: SG&A % of revenue | B86: 0.15 | C86: 0.152 | D86: 0.155 | E86: 0.142 | F86: 0.146 | G86: 0.152 | H86: 0.135 | I86: 0.14 | J86: 0.148 | K86: 0.128 | L86: 0.134 | M86: 0.144 | N86: 0.122 | O86: 0.13 | P86: 0.14
A87: R&D % of revenue | B87: 0.076 | C87: 0.077 | D87: 0.078 | E87: 0.074 | F87: 0.075 | G87: 0.077 | H87: 0.071 | I87: 0.073 | J87: 0.076 | K87: 0.069 | L87: 0.071 | M87: 0.075 | N87: 0.067 | O87: 0.069 | P87: 0.074
A88: Other operating expense % of revenue | B88: 0.12 | C88: 0.124 | D88: 0.126 | E88: 0.113 | F88: 0.118 | G88: 0.124 | H88: 0.106 | I88: 0.112 | J88: 0.122 | K88: 0.098 | L88: 0.106 | M88: 0.12 | N88: 0.092 | O88: 0.1 | P88: 0.117
A89: Interest expense % of revenue (base) | B89: 0.0065 | C89: 0.0075 | D89: 0.0085 | E89: 0.006 | F89: 0.007 | G89: 0.008 | H89: 0.0055 | I89: 0.0065 | J89: 0.0075 | K89: 0.005 | L89: 0.006 | M89: 0.007 | N89: 0.0045 | O89: 0.0055 | P89: 0.0065
A90: Other expense/(income) % of revenue | B90: 0.003 | C90: 0.004 | D90: 0.005 | E90: 0.003 | F90: 0.004 | G90: 0.005 | H90: 0.003 | I90: 0.004 | J90: 0.005 | K90: 0.003 | L90: 0.004 | M90: 0.005 | N90: 0.003 | O90: 0.004 | P90: 0.005
A91: Effective tax rate % | B91: 0.285 | C91: 0.29 | D91: 0.295 | E91: 0.285 | F91: 0.29 | G91: 0.295 | H91: 0.285 | I91: 0.29 | J91: 0.295 | K91: 0.285 | L91: 0.29 | M91: 0.295 | N91: 0.285 | O91: 0.29 | P91: 0.295
A92: Diluted share count change % | B92: -0.004 | C92: -0.003 | D92: -0.002 | E92: -0.004 | F92: -0.003 | G92: -0.002 | H92: -0.004 | I92: -0.003 | J92: -0.002 | K92: -0.004 | L92: -0.003 | M92: -0.002 | N92: -0.004 | O92: -0.003 | P92: -0.002
A93: Revolver interest rate % | B93: 0.08 | C93: 0.083 | D93: 0.085 | E93: 0.078 | F93: 0.08 | G93: 0.082 | H93: 0.075 | I93: 0.078 | J93: 0.08 | K93: 0.073 | L93: 0.075 | M93: 0.078 | N93: 0.07 | O93: 0.073 | P93: 0.075
A94: Minimum cash balance ($mm) | B94: 2000 | C94: 2250 | D94: 2500 | E94: 2250 | F94: 2500 | G94: 2750 | H94: 2500 | I94: 2750 | J94: 3000 | K94: 2750 | L94: 3000 | M94: 3250 | N94: 3000 | O94: 3250 | P94: 3500
A95: CASH FLOW DRIVERS
A96: D&A % of revenue | B96: 0.03 | C96: 0.03 | D96: 0.03 | E96: 0.03 | F96: 0.03 | G96: 0.031 | H96: 0.029 | I96: 0.03 | J96: 0.031 | K96: 0.029 | L96: 0.029 | M96: 0.03 | N96: 0.028 | O96: 0.029 | P96: 0.03
A97: Stock-based comp % of revenue | B97: 0.01 | C97: 0.011 | D97: 0.011 | E97: 0.009 | F97: 0.01 | G97: 0.011 | H97: 0.009 | I97: 0.01 | J97: 0.01 | K97: 0.008 | L97: 0.009 | M97: 0.01 | N97: 0.008 | O97: 0.009 | P97: 0.009
A98: Capex % of revenue | B98: 0.06 | C98: 0.063 | D98: 0.065 | E98: 0.055 | F98: 0.058 | G98: 0.06 | H98: 0.05 | I98: 0.053 | J98: 0.055 | K98: 0.045 | L98: 0.048 | M98: 0.05 | N98: 0.042 | O98: 0.045 | P98: 0.047
A99: Acquisitions ($, outflow negative) | B99: 0 | C99: 0 | D99: 0 | E99: 0 | F99: 0 | G99: 0 | H99: 0 | I99: 0 | J99: 0 | K99: 0 | L99: 0 | M99: 0 | N99: 0 | O99: 0 | P99: 0
A100: Share repurchase/(issuance) ($, buyback neg) | B100: -750 | C100: -500 | D100: -250 | E100: -1000 | F100: -750 | G100: -500 | H100: -1250 | I100: -1000 | J100: -750 | K100: -1500 | L100: -1250 | M100: -1000 | N100: -2000 | O100: -1500 | P100: -1250
A101: Dividends paid ($, outflow negative) | B101: 0 | C101: 0 | D101: 0 | E101: 0 | F101: 0 | G101: 0 | H101: 0 | I101: 0 | J101: 0 | K101: 0 | L101: 0 | M101: 0 | N101: 0 | O101: 0 | P101: 0
A102: FX effect on cash ($) | B102: 0 | C102: -100 | D102: -200 | E102: 0 | F102: -100 | G102: -150 | H102: 0 | I102: -100 | J102: -150 | K102: 0 | L102: -100 | M102: -100 | N102: 0 | O102: -100 | P102: -100
...

Sheet Assumptions (Quarterly)
A1: MercadoLibre (MELI) | Forecast Assumptions - Quarterly
A2: Quarterly revenue = GMV x commerce take rate + TPV x fintech take rate. Cols B-E trailing actuals | F-L forecasts. $ in millions.
A3: Driver / KPI | B3: Q2'25 | C3: Q3'25 | D3: Q4'25 | E3: Q1'26 | F3: Q2'26E | G3: Q3'26E | H3: Q4'26E | I3: Q1'27E | J3: Q2'27E | K3: Q3'27E | L3: Q4'27E
A4: KPI / REVENUE BUILD
A5: GMV ($mm) | B5: 14900 | C5: 16851 | D5: 19906 | E5: 19000 | F5: =B5*(1+F6) -> 19370 | G5: =C5*(1+G6) -> 21400.77 | H5: =D5*(1+H6) -> 24683.44 | I5: =E5*(1+I6) -> 23560 | J5: =F5*(1+J6) -> 23631.4 | K5: =G5*(1+K6) -> 25680.924 | L5: =H5*(1+L6) -> 29126.459
A6: GMV YoY growth % | F6: 0.3 | G6: 0.27 | H6: 0.24 | I6: 0.24 | J6: 0.22 | K6: 0.2 | L6: 0.18
A7: Commerce take rate % | B7: 0.255 | C7: 0.255 | D7: 0.262 | E7: 0.263 | F7: 0.26 | G7: 0.262 | H7: 0.265 | I7: 0.262 | J7: 0.264 | K7: 0.266 | L7: 0.268
A8: Commerce revenue ($mm) | B8: =B5*B7 -> 3799.5 | C8: =C5*C7 -> 4297.005 | D8: =D5*D7 -> 5215.372 | E8: =E5*E7 -> 4997 | F8: =F5*F7 -> 5036.2 | G8: =G5*G7 -> 5607.0017 | H8: =H5*H7 -> 6541.1116 | I8: =I5*I7 -> 6172.72 | ... L8: =L5*L7 -> 7805.8911
A9: TPV ($mm) | B9: 64500 | C9: 71496 | D9: 83694 | E9: 87200 | F9: =B9*(1+F10) -> 89010 | G9: =C9*(1+G10) -> 95804.64 | H9: =D9*(1+H10) -> 108802.2 | I9: =E9*(1+I10) -> 113360 | J9: =F9*(1+J10) -> 113932.8 | K9: =G9*(1+K10) -> 120713.85 | L9: =H9*(1+L10) -> 134914.73
A10: TPV YoY growth % | F10: 0.38 | G10: 0.34 | H10: 0.3 | I10: 0.3 | J10: 0.28 | K10: 0.26 | L10: 0.24
A11: Fintech take rate % | B11: 0.046 | C11: 0.046 | D11: 0.046 | E11: 0.046 | F11: 0.046 | G11: 0.047 | H11: 0.047 | I11: 0.047 | J11: 0.047 | K11: 0.048 | L11: 0.048
A12: Fintech revenue ($mm) | B12: =B9*B11 -> 2967 | C12: =C9*C11 -> 3288.816 | D12: =D9*D11 -> 3849.924 | E12: =E9*E11 -> 4011.2 | F12: =F9*F11 -> 4094.46 | G12: =G9*G11 -> 4502.8181 | H12: =H9*H11 -> 5113.7034 | I12: =I9*I11 -> 5327.92 | ... L12: =L9*L11 -> 6475.9069
A13: Total revenue ($mm) | B13: =B8+B12 -> 6766.5 | C13: =C8+C12 -> 7585.821 | D13: =D8+D12 -> 9065.296 | E13: =E8+E12 -> 9008.2 | F13: =F8+F12 -> 9130.66 | G13: =G8+G12 -> 10109.82 | H13: =H8+H12 -> 11654.815 | I13: =I8+I12 -> 11500.64 | ... L13: =L8+L12 -> 14281.798
A14: MARGIN & INCOME STATEMENT DRIVERS
A15: Gross margin % | F15: 0.44 | G15: 0.442 | H15: 0.445 | I15: 0.44 | J15: 0.443 | K15: 0.445 | L15: 0.448
A16: SG&A % of revenue | F16: 0.146 | G16: 0.145 | H16: 0.142 | I16: 0.144 | J16: 0.142 | K16: 0.141 | L16: 0.138
A17: R&D % of revenue | F17: 0.079 | G17: 0.078 | H17: 0.077 | I17: 0.078 | J17: 0.077 | K17: 0.076 | L17: 0.075
A18: Other operating expense % of revenue | F18: 0.125 | G18: 0.12 | H18: 0.115 | I18: 0.122 | J18: 0.118 | K18: 0.114 | L18: 0.11
A19: Interest expense % of revenue (base) | F19: 0.007 | G19: 0.007 | H19: 0.007 | I19: 0.007 | J19: 0.007 | K19: 0.006 | L19: 0.006
A20: Other expense/(income) % of revenue | F20: 0.005 | G20: 0.005 | H20: 0.005 | I20: 0.005 | J20: 0.005 | K20: 0.005 | L20: 0.005
A21: Effective tax rate % | F21: 0.29 | G21: 0.29 | H21: 0.29 | I21: 0.29 | J21: 0.29 | K21: 0.29 | L21: 0.29
A22: Diluted share count change % (q/q) | F22: -0.001 | G22: -0.001 | H22: -0.001 | I22: -0.001 | J22: -0.001 | K22: -0.001 | L22: -0.001
A23: Revolver interest rate % (quarterly) | F23: 0.0225 | G23: 0.0225 | H23: 0.0225 | I23: 0.0225 | J23: 0.0225 | K23: 0.0225 | L23: 0.0225
A24: Minimum cash balance ($mm) | F24: 2000 | G24: 2000 | H24: 2000 | I24: 2000 | J24: 2000 | K24: 2000 | L24: 2000
A25: CASH FLOW DRIVERS
A26: D&A % of revenue | F26: 0.029 | G26: 0.029 | H26: 0.029 | I26: 0.029 | J26: 0.029 | K26: 0.03 | L26: 0.03
A27: Stock-based comp % of revenue | F27: 0.011 | G27: 0.011 | H27: 0.011 | I27: 0.011 | J27: 0.011 | K27: 0.011 | L27: 0.011
A28: Capex % of revenue | F28: 0.045 | G28: 0.045 | H28: 0.044 | I28: 0.044 | J28: 0.043 | K28: 0.043 | L28: 0.042
A29: Acquisitions ($, outflow negative) | F29: 0 | G29: 0 | H29: 0 | I29: 0 | J29: 0 | K29: 0 | L29: 0
A30: Share repurchase/(issuance) ($) | F30: 0 | G30: 0 | H30: 0 | I30: 0 | J30: 0 | K30: 0 | L30: 0
A31: Dividends paid ($) | F31: 0 | G31: 0 | H31: 0 | I31: 0 | J31: 0 | K31: 0 | L31: 0
A32: FX effect on cash ($) | F32: 0 | G32: 0 | H32: 0 | I32: 0 | J32: 0 | K32: 0 | L32: 0
A33: Preferred dividends ($) | F33: 0 | G33: 0 | H33: 0 | I33: 0 | J33: 0 | K33: 0 | L33: 0
A34: BALANCE SHEET DRIVERS (x quarterly revenue)
A35: Receivables / qtr revenue | F35: 0.96 | G35: 0.96 | H35: 0.95 | I35: 0.96 | J35: 0.96 | K35: 0.96 | L35: 0.95
A36: Inventory / qtr revenue | F36: 0.077 | G36: 0.077 | H36: 0.076 | I36: 0.077 | J36: 0.077 | K36: 0.077 | L36: 0.076
A37: Other current assets / qtr revenue | F37: 0.075 | G37: 0.075 | H37: 0.074 | I37: 0.075 | J37: 0.075 | K37: 0.075 | L37: 0.074
A38: Short-term investments / qtr revenue | F38: 1.37 | G38: 1.35 | H38: 1.3 | I38: 1.3 | J38: 1.28 | K38: 1.26 | L38: 1.24
A39: Accounts payable / qtr revenue | F39: 2.78 | G39: 2.8 | H39: 2.78 | I39: 2.8 | J39: 2.82 | K39: 2.84 | L39: 2.82
A40: Other current liabilities / qtr revenue | F40: 0.184 | G40: 0.184 | H40: 0.184 | I40: 0.184 | J40: 0.184 | K40: 0.184 | L40: 0.184
A41: Current debt (term) / qtr revenue | F41: 0.654 | G41: 0.654 | H41: 0.654 | I41: 0.654 | J41: 0.654 | K41: 0.654 | L41: 0.654
A42: Other long-term assets / qtr revenue | F42: 0.287 | G42: 0.287 | H42: 0.287 | I42: 0.287 | J42: 0.287 | K42: 0.287 | L42: 0.287
A43: Other long-term liabilities / qtr revenue | F43: 0.127 | G43: 0.127 | H43: 0.127 | I43: 0.127 | J43: 0.127 | K43: 0.127 | L43: 0.127
A44: Long-term investments growth % (q/q) | F44: 0.025 | G44: 0.025 | H44: 0.025 | I44: 0.025 | J44: 0.025 | K44: 0.025 | L44: 0.025
A45: Long-term debt growth % (q/q) | F45: 0.035 | G45: 0.035 | H45: 0.035 | I45: 0.03 | J45: 0.03 | K45: 0.03 | L45: 0.025
A46: Goodwill & intangibles ($, flat) | F46: 198 | G46: 198 | H46: 198 | I46: 198 | J46: 198 | K46: 198 | L46: 198
A48: Methodology:
A49: - Quarterly revenue = GMV x commerce take rate + TPV x fintech take rate. GMV and TPV grow off the same quarter a year earlier (seasonality).
A50: - Anchors (grey, cols B-E) are the trailing four quarters of GMV and TPV. Same indirect cash flow and revolver logic as the annual tab.
A51: - Forecast quarters reconcile to the independent annual forecast within ~1-2% for FY26 and FY27.

Sheet Valuation
A1: MercadoLibre (MELI) | Discounted Cash Flow - Probable Case
B2: Discount period (yr 1 = 2026E ... yr 5 = 2030E) | C2: 1 | D2: 2 | E2: 3 | F2: 4 | G2: 5
B3: Free cash flow ($mm) | C3: =Annual!W100 -> 3908.2243 | D3: =Annual!X100 -> 5434.5333 | E3: =Annual!Y100 -> 6836.472 | F3: =Annual!Z100 -> 7554.237 | G3: =Annual!AA100 -> 8985.7348
B4: PV of free cash flow ($mm) | C4: =C3/(1+$C$8)^C2 -> 3443.3695 | D4: =D3/(1+$C$8)^D2 -> 4218.6212 | E4: =E3/(1+$C$8)^E2 -> 4675.6765 | F4: =F3/(1+$C$8)^F2 -> 4552.0514 | G4: =G3/(1+$C$8)^G2 -> 4770.6141
B7: Current share price ($) | C7: 1584
B8: Discount rate (WACC) | C8: 0.135
B9: Terminal EV / EBIT (x) [on operating income] | C9: 15
B10: PV of terminal value ($mm) | C10: =(C9*Annual!AA13)/(1+C8)^G2 -> 74364.19
B11: Enterprise value ($mm) | C11: =SUM(C10,C4:G4) -> 96024.523
B12: Equity value ($mm) | C12: =C11+Annual!V39-Annual!V66 -> 109653.52
B13: Implied value per share ($) | C13: =C12/Annual!V23 -> 2162.9057
B14: Upside / (downside) to current | C14: =C13/C7-1 -> 0.36547078
