Workbook

Sheet META Model
A1: Meta Platforms Quarterly Model
B2: Q125 | C2: Q225 | D2: Q325 | E2: Q425 | F2: Q126 | G2: Q226 | H2: Q326 | I2: Q426 | K2: FY25 | L2: FY26
A4: Advertising | B4: 41392 | C4: 46563 | D4: 50082 | E4: 58137 | F4: 55024 | G4: =C4*(1+G46)*(1+G47) -> 58902.195 | H4: =D4*(1+H46)*(1+H47) -> 61685.999 | I4: =E4*(1+I46)*(1+I47) -> 70662.617 | K4: =SUM(B4:E4) -> 196174 | L4: =SUM(F4:I4) -> 246274.81
A5: Other revenue | B5: 510 | C5: 583 | D5: 690 | E5: 801 | F5: 885 | G5: 990 | H5: 1100 | I5: 1200 | K5: =SUM(B5:E5) -> 2584 | L5: =SUM(F5:I5) -> 4175
A6: Family of Apps | B6: =SUM(B4:B5) -> 41902 | C6: =SUM(C4:C5) -> 47146 | D6: =SUM(D4:D5) -> 50772 | E6: =SUM(E4:E5) -> 58938 | F6: =SUM(F4:F5) -> 55909 | G6: =SUM(G4:G5) -> 59892.195 | H6: =SUM(H4:H5) -> 62785.999 | I6: =SUM(I4:I5) -> 71862.617 | K6: =SUM(B6:E6) -> 198758 | L6: =SUM(F6:I6) -> 250449.81
A7: Reality Labs | B7: 412 | C7: 370 | D7: 470 | E7: 955 | F7: 402 | G7: 445 | H7: 540 | I7: 1100 | K7: =SUM(B7:E7) -> 2207 | L7: =SUM(F7:I7) -> 2487
A8: Total revenue | B8: =SUM(B6:B7) -> 42314 | C8: =SUM(C6:C7) -> 47516 | D8: =SUM(D6:D7) -> 51242 | E8: =SUM(E6:E7) -> 59893 | F8: =SUM(F6:F7) -> 56311 | G8: =SUM(G6:G7) -> 60337.195 | H8: =SUM(H6:H7) -> 63325.999 | I8: =SUM(I6:I7) -> 72962.617 | K8: =SUM(B8:E8) -> 200965 | L8: =SUM(F8:I8) -> 252936.81
A10: Cost of revenue | B10: 7572 | C10: 8491 | D10: 9206 | E10: 10905 | F10: 10218 | G10: 11500 | H10: 12700 | I10: 14600 | K10: =SUM(B10:E10) -> 36174 | L10: =SUM(F10:I10) -> 49018
A11: Gross profit | B11: =B8-B10 -> 34742 | C11: =C8-C10 -> 39025 | D11: =D8-D10 -> 42036 | E11: =E8-E10 -> 48988 | F11: =F8-F10 -> 46093 | G11: =G8-G10 -> 48837.195 | H11: =H8-H10 -> 50625.999 | I11: =I8-I10 -> 58362.617 | K11: =SUM(B11:E11) -> 164791 | L11: =SUM(F11:I11) -> 203918.81
A12: Research and development | B12: 12150 | C12: 12942 | D12: 15144 | E12: 17136 | F12: 17699 | G12: 21700 | H12: 24000 | I12: 27300 | K12: =SUM(B12:E12) -> 57372 | L12: =SUM(F12:I12) -> 90699
A13: Marketing and sales | B13: 2757 | C13: 2979 | D13: 2845 | E13: 3410 | F13: 2908 | G13: 3000 | H13: 3200 | I13: 3800 | K13: =SUM(B13:E13) -> 11991 | L13: =SUM(F13:I13) -> 12908
A14: General and administrative | B14: 2280 | C14: 2663 | D14: 3512 | E14: 3697 | F14: 2614 | G14: 2800 | H14: 3600 | I14: 3861 | K14: =SUM(B14:E14) -> 12152 | L14: =SUM(F14:I14) -> 12875
A15: Total costs and expenses | B15: =SUM(B10,B12:B14) -> 24759 | C15: =SUM(C10,C12:C14) -> 27075 | D15: =SUM(D10,D12:D14) -> 30707 | E15: =SUM(E10,E12:E14) -> 35148 | F15: =SUM(F10,F12:F14) -> 33439 | G15: =SUM(G10,G12:G14) -> 39000 | H15: =SUM(H10,H12:H14) -> 43500 | I15: =SUM(I10,I12:I14) -> 49561 | K15: =SUM(B15:E15) -> 117689 | L15: =SUM(F15:I15) -> 165500
A16: Income from operations | B16: =B8-B15 -> 17555 | C16: =C8-C15 -> 20441 | D16: =D8-D15 -> 20535 | E16: =E8-E15 -> 24745 | F16: =F8-F15 -> 22872 | G16: =G8-G15 -> 21337.195 | H16: =H8-H15 -> 19825.999 | I16: =I8-I15 -> 23401.617 | K16: =SUM(B16:E16) -> 83276 | L16: =SUM(F16:I16) -> 87436.811
A17: Interest and other income (expense), net | B17: 827 | C17: 93 | D17: 1128 | E17: 609 | F17: -1120 | G17: 490 | H17: 390 | I17: 280 | K17: =SUM(B17:E17) -> 2657 | L17: =SUM(F17:I17) -> 40
A18: Income before income taxes | B18: =SUM(B16:B17) -> 18382 | C18: =SUM(C16:C17) -> 20534 | D18: =SUM(D16:D17) -> 21663 | E18: =SUM(E16:E17) -> 25354 | F18: =SUM(F16:F17) -> 21752 | G18: =SUM(G16:G17) -> 21827.195 | H18: =SUM(H16:H17) -> 20215.999 | I18: =SUM(I16:I17) -> 23681.617 | K18: =SUM(B18:E18) -> 85933 | L18: =SUM(F18:I18) -> 87476.811
A19: Provision (benefit) for income taxes | B19: 1738 | C19: 2197 | D19: 18954 | E19: 2586 | F19: -5021 | G19: =G18*G37 -> 3164.9433 | H19: =H18*H37 -> 2931.3199 | I19: =I18*I37 -> 3433.8344 | K19: =SUM(B19:E19) -> 25475 | L19: =SUM(F19:I19) -> 4509.0976
A20: Net income | B20: =B18-B19 -> 16644 | C20: =C18-C19 -> 18337 | D20: =D18-D19 -> 2709 | E20: =E18-E19 -> 22768 | F20: =F18-F19 -> 26773 | G20: =G18-G19 -> 18662.252 | H20: =H18-H19 -> 17284.679 | I20: =I18-I19 -> 20247.782 | K20: =SUM(B20:E20) -> 60458 | L20: =SUM(F20:I20) -> 82967.713
A22: Weighted average basic shares | B22: 2527 | C22: 2518 | D22: 2517 | E22: 2525 | F22: 2534 | G22: 2534 | H22: 2534 | I22: 2534 | K22: =SUM(B22:E22) -> 10087 | L22: =AVERAGE(F22:I22) -> 2534
A23: Weighted average diluted shares | B23: 2590 | C23: 2570 | D23: 2572 | E23: 2565 | F23: 2564 | G23: 2564 | H23: 2564 | I23: 2564 | K23: =SUM(B23:E23) -> 10297 | L23: =AVERAGE(F23:I23) -> 2564
A24: Basic EPS | B24: =B20/B22 -> 6.5864662 | C24: =C20/C22 -> 7.282367 | D24: =D20/D22 -> 1.0762813 | E24: =E20/E22 -> 9.0170297 | F24: =F20/F22 -> 10.565509 | G24: =G20/G22 -> 7.3647402 | H24: =H20/H22 -> 6.8211048 | I24: =I20/I22 -> 7.9904429 | K24: =SUM(B24:E24) -> 23.962144 | L24: =SUM(F24:I24) -> 32.741797
A25: Diluted EPS | B25: =B20/B23 -> 6.4262548 | C25: =C20/C23 -> 7.1350195 | D25: =D20/D23 -> 1.0532659 | E25: =E20/E23 -> 8.8764133 | F25: =F20/F23 -> 10.441888 | G25: =G20/G23 -> 7.2785693 | H25: =H20/H23 -> 6.7412947 | I25: =I20/I23 -> 7.8969509 | K25: =SUM(B25:E25) -> 23.490953 | L25: =SUM(F25:I25) -> 32.358703
A27: Key Performance Indicators
A28: Margins
A29: Gross margin | B29: =B11/B8 -> 0.82105213 | C29: =C11/C8 -> 0.8213023 | D29: =D11/D8 -> 0.82034269 | E29: =E11/E8 -> 0.8179253 | F29: =F11/F8 -> 0.81854345 | G29: =G11/G8 -> 0.80940446 | H29: =H11/H8 -> 0.79945046 | I29: =I11/I8 -> 0.79989753 | K29: =K11/K8 -> 0.81999851 | L29: =L11/L8 -> 0.80620456
A30: Cost of revenue as % of revenue | B30: =B10/B8 -> 0.17894787 | C30: =C10/C8 -> 0.1786977 | D30: =D10/D8 -> 0.17965731 | E30: =E10/E8 -> 0.1820747 | F30: =F10/F8 -> 0.18145655 | G30: =G10/G8 -> 0.19059554 | H30: =H10/H8 -> 0.20054954 | I30: =I10/I8 -> 0.20010247 | K30: =K10/K8 -> 0.18000149 | L30: =L10/L8 -> 0.19379544
A31: Research and development as % of revenue | B31: =B12/B8 -> 0.28713901 | C31: =C12/C8 -> 0.27237141 | D31: =D12/D8 -> 0.29553882 | E31: =E12/E8 -> 0.28611023 | F31: =F12/F8 -> 0.31430804 | G31: =G12/G8 -> 0.35964549 | H31: =H12/H8 -> 0.37899126 | I31: =I12/I8 -> 0.37416421 | K31: =K12/K8 -> 0.28548255 | L31: =L12/L8 -> 0.35858363
A32: Marketing and sales as % of revenue | B32: =B13/B8 -> 0.06515574 | C32: =C13/C8 -> 0.062694671 | D32: =D13/D8 -> 0.055520862 | E32: =E13/E8 -> 0.056934867 | F32: =F13/F8 -> 0.051641775 | G32: =G13/G8 -> 0.049720575 | H32: =H13/H8 -> 0.050532167 | I32: =I13/I8 -> 0.052081465 | K32: =K13/K8 -> 0.059667106 | L32: =L13/L8 -> 0.051032509
A33: General and administrative as % of revenue | B33: =B14/B8 -> 0.053882876 | C33: =C14/C8 -> 0.05604428 | D33: =D14/D8 -> 0.068537528 | E33: =E14/E8 -> 0.061726746 | F33: =F14/F8 -> 0.04642077 | G33: =G14/G8 -> 0.04640587 | H33: =H14/H8 -> 0.056848688 | I33: =I14/I8 -> 0.05291751 | K33: =K14/K8 -> 0.060468241 | L33: =L14/L8 -> 0.050902041
A34: Operating margin | B34: =B16/B8 -> 0.41487451 | C34: =C16/C8 -> 0.43019194 | D34: =D16/D8 -> 0.40074548 | E34: =E16/E8 -> 0.41315346 | F34: =F16/F8 -> 0.40617286 | G34: =G16/G8 -> 0.35363253 | H34: =H16/H8 -> 0.31307835 | I34: =I16/I8 -> 0.32073434 | K34: =K16/K8 -> 0.41438061 | L34: =L16/L8 -> 0.34568638
A35: Pre-tax margin | B35: =B18/B8 -> 0.43441887 | C35: =C18/C8 -> 0.43214917 | D35: =D18/D8 -> 0.42275867 | E35: =E18/E8 -> 0.42332159 | F35: =F18/F8 -> 0.38628332 | G35: =G18/G8 -> 0.36175356 | H35: =H18/H8 -> 0.31923696 | I35: =I18/I8 -> 0.32457192 | K35: =K18/K8 -> 0.42760182 | L35: =L18/L8 -> 0.34584452
A36: Net margin | B36: =B20/B8 -> 0.39334499 | C36: =C20/C8 -> 0.38591211 | D36: =D20/D8 -> 0.052866789 | E36: =E20/E8 -> 0.38014459 | F36: =F20/F8 -> 0.47544885 | G36: =G20/G8 -> 0.30929929 | H36: =H20/H8 -> 0.2729476 | I36: =I20/I8 -> 0.27750899 | K36: =K20/K8 -> 0.30083845 | L36: =L20/L8 -> 0.32801755
A37: Effective tax rate | B37: =B19/B18 -> 0.094549015 | C37: =C19/C18 -> 0.10699328 | D37: =D19/D18 -> 0.87494807 | E37: =E19/E18 -> 0.10199574 | F37: =F19/F18 -> -0.23082935 | G37: 0.145 | H37: 0.145 | I37: 0.145 | K37: =K19/K18 -> 0.29645189 | L37: =L19/L18 -> 0.051546205
A38: EBITDA margin | B38: =B43/B8 -> 0.50704259 | C38: =C43/C8 -> 0.52157168 | D38: =D43/D8 -> 0.49759963 | E38: =E43/E8 -> 0.5034979 | F38: =F43/F8 -> 0.51270622 | G38: =G43/G8 -> 0.46185765 | H38: =H43/H8 -> 0.4251966 | I38: =I43/I8 -> 0.42818663 | K38: =K43/K8 -> 0.50701366 | L38: =L43/L8 -> 0.45428663
A40: Profitability and Operating KPIs
A41: EBIT | B41: =B16 -> 17555 | C41: =C16 -> 20441 | D41: =D16 -> 20535 | E41: =E16 -> 24745 | F41: =F16 -> 22872 | G41: =G16 -> 21337.195 | H41: =H16 -> 19825.999 | I41: =I16 -> 23401.617 | K41: =SUM(B41:E41) -> 83276 | L41: =SUM(F41:I41) -> 87436.811
A42: D&A | B42: 3900 | C42: 4342 | D42: 4963 | E42: 5411 | F42: 5999 | G42: 6530 | H42: 7100 | I42: 7840 | K42: =SUM(B42:E42) -> 18616 | L42: =SUM(F42:I42) -> 27469
A43: EBITDA | B43: =SUM(B41:B42) -> 21455 | C43: =SUM(C41:C42) -> 24783 | D43: =SUM(D41:D42) -> 25498 | E43: =SUM(E41:E42) -> 30156 | F43: =SUM(F41:F42) -> 28871 | G43: =SUM(G41:G42) -> 27867.195 | H43: =SUM(H41:H42) -> 26925.999 | I43: =SUM(I41:I42) -> 31241.617 | K43: =SUM(B43:E43) -> 101892 | L43: =SUM(F43:I43) -> 114905.81
A44: Family daily active people (billions) | B44: 3.43 | C44: 3.48 | D44: 3.54 | E44: 3.58 | F44: 3.56 | G44: 3.6 | H44: 3.63 | I44: 3.66
A45: Family DAP growth | B45: 0.06 | C45: 0.06 | D45: 0.08 | E45: 0.07 | F45: 0.04 | G45: =G44/C44-1 -> 0.034482759 | H45: =H44/D44-1 -> 0.025423729 | I45: =I44/E44-1 -> 0.022346369
A46: Ad impressions growth | B46: 0.05 | C46: 0.11 | D46: 0.14 | E46: 0.18 | F46: 0.19 | G46: 0.15 | H46: 0.13 | I46: 0.11
A47: Average price per ad growth | B47: 0.1 | C47: 0.09 | D47: 0.1 | E47: 0.06 | F47: 0.12 | G47: 0.1 | H47: 0.09 | I47: 0.095
A48: Headcount | B48: 76834 | C48: 75945 | D48: 78450 | E48: 78865 | F48: 77986 | G48: 70500 | H48: 71500 | I48: 72500
A49: Family of Apps operating income | B49: 21765 | C49: 24971 | D49: 24967 | E49: 30766 | F49: 26900 | G49: =G16-G51 -> 26037.195 | H49: =H16-H51 -> 24525.999 | I49: =I16-I51 -> 29166.617 | K49: =SUM(B49:E49) -> 102469 | L49: =SUM(F49:I49) -> 106629.81
A50: Family of Apps operating margin | B50: =B49/B6 -> 0.51942628 | C50: =C49/C6 -> 0.52965257 | D50: =D49/D6 -> 0.49174742 | E50: =E49/E6 -> 0.52200618 | F50: =F49/F6 -> 0.48113899 | G50: =G49/G6 -> 0.43473436 | H50: =H49/H6 -> 0.39062848 | I50: =I49/I6 -> 0.40586633 | K50: =K49/K6 -> 0.51554654 | L50: =L49/L6 -> 0.42575321
A51: Reality Labs operating income (loss) | B51: -4210 | C51: -4530 | D51: -4432 | E51: -6021 | F51: -4028 | G51: -4700 | H51: -4700 | I51: -5765 | K51: =SUM(B51:E51) -> -19193 | L51: =SUM(F51:I51) -> -19193
A52: Reality Labs operating margin | B52: =B51/B7 -> -10.218447 | C52: =C51/C7 -> -12.243243 | D52: =D51/D7 -> -9.4297872 | E52: =E51/E7 -> -6.304712 | F52: =F51/F7 -> -10.0199 | G52: =G51/G7 -> -10.561798 | H52: =H51/H7 -> -8.7037037 | I52: =I51/I7 -> -5.2409091 | K52: =K51/K7 -> -8.6964205 | L52: =L51/L7 -> -7.7173301
A54: Free Cash Flow to Firm
A55: EBIT | B55: =B41 -> 17555 | C55: =C41 -> 20441 | D55: =D41 -> 20535 | E55: =E41 -> 24745 | F55: =F41 -> 22872 | G55: =G41 -> 21337.195 | H55: =H41 -> 19825.999 | I55: =I41 -> 23401.617 | K55: =SUM(B55:E55) -> 83276 | L55: =SUM(F55:I55) -> 87436.811
A56: Normalized operating tax rate | B56: 0.13 | C56: 0.13 | D56: 0.13 | E56: 0.13 | F56: 0.14 | G56: =G37 -> 0.145 | H56: =H37 -> 0.145 | I56: =I37 -> 0.145 | K56: =1-K57/K55 -> 0.13 | L56: =1-L57/L55 -> 0.14369208
A57: NOPAT | B57: =B55*(1-B56) -> 15272.85 | C57: =C55*(1-C56) -> 17783.67 | D57: =D55*(1-D56) -> 17865.45 | E57: =E55*(1-E56) -> 21528.15 | F57: =F55*(1-F56) -> 19669.92 | G57: =G55*(1-G56) -> 18243.302 | H57: =H55*(1-H56) -> 16951.229 | I57: =I55*(1-I56) -> 20008.382 | K57: =SUM(B57:E57) -> 72450.12 | L57: =SUM(F57:I57) -> 74872.833
A58: D&A | B58: =B42 -> 3900 | C58: =C42 -> 4342 | D58: =D42 -> 4963 | E58: =E42 -> 5411 | F58: =F42 -> 5999 | G58: =G42 -> 6530 | H58: =H42 -> 7100 | I58: =I42 -> 7840 | K58: =SUM(B58:E58) -> 18616 | L58: =SUM(F58:I58) -> 27469
A59: Capex | B59: 13692 | C59: 17012 | D59: 19374 | E59: 22137 | F59: 19840 | G59: 32000 | H59: 40000 | I59: 43160 | K59: =SUM(B59:E59) -> 72215 | L59: =SUM(F59:I59) -> 135000
A60: Accounts receivable, net | B60: =B77 -> 14514 | C60: =C77 -> 16561 | D60: =D77 -> 17297 | E60: =E77 -> 19769 | F60: =F77 -> 17470 | G60: =G77 -> 20100 | H60: =H77 -> 21600 | I60: =I77 -> 26400 | K60: =E60 -> 19769 | L60: =I60 -> 26400
A61: Prepaid expenses and other current assets | B61: =B78 -> 5483 | C61: =C78 -> 9981 | D61: =D78 -> 11373 | E61: =E78 -> 7361 | F61: =F78 -> 11115 | G61: =G78 -> 10500 | H61: =H78 -> 10000 | I61: =I78 -> 10500 | K61: =E61 -> 7361 | L61: =I61 -> 10500
A62: Operating current assets | B62: =SUM(B60:B61) -> 19997 | C62: =SUM(C60:C61) -> 26542 | D62: =SUM(D60:D61) -> 28670 | E62: =SUM(E60:E61) -> 27130 | F62: =SUM(F60:F61) -> 28585 | G62: =SUM(G60:G61) -> 30600 | H62: =SUM(H60:H61) -> 31600 | I62: =SUM(I60:I61) -> 36900 | K62: =E62 -> 27130 | L62: =I62 -> 36900
A63: Accounts payable | B63: =B88 -> 8512 | C63: =C88 -> 10271 | D63: =D88 -> 7798 | E63: =E88 -> 8894 | F63: =F88 -> 13326 | G63: =G88 -> 16000 | H63: =H88 -> 18500 | I63: =I88 -> 14000 | K63: =E63 -> 8894 | L63: =I63 -> 14000
A64: Operating lease liabilities, current | B64: =B89 -> 1976 | C64: =C89 -> 1977 | D64: =D89 -> 2113 | E64: =E89 -> 2213 | F64: =F89 -> 2414 | G64: =G89 -> 2500 | H64: =H89 -> 2600 | I64: =I89 -> 2700 | K64: =E64 -> 2213 | L64: =I64 -> 2700
A65: Accrued expenses and other current liabilities | B65: =B90 -> 23402 | C65: =C90 -> 25057 | D65: =D90 -> 27047 | E65: =E90 -> 30729 | F65: =F90 -> 31013 | G65: =G90 -> 33000 | H65: =H90 -> 35500 | I65: =I90 -> 38500 | K65: =E65 -> 30729 | L65: =I65 -> 38500
A66: Operating current liabilities | B66: =SUM(B63:B65) -> 33890 | C66: =SUM(C63:C65) -> 37305 | D66: =SUM(D63:D65) -> 36958 | E66: =SUM(E63:E65) -> 41836 | F66: =SUM(F63:F65) -> 46753 | G66: =SUM(G63:G65) -> 51500 | H66: =SUM(H63:H65) -> 56600 | I66: =SUM(I63:I65) -> 55200 | K66: =E66 -> 41836 | L66: =I66 -> 55200
A67: NOWC | B67: =B62-B66 -> -13893 | C67: =C62-C66 -> -10763 | D67: =D62-D66 -> -8288 | E67: =E62-E66 -> -14706 | F67: =F62-F66 -> -18168 | G67: =G62-G66 -> -20900 | H67: =H62-H66 -> -25000 | I67: =I62-I66 -> -18300 | K67: =E67 -> -14706 | L67: =I67 -> -18300
A68: Prior quarter NOWC | B68: -11366 | C68: =B67 -> -13893 | D68: =C67 -> -10763 | E68: =D67 -> -8288 | F68: =E67 -> -14706 | G68: =F67 -> -18168 | H68: =G67 -> -20900 | I68: =H67 -> -25000 | K68: =E68 -> -8288 | L68: =I68 -> -25000
A69: Investment in NOWC | B69: =B67-B68 -> -2527 | C69: =C67-C68 -> 3130 | D69: =D67-D68 -> 2475 | E69: =E67-E68 -> -6418 | F69: =F67-F68 -> -3462 | G69: =G67-G68 -> -2732 | H69: =H67-H68 -> -4100 | I69: =I67-I68 -> 6700 | K69: =E69 -> -6418 | L69: =I69 -> 6700
A70: FCFF | B70: =B57+B58-B59-B69 -> 8007.85 | C70: =C57+C58-C59-C69 -> 1983.67 | D70: =D57+D58-D59-D69 -> 979.45 | E70: =E57+E58-E59-E69 -> 11220.15 | F70: =F57+F58-F59-F69 -> 9290.92 | G70: =G57+G58-G59-G69 -> -4494.6983 | H70: =H57+H58-H59-H69 -> -11848.771 | I70: =I57+I58-I59-I69 -> -22011.618 | K70: =E70 -> 11220.15 | L70: =I70 -> -22011.618
A72: Balance Sheet
A73: Assets
A74: Cash and cash equivalents | B74: 28750 | C74: 12005 | D74: 10187 | E74: 35873 | F74: 23426
A75: Marketable securities | B75: 41480 | C75: 35066 | D75: 34261 | E75: 45719 | F75: 57754
A76: Total cash, cash equivalents, and marketable securities | B76: =SUM(B74:B75) -> 70230 | C76: =SUM(C74:C75) -> 47071 | D76: =SUM(D74:D75) -> 44448 | E76: =SUM(E74:E75) -> 81592 | F76: =SUM(F74:F75) -> 81180
A77: Accounts receivable, net | B77: 14514 | C77: 16561 | D77: 17297 | E77: 19769 | F77: 17470 | G77: 20100 | H77: 21600 | I77: 26400
A78: Prepaid expenses and other current assets | B78: 5483 | C78: 9981 | D78: 11373 | E78: 7361 | F78: 11115 | G78: 10500 | H78: 10000 | I78: 10500
A79: Total current assets | B79: =SUM(B76:B78) -> 90227 | C79: =SUM(C76:C78) -> 73613 | D79: =SUM(D76:D78) -> 73118 | E79: =SUM(E76:E78) -> 108722 | F79: =SUM(F76:F78) -> 109765
A80: Non-marketable equity investments | B80: 6168 | C80: 21988 | D80: 25074 | E80: 27524 | F80: 28410
A81: Property and equipment, net | B81: 133567 | C81: 147039 | D81: 160270 | E81: 176400 | F81: 194776
A82: Operating lease right-of-use assets | B82: 15505 | C82: 15662 | D82: 17372 | E82: 20404 | F82: 23268
A83: Goodwill | B83: 20654 | C83: 20654 | D83: 21158 | E83: 24534 | F83: 24748
A84: Other assets | B84: 14092 | C84: 15788 | D84: 6852 | E84: 8437 | F84: 14283
A85: Total assets | B85: =SUM(B79:B84) -> 280213 | C85: =SUM(C79:C84) -> 294744 | D85: =SUM(D79:D84) -> 303844 | E85: =SUM(E79:E84) -> 366021 | F85: =SUM(F79:F84) -> 395250
A87: Liabilities and Stockholders' Equity
A88: Accounts payable | B88: 8512 | C88: 10271 | D88: 7798 | E88: 8894 | F88: 13326 | G88: 16000 | H88: 18500 | I88: 14000
A89: Operating lease liabilities, current | B89: 1976 | C89: 1977 | D89: 2113 | E89: 2213 | F89: 2414 | G89: 2500 | H89: 2600 | I89: 2700
A90: Accrued expenses and other current liabilities | B90: 23402 | C90: 25057 | D90: 27047 | E90: 30729 | F90: 31013 | G90: 33000 | H90: 35500 | I90: 38500
A91: Total current liabilities | B91: =SUM(B88:B90) -> 33890 | C91: =SUM(C88:C90) -> 37305 | D91: =SUM(D88:D90) -> 36958 | E91: =SUM(E88:E90) -> 41836 | F91: =SUM(F88:F90) -> 46753 | G91: =SUM(G88:G90) -> 51500 | H91: =SUM(H88:H90) -> 56600 | I91: =SUM(I88:I90) -> 55200
A92: Operating lease liabilities, non-current | B92: 18714 | C92: 18751 | D92: 20113 | E92: 22940 | F92: 25607
A93: Long-term debt | B93: 28829 | C93: 28832 | D93: 28834 | E93: 58744 | F93: 58748
A94: Long-term income taxes | B94: 10991 | C94: 12046 | D94: 11738 | E94: 21005 | F94: 16849
A95: Other liabilities | B95: 2760 | C95: 2740 | D95: 12135 | E95: 4253 | F95: 3612
A96: Total liabilities | B96: =SUM(B91:B95) -> 95184 | C96: =SUM(C91:C95) -> 99674 | D96: =SUM(D91:D95) -> 109778 | E96: =SUM(E91:E95) -> 148778 | F96: =SUM(F91:F95) -> 151569
A98: Stockholders' Equity
A99: Common stock and additional paid-in capital | B99: 85568 | C99: 88496 | D99: 92330 | E99: 95793 | F99: 99337
A100: Accumulated other comprehensive income (loss) | B100: -1865 | C100: 229 | D100: 159 | E100: 271 | F100: -303
A101: Retained earnings | B101: 101326 | C101: 106345 | D101: 101577 | E101: 121179 | F101: 144647
A102: Total stockholders' equity | B102: =SUM(B99:B101) -> 185029 | C102: =SUM(C99:C101) -> 195070 | D102: =SUM(D99:D101) -> 194066 | E102: =SUM(E99:E101) -> 217243 | F102: =SUM(F99:F101) -> 243681
A103: Total liabilities and stockholders' equity | B103: =SUM(B96,B102) -> 280213 | C103: =SUM(C96,C102) -> 294744 | D103: =SUM(D96,D102) -> 303844 | E103: =SUM(E96,E102) -> 366021 | F103: =SUM(F96,F102) -> 395250

Sheet Segment Profitability
A1: Meta Platforms Segment Profitability
A2: USD in millions
A4: Segment Profitability
B5: Q125 | C5: Q225 | D5: Q325 | E5: Q425 | F5: Q126 | G5: Q226 | H5: Q326 | I5: Q426 | K5: FY25 | L5: FY26
A6: Family of Apps
A7: Advertising | B7: 41392 | C7: 46563 | D7: 50082 | E7: 58137 | F7: 55024 | G7: ='META Model'!G4 -> 58902.195 | H7: ='META Model'!H4 -> 61685.999 | I7: ='META Model'!I4 -> 70662.617 | K7: =SUM(B7:E7) -> 196174 | L7: =SUM(F7:I7) -> 246274.81
A8: Other revenue | B8: 510 | C8: 583 | D8: 690 | E8: 801 | F8: 885 | G8: ='META Model'!G5 -> 990 | H8: ='META Model'!H5 -> 1100 | I8: ='META Model'!I5 -> 1200 | K8: =SUM(B8:E8) -> 2584 | L8: =SUM(F8:I8) -> 4175
A9: Revenue | B9: =SUM(B7:B8) -> 41902 | C9: =SUM(C7:C8) -> 47146 | D9: =SUM(D7:D8) -> 50772 | E9: =SUM(E7:E8) -> 58938 | F9: =SUM(F7:F8) -> 55909 | G9: =SUM(G7:G8) -> 59892.195 | H9: =SUM(H7:H8) -> 62785.999 | I9: =SUM(I7:I8) -> 71862.617 | K9: =SUM(B9:E9) -> 198758 | L9: =SUM(F9:I9) -> 250449.81
A10: Revenue growth | B10: 0.16345967 | C10: 0.21767653 | D10: 0.25925742 | E10: 0.24599383 | F10: =F9/B9-1 -> 0.33427999 | G10: =G9/C9-1 -> 0.27035581 | H10: =H9/D9-1 -> 0.23662648 | I10: =I9/E9-1 -> 0.21929174 | L10: =L9/K9-1 -> 0.26007412
A11: Total costs and expenses | B11: =B9-B12 -> 20137 | C11: =C9-C12 -> 22175 | D11: =D9-D12 -> 25805 | E11: =E9-E12 -> 28172 | F11: =F9-F12 -> 29009 | G11: =G9-G12 -> 33855 | H11: =H9-H12 -> 38260 | I11: =I9-I12 -> 42696 | K11: =SUM(B11:E11) -> 96289 | L11: =SUM(F11:I11) -> 143820
A12: Operating income | B12: 21765 | C12: 24971 | D12: 24967 | E12: 30766 | F12: 26900 | G12: ='META Model'!G49 -> 26037.195 | H12: ='META Model'!H49 -> 24525.999 | I12: ='META Model'!I49 -> 29166.617 | K12: =SUM(B12:E12) -> 102469 | L12: =SUM(F12:I12) -> 106629.81
A13: Operating income growth | B13: 0.23216712 | C13: 0.29149211 | D13: 0.14643218 | E13: 0.085909925 | F13: =F12/B12-1 -> 0.23592924 | G13: =G12/C12-1 -> 0.042697329 | H13: =H12/D12-1 -> -0.01766334 | I13: =I12/E12-1 -> -0.051985417 | L13: =L12/K12-1 -> 0.040605559
A14: Operating margin | B14: =B12/B9 -> 0.51942628 | C14: =C12/C9 -> 0.52965257 | D14: =D12/D9 -> 0.49174742 | E14: =E12/E9 -> 0.52200618 | F14: =F12/F9 -> 0.48113899 | G14: =G12/G9 -> 0.43473436 | H14: =H12/H9 -> 0.39062848 | I14: =I12/I9 -> 0.40586633 | K14: =K12/K9 -> 0.51554654 | L14: =L12/L9 -> 0.42575321
A16: Reality Labs
A17: Revenue | B17: 412 | C17: 370 | D17: 470 | E17: 955 | F17: 402 | G17: ='META Model'!G7 -> 445 | H17: ='META Model'!H7 -> 540 | I17: ='META Model'!I7 -> 1100 | K17: =SUM(B17:E17) -> 2207 | L17: =SUM(F17:I17) -> 2487
A18: Revenue growth | B18: -0.063636364 | C18: 0.04815864 | D18: 0.74074074 | E18: -0.11819021 | F18: =F17/B17-1 -> -0.024271845 | G18: =G17/C17-1 -> 0.2027027 | H18: =H17/D17-1 -> 0.14893617 | I18: =I17/E17-1 -> 0.15183246 | L18: =L17/K17-1 -> 0.12686905
A19: Total costs and expenses | B19: =B17-B20 -> 4622 | C19: =C17-C20 -> 4900 | D19: =D17-D20 -> 4902 | E19: =E17-E20 -> 6976 | F19: =F17-F20 -> 4430 | G19: =G17-G20 -> 5145 | H19: =H17-H20 -> 5240 | I19: =I17-I20 -> 6865 | K19: =SUM(B19:E19) -> 21400 | L19: =SUM(F19:I19) -> 21680
A20: Operating income (loss) | B20: -4210 | C20: -4530 | D20: -4432 | E20: -6021 | F20: -4028 | G20: ='META Model'!G51 -> -4700 | H20: ='META Model'!H51 -> -4700 | I20: ='META Model'!I51 -> -5765 | K20: =SUM(B20:E20) -> -19193 | L20: =SUM(F20:I20) -> -19193
A21: Operating margin | B21: =B20/B17 -> -10.218447 | C21: =C20/C17 -> -12.243243 | D21: =D20/D17 -> -9.4297872 | E21: =E20/E17 -> -6.304712 | F21: =F20/F17 -> -10.0199 | G21: =G20/G17 -> -10.561798 | H21: =H20/H17 -> -8.7037037 | I21: =I20/I17 -> -5.2409091 | K21: =K20/K17 -> -8.6964205 | L21: =L20/L17 -> -7.7173301
A23: Consolidated Reconciliation
A24: Family of Apps revenue | B24: =B9 -> 41902 | C24: =C9 -> 47146 | D24: =D9 -> 50772 | E24: =E9 -> 58938 | F24: =F9 -> 55909 | G24: =G9 -> 59892.195 | H24: =H9 -> 62785.999 | I24: =I9 -> 71862.617 | K24: =SUM(B24:E24) -> 198758 | L24: =SUM(F24:I24) -> 250449.81
A25: Reality Labs revenue | B25: =B17 -> 412 | C25: =C17 -> 370 | D25: =D17 -> 470 | E25: =E17 -> 955 | F25: =F17 -> 402 | G25: =G17 -> 445 | H25: =H17 -> 540 | I25: =I17 -> 1100 | K25: =SUM(B25:E25) -> 2207 | L25: =SUM(F25:I25) -> 2487
A26: Total revenue | B26: =SUM(B24:B25) -> 42314 | C26: =SUM(C24:C25) -> 47516 | D26: =SUM(D24:D25) -> 51242 | E26: =SUM(E24:E25) -> 59893 | F26: =SUM(F24:F25) -> 56311 | G26: =SUM(G24:G25) -> 60337.195 | H26: =SUM(H24:H25) -> 63325.999 | I26: =SUM(I24:I25) -> 72962.617 | K26: =SUM(B26:E26) -> 200965 | L26: =SUM(F26:I26) -> 252936.81
A27: Family of Apps operating income | B27: =B12 -> 21765 | C27: =C12 -> 24971 | D27: =D12 -> 24967 | E27: =E12 -> 30766 | F27: =F12 -> 26900 | G27: =G12 -> 26037.195 | H27: =H12 -> 24525.999 | I27: =I12 -> 29166.617 | K27: =SUM(B27:E27) -> 102469 | L27: =SUM(F27:I27) -> 106629.81
A28: Reality Labs operating income (loss) | B28: =B20 -> -4210 | C28: =C20 -> -4530 | D28: =D20 -> -4432 | E28: =E20 -> -6021 | F28: =F20 -> -4028 | G28: =G20 -> -4700 | H28: =H20 -> -4700 | I28: =I20 -> -5765 | K28: =SUM(B28:E28) -> -19193 | L28: =SUM(F28:I28) -> -19193
A29: Total income from operations | B29: =SUM(B27:B28) -> 17555 | C29: =SUM(C27:C28) -> 20441 | D29: =SUM(D27:D28) -> 20535 | E29: =SUM(E27:E28) -> 24745 | F29: =SUM(F27:F28) -> 22872 | G29: =SUM(G27:G28) -> 21337.195 | H29: =SUM(H27:H28) -> 19825.999 | I29: =SUM(I27:I28) -> 23401.617 | K29: =SUM(B29:E29) -> 83276 | L29: =SUM(F29:I29) -> 87436.811
A30: Operating income growth | B30: 0.27044435 | C30: 0.37677645 | D30: 0.18357349 | E30: 0.059062701 | F30: =F29/B29-1 -> 0.30287667 | G30: =G29/C29-1 -> 0.043843012 | H30: =H29/D29-1 -> -0.034526448 | I30: =I29/E29-1 -> -0.054289083 | L30: =L29/K29-1 -> 0.049964108
A31: Operating margin | B31: =B29/B26 -> 0.41487451 | C31: =C29/C26 -> 0.43019194 | D31: =D29/D26 -> 0.40074548 | E31: =E29/E26 -> 0.41315346 | F31: =F29/F26 -> 0.40617286 | G31: =G29/G26 -> 0.35363253 | H31: =H29/H26 -> 0.31307835 | I31: =I29/I26 -> 0.32073434 | K31: =K29/K26 -> 0.41438061 | L31: =L29/L26 -> 0.34568638
A33: Profitability Summary
B34: Q125 | C34: Q225 | D34: Q325 | E34: Q425 | F34: Q126 | G34: Q226 | H34: Q326 | I34: Q426 | K34: FY25 | L34: FY26
A35: Family of Apps operating margin | B35: =B14 -> 0.51942628 | C35: =C14 -> 0.52965257 | D35: =D14 -> 0.49174742 | E35: =E14 -> 0.52200618 | F35: =F14 -> 0.48113899 | G35: =G14 -> 0.43473436 | H35: =H14 -> 0.39062848 | I35: =I14 -> 0.40586633 | K35: =K14 -> 0.51554654 | L35: =L14 -> 0.42575321
A36: Reality Labs operating margin | B36: =B21 -> -10.218447 | C36: =C21 -> -12.243243 | D36: =D21 -> -9.4297872 | E36: =E21 -> -6.304712 | F36: =F21 -> -10.0199 | G36: =G21 -> -10.561798 | H36: =H21 -> -8.7037037 | I36: =I21 -> -5.2409091 | K36: =K21 -> -8.6964205 | L36: =L21 -> -7.7173301
A37: Consolidated operating margin | B37: =B31 -> 0.41487451 | C37: =C31 -> 0.43019194 | D37: =D31 -> 0.40074548 | E37: =E31 -> 0.41315346 | F37: =F31 -> 0.40617286 | G37: =G31 -> 0.35363253 | H37: =H31 -> 0.31307835 | I37: =I31 -> 0.32073434 | K37: =K31 -> 0.41438061 | L37: =L31 -> 0.34568638
A39: Family of Apps revenue mix | B39: =B24/B26 -> 0.99026327 | C39: =C24/C26 -> 0.99221315 | D39: =D24/D26 -> 0.99082784 | E39: =E24/E26 -> 0.9840549 | F39: =F24/F26 -> 0.99286108 | G39: =G24/G26 -> 0.99262478 | H39: =H24/H26 -> 0.9914727 | I39: =I24/I26 -> 0.98492379 | K39: =K24/K26 -> 0.98901799 | L39: =L24/L26 -> 0.9901675
A40: Reality Labs revenue mix | B40: =B25/B26 -> 0.0097367302 | C40: =C25/C26 -> 0.0077868507 | D40: =D25/D26 -> 0.0091721635 | E40: =E25/E26 -> 0.015945102 | F40: =F25/F26 -> 0.0071389249 | G40: =G25/G26 -> 0.0073752186 | H40: =H25/H26 -> 0.0085273032 | I40: =I25/I26 -> 0.015076214 | K40: =K25/K26 -> 0.010982012 | L40: =L25/L26 -> 0.0098324953
A41: Advertising as % of total revenue | B41: =B7/B26 -> 0.97821052 | C41: =C7/C26 -> 0.9799436 | D41: =D7/D26 -> 0.97736232 | E41: =E7/E26 -> 0.97068105 | F41: =F7/F26 -> 0.97714479 | G41: =G7/G26 -> 0.97621699 | H41: =H7/H26 -> 0.97410226 | I41: =I7/I26 -> 0.96847701 | K41: =K7/K26 -> 0.97616003 | L41: =L7/L26 -> 0.97366141
