Workbook

Sheet Financials
A1: MRVL — Equity Research Model
A2: All figures in $mm unless noted | Blue = forecast
B3: Q2FY23 | C3: Q3FY23 | D3: Q4FY23 | E3: Q1FY24 | F3: Q2FY24 | G3: Q3FY24 | H3: Q4FY24 | I3: Q1FY25 | J3: Q2FY25 | K3: Q3FY25 | L3: Q4FY25 | M3: Q1FY26 | N3: Q2FY26 | O3: Q3FY26 | P3: Q4FY26 | Q3: Q1FY27 | R3: Q2FY27E | S3: Q3FY27E | T3: Q4FY27E | U3: Q1FY28E | V3: Q2FY28E | W3: Q3FY28E | X3: Q4FY28E | Y3: Q1FY29E
A4: Stock
A5: Current Stock Price | B5: 290.79
A6: Market Cap ($mm) | B6: =$B$5*$Q$37
A7: Cash ($mm) | B7: =Q48+Q49
A8: Debt ($mm) | B8: =Q62+Q63+Q67
A9: Enterprise Value ($mm) | B9: =$B$6+$B$8-$B$7
A10: Trailing P/E | B10: =$B$5/($N$35+$O$35+$P$35+$Q$35)
A11: Trailing EV/EBIT | B11: =$B$9/($N$39+$O$39+$P$39+$Q$39)
A12: Trailing EV/EBITDA | B12: =$B$9/($N$40+$O$40+$P$40+$Q$40)
A13: Trailing EV/FCFE | B13: =$B$9/($N$109+$O$109+$P$109+$Q$109)
A14: EPS Yield | B14: =($N$35+$O$35+$P$35+$Q$35)/($B$5)
A16: INCOME STATEMENT
B17: Q2FY23 | C17: Q3FY23 | D17: Q4FY23 | E17: Q1FY24 | F17: Q2FY24 | G17: Q3FY24 | H17: Q4FY24 | I17: Q1FY25 | J17: Q2FY25 | K17: Q3FY25 | L17: Q4FY25 | M17: Q1FY26 | N17: Q2FY26 | O17: Q3FY26 | P17: Q4FY26 | Q17: Q1FY27 | R17: Q2FY27E | S17: Q3FY27E | T17: Q4FY27E | U17: Q1FY28E | V17: Q2FY28E | W17: Q3FY28E | X17: Q4FY28E | Y17: Q1FY29E
A18: Total Revenue | B18: 1516.9 | C18: 1537.3 | D18: 1418.5 | E18: 1321.7 | F18: 1340.9 | G18: 1418.6 | H18: 1426.5 | I18: 1160.9 | J18: 1272.9 | K18: 1516.1 | L18: 1817.4 | M18: 1895.3 | N18: 2006.1 | O18: 2074.5 | P18: 2218.7 | Q18: 2417.8 | R18: ='Assumptions'!$R$5 | S18: ='Assumptions'!$S$5 | T18: ='Assumptions'!$T$5 | U18: ='Assumptions'!$U$5 | V18: ='Assumptions'!$V$5 | W18: ='Assumptions'!$W$5 | X18: ='Assumptions'!$X$5 | Y18: ='Assumptions'!$Y$5
A19: Cost of Revenue | B19: 730.9 | C19: 760 | D19: 745.2 | E19: 764.5 | F19: 819.8 | G19: 867.4 | H19: 762.4 | I19: 633.1 | J19: 685.3 | K19: 1166.7 | L19: 900 | M19: 942.9 | N19: 995.5 | O19: 1004.7 | P19: 1070.8 | Q19: 1157 | R19: =$R$18*(1-'Assumptions'!$R$9) | S19: =$S$18*(1-'Assumptions'!$S$9) | T19: =$T$18*(1-'Assumptions'!$T$9) | U19: =$U$18*(1-'Assumptions'!$U$9) | V19: =$V$18*(1-'Assumptions'!$V$9) | W19: =$W$18*(1-'Assumptions'!$W$9) | X19: =$X$18*(1-'Assumptions'!$X$9) | Y19: =$Y$18*(1-'Assumptions'!$Y$9)
A20: Gross Profit | B20: 786 | C20: 777.3 | D20: 673.3 | E20: 557.2 | F20: 521.1 | G20: 551.2 | H20: 664.1 | I20: 527.8 | J20: 587.6 | K20: 349.4 | L20: 917.4 | M20: 952.4 | N20: 1010.6 | O20: 1069.8 | P20: 1147.9 | Q20: 1260.8 | R20: =$R$18-$R$19 | S20: =$S$18-$S$19 | T20: =$T$18-$T$19 | U20: =$U$18-$U$19 | V20: =$V$18-$V$19 | W20: =$W$18-$W$19 | X20: =$X$18-$X$19 | Y20: =$Y$18-$Y$19
A21: -- Gross Margin % | B21: 0.51816204 | C21: 0.50562675 | D21: 0.47465633 | E21: 0.42157827 | F21: 0.38861958 | G21: 0.38855209 | H21: 0.46554504 | I21: 0.45464726 | J21: 0.46162307 | K21: 0.23045973 | L21: 0.50478706 | M21: 0.5025062 | N21: 0.50376352 | O21: 0.51569053 | P21: 0.51737504 | Q21: 0.5214658 | R21: =$R$20/$R$18 | S21: =$S$20/$S$18 | T21: =$T$20/$T$18 | U21: =$U$20/$U$18 | V21: =$V$20/$V$18 | W21: =$W$20/$W$18 | X21: =$X$20/$X$18 | Y21: =$Y$20/$Y$18
A22: Research & Development | B22: 449 | C22: 448.1 | D22: 443.1 | E22: 480.7 | F22: 474.8 | G22: 481.1 | H22: 459.6 | I22: 476.1 | J22: 486.7 | K22: 488.6 | L22: 499 | M22: 507.7 | N22: 519 | O22: 512.5 | P22: 536 | Q22: 652.3 | R22: ='Assumptions'!$R$11 | S22: ='Assumptions'!$S$11 | T22: ='Assumptions'!$T$11 | U22: ='Assumptions'!$U$11 | V22: ='Assumptions'!$V$11 | W22: ='Assumptions'!$W$11 | X22: ='Assumptions'!$X$11 | Y22: ='Assumptions'!$Y$11
A23: Sales, General & Administrative | B23: 211.7 | C23: 207.8 | D23: 203.4 | E23: 199 | F23: 210 | G23: 213 | H23: 212 | I23: 199.9 | J23: 197.3 | K23: 205.3 | L23: 195.7 | M23: 186.4 | N23: 192.8 | O23: 189.9 | P23: 198 | Q23: 258.4 | R23: ='Assumptions'!$R$13 | S23: ='Assumptions'!$S$13 | T23: ='Assumptions'!$T$13 | U23: ='Assumptions'!$U$13 | V23: ='Assumptions'!$V$13 | W23: ='Assumptions'!$W$13 | X23: ='Assumptions'!$X$13 | Y23: ='Assumptions'!$Y$13
A24: Total Operating Expenses | R24: =$R$22+$R$23 | S24: =$S$22+$S$23 | T24: =$T$22+$T$23 | U24: =$U$22+$U$23 | V24: =$V$22+$V$23 | W24: =$W$22+$W$23 | X24: =$X$22+$X$23 | Y24: =$Y$22+$Y$23
A25: Operating Income (EBIT) | B25: 39.1 | C25: 105.8 | D25: 23.3 | E25: -182.4 | F25: -205.7 | G25: -146.3 | H25: -33.3 | I25: -152.3 | J25: -100.4 | K25: -702.8 | L25: 235.2 | M25: 270.6 | N25: 290.1 | O25: 357.8 | P25: 404.4 | Q25: 339.4 | R25: =$R$20-$R$24 | S25: =$S$20-$S$24 | T25: =$T$20-$T$24 | U25: =$U$20-$U$24 | V25: =$V$20-$V$24 | W25: =$W$20-$W$24 | X25: =$X$20-$X$24 | Y25: =$Y$20-$Y$24
A26: -- Operating Margin % | B26: 0.025776254 | C26: 0.068821961 | D26: 0.016425802 | E26: -0.13800409 | F26: -0.15340443 | G26: -0.10312985 | H26: -0.023343849 | I26: -0.13119132 | J26: -0.07887501 | K26: -0.46355781 | L26: 0.12941565 | M26: 0.14277423 | N26: 0.14460894 | O26: 0.1724753 | P26: 0.1822689 | Q26: 0.14037555 | R26: =$R$25/$R$18 | S26: =$S$25/$S$18 | T26: =$T$25/$T$18 | U26: =$U$25/$U$18 | V26: =$V$25/$V$18 | W26: =$W$25/$W$18 | X26: =$X$25/$X$18 | Y26: =$Y$25/$Y$18
A27: Interest Income | B27: 0.8 | C27: 1.5 | D27: 2.5 | E27: 2.5 | F27: 1.6 | G27: 1.7 | H27: 3 | R27: ='Assumptions'!$R$22 | S27: ='Assumptions'!$S$22 | T27: ='Assumptions'!$T$22 | U27: ='Assumptions'!$U$22 | V27: ='Assumptions'!$V$22 | W27: ='Assumptions'!$W$22 | X27: ='Assumptions'!$X$22 | Y27: ='Assumptions'!$Y$22
A28: Interest Expense | B28: 37.4 | C28: 42.4 | D28: 46.9 | E28: 50.5 | F28: 51.9 | G28: 49.6 | H28: 50.9 | I28: 46.8 | J28: 46.5 | K28: 45.6 | L28: 44.1 | M28: 44.8 | N28: 46.8 | O28: 47.9 | P28: 47.8 | Q28: 50 | R28: ='Assumptions'!$R$23 | S28: ='Assumptions'!$S$23 | T28: ='Assumptions'!$T$23 | U28: ='Assumptions'!$U$23 | V28: ='Assumptions'!$V$23 | W28: ='Assumptions'!$W$23 | X28: ='Assumptions'!$X$23 | Y28: ='Assumptions'!$Y$23
A29: Other Income (Expense), net | D29: -152.9 | E29: -49.9 | F29: -45.9 | G29: -41.2 | H29: -54 | I29: -45.5 | J29: -45.8 | K29: -47.7 | L29: -35.4 | M29: -54.7 | N29: -56.4 | O29: 1857.6 | P29: -22.8 | Q29: -256.1 | R29: =0 | S29: =0 | T29: =0 | U29: =0 | V29: =0 | W29: =0 | X29: =0 | Y29: =0
A30: Pretax Income | B30: 3.8 | C30: 65.3 | D30: -23.2 | E30: -232.3 | F30: -251.6 | G30: -187.5 | H30: -87.3 | I30: -197.8 | J30: -146.2 | K30: -750.5 | L30: 199.8 | M30: 215.9 | N30: 233.7 | O30: 2215.4 | P30: 381.6 | Q30: 83.3 | R30: =$R$25+$R$27-$R$28+$R$29 | S30: =$S$25+$S$27-$S$28+$S$29 | T30: =$T$25+$T$27-$T$28+$T$29 | U30: =$U$25+$U$27-$U$28+$U$29 | V30: =$V$25+$V$27-$V$28+$V$29 | W30: =$W$25+$W$27-$W$28+$W$29 | X30: =$X$25+$X$27-$X$28+$X$29 | Y30: =$Y$25+$Y$27-$Y$28+$Y$29
A31: Income Tax Expense | B31: -0.5 | C31: 52 | D31: -7.8 | E31: -63.4 | F31: -44.1 | G31: -23.2 | H31: 305.4 | I31: 17.8 | J31: 47.1 | K31: -74.2 | L31: -0.4 | M31: 38 | N31: 38.9 | O31: 314.1 | P31: -14.5 | Q31: 48.8 | R31: =$R$30*'Assumptions'!$R$24 | S31: =$S$30*'Assumptions'!$S$24 | T31: =$T$30*'Assumptions'!$T$24 | U31: =$U$30*'Assumptions'!$U$24 | V31: =$V$30*'Assumptions'!$V$24 | W31: =$W$30*'Assumptions'!$W$24 | X31: =$X$30*'Assumptions'!$X$24 | Y31: =$Y$30*'Assumptions'!$Y$24
A32: -- Effective Tax Rate % | B32: -0.13157895 | C32: 0.79632466 | D32: 0.3362069 | E32: 0.27292294 | F32: 0.17527822 | G32: 0.12373333 | H32: -3.4982818 | I32: -0.089989889 | J32: -0.32216142 | K32: 0.098867422 | L32: -0.002002002 | M32: 0.17600741 | N32: 0.16645272 | O32: 0.14178027 | P32: -0.037997904 | Q32: 0.58583433 | R32: ='Assumptions'!$R$24 | S32: ='Assumptions'!$S$24 | T32: ='Assumptions'!$T$24 | U32: ='Assumptions'!$U$24 | V32: ='Assumptions'!$V$24 | W32: ='Assumptions'!$W$24 | X32: ='Assumptions'!$X$24 | Y32: ='Assumptions'!$Y$24
A33: Net Income | B33: 4.3 | C33: 13.3 | D33: -15.4 | E33: -168.9 | F33: -207.5 | G33: -164.3 | H33: -392.7 | I33: -215.6 | J33: -193.3 | K33: -676.3 | L33: 200.2 | M33: 177.9 | N33: 194.8 | O33: 1901.3 | P33: 396.1 | Q33: 34.5 | R33: =$R$30-$R$31 | S33: =$S$30-$S$31 | T33: =$T$30-$T$31 | U33: =$U$30-$U$31 | V33: =$V$30-$V$31 | W33: =$W$30-$W$31 | X33: =$X$30-$X$31 | Y33: =$Y$30-$Y$31
A34: EPS (Basic) | B34: 0.01 | C34: 0.02 | D34: -0.018 | E34: -0.2 | F34: -0.24 | G34: -0.19 | H34: -0.454 | I34: -0.25 | J34: -0.22 | K34: -0.78 | L34: 0.2313 | M34: 0.21 | N34: 0.23 | O34: 2.22 | P34: 0.4602 | Q34: 0.04
A35: EPS (Diluted) | B35: 0.01 | C35: 0.02 | D35: -0.0183 | E35: -0.2 | F35: -0.24 | G35: -0.19 | H35: -0.454 | I35: -0.25 | J35: -0.22 | K35: -0.78 | L35: 0.2313 | M35: 0.2 | N35: 0.22 | O35: 2.2 | P35: 0.4558 | Q35: 0.04
A36: Shares (Basic, mm) | B36: 850.9 | C36: 852.6 | D36: 854.1 | E36: 856.7 | F36: 860.9 | G36: 862.6 | H36: 865 | I36: 865 | J36: 865.7 | K36: 865.7 | L36: 865.6 | M36: 864.8 | N36: 862.6 | O36: 855.8 | P36: 860.8 | Q36: 882 | R36: ='Assumptions'!$R$28 | S36: ='Assumptions'!$S$28 | T36: ='Assumptions'!$T$28 | U36: ='Assumptions'!$U$28 | V36: ='Assumptions'!$V$28 | W36: ='Assumptions'!$W$28 | X36: ='Assumptions'!$X$28 | Y36: ='Assumptions'!$Y$28
A37: Shares (Diluted, mm) | B37: 857.9 | C37: 858.4 | D37: 841.3 | E37: 856.7 | F37: 860.9 | G37: 862.6 | H37: 865 | I37: 865 | J37: 865.7 | K37: 865.7 | L37: 865.6 | M37: 875.6 | N37: 870.4 | O37: 863.7 | P37: 869.1 | Q37: 893.3 | R37: ='Assumptions'!$R$26 | S37: ='Assumptions'!$S$26 | T37: ='Assumptions'!$T$26 | U37: ='Assumptions'!$U$26 | V37: ='Assumptions'!$V$26 | W37: ='Assumptions'!$W$26 | X37: ='Assumptions'!$X$26 | Y37: ='Assumptions'!$Y$26
A38: NON-GAAP KPIs
A39: Clean EBIT | B39: 39.1 | C39: 105.8 | D39: 23.3 | E39: -182.4 | F39: -205.7 | G39: -146.3 | H39: -33.3 | I39: -152.3 | J39: -100.4 | K39: -702.8 | L39: 235.2 | M39: 270.6 | N39: 290.1 | O39: 357.8 | P39: 404.4 | Q39: 339.4 | R39: =$R$25 | S39: =$S$25 | T39: =$T$25 | U39: =$U$25 | V39: =$V$25 | W39: =$W$25 | X39: =$X$25 | Y39: =$Y$25
A40: Clean EBITDA | B40: 387.8 | C40: 450.1 | D40: 374.4 | E40: 166 | F40: 141.6 | G40: 195.6 | H40: 326.8 | I40: 185.2 | J40: 251.6 | K40: -361.3 | L40: 561.1 | M40: 600.5 | N40: 617.9 | O40: 673.7 | P40: 721.4 | Q40: 660
A41: Depreciation & Amortization | B41: 348.7 | C41: 344.3 | D41: 351.1 | E41: 348.4 | F41: 347.3 | G41: 341.9 | H41: 360.1 | I41: 337.5 | J41: 352 | K41: 341.5 | L41: 325.9 | M41: 329.9 | N41: 327.8 | O41: 315.9 | P41: 317 | Q41: 320.6 | R41: ='Assumptions'!$R$16 | S41: ='Assumptions'!$S$16 | T41: ='Assumptions'!$T$16 | U41: ='Assumptions'!$U$16 | V41: ='Assumptions'!$V$16 | W41: ='Assumptions'!$W$16 | X41: ='Assumptions'!$X$16 | Y41: ='Assumptions'!$Y$16
A42: Normalized Earnings | B42: 2.2 | C42: 11.4 | D42: -15.8 | E42: -169.5 | F42: -213.5 | G42: -172.7 | H42: -389.6 | I42: -216.9 | J42: -194 | K42: -674.2 | L42: 191.5 | M42: 187.8 | N42: 204.4 | O42: -4.2 | P42: 371.1 | Q42: 240.6 | R42: =$R$39-$R$28-$R$31 | S42: =$S$39-$S$28-$S$31 | T42: =$T$39-$T$28-$T$31 | U42: =$U$39-$U$28-$U$31 | V42: =$V$39-$V$28-$V$31 | W42: =$W$39-$W$28-$W$31 | X42: =$X$39-$X$28-$X$31 | Y42: =$Y$39-$Y$28-$Y$31
A43: Clean EPS | B43: 0.0025644014 | C43: 0.013280522 | D43: -0.018780459 | E43: -0.19785222 | F43: -0.24799628 | G43: -0.20020867 | H43: -0.45040462 | I43: -0.25075145 | J43: -0.22409611 | K43: -0.77879173 | L43: 0.22123383 | M43: 0.2144815 | N43: 0.23483456 | O43: -0.0048627996 | P43: 0.42699344 | Q43: 0.26933841 | R43: =$R$42/$R$37 | S43: =$S$42/$S$37 | T43: =$T$42/$T$37 | U43: =$U$42/$U$37 | V43: =$V$42/$V$37 | W43: =$W$42/$W$37 | X43: =$X$42/$X$37 | Y43: =$Y$42/$Y$37
A45: BALANCE SHEET
B46: Q2FY23 | C46: Q3FY23 | D46: Q4FY23 | E46: Q1FY24 | F46: Q2FY24 | G46: Q3FY24 | H46: Q4FY24 | I46: Q1FY25 | J46: Q2FY25 | K46: Q3FY25 | L46: Q4FY25 | M46: Q1FY26 | N46: Q2FY26 | O46: Q3FY26 | P46: Q4FY26 | Q46: Q1FY27 | R46: Q2FY27E | S46: Q3FY27E | T46: Q4FY27E | U46: Q1FY28E | V46: Q2FY28E | W46: Q3FY28E | X46: Q4FY28E | Y46: Q1FY29E
A47: ASSETS
A48: Cash & Equivalents | B48: 617.1 | C48: 723.4 | D48: 911 | E48: 1028.3 | F48: 423.4 | G48: 725.6 | H48: 950.8 | I48: 847.7 | J48: 808.7 | K48: 868.1 | L48: 948.3 | M48: 885.9 | N48: 1224.4 | O48: 2714.5 | P48: 2638.8 | Q48: 3843.6
A49: Short-term Investments | R49: =$Q$49 | S49: =$R$49 | T49: =$S$49 | U49: =$T$49 | V49: =$U$49 | W49: =$V$49 | X49: =$W$49 | Y49: =$X$49
A50: Accounts Receivable, net | B50: 1291.3 | C50: 1390.7 | D50: 1192.2 | E50: 1000.9 | F50: 1209.2 | G50: 1214.6 | H50: 1121.6 | I50: 881.9 | J50: 1060.1 | K50: 997.9 | L50: 1028.4 | M50: 1144 | N50: 1451.7 | O50: 1546.3 | P50: 2186.6 | Q50: 1871.7 | R50: =$R$18/91*'Assumptions'!$R$30 | S50: =$S$18/91*'Assumptions'!$S$30 | T50: =$T$18/91*'Assumptions'!$T$30 | U50: =$U$18/91*'Assumptions'!$U$30 | V50: =$V$18/91*'Assumptions'!$V$30 | W50: =$W$18/91*'Assumptions'!$W$30 | X50: =$X$18/91*'Assumptions'!$X$30 | Y50: =$Y$18/91*'Assumptions'!$Y$30
A51: Inventories | B51: 913.1 | C51: 957.5 | D51: 1068.3 | E51: 1026 | F51: 1015.8 | G51: 941.5 | H51: 864.4 | I51: 826.4 | J51: 817.8 | K51: 859.4 | L51: 1029.7 | M51: 1071.4 | N51: 1051.6 | O51: 1014.5 | P51: 1388 | Q51: 1400.9 | R51: =$R$19/91*'Assumptions'!$R$31 | S51: =$S$19/91*'Assumptions'!$S$31 | T51: =$T$19/91*'Assumptions'!$T$31 | U51: =$U$19/91*'Assumptions'!$U$31 | V51: =$V$19/91*'Assumptions'!$V$31 | W51: =$W$19/91*'Assumptions'!$W$31 | X51: =$X$19/91*'Assumptions'!$X$31 | Y51: =$Y$19/91*'Assumptions'!$Y$31
A52: Prepaid Expenses & Other Current Assets | B52: 93.5 | C52: 107.7 | D52: 109.6 | E52: 147.7 | F52: 118.8 | G52: 91.5 | H52: 125.9 | I52: 91.7 | J52: 77.3 | K52: 91.4 | L52: 113.9 | M52: 148.1 | N52: 189.7 | O52: 237.2 | P52: 247.2 | Q52: 347.8
A53: Total Current Assets | B53: 2915 | C53: 3179.3 | D53: 3281.1 | E53: 3202.9 | F53: 2767.2 | G53: 2973.2 | H53: 3062.7 | I53: 2647.7 | J53: 2763.9 | K53: 2816.8 | L53: 3120.3 | M53: 3837.6 | N53: 4512.9 | O53: 5512.5 | P53: 6460.6 | Q53: 7464 | R53: =SUM($R$48,$R$49,$R$50,$R$51,$R$52) | S53: =SUM($S$48,$S$49,$S$50,$S$51,$S$52) | T53: =SUM($T$48,$T$49,$T$50,$T$51,$T$52) | U53: =SUM($U$48,$U$49,$U$50,$U$51,$U$52) | V53: =SUM($V$48,$V$49,$V$50,$V$51,$V$52) | W53: =SUM($W$48,$W$49,$W$50,$W$51,$W$52) | X53: =SUM($X$48,$X$49,$X$50,$X$51,$X$52) | Y53: =SUM($Y$48,$Y$49,$Y$50,$Y$51,$Y$52)
A54: PP&E, net | B54: 508.2 | C54: 521.5 | D54: 577.4 | E54: 636.2 | F54: 693.8 | G54: 701.6 | H54: 756 | I54: 758 | J54: 781.5 | K54: 781.9 | L54: 790.5 | M54: 774.7 | N54: 794.5 | O54: 854.8 | P54: 935 | Q54: 972.5 | R54: =$Q$54+'Assumptions'!$R$17-'Assumptions'!$R$16 | S54: =$R$54+'Assumptions'!$S$17-'Assumptions'!$S$16 | T54: =$S$54+'Assumptions'!$T$17-'Assumptions'!$T$16 | U54: =$T$54+'Assumptions'!$U$17-'Assumptions'!$U$16 | V54: =$U$54+'Assumptions'!$V$17-'Assumptions'!$V$16 | W54: =$V$54+'Assumptions'!$W$17-'Assumptions'!$W$16 | X54: =$W$54+'Assumptions'!$X$17-'Assumptions'!$X$16 | Y54: =$X$54+'Assumptions'!$Y$17-'Assumptions'!$Y$16
A55: Goodwill | B55: 11579 | C55: 11579 | D55: 11586.9 | E55: 11586.9 | F55: 11586.9 | G55: 11586.9 | H55: 11586.9 | I55: 11586.9 | J55: 11586.9 | K55: 11586.9 | L55: 11586.9 | M55: 11062.2 | N55: 11062.2 | O55: 11062.2 | P55: 11062.2 | Q55: 13883.5
A56: Intangible Assets, net | B56: 5642.5 | C56: 5372.6 | D56: 5102 | E56: 4832 | F56: 4560.2 | G56: 4290.4 | H56: 4004.1 | I56: 3739.2 | J56: 3463.4 | K56: 2957.7 | L56: 2710.6 | M56: 2450.9 | N56: 2207.2 | O56: 1978.3 | P56: 1754.7 | Q56: 2561.5
A57: Other Long-term Assets | B57: 1206.9 | C57: 1417.9 | D57: 1508.8 | E57: 1407 | F57: 1441.1 | G57: 1402.8 | H57: 1506.9 | I57: 1432.2 | J57: 1350.2 | K57: 1165.8 | L57: 1595 | M57: 1492.4 | N57: 1599.6 | O57: 1767.7 | P57: 1726.9 | Q57: 1743.2
A58: Total Assets | B58: 22162.1 | C58: 22522.1 | D58: 22522.1 | E58: 22273.2 | F58: 21750.1 | G58: 21714.4 | H58: 21228.5 | I58: 20491 | J58: 20293.4 | K58: 19715.6 | L58: 20204.5 | M58: 20023.7 | N58: 20586.3 | O58: 21579 | P58: 22285.3 | Q58: 26944.5 | R58: =SUM($R$53,$R$54,$R$55,$R$56,$R$57) | S58: =SUM($S$53,$S$54,$S$55,$S$56,$S$57) | T58: =SUM($T$53,$T$54,$T$55,$T$56,$T$57) | U58: =SUM($U$53,$U$54,$U$55,$U$56,$U$57) | V58: =SUM($V$53,$V$54,$V$55,$V$56,$V$57) | W58: =SUM($W$53,$W$54,$W$55,$W$56,$W$57) | X58: =SUM($X$53,$X$54,$X$55,$X$56,$X$57) | Y58: =SUM($Y$53,$Y$54,$Y$55,$Y$56,$Y$57)
A59: LIABILITIES
A60: Accounts Payable | B60: 490.3 | C60: 476.2 | D60: 465.8 | E60: 388.4 | F60: 412.8 | G60: 419.1 | H60: 411.3 | I60: 320.9 | J60: 453.4 | K60: 538.1 | L60: 622.2 | M60: 562.7 | N60: 610.7 | O60: 633.7 | P60: 1073.8 | Q60: 709.7 | R60: =$R$19/91*'Assumptions'!$R$32 | S60: =$S$19/91*'Assumptions'!$S$32 | T60: =$T$19/91*'Assumptions'!$T$32 | U60: =$U$19/91*'Assumptions'!$U$32 | V60: =$V$19/91*'Assumptions'!$V$32 | W60: =$W$19/91*'Assumptions'!$W$32 | X60: =$X$19/91*'Assumptions'!$X$32 | Y60: =$Y$19/91*'Assumptions'!$Y$32
A61: Accrued Liabilities | D61: 1092 | H61: 1032.9 | I61: 861 | J61: 763.8 | K61: 825.2 | L61: 972.6 | M61: 939.8 | N61: 1078.5 | O61: 1351.1 | P61: 1337.1 | Q61: 1335.6
A62: Short-term Debt | B62: 653.5 | C62: 584 | D62: 584.4 | E62: 1517.6 | F62: 1018.6 | G62: 96.3 | H62: 107.3 | I62: 118.3 | J62: 129.3 | K62: 129.4 | L62: 129.5 | M62: 1255.2 | N62: 499.3 | O62: 499.5 | P62: 499.8 | Q62: 0 | R62: ='Assumptions'!$R$34 | S62: ='Assumptions'!$S$34 | T62: ='Assumptions'!$T$34 | U62: ='Assumptions'!$U$34 | V62: ='Assumptions'!$V$34 | W62: ='Assumptions'!$W$34 | X62: ='Assumptions'!$X$34 | Y62: ='Assumptions'!$Y$34
A63: Current Portion of LT Debt | D63: 584.4 | P63: 499.8 | Q63: 0
A64: Deferred Revenue (Current) | B64: 28.9 | C64: 47 | D64: 45.2 | E64: 44.4 | F64: 44.6 | G64: 56.9 | H64: 43.2 | I64: 33.9 | J64: 39.2 | K64: 34.5 | L64: 22.1 | M64: 31.8 | N64: 41.3 | O64: 32.2 | P64: 40.1 | Q64: 63.7
A65: Other Current Liabilities
A66: Total Current Liabilities | B66: 2155.8 | C66: 2420.2 | D66: 2386.7 | E66: 3061.4 | F66: 2685.2 | G66: 1879.6 | H66: 1814.2 | I66: 1467.7 | J66: 1546.5 | K66: 1763.6 | L66: 2026.8 | M66: 2941.4 | N66: 2399.3 | O66: 2736.7 | P66: 3220.5 | Q66: 2276.8 | R66: =SUM($R$60,$R$61,$R$62,$R$63,$R$64,$R$65) | S66: =SUM($S$60,$S$61,$S$62,$S$63,$S$64,$S$65) | T66: =SUM($T$60,$T$61,$T$62,$T$63,$T$64,$T$65) | U66: =SUM($U$60,$U$61,$U$62,$U$63,$U$64,$U$65) | V66: =SUM($V$60,$V$61,$V$62,$V$63,$V$64,$V$65) | W66: =SUM($W$60,$W$61,$W$62,$W$63,$W$64,$W$65) | X66: =SUM($X$60,$X$61,$X$62,$X$63,$X$64,$X$65) | Y66: =SUM($Y$60,$Y$61,$Y$62,$Y$63,$Y$64,$Y$65)
A67: Long-term Debt | B67: 3947.4 | C67: 3927.6 | D67: 3907.7 | E67: 3154.9 | F67: 3134.5 | G67: 4089.6 | H67: 4058.6 | I67: 4027.6 | J67: 3996.5 | K67: 3965.5 | L67: 3934.3 | M67: 2977.4 | N67: 3967.9 | O67: 3969.4 | P67: 3970.8 | Q67: 4961.3 | R67: ='Assumptions'!$R$35 | S67: ='Assumptions'!$S$35 | T67: ='Assumptions'!$T$35 | U67: ='Assumptions'!$U$35 | V67: ='Assumptions'!$V$35 | W67: ='Assumptions'!$W$35 | X67: ='Assumptions'!$X$35 | Y67: ='Assumptions'!$Y$35
A68: Long-term Deferred Revenue
A69: Other Long-term Liabilities | B69: 528.7 | C69: 615.3 | D69: 590.5 | E69: 563 | F69: 540.9 | G69: 511.8 | H69: 524.3 | I69: 517 | J69: 545.5 | K69: 613.6 | L69: 816.4 | M69: 792.2 | N69: 797.4 | O69: 816.3 | P69: 785.6 | Q69: 1490.6
A70: Total Liabilities | B70: 6631.9 | C70: 6963.1 | D70: 6884.9 | E70: 6779.3 | F70: 6360.6 | G70: 6481 | H70: 6397.1 | I70: 6012.3 | J70: 6088.5 | K70: 6342.7 | L70: 6777.5 | M70: 6711 | N70: 7164.6 | O70: 7522.4 | P70: 7976.9 | Q70: 8728.7 | R70: =SUM($R$66,$R$67,$R$68,$R$69) | S70: =SUM($S$66,$S$67,$S$68,$S$69) | T70: =SUM($T$66,$T$67,$T$68,$T$69) | U70: =SUM($U$66,$U$67,$U$68,$U$69) | V70: =SUM($V$66,$V$67,$V$68,$V$69) | W70: =SUM($W$66,$W$67,$W$68,$W$69) | X70: =SUM($X$66,$X$67,$X$68,$X$69) | Y70: =SUM($Y$66,$Y$67,$Y$68,$Y$69)
A71: EQUITY
A72: Additional Paid-in Capital | B72: 14300.5 | C72: 14367.9 | D72: 14512 | E72: 14589.9 | F72: 14744.8 | G72: 14805.2 | H72: 14845.3 | I72: 14760.7 | J72: 14732.9 | K72: 14629 | L72: 14534.1 | M72: 14294.2 | N72: 14259.4 | O72: 13044 | P72: 12950.9 | Q72: 16877.5
A73: Retained Earnings (Accumulated Deficit) | B73: 1228 | C73: 1190.2 | D73: 1123.5 | E73: 903.2 | F73: 644 | G73: 427.9 | H73: -16.7 | I73: -284.1 | J73: -529.3 | K73: -1257.5 | L73: -1109.2 | M73: -983.1 | N73: -840 | O73: 1010.5 | P73: 1355.8 | Q73: 1336.5
A74: Accumulated OCI | C74: -0.8 | D74: 0 | E74: -0.9 | F74: -1 | G74: -1.4 | H74: 1.1 | I74: 0.4 | J74: -0.4 | K74: -0.3 | L74: 0.4 | M74: -0.1 | N74: 0.6 | O74: 0.4 | P74: 0
A75: Total Stockholders' Equity | B75: 15530.2 | C75: 15559 | D75: 15637.2 | E75: 15493.9 | F75: 15389.5 | G75: 15233.4 | H75: 14831.4 | I75: 14478.7 | J75: 14204.9 | K75: 13372.9 | L75: 13427 | M75: 13312.7 | N75: 13421.7 | O75: 14056.6 | P75: 14308.4 | Q75: 18215.8 | R75: =$R$58-$R$70 | S75: =$S$58-$S$70 | T75: =$T$58-$T$70 | U75: =$U$58-$U$70 | V75: =$V$58-$V$70 | W75: =$W$58-$W$70 | X75: =$X$58-$X$70 | Y75: =$Y$58-$Y$70
A76: Total Liabilities & Equity | B76: 22162.1 | C76: 22522.1 | D76: 22522.1 | E76: 22273.2 | F76: 21750.1 | G76: 21714.4 | H76: 21228.5 | I76: 20491 | J76: 20293.4 | K76: 19715.6 | L76: 20204.5 | M76: 20023.7 | N76: 20586.3 | O76: 21579 | P76: 22285.3 | Q76: 26944.5 | R76: =$R$58 | S76: =$S$58 | T76: =$T$58 | U76: =$U$58 | V76: =$V$58 | W76: =$W$58 | X76: =$X$58 | Y76: =$Y$58
A77: WORKING CAPITAL
A78: Net Operating Working Capital | B78: 1778.7 | C78: 1932.7 | D78: 767.1 | E78: 1741.8 | F78: 1886.4 | G78: 1771.6 | H78: 624.5 | I78: 584.2 | J78: 698.8 | K78: 550.9 | L78: 555.1 | M78: 829.2 | N78: 962.5 | O78: 781 | P78: 1370.8 | Q78: 1511.4 | R78: =($R$50+$R$51+$R$52)-($R$60+$R$61+$R$64+$R$65) | S78: =($S$50+$S$51+$S$52)-($S$60+$S$61+$S$64+$S$65) | T78: =($T$50+$T$51+$T$52)-($T$60+$T$61+$T$64+$T$65) | U78: =($U$50+$U$51+$U$52)-($U$60+$U$61+$U$64+$U$65) | V78: =($V$50+$V$51+$V$52)-($V$60+$V$61+$V$64+$V$65) | W78: =($W$50+$W$51+$W$52)-($W$60+$W$61+$W$64+$W$65) | X78: =($X$50+$X$51+$X$52)-($X$60+$X$61+$X$64+$X$65) | Y78: =($Y$50+$Y$51+$Y$52)-($Y$60+$Y$61+$Y$64+$Y$65)
A79: Change in NOWC | C79: 154 | D79: -1165.6 | E79: 974.7 | F79: 144.6 | G79: -114.8 | H79: -1147.1 | I79: -40.3 | J79: 114.6 | K79: -147.9 | L79: 4.2 | M79: 274.1 | N79: 133.3 | O79: -181.5 | P79: 589.8 | Q79: 140.6 | R79: =$R$78-$Q$78 | S79: =$S$78-$R$78 | T79: =$T$78-$S$78 | U79: =$U$78-$T$78 | V79: =$V$78-$U$78 | W79: =$W$78-$V$78 | X79: =$X$78-$W$78 | Y79: =$Y$78-$X$78
A81: CASH FLOW STATEMENT
B82: Q2FY23 | C82: Q3FY23 | D82: Q4FY23 | E82: Q1FY24 | F82: Q2FY24 | G82: Q3FY24 | H82: Q4FY24 | I82: Q1FY25 | J82: Q2FY25 | K82: Q3FY25 | L82: Q4FY25 | M82: Q1FY26 | N82: Q2FY26 | O82: Q3FY26 | P82: Q4FY26 | Q82: Q1FY27 | R82: Q2FY27E | S82: Q3FY27E | T82: Q4FY27E | U82: Q1FY28E | V82: Q2FY28E | W82: Q3FY28E | X82: Q4FY28E | Y82: Q1FY29E
A83: OPERATING ACTIVITIES
A84: Net Income | B84: 4.3 | C84: 13.3 | D84: -15.4 | E84: -168.9 | F84: -207.5 | G84: -164.3 | H84: -392.7 | I84: -215.6 | J84: -193.3 | K84: -676.3 | L84: 200.2 | M84: 177.9 | N84: 194.8 | O84: 1901.3 | P84: 396.1 | Q84: 34.5 | R84: =$R$33 | S84: =$S$33 | T84: =$T$33 | U84: =$U$33 | V84: =$V$33 | W84: =$W$33 | X84: =$X$33 | Y84: =$Y$33
A85: Depreciation & Amortization | B85: 348.7 | C85: 344.3 | D85: 351.1 | E85: 348.4 | F85: 347.3 | G85: 341.9 | H85: 360.1 | I85: 337.5 | J85: 352 | K85: 341.5 | L85: 325.9 | M85: 329.9 | N85: 327.8 | O85: 315.9 | P85: 317 | Q85: 320.6 | R85: ='Assumptions'!$R$16 | S85: ='Assumptions'!$S$16 | T85: ='Assumptions'!$T$16 | U85: ='Assumptions'!$U$16 | V85: ='Assumptions'!$V$16 | W85: ='Assumptions'!$W$16 | X85: ='Assumptions'!$X$16 | Y85: ='Assumptions'!$Y$16
A86: Stock-Based Compensation | B86: 144.5 | C86: 146.1 | D86: 130.7 | E86: 143.2 | F86: 152.8 | G86: 158.5 | H86: 155.3 | I86: 136.5 | J86: 154.9 | K86: 158.4 | L86: 147.6 | M86: 142.1 | N86: 153.6 | O86: 152.1 | P86: 143 | Q86: 207.6 | R86: ='Assumptions'!$R$20 | S86: ='Assumptions'!$S$20 | T86: ='Assumptions'!$T$20 | U86: ='Assumptions'!$U$20 | V86: ='Assumptions'!$V$20 | W86: ='Assumptions'!$W$20 | X86: ='Assumptions'!$X$20 | Y86: ='Assumptions'!$Y$20
A87: Change in Accounts Receivable | B87: 100.2 | C87: 101.8 | D87: -198.8 | E87: -191.3 | F87: 208.2 | G87: 5.5 | H87: -93 | I87: -239.7 | J87: 178.2 | K87: -62.2 | L87: 30.5 | M87: 115.6 | N87: 307.7 | O87: 94.7 | P87: 640.2 | Q87: -314.9 | R87: =-($R$50-$Q$50) | S87: =-($S$50-$R$50) | T87: =-($T$50-$S$50) | U87: =-($U$50-$T$50) | V87: =-($V$50-$U$50) | W87: =-($W$50-$V$50) | X87: =-($X$50-$W$50) | Y87: =-($Y$50-$X$50)
A88: Change in Inventories | B88: 81.3 | C88: 56.3 | D88: 122.5 | E88: -41.2 | F88: -11.3 | G88: -70.6 | H88: -78.8 | I88: -38.8 | J88: -9.2 | K88: 108.2 | L88: 169.8 | M88: 69.9 | N88: -15.4 | O88: -35.2 | P88: 370.5 | Q88: 11.4 | R88: =-($R$51-$Q$51) | S88: =-($S$51-$R$51) | T88: =-($T$51-$S$51) | U88: =-($U$51-$T$51) | V88: =-($V$51-$U$51) | W88: =-($W$51-$V$51) | X88: =-($X$51-$W$51) | Y88: =-($Y$51-$X$51)
A89: Change in Prepaid & Other Assets
A90: Change in Accounts Payable | B90: -57.5 | C90: -37.8 | D90: -53.9 | E90: -104.8 | F90: 18 | G90: -0.7 | H90: -61.6 | I90: -58.3 | J90: 93.1 | K90: 75 | L90: 71.7 | M90: -37.4 | N90: -30.7 | O90: -11 | P90: 378.4 | Q90: -355.9 | R90: =$R$60-$Q$60 | S90: =$S$60-$R$60 | T90: =$T$60-$S$60 | U90: =$U$60-$T$60 | V90: =$V$60-$U$60 | W90: =$W$60-$V$60 | X90: =$X$60-$W$60 | Y90: =$Y$60-$X$60
A91: Change in Accrued Liabilities | R91: =$R$61-$Q$61 | S91: =$S$61-$R$61 | T91: =$T$61-$S$61 | U91: =$U$61-$T$61 | V91: =$V$61-$U$61 | W91: =$W$61-$V$61 | X91: =$X$61-$W$61 | Y91: =$Y$61-$X$61
A92: Change in Deferred Revenue | R92: =$R$64-$Q$64 | S92: =$S$64-$R$64 | T92: =$T$64-$S$64 | U92: =$U$64-$T$64 | V92: =$V$64-$U$64 | W92: =$W$64-$V$64 | X92: =$X$64-$W$64 | Y92: =$Y$64-$X$64
A93: Other Operating Activities
A94: Total Operating Cash Flow | B94: 331.5 | C94: 411 | D94: 351.5 | E94: 208.4 | F94: 112.5 | G94: 503 | H94: 546.6 | I94: 324.5 | J94: 306.4 | K94: 536.3 | L94: 514 | M94: 332.9 | N94: 461.6 | O94: 582.3 | P94: 373.7 | Q94: 638.8 | R94: =SUM($R$84,$R$85,$R$86,$R$87,$R$88,$R$90,$R$91,$R$92,$R$93) | S94: =SUM($S$84,$S$85,$S$86,$S$87,$S$88,$S$90,$S$91,$S$92,$S$93) | T94: =SUM($T$84,$T$85,$T$86,$T$87,$T$88,$T$90,$T$91,$T$92,$T$93) | U94: =SUM($U$84,$U$85,$U$86,$U$87,$U$88,$U$90,$U$91,$U$92,$U$93) | V94: =SUM($V$84,$V$85,$V$86,$V$87,$V$88,$V$90,$V$91,$V$92,$V$93) | W94: =SUM($W$84,$W$85,$W$86,$W$87,$W$88,$W$90,$W$91,$W$92,$W$93) | X94: =SUM($X$84,$X$85,$X$86,$X$87,$X$88,$X$90,$X$91,$X$92,$X$93) | Y94: =SUM($Y$84,$Y$85,$Y$86,$Y$87,$Y$88,$Y$90,$Y$91,$Y$92,$Y$93)
A95: INVESTING ACTIVITIES
A96: Capital Expenditures | B96: -72.6 | C96: -42.7 | D96: -54 | E96: -99.8 | F96: -111.1 | G96: -54.4 | H96: -71 | I96: -91.5 | J96: -48.2 | K96: -75 | L96: -69.9 | M96: -118.8 | N96: -47.5 | O96: -73.5 | P96: -114.3 | Q96: -155.7 | R96: =-'Assumptions'!$R$17 | S96: =-'Assumptions'!$S$17 | T96: =-'Assumptions'!$T$17 | U96: =-'Assumptions'!$U$17 | V96: =-'Assumptions'!$V$17 | W96: =-'Assumptions'!$W$17 | X96: =-'Assumptions'!$X$17 | Y96: =-'Assumptions'!$Y$17
A97: Purchases of Investments
A98: Proceeds from Investments
A99: Other Investing Activities
A100: Total Investing Cash Flow | B100: -129.9 | C100: -51.9 | D100: -64.2 | E100: -102.7 | F100: -117 | G100: -54.6 | H100: -76.2 | I100: -101.9 | J100: -53 | K100: -75.5 | L100: -70.3 | M100: -94.1 | N100: -77.2 | O100: 2391.2 | P100: -122.1 | Q100: -1421.4 | R100: =SUM($R$96,$R$97,$R$98,$R$99) | S100: =SUM($S$96,$S$97,$S$98,$S$99) | T100: =SUM($T$96,$T$97,$T$98,$T$99) | U100: =SUM($U$96,$U$97,$U$98,$U$99) | V100: =SUM($V$96,$V$97,$V$98,$V$99) | W100: =SUM($W$96,$W$97,$W$98,$W$99) | X100: =SUM($X$96,$X$97,$X$98,$X$99) | Y100: =SUM($Y$96,$Y$97,$Y$98,$Y$99)
A101: FINANCING ACTIVITIES
A102: Debt Proceeds (Repayments) | B102: -141 | C102: -91.9 | D102: -21.8 | E102: -21.9 | F102: -571.8 | G102: -1006.9 | H102: -21.9 | I102: -21.9 | J102: -21.9 | K102: -32.8 | L102: -32.8 | M102: -32.8 | N102: -757.8 | O102: 0 | P102: 0 | Q102: -500
A103: Share Repurchases | B103: -50 | C103: -50 | D103: 0 | E103: 0 | F103: 0 | G103: -50 | H103: -100 | I103: -150 | J103: -175 | K103: -200 | L103: -200 | M103: -340 | N103: -200 | O103: -1300 | P103: -200.1 | Q103: -200
...

Sheet Assumptions
A1: MRVL — Model Assumptions
A2: Yellow = editable forecast inputs | Blue shading = forecast period
B3: Q2FY23 | C3: Q3FY23 | D3: Q4FY23 | E3: Q1FY24 | F3: Q2FY24 | G3: Q3FY24 | H3: Q4FY24 | I3: Q1FY25 | J3: Q2FY25 | K3: Q3FY25 | L3: Q4FY25 | M3: Q1FY26 | N3: Q2FY26 | O3: Q3FY26 | P3: Q4FY26 | Q3: Q1FY27 | R3: Q2FY27E | S3: Q3FY27E | T3: Q4FY27E | U3: Q1FY28E | V3: Q2FY28E | W3: Q3FY28E | X3: Q4FY28E | Y3: Q1FY29E
A4: REVENUE DRIVERS
A5: Total Revenue ($mm) | B5: 1516.9 | C5: 1537.3 | D5: 1418.5 | E5: 1321.7 | F5: 1340.9 | G5: 1418.6 | H5: 1426.5 | I5: 1160.9 | J5: 1272.9 | K5: 1516.1 | L5: 1817.4 | M5: 1895.3 | N5: 2006.1 | O5: 2074.5 | P5: 2218.7 | Q5: 2417.8 | R5: =Q5*(1+R6) | S5: =R5*(1+S6) | T5: =S5*(1+T6) | U5: =T5*(1+U6) | V5: =U5*(1+V6) | W5: =V5*(1+W6) | X5: =W5*(1+X6) | Y5: =X5*(1+Y6)
A6: Revenue Growth % (QoQ) | C6: =C5/B5-1 | D6: =D5/C5-1 | E6: =E5/D5-1 | F6: =F5/E5-1 | G6: =G5/F5-1 | H6: =H5/G5-1 | I6: =I5/H5-1 | J6: =J5/I5-1 | ... Q6: =Q5/P5-1 | R6: 0.063 | S6: 0.063 | T6: 0.063 | U6: 0.063 | V6: 0.063 | W6: 0.063 | X6: 0.063 | Y6: 0.063
A7: Revenue Growth % (YoY) | F7: =F5/B5-1 | G7: =G5/C5-1 | H7: =H5/D5-1 | I7: =I5/E5-1 | J7: =J5/F5-1 | K7: =K5/G5-1 | L7: =L5/H5-1 | M7: =M5/I5-1 | ... Y7: =Y5/U5-1
A8: MARGIN DRIVERS
A9: Gross Margin % | B9: 0.51816204 | C9: 0.50562675 | D9: 0.47465633 | E9: 0.42157827 | F9: 0.38861958 | G9: 0.38855209 | H9: 0.46554504 | I9: 0.45464726 | J9: 0.46162307 | K9: 0.23045973 | L9: 0.50478706 | M9: 0.5025062 | N9: 0.50376352 | O9: 0.51569053 | P9: 0.51737504 | Q9: 0.5214658 | R9: 0.5215 | S9: 0.5215 | T9: 0.5215 | U9: 0.5215 | V9: 0.5215 | W9: 0.5215 | X9: 0.5215 | Y9: 0.5215
A10: OPEX DRIVERS
A11: R&D ($mm) | B11: 449 | C11: 448.1 | D11: 443.1 | E11: 480.7 | F11: 474.8 | G11: 481.1 | H11: 459.6 | I11: 476.1 | J11: 486.7 | K11: 488.6 | L11: 499 | M11: 507.7 | N11: 519 | O11: 512.5 | P11: 536 | Q11: 652.3 | R11: 652.3 | S11: 652.3 | T11: 652.3 | U11: 652.3 | V11: 652.3 | W11: 652.3 | X11: 652.3 | Y11: 652.3
A12: R&D % of Revenue | B12: 0.296 | C12: 0.2915 | D12: 0.3124 | E12: 0.3637 | F12: 0.3541 | G12: 0.3391 | H12: 0.3222 | I12: 0.4101 | J12: 0.3824 | K12: 0.3223 | L12: 0.2746 | M12: 0.2679 | N12: 0.2587 | O12: 0.247 | P12: 0.2416 | Q12: 0.2698 | R12: 0.2698 | S12: 0.2698 | T12: 0.2698 | U12: 0.2698 | V12: 0.2698 | W12: 0.2698 | X12: 0.2698 | Y12: 0.2698
A13: SG&A ($mm) | B13: 211.7 | C13: 207.8 | D13: 203.4 | E13: 199 | F13: 210 | G13: 213 | H13: 212 | I13: 199.9 | J13: 197.3 | K13: 205.3 | L13: 195.7 | M13: 186.4 | N13: 192.8 | O13: 189.9 | P13: 198 | Q13: 258.4 | R13: 258.4 | S13: 258.4 | T13: 258.4 | U13: 258.4 | V13: 258.4 | W13: 258.4 | X13: 258.4 | Y13: 258.4
A14: SG&A % of Revenue | B14: 0.1396 | C14: 0.1352 | D14: 0.1434 | E14: 0.1506 | F14: 0.1566 | G14: 0.1501 | H14: 0.1486 | I14: 0.1722 | J14: 0.155 | K14: 0.1354 | L14: 0.1077 | M14: 0.0983 | N14: 0.0961 | O14: 0.0915 | P14: 0.0892 | Q14: 0.1069 | R14: 0.1069 | S14: 0.1069 | T14: 0.1069 | U14: 0.1069 | V14: 0.1069 | W14: 0.1069 | X14: 0.1069 | Y14: 0.1069
A15: D&A & CAPEX
A16: Depreciation & Amortization ($mm) | B16: 348.7 | C16: 344.3 | D16: 351.1 | E16: 348.4 | F16: 347.3 | G16: 341.9 | H16: 360.1 | I16: 337.5 | J16: 352 | K16: 341.5 | L16: 325.9 | M16: 329.9 | N16: 327.8 | O16: 315.9 | P16: 317 | Q16: 320.6 | R16: 320.6 | S16: 320.6 | T16: 320.6 | U16: 320.6 | V16: 320.6 | W16: 320.6 | X16: 320.6 | Y16: 320.6
A17: Capital Expenditures ($mm) | B17: -72.6 | C17: -42.7 | D17: -54 | E17: -99.8 | F17: -111.1 | G17: -54.4 | H17: -71 | I17: -91.5 | J17: -48.2 | K17: -75 | L17: -69.9 | M17: -118.8 | N17: -47.5 | O17: -73.5 | P17: -114.3 | Q17: -155.7 | R17: -155.7 | S17: -155.7 | T17: -155.7 | U17: -155.7 | V17: -155.7 | W17: -155.7 | X17: -155.7 | Y17: -155.7
A18: Capex % of Revenue | B18: 0.0479 | C18: 0.0278 | D18: 0.0381 | E18: 0.0755 | F18: 0.0829 | G18: 0.0383 | H18: 0.0498 | I18: 0.0788 | J18: 0.0379 | K18: 0.0495 | L18: 0.0385 | M18: 0.0627 | N18: 0.0237 | O18: 0.0354 | P18: 0.0515 | Q18: 0.0644 | R18: 0.0644 | S18: 0.0644 | T18: 0.0644 | U18: 0.0644 | V18: 0.0644 | W18: 0.0644 | X18: 0.0644 | Y18: 0.0644
A19: OTHER
A20: Stock-Based Compensation ($mm) | B20: 144.5 | C20: 146.1 | D20: 130.7 | E20: 143.2 | F20: 152.8 | G20: 158.5 | H20: 155.3 | I20: 136.5 | J20: 154.9 | K20: 158.4 | L20: 147.6 | M20: 142.1 | N20: 153.6 | O20: 152.1 | P20: 143 | Q20: 207.6 | R20: 207.6 | S20: 207.6 | T20: 207.6 | U20: 207.6 | V20: 207.6 | W20: 207.6 | X20: 207.6 | Y20: 207.6
A21: SBC % of Revenue | B21: 0.0953 | C21: 0.095 | D21: 0.0921 | E21: 0.1083 | F21: 0.114 | G21: 0.1117 | H21: 0.1089 | I21: 0.1176 | J21: 0.1217 | K21: 0.1045 | L21: 0.0812 | M21: 0.075 | N21: 0.0766 | O21: 0.0733 | P21: 0.0645 | Q21: 0.0859 | R21: 0.0859 | S21: 0.0859 | T21: 0.0859 | U21: 0.0859 | V21: 0.0859 | W21: 0.0859 | X21: 0.0859 | Y21: 0.0859
A22: Interest Income ($mm) | B22: 0.8 | C22: 1.5 | D22: 2.5 | E22: 2.5 | F22: 1.6 | G22: 1.7 | H22: 3 | R22: 0 | S22: 0 | T22: 0 | U22: 0 | V22: 0 | W22: 0 | X22: 0 | Y22: 0
A23: Interest Expense ($mm) | B23: 37.4 | C23: 42.4 | D23: 46.9 | E23: 50.5 | F23: 51.9 | G23: 49.6 | H23: 50.9 | I23: 46.8 | J23: 46.5 | K23: 45.6 | L23: 44.1 | M23: 44.8 | N23: 46.8 | O23: 47.9 | P23: 47.8 | Q23: 50 | R23: 50 | S23: 50 | T23: 50 | U23: 50 | V23: 50 | W23: 50 | X23: 50 | Y23: 50
A24: Effective Tax Rate % | B24: -0.13157895 | C24: 0.79632466 | D24: 0.3362069 | E24: 0.27292294 | F24: 0.17527822 | G24: 0.12373333 | H24: -3.4982818 | I24: -0.089989889 | J24: -0.32216142 | K24: 0.098867422 | L24: -0.002002002 | M24: 0.17600741 | N24: 0.16645272 | O24: 0.14178027 | P24: -0.037997904 | Q24: 0.58583433 | R24: 0.5858 | S24: 0.5858 | T24: 0.5858 | U24: 0.5858 | V24: 0.5858 | W24: 0.5858 | X24: 0.5858 | Y24: 0.5858
A25: SHARES
A26: Diluted Shares (mm) | B26: 857.9 | C26: 858.4 | D26: 841.3 | E26: 856.7 | F26: 860.9 | G26: 862.6 | H26: 865 | I26: 865 | J26: 865.7 | K26: 865.7 | L26: 865.6 | M26: 875.6 | N26: 870.4 | O26: 863.7 | P26: 869.1 | Q26: 893.3 | R26: 893.3 | S26: 893.3 | T26: 893.3 | U26: 893.3 | V26: 893.3 | W26: 893.3 | X26: 893.3 | Y26: 893.3
A27: QoQ Share Change (mm) | C27: =C26-B26 | D27: =D26-C26 | E27: =E26-D26 | F27: =F26-E26 | G27: =G26-F26 | H27: =H26-G26 | I27: =I26-H26 | J27: =J26-I26 | ... Y27: =Y26-X26
A28: Basic Shares (mm) | B28: 850.9 | C28: 852.6 | D28: 854.1 | E28: 856.7 | F28: 860.9 | G28: 862.6 | H28: 865 | I28: 865 | J28: 865.7 | K28: 865.7 | L28: 865.6 | M28: 864.8 | N28: 862.6 | O28: 855.8 | P28: 860.8 | Q28: 882 | R28: 882 | S28: 882 | T28: 882 | U28: 882 | V28: 882 | W28: 882 | X28: 882 | Y28: 882
A29: WORKING CAPITAL DAYS
A30: Days Sales Outstanding | B30: 77.5 | C30: 82.3 | D30: 76.5 | E30: 68.9 | F30: 82.1 | G30: 77.9 | H30: 71.5 | I30: 69.1 | J30: 75.8 | K30: 59.9 | L30: 51.5 | M30: 54.9 | N30: 65.9 | O30: 67.8 | P30: 89.7 | Q30: 70.4 | R30: 73.5 | S30: 73.5 | T30: 73.5 | U30: 73.5 | V30: 73.5 | W30: 73.5 | X30: 73.5 | Y30: 73.5
A31: Inventory Days | B31: 113.7 | C31: 114.6 | D31: 130.5 | E31: 122.1 | F31: 112.8 | G31: 98.8 | H31: 103.2 | I31: 118.8 | J31: 108.6 | K31: 67 | L31: 104.1 | M31: 103.4 | N31: 96.1 | O31: 91.9 | P31: 118 | Q31: 110.2 | R31: 104 | S31: 104 | T31: 104 | U31: 104 | V31: 104 | W31: 104 | X31: 104 | Y31: 104
A32: Days Payable Outstanding | B32: 61 | C32: 57 | D32: 56.9 | E32: 46.2 | F32: 45.8 | G32: 44 | H32: 49.1 | I32: 46.1 | J32: 60.2 | K32: 42 | L32: 62.9 | M32: 54.3 | N32: 55.8 | O32: 57.4 | P32: 91.3 | Q32: 55.8 | R32: 65.1 | S32: 65.1 | T32: 65.1 | U32: 65.1 | V32: 65.1 | W32: 65.1 | X32: 65.1 | Y32: 65.1
A33: DEBT SCHEDULE
A34: Short-term Debt ($mm) | B34: 653.5 | C34: 584 | D34: 584.4 | E34: 1517.6 | F34: 1018.6 | G34: 96.3 | H34: 107.3 | I34: 118.3 | J34: 129.3 | K34: 129.4 | L34: 129.5 | M34: 1255.2 | N34: 499.3 | O34: 499.5 | P34: 499.8 | Q34: 0 | R34: 0 | S34: 0 | T34: 0 | U34: 0 | V34: 0 | W34: 0 | X34: 0 | Y34: 0
A35: Long-term Debt ($mm) | B35: 3947.4 | C35: 3927.6 | D35: 3907.7 | E35: 3154.9 | F35: 3134.5 | G35: 4089.6 | H35: 4058.6 | I35: 4027.6 | J35: 3996.5 | K35: 3965.5 | L35: 3934.3 | M35: 2977.4 | N35: 3967.9 | O35: 3969.4 | P35: 3970.8 | Q35: 4961.3 | R35: 4961.3 | S35: 4961.3 | T35: 4961.3 | U35: 4961.3 | V35: 4961.3 | W35: 4961.3 | X35: 4961.3 | Y35: 4961.3
A36: Total Debt ($mm) | B36: =B34+B35 | C36: =C34+C35 | D36: =D34+D35 | E36: =E34+E35 | F36: =F34+F35 | G36: =G34+G35 | H36: =H34+H35 | I36: =I34+I35 | ... Y36: =Y34+Y35
