Workbook

Sheet Assumptions
A1: NAVITAS SEMICONDUCTOR (NVTS) | REVENUE AND P&L ASSUMPTIONS | FY2025-FY2030
A2: Assumption | B2: Source / Rationale | C2: FY2025 | D2: FY2026 | E2: FY2027 | F2: FY2028 | G2: FY2029 | H2: FY2030
A3: Blue = hardcoded input Black = formula Yellow = USER_REQUIRED or MISSING_EVIDENCE
A4: REVENUE DRIVER ASSUMPTIONS | Driver: MW Addressed x Content ($/MW) / 1,000,000 = Revenue ($M)
A5: DATA CENTER
A6: MW Addressed (MW) | B6: MW of hyperscaler AI/GPU server power capacity addressed. FY2025 early ramp per 10-K FY2024. FY2030 implies ~30% of hyperscaler AI power consumption; USER_REQUIRED: validate vs disclosed capex plans. | C6: 100 | D6: 300 | E6: 800 | F6: 1500 | G6: 2500 | H6: 4000
A7: SiC Content ($/MW) | B7: SiC in PSU rectifier stage. $17,500/MW is ~1-2% of total PSU BOM at scale. Source: Gemini V2. | C7: 17500 | D7: 17500 | E7: 17500 | F7: 17500 | G7: 17500 | H7: 17500
A8: GaN Content ($/MW) | B8: GaN in AC/DC totem-pole topology in AI server power delivery. Source: Gemini V2. | C8: 12500 | D8: 12500 | E8: 12500 | F8: 12500 | G8: 12500 | H8: 12500
A10: MOBILE AND CONSUMER ELECTRONICS
A11: MW Addressed (MW) | B11: MW equivalent of GaN charger ICs shipped into USB-PD and fast-charger sockets. ~2-4% attach rate on global smartphone charger shipments. Growth capped by ASP erosion from Chinese GaN entrants. | C11: 1400 | D11: 1500 | E11: 1650 | F11: 1875 | G11: 2250 | H11: 2625
A12: SiC Content ($/MW) | B12: No SiC in mobile/consumer. Pure GaN segment. | C12: 0 | D12: 0 | E12: 0 | F12: 0 | G12: 0 | H12: 0
A13: GaN Content ($/MW) | B13: Derived from Gemini V2 ($20M / 1,500 MW FY2026). USER_REQUIRED: reconcile against NVTS disclosed ASP data. | C13: 13333 | D13: 13333 | E13: 13333 | F13: 13333 | G13: 13333 | H13: 13333
A15: ELECTRIC VEHICLES
A16: MW Addressed (MW) | B16: MW equivalent of EV on-board charger and DC/DC converter power addressed. FY2025 pre-production. FY2030 implies ~5-6% of global EV production. USER_REQUIRED: validate against named customer SOPs. | C16: 8000 | D16: 15000 | E16: 30000 | F16: 52500 | G16: 82500 | H16: 120000
A17: SiC Content ($/MW) | B17: $400/MW is below STM and Wolfspeed OBC pricing, reflecting NVTS competitive positioning. MISSING_EVIDENCE: no NVTS EV contract pricing disclosed. Source: Gemini V2. | C17: 400 | D17: 400 | E17: 400 | F17: 400 | G17: 400 | H17: 400
A18: GaN Content ($/MW) | B18: GaN in auxiliary power stages. Smaller BOM share than SiC in EV powertrain. Source: Gemini V2. | C18: 100 | D18: 100 | E18: 100 | F18: 100 | G18: 100 | H18: 100
A20: SOLAR AND ENERGY STORAGE
A21: MW Addressed (MW) | B21: MW of string inverter and storage inverter capacity addressed. Ramp begins FY2026. FY2030 consistent with global solar installation growth ~10-12% per year. | C21: 500 | D21: 800 | E21: 1400 | F21: 2200 | G21: 3400 | H21: 5000
A22: SiC Content ($/MW) | B22: SiC dominates solar inverter at 1,200V. $5,000/MW credible for residential/C&I string inverter. NVTS GeneSiC differentiated at this voltage. Source: Gemini V2. | C22: 5000 | D22: 5000 | E22: 5000 | F22: 5000 | G22: 5000 | H22: 5000
A23: GaN Content ($/MW) | B23: Minimal GaN in solar inverter. SiC preferred for 650V+ breakdown voltage. Source: Gemini V2. | C23: 0 | D23: 0 | E23: 0 | F23: 0 | G23: 0 | H23: 0
A25: INDUSTRIAL AND MOTOR DRIVES
A26: MW Addressed (MW) | B26: MW of motor drive, servo drive, and HVAC compressor power addressed. MISSING_EVIDENCE: no NVTS industrial customer names disclosed. Source: Gemini V2. | C26: 700 | D26: 1000 | E26: 1800 | F26: 2800 | G26: 4200 | H26: 6000
A27: SiC Content ($/MW) | B27: SiC in servo drives and HVAC compressors. Source: Gemini V2. | C27: 3000 | D27: 3000 | E27: 3000 | F27: 3000 | G27: 3000 | H27: 3000
A28: GaN Content ($/MW) | B28: GaN in lower-power motor drive auxiliary stages. Source: Gemini V2. | C28: 1000 | D28: 1000 | E28: 1000 | F28: 1000 | G28: 1000 | H28: 1000
A30: P&L ASSUMPTIONS | Gross Margin by Segment | R&D and SG&A as % of Total Corporate Revenue
A31: GROSS MARGIN (% of Segment Revenue) - Revenue minus wafer, assembly, and test cost
A32: Data Center | B32: Premium segment. High ASP, limited direct competition in AI PSU silicon. Expands toward 55% at scale. MISSING_EVIDENCE: NVTS does not disclose segment-level gross margin. | C32: 0.48 | D32: 0.5 | E32: 0.52 | F32: 0.53 | G32: 0.54 | H32: 0.55
A33: Mobile / Consumer | B33: Most competitive segment. Innoscience, Navitas, GaN Systems competing for USB-PD socket. ASP erosion 3-5% per year. USER_REQUIRED: confirm against NVTS pricing commentary. | C33: 0.36 | D33: 0.35 | E33: 0.34 | F33: 0.34 | G33: 0.33 | H33: 0.33
A34: Electric Vehicles | B34: Severe OEM pricing pressure. Margin recovery requires volume scale and SiC IP leverage. MISSING_EVIDENCE: no NVTS EV contract pricing disclosed. | C34: 0.3 | D34: 0.31 | E34: 0.33 | F34: 0.35 | G34: 0.36 | H34: 0.38
A35: Solar / Storage | B35: SiC-dominant. String inverter OEMs pay premium for efficiency at 1,200V. NVTS GeneSiC differentiated. Margin expands with volume. | C35: 0.42 | D35: 0.43 | E35: 0.44 | F35: 0.45 | G35: 0.46 | H35: 0.47
A36: Industrial / Motor Drives | B36: Custom-adjacent applications with smaller runs and design-in stickiness. Better mix than mobile. MISSING_EVIDENCE: no industrial segment margin disclosure from NVTS. | C36: 0.44 | D36: 0.44 | E36: 0.45 | F36: 0.46 | G36: 0.47 | H36: 0.48
A38: R&D EXPENSE (% of Total Corporate Revenue) - Allocated to segments by revenue mix
A39: R&D Rate | B39: NVTS FY2024 R&D/revenue ~38-40% per 10-K. Fabless model requires heavy GaN and SiC IP investment. Leverages down as revenue scales. Long-term target ~25%, consistent with fabless semis at maturity. | C39: 0.38 | D39: 0.35 | E39: 0.32 | F39: 0.3 | G39: 0.28 | H39: 0.26
A41: SG&A EXPENSE (% of Total Corporate Revenue) - Allocated to segments by revenue mix
A42: SG&A Rate | B42: NVTS FY2024 SG&A/revenue ~20-22% per 10-K. Long-term target ~12-14%, consistent with Monolithic Power Systems at scale. | C42: 0.22 | D42: 0.2 | E42: 0.18 | F42: 0.16 | G42: 0.15 | H42: 0.14

Sheet Revenue Model
A1: NAVITAS SEMICONDUCTOR (NVTS) | SEGMENT REVENUE MODEL | FY2025-FY2030 ($M)
A2: Driver: MW Addressed x $ Content per MW | Blue = input | Black = formula | Green = cross-sheet link
A3: Segment | B3: Driver | C3: FY2025 | D3: FY2026 | E3: FY2027 | F3: FY2028 | G3: FY2029 | H3: FY2030
A5: DATA CENTER
A6: MW Addressed | B6: Input (MW) | C6: =Assumptions!C6 -> 100 | D6: =Assumptions!D6 -> 300 | E6: =Assumptions!E6 -> 800 | F6: =Assumptions!F6 -> 1500 | G6: =Assumptions!G6 -> 2500 | H6: =Assumptions!H6 -> 4000
A7: SiC Revenue | B7: MW x SiC$/MW /1M | C7: =C6*Assumptions!C7/1000000 -> 1.75 | D7: =D6*Assumptions!D7/1000000 -> 5.25 | E7: =E6*Assumptions!E7/1000000 -> 14 | F7: =F6*Assumptions!F7/1000000 -> 26.25 | G7: =G6*Assumptions!G7/1000000 -> 43.75 | H7: =H6*Assumptions!H7/1000000 -> 70
A8: GaN Revenue | B8: MW x GaN$/MW /1M | C8: =C6*Assumptions!C8/1000000 -> 1.25 | D8: =D6*Assumptions!D8/1000000 -> 3.75 | E8: =E6*Assumptions!E8/1000000 -> 10 | F8: =F6*Assumptions!F8/1000000 -> 18.75 | G8: =G6*Assumptions!G8/1000000 -> 31.25 | H8: =H6*Assumptions!H8/1000000 -> 50
A9: Total Data Center | B9: SiC + GaN | C9: =C7+C8 -> 3 | D9: =D7+D8 -> 9 | E9: =E7+E8 -> 24 | F9: =F7+F8 -> 45 | G9: =G7+G8 -> 75 | H9: =H7+H8 -> 120
A11: MOBILE / CONSUMER
A12: MW Addressed | B12: Input (MW) | C12: =Assumptions!C11 -> 1400 | D12: =Assumptions!D11 -> 1500 | E12: =Assumptions!E11 -> 1650 | F12: =Assumptions!F11 -> 1875 | G12: =Assumptions!G11 -> 2250 | H12: =Assumptions!H11 -> 2625
A13: SiC Revenue | B13: MW x SiC$/MW /1M | C13: =C12*Assumptions!C12/1000000 -> 0 | D13: =D12*Assumptions!D12/1000000 -> 0 | E13: =E12*Assumptions!E12/1000000 -> 0 | F13: =F12*Assumptions!F12/1000000 -> 0 | G13: =G12*Assumptions!G12/1000000 -> 0 | H13: =H12*Assumptions!H12/1000000 -> 0
A14: GaN Revenue | B14: MW x GaN$/MW /1M | C14: =C12*Assumptions!C13/1000000 -> 18.6662 | D14: =D12*Assumptions!D13/1000000 -> 19.9995 | E14: =E12*Assumptions!E13/1000000 -> 21.99945 | F14: =F12*Assumptions!F13/1000000 -> 24.999375 | G14: =G12*Assumptions!G13/1000000 -> 29.99925 | H14: =H12*Assumptions!H13/1000000 -> 34.999125
A15: Total Mobile / Consumer | B15: SiC + GaN | C15: =C13+C14 -> 18.6662 | D15: =D13+D14 -> 19.9995 | E15: =E13+E14 -> 21.99945 | F15: =F13+F14 -> 24.999375 | G15: =G13+G14 -> 29.99925 | H15: =H13+H14 -> 34.999125
A17: ELECTRIC VEHICLES
A18: MW Addressed | B18: Input (MW) | C18: =Assumptions!C16 -> 8000 | D18: =Assumptions!D16 -> 15000 | E18: =Assumptions!E16 -> 30000 | F18: =Assumptions!F16 -> 52500 | G18: =Assumptions!G16 -> 82500 | H18: =Assumptions!H16 -> 120000
A19: SiC Revenue | B19: MW x SiC$/MW /1M | C19: =C18*Assumptions!C17/1000000 -> 3.2 | D19: =D18*Assumptions!D17/1000000 -> 6 | E19: =E18*Assumptions!E17/1000000 -> 12 | F19: =F18*Assumptions!F17/1000000 -> 21 | G19: =G18*Assumptions!G17/1000000 -> 33 | H19: =H18*Assumptions!H17/1000000 -> 48
A20: GaN Revenue | B20: MW x GaN$/MW /1M | C20: =C18*Assumptions!C18/1000000 -> 0.8 | D20: =D18*Assumptions!D18/1000000 -> 1.5 | E20: =E18*Assumptions!E18/1000000 -> 3 | F20: =F18*Assumptions!F18/1000000 -> 5.25 | G20: =G18*Assumptions!G18/1000000 -> 8.25 | H20: =H18*Assumptions!H18/1000000 -> 12
A21: Total Electric Vehicles | B21: SiC + GaN | C21: =C19+C20 -> 4 | D21: =D19+D20 -> 7.5 | E21: =E19+E20 -> 15 | F21: =F19+F20 -> 26.25 | G21: =G19+G20 -> 41.25 | H21: =H19+H20 -> 60
A23: SOLAR / STORAGE
A24: MW Addressed | B24: Input (MW) | C24: =Assumptions!C21 -> 500 | D24: =Assumptions!D21 -> 800 | E24: =Assumptions!E21 -> 1400 | F24: =Assumptions!F21 -> 2200 | G24: =Assumptions!G21 -> 3400 | H24: =Assumptions!H21 -> 5000
A25: SiC Revenue | B25: MW x SiC$/MW /1M | C25: =C24*Assumptions!C22/1000000 -> 2.5 | D25: =D24*Assumptions!D22/1000000 -> 4 | E25: =E24*Assumptions!E22/1000000 -> 7 | F25: =F24*Assumptions!F22/1000000 -> 11 | G25: =G24*Assumptions!G22/1000000 -> 17 | H25: =H24*Assumptions!H22/1000000 -> 25
A26: GaN Revenue | B26: MW x GaN$/MW /1M | C26: =C24*Assumptions!C23/1000000 -> 0 | D26: =D24*Assumptions!D23/1000000 -> 0 | E26: =E24*Assumptions!E23/1000000 -> 0 | F26: =F24*Assumptions!F23/1000000 -> 0 | G26: =G24*Assumptions!G23/1000000 -> 0 | H26: =H24*Assumptions!H23/1000000 -> 0
A27: Total Solar / Storage | B27: SiC + GaN | C27: =C25+C26 -> 2.5 | D27: =D25+D26 -> 4 | E27: =E25+E26 -> 7 | F27: =F25+F26 -> 11 | G27: =G25+G26 -> 17 | H27: =H25+H26 -> 25
A29: INDUSTRIAL / MOTOR DRIVES
A30: MW Addressed | B30: Input (MW) | C30: =Assumptions!C26 -> 700 | D30: =Assumptions!D26 -> 1000 | E30: =Assumptions!E26 -> 1800 | F30: =Assumptions!F26 -> 2800 | G30: =Assumptions!G26 -> 4200 | H30: =Assumptions!H26 -> 6000
A31: SiC Revenue | B31: MW x SiC$/MW /1M | C31: =C30*Assumptions!C27/1000000 -> 2.1 | D31: =D30*Assumptions!D27/1000000 -> 3 | E31: =E30*Assumptions!E27/1000000 -> 5.4 | F31: =F30*Assumptions!F27/1000000 -> 8.4 | G31: =G30*Assumptions!G27/1000000 -> 12.6 | H31: =H30*Assumptions!H27/1000000 -> 18
A32: GaN Revenue | B32: MW x GaN$/MW /1M | C32: =C30*Assumptions!C28/1000000 -> 0.7 | D32: =D30*Assumptions!D28/1000000 -> 1 | E32: =E30*Assumptions!E28/1000000 -> 1.8 | F32: =F30*Assumptions!F28/1000000 -> 2.8 | G32: =G30*Assumptions!G28/1000000 -> 4.2 | H32: =H30*Assumptions!H28/1000000 -> 6
A33: Total Industrial / Motor Drives | B33: SiC + GaN | C33: =C31+C32 -> 2.8 | D33: =D31+D32 -> 4 | E33: =E31+E32 -> 7.2 | F33: =F31+F32 -> 11.2 | G33: =G31+G32 -> 16.8 | H33: =H31+H32 -> 24
A35: TOTAL CORPORATE REVENUE ($M)
A36: Data Center | C36: ='Revenue Model'!C9 -> 3 | D36: ='Revenue Model'!D9 -> 9 | E36: ='Revenue Model'!E9 -> 24 | F36: ='Revenue Model'!F9 -> 45 | G36: ='Revenue Model'!G9 -> 75 | H36: ='Revenue Model'!H9 -> 120
A37: Mobile / Consumer | C37: ='Revenue Model'!C15 -> 18.6662 | D37: ='Revenue Model'!D15 -> 19.9995 | E37: ='Revenue Model'!E15 -> 21.99945 | F37: ='Revenue Model'!F15 -> 24.999375 | G37: ='Revenue Model'!G15 -> 29.99925 | H37: ='Revenue Model'!H15 -> 34.999125
A38: Electric Vehicles | C38: ='Revenue Model'!C21 -> 4 | D38: ='Revenue Model'!D21 -> 7.5 | E38: ='Revenue Model'!E21 -> 15 | F38: ='Revenue Model'!F21 -> 26.25 | G38: ='Revenue Model'!G21 -> 41.25 | H38: ='Revenue Model'!H21 -> 60
A39: Solar / Storage | C39: ='Revenue Model'!C27 -> 2.5 | D39: ='Revenue Model'!D27 -> 4 | E39: ='Revenue Model'!E27 -> 7 | F39: ='Revenue Model'!F27 -> 11 | G39: ='Revenue Model'!G27 -> 17 | H39: ='Revenue Model'!H27 -> 25
A40: Industrial / Motor Drives | C40: ='Revenue Model'!C33 -> 2.8 | D40: ='Revenue Model'!D33 -> 4 | E40: ='Revenue Model'!E33 -> 7.2 | F40: ='Revenue Model'!F33 -> 11.2 | G40: ='Revenue Model'!G33 -> 16.8 | H40: ='Revenue Model'!H33 -> 24
A41: Total SiC Revenue | B41: SUM of SiC rows | C41: =C7+C13+C19+C25+C31 -> 9.55 | D41: =D7+D13+D19+D25+D31 -> 18.25 | E41: =E7+E13+E19+E25+E31 -> 38.4 | F41: =F7+F13+F19+F25+F31 -> 66.65 | G41: =G7+G13+G19+G25+G31 -> 106.35 | H41: =H7+H13+H19+H25+H31 -> 161
A42: Total GaN Revenue | B42: SUM of GaN rows | C42: =C8+C14+C20+C26+C32 -> 21.4162 | D42: =D8+D14+D20+D26+D32 -> 26.2495 | E42: =E8+E14+E20+E26+E32 -> 36.79945 | F42: =F8+F14+F20+F26+F32 -> 51.799375 | G42: =G8+G14+G20+G26+G32 -> 73.69925 | H42: =H8+H14+H20+H26+H32 -> 102.99912
A43: TOTAL CORPORATE REVENUE | B43: All Segments | C43: =C9+C15+C21+C27+C33 -> 30.9662 | D43: =D9+D15+D21+D27+D33 -> 44.4995 | E43: =E9+E15+E21+E27+E33 -> 75.19945 | F43: =F9+F15+F21+F27+F33 -> 118.44938 | G43: =G9+G15+G21+G27+G33 -> 180.04925 | H43: =H9+H15+H21+H27+H33 -> 263.99912
A45: YoY REVENUE GROWTH
A46: Data Center | C46: n/a | D46: =IF(C9=0,"-",(D9-C9)/C9) -> 2 | E46: =IF(D9=0,"-",(E9-D9)/D9) -> 1.6666667 | F46: =IF(E9=0,"-",(F9-E9)/E9) -> 0.875 | G46: =IF(F9=0,"-",(G9-F9)/F9) -> 0.66666667 | H46: =IF(G9=0,"-",(H9-G9)/G9) -> 0.6
A47: Mobile / Consumer | C47: n/a | D47: =IF(C15=0,"-",(D15-C15)/C15) -> 0.071428571 | E47: =IF(D15=0,"-",(E15-D15)/D15) -> 0.1 | F47: =IF(E15=0,"-",(F15-E15)/E15) -> 0.13636364 | G47: =IF(F15=0,"-",(G15-F15)/F15) -> 0.2 | H47: =IF(G15=0,"-",(H15-G15)/G15) -> 0.16666667
A48: Electric Vehicles | C48: n/a | D48: =IF(C21=0,"-",(D21-C21)/C21) -> 0.875 | E48: =IF(D21=0,"-",(E21-D21)/D21) -> 1 | F48: =IF(E21=0,"-",(F21-E21)/E21) -> 0.75 | G48: =IF(F21=0,"-",(G21-F21)/F21) -> 0.57142857 | H48: =IF(G21=0,"-",(H21-G21)/G21) -> 0.45454545
A49: Solar / Storage | C49: n/a | D49: =IF(C27=0,"-",(D27-C27)/C27) -> 0.6 | E49: =IF(D27=0,"-",(E27-D27)/D27) -> 0.75 | F49: =IF(E27=0,"-",(F27-E27)/E27) -> 0.57142857 | G49: =IF(F27=0,"-",(G27-F27)/F27) -> 0.54545455 | H49: =IF(G27=0,"-",(H27-G27)/G27) -> 0.47058824
A50: Industrial / Motor Drives | C50: n/a | D50: =IF(C33=0,"-",(D33-C33)/C33) -> 0.42857143 | E50: =IF(D33=0,"-",(E33-D33)/D33) -> 0.8 | F50: =IF(E33=0,"-",(F33-E33)/E33) -> 0.55555556 | G50: =IF(F33=0,"-",(G33-F33)/F33) -> 0.5 | H50: =IF(G33=0,"-",(H33-G33)/G33) -> 0.42857143
A51: Total Corporate | C51: n/a | D51: =IF(C43=0,"-",(D43-C43)/C43) -> 0.43703457 | E51: =IF(D43=0,"-",(E43-D43)/D43) -> 0.68989427 | F51: =IF(E43=0,"-",(F43-E43)/E43) -> 0.57513619 | G51: =IF(F43=0,"-",(G43-F43)/F43) -> 0.52005234 | H51: =IF(G43=0,"-",(H43-G43)/G43) -> 0.46626062
A53: SEGMENT MIX (% of Total Revenue)
A54: Data Center | C54: =IF(C43=0,"-",C9/C43) -> 0.096879824 | D54: =IF(D43=0,"-",D9/D43) -> 0.20224946 | E54: =IF(E43=0,"-",E9/E43) -> 0.31915127 | F54: =IF(F43=0,"-",F9/F43) -> 0.37990914 | G54: =IF(G43=0,"-",G9/G43) -> 0.41655269 | H54: =IF(H43=0,"-",H9/H43) -> 0.45454696
A55: Mobile / Consumer | C55: =IF(C43=0,"-",C15/C43) -> 0.60279272 | D55: =IF(D43=0,"-",D15/D43) -> 0.44943202 | E55: =IF(E43=0,"-",E15/E43) -> 0.29254802 | F55: =IF(F43=0,"-",F15/F43) -> 0.21105536 | G55: =IF(G43=0,"-",G15/G43) -> 0.16661691 | H55: =IF(H43=0,"-",H15/H43) -> 0.13257288
A56: Electric Vehicles | C56: =IF(C43=0,"-",C21/C43) -> 0.1291731 | D56: =IF(D43=0,"-",D21/D43) -> 0.16854122 | E56: =IF(E43=0,"-",E21/E43) -> 0.19946954 | F56: =IF(F43=0,"-",F21/F43) -> 0.22161366 | G56: =IF(G43=0,"-",G21/G43) -> 0.22910398 | H56: =IF(H43=0,"-",H21/H43) -> 0.22727348
A57: Solar / Storage | C57: =IF(C43=0,"-",C27/C43) -> 0.080733187 | D57: =IF(D43=0,"-",D27/D43) -> 0.08988865 | E57: =IF(E43=0,"-",E27/E43) -> 0.093085787 | F57: =IF(F43=0,"-",F27/F43) -> 0.092866678 | G57: =IF(G43=0,"-",G27/G43) -> 0.09441861 | H57: =IF(H43=0,"-",H27/H43) -> 0.094697284
A58: Industrial / Motor Drives | C58: =IF(C43=0,"-",C33/C43) -> 0.090421169 | D58: =IF(D43=0,"-",D33/D43) -> 0.08988865 | E58: =IF(E43=0,"-",E33/E43) -> 0.095745381 | F58: =IF(F43=0,"-",F33/F43) -> 0.094555163 | G58: =IF(G43=0,"-",G33/G43) -> 0.093307803 | H58: =IF(H43=0,"-",H33/H43) -> 0.090909392
A60: SiC % of Revenue | C60: =IF(C43=0,"-",C41/C43) -> 0.30840077 | D60: =IF(D43=0,"-",D41/D43) -> 0.41011697 | E60: =IF(E43=0,"-",E41/E43) -> 0.51064203 | F60: =IF(F43=0,"-",F41/F43) -> 0.56268765 | G60: =IF(G43=0,"-",G41/G43) -> 0.59067172 | H60: =IF(H43=0,"-",H41/H43) -> 0.60985051
A61: GaN % of Revenue | C61: =IF(C43=0,"-",C42/C43) -> 0.69159923 | D61: =IF(D43=0,"-",D42/D43) -> 0.58988303 | E61: =IF(E43=0,"-",E42/E43) -> 0.48935797 | F61: =IF(F43=0,"-",F42/F43) -> 0.43731235 | G61: =IF(G43=0,"-",G42/G43) -> 0.40932828 | H61: =IF(H43=0,"-",H42/H43) -> 0.39014949
A64: SEGMENT P&L | GROSS PROFIT, ALLOCATED OPEX, AND EBIT BY SEGMENT ($M)
A65: DATA CENTER
A66: Revenue | B66: Link: Revenue Model row 9 | C66: =C9 -> 3 | D66: =D9 -> 9 | E66: =E9 -> 24 | F66: =F9 -> 45 | G66: =G9 -> 75 | H66: =H9 -> 120
A67: Gross Margin % | B67: Input: Assumptions sheet | C67: =Assumptions!C32 -> 0.48 | D67: =Assumptions!D32 -> 0.5 | E67: =Assumptions!E32 -> 0.52 | F67: =Assumptions!F32 -> 0.53 | G67: =Assumptions!G32 -> 0.54 | H67: =Assumptions!H32 -> 0.55
A68: Gross Profit | B68: Revenue x GM% | C68: =C66*C67 -> 1.44 | D68: =D66*D67 -> 4.5 | E68: =E66*E67 -> 12.48 | F68: =F66*F67 -> 23.85 | G68: =G66*G67 -> 40.5 | H68: =H66*H67 -> 66
A69: R&D (allocated) | B69: Corp R&D rate x seg revenue mix | C69: =C66*Assumptions!C39 -> 1.14 | D69: =D66*Assumptions!D39 -> 3.15 | E69: =E66*Assumptions!E39 -> 7.68 | F69: =F66*Assumptions!F39 -> 13.5 | G69: =G66*Assumptions!G39 -> 21 | H69: =H66*Assumptions!H39 -> 31.2
A70: SG&A (allocated) | B70: Corp SG&A rate x seg revenue mix | C70: =C66*Assumptions!C42 -> 0.66 | D70: =D66*Assumptions!D42 -> 1.8 | E70: =E66*Assumptions!E42 -> 4.32 | F70: =F66*Assumptions!F42 -> 7.2 | G70: =G66*Assumptions!G42 -> 11.25 | H70: =H66*Assumptions!H42 -> 16.8
A71: EBIT — Data Center | B71: GP - R&D alloc - SG&A alloc | C71: =C68-C69-C70 -> -0.36 | D71: =D68-D69-D70 -> -0.45 | E71: =E68-E69-E70 -> 0.48 | F71: =F68-F69-F70 -> 3.15 | G71: =G68-G69-G70 -> 8.25 | H71: =H68-H69-H70 -> 18
A72: EBIT Margin % | B72: EBIT / Revenue | C72: =IF(C66=0,"-",C71/C66) -> -0.12 | D72: =IF(D66=0,"-",D71/D66) -> -0.05 | E72: =IF(E66=0,"-",E71/E66) -> 0.02 | F72: =IF(F66=0,"-",F71/F66) -> 0.07 | G72: =IF(G66=0,"-",G71/G66) -> 0.11 | H72: =IF(H66=0,"-",H71/H66) -> 0.15
A74: MOBILE / CONSUMER
A75: Revenue | B75: Link: Revenue Model row 15 | C75: =C15 -> 18.6662 | D75: =D15 -> 19.9995 | E75: =E15 -> 21.99945 | F75: =F15 -> 24.999375 | G75: =G15 -> 29.99925 | H75: =H15 -> 34.999125
A76: Gross Margin % | B76: Input: Assumptions sheet | C76: =Assumptions!C33 -> 0.36 | D76: =Assumptions!D33 -> 0.35 | E76: =Assumptions!E33 -> 0.34 | F76: =Assumptions!F33 -> 0.34 | G76: =Assumptions!G33 -> 0.33 | H76: =Assumptions!H33 -> 0.33
A77: Gross Profit | B77: Revenue x GM% | C77: =C75*C76 -> 6.719832 | D77: =D75*D76 -> 6.999825 | E77: =E75*E76 -> 7.479813 | F77: =F75*F76 -> 8.4997875 | G77: =G75*G76 -> 9.8997525 | H77: =H75*H76 -> 11.549711
A78: R&D (allocated) | B78: Corp R&D rate x seg revenue mix | C78: =C75*Assumptions!C39 -> 7.093156 | D78: =D75*Assumptions!D39 -> 6.999825 | E78: =E75*Assumptions!E39 -> 7.039824 | F78: =F75*Assumptions!F39 -> 7.4998125 | G78: =G75*Assumptions!G39 -> 8.39979 | H78: =H75*Assumptions!H39 -> 9.0997725
A79: SG&A (allocated) | B79: Corp SG&A rate x seg revenue mix | C79: =C75*Assumptions!C42 -> 4.106564 | D79: =D75*Assumptions!D42 -> 3.9999 | E79: =E75*Assumptions!E42 -> 3.959901 | F79: =F75*Assumptions!F42 -> 3.9999 | G79: =G75*Assumptions!G42 -> 4.4998875 | H79: =H75*Assumptions!H42 -> 4.8998775
A80: EBIT — Mobile / Consumer | B80: GP - R&D alloc - SG&A alloc | C80: =C77-C78-C79 -> -4.479888 | D80: =D77-D78-D79 -> -3.9999 | E80: =E77-E78-E79 -> -3.519912 | F80: =F77-F78-F79 -> -2.999925 | G80: =G77-G78-G79 -> -2.999925 | H80: =H77-H78-H79 -> -2.4499388
A81: EBIT Margin % | B81: EBIT / Revenue | C81: =IF(C75=0,"-",C80/C75) -> -0.24 | D81: =IF(D75=0,"-",D80/D75) -> -0.2 | E81: =IF(E75=0,"-",E80/E75) -> -0.16 | F81: =IF(F75=0,"-",F80/F75) -> -0.12 | G81: =IF(G75=0,"-",G80/G75) -> -0.1 | H81: =IF(H75=0,"-",H80/H75) -> -0.07
A83: ELECTRIC VEHICLES
A84: Revenue | B84: Link: Revenue Model row 21 | C84: =C21 -> 4 | D84: =D21 -> 7.5 | E84: =E21 -> 15 | F84: =F21 -> 26.25 | G84: =G21 -> 41.25 | H84: =H21 -> 60
A85: Gross Margin % | B85: Input: Assumptions sheet | C85: =Assumptions!C34 -> 0.3 | D85: =Assumptions!D34 -> 0.31 | E85: =Assumptions!E34 -> 0.33 | F85: =Assumptions!F34 -> 0.35 | G85: =Assumptions!G34 -> 0.36 | H85: =Assumptions!H34 -> 0.38
A86: Gross Profit | B86: Revenue x GM% | C86: =C84*C85 -> 1.2 | D86: =D84*D85 -> 2.325 | E86: =E84*E85 -> 4.95 | F86: =F84*F85 -> 9.1875 | G86: =G84*G85 -> 14.85 | H86: =H84*H85 -> 22.8
A87: R&D (allocated) | B87: Corp R&D rate x seg revenue mix | C87: =C84*Assumptions!C39 -> 1.52 | D87: =D84*Assumptions!D39 -> 2.625 | E87: =E84*Assumptions!E39 -> 4.8 | F87: =F84*Assumptions!F39 -> 7.875 | G87: =G84*Assumptions!G39 -> 11.55 | H87: =H84*Assumptions!H39 -> 15.6
A88: SG&A (allocated) | B88: Corp SG&A rate x seg revenue mix | C88: =C84*Assumptions!C42 -> 0.88 | D88: =D84*Assumptions!D42 -> 1.5 | E88: =E84*Assumptions!E42 -> 2.7 | F88: =F84*Assumptions!F42 -> 4.2 | G88: =G84*Assumptions!G42 -> 6.1875 | H88: =H84*Assumptions!H42 -> 8.4
A89: EBIT — Electric Vehicles | B89: GP - R&D alloc - SG&A alloc | C89: =C86-C87-C88 -> -1.2 | D89: =D86-D87-D88 -> -1.8 | E89: =E86-E87-E88 -> -2.55 | F89: =F86-F87-F88 -> -2.8875 | G89: =G86-G87-G88 -> -2.8875 | H89: =H86-H87-H88 -> -1.2
A90: EBIT Margin % | B90: EBIT / Revenue | C90: =IF(C84=0,"-",C89/C84) -> -0.3 | D90: =IF(D84=0,"-",D89/D84) -> -0.24 | E90: =IF(E84=0,"-",E89/E84) -> -0.17 | F90: =IF(F84=0,"-",F89/F84) -> -0.11 | G90: =IF(G84=0,"-",G89/G84) -> -0.07 | H90: =IF(H84=0,"-",H89/H84) -> -0.02
A92: SOLAR / STORAGE
A93: Revenue | B93: Link: Revenue Model row 27 | C93: =C27 -> 2.5 | D93: =D27 -> 4 | E93: =E27 -> 7 | F93: =F27 -> 11 | G93: =G27 -> 17 | H93: =H27 -> 25
A94: Gross Margin % | B94: Input: Assumptions sheet | C94: =Assumptions!C35 -> 0.42 | D94: =Assumptions!D35 -> 0.43 | E94: =Assumptions!E35 -> 0.44 | F94: =Assumptions!F35 -> 0.45 | G94: =Assumptions!G35 -> 0.46 | H94: =Assumptions!H35 -> 0.47
A95: Gross Profit | B95: Revenue x GM% | C95: =C93*C94 -> 1.05 | D95: =D93*D94 -> 1.72 | E95: =E93*E94 -> 3.08 | F95: =F93*F94 -> 4.95 | G95: =G93*G94 -> 7.82 | H95: =H93*H94 -> 11.75
A96: R&D (allocated) | B96: Corp R&D rate x seg revenue mix | C96: =C93*Assumptions!C39 -> 0.95 | D96: =D93*Assumptions!D39 -> 1.4 | E96: =E93*Assumptions!E39 -> 2.24 | F96: =F93*Assumptions!F39 -> 3.3 | G96: =G93*Assumptions!G39 -> 4.76 | H96: =H93*Assumptions!H39 -> 6.5
A97: SG&A (allocated) | B97: Corp SG&A rate x seg revenue mix | C97: =C93*Assumptions!C42 -> 0.55 | D97: =D93*Assumptions!D42 -> 0.8 | E97: =E93*Assumptions!E42 -> 1.26 | F97: =F93*Assumptions!F42 -> 1.76 | G97: =G93*Assumptions!G42 -> 2.55 | H97: =H93*Assumptions!H42 -> 3.5
A98: EBIT — Solar / Storage | B98: GP - R&D alloc - SG&A alloc | C98: =C95-C96-C97 -> -0.45 | D98: =D95-D96-D97 -> -0.48 | E98: =E95-E96-E97 -> -0.42 | F98: =F95-F96-F97 -> -0.11 | G98: =G95-G96-G97 -> 0.51 | H98: =H95-H96-H97 -> 1.75
A99: EBIT Margin % | B99: EBIT / Revenue | C99: =IF(C93=0,"-",C98/C93) -> -0.18 | D99: =IF(D93=0,"-",D98/D93) -> -0.12 | E99: =IF(E93=0,"-",E98/E93) -> -0.06 | F99: =IF(F93=0,"-",F98/F93) -> -0.01 | G99: =IF(G93=0,"-",G98/G93) -> 0.03 | H99: =IF(H93=0,"-",H98/H93) -> 0.07
A101: INDUSTRIAL / MOTOR DRIVES
A102: Revenue | B102: Link: Revenue Model row 33 | C102: =C33 -> 2.8 | D102: =D33 -> 4 | E102: =E33 -> 7.2 | F102: =F33 -> 11.2 | G102: =G33 -> 16.8 | H102: =H33 -> 24
A103: Gross Margin % | B103: Input: Assumptions sheet | C103: =Assumptions!C36 -> 0.44 | D103: =Assumptions!D36 -> 0.44 | E103: =Assumptions!E36 -> 0.45 | F103: =Assumptions!F36 -> 0.46 | G103: =Assumptions!G36 -> 0.47 | H103: =Assumptions!H36 -> 0.48
A104: Gross Profit | B104: Revenue x GM% | C104: =C102*C103 -> 1.232 | D104: =D102*D103 -> 1.76 | E104: =E102*E103 -> 3.24 | F104: =F102*F103 -> 5.152 | G104: =G102*G103 -> 7.896 | H104: =H102*H103 -> 11.52
A105: R&D (allocated) | B105: Corp R&D rate x seg revenue mix | C105: =C102*Assumptions!C39 -> 1.064 | D105: =D102*Assumptions!D39 -> 1.4 | E105: =E102*Assumptions!E39 -> 2.304 | F105: =F102*Assumptions!F39 -> 3.36 | G105: =G102*Assumptions!G39 -> 4.704 | H105: =H102*Assumptions!H39 -> 6.24
A106: SG&A (allocated) | B106: Corp SG&A rate x seg revenue mix | C106: =C102*Assumptions!C42 -> 0.616 | D106: =D102*Assumptions!D42 -> 0.8 | E106: =E102*Assumptions!E42 -> 1.296 | F106: =F102*Assumptions!F42 -> 1.792 | G106: =G102*Assumptions!G42 -> 2.52 | H106: =H102*Assumptions!H42 -> 3.36
A107: EBIT — Industrial / Motor Drives | B107: GP - R&D alloc - SG&A alloc | C107: =C104-C105-C106 -> -0.448 | D107: =D104-D105-D106 -> -0.44 | E107: =E104-E105-E106 -> -0.36 | F107: =F104-F105-F106 -> 0 | G107: =G104-G105-G106 -> 0.672 | H107: =H104-H105-H106 -> 1.92
A108: EBIT Margin % | B108: EBIT / Revenue | C108: =IF(C102=0,"-",C107/C102) -> -0.16 | D108: =IF(D102=0,"-",D107/D102) -> -0.11 | E108: =IF(E102=0,"-",E107/E102) -> -0.05 | F108: =IF(F102=0,"-",F107/F102) -> 0 | G108: =IF(G102=0,"-",G107/G102) -> 0.04 | H108: =IF(H102=0,"-",H107/H102) -> 0.08
A110: CONSOLIDATED P&L SUMMARY ($M)
A111: Total Revenue | B111: All segments | C111: =C43 -> 30.9662 | D111: =D43 -> 44.4995 | E111: =E43 -> 75.19945 | F111: =F43 -> 118.44938 | G111: =G43 -> 180.04925 | H111: =H43 -> 263.99912
A112: Total Gross Profit | B112: Sum of segment GPs | C112: =C68+C77+C86+C95+C104 -> 11.641832 | D112: =D68+D77+D86+D95+D104 -> 17.304825 | E112: =E68+E77+E86+E95+E104 -> 31.229813 | F112: =F68+F77+F86+F95+F104 -> 51.639288 | G112: =G68+G77+G86+G95+G104 -> 80.965752 | H112: =H68+H77+H86+H95+H104 -> 123.61971
A113: Blended Gross Margin % | B113: Total GP / Total Revenue | C113: =IF(C111=0,"-",C112/C111) -> 0.37595288 | D113: =IF(D111=0,"-",D112/D111) -> 0.38887684 | E113: =IF(E111=0,"-",E112/E111) -> 0.4152931 | F113: =IF(F111=0,"-",F112/F111) -> 0.43596083 | G113: =IF(G111=0,"-",G112/G111) -> 0.4496867 | H113: =IF(H111=0,"-",H112/H111) -> 0.46825803
A114: Total R&D Expense | B114: Corporate rate x total revenue | C114: =C111*Assumptions!C39 -> 11.767156 | D114: =D111*Assumptions!D39 -> 15.574825 | E114: =E111*Assumptions!E39 -> 24.063824 | F114: =F111*Assumptions!F39 -> 35.534813 | G114: =G111*Assumptions!G39 -> 50.41379 | H114: =H111*Assumptions!H39 -> 68.639773
A115: Total SG&A Expense | B115: Corporate rate x total revenue | C115: =C111*Assumptions!C42 -> 6.812564 | D115: =D111*Assumptions!D42 -> 8.8999 | E115: =E111*Assumptions!E42 -> 13.535901 | F115: =F111*Assumptions!F42 -> 18.9519 | G115: =G111*Assumptions!G42 -> 27.007388 | H115: =H111*Assumptions!H42 -> 36.959878
A116: TOTAL EBIT | B116: GP - R&D - SG&A | C116: =C112-C114-C115 -> -6.937888 | D116: =D112-D114-D115 -> -7.1699 | E116: =E112-E114-E115 -> -6.369912 | F116: =F112-F114-F115 -> -2.847425 | G116: =G112-G114-G115 -> 3.544575 | H116: =H112-H114-H115 -> 18.020061
...
