Workbook

Sheet Summary
A1: onsemi / Synaptics - $7B All-Stock Acquisition - Deal Summary
A2: Announced 6/25/2026. All-stock, fixed 1.350 exchange ratio. Target close mid-2027. $ in millions except per-share.
A4: DEAL TERMS | D4: MARKET REACTION
A5: Enterprise value | B5: ='Deal & Accretion'!C8 -> 6924.4095 | D5: onsemi market cap change today | E5: ='Value Creation'!B16 -> -10196.72
A6: Exchange ratio (ON per SYNA) | B6: =Assumptions!$B$25 -> 1.35 | D6: Mkt cap loss / deal EV | E6: ='Value Creation'!B19 -> 1.4725761
A7: Premium (10-day VWAP) | B7: =Assumptions!$B$26 -> 0.19 | D7: Control premium paid | E7: ='Value Creation'!B7 -> 1036.5553
A8: New ON shares issued (mm) | B8: ='Deal & Accretion'!B5 -> 54.675 | D8: Synergy value (perpetuity) | E8: ='Value Creation'!B10 -> 2100
A9: SYNA holders ownership % | B9: ='Deal & Accretion'!B22 -> 0.12185881 | D9: Net value creation (if synergies real) | E9: ='Value Creation'!B11 -> 1063.4447
A10: Target synergies (pretax) | B10: =Assumptions!$B$27 -> 200
A11: SYNA termination fee | B11: 235 | D11: VERDICT
A12: ON reverse termination fee | B12: 320 | D12: Crash is roughly half deal-skepticism, half unrelated sector beta. EPS accretion is fixed and positive but synergy-dependent. China SAMR is the binding regulatory risk and the reason for the mid-2027 close and the $320M reverse breakup fee. On EPS math and the cheaper post-crash multiple it is defensible; on strategic drift and execution it is not de-risked. Stance: Hold.
A14: MULTIPLES PAID (announcement)
A15: EV / Revenue | B15: ='Deal & Accretion'!C11 -> 5.8532625
A16: EV / EBITDA | B16: ='Deal & Accretion'!C12 -> 26.726091
A17: P/E (non-GAAP) | B17: ='Deal & Accretion'!C13 -> 36.960563
A19: ACCRETION / (DILUTION), non-GAAP EPS
A20: No synergies | B20: ='Deal & Accretion'!B34 -> 0.021318753
A21: Year 1 (50% synergies) | B21: ='Deal & Accretion'!C34 -> 0.089789801
A22: Full run-rate synergies | B22: ='Deal & Accretion'!D34 -> 0.15826085
A24: Tabs: Summary | Assumptions (inputs) | Standalone | Deal & Accretion | Sensitivity | Value Creation

Sheet Assumptions
A1: onsemi (ON) / Synaptics (SYNA) - Deal Model Assumptions
A2: All figures $ in millions unless noted. Blue = input. Announced 6/25/2026. Share counts estimated pending S-4/proxy.
A4: ONSEMI (ON) STANDALONE - FY2026E
A5: ON Revenue ($mm) | B5: 6500 | D5: Est. Q1'26 actual $1,513M + Q2'26 guide mid $1,585M, modest H2 recovery
A6: ON Non-GAAP gross margin (%) | B6: 0.385 | D6: Source: onsemi Q1'26 release, 5/4/2026
A7: ON Non-GAAP operating expenses ($mm) | B7: 1200 | D7: Est. ~$295-300M/qtr run-rate
A8: ON Net interest & other ($mm) | B8: -20 | D8: Estimate
A9: ON Non-GAAP tax rate (%) | B9: 0.16 | D9: Estimate
A10: ON Diluted shares (mm) | B10: 394 | D10: Source: onsemi Q1'26 non-GAAP diluted share count
A11: ON share price - announcement ($) | B11: 118.74 | D11: Close Thu 6/25/2026
A12: ON share price - current ($) | B12: 92.86 | D12: Intraday 6/26/2026
A13: SYNAPTICS (SYNA) STANDALONE - FY2026E
A14: SYNA Revenue ($mm) | B14: 1183 | D14: Q1 $292.5 + Q2 est ~$291 + Q3 $294.2 + Q4 guide $305
A15: SYNA Non-GAAP gross margin (%) | B15: 0.536 | D15: Source: SYNA Q3 FY26 release, 5/7/2026
A16: SYNA Non-GAAP operating expenses ($mm) | B16: 420 | D16: ~$105M/qtr (Q4 guide $105M)
A17: SYNA Net interest & other ($mm) | B17: -20 | D17: Est. (net of $837M debt / $404M cash)
A18: SYNA Non-GAAP tax rate (%) | B18: 0.095 | D18: Calibrated to ~$176M run-rate non-GAAP NI
A19: SYNA D&A ($mm) | B19: 45 | D19: Estimate, for EBITDA
A20: SYNA Diluted shares (mm) | B20: 40.5 | D20: Implied from Q3 $44.1M NI / $1.09 EPS
A21: SYNA share price - announcement ($) | B21: 125.62 | D21: Close Thu 6/25/2026
A22: SYNA Cash ($mm) | B22: 404.4 | D22: Source: SYNA balance sheet 3/28/2026
A23: SYNA Debt ($mm) | B23: 836.7 | D23: Source: SYNA balance sheet 3/28/2026
A24: DEAL TERMS
A25: Exchange ratio (ON shares per SYNA) | B25: 1.35 | D25: Source: merger agreement, 6/25/2026
A26: Premium to 10-day VWAP (%) | B26: 0.19 | D26: Stated in joint press release
A27: Synergies - pretax run-rate ($mm) | B27: 200 | D27: Company target; cost/revenue split not disclosed
A28: Synergy phase-in - Year 1 (%) | B28: 0.5 | D28: Assumption (full by ~18-24 mo.)
A29: Synergy tax rate (%) | B29: 0.16 | D29: Assumption
A30: VALUE-CREATION INPUTS
A31: Discount rate (%) | B31: 0.1 | D31: Assumption for synergy capitalization
A32: Synergy perpetuity growth (%) | B32: 0.02 | D32: Assumption

Sheet Standalone
A1: Standalone Operating Models - FY2026E Non-GAAP
A2: $ in millions except per-share
B3: onsemi | C3: Synaptics
A4: Revenue | B4: =Assumptions!$B$5 -> 6500 | C4: =Assumptions!$B$14 -> 1183
A5: Gross profit | B5: =B4*Assumptions!$B$6 -> 2502.5 | C5: =C4*Assumptions!$B$15 -> 634.088
A6: Gross margin % | B6: =B5/B4 -> 0.385 | C6: =C5/C4 -> 0.536
A7: Operating expenses | B7: =Assumptions!$B$7 -> 1200 | C7: =Assumptions!$B$16 -> 420
A8: Operating income | B8: =B5-B7 -> 1302.5 | C8: =C5-C7 -> 214.088
A9: Operating margin % | B9: =B8/B4 -> 0.20038462 | C9: =C8/C4 -> 0.18097041
A10: Net interest & other | B10: =Assumptions!$B$8 -> -20 | C10: =Assumptions!$B$17 -> -20
A11: Pretax income | B11: =B8+B10 -> 1282.5 | C11: =C8+C10 -> 194.088
A12: Taxes | B12: =-B11*Assumptions!$B$9 -> -205.2 | C12: =-C11*Assumptions!$B$18 -> -18.43836
A13: Non-GAAP net income | B13: =B11+B12 -> 1077.3 | C13: =C11+C12 -> 175.64964
A14: Diluted shares (mm) | B14: =Assumptions!$B$10 -> 394 | C14: =Assumptions!$B$20 -> 40.5
A15: Non-GAAP EPS | B15: =B13/B14 -> 2.734264 | C15: =C13/C14 -> 4.3370281
A16: Memo: EBITDA | B16: =B8 -> 1302.5 | C16: =C8+Assumptions!$B$19 -> 259.088 | D16: ON EBITDA = op income (D&A not modeled separately)
A17: Implied P/E at announcement px | B17: =Assumptions!$B$11/B15 -> 43.426678 | C17: =Assumptions!$B$21/C15 -> 28.964534

Sheet Deal & Accretion
A1: Deal Structure, Consideration & Accretion / Dilution
A2: $ in millions except per-share and ratios
A4: CONSIDERATION | C4: Announcement | D4: Current px | F4: KEY POINT
A5: New onsemi shares issued (mm) | B5: =Assumptions!$B$20*Assumptions!$B$25 -> 54.675 | F5: The exchange ratio is fixed at 1.350, so shares issued do not move with onsemi's price. EPS accretion is price-independent: the crash does not change the +/- on EPS.
A6: Equity value to Synaptics | C6: =B5*Assumptions!$B$11 -> 6492.1095 | D6: =B5*Assumptions!$B$12 -> 5077.1205
A7: (+) Net debt assumed | C7: =Assumptions!$B$23-Assumptions!$B$22 -> 432.3 | D7: =Assumptions!$B$23-Assumptions!$B$22 -> 432.3
A8: Enterprise value | C8: =C6+C7 -> 6924.4095 | D8: =D6+D7 -> 5509.4205
A10: MULTIPLES PAID | C10: Announcement | D10: Current px
A11: EV / Revenue | C11: =C8/Assumptions!$B$14 -> 5.8532625 | D11: =D8/Assumptions!$B$14 -> 4.6571602 | F11: What the price DID change: the multiple onsemi pays. ~5.9x sales at announcement vs ~4.7x post-crash. The drop made the deal cheaper for onsemi while leaving accretion intact.
A12: EV / EBITDA | C12: =C8/Standalone!C16 -> 26.726091 | D12: =D8/Standalone!C16 -> 21.264669
A13: Equity value / non-GAAP NI (P/E) | C13: =C6/Standalone!C13 -> 36.960563 | D13: =D6/Standalone!C13 -> 28.904816
A14: Premium to SYNA spot close | C14: =C6/(Assumptions!$B$21*Assumptions!$B$20)-1 -> 0.27606273 | D14: =D6/(Assumptions!$B$21*Assumptions!$B$20)-1 -> -0.0020617736
A15: Stated premium to 10-day VWAP | C15: =Assumptions!$B$26 -> 0.19
A17: PRO FORMA OWNERSHIP
A18: onsemi existing shares (mm) | B18: =Assumptions!$B$10 -> 394
A19: New shares to Synaptics (mm) | B19: =B5 -> 54.675
A20: Total pro forma shares (mm) | B20: =B18+B19 -> 448.675
A21: onsemi holders % | B21: =B18/B20 -> 0.87814119
A22: Synaptics holders % | B22: =B19/B20 -> 0.12185881
A24: ACCRETION / (DILUTION) - illustrative full-year, non-GAAP | F24: Accretion lives on synergies. Strip them out and the deal is ~+3% EPS while handing over 12% of the company. The case rests on $200M of synergies not split between cost and revenue.
B25: No synergies | C25: Year 1 (50%) | D25: Full run-rate
A26: onsemi standalone net income | B26: =Standalone!B13 -> 1077.3 | C26: =Standalone!B13 -> 1077.3 | D26: =Standalone!B13 -> 1077.3
A27: (+) Synaptics net income | B27: =Standalone!C13 -> 175.64964 | C27: =Standalone!C13 -> 175.64964 | D27: =Standalone!C13 -> 175.64964
A28: (+) After-tax synergies | B28: =Assumptions!$B$27*0*(1-Assumptions!$B$29) -> 0 | C28: =Assumptions!$B$27*Assumptions!$B$28*(1-Assumptions!$B$29) -> 84 | D28: =Assumptions!$B$27*1*(1-Assumptions!$B$29) -> 168
A29: Combined net income | B29: =SUM(B26:B28) -> 1252.9496 | C29: =SUM(C26:C28) -> 1336.9496 | D29: =SUM(D26:D28) -> 1420.9496
A30: Pro forma shares (mm) | B30: =$B$20 -> 448.675 | C30: =$B$20 -> 448.675 | D30: =$B$20 -> 448.675
A31: Pro forma non-GAAP EPS | B31: =B29/B30 -> 2.7925551 | C31: =C29/C30 -> 2.979773 | D31: =D29/D30 -> 3.1669909
A32: onsemi standalone EPS | B32: =Standalone!B15 -> 2.734264 | C32: =Standalone!B15 -> 2.734264 | D32: =Standalone!B15 -> 2.734264
A33: Accretion / (dilution) $ | B33: =B31-B32 -> 0.058291097 | C33: =C31-C32 -> 0.24550902 | D33: =D31-D32 -> 0.43272694
A34: Accretion / (dilution) % | B34: =B31/B32-1 -> 0.021318753 | C34: =C31/C32-1 -> 0.089789801 | D34: =D31/D32-1 -> 0.15826085

Sheet Sensitivity
A1: Sensitivity Tables
A3: Full-year EPS accretion / (dilution) % - synergy realization (rows) x exchange ratio (cols)
A4: Synergy \ Ex-ratio | B4: 1.25 | C4: 1.3 | D4: 1.35 | E4: 1.4 | F4: 1.45
A5: 0 | B5: =((Standalone!$B$13+Standalone!$C$13+Assumptions!$B$27*$A$5*(1-Assumptions!$B$29))/(Assumptions!$B$10+Assumptions!$B$20*$B$4))/Standalone!$B$15-1 -> 0.03062174 | C5: =((Standalone!$B$13+Standalone!$C$13+Assumptions!$B$27*$A$5*(1-Assumptions!$B$29))/(Assumptions!$B$10+Assumptions!$B$20*$C$4))/Standalone!$B$15-1 -> 0.025949158 | D5: =((Standalone!$B$13+Standalone!$C$13+Assumptions!$B$27*$A$5*(1-Assumptions!$B$29))/(Assumptions!$B$10+Assumptions!$B$20*$D$4))/Standalone!$B$15-1 -> 0.021318753 | E5: =((Standalone!$B$13+Standalone!$C$13+Assumptions!$B$27*$A$5*(1-Assumptions!$B$29))/(Assumptions!$B$10+Assumptions!$B$20*$E$4))/Standalone!$B$15-1 -> 0.016729956 | F5: =((Standalone!$B$13+Standalone!$C$13+Assumptions!$B$27*$A$5*(1-Assumptions!$B$29))/(Assumptions!$B$10+Assumptions!$B$20*$F$4))/Standalone!$B$15-1 -> 0.012182211
A6: 0.25 | B6: =((Standalone!$B$13+Standalone!$C$13+Assumptions!$B$27*$A$6*(1-Assumptions!$B$29))/(Assumptions!$B$10+Assumptions!$B$20*$B$4))/Standalone!$B$15-1 -> 0.065169109 | C6: =((Standalone!$B$13+Standalone!$C$13+Assumptions!$B$27*$A$6*(1-Assumptions!$B$29))/(Assumptions!$B$10+Assumptions!$B$20*$C$4))/Standalone!$B$15-1 -> 0.060339897 | D6: =((Standalone!$B$13+Standalone!$C$13+Assumptions!$B$27*$A$6*(1-Assumptions!$B$29))/(Assumptions!$B$10+Assumptions!$B$20*$D$4))/Standalone!$B$15-1 -> 0.055554277 | E6: =((Standalone!$B$13+Standalone!$C$13+Assumptions!$B$27*$A$6*(1-Assumptions!$B$29))/(Assumptions!$B$10+Assumptions!$B$20*$E$4))/Standalone!$B$15-1 -> 0.05081166 | F6: =((Standalone!$B$13+Standalone!$C$13+Assumptions!$B$27*$A$6*(1-Assumptions!$B$29))/(Assumptions!$B$10+Assumptions!$B$20*$F$4))/Standalone!$B$15-1 -> 0.04611147
A7: 0.5 | B7: =((Standalone!$B$13+Standalone!$C$13+Assumptions!$B$27*$A$7*(1-Assumptions!$B$29))/(Assumptions!$B$10+Assumptions!$B$20*$B$4))/Standalone!$B$15-1 -> 0.099716478 | C7: =((Standalone!$B$13+Standalone!$C$13+Assumptions!$B$27*$A$7*(1-Assumptions!$B$29))/(Assumptions!$B$10+Assumptions!$B$20*$C$4))/Standalone!$B$15-1 -> 0.094730637 | D7: =((Standalone!$B$13+Standalone!$C$13+Assumptions!$B$27*$A$7*(1-Assumptions!$B$29))/(Assumptions!$B$10+Assumptions!$B$20*$D$4))/Standalone!$B$15-1 -> 0.089789801 | E7: =((Standalone!$B$13+Standalone!$C$13+Assumptions!$B$27*$A$7*(1-Assumptions!$B$29))/(Assumptions!$B$10+Assumptions!$B$20*$E$4))/Standalone!$B$15-1 -> 0.084893364 | F7: =((Standalone!$B$13+Standalone!$C$13+Assumptions!$B$27*$A$7*(1-Assumptions!$B$29))/(Assumptions!$B$10+Assumptions!$B$20*$F$4))/Standalone!$B$15-1 -> 0.080040729
A8: 0.75 | B8: =((Standalone!$B$13+Standalone!$C$13+Assumptions!$B$27*$A$8*(1-Assumptions!$B$29))/(Assumptions!$B$10+Assumptions!$B$20*$B$4))/Standalone!$B$15-1 -> 0.13426385 | C8: =((Standalone!$B$13+Standalone!$C$13+Assumptions!$B$27*$A$8*(1-Assumptions!$B$29))/(Assumptions!$B$10+Assumptions!$B$20*$C$4))/Standalone!$B$15-1 -> 0.12912138 | D8: =((Standalone!$B$13+Standalone!$C$13+Assumptions!$B$27*$A$8*(1-Assumptions!$B$29))/(Assumptions!$B$10+Assumptions!$B$20*$D$4))/Standalone!$B$15-1 -> 0.12402533 | E8: =((Standalone!$B$13+Standalone!$C$13+Assumptions!$B$27*$A$8*(1-Assumptions!$B$29))/(Assumptions!$B$10+Assumptions!$B$20*$E$4))/Standalone!$B$15-1 -> 0.11897507 | F8: =((Standalone!$B$13+Standalone!$C$13+Assumptions!$B$27*$A$8*(1-Assumptions!$B$29))/(Assumptions!$B$10+Assumptions!$B$20*$F$4))/Standalone!$B$15-1 -> 0.11396999
A9: 1 | B9: =((Standalone!$B$13+Standalone!$C$13+Assumptions!$B$27*$A$9*(1-Assumptions!$B$29))/(Assumptions!$B$10+Assumptions!$B$20*$B$4))/Standalone!$B$15-1 -> 0.16881122 | C9: =((Standalone!$B$13+Standalone!$C$13+Assumptions!$B$27*$A$9*(1-Assumptions!$B$29))/(Assumptions!$B$10+Assumptions!$B$20*$C$4))/Standalone!$B$15-1 -> 0.16351212 | D9: =((Standalone!$B$13+Standalone!$C$13+Assumptions!$B$27*$A$9*(1-Assumptions!$B$29))/(Assumptions!$B$10+Assumptions!$B$20*$D$4))/Standalone!$B$15-1 -> 0.15826085 | E9: =((Standalone!$B$13+Standalone!$C$13+Assumptions!$B$27*$A$9*(1-Assumptions!$B$29))/(Assumptions!$B$10+Assumptions!$B$20*$E$4))/Standalone!$B$15-1 -> 0.15305677 | F9: =((Standalone!$B$13+Standalone!$C$13+Assumptions!$B$27*$A$9*(1-Assumptions!$B$29))/(Assumptions!$B$10+Assumptions!$B$20*$F$4))/Standalone!$B$15-1 -> 0.14789925
A12: What onsemi pays vs its share price (fixed 1.350 ratio)
A13: onsemi price | B13: Equity value | C13: Enterprise value | D13: EV/Revenue | E13: EV/EBITDA | F13: Prem to SYNA spot
A14: 70 | B14: =Assumptions!$B$20*Assumptions!$B$25*$A14 -> 3827.25 | C14: =B14+(Assumptions!$B$23-Assumptions!$B$22) -> 4259.55 | D14: =C14/Assumptions!$B$14 -> 3.600634 | E14: =C14/Standalone!$C$16 -> 16.440553 | F14: =B14/(Assumptions!$B$21*Assumptions!$B$20)-1 -> -0.24773125
A15: 80 | B15: =Assumptions!$B$20*Assumptions!$B$25*$A15 -> 4374 | C15: =B15+(Assumptions!$B$23-Assumptions!$B$22) -> 4806.3 | D15: =C15/Assumptions!$B$14 -> 4.0628064 | E15: =C15/Standalone!$C$16 -> 18.55084 | F15: =B15/(Assumptions!$B$21*Assumptions!$B$20)-1 -> -0.14026429
A16: 92.86 | B16: =Assumptions!$B$20*Assumptions!$B$25*$A16 -> 5077.1205 | C16: =B16+(Assumptions!$B$23-Assumptions!$B$22) -> 5509.4205 | D16: =C16/Assumptions!$B$14 -> 4.6571602 | E16: =C16/Standalone!$C$16 -> 21.264669 | F16: =B16/(Assumptions!$B$21*Assumptions!$B$20)-1 -> -0.0020617736
A17: 100 | B17: =Assumptions!$B$20*Assumptions!$B$25*$A17 -> 5467.5 | C17: =B17+(Assumptions!$B$23-Assumptions!$B$22) -> 5899.8 | D17: =C17/Assumptions!$B$14 -> 4.9871513 | E17: =C17/Standalone!$C$16 -> 22.771414 | F17: =B17/(Assumptions!$B$21*Assumptions!$B$20)-1 -> 0.074669639
A18: 118.74 | B18: =Assumptions!$B$20*Assumptions!$B$25*$A18 -> 6492.1095 | C18: =B18+(Assumptions!$B$23-Assumptions!$B$22) -> 6924.4095 | D18: =C18/Assumptions!$B$14 -> 5.8532625 | E18: =C18/Standalone!$C$16 -> 26.726091 | F18: =B18/(Assumptions!$B$21*Assumptions!$B$20)-1 -> 0.27606273
A19: 130 | B19: =Assumptions!$B$20*Assumptions!$B$25*$A19 -> 7107.75 | C19: =B19+(Assumptions!$B$23-Assumptions!$B$22) -> 7540.05 | D19: =C19/Assumptions!$B$14 -> 6.3736686 | E19: =C19/Standalone!$C$16 -> 29.102274 | F19: =B19/(Assumptions!$B$21*Assumptions!$B$20)-1 -> 0.39707053
A21: Highlighted: current price $92.86 and announcement close $118.74.

Sheet Value Creation
A1: Value Creation & Market Reaction
A2: $ in millions
A4: PREMIUM vs SYNERGY VALUE | D4: READ
A5: Offer equity value (announcement) | B5: ='Deal & Accretion'!C6 -> 6492.1095 | D5: • If the $200M synergies are real and fully captured, capitalized value exceeds the control premium, so the deal creates value on paper.
A6: SYNA undisturbed equity (10-day VWAP basis) | B6: =B5/(1+Assumptions!$B$26) -> 5455.5542
A7: Control premium paid | B7: =B5-B6 -> 1036.5553
D8: • The market disagrees. onsemi shed roughly the entire deal value and more in market cap, far above the premium paid.
A9: After-tax synergy run-rate | B9: =Assumptions!$B$27*(1-Assumptions!$B$29) -> 168
A10: Synergy value (perpetuity, disc - growth) | B10: =B9/(Assumptions!$B$31-Assumptions!$B$32) -> 2100
A11: Net value creation (synergy value - premium) | B11: =B10-B7 -> 1063.4447 | D11: • That gap is the market de-rating onsemi for strategic drift into edge compute, plus a same-day semis selloff (KOSPI halted, SK Hynix HBM scare, hawkish Fed) that is not deal-related.
A13: MARKET REACTION (today)
A14: onsemi market cap at announcement close | B14: =Assumptions!$B$11*Assumptions!$B$10 -> 46783.56 | D14: • Synergy value is highly sensitive to the discount rate and to whether the $200M is cost (credible) or revenue (speculative). Treat the perpetuity as an upper bound.
A15: onsemi market cap at current price | B15: =Assumptions!$B$12*Assumptions!$B$10 -> 36586.84
A16: Market cap change | B16: =B15-B14 -> -10196.72
A17: Deal enterprise value (announcement) | B17: ='Deal & Accretion'!C8 -> 6924.4095 | D17: • Share counts are estimates pending the S-4/proxy. Refresh diluted shares, SYNA net debt, and consensus NI when filed.
A18: Control premium paid | B18: =B7 -> 1036.5553
A19: Mkt cap loss / deal EV | B19: =-B16/B17 -> 1.4725761
A20: Mkt cap loss / premium paid | B20: =-B16/B18 -> 9.8371211
