Workbook

Sheet SOTP
B1: QUALCOMM (QCOM) | Sum-of-the-Parts Valuation | C1: $ in millions, except per share
B3: Segment | C3: EV ($mm) | D3: WACC | E3: Exit | F3: FY26E Rev | G3: FY29E Rev | H3: FY29 EBIT % | I3: % of EV | J3: EV/FY29 Rev
B4: AI Datacenter Chips | C4: =DC!C35 -> 58153.595 | D4: =DC!C31 -> 0.11 | E4: =DC!C32 -> 13 | F4: =DC!C9 -> 100 | G4: =DC!F9 -> 15000 | H4: =DC!F13 -> 0.25 | I4: =C4/C10 -> 0.25301805 | J4: =IFERROR(C4/G4,"-") -> 3.8769063
B5: QCT Handsets | C5: =Handsets!C35 -> 56721.524 | D5: =Handsets!C31 -> 0.1 | E5: =Handsets!C32 -> 10 | F5: =Handsets!C9 -> 27500 | G5: =Handsets!F9 -> 24583.68 | H5: =Handsets!F13 -> 0.26 | I5: =C5/C10 -> 0.24678731 | J5: =IFERROR(C5/G5,"-") -> 2.3072837
B6: Automotive & ADAS | C6: =Auto!C35 -> 32577.765 | D6: =Auto!C31 -> 0.11 | E6: =Auto!C32 -> 15 | F6: =Auto!C9 -> 4500 | G6: =Auto!F9 -> 9962.55 | H6: =Auto!F13 -> 0.2 | I6: =C6/C10 -> 0.14174124 | J6: =IFERROR(C6/G6,"-") -> 3.2700228
B7: Industrial & Robotics | C7: =IoT_Industrial!C35 -> 30427.35 | D7: =IoT_Industrial!C31 -> 0.11 | E7: =IoT_Industrial!C32 -> 14 | F7: =IoT_Industrial!C9 -> 3200 | G7: =IoT_Industrial!F9 -> 8529.92 | H7: =IoT_Industrial!F13 -> 0.24 | I7: =C7/C10 -> 0.13238509 | J7: =IFERROR(C7/G7,"-") -> 3.567132
B8: Personal AI & XR | C8: =IoT_PersonalAI!C35 -> 16868.329 | D8: =IoT_PersonalAI!C31 -> 0.13 | E8: =IoT_PersonalAI!C32 -> 14 | F8: =IoT_PersonalAI!C9 -> 2400 | G8: =IoT_PersonalAI!F9 -> 6333.6 | H8: =IoT_PersonalAI!F13 -> 0.18 | I8: =C8/C10 -> 0.073391711 | J8: =IFERROR(C8/G8,"-") -> 2.6633083
B9: QTL Licensing | C9: =QTL!C35 -> 35091.143 | D9: =QTL!C31 -> 0.09 | E9: =QTL!C32 -> 10 | F9: =QTL!C9 -> 5550 | G9: =QTL!F9 -> 5330.7639 | H9: =QTL!F13 -> 0.71 | I9: =C9/C10 -> 0.15267659 | J9: =IFERROR(C9/G9,"-") -> 6.5827606
B10: Total Enterprise Value | C10: =SUM(C4:C9) -> 229839.71
B12: EQUITY BRIDGE
B13: Share Price | C13: 188
B14: Total Enterprise Value | C14: =C10 -> 229839.71
B15: Less: Net Debt / (Plus: Net Cash) | C15: -6000
B16: Equity Value | C16: =C14-C15 -> 235839.71
B17: Diluted Shares (mm) | C17: 1340
B19: PRICE TARGET
B20: Scenario | C20: Equity Value ($mm) | D20: Shares (mm) | E20: Value / Share | F20: Change | G20: Key Driver
B21: Bear | C21: =C16*0.7 -> 165087.79 | D21: =C17 -> 1340 | E21: =C21/D21 -> 123.19985 | F21: =E21/$C$13-1 -> -0.34468167 | G21: DC ramp slips; Apple modem accelerates handset loss; QTL unit pressure
B22: Base | C22: =C16*1 -> 235839.71 | D22: =C17 -> 1340 | E22: =C22/D22 -> 175.99978 | F22: =E22/$C$13-1 -> -0.063830952 | G22: Investor Day achieved: $40B non-handset FY29 ($15B DC, $10B Auto, $15B IoT)
B23: Bull | C23: =C16*1.25 -> 294799.63 | D23: =C17 -> 1340 | E23: =C23/D23 -> 219.99973 | F23: =E23/$C$13-1 -> 0.17021131 | G23: DC >$20B FY29; auto pipeline overconverts; margin upside
B24: Spot price $209 (Investor Day close, Jun 24 2026). Blue = input, green = segment link, black = calc.

Sheet DC
A1: QCOM | B1: QUALCOMM (QCOM) | AI Datacenter Chips | C1: Sum-of-the-Parts DCF | $ in millions | D1: =TODAY() -> 46200 | I1: =TODAY() -> 46200
B3: Discount Period (years) | C3: 0.5133 | D3: =C3+1 -> 1.5133 | E3: =D3+1 -> 2.5133 | F3: =E3+1 -> 3.5133 | G3: =F3+1 -> 4.5133 | H3: =G3+1 -> 5.5133 | I3: =H3+1 -> 6.5133
B4: Year | C4: 2026 | D4: =C4+1 -> 2027 | E4: =D4+1 -> 2028 | F4: =E4+1 -> 2029 | G4: =F4+1 -> 2030 | H4: =G4+1 -> 2031 | I4: =H4+1 -> 2032
B5: Fiscal Year (ending September) | C5: FY2026 | D5: FY2027 | E5: FY2028 | F5: FY2029 | G5: FY2030 | H5: FY2031 | I5: FY2032
B6: Status | C6: A/E | D6: E | E6: E | F6: E | G6: E | H6: E | I6: E
B7: REVENUE
B9: Datacenter Revenue ($mm) | C9: 100 | D9: 5000 | E9: 10000 | F9: 15000 | G9: 19500 | H9: 23790 | I9: 27359
B10: Growth (% YoY, calc) | D10: =D9/C9-1 -> 49 | E10: =E9/D9-1 -> 1 | F10: =F9/E9-1 -> 0.5 | G10: =G9/F9-1 -> 0.3 | H10: =H9/G9-1 -> 0.22 | I10: =I9/H9-1 -> 0.15002102
B11: PROFITABILITY
B13: EBIT Margin (%) | C13: -1 | D13: 0.12 | E13: 0.22 | F13: 0.25 | G13: 0.27 | H13: 0.28 | I13: 0.28
B14: EBIT ($mm) | C14: =C13*C9 -> -100 | D14: =D13*D9 -> 600 | E14: =E13*E9 -> 2200 | F14: =F13*F9 -> 3750 | G14: =G13*G9 -> 5265 | H14: =H13*H9 -> 6661.2 | I14: =I13*I9 -> 7660.52
B15: Effective Tax Rate (%) | C15: 0.21 | D15: 0.21 | E15: 0.21 | F15: 0.21 | G15: 0.21 | H15: 0.21 | I15: 0.21
B16: NOPAT ($mm) | C16: =C14*(1-C15) -> -79 | D16: =D14*(1-D15) -> 474 | E16: =E14*(1-E15) -> 1738 | F16: =F14*(1-F15) -> 2962.5 | G16: =G14*(1-G15) -> 4159.35 | H16: =H14*(1-H15) -> 5262.348 | I16: =I14*(1-I15) -> 6051.8108
B17: REINVESTMENT
B20: D&A (% of revenue) | C20: 0.2667 | D20: 0.035 | E20: 0.0325 | F20: 0.035 | G20: 0.0346 | H20: 0.0346 | I20: 0.0377
B21: D&A ($mm) | C21: =C20*C9 -> 26.67 | D21: =D20*D9 -> 175 | E21: =E20*E9 -> 325 | F21: =F20*F9 -> 525 | G21: =G20*G9 -> 674.7 | H21: =H20*H9 -> 823.134 | I21: =I20*I9 -> 1031.4343
B22: CapEx (% of revenue) | C22: 0.8333 | D22: 0.1 | E22: 0.0725 | F22: 0.0633 | G22: 0.0543 | H22: 0.0494 | I22: 0.0503
B23: CapEx ($mm) | C23: =C22*C9 -> 83.33 | D23: =D22*D9 -> 500 | E23: =E22*E9 -> 725 | F23: =F22*F9 -> 949.5 | G23: =G22*G9 -> 1058.85 | H23: =H22*H9 -> 1175.226 | I23: =I22*I9 -> 1376.1577
B24: Change in NWC (% of revenue) | C24: 0.5 | D24: 0.21 | E24: 0.078 | F24: 0.068 | G24: 0.0254 | H24: 0.0201 | I24: 0.0203
B25: FREE CASH FLOW
B27: Unlevered FCF ($mm) | C27: =C16+C21-C23-C24*C9 -> -185.66 | D27: =D16+D21-D23-D24*D9 -> -901 | E27: =E16+E21-E23-E24*E9 -> 558 | F27: =F16+F21-F23-F24*F9 -> 1518 | G27: =G16+G21-G23-G24*G9 -> 3279.9 | H27: =H16+H21-H23-H24*H9 -> 4432.077 | I27: =I16+I21-I23-I24*I9 -> 5151.6997
B28: Discounted FCF ($mm) | C28: =C27/(1+$C$31)^C3 -> -175.97625 | D28: =D27/(1+$C$31)^D3 -> -769.37404 | E28: =E27/(1+$C$31)^E3 -> 429.26349 | F28: =F27/(1+$C$31)^F3 -> 1052.0553 | G28: =G27/(1+$C$31)^G3 -> 2047.8795 | H28: =H27/(1+$C$31)^H3 -> 2493.0335 | I28: =I27/(1+$C$31)^I3 -> 2610.6484
B29: VALUATION
B31: WACC (%) | C31: 0.11
B32: Exit EBIT Multiple | C32: 13
B33: PV of Terminal Value ($mm) | C33: =(C32*I14)/(1+C31)^I3 -> 50466.065
B35: SEGMENT ENTERPRISE VALUE ($mm) | C35: =C33+SUM(C28:I28) -> 58153.595

Sheet Handsets
A1: QCOM | B1: QUALCOMM (QCOM) | QCT Mobile Handsets | C1: Sum-of-the-Parts DCF | $ in millions | D1: =TODAY() -> 46200 | I1: =TODAY() -> 46200
B3: Discount Period (years) | C3: 0.5133 | D3: =C3+1 -> 1.5133 | E3: =D3+1 -> 2.5133 | F3: =E3+1 -> 3.5133 | G3: =F3+1 -> 4.5133 | H3: =G3+1 -> 5.5133 | I3: =H3+1 -> 6.5133
B4: Year | C4: 2026 | D4: =C4+1 -> 2027 | E4: =D4+1 -> 2028 | F4: =E4+1 -> 2029 | G4: =F4+1 -> 2030 | H4: =G4+1 -> 2031 | I4: =H4+1 -> 2032
B5: Fiscal Year (ending September) | C5: FY2026 | D5: FY2027 | E5: FY2028 | F5: FY2029 | G5: FY2030 | H5: FY2031 | I5: FY2032
B6: Status | C6: A/E | D6: E | E6: E | F6: E | G6: E | H6: E | I6: E
B7: REVENUE
B9: Handsets Revenue ($mm) | C9: 27500 | D9: =C9*(1+D10) -> 26675 | E9: =D9*(1+E10) -> 25608 | F9: =E9*(1+F10) -> 24583.68 | G9: =F9*(1+G10) -> 24092.006 | H9: =G9*(1+H10) -> 23851.086 | I9: =H9*(1+I10) -> 23612.575
B10: Growth (% YoY) | D10: -0.03 | E10: -0.04 | F10: -0.04 | G10: -0.02 | H10: -0.01 | I10: -0.01
B11: PROFITABILITY
B13: EBIT Margin (%) | C13: 0.27 | D13: 0.27 | E13: 0.27 | F13: 0.26 | G13: 0.26 | H13: 0.25 | I13: 0.25
B14: EBIT ($mm) | C14: =C13*C9 -> 7425 | D14: =D13*D9 -> 7202.25 | E14: =E13*E9 -> 6914.16 | F14: =F13*F9 -> 6391.7568 | G14: =G13*G9 -> 6263.9217 | H14: =H13*H9 -> 5962.7716 | I14: =I13*I9 -> 5903.1439
B15: Effective Tax Rate (%) | C15: 0.21 | D15: 0.21 | E15: 0.21 | F15: 0.21 | G15: 0.21 | H15: 0.21 | I15: 0.21
B16: NOPAT ($mm) | C16: =C14*(1-C15) -> 5865.75 | D16: =D14*(1-D15) -> 5689.7775 | E16: =E14*(1-E15) -> 5462.1864 | F16: =F14*(1-F15) -> 5049.4879 | G16: =G14*(1-G15) -> 4948.4981 | H16: =H14*(1-H15) -> 4710.5896 | I16: =I14*(1-I15) -> 4663.4837
B17: REINVESTMENT
B20: D&A (% of revenue) | C20: 0.035 | D20: 0.035 | E20: 0.035 | F20: 0.035 | G20: 0.035 | H20: 0.035 | I20: 0.035
B21: D&A ($mm) | C21: =C20*C9 -> 962.5 | D21: =D20*D9 -> 933.625 | E21: =E20*E9 -> 896.28 | F21: =F20*F9 -> 860.4288 | G21: =G20*G9 -> 843.22022 | H21: =H20*H9 -> 834.78802 | I21: =I20*I9 -> 826.44014
B22: CapEx (% of revenue) | C22: 0.04 | D22: 0.04 | E22: 0.04 | F22: 0.04 | G22: 0.04 | H22: 0.04 | I22: 0.04
B23: CapEx ($mm) | C23: =C22*C9 -> 1100 | D23: =D22*D9 -> 1067 | E23: =E22*E9 -> 1024.32 | F23: =F22*F9 -> 983.3472 | G23: =G22*G9 -> 963.68026 | H23: =H22*H9 -> 954.04345 | I23: =I22*I9 -> 944.50302
B24: Change in NWC (% of revenue) | C24: 0.01 | D24: 0.01 | E24: 0.01 | F24: 0.01 | G24: 0.01 | H24: 0.01 | I24: 0.01
B25: FREE CASH FLOW
B27: Unlevered FCF ($mm) | C27: =C16+C21-C23-C24*C9 -> 5453.25 | D27: =D16+D21-D23-D24*D9 -> 5289.6525 | E27: =E16+E21-E23-E24*E9 -> 5078.0664 | F27: =F16+F21-F23-F24*F9 -> 4680.7327 | G27: =G16+G21-G23-G24*G9 -> 4587.118 | H27: =H16+H21-H23-H24*H9 -> 4352.8233 | I27: =I16+I21-I23-I24*I9 -> 4309.295
B28: Discounted FCF ($mm) | C28: =C27/(1+$C$31)^C3 -> 5192.8831 | D28: =D27/(1+$C$31)^D3 -> 4579.1787 | E28: =E27/(1+$C$31)^E3 -> 3996.3741 | F28: =F27/(1+$C$31)^F3 -> 3348.7977 | G28: =G27/(1+$C$31)^G3 -> 2983.4743 | H28: =H27/(1+$C$31)^H3 -> 2573.7167 | I28: =I27/(1+$C$31)^I3 -> 2316.345
B29: VALUATION
B31: WACC (%) | C31: 0.1
B32: Exit EBIT Multiple | C32: 10
B33: PV of Terminal Value ($mm) | C33: =(C32*I14)/(1+C31)^I3 -> 31730.754
B35: SEGMENT ENTERPRISE VALUE ($mm) | C35: =C33+SUM(C28:I28) -> 56721.524

Sheet Auto
A1: QCOM | B1: QUALCOMM (QCOM) | Automotive & ADAS | C1: Sum-of-the-Parts DCF | $ in millions | D1: =TODAY() -> 46200 | I1: =TODAY() -> 46200
B3: Discount Period (years) | C3: 0.5133 | D3: =C3+1 -> 1.5133 | E3: =D3+1 -> 2.5133 | F3: =E3+1 -> 3.5133 | G3: =F3+1 -> 4.5133 | H3: =G3+1 -> 5.5133 | I3: =H3+1 -> 6.5133
B4: Year | C4: 2026 | D4: =C4+1 -> 2027 | E4: =D4+1 -> 2028 | F4: =E4+1 -> 2029 | G4: =F4+1 -> 2030 | H4: =G4+1 -> 2031 | I4: =H4+1 -> 2032
B5: Fiscal Year (ending September) | C5: FY2026 | D5: FY2027 | E5: FY2028 | F5: FY2029 | G5: FY2030 | H5: FY2031 | I5: FY2032
B6: Status | C6: A/E | D6: E | E6: E | F6: E | G6: E | H6: E | I6: E
B7: REVENUE
B9: Automotive Revenue ($mm) | C9: 4500 | D9: =C9*(1+D10) -> 5850 | E9: =D9*(1+E10) -> 7605 | F9: =E9*(1+F10) -> 9962.55 | G9: =F9*(1+G10) -> 11755.809 | H9: =G9*(1+H10) -> 13519.18 | I9: =H9*(1+I10) -> 15141.482
B10: Growth (% YoY) | D10: 0.3 | E10: 0.3 | F10: 0.31 | G10: 0.18 | H10: 0.15 | I10: 0.12
B11: PROFITABILITY
B13: EBIT Margin (%) | C13: 0.14 | D13: 0.12 | E13: 0.16 | F13: 0.2 | G13: 0.22 | H13: 0.24 | I13: 0.24
B14: EBIT ($mm) | C14: =C13*C9 -> 630 | D14: =D13*D9 -> 702 | E14: =E13*E9 -> 1216.8 | F14: =F13*F9 -> 1992.51 | G14: =G13*G9 -> 2586.278 | H14: =H13*H9 -> 3244.6033 | I14: =I13*I9 -> 3633.9557
B15: Effective Tax Rate (%) | C15: 0.21 | D15: 0.21 | E15: 0.21 | F15: 0.21 | G15: 0.21 | H15: 0.21 | I15: 0.21
B16: NOPAT ($mm) | C16: =C14*(1-C15) -> 497.7 | D16: =D14*(1-D15) -> 554.58 | E16: =E14*(1-E15) -> 961.272 | F16: =F14*(1-F15) -> 1574.0829 | G16: =G14*(1-G15) -> 2043.1596 | H16: =H14*(1-H15) -> 2563.2366 | I16: =I14*(1-I15) -> 2870.825
B17: REINVESTMENT
B20: D&A (% of revenue) | C20: 0.04 | D20: 0.04 | E20: 0.04 | F20: 0.035 | G20: 0.035 | H20: 0.035 | I20: 0.035
B21: D&A ($mm) | C21: =C20*C9 -> 180 | D21: =D20*D9 -> 234 | E21: =E20*E9 -> 304.2 | F21: =F20*F9 -> 348.68925 | G21: =G20*G9 -> 411.45332 | H21: =H20*H9 -> 473.17131 | I21: =I20*I9 -> 529.95187
B22: CapEx (% of revenue) | C22: 0.05 | D22: 0.05 | E22: 0.05 | F22: 0.045 | G22: 0.04 | H22: 0.04 | I22: 0.04
B23: CapEx ($mm) | C23: =C22*C9 -> 225 | D23: =D22*D9 -> 292.5 | E23: =E22*E9 -> 380.25 | F23: =F22*F9 -> 448.31475 | G23: =G22*G9 -> 470.23236 | H23: =H22*H9 -> 540.76721 | I23: =I22*I9 -> 605.65928
B24: Change in NWC (% of revenue) | C24: 0.06 | D24: 0.05 | E24: 0.04 | F24: 0.035 | G24: 0.03 | H24: 0.03 | I24: 0.03
B25: FREE CASH FLOW
B27: Unlevered FCF ($mm) | C27: =C16+C21-C23-C24*C9 -> 182.7 | D27: =D16+D21-D23-D24*D9 -> 203.58 | E27: =E16+E21-E23-E24*E9 -> 581.022 | F27: =F16+F21-F23-F24*F9 -> 1125.7682 | G27: =G16+G21-G23-G24*G9 -> 1631.7063 | H27: =H16+H21-H23-H24*H9 -> 2090.0653 | I27: =I16+I21-I23-I24*I9 -> 2340.8731
B28: Discounted FCF ($mm) | C28: =C27/(1+$C$31)^C3 -> 173.17064 | D28: =D27/(1+$C$31)^D3 -> 173.83925 | E28: =E27/(1+$C$31)^E3 -> 446.97408 | F28: =F27/(1+$C$31)^F3 -> 780.21759 | G28: =G27/(1+$C$31)^G3 -> 1018.7926 | H28: =H27/(1+$C$31)^H3 -> 1175.6571 | I28: =I27/(1+$C$31)^I3 -> 1186.2486
B29: VALUATION
B31: WACC (%) | C31: 0.11
B32: Exit EBIT Multiple | C32: 15
B33: PV of Terminal Value ($mm) | C33: =(C32*I14)/(1+C31)^I3 -> 27622.865
B35: SEGMENT ENTERPRISE VALUE ($mm) | C35: =C33+SUM(C28:I28) -> 32577.765

Sheet IoT_Industrial
A1: QCOM | B1: QUALCOMM (QCOM) | Industrial, Networking & Robotics | C1: Sum-of-the-Parts DCF | $ in millions | D1: =TODAY() -> 46200 | I1: =TODAY() -> 46200
B3: Discount Period (years) | C3: 0.5133 | D3: =C3+1 -> 1.5133 | E3: =D3+1 -> 2.5133 | F3: =E3+1 -> 3.5133 | G3: =F3+1 -> 4.5133 | H3: =G3+1 -> 5.5133 | I3: =H3+1 -> 6.5133
B4: Year | C4: 2026 | D4: =C4+1 -> 2027 | E4: =D4+1 -> 2028 | F4: =E4+1 -> 2029 | G4: =F4+1 -> 2030 | H4: =G4+1 -> 2031 | I4: =H4+1 -> 2032
B5: Fiscal Year (ending September) | C5: FY2026 | D5: FY2027 | E5: FY2028 | F5: FY2029 | G5: FY2030 | H5: FY2031 | I5: FY2032
B6: Status | C6: A/E | D6: E | E6: E | F6: E | G6: E | H6: E | I6: E
B7: REVENUE
B9: Industrial IoT Revenue ($mm) | C9: 3200 | D9: =C9*(1+D10) -> 4480 | E9: =D9*(1+E10) -> 6272 | F9: =E9*(1+F10) -> 8529.92 | G9: =F9*(1+G10) -> 10235.904 | H9: =G9*(1+H10) -> 11771.29 | I9: =H9*(1+I10) -> 12948.419
B10: Growth (% YoY) | D10: 0.4 | E10: 0.4 | F10: 0.36 | G10: 0.2 | H10: 0.15 | I10: 0.1
B11: PROFITABILITY
B13: EBIT Margin (%) | C13: 0.14 | D13: 0.16 | E13: 0.2 | F13: 0.24 | G13: 0.26 | H13: 0.27 | I13: 0.27
B14: EBIT ($mm) | C14: =C13*C9 -> 448 | D14: =D13*D9 -> 716.8 | E14: =E13*E9 -> 1254.4 | F14: =F13*F9 -> 2047.1808 | G14: =G13*G9 -> 2661.335 | H14: =H13*H9 -> 3178.2482 | I14: =I13*I9 -> 3496.073
B15: Effective Tax Rate (%) | C15: 0.21 | D15: 0.21 | E15: 0.21 | F15: 0.21 | G15: 0.21 | H15: 0.21 | I15: 0.21
B16: NOPAT ($mm) | C16: =C14*(1-C15) -> 353.92 | D16: =D14*(1-D15) -> 566.272 | E16: =E14*(1-E15) -> 990.976 | F16: =F14*(1-F15) -> 1617.2728 | G16: =G14*(1-G15) -> 2102.4547 | H16: =H14*(1-H15) -> 2510.8161 | I16: =I14*(1-I15) -> 2761.8977
B17: REINVESTMENT
B20: D&A (% of revenue) | C20: 0.04 | D20: 0.035 | E20: 0.035 | F20: 0.035 | G20: 0.035 | H20: 0.035 | I20: 0.035
B21: D&A ($mm) | C21: =C20*C9 -> 128 | D21: =D20*D9 -> 156.8 | E21: =E20*E9 -> 219.52 | F21: =F20*F9 -> 298.5472 | G21: =G20*G9 -> 358.25664 | H21: =H20*H9 -> 411.99514 | I21: =I20*I9 -> 453.19465
B22: CapEx (% of revenue) | C22: 0.05 | D22: 0.05 | E22: 0.045 | F22: 0.04 | G22: 0.04 | H22: 0.04 | I22: 0.04
B23: CapEx ($mm) | C23: =C22*C9 -> 160 | D23: =D22*D9 -> 224 | E23: =E22*E9 -> 282.24 | F23: =F22*F9 -> 341.1968 | G23: =G22*G9 -> 409.43616 | H23: =H22*H9 -> 470.85158 | I23: =I22*I9 -> 517.93674
B24: Change in NWC (% of revenue) | C24: 0.04 | D24: 0.035 | E24: 0.03 | F24: 0.025 | G24: 0.02 | H24: 0.02 | I24: 0.02
B25: FREE CASH FLOW
B27: Unlevered FCF ($mm) | C27: =C16+C21-C23-C24*C9 -> 193.92 | D27: =D16+D21-D23-D24*D9 -> 342.272 | E27: =E16+E21-E23-E24*E9 -> 740.096 | F27: =F16+F21-F23-F24*F9 -> 1361.3752 | G27: =G16+G21-G23-G24*G9 -> 1846.5571 | H27: =H16+H21-H23-H24*H9 -> 2216.5338 | I27: =I16+I21-I23-I24*I9 -> 2438.1872
B28: Discounted FCF ($mm) | C28: =C27/(1+$C$31)^C3 -> 183.80542 | D28: =D27/(1+$C$31)^D3 -> 292.26991 | E28: =E27/(1+$C$31)^E3 -> 569.34802 | F28: =F27/(1+$C$31)^F3 -> 943.50591 | G28: =G27/(1+$C$31)^G3 -> 1152.9395 | H28: =H27/(1+$C$31)^H3 -> 1246.7954 | I28: =I27/(1+$C$31)^I3 -> 1235.563
B29: VALUATION
B31: WACC (%) | C31: 0.11
B32: Exit EBIT Multiple | C32: 14
B33: PV of Terminal Value ($mm) | C33: =(C32*I14)/(1+C31)^I3 -> 24803.123
B35: SEGMENT ENTERPRISE VALUE ($mm) | C35: =C33+SUM(C28:I28) -> 30427.35

Sheet IoT_PersonalAI
A1: QCOM | B1: QUALCOMM (QCOM) | Personal AI & XR Compute | C1: Sum-of-the-Parts DCF | $ in millions | D1: =TODAY() -> 46200 | I1: =TODAY() -> 46200
B3: Discount Period (years) | C3: 0.5133 | D3: =C3+1 -> 1.5133 | E3: =D3+1 -> 2.5133 | F3: =E3+1 -> 3.5133 | G3: =F3+1 -> 4.5133 | H3: =G3+1 -> 5.5133 | I3: =H3+1 -> 6.5133
B4: Year | C4: 2026 | D4: =C4+1 -> 2027 | E4: =D4+1 -> 2028 | F4: =E4+1 -> 2029 | G4: =F4+1 -> 2030 | H4: =G4+1 -> 2031 | I4: =H4+1 -> 2032
B5: Fiscal Year (ending September) | C5: FY2026 | D5: FY2027 | E5: FY2028 | F5: FY2029 | G5: FY2030 | H5: FY2031 | I5: FY2032
B6: Status | C6: A/E | D6: E | E6: E | F6: E | G6: E | H6: E | I6: E
B7: REVENUE
B9: Personal AI / XR Revenue ($mm) | C9: 2400 | D9: =C9*(1+D10) -> 3480 | E9: =D9*(1+E10) -> 4872 | F9: =E9*(1+F10) -> 6333.6 | G9: =F9*(1+G10) -> 7600.32 | H9: =G9*(1+H10) -> 8740.368 | I9: =H9*(1+I10) -> 9789.2122
B10: Growth (% YoY) | D10: 0.45 | E10: 0.4 | F10: 0.3 | G10: 0.2 | H10: 0.15 | I10: 0.12
B11: PROFITABILITY
B13: EBIT Margin (%) | C13: -0.1 | D13: 0.05 | E13: 0.12 | F13: 0.18 | G13: 0.22 | H13: 0.24 | I13: 0.24
B14: EBIT ($mm) | C14: =C13*C9 -> -240 | D14: =D13*D9 -> 174 | E14: =E13*E9 -> 584.64 | F14: =F13*F9 -> 1140.048 | G14: =G13*G9 -> 1672.0704 | H14: =H13*H9 -> 2097.6883 | I14: =I13*I9 -> 2349.4109
B15: Effective Tax Rate (%) | C15: 0.21 | D15: 0.21 | E15: 0.21 | F15: 0.21 | G15: 0.21 | H15: 0.21 | I15: 0.21
B16: NOPAT ($mm) | C16: =C14*(1-C15) -> -189.6 | D16: =D14*(1-D15) -> 137.46 | E16: =E14*(1-E15) -> 461.8656 | F16: =F14*(1-F15) -> 900.63792 | G16: =G14*(1-G15) -> 1320.9356 | H16: =H14*(1-H15) -> 1657.1738 | I16: =I14*(1-I15) -> 1856.0346
B17: REINVESTMENT
B20: D&A (% of revenue) | C20: 0.05 | D20: 0.04 | E20: 0.04 | F20: 0.035 | G20: 0.035 | H20: 0.035 | I20: 0.035
B21: D&A ($mm) | C21: =C20*C9 -> 120 | D21: =D20*D9 -> 139.2 | E21: =E20*E9 -> 194.88 | F21: =F20*F9 -> 221.676 | G21: =G20*G9 -> 266.0112 | H21: =H20*H9 -> 305.91288 | I21: =I20*I9 -> 342.62243
B22: CapEx (% of revenue) | C22: 0.08 | D22: 0.07 | E22: 0.06 | F22: 0.055 | G22: 0.05 | H22: 0.045 | I22: 0.04
B23: CapEx ($mm) | C23: =C22*C9 -> 192 | D23: =D22*D9 -> 243.6 | E23: =E22*E9 -> 292.32 | F23: =F22*F9 -> 348.348 | G23: =G22*G9 -> 380.016 | H23: =H22*H9 -> 393.31656 | I23: =I22*I9 -> 391.56849
B24: Change in NWC (% of revenue) | C24: 0.06 | D24: 0.05 | E24: 0.04 | F24: 0.03 | G24: 0.025 | H24: 0.02 | I24: 0.02
B25: FREE CASH FLOW
B27: Unlevered FCF ($mm) | C27: =C16+C21-C23-C24*C9 -> -405.6 | D27: =D16+D21-D23-D24*D9 -> -140.94 | E27: =E16+E21-E23-E24*E9 -> 169.5456 | F27: =F16+F21-F23-F24*F9 -> 583.95792 | G27: =G16+G21-G23-G24*G9 -> 1016.9228 | H27: =H16+H21-H23-H24*H9 -> 1394.9627 | I27: =I16+I21-I23-I24*I9 -> 1611.3043
B28: Discounted FCF ($mm) | C28: =C27/(1+$C$31)^C3 -> -380.93667 | D28: =D27/(1+$C$31)^D3 -> -117.14147 | E28: =E27/(1+$C$31)^E3 -> 124.70517 | F28: =F27/(1+$C$31)^F3 -> 380.10279 | G28: =G27/(1+$C$31)^G3 -> 585.7726 | H28: =H27/(1+$C$31)^H3 -> 711.09107 | I28: =I27/(1+$C$31)^I3 -> 726.87837
B29: VALUATION
B31: WACC (%) | C31: 0.13
B32: Exit EBIT Multiple | C32: 14
B33: PV of Terminal Value ($mm) | C33: =(C32*I14)/(1+C31)^I3 -> 14837.857
B35: SEGMENT ENTERPRISE VALUE ($mm) | C35: =C33+SUM(C28:I28) -> 16868.329

Sheet QTL
A1: QCOM | B1: QUALCOMM (QCOM) | Technology Licensing | C1: Sum-of-the-Parts DCF | $ in millions | D1: =TODAY() -> 46200 | I1: =TODAY() -> 46200
B3: Discount Period (years) | C3: 0.5133 | D3: =C3+1 -> 1.5133 | E3: =D3+1 -> 2.5133 | F3: =E3+1 -> 3.5133 | G3: =F3+1 -> 4.5133 | H3: =G3+1 -> 5.5133 | I3: =H3+1 -> 6.5133
B4: Year | C4: 2026 | D4: =C4+1 -> 2027 | E4: =D4+1 -> 2028 | F4: =E4+1 -> 2029 | G4: =F4+1 -> 2030 | H4: =G4+1 -> 2031 | I4: =H4+1 -> 2032
B5: Fiscal Year (ending September) | C5: FY2026 | D5: FY2027 | E5: FY2028 | F5: FY2029 | G5: FY2030 | H5: FY2031 | I5: FY2032
B6: Status | C6: A/E | D6: E | E6: E | F6: E | G6: E | H6: E | I6: E
B7: REVENUE
B9: Licensing Revenue ($mm) | C9: 5550 | D9: =C9*(1+D10) -> 5494.5 | E9: =D9*(1+E10) -> 5439.555 | F9: =E9*(1+F10) -> 5330.7639 | G9: =F9*(1+G10) -> 5224.1486 | H9: =G9*(1+H10) -> 5093.5449 | I9: =H9*(1+I10) -> 4966.2063
B10: Growth (% YoY) | D10: -0.01 | E10: -0.01 | F10: -0.02 | G10: -0.02 | H10: -0.025 | I10: -0.025
B11: PROFITABILITY
B13: EBIT Margin (%) | C13: 0.72 | D13: 0.72 | E13: 0.71 | F13: 0.71 | G13: 0.7 | H13: 0.7 | I13: 0.69
B14: EBIT ($mm) | C14: =C13*C9 -> 3996 | D14: =D13*D9 -> 3956.04 | E14: =E13*E9 -> 3862.084 | F14: =F13*F9 -> 3784.8424 | G14: =G13*G9 -> 3656.904 | H14: =H13*H9 -> 3565.4814 | I14: =I13*I9 -> 3426.6823
B15: Effective Tax Rate (%) | C15: 0.21 | D15: 0.21 | E15: 0.21 | F15: 0.21 | G15: 0.21 | H15: 0.21 | I15: 0.21
B16: NOPAT ($mm) | C16: =C14*(1-C15) -> 3156.84 | D16: =D14*(1-D15) -> 3125.2716 | E16: =E14*(1-E15) -> 3051.0464 | F16: =F14*(1-F15) -> 2990.0255 | G16: =G14*(1-G15) -> 2888.9542 | H16: =H14*(1-H15) -> 2816.7303 | I16: =I14*(1-I15) -> 2707.079
B17: REINVESTMENT
B20: D&A (% of revenue) | C20: 0.005 | D20: 0.005 | E20: 0.005 | F20: 0.005 | G20: 0.005 | H20: 0.005 | I20: 0.005
B21: D&A ($mm) | C21: =C20*C9 -> 27.75 | D21: =D20*D9 -> 27.4725 | E21: =E20*E9 -> 27.197775 | F21: =F20*F9 -> 26.65382 | G21: =G20*G9 -> 26.120743 | H21: =H20*H9 -> 25.467725 | I21: =I20*I9 -> 24.831031
B22: CapEx (% of revenue) | C22: 0.005 | D22: 0.005 | E22: 0.005 | F22: 0.005 | G22: 0.005 | H22: 0.005 | I22: 0.005
B23: CapEx ($mm) | C23: =C22*C9 -> 27.75 | D23: =D22*D9 -> 27.4725 | E23: =E22*E9 -> 27.197775 | F23: =F22*F9 -> 26.65382 | G23: =G22*G9 -> 26.120743 | H23: =H22*H9 -> 25.467725 | I23: =I22*I9 -> 24.831031
B24: Change in NWC (% of revenue) | C24: 0.005 | D24: 0.005 | E24: 0.005 | F24: 0.005 | G24: 0.005 | H24: 0.005 | I24: 0.005
B25: FREE CASH FLOW
B27: Unlevered FCF ($mm) | C27: =C16+C21-C23-C24*C9 -> 3129.09 | D27: =D16+D21-D23-D24*D9 -> 3097.7991 | E27: =E16+E21-E23-E24*E9 -> 3023.8486 | F27: =F16+F21-F23-F24*F9 -> 2963.3717 | G27: =G16+G21-G23-G24*G9 -> 2862.8334 | H27: =H16+H21-H23-H24*H9 -> 2791.2626 | I27: =I16+I21-I23-I24*I9 -> 2682.248
B28: Discounted FCF ($mm) | C28: =C27/(1+$C$31)^C3 -> 2993.6914 | D28: =D27/(1+$C$31)^D3 -> 2719.0408 | E28: =E27/(1+$C$31)^E3 -> 2434.9835 | F28: =F27/(1+$C$31)^F3 -> 2189.2513 | G28: =G27/(1+$C$31)^G3 -> 1940.3455 | H28: =H27/(1+$C$31)^H3 -> 1735.6302 | I28: =I27/(1+$C$31)^I3 -> 1530.1321
B29: VALUATION
B31: WACC (%) | C31: 0.09
B32: Exit EBIT Multiple | C32: 10
B33: PV of Terminal Value ($mm) | C33: =(C32*I14)/(1+C31)^I3 -> 19548.068
B35: SEGMENT ENTERPRISE VALUE ($mm) | C35: =C33+SUM(C28:I28) -> 35091.143
