Workbook

Sheet Income Statement
A1: Quest Diagnostics Incorporated
A2: Consolidated Statements of Operations
A3: In Millions, Except Per Share Amounts
B4: FY2021 | C4: FY2022 | D4: FY2023 | E4: FY2024 | F4: FY2025
A5: Net revenues | B5: 10788 | C5: 9883 | D5: 9252 | E5: 9872 | F5: 11035
A6: Cost of services | B6: 6579 | C6: 6450 | D6: 6199 | E6: 6628 | F6: 7370
A7: Gross profit | B7: =B5-B6 -> 4209 | C7: =C5-C6 -> 3433 | D7: =D5-D6 -> 3053 | E7: =E5-E6 -> 3244 | F7: =F5-F6 -> 3665
A8: Selling, general and administrative | B8: 1727 | C8: 1874 | D8: 1642 | E8: 1770 | F8: 1967
A9: Amortization of intangible assets | B9: 103 | C9: 120 | D9: 108 | E9: 127 | F9: 154
A10: Other operating expense (income), net | B10: -2 | C10: 11 | D10: 41 | E10: 1 | F10: -12
A11: Total operating costs and expenses, net | B11: =B6+B8+B9+B10 -> 8407 | C11: =C6+C8+C9+C10 -> 8455 | D11: =D6+D8+D9+D10 -> 7990 | E11: =E6+E8+E9+E10 -> 8526 | F11: =F6+F8+F9+F10 -> 9479
A12: Operating income | B12: =B5-B11 -> 2381 | C12: =C5-C11 -> 1428 | D12: =D5-D11 -> 1262 | E12: =E5-E11 -> 1346 | F12: =F5-F11 -> 1556
A13: Interest expense, net | B13: -151 | C13: -138 | D13: -152 | E13: -201 | F13: -264
A14: Other income (expense), net | B14: 369 | C14: -55 | D14: 20 | E14: 30 | F14: 26
A15: Total non-operating income (expense), net | B15: =B13+B14 -> 218 | C15: =C13+C14 -> -193 | D15: =D13+D14 -> -132 | E15: =E13+E14 -> -171 | F15: =F13+F14 -> -238
A16: Income before income taxes and equity in earnings of equity method investees | B16: =B12+B15 -> 2599 | C16: =C12+C15 -> 1235 | D16: =D12+D15 -> 1130 | E16: =E12+E15 -> 1175 | F16: =F12+F15 -> 1318
A17: Income tax expense | B17: -597 | C17: -264 | D17: -248 | E17: -273 | F17: -314
A18: Equity in earnings of equity method investees, net of taxes | B18: 78 | C18: 44 | D18: 26 | E18: 19 | F18: 42
A19: Net income | B19: =B16+B17+B18 -> 2080 | C19: =C16+C17+C18 -> 1015 | D19: =D16+D17+D18 -> 908 | E19: =E16+E17+E18 -> 921 | F19: =F16+F17+F18 -> 1046
A20: Less: Net income attributable to noncontrolling interests | B20: 85 | C20: 69 | D20: 54 | E20: 50 | F20: 54
A21: Net income attributable to Quest Diagnostics | B21: =B19-B20 -> 1995 | C21: =C19-C20 -> 946 | D21: =D19-D20 -> 854 | E21: =E19-E20 -> 871 | F21: =F19-F20 -> 992
A23: Earnings per share attributable to Quest Diagnostics common stockholders:
A24: Basic ($) | B24: 15.85 | C24: 8.1 | D24: 7.59 | E24: 7.78 | F24: 8.87
A25: Diluted ($) | B25: 15.55 | C25: 7.97 | D25: 7.49 | E25: 7.69 | F25: 8.75
A27: Weighted average shares outstanding (millions):
A28: Basic | B28: 125.9 | C28: 116.8 | D28: 112.5 | E28: 112 | F28: 111.8
A29: Diluted | B29: 128.3 | C29: 118.7 | D29: 114 | E29: 113.3 | F29: 113.4

Sheet Balance Sheet
A1: Quest Diagnostics Incorporated
A2: Consolidated Balance Sheets
A3: In Millions
B4: FY2021 | C4: FY2022 | D4: FY2023 | E4: FY2024 | F4: FY2025
A5: ASSETS
A6: Current assets:
A7: Cash and cash equivalents | B7: 872 | C7: 315 | D7: 686 | E7: 549 | F7: 420
A8: Accounts receivable, net | B8: 1438 | C8: 1195 | D8: 1210 | E8: 1304 | F8: 1408
A9: Inventories | B9: 208 | C9: 192 | D9: 190 | E9: 188 | F9: 189
A10: Prepaid expenses and other current assets | B10: 223 | C10: 196 | D10: 286 | E10: 351 | F10: 361
A11: Total current assets | B11: =B7+B8+B9+B10 -> 2741 | C11: =C7+C8+C9+C10 -> 1898 | D11: =D7+D8+D9+D10 -> 2372 | E11: =E7+E8+E9+E10 -> 2392 | F11: =F7+F8+F9+F10 -> 2378
A12: Property, plant and equipment, net | B12: 1707 | C12: 1766 | D12: 1816 | E12: 2113 | F12: 2203
A13: Operating lease right-of-use assets | B13: 597 | C13: 585 | D13: 602 | E13: 651 | F13: 657
A14: Goodwill | B14: 7095 | C14: 7220 | D14: 7733 | E14: 8856 | F14: 8945
A15: Intangible assets, net | B15: 1167 | C15: 1092 | D15: 1166 | E15: 1763 | F15: 1636
A16: Investments in equity method investees | B16: 141 | C16: 132 | D16: 135 | E16: 123 | F16: 136
A17: Other assets | B17: 163 | C17: 144 | D17: 198 | E17: 255 | F17: 270
A18: Total assets | B18: =B11+B12+B13+B14+B15+B16+B17 -> 13611 | C18: =C11+C12+C13+C14+C15+C16+C17 -> 12837 | D18: =D11+D12+D13+D14+D15+D16+D17 -> 14022 | E18: =E11+E12+E13+E14+E15+E16+E17 -> 16153 | F18: =F11+F12+F13+F14+F15+F16+F17 -> 16225
A20: LIABILITIES AND STOCKHOLDERS' EQUITY
A21: Current liabilities:
A22: Accounts payable and accrued expenses | B22: 1600 | C22: 1396 | D22: 1359 | E22: 1394 | F22: 1600
A23: Current portion of long-term debt | B23: 2 | C23: 2 | D23: 303 | E23: 602 | F23: 504
A24: Current portion of long-term operating lease liabilities | B24: 151 | C24: 153 | D24: 153 | E24: 173 | F24: 174
A25: Total current liabilities | B25: =B22+B23+B24 -> 1753 | C25: =C22+C23+C24 -> 1551 | D25: =D22+D23+D24 -> 1815 | E25: =E22+E23+E24 -> 2169 | F25: =F22+F23+F24 -> 2278
A26: Long-term debt | B26: 4010 | C26: 3978 | D26: 4410 | E26: 5615 | F26: 5167
A27: Long-term operating lease liabilities | B27: 494 | C27: 489 | D27: 503 | E27: 535 | F27: 537
A28: Other liabilities | B28: 792 | C28: 812 | D28: 876 | E28: 938 | F28: 957
A29: Total liabilities | B29: =B25+B26+B27+B28 -> 7049 | C29: =C25+C26+C27+C28 -> 6830 | D29: =D25+D26+D27+D28 -> 7604 | E29: =E25+E26+E27+E28 -> 9257 | F29: =F25+F26+F27+F28 -> 8939
A30: Redeemable noncontrolling interest (mezzanine) | B30: 79 | C30: 77 | D30: 76 | E30: 83 | F30: 80
A31: Stockholders' equity:
A32: Common stock and additional paid-in capital | B32: 2262 | C32: 2297 | D32: 2322 | E32: 2363 | F32: 2383
A33: Retained earnings | B33: 7649 | C33: 8290 | D33: 8825 | E33: 9360 | F33: 9994
A34: Accumulated other comprehensive loss | B34: -14 | C34: -21 | D34: -14 | E34: -88 | F34: -27
A35: Treasury stock, at cost | B35: -3453 | C35: -4673 | D35: -4826 | E35: -4857 | F35: -5180
A36: Total Quest Diagnostics stockholders' equity | B36: =B32+B33+B34+B35 -> 6444 | C36: =C32+C33+C34+C35 -> 5893 | D36: =D32+D33+D34+D35 -> 6307 | E36: =E32+E33+E34+E35 -> 6778 | F36: =F32+F33+F34+F35 -> 7170
A37: Noncontrolling interests | B37: 39 | C37: 37 | D37: 35 | E37: 35 | F37: 36
A38: Total stockholders' equity | B38: =B36+B37 -> 6483 | C38: =C36+C37 -> 5930 | D38: =D36+D37 -> 6342 | E38: =E36+E37 -> 6813 | F38: =F36+F37 -> 7206
A39: Total liabilities and stockholders' equity | B39: =B29+B30+B38 -> 13611 | C39: =C29+C30+C38 -> 12837 | D39: =D29+D30+D38 -> 14022 | E39: =E29+E30+E38 -> 16153 | F39: =F29+F30+F38 -> 16225

Sheet Cash Flow Statement
A1: Quest Diagnostics Incorporated
A2: Consolidated Statements of Cash Flows
A3: In Millions
B4: FY2021 | C4: FY2022 | D4: FY2023 | E4: FY2024 | F4: FY2025
A5: Cash and cash equivalents, beginning of year | B5: 1158 | C5: 872 | D5: 315 | E5: 686 | F5: 549
A7: OPERATING ACTIVITIES
A8: Net income | B8: 2080 | C8: 1015 | D8: 908 | E8: 921 | F8: 1046
A9: Adjustments to reconcile net income to net cash provided by operating activities:
A10: Depreciation and amortization | B10: 408 | C10: 437 | D10: 439 | E10: 493 | F10: 570
A11: Provision for credit losses | B11: 4 | C11: 3 | D11: 1 | E11: 5 | F11: 3
A12: Deferred income tax provision (benefit) | B12: -57 | C12: 1 | D12: -49 | E12: 13 | F12: 105
A13: Stock-based compensation expense | B13: 79 | C13: 77 | D13: 77 | E13: 88 | F13: 88
A14: Gain on disposition of joint venture | B14: -314 | C14: 0 | D14: 0 | E14: 0 | F14: 0
A15: Other, net | B15: -54 | C15: 66 | D15: 41 | E15: 15 | F15: 24
A16: Accounts receivable | B16: 81 | C16: 246 | D16: -15 | E16: -71 | F16: -106
A17: Accounts payable and accrued expenses | B17: 35 | C17: -149 | D17: -55 | E17: -67 | F17: 129
A18: Income taxes payable | B18: -20 | C18: -31 | D18: -2 | E18: 16 | F18: 24
A19: Termination of interest rate swap agreements | B19: 0 | C19: 0 | D19: 0 | E19: 0 | F19: 0
A20: Other assets and liabilities, net | B20: -9 | C20: 53 | D20: -73 | E20: -79 | F20: 3
A21: Net cash provided by operating activities | B21: =B8+B10+B11+B12+B13+B14+B15+B16+B17+B18+B19+B20 -> 2233 | C21: =C8+C10+C11+C12+C13+C14+C15+C16+C17+C18+C19+C20 -> 1718 | D21: =D8+D10+D11+D12+D13+D14+D15+D16+D17+D18+D19+D20 -> 1272 | E21: =E8+E10+E11+E12+E13+E14+E15+E16+E17+E18+E19+E20 -> 1334 | F21: =F8+F10+F11+F12+F13+F14+F15+F16+F17+F18+F19+F20 -> 1886
A23: INVESTING ACTIVITIES
A24: Business acquisitions, net of cash acquired | B24: -331 | C24: -144 | D24: -611 | E24: -2164 | F24: -101
A25: Proceeds from disposition of joint venture | B25: 755 | C25: 0 | D25: 0 | E25: 0 | F25: 0
A26: Capital expenditures | B26: -403 | C26: -404 | D26: -408 | E26: -425 | F26: -527
A27: Other investing activities, net | B27: 0 | C27: 5 | D27: -42 | E27: 41 | F27: -3
A28: Net cash provided by (used in) investing activities | B28: =B24+B25+B26+B27 -> 21 | C28: =C24+C25+C26+C27 -> -543 | D28: =D24+D25+D26+D27 -> -1061 | E28: =E24+E25+E26+E27 -> -2548 | F28: =F24+F25+F26+F27 -> -631
A30: FINANCING ACTIVITIES
A31: Proceeds from borrowings | B31: 0 | C31: 0 | D31: 2592 | E31: 1846 | F31: 410
A32: Repayments of debt | B32: -2 | C32: -2 | D32: -1844 | E32: -303 | F32: -1012
A33: Purchases of treasury stock | B33: -2199 | C33: -1408 | D33: -275 | E33: -151 | F33: -450
A34: Exercise of stock options | B34: 129 | C34: 123 | D34: 72 | E34: 73 | F34: 79
A35: Employee payroll tax withholdings on stock issued under stock-based compensation plans | B35: -22 | C35: -28 | D35: -28 | E35: -24 | F35: -45
A36: Dividends paid | B36: -309 | C36: -305 | D36: -314 | E36: -331 | F36: -353
A37: Distributions to noncontrolling interest partners | B37: -99 | C37: -73 | D37: -57 | E37: -47 | F37: -56
A38: Other financing activities, net | B38: -38 | C38: -39 | D38: 14 | E38: 21 | F38: 39
A39: Net cash provided by (used in) financing activities | B39: =B31+B32+B33+B34+B35+B36+B37+B38 -> -2540 | C39: =C31+C32+C33+C34+C35+C36+C37+C38 -> -1732 | D39: =D31+D32+D33+D34+D35+D36+D37+D38 -> 160 | E39: =E31+E32+E33+E34+E35+E36+E37+E38 -> 1084 | F39: =F31+F32+F33+F34+F35+F36+F37+F38 -> -1388
A40: Effect of exchange rate changes on cash and cash equivalents | B40: 0 | C40: 0 | D40: 0 | E40: -7 | F40: 4
A42: Net change in cash and cash equivalents | B42: =B21+B28+B39+B40 -> -286 | C42: =C21+C28+C39+C40 -> -557 | D42: =D21+D28+D39+D40 -> 371 | E42: =E21+E28+E39+E40 -> -137 | F42: =F21+F28+F39+F40 -> -129
A43: Cash and cash equivalents, end of year | B43: =B5+B42 -> 872 | C43: =C5+C42 -> 315 | D43: =D5+D42 -> 686 | E43: =E5+E42 -> 549 | F43: =F5+F42 -> 420

Sheet Segment & Volume
A1: Quest Diagnostics Incorporated
A2: Segment Revenue, Volume and Payer Mix
A3: In Millions unless stated otherwise
B4: FY2021 | C4: FY2022 | D4: FY2023 | E4: FY2024 | F4: FY2025
A5: SEGMENT REVENUE ($mm)
A6: Diagnostic Information Services | B6: 10494 | C6: 9609 | D6: 8976 | E6: 9614 | F6: 10785
A7: of which: COVID-19 testing revenues | B7: 2770 | C7: 1454 | D7: 0 | E7: 0 | F7: 0
A8: Diagnostic Solutions | B8: 294 | C8: 274 | D8: 276 | E8: 258 | F8: 250
A9: Total Net Revenues | B9: 10788 | C9: 9883 | D9: 9252 | E9: 9872 | F9: 11035
A10: Source: MD&A highlights table in each year's 10-K filing. COVID-19 testing revenues discontinued as a separately reported metric from FY2023.
A12: DIAGNOSTIC INFORMATION SERVICES VOLUME METRICS (Year-over-Year % Change)
A13: Source: MD&A highlights table. Changes are as disclosed; absolute volumes stated below.
A14: Requisition volume change | B14: -0.016 | C14: -0.045 | D14: -0.006 | E14: 0.055 | F14: 0.123
A15: Organic requisition volume change | B15: 0.136 | C15: -0.051 | D15: -0.01 | E15: 0.007 | F15: 0.034
A16: Revenue per requisition change | B16: -0.016 | C16: -0.045 | D16: -0.059 | E16: 0.013 | F16: 0.001
A18: APPROXIMATE TEST REQUISITION VOLUMES (millions)
A19: Source: Business section and MD&A of each 10-K filing. FY2021 back-calculated from FY2022 volume and disclosed change rate.
A20: Total test requisitions processed (approximate, millions) | B20: 218 | C20: 208 | D20: 206 | E20: 217 | F20: 244
A22: PAYER MIX - % OF DIAGNOSTIC INFORMATION SERVICES VOLUME
A23: Source: Critical Accounting Policies table in each 10-K filing. FY2021 not separately disclosed in filings provided.
A24: Healthcare insurers | B24: n/a | C24: 0.47 | D24: 0.47 | E24: 0.46 | F24: 0.43
A25: Government payers | B25: n/a | C25: 0.1 | D25: 0.1 | E25: 0.12 | F25: 0.17
A26: Client payers | B26: n/a | C26: 0.4 | D26: 0.42 | E26: 0.39 | F26: 0.37
A27: Patients | B27: n/a | C27: 0.01 | D27: 0.01 | E27: 0.01 | F27: 0.01
A29: PAYER MIX - % OF CONSOLIDATED NET REVENUES
A30: Source: Critical Accounting Policies table in each 10-K filing. FY2021 not separately disclosed in filings provided.
A31: Healthcare insurers | B31: n/a | C31: 0.41 | D31: 0.4 | E31: 0.4 | F31: 0.39
A32: Government payers | B32: n/a | C32: 0.11 | D32: 0.11 | E32: 0.13 | F32: 0.16
A33: Client payers | B33: n/a | C33: 0.33 | D33: 0.34 | E33: 0.33 | F33: 0.31
A34: Patients | B34: n/a | C34: 0.12 | D34: 0.12 | E34: 0.11 | F34: 0.12
A36: INVIGORATE PROGRAM AND RESTRUCTURING PRE-TAX CHARGES ($mm)
A37: Source: Restructuring Activities note and MD&A in each 10-K filing. FY2022 total includes $69mm from restructuring note plus $19mm from Invigorate integration costs.
A38: Employee separation costs | B38: 11 | C38: 55 | D38: 25 | E38: 28 | F38: 28
A39: Facility-related costs | B39: 1 | C39: 0 | D39: 0 | E39: 0 | F39: 0
A40: Asset impairment charges | B40: 0 | C40: 14 | D40: 29 | E40: 0 | F40: 29
A41: Other integration and restructuring costs | B41: 0 | C41: 19 | D41: 18 | E41: 34 | F41: 25
A42: Total Invigorate and Restructuring Charges (pre-tax) | B42: 12 | C42: 88 | D42: 43 | E42: 62 | F42: 53

Sheet Profitability & Returns
A1: Quest Diagnostics Incorporated
A2: Profitability and Returns
A3: In Millions unless stated otherwise
B4: FY2021 | C4: FY2022 | D4: FY2023 | E4: FY2024 | F4: FY2025
A5: INCOME STATEMENT SUMMARY ($mm)
A6: Net Revenues | B6: 10788 | C6: 9883 | D6: 9252 | E6: 9872 | F6: 11035
A7: Year-over-Year Revenue Growth | B7: n/a | C7: -0.083889507 | D7: -0.06384701 | E7: 0.067012538 | F7: 0.11780794
A8: Gross Profit | B8: 4209 | C8: 3433 | D8: 3053 | E8: 3244 | F8: 3665
A9: Earnings Before Interest, Taxes, Depreciation and Amortization | B9: 2789 | C9: 1865 | D9: 1701 | E9: 1839 | F9: 2126
A10: Operating Income | B10: 2381 | C10: 1428 | D10: 1262 | E10: 1346 | F10: 1556
A11: Net Income | B11: 2080 | C11: 1015 | D11: 908 | E11: 921 | F11: 1046
A12: Net Income Attributable to Quest Diagnostics | B12: 1995 | C12: 946 | D12: 854 | E12: 871 | F12: 992
A14: MARGIN ANALYSIS (% of Net Revenues)
A15: Gross Margin | B15: 0.39015573 | C15: 0.34736416 | D15: 0.32998271 | E15: 0.32860616 | F15: 0.33212506
A16: Selling, General and Administrative as % of Revenue | B16: 0.16008528 | C16: 0.18961854 | D16: 0.17747514 | E16: 0.17929498 | F16: 0.17825102
A17: Research and Development Expense | B17: n/a | C17: n/a | D17: n/a | E17: n/a | F17: n/a
A18: Quest Diagnostics does not separately report a research and development expense line item; development costs are embedded in cost of services and selling, general and administrative.
A19: Earnings Before Interest, Taxes, Depreciation and Amortization Margin | B19: 0.25852799 | C19: 0.18870788 | D19: 0.18385214 | E19: 0.18628444 | F19: 0.19265972
A20: Operating Margin | B20: 0.22070819 | C20: 0.14449054 | D20: 0.13640294 | E20: 0.13634522 | F20: 0.14100589
A21: Net Margin (Consolidated) | B21: 0.19280682 | C21: 0.10270161 | D21: 0.098140942 | E21: 0.093294165 | F21: 0.094789307
A22: Net Margin (Quest Attributable) | B22: 0.1849277 | C22: 0.095719923 | D22: 0.092304367 | E22: 0.088229335 | F22: 0.089895786
A23: Effective Tax Rate | B23: 0.22970373 | C23: 0.21376518 | D23: 0.21946903 | E23: 0.23234043 | F23: 0.23823976
A25: RETURN METRICS
A26: Return on Assets (Net Income / Total Assets) | B26: 0.15281757 | C26: 0.079068318 | D26: 0.064755384 | E26: 0.057017272 | F26: 0.064468413
A27: Return on Equity (Quest Attributable Net Income / Quest Equity) | B27: 0.30959032 | C27: 0.16052944 | D27: 0.13540511 | E27: 0.12850398 | F27: 0.13835425
A29: HEADCOUNT AND PRODUCTIVITY
A30: Source: Human Capital section of each 10-K. FY2021 not separately disclosed as a year-end figure in filings provided.
A31: Total Employees (approximate, year-end) | B31: n/a | C31: 49000 | D31: 48000 | E31: 56000 | F31: 57000
A32: Revenue per Employee ($K) | B32: n/a | C32: 0.20169388 | D32: 0.19275 | E32: 0.17628571 | F32: 0.19359649
A33: Operating Income per Employee ($K) | B33: n/a | C33: 0.029142857 | D33: 0.026291667 | E33: 0.024035714 | F33: 0.027298246
A35: EBIT | B35: ='Income Statement'!B7-'Income Statement'!B8-'Income Statement'!B9 -> 2379 | C35: ='Income Statement'!C7-'Income Statement'!C8-'Income Statement'!C9 -> 1439 | D35: ='Income Statement'!D7-'Income Statement'!D8-'Income Statement'!D9 -> 1303 | E35: ='Income Statement'!E7-'Income Statement'!E8-'Income Statement'!E9 -> 1347 | F35: ='Income Statement'!F7-'Income Statement'!F8-'Income Statement'!F9 -> 1544
A36: EBITDA | B36: =B35+'Cash Flow Statement'!B10 -> 2787 | C36: =C35+'Cash Flow Statement'!C10 -> 1876 | D36: =D35+'Cash Flow Statement'!D10 -> 1742 | E36: =E35+'Cash Flow Statement'!E10 -> 1840 | F36: =F35+'Cash Flow Statement'!F10 -> 2114

Sheet Cash Flow & Capital
A1: Quest Diagnostics Incorporated
A2: Cash Flow and Capital Intensity
A3: In Millions unless stated otherwise
B4: FY2021 | C4: FY2022 | D4: FY2023 | E4: FY2024 | F4: FY2025
A5: CASH FLOW SUMMARY ($mm)
A6: Net Cash from Operating Activities | B6: 2233 | C6: 1718 | D6: 1272 | E6: 1334 | F6: 1886
A7: Capital Expenditures | B7: -403 | C7: -404 | D7: -408 | E7: -425 | F7: -527
A8: Free Cash Flow (Operating Cash Flow + Capital Expenditures) | B8: =B6+B7 -> 1830 | C8: =C6+C7 -> 1314 | D8: =D6+D7 -> 864 | E8: =E6+E7 -> 909 | F8: =F6+F7 -> 1359
A9: Business Acquisitions, Net of Cash | B9: -331 | C9: -144 | D9: -611 | E9: -2164 | F9: -101
A10: Dividends Paid | B10: -309 | C10: -305 | D10: -314 | E10: -331 | F10: -353
A11: Purchases of Treasury Stock | B11: -2199 | C11: -1408 | D11: -275 | E11: -151 | F11: -450
A13: DEPRECIATION, AMORTIZATION AND STOCK-BASED COMPENSATION ($mm)
A14: Depreciation and Amortization | B14: 408 | C14: 437 | D14: 439 | E14: 493 | F14: 570
A15: of which: Amortization of intangible assets (income statement line) | B15: 103 | C15: 120 | D15: 108 | E15: 127 | F15: 154
A16: of which: Depreciation (implied) | B16: 305 | C16: 317 | D16: 331 | E16: 366 | F16: 416
A17: Stock-Based Compensation Expense | B17: 79 | C17: 77 | D17: 77 | E17: 88 | F17: 88
A19: CAPITAL INTENSITY METRICS
A20: Capital Expenditures / Revenue | B20: 0.037356322 | C20: 0.040878276 | D20: 0.044098573 | E20: 0.043051053 | F20: 0.047757136
A21: Depreciation and Amortization / Revenue | B21: 0.0378198 | C21: 0.044217343 | D21: 0.0474492 | E21: 0.049939222 | F21: 0.051653829
A22: Depreciation and Amortization / Property, Plant and Equipment (Net) | B22: 0.23901582 | C22: 0.24745187 | D22: 0.24174009 | E22: 0.23331756 | F22: 0.25873808
A23: Goodwill + Intangible Assets / Total Assets | B23: 0.60700904 | C23: 0.64750331 | D23: 0.63464556 | E23: 0.6574011 | F23: 0.65214176
A25: ACQUISITION ACTIVITY SUMMARY ($mm)
A26: Source: Investing activities and business acquisition note in each 10-K filing.
A27: Business Acquisitions, Net of Cash | B27: -331 | C27: -144 | D27: -611 | E27: -2164 | F27: -101
A28: FY2024 includes LifeLabs acquisition (~$1.4B) and IQVIA laboratory services assets (~$741M). FY2023 includes multiple tuck-in acquisitions.

Sheet Capital Structure & Per Share
A1: Quest Diagnostics Incorporated
A2: Capital Structure, Working Capital and Per Share Metrics
A3: In Millions unless stated otherwise
B4: FY2021 | C4: FY2022 | D4: FY2023 | E4: FY2024 | F4: FY2025
A5: LIQUIDITY ($mm)
A6: Cash and Cash Equivalents | B6: 872 | C6: 315 | D6: 686 | E6: 549 | F6: 420
A7: Quest Diagnostics does not hold a material short-term investment portfolio; liquidity is primarily cash. | B7: 872 | C7: 315 | D7: 686 | E7: 549 | F7: 420
A9: CAPITAL STRUCTURE ($mm)
A10: Current portion of long-term debt | B10: 2 | C10: 2 | D10: 303 | E10: 602 | F10: 504
A11: Long-term debt | B11: 4010 | C11: 3978 | D11: 4410 | E11: 5615 | F11: 5167
A12: Total Debt | B12: 4012 | C12: 3980 | D12: 4713 | E12: 6217 | F12: 5671
A13: Net Debt (Total Debt minus Cash) | B13: 3140 | C13: 3665 | D13: 4027 | E13: 5668 | F13: 5251
A14: Total Quest Diagnostics Stockholders' Equity | B14: 6444 | C14: 5893 | D14: 6307 | E14: 6778 | F14: 7170
A15: Noncontrolling Interests | B15: 39 | C15: 37 | D15: 35 | E15: 35 | F15: 36
A16: Redeemable Noncontrolling Interest (mezzanine) | B16: 79 | C16: 77 | D16: 76 | E16: 83 | F16: 80
A17: Total Stockholders' Equity (incl. all noncontrolling interests) | B17: 6562 | C17: 6007 | D17: 6418 | E17: 6896 | F17: 7286
A19: LEVERAGE METRICS
A20: Earnings Before Interest, Taxes, Depreciation and Amortization: FY2021 $2,789mm, FY2022 $1,865mm, FY2023 $1,701mm, FY2024 $1,839mm, FY2025 $2,126mm.
A21: Total Debt / Earnings Before Interest, Taxes, Depreciation and Amortization | B21: 1.4385084 | C21: 2.1340483 | D21: 2.7707231 | E21: 3.3806417 | F21: 2.6674506
A22: Net Debt / Earnings Before Interest, Taxes, Depreciation and Amortization | B22: 1.1258516 | C22: 1.9651475 | D22: 2.3674309 | E22: 3.0821098 | F22: 2.4698965
A23: Total Debt / Total Quest Diagnostics Stockholders' Equity | B23: 0.62259466 | C23: 0.67537757 | D23: 0.74726494 | E23: 0.91723222 | F23: 0.79093445
A25: LIQUIDITY RATIOS
A26: Current Ratio (Current Assets / Current Liabilities) | B26: 1.5636052 | C26: 1.2237266 | D26: 1.3068871 | E26: 1.1028124 | F26: 1.0438982
A27: Quick Ratio ((Current Assets minus Inventories) / Current Liabilities) | B27: 1.4449515 | C27: 1.0999355 | D27: 1.2022039 | E27: 1.0161365 | F27: 0.96093064
A29: WORKING CAPITAL EFFICIENCY (Days)
A30: Days Sales Outstanding = Accounts Receivable / Net Revenues x 365. Days Inventory Outstanding = Inventories / Cost of Services x 365. Days Payable Outstanding = Accounts Payable and Accrued Expenses / Cost of Services x 365.
A31: Days Sales Outstanding | B31: 48.653133 | C31: 44.133866 | D31: 47.735625 | E31: 48.213128 | F31: 46.571817
A32: Days Inventory Outstanding | B32: 11.539748 | C32: 10.865116 | D32: 11.187288 | E32: 10.353048 | F32: 9.3602442
A33: Days Payable Outstanding | B33: 88.76729 | C33: 78.99845 | D33: 80.018551 | E33: 76.766747 | F33: 79.240163
A34: Cash Conversion Cycle (Days Sales Outstanding + Days Inventory Outstanding minus Days Payable Outstanding) | B34: -28.574409 | C34: -23.999467 | D34: -21.095638 | E34: -18.200571 | F34: -23.308102
A36: PER SHARE METRICS
A37: Earnings Per Share - Basic ($) | B37: 15.85 | C37: 8.1 | D37: 7.59 | E37: 7.78 | F37: 8.87
A38: Earnings Per Share - Diluted ($) | B38: 15.55 | C38: 7.97 | D38: 7.49 | E38: 7.69 | F38: 8.75
A39: Dividends Per Share ($) | B39: n/a | C39: n/a | D39: n/a | E39: n/a | F39: n/a
A40: Dividends per share not directly disclosed in the 10-K filings uploaded; total dividends paid: FY2021 $309mm, FY2022 $305mm, FY2023 $314mm, FY2024 $331mm, FY2025 $353mm.
A41: Book Value per Share - Quest Equity ($) | B41: 50.227669 | C41: 49.648214 | D41: 55.315492 | E41: 59.842503 | F41: 63.243448
A42: Weighted Average Shares Outstanding - Diluted (millions) | B42: 128.3 | C42: 118.7 | D42: 114 | E42: 113.3 | F42: 113.4
A43: Shares Outstanding (period-end, approximate, millions) | B43: 119 | C43: 111 | D43: 111 | E43: 111 | F43: 110
