Workbook

Sheet Financials
A1: SMCI — Equity Research Model
A2: All figures in $mm unless noted | Blue = forecast
B3: Q4FY22 | C3: Q1FY23 | D3: Q2FY23 | E3: Q3FY23 | F3: Q4FY23 | G3: Q1FY24 | H3: Q2FY24 | I3: Q3FY24 | J3: Q4FY24 | K3: Q1FY25 | L3: Q2FY25 | M3: Q3FY25 | N3: Q4FY25 | O3: Q1FY26 | P3: Q2FY26 | Q3: Q3FY26 | R3: Q4FY26E | S3: Q1FY27E | T3: Q2FY27E | U3: Q3FY27E | V3: Q4FY27E | W3: Q1FY28E | X3: Q2FY28E | Y3: Q3FY28E
A4: Stock
A5: Current Stock Price | B5: 47.16
A6: Market Cap ($mm) | B6: =$B$5*$Q$37 -> 32643.633
A7: Cash ($mm) | B7: =Q48 -> 1290.324
A8: Debt ($mm) | B8: =Q59+Q60+Q63 -> 8773.101
A9: Enterprise Value ($mm) | B9: =$B$6+$B$8-$B$7 -> 40126.41
A10: Trailing P/E | B10: =$B$5/($N$35+$O$35+$P$35+$Q$35) -> 24.86686
A11: Trailing EV/EBIT | B11: =$B$9/($N$39+$O$39+$P$39+$Q$39) -> 26.559482
A12: Trailing EV/EBITDA | B12: =$B$9/($N$40+$O$40+$P$40+$Q$40) -> 25.70866
A13: Trailing EV/FCFE | B13: =$B$9/($N$94+$O$94+$P$94+$Q$94) -> -5.4691598
A14: EPS Yield | B14: =($N$35+$O$35+$P$35+$Q$35)/($B$5) -> 0.040214165
A16: INCOME STATEMENT
B17: Q4FY22 | C17: Q1FY23 | D17: Q2FY23 | E17: Q3FY23 | F17: Q4FY23 | G17: Q1FY24 | H17: Q2FY24 | I17: Q3FY24 | J17: Q4FY24 | K17: Q1FY25 | L17: Q2FY25 | M17: Q3FY25 | N17: Q4FY25 | O17: Q1FY26 | P17: Q2FY26 | Q17: Q3FY26 | R17: Q4FY26E | S17: Q1FY27E | T17: Q2FY27E | U17: Q3FY27E | V17: Q4FY27E | W17: Q1FY28E | X17: Q2FY28E | Y17: Q3FY28E
A18: Total Revenue | B18: 1635.46 | C18: 1852.13 | D18: 1803.195 | E18: 1283.296 | F18: 2184.861 | G18: 2119.672 | H18: 3664.924 | I18: 3850.066 | J18: 5354.589 | K18: 5937.256 | L18: 5677.962 | M18: 4599.913 | N18: 5756.911 | O18: 5017.79 | P18: 12682.491 | Q18: 10243.014 | R18: =Assumptions!$R$5 -> 10634.217 | S18: =Assumptions!$S$5 -> 11040.253 | T18: =Assumptions!$T$5 -> 11464.35 | U18: =Assumptions!$U$5 -> 11907.003 | V18: =Assumptions!$V$5 -> 12364.012 | W18: =Assumptions!$W$5 -> 12843.904 | X18: =Assumptions!$X$5 -> 13338.768 | Y18: =Assumptions!$Y$5 -> 13858.572
A19: Cost of Revenue | B19: 1348.116 | C19: 1504.595 | D19: 1465.773 | E19: 1056.937 | F19: 1813.165 | G19: 1765.981 | H19: 3100.602 | I19: 3252.698 | J19: 4808.56 | K19: 5161.676 | L19: 5007.94 | M19: 4159.695 | N19: 5212.809 | O19: 4550.417 | P19: 11883.924 | Q19: 9224.334 | R19: =$R$18*(1-Assumptions!$R$9) -> 9623.9663 | S19: =$S$18*(1-Assumptions!$S$9) -> 9985.9093 | T19: =$T$18*(1-Assumptions!$T$9) -> 10363.772 | U19: =$U$18*(1-Assumptions!$U$9) -> 10757.977 | V19: =$V$18*(1-Assumptions!$V$9) -> 11158.521 | W19: =$W$18*(1-Assumptions!$W$9) -> 11578.779 | X19: =$X$18*(1-Assumptions!$X$9) -> 12011.561 | Y19: =$Y$18*(1-Assumptions!$Y$9) -> 12472.715
A20: Gross Profit | B20: 287.344 | C20: 347.535 | D20: 337.422 | E20: 226.359 | F20: 371.696 | G20: 353.691 | H20: 564.322 | I20: 597.368 | J20: 546.029 | K20: 775.58 | L20: 670.022 | M20: 440.218 | N20: 544.102 | O20: 467.373 | P20: 798.567 | Q20: 1018.68 | R20: =$R$18-$R$19 -> 1010.2506 | S20: =$S$18-$S$19 -> 1054.3442 | T20: =$T$18-$T$19 -> 1100.5776 | U20: =$U$18-$U$19 -> 1149.0258 | V20: =$V$18-$V$19 -> 1205.4912 | W20: =$W$18-$W$19 -> 1265.1245 | X20: =$X$18-$X$19 -> 1327.2074 | Y20: =$Y$18-$Y$19 -> 1385.8572
A21: -- Gross Margin % | B21: 0.17569613 | C21: 0.18764072 | D21: 0.18712452 | E21: 0.17638877 | F21: 0.17012341 | G21: 0.16686119 | H21: 0.15397918 | I21: 0.15515786 | J21: 0.10197403 | K21: 0.13062937 | L21: 0.11800396 | M21: 0.095701375 | N21: 0.094512839 | O21: 0.093143197 | P21: 0.0629661 | Q21: 0.099451197 | R21: =$R$20/$R$18 -> 0.095 | S21: =$S$20/$S$18 -> 0.0955 | T21: =$T$20/$T$18 -> 0.096 | U21: =$U$20/$U$18 -> 0.0965 | V21: =$V$20/$V$18 -> 0.0975 | W21: =$W$20/$W$18 -> 0.0985 | X21: =$X$20/$X$18 -> 0.0995 | Y21: =$Y$20/$Y$18 -> 0.1
A22: Research & Development | B22: 70.79 | C22: 74.243 | D22: 70.7 | E22: 77.515 | F22: 84.802 | G22: 111.027 | H22: 108.824 | I22: 116.226 | J22: 127.471 | K22: 132.243 | L22: 158.229 | M22: 162.857 | N22: 183.221 | O22: 173.314 | P22: 180.761 | Q22: 215.659 | R22: =Assumptions!$R$11 -> 215.7 | S22: =Assumptions!$S$11 -> 215.7 | T22: =Assumptions!$T$11 -> 215.7 | U22: =Assumptions!$U$11 -> 215.7 | V22: =Assumptions!$V$11 -> 215.7 | W22: =Assumptions!$W$11 -> 215.7 | X22: =Assumptions!$X$11 -> 215.7 | Y22: =Assumptions!$Y$11 -> 215.7
A23: Sales, General & Administrative | B23: 51.341 | C23: 53.169 | D23: 51.54 | E23: 49.762 | F23: 60.139 | G23: 70.154 | H23: 84.034 | I23: 102.828 | J23: 130.072 | K23: 134.138 | L23: 143.169 | M23: 130.581 | N23: 132.49 | O23: 111.803 | P23: 143.508 | Q23: 177.153 | R23: =Assumptions!$R$13 -> 177.2 | S23: =Assumptions!$S$13 -> 177.2 | T23: =Assumptions!$T$13 -> 177.2 | U23: =Assumptions!$U$13 -> 177.2 | V23: =Assumptions!$V$13 -> 177.2 | W23: =Assumptions!$W$13 -> 177.2 | X23: =Assumptions!$X$13 -> 177.2 | Y23: =Assumptions!$Y$13 -> 177.2
A24: Total Operating Expenses | B24: 122.131 | C24: 127.412 | D24: 122.24 | E24: 127.277 | F24: 144.941 | G24: 181.181 | H24: 192.858 | I24: 219.054 | J24: 257.543 | K24: 266.381 | L24: 301.398 | M24: 293.438 | N24: 315.711 | O24: 285.117 | P24: 324.269 | Q24: 392.812 | R24: =$R$22+$R$23 -> 392.9 | S24: =$S$22+$S$23 -> 392.9 | T24: =$T$22+$T$23 -> 392.9 | U24: =$U$22+$U$23 -> 392.9 | V24: =$V$22+$V$23 -> 392.9 | W24: =$W$22+$W$23 -> 392.9 | X24: =$X$22+$X$23 -> 392.9 | Y24: =$Y$22+$Y$23 -> 392.9
A25: Operating Income (EBIT) | B25: 165.213 | C25: 220.123 | D25: 215.182 | E25: 99.082 | F25: 226.755 | G25: 172.51 | H25: 371.464 | I25: 378.314 | J25: 288.486 | K25: 509.199 | L25: 368.624 | M25: 146.78 | N25: 228.391 | O25: 182.256 | P25: 474.298 | Q25: 625.868 | R25: =$R$20-$R$24 -> 617.35061 | S25: =$S$20-$S$24 -> 661.44421 | T25: =$T$20-$T$24 -> 707.6776 | U25: =$U$20-$U$24 -> 756.12576 | V25: =$V$20-$V$24 -> 812.59115 | W25: =$W$20-$W$24 -> 872.22454 | X25: =$X$20-$X$24 -> 934.30744 | Y25: =$Y$20-$Y$24 -> 992.95724
A26: -- Operating Margin % | B26: 0.10101929 | C26: 0.11884857 | D26: 0.11933374 | E26: 0.077208999 | F26: 0.10378463 | G26: 0.081385233 | H26: 0.10135654 | I26: 0.098261692 | J26: 0.053876404 | K26: 0.085763356 | L26: 0.064921886 | M26: 0.031909299 | N26: 0.039672491 | O26: 0.036321966 | P26: 0.037397858 | Q26: 0.061101937 | R26: =$R$25/$R$18 -> 0.058053227 | S26: =$S$25/$S$18 -> 0.059912049 | T26: =$T$25/$T$18 -> 0.061728541 | U26: =$U$25/$U$18 -> 0.063502611 | V26: =$V$25/$V$18 -> 0.065722288 | W26: =$W$25/$W$18 -> 0.067909612 | X26: =$X$25/$X$18 -> 0.070044507 | Y26: =$Y$25/$Y$18 -> 0.071649316
A27: Interest Income | L27: 8.776 | M27: 14.654 | P27: 51.042 | Q27: 45.437 | R27: =Assumptions!$R$22 -> 43.6 | S27: =Assumptions!$S$22 -> 41.9 | T27: =Assumptions!$T$22 -> 40.2 | U27: =Assumptions!$U$22 -> 38.6 | V27: =Assumptions!$V$22 -> 37 | W27: =Assumptions!$W$22 -> 35.6 | X27: =Assumptions!$X$22 -> 34.1 | Y27: =Assumptions!$Y$22 -> 32.8
A28: Interest Expense | B28: 2.928 | C28: 3.938 | D28: 1.756 | E28: 1.288 | F28: 3.509 | G28: 1.863 | H28: 8.131 | I28: 6.246 | R28: =Assumptions!$R$23 -> 109.66375 | S28: =Assumptions!$S$23 -> 109.66375 | T28: =Assumptions!$T$23 -> 109.66375 | U28: =Assumptions!$U$23 -> 109.66375 | V28: =Assumptions!$V$23 -> 109.66375 | W28: =Assumptions!$W$23 -> 109.66375 | X28: =Assumptions!$X$23 -> 109.66375 | Y28: =Assumptions!$Y$23 -> 109.66375
A29: Other Income (Expense), net | B29: 3.973 | C29: 8.054 | D29: -6.335 | E29: -0.078 | F29: 2.005 | G29: 6.613 | H29: -7.886 | I29: 10.035 | J29: 13.955 | K29: 7.233 | L29: 12.959 | M29: -18.313 | N29: 16.616 | O29: 51.227 | R29: =0 -> 0 | S29: =0 -> 0 | T29: =0 -> 0 | U29: =0 -> 0 | V29: =0 -> 0 | W29: =0 -> 0 | X29: =0 -> 0 | Y29: =0 -> 0
A30: Pretax Income | B30: 166.582 | C30: 223.35 | D30: 205.74 | E30: 96.703 | F30: 224.871 | G30: 177.21 | H30: 357.471 | I30: 382.476 | J30: 298.803 | K30: 499.059 | L30: 377.565 | M30: 114.62 | N30: 214.461 | O30: 208.446 | P30: 499.715 | Q30: 610.274 | R30: =$R$25+$R$27-$R$28+$R$29 -> 551.28686 | S30: =$S$25+$S$27-$S$28+$S$29 -> 593.68046 | T30: =$T$25+$T$27-$T$28+$T$29 -> 638.21385 | U30: =$U$25+$U$27-$U$28+$U$29 -> 685.06201 | V30: =$V$25+$V$27-$V$28+$V$29 -> 739.9274 | W30: =$W$25+$W$27-$W$28+$W$29 -> 798.16079 | X30: =$X$25+$X$27-$X$28+$X$29 -> 858.74369 | Y30: =$Y$25+$Y$27-$Y$28+$Y$29 -> 916.09349
A31: Income Tax Expense | B31: 25.76 | C31: 38.934 | D31: 29.573 | E31: 10.857 | F31: 31.302 | G31: 20.215 | H31: 61.503 | I31: -19.983 | J31: 1.559 | K31: 74.732 | L31: 56.969 | M31: 5.843 | N31: 19.307 | O31: 40.161 | P31: 99.151 | Q31: 126.887 | R31: =$R$30*Assumptions!$R$24 -> 114.61254 | S31: =$S$30*Assumptions!$S$24 -> 123.42617 | T31: =$T$30*Assumptions!$T$24 -> 132.68466 | U31: =$U$30*Assumptions!$U$24 -> 142.42439 | V31: =$V$30*Assumptions!$V$24 -> 153.83091 | W31: =$W$30*Assumptions!$W$24 -> 165.93763 | X31: =$X$30*Assumptions!$X$24 -> 178.53281 | Y31: =$Y$30*Assumptions!$Y$24 -> 190.45584
A32: -- Effective Tax Rate % | B32: 0.15463856 | C32: 0.17431833 | D32: 0.14373967 | E32: 0.11227159 | F32: 0.13919981 | G32: 0.1140737 | H32: 0.17205032 | I32: -0.052246415 | J32: 0.0052174844 | K32: 0.14974582 | L32: 0.15088528 | M32: 0.050977142 | N32: 0.090025692 | O32: 0.1926686 | P32: 0.1984151 | Q32: 0.20791808 | R32: =Assumptions!$R$24 -> 0.2079 | S32: =Assumptions!$S$24 -> 0.2079 | T32: =Assumptions!$T$24 -> 0.2079 | U32: =Assumptions!$U$24 -> 0.2079 | V32: =Assumptions!$V$24 -> 0.2079 | W32: =Assumptions!$W$24 -> 0.2079 | X32: =Assumptions!$X$24 -> 0.2079 | Y32: =Assumptions!$Y$24 -> 0.2079
A33: Net Income | B33: 140.822 | C33: 184.416 | D33: 176.167 | E33: 85.846 | F33: 193.569 | G33: 156.995 | H33: 295.968 | I33: 402.459 | J33: 297.244 | K33: 424.327 | L33: 320.596 | M33: 108.777 | N33: 195.154 | O33: 168.285 | P33: 400.564 | Q33: 483.387 | R33: =$R$30-$R$31 -> 436.67432 | S33: =$S$30-$S$31 -> 470.25429 | T33: =$T$30-$T$31 -> 505.52919 | U33: =$U$30-$U$31 -> 542.63761 | V33: =$V$30-$V$31 -> 586.09649 | W33: =$W$30-$W$31 -> 632.22316 | X33: =$X$30-$X$31 -> 680.21088 | Y33: =$Y$30-$Y$31 -> 725.63765
A34: EPS (Basic) | B34: 0.2772 | C34: 0.351 | D34: 0.331 | E34: 0.161 | F34: 0.368 | G34: 0.3 | H34: 0.55 | I34: 0.71 | J34: 0.5069 | K34: 0.72 | L34: 0.54 | M34: 0.18 | N34: 0.3266 | O34: 0.28 | P34: 0.67 | Q34: 0.81 | R34: =$R$33/$R$36 -> 0.72754802 | S34: =$S$33/$S$36 -> 0.78349599 | T34: =$T$33/$T$36 -> 0.8422679 | U34: =$U$33/$U$36 -> 0.90409466 | V34: =$V$33/$V$36 -> 0.97650199 | W34: =$W$33/$W$36 -> 1.0533542 | X34: =$X$33/$X$36 -> 1.133307 | Y34: =$Y$33/$Y$36 -> 1.2089931
A35: EPS (Diluted) | B35: 0.2661 | C35: 0.335 | D35: 0.314 | E35: 0.153 | F35: 0.3518 | G35: 0.27 | H35: 0.51 | I35: 0.66 | J35: 0.4633 | K35: 0.67 | L35: 0.51 | M35: 0.17 | N35: 0.3165 | O35: 0.26 | P35: 0.6 | Q35: 0.72 | R35: =$R$33/$R$37 -> 0.63084993 | S35: =$S$33/$S$37 -> 0.67936188 | T35: =$T$33/$T$37 -> 0.73032244 | U35: =$U$33/$U$37 -> 0.78393183 | V35: =$V$33/$V$37 -> 0.84671554 | W35: =$W$33/$W$37 -> 0.91335331 | X35: =$X$33/$X$37 -> 0.98267969 | Y35: =$Y$33/$Y$37 -> 1.0483063
A36: Shares (Basic, mm) | B36: 507.96 | C36: 525.98 | D36: 531.6 | E36: 532.8 | F36: 525.98 | G36: 530.928 | H36: 541.354 | I36: 564.78 | J36: 586.45 | K36: 589.558 | L36: 592.507 | M36: 595.041 | N36: 597.554 | O36: 595.624 | P36: 598.004 | Q36: 600.205 | R36: =Assumptions!$R$28 -> 600.2 | S36: =Assumptions!$S$28 -> 600.2 | T36: =Assumptions!$T$28 -> 600.2 | U36: =Assumptions!$U$28 -> 600.2 | V36: =Assumptions!$V$28 -> 600.2 | W36: =Assumptions!$W$28 -> 600.2 | X36: =Assumptions!$X$28 -> 600.2 | Y36: =Assumptions!$Y$28 -> 600.2
A37: Shares (Diluted, mm) | B37: 529.16 | C37: 550.17 | D37: 561.44 | E37: 562.33 | F37: 550.17 | G37: 571.853 | H37: 580.777 | I37: 614.31 | J37: 641.644 | K37: 639.148 | L37: 636.047 | M37: 621.809 | N37: 616.604 | O37: 663.235 | P37: 693.989 | Q37: 692.189 | R37: =Assumptions!$R$26 -> 692.2 | S37: =Assumptions!$S$26 -> 692.2 | T37: =Assumptions!$T$26 -> 692.2 | U37: =Assumptions!$U$26 -> 692.2 | V37: =Assumptions!$V$26 -> 692.2 | W37: =Assumptions!$W$26 -> 692.2 | X37: =Assumptions!$X$26 -> 692.2 | Y37: =Assumptions!$Y$26 -> 692.2
A38: NON-GAAP KPIs
A39: Clean EBIT | B39: 165.213 | C39: 220.123 | D39: 215.182 | E39: 99.082 | F39: 226.755 | G39: 172.51 | H39: 371.464 | I39: 378.314 | J39: 288.486 | K39: 509.199 | L39: 368.624 | M39: 146.78 | N39: 228.391 | O39: 182.256 | P39: 474.298 | Q39: 625.868 | R39: =$R$25 -> 617.35061 | S39: =$S$25 -> 661.44421 | T39: =$T$25 -> 707.6776 | U39: =$U$25 -> 756.12576 | V39: =$V$25 -> 812.59115 | W39: =$W$25 -> 872.22454 | X39: =$X$25 -> 934.30744 | Y39: =$Y$25 -> 992.95724
A40: Clean EBITDA | B40: 165.964 | C40: 228.67 | D40: 223.831 | E40: 107.818 | F40: 227.723 | G40: 179.51 | H40: 378.764 | I40: 385.914 | J40: 296.686 | K40: 518.199 | L40: 378.124 | M40: 157.68 | N40: 239.991 | O40: 194.356 | P40: 487.098 | Q40: 639.368 | R40: =$R$39+$R$41 -> 630.85061 | S40: =$S$39+$S$41 -> 674.94421 | T40: =$T$39+$T$41 -> 721.1776 | U40: =$U$39+$U$41 -> 769.62576 | V40: =$V$39+$V$41 -> 826.09115 | W40: =$W$39+$W$41 -> 885.72454 | X40: =$X$39+$X$41 -> 947.80744 | Y40: =$Y$39+$Y$41 -> 1006.4572
A41: Depreciation & Amortization | B41: 0.751 | C41: 8.547 | D41: 8.649 | E41: 8.736 | F41: 0.968 | G41: 7 | H41: 7.3 | I41: 7.6 | J41: 8.2 | K41: 9 | L41: 9.5 | M41: 10.9 | N41: 11.6 | O41: 12.1 | P41: 12.8 | Q41: 13.5 | R41: =Assumptions!$R$16 -> 13.5 | S41: =Assumptions!$S$16 -> 13.5 | T41: =Assumptions!$T$16 -> 13.5 | U41: =Assumptions!$U$16 -> 13.5 | V41: =Assumptions!$V$16 -> 13.5 | W41: =Assumptions!$W$16 -> 13.5 | X41: =Assumptions!$X$16 -> 13.5 | Y41: =Assumptions!$Y$16 -> 13.5
A42: Normalized Earnings | B42: 136.525 | C42: 177.251 | D42: 183.853 | E42: 86.937 | F42: 191.944 | G42: 150.432 | H42: 301.83 | I42: 392.051 | J42: 286.927 | K42: 434.467 | L42: 311.655 | M42: 140.937 | N42: 209.084 | O42: 142.095 | P42: 375.147 | Q42: 498.981 | R42: =$R$39-$R$28-$R$31 -> 393.07432 | S42: =$S$39-$S$28-$S$31 -> 428.35429 | T42: =$T$39-$T$28-$T$31 -> 465.32919 | U42: =$U$39-$U$28-$U$31 -> 504.03761 | V42: =$V$39-$V$28-$V$31 -> 549.09649 | W42: =$W$39-$W$28-$W$31 -> 596.62316 | X42: =$X$39-$X$28-$X$31 -> 646.11088 | Y42: =$Y$39-$Y$28-$Y$31 -> 692.83765
A43: Clean EPS | B43: 0.25800325 | C43: 0.32217496 | D43: 0.32746687 | E43: 0.15460139 | F43: 0.34888125 | G43: 0.26306061 | H43: 0.51970033 | I43: 0.63819733 | J43: 0.44717476 | K43: 0.67975962 | L43: 0.48998738 | M43: 0.22665642 | N43: 0.33908959 | O43: 0.21424533 | P43: 0.5405662 | Q43: 0.72087392 | R43: =$R$42/$R$37 -> 0.56786235 | S43: =$S$42/$S$37 -> 0.61883024 | T43: =$T$42/$T$37 -> 0.67224674 | U43: =$U$42/$U$37 -> 0.7281676 | V43: =$V$42/$V$37 -> 0.79326278 | W43: =$W$42/$W$37 -> 0.86192309 | X43: =$X$42/$X$37 -> 0.93341647 | Y43: =$Y$42/$Y$37 -> 1.0009212
A45: BALANCE SHEET
B46: Q4FY22 | C46: Q1FY23 | D46: Q2FY23 | E46: Q3FY23 | F46: Q4FY23 | G46: Q1FY24 | H46: Q2FY24 | I46: Q3FY24 | J46: Q4FY24 | K46: Q1FY25 | L46: Q2FY25 | M46: Q3FY25 | N46: Q4FY25 | O46: Q1FY26 | P46: Q2FY26 | Q46: Q3FY26 | R46: Q4FY26E | S46: Q1FY27E | T46: Q2FY27E | U46: Q3FY27E | V46: Q4FY27E | W46: Q1FY28E | X46: Q2FY28E | Y46: Q3FY28E
A47: ASSETS
A48: Cash & Equivalents | B48: 267.397 | C48: 238.268 | D48: 304.595 | E48: 362.801 | F48: 440.459 | G48: 543.156 | H48: 725.66 | I48: 2115.476 | J48: 1669.766 | K48: 2088.718 | L48: 1430.002 | M48: 2536.101 | N48: 5169.911 | O48: 4196.867 | P48: 4091.083 | Q48: 1290.324
A49: Accounts Receivable, net | B49: 834.513 | C49: 736.312 | D49: 768.167 | E49: 672.055 | F49: 1148.259 | G49: 845.729 | H49: 1502.971 | I49: 1650.153 | J49: 2737.331 | K49: 2731.74 | L49: 3059.51 | M49: 2642.556 | N49: 2203.942 | O49: 2525.039 | P49: 11004.122 | Q49: 8413.396 | R49: =$R$18/91*Assumptions!$R$30 -> 6847.9683 | S49: =$S$18/91*Assumptions!$S$30 -> 7109.438 | T49: =$T$18/91*Assumptions!$T$30 -> 7382.5375 | U49: =$U$18/91*Assumptions!$U$30 -> 7667.5863 | V49: =$V$18/91*Assumptions!$V$30 -> 7961.8801 | W49: =$W$18/91*Assumptions!$W$30 -> 8270.9096 | X49: =$X$18/91*Assumptions!$X$30 -> 8589.5804 | Y49: =$Y$18/91*Assumptions!$Y$30 -> 8924.3114
A50: Inventories | B50: 1545.606 | C50: 1736.055 | D50: 1421.817 | E50: 1540.419 | F50: 1445.564 | G50: 2052.805 | H50: 2466.997 | I50: 4124.587 | J50: 4333.029 | K50: 4930.623 | L50: 3596.145 | M50: 3870.243 | N50: 4680.375 | O50: 5730.002 | P50: 10595.448 | Q50: 11103.376 | R50: =$R$19/91*Assumptions!$R$31 -> 10226.786 | S50: =$S$19/91*Assumptions!$S$31 -> 10611.4 | T50: =$T$19/91*Assumptions!$T$31 -> 11012.932 | U50: =$U$19/91*Assumptions!$U$31 -> 11431.828 | V50: =$V$19/91*Assumptions!$V$31 -> 11857.461 | W50: =$W$19/91*Assumptions!$W$31 -> 12304.044 | X50: =$X$19/91*Assumptions!$X$31 -> 12763.933 | Y50: =$Y$19/91*Assumptions!$Y$31 -> 13253.973
A51: Prepaid Expenses & Other Current Assets | B51: 158.799 | C51: 169.245 | D51: 154.924 | E51: 139.9 | F51: 145.144 | G51: 129.144 | H51: 146.727 | I51: 173.716 | J51: 191.834 | K51: 100.503 | L51: 581.413 | M51: 464.689 | N51: 247.426 | O51: 209.426 | P51: 433.944 | Q51: 761.19 | R51: =$Q$51 -> 761.19 | S51: =$R$51 -> 761.19 | T51: =$S$51 -> 761.19 | U51: =$T$51 -> 761.19 | V51: =$U$51 -> 761.19 | W51: =$V$51 -> 761.19 | X51: =$W$51 -> 761.19 | Y51: =$X$51 -> 761.19
A52: Total Current Assets | B52: 2806.315 | C52: 2879.88 | D52: 2649.503 | E52: 2715.175 | F52: 3179.426 | G52: 3570.834 | H52: 4842.355 | I52: 8063.932 | J52: 8931.96 | K52: 9851.584 | L52: 8667.07 | M52: 9513.589 | N52: 12301.654 | O52: 12661.334 | P52: 26124.597 | Q52: 21568.286 | R52: =SUM($R$48,$R$49,$R$50,$R$51) -> 17835.944 | S52: =SUM($S$48,$S$49,$S$50,$S$51) -> 18482.028 | T52: =SUM($T$48,$T$49,$T$50,$T$51) -> 19156.659 | U52: =SUM($U$48,$U$49,$U$50,$U$51) -> 19860.605 | V52: =SUM($V$48,$V$49,$V$50,$V$51) -> 20580.531 | W52: =SUM($W$48,$W$49,$W$50,$W$51) -> 21336.143 | X52: =SUM($X$48,$X$49,$X$50,$X$51) -> 22114.704 | Y52: =SUM($Y$48,$Y$49,$Y$50,$Y$51) -> 22939.475
A53: PP&E, net | B53: 285.972 | C53: 290.752 | D53: 289.255 | E53: 290.038 | F53: 290.24 | G53: 291.669 | H53: 297.102 | I53: 385.566 | J53: 414.008 | K53: 451.06 | L53: 477.492 | M53: 492.565 | N53: 504.488 | O53: 520.712 | P53: 538.584 | Q53: 607.659 | R53: =$Q$53+Assumptions!$R$17-Assumptions!$R$16 -> 513.859 | S53: =$R$53+Assumptions!$S$17-Assumptions!$S$16 -> 420.059 | T53: =$S$53+Assumptions!$T$17-Assumptions!$T$16 -> 326.259 | U53: =$T$53+Assumptions!$U$17-Assumptions!$U$16 -> 232.459 | V53: =$U$53+Assumptions!$V$17-Assumptions!$V$16 -> 138.659 | W53: =$V$53+Assumptions!$W$17-Assumptions!$W$16 -> 44.859 | X53: =$W$53+Assumptions!$X$17-Assumptions!$X$16 -> -48.941 | Y53: =$X$53+Assumptions!$Y$17-Assumptions!$Y$16 -> -142.741
A54: Other Long-term Assets | B54: 42.861 | C54: 37.144 | D54: 37.246 | E54: 38.833 | F54: 42.409 | G54: 47.786 | H54: 47.269 | I54: 83.035 | J54: 114.952 | K54: 137.016 | L54: 142.536 | M54: 251.155 | N54: 604.871 | O54: 586.734 | P54: 683.062 | Q54: 643.369 | R54: =$Q$54 -> 643.369 | S54: =$R$54 -> 643.369 | T54: =$S$54 -> 643.369 | U54: =$T$54 -> 643.369 | V54: =$U$54 -> 643.369 | W54: =$V$54 -> 643.369 | X54: =$W$54 -> 643.369 | Y54: =$X$54 -> 643.369
A55: Total Assets | B55: 3205.077 | C55: 3301.283 | D55: 3074.942 | E55: 3192.604 | F55: 3674.729 | G55: 4095.964 | H55: 5405 | I55: 8862.781 | J55: 9826.092 | K55: 10851.383 | L55: 9728.348 | M55: 10738.525 | N55: 14018.429 | O55: 14386.037 | P55: 28001.61 | Q55: 23452.029 | R55: =SUM($R$52,$R$53,$R$54) -> 18993.172 | S55: =SUM($S$52,$S$53,$S$54) -> 19545.456 | T55: =SUM($T$52,$T$53,$T$54) -> 20126.287 | U55: =SUM($U$52,$U$53,$U$54) -> 20736.433 | V55: =SUM($V$52,$V$53,$V$54) -> 21362.559 | W55: =SUM($W$52,$W$53,$W$54) -> 22024.371 | X55: =SUM($X$52,$X$53,$X$54) -> 22709.132 | Y55: =SUM($Y$52,$Y$53,$Y$54) -> 23440.103
A56: LIABILITIES
A57: Accounts Payable | B57: 655.403 | C57: 785.025 | D57: 559.962 | E57: 641.839 | F57: 776.831 | G57: 1084.058 | H57: 1261.533 | I57: 1092.445 | J57: 1472.381 | K57: 1682.968 | L57: 549.323 | M57: 643.05 | N57: 1281.977 | O57: 1279.667 | P57: 13753.207 | Q57: 3686.991 | R57: =$R$19/91*Assumptions!$R$32 -> 5012.9231 | S57: =$S$19/91*Assumptions!$S$32 -> 5201.4516 | T57: =$T$19/91*Assumptions!$T$32 -> 5398.2727 | U57: =$U$19/91*Assumptions!$U$32 -> 5603.6055 | V57: =$V$19/91*Assumptions!$V$32 -> 5812.2404 | W57: =$W$19/91*Assumptions!$W$32 -> 6031.1445 | X57: =$X$19/91*Assumptions!$X$32 -> 6256.5712 | Y57: =$Y$19/91*Assumptions!$Y$32 -> 6496.7769
A58: Accrued Liabilities | B58: 212.419 | C58: 213.521 | D58: 169.866 | E58: 155.224 | F58: 163.865 | G58: 152.5 | H58: 214.462 | I58: 290.37 | J58: 259.674 | K58: 308.777 | L58: 229.147 | M58: 344.679 | N58: 565.637 | O58: 313.393 | P58: 548.179 | Q58: 830.007 | R58: =$Q$58 -> 830.007 | S58: =$R$58 -> 830.007 | T58: =$S$58 -> 830.007 | U58: =$T$58 -> 830.007 | V58: =$U$58 -> 830.007 | W58: =$V$58 -> 830.007 | X58: =$W$58 -> 830.007 | Y58: =$X$58 -> 830.007
A59: Short-term Debt | B59: 449.146 | C59: 101.173 | F59: 170.123 | R59: =Assumptions!$R$34 -> 0 | S59: =Assumptions!$S$34 -> 0 | T59: =Assumptions!$T$34 -> 0 | U59: =Assumptions!$U$34 -> 0 | V59: =Assumptions!$V$34 -> 0 | W59: =Assumptions!$W$34 -> 0 | X59: =Assumptions!$X$34 -> 0 | Y59: =Assumptions!$Y$34 -> 0
A60: Current Portion of LT Debt | B60: 449.146 | C60: 37.66 | D60: 38.776 | E60: 39.26 | F60: 170.123 | G60: 40.843 | H60: 42.621 | I60: 41.169 | J60: 402.346 | K60: 41.594 | L60: 40.147 | M60: 39.805 | N60: 75.06 | O60: 18.77 | P60: 18.252 | Q60: 1805.882 | R60: =$Q$60 -> 1805.882 | S60: =$R$60 -> 1805.882 | T60: =$S$60 -> 1805.882 | U60: =$T$60 -> 1805.882 | V60: =$U$60 -> 1805.882 | W60: =$V$60 -> 1805.882 | X60: =$W$60 -> 1805.882 | Y60: =$X$60 -> 1805.882
A61: Deferred Revenue (Current) | B61: 111.313 | C61: 185.225 | D61: 120.53 | E61: 148.747 | F61: 134.667 | G61: 166.025 | H61: 193.334 | I61: 233.293 | J61: 193.052 | K61: 305.84 | L61: 309.238 | M61: 352.803 | N61: 368.737 | O61: 597.322 | P61: 774.846 | Q61: 1472.235 | R61: =$Q$61 -> 1472.235 | S61: =$R$61 -> 1472.235 | T61: =$S$61 -> 1472.235 | U61: =$T$61 -> 1472.235 | V61: =$U$61 -> 1472.235 | W61: =$V$61 -> 1472.235 | X61: =$W$61 -> 1472.235 | Y61: =$X$61 -> 1472.235
A62: Total Current Liabilities | B62: 1470.024 | C62: 1353.355 | D62: 916.94 | E62: 1092.38 | F62: 1374.652 | G62: 1604.821 | H62: 1992.089 | I62: 1717.695 | J62: 2345.721 | K62: 2871.101 | L62: 1357.81 | M62: 1428.136 | N62: 2344.792 | O62: 2347.235 | P62: 15396.708 | Q62: 8122.635 | R62: =SUM($R$57,$R$58,$R$59,$R$60,$R$61) -> 9121.0471 | S62: =SUM($S$57,$S$58,$S$59,$S$60,$S$61) -> 9309.5756 | T62: =SUM($T$57,$T$58,$T$59,$T$60,$T$61) -> 9506.3967 | U62: =SUM($U$57,$U$58,$U$59,$U$60,$U$61) -> 9711.7295 | V62: =SUM($V$57,$V$58,$V$59,$V$60,$V$61) -> 9920.3644 | W62: =SUM($W$57,$W$58,$W$59,$W$60,$W$61) -> 10139.268 | X62: =SUM($X$57,$X$58,$X$59,$X$60,$X$61) -> 10364.695 | Y62: =SUM($Y$57,$Y$58,$Y$59,$Y$60,$Y$61) -> 10604.901
A63: Long-term Debt | B63: 147.618 | C63: 212.064 | D63: 131.366 | E63: 147.947 | F63: 120.179 | G63: 105.389 | H63: 333.008 | I63: 126.043 | J63: 1771.799 | K63: 2217.124 | L63: 1868.888 | M63: 2452.489 | N63: 4682.593 | O63: 4756.936 | P63: 4859.584 | Q63: 6967.219 | R63: =Assumptions!$R$35 -> 8773.1 | S63: =Assumptions!$S$35 -> 8773.1 | T63: =Assumptions!$T$35 -> 8773.1 | U63: =Assumptions!$U$35 -> 8773.1 | V63: =Assumptions!$V$35 -> 8773.1 | W63: =Assumptions!$W$35 -> 8773.1 | X63: =Assumptions!$X$35 -> 8773.1 | Y63: =Assumptions!$Y$35 -> 8773.1
A64: Long-term Deferred Revenue | B64: 122.548 | C64: 134.625 | D64: 159.574 | E64: 161.176 | F64: 169.781 | G64: 174.478 | H64: 190.342 | I64: 203.198 | J64: 223.324 | K64: 252.342 | L64: 289.414 | M64: 312.994 | N64: 362.645 | O64: 430.682 | P64: 527.909 | Q64: 663.41 | R64: =$Q$64 -> 663.41 | S64: =$R$64 -> 663.41 | T64: =$S$64 -> 663.41 | U64: =$T$64 -> 663.41 | V64: =$U$64 -> 663.41 | W64: =$V$64 -> 663.41 | X64: =$W$64 -> 663.41 | Y64: =$X$64 -> 663.41
A65: Other Long-term Liabilities | B65: 39.14 | C65: 39.549 | D65: 37.313 | E65: 37.24 | F65: 37.947 | G65: 45.737 | H65: 46.173 | I65: 65.831 | J65: 67.878 | K65: 86.113 | L65: 88.611 | M65: 189.593 | N65: 326.528 | O65: 409.472 | P65: 408.756 | Q65: 412.361 | R65: =$Q$65 -> 412.361 | S65: =$R$65 -> 412.361 | T65: =$S$65 -> 412.361 | U65: =$T$65 -> 412.361 | V65: =$U$65 -> 412.361 | W65: =$V$65 -> 412.361 | X65: =$W$65 -> 412.361 | Y65: =$X$65 -> 412.361
A66: Total Liabilities | B66: 1779.33 | C66: 1676.08 | D66: 1256.1 | E66: 1424.031 | F66: 1702.559 | G66: 1930.425 | H66: 2327.926 | I66: 3768.625 | J66: 4408.722 | K66: 4974.466 | L66: 3489.882 | M66: 4359.046 | N66: 7716.558 | O66: 7862.477 | P66: 21009.433 | Q66: 15876.438 | R66: =SUM($R$62,$R$63,$R$64,$R$65) -> 18969.918 | S66: =SUM($S$62,$S$63,$S$64,$S$65) -> 19158.447 | T66: =SUM($T$62,$T$63,$T$64,$T$65) -> 19355.268 | U66: =SUM($U$62,$U$63,$U$64,$U$65) -> 19560.601 | V66: =SUM($V$62,$V$63,$V$64,$V$65) -> 19769.235 | W66: =SUM($W$62,$W$63,$W$64,$W$65) -> 19988.139 | X66: =SUM($X$62,$X$63,$X$64,$X$65) -> 20213.566 | Y66: =SUM($Y$62,$Y$63,$Y$64,$Y$65) -> 20453.772
A67: EQUITY
A68: Retained Earnings (Accumulated Deficit) | B68: 942.923 | C68: 1127.339 | D68: 1303.506 | E68: 1239.445 | F68: 1433.014 | G68: 1590.009 | H68: 1885.977 | I68: 2288.436 | J68: 2585.68 | K68: 3010.007 | L68: 3330.603 | M68: 3439.38 | N68: 3434.539 | O68: 3602.824 | P68: 4003.388 | Q68: 4486.775 | R68: =$Q$68+$R$33 -> 4923.4493 | S68: =$R$68+$S$33 -> 5393.7036 | T68: =$S$68+$T$33 -> 5899.2328 | U68: =$T$68+$U$33 -> 6441.8704 | V68: =$U$68+$V$33 -> 7027.9669 | W68: =$V$68+$W$33 -> 7660.1901 | X68: =$W$68+$X$33 -> 8340.401 | Y68: =$X$68+$Y$33 -> 9066.0386
A69: Accumulated OCI | B69: 0.911 | C69: 0.514 | D69: 0.612 | E69: 0.683 | F69: 0.639 | G69: 0.651 | H69: 0.657 | I69: 0.549 | J69: 0.706 | K69: 0.8 | L69: 0.652 | M69: 0.663 | N69: 0.705 | O69: 0.698 | P69: 0.695 | Q69: 0.692 | R69: =$Q$69 -> 0.692 | S69: =$R$69 -> 0.692 | T69: =$S$69 -> 0.692 | U69: =$T$69 -> 0.692 | V69: =$U$69 -> 0.692 | W69: =$V$69 -> 0.692 | X69: =$W$69 -> 0.692 | Y69: =$X$69 -> 0.692
A70: Total Stockholders' Equity | B70: 1425.575 | C70: 1625.036 | D70: 1818.677 | E70: 1768.407 | F70: 1972.005 | G70: 2165.378 | H70: 3076.91 | I70: 5093.993 | J70: 5417.206 | K70: 5876.754 | L70: 6238.307 | M70: 6379.319 | N70: 6301.693 | O70: 6523.39 | P70: 6992.015 | Q70: 7575.43 | R70: =$R$55-$R$66 -> 23.254343 | S70: =$S$55-$S$66 -> 387.00961 | T70: =$T$55-$T$66 -> 771.01962 | U70: =$U$55-$U$66 -> 1175.832 | V70: =$V$55-$V$66 -> 1593.3236 | W70: =$W$55-$W$66 -> 2036.2318 | X70: =$X$55-$X$66 -> 2495.5655 | Y70: =$Y$55-$Y$66 -> 2986.3306
A71: Total Liabilities & Equity | B71: 3205.077 | C71: 3301.283 | D71: 3074.942 | E71: 3192.604 | F71: 3674.729 | G71: 4095.964 | H71: 5405 | I71: 8862.781 | J71: 9826.092 | K71: 10851.383 | L71: 9728.348 | M71: 10738.525 | N71: 14018.429 | O71: 14386.037 | P71: 28001.61 | Q71: 23452.029 | R71: =$R$55 -> 18993.172 | S71: =$S$55 -> 19545.456 | T71: =$T$55 -> 20126.287 | U71: =$U$55 -> 20736.433 | V71: =$V$55 -> 21362.559 | W71: =$W$55 -> 22024.371 | X71: =$X$55 -> 22709.132 | Y71: =$Y$55 -> 23440.103
A72: WORKING CAPITAL
A73: Net Operating Working Capital | B73: 1559.783 | C73: 1457.841 | D73: 1494.55 | E73: 1406.564 | F73: 1663.604 | G73: 1625.095 | H73: 2447.366 | I73: 4332.348 | J73: 5337.087 | K73: 5465.281 | L73: 6149.36 | M73: 5636.956 | N73: 4915.392 | O73: 6274.085 | P73: 6957.282 | Q73: 14288.729 | R73: =($R$49+$R$50+$R$51)-($R$57+$R$58+$R$61) -> 10520.779 | S73: =($S$49+$S$50+$S$51)-($S$57+$S$58+$S$61) -> 10978.335 | T73: =($T$49+$T$50+$T$51)-($T$57+$T$58+$T$61) -> 11456.145 | U73: =($U$49+$U$50+$U$51)-($U$57+$U$58+$U$61) -> 11954.757 | V73: =($V$49+$V$50+$V$51)-($V$57+$V$58+$V$61) -> 12466.049 | W73: =($W$49+$W$50+$W$51)-($W$57+$W$58+$W$61) -> 13002.757 | X73: =($X$49+$X$50+$X$51)-($X$57+$X$58+$X$61) -> 13555.891 | Y73: =($Y$49+$Y$50+$Y$51)-($Y$57+$Y$58+$Y$61) -> 14140.456
A74: Change in NOWC | C74: -101.942 | D74: 36.709 | E74: -87.986 | F74: 257.04 | G74: -38.509 | H74: 822.271 | I74: 1884.982 | J74: 1004.739 | K74: 128.194 | L74: 684.079 | M74: -512.404 | N74: -721.564 | O74: 1358.693 | P74: 683.197 | Q74: 7331.447 | R74: =$R$73-$Q$73 -> -3767.9497 | S74: =$S$73-$R$73 -> 457.55527 | T74: =$T$73-$S$73 -> 477.81001 | U74: =$U$73-$T$73 -> 498.61234 | V74: =$V$73-$U$73 -> 511.29169 | W74: =$W$73-$V$73 -> 536.70813 | X74: =$X$73-$W$73 -> 553.13374 | Y74: =$Y$73-$X$73 -> 584.56513
A76: CASH FLOW STATEMENT
B77: Q4FY22 | C77: Q1FY23 | D77: Q2FY23 | E77: Q3FY23 | F77: Q4FY23 | G77: Q1FY24 | H77: Q2FY24 | I77: Q3FY24 | J77: Q4FY24 | K77: Q1FY25 | L77: Q2FY25 | M77: Q3FY25 | N77: Q4FY25 | O77: Q1FY26 | P77: Q2FY26 | Q77: Q3FY26 | R77: Q4FY26E | S77: Q1FY27E | T77: Q2FY27E | U77: Q3FY27E | V77: Q4FY27E | W77: Q1FY28E | X77: Q2FY28E | Y77: Q3FY28E
A78: OPERATING ACTIVITIES
A79: Net Income | B79: 140.822 | C79: 184.416 | D79: 176.167 | E79: 85.846 | F79: 193.569 | G79: 156.995 | H79: 295.968 | I79: 402.459 | J79: 297.244 | K79: 424.327 | L79: 320.596 | M79: 108.777 | N79: 195.154 | O79: 168.285 | P79: 400.564 | Q79: 483.387 | R79: =$R$33 -> 436.67432 | S79: =$S$33 -> 470.25429 | T79: =$T$33 -> 505.52919 | U79: =$U$33 -> 542.63761 | V79: =$V$33 -> 586.09649 | W79: =$W$33 -> 632.22316 | X79: =$X$33 -> 680.21088 | Y79: =$Y$33 -> 725.63765
A80: Depreciation & Amortization | B80: 0.751 | C80: 8.547 | D80: 8.649 | E80: 8.736 | F80: 0.968 | G80: 7 | H80: 7.3 | I80: 7.6 | J80: 8.2 | K80: 9 | L80: 9.5 | M80: 10.9 | N80: 11.6 | O80: 12.1 | P80: 12.8 | Q80: 13.5 | R80: =Assumptions!$R$16 -> 13.5 | S80: =Assumptions!$S$16 -> 13.5 | T80: =Assumptions!$T$16 -> 13.5 | U80: =Assumptions!$U$16 -> 13.5 | V80: =Assumptions!$V$16 -> 13.5 | W80: =Assumptions!$W$16 -> 13.5 | X80: =Assumptions!$X$16 -> 13.5 | Y80: =Assumptions!$Y$16 -> 13.5
A81: Stock-Based Compensation | B81: 8.884 | C81: 11.014 | D81: 16.981 | E81: 13.652 | F81: 12.786 | G81: 57.379 | H81: 43.061 | I81: 56.107 | J81: 74.96 | K81: 64.014 | L81: 82.122 | M81: 84.704 | N81: 83.612 | O81: 89.139 | P81: 90.485 | Q81: 125.934 | R81: =Assumptions!$R$20 -> 125.9 | S81: =Assumptions!$S$20 -> 125.9 | T81: =Assumptions!$T$20 -> 125.9 | U81: =Assumptions!$U$20 -> 125.9 | V81: =Assumptions!$V$20 -> 125.9 | W81: =Assumptions!$W$20 -> 125.9 | X81: =Assumptions!$X$20 -> 125.9 | Y81: =Assumptions!$Y$20 -> 125.9
A82: Change in Accounts Receivable | B82: -155.974 | C82: 95.088 | D82: -27.052 | E82: 97.847 | F82: -477.78 | G82: 302.501 | H82: -657.186 | I82: -147.185 | J82: -1087.317 | K82: 15.288 | L82: -334.662 | M82: 414.156 | N82: 438.559 | O82: -321.244 | P82: -8471.584 | Q82: 2582.997 | R82: =-($R$49-$Q$49) -> 1565.4277 | S82: =-($S$49-$R$49) -> -261.46969 | T82: =-($T$49-$S$49) -> -273.09953 | U82: =-($U$49-$T$49) -> -285.04882 | V82: =-($V$49-$U$49) -> -294.29381 | W82: =-($W$49-$V$49) -> -309.02947 | X82: =-($X$49-$W$49) -> -318.67085 | Y82: =-($Y$49-$X$49) -> -334.73099
A83: Change in Inventories | B83: 56.811 | C83: -190.449 | D83: 314.238 | E83: -118.602 | F83: 94.855 | G83: -607.241 | H83: -414.192 | I83: -1657.59 | J83: -220.973 | K83: -606.873 | L83: 1306.486 | M83: -400.766 | N83: -654.453 | O83: -1087.01 | P83: -5001.809 | Q83: -580.741 | R83: =-($R$50-$Q$50) -> 876.58981 | S83: =-($S$50-$R$50) -> -384.61411 | T83: =-($T$50-$S$50) -> -401.5315 | U83: =-($U$50-$T$50) -> -418.89639 | V83: =-($V$50-$U$50) -> -425.63276 | W83: =-($W$50-$V$50) -> -446.58269 | X83: =-($X$50-$W$50) -> -459.88967 | Y83: =-($Y$50-$X$50) -> -490.03979
A84: Change in Accounts Payable | B84: -122.886 | C84: 132.302 | D84: -223.21 | E84: 81.788 | F84: 136.255 | G84: 302.973 | H84: 176.64 | I84: -170 | J84: 369.577 | K84: 220.353 | L84: -1127.269 | M84: 95.226 | N84: 630.722 | O84: 0.901 | P84: 12465.867 | Q84: -10059.838 | R84: =$R$57-$Q$57 -> 1325.9321 | S84: =$S$57-$R$57 -> 188.52853 | T84: =$T$57-$S$57 -> 196.82103 | U84: =$U$57-$T$57 -> 205.33287 | V84: =$V$57-$U$57 -> 208.63488 | W84: =$W$57-$V$57 -> 218.90403 | X84: =$X$57-$W$57 -> 225.42679 | Y84: =$Y$57-$X$57 -> 240.20565
A85: Total Operating Cash Flow | B85: -25.143 | C85: 313.587 | D85: 161.087 | E85: 198.245 | F85: -9.339 | G85: 270.465 | H85: -595.085 | I85: -1513.538 | J85: -647.814 | K85: 408.904 | L85: -239.757 | M85: 626.764 | N85: 863.613 | O85: -917.523 | P85: -23.898 | Q85: -6615.426 | R85: =SUM($R$79,$R$80,$R$81,$R$82,$R$83,$R$84) -> 4344.024 | S85: =SUM($S$79,$S$80,$S$81,$S$82,$S$83,$S$84) -> 152.09902 | T85: =SUM($T$79,$T$80,$T$81,$T$82,$T$83,$T$84) -> 167.11918 | U85: =SUM($U$79,$U$80,$U$81,$U$82,$U$83,$U$84) -> 183.42528 | V85: =SUM($V$79,$V$80,$V$81,$V$82,$V$83,$V$84) -> 214.20481 | W85: =SUM($W$79,$W$80,$W$81,$W$82,$W$83,$W$84) -> 234.91503 | X85: =SUM($X$79,$X$80,$X$81,$X$82,$X$83,$X$84) -> 266.47714 | Y85: =SUM($Y$79,$Y$80,$Y$81,$Y$82,$Y$83,$Y$84) -> 280.47252
A86: INVESTING ACTIVITIES
A87: Capital Expenditures | B87: -11.025 | C87: -10.746 | D87: -9.885 | E87: -7.987 | F87: -8.175 | G87: -2.631 | H87: -14.72 | I87: -92.945 | J87: -13.983 | K87: -44.3 | L87: -27.536 | M87: -32.7 | N87: -22.678 | O87: -32.27 | P87: -21.221 | Q87: -80.278 | R87: =-Assumptions!$R$17 -> 80.3 | S87: =-Assumptions!$S$17 -> 80.3 | T87: =-Assumptions!$T$17 -> 80.3 | U87: =-Assumptions!$U$17 -> 80.3 | V87: =-Assumptions!$V$17 -> 80.3 | W87: =-Assumptions!$W$17 -> 80.3 | X87: =-Assumptions!$X$17 -> 80.3 | Y87: =-Assumptions!$Y$17 -> 80.3
A88: Purchases of Investments | F88: -0.5 | J88: -69.673 | L88: 0 | M88: 0 | N88: -56 | P88: -25 | Q88: -17
A89: Total Investing Cash Flow | B89: -11.025 | C89: -10.746 | D89: -9.885 | E89: -7.987 | F89: -10.868 | G89: -7.631 | H89: -14.904 | I89: -115.434 | J89: -56.279 | K89: -44.3 | L89: -27.536 | M89: -32.7 | N89: -78.678 | O89: -32.27 | P89: -46.221 | Q89: -97.278 | R89: =SUM($R$87,$R$88) -> 80.3 | S89: =SUM($S$87,$S$88) -> 80.3 | T89: =SUM($T$87,$T$88) -> 80.3 | U89: =SUM($U$87,$U$88) -> 80.3 | V89: =SUM($V$87,$V$88) -> 80.3 | W89: =SUM($W$87,$W$88) -> 80.3 | X89: =SUM($X$87,$X$88) -> 80.3 | Y89: =SUM($Y$87,$Y$88) -> 80.3
A90: FINANCING ACTIVITIES
A91: Total Financing Cash Flow | B91: 56.506 | C91: -331.183 | D91: -84.638 | E91: -131.47 | F91: 98.998 | G91: -159.941 | H91: 792.135 | I91: 3020.589 | J91: 258.941 | K91: 49.854 | L91: -387.288 | M91: 512.052 | N91: 1849.427 | O91: -18.665 | P91: 66.162 | Q91: 3859.338
A92: Net Change in Cash | B92: 19.964 | C92: -29.813 | D92: 66.342 | E92: 58.212 | F92: 77.66 | G92: 102.69 | H92: 182.519 | I92: 1389.813 | J92: -445.709 | K92: 418.958 | L92: -658.244 | M92: 1106.105 | N92: 2635.209 | O92: -973.046 | P92: -5.53 | Q92: -2853.759 | R92: =$R$85+$R$89+$R$91 -> 4424.324 | S92: =$S$85+$S$89+$S$91 -> 232.39902 | T92: =$T$85+$T$89+$T$91 -> 247.41918 | U92: =$U$85+$U$89+$U$91 -> 263.72528 | V92: =$V$85+$V$89+$V$91 -> 294.50481 | W92: =$W$85+$W$89+$W$91 -> 315.21503 | X92: =$X$85+$X$89+$X$91 -> 346.77714 | Y92: =$Y$85+$Y$89+$Y$91 -> 360.77252
A93: FREE CASH FLOW
A94: FCFE | B94: -45.052 | C94: 291.827 | D94: 134.221 | E94: 176.606 | F94: -32.993 | G94: 205.455 | H94: -653.05 | I94: -1685.079 | J94: -779.053 | K94: 300.59 | L94: -349.415 | M94: 509.36 | N94: 701.323 | O94: -1038.932 | P94: -160.604 | Q94: -6838.638 | R94: =$R$85+$R$89-$R$81 -> 4298.424 | S94: =$S$85+$S$89-$S$81 -> 106.49902 | T94: =$T$85+$T$89-$T$81 -> 121.51918 | U94: =$U$85+$U$89-$U$81 -> 137.82528 | V94: =$V$85+$V$89-$V$81 -> 168.60481 | W94: =$W$85+$W$89-$W$81 -> 189.31503 | X94: =$X$85+$X$89-$X$81 -> 220.87714 | Y94: =$Y$85+$Y$89-$Y$81 -> 234.87252

Sheet Assumptions
A1: SMCI — Model Assumptions
A2: Yellow = editable forecast inputs | Blue shading = forecast period
B3: Q4FY22 | C3: Q1FY23 | D3: Q2FY23 | E3: Q3FY23 | F3: Q4FY23 | G3: Q1FY24 | H3: Q2FY24 | I3: Q3FY24 | J3: Q4FY24 | K3: Q1FY25 | L3: Q2FY25 | M3: Q3FY25 | N3: Q4FY25 | O3: Q1FY26 | P3: Q2FY26 | Q3: Q3FY26 | R3: Q4FY26E | S3: Q1FY27E | T3: Q2FY27E | U3: Q3FY27E | V3: Q4FY27E | W3: Q1FY28E | X3: Q2FY28E | Y3: Q3FY28E
A4: REVENUE DRIVERS
A5: Total Revenue ($mm) | B5: 1635.46 | C5: 1852.13 | D5: 1803.195 | E5: 1283.296 | F5: 2184.861 | G5: 2119.672 | H5: 3664.924 | I5: 3850.066 | J5: 5354.589 | K5: 5937.256 | L5: 5677.962 | M5: 4599.913 | N5: 5756.911 | O5: 5017.79 | P5: 12682.491 | Q5: 10243.014 | R5: =R46 -> 10634.217 | S5: =S46 -> 11040.253 | T5: =T46 -> 11464.35 | U5: =U46 -> 11907.003 | V5: =V46 -> 12364.012 | W5: =W46 -> 12843.904 | X5: =X46 -> 13338.768 | Y5: =Y46 -> 13858.572
A6: Revenue Growth % (QoQ) | C6: =C5/B5-1 -> 0.1324826 | D6: =D5/C5-1 -> -0.026420932 | E6: =E5/D5-1 -> -0.28832101 | F6: =F5/E5-1 -> 0.70253862 | G6: =G5/F5-1 -> -0.029836681 | H6: =H5/G5-1 -> 0.72900524 | I6: =I5/H5-1 -> 0.050517282 | J6: =J5/I5-1 -> 0.3907785 | ... Y6: =Y5/X5-1 -> 0.038969422
A7: Revenue Growth % (YoY) | F7: =F5/B5-1 -> 0.33593056 | G7: =G5/C5-1 -> 0.14445098 | H7: =H5/D5-1 -> 1.0324613 | I7: =I5/E5-1 -> 2.0001387 | J7: =J5/F5-1 -> 1.4507687 | K7: =K5/G5-1 -> 1.8010258 | L7: =L5/H5-1 -> 0.54927142 | M7: =M5/I5-1 -> 0.19476212 | ... Y7: =Y5/U5-1 -> 0.16390101
A8: MARGIN DRIVERS
A9: Gross Margin % | B9: 0.17569613 | C9: 0.18764072 | D9: 0.18712452 | E9: 0.17638877 | F9: 0.17012341 | G9: 0.16686119 | H9: 0.15397918 | I9: 0.15515786 | J9: 0.10197403 | K9: 0.13062937 | L9: 0.11800396 | M9: 0.095701375 | N9: 0.094512839 | O9: 0.093143197 | P9: 0.0629661 | Q9: 0.099451197 | R9: 0.095 | S9: 0.0955 | T9: 0.096 | U9: 0.0965 | V9: 0.0975 | W9: 0.0985 | X9: 0.0995 | Y9: 0.1 | AA9: AI-mix GM: stabilize ~9.5%->10.0%
A10: OPEX DRIVERS
A11: R&D ($mm) | B11: 70.79 | C11: 74.243 | D11: 70.7 | E11: 77.515 | F11: 84.802 | G11: 111.027 | H11: 108.824 | I11: 116.226 | J11: 127.471 | K11: 132.243 | L11: 158.229 | M11: 162.857 | N11: 183.221 | O11: 173.314 | P11: 180.761 | Q11: 215.659 | R11: 215.7 | S11: 215.7 | T11: 215.7 | U11: 215.7 | V11: 215.7 | W11: 215.7 | X11: 215.7 | Y11: 215.7
A12: R&D % of Revenue | B12: 0.0433 | C12: 0.0401 | D12: 0.0392 | E12: 0.0604 | F12: 0.0388 | G12: 0.0524 | H12: 0.0297 | I12: 0.0302 | J12: 0.0238 | K12: 0.0223 | L12: 0.0279 | M12: 0.0354 | N12: 0.0318 | O12: 0.0345 | P12: 0.0143 | Q12: 0.0211 | R12: 0.0211 | S12: 0.0211 | T12: 0.0211 | U12: 0.0211 | V12: 0.0211 | W12: 0.0211 | X12: 0.0211 | Y12: 0.0211
A13: SG&A ($mm) | B13: 51.341 | C13: 53.169 | D13: 51.54 | E13: 49.762 | F13: 60.139 | G13: 70.154 | H13: 84.034 | I13: 102.828 | J13: 130.072 | K13: 134.138 | L13: 143.169 | M13: 130.581 | N13: 132.49 | O13: 111.803 | P13: 143.508 | Q13: 177.153 | R13: 177.2 | S13: 177.2 | T13: 177.2 | U13: 177.2 | V13: 177.2 | W13: 177.2 | X13: 177.2 | Y13: 177.2
A14: SG&A % of Revenue | B14: 0.0314 | C14: 0.0287 | D14: 0.0286 | E14: 0.0388 | F14: 0.0275 | G14: 0.0331 | H14: 0.0229 | I14: 0.0267 | J14: 0.0243 | K14: 0.0226 | L14: 0.0252 | M14: 0.0284 | N14: 0.023 | O14: 0.0223 | P14: 0.0113 | Q14: 0.0173 | R14: 0.0173 | S14: 0.0173 | T14: 0.0173 | U14: 0.0173 | V14: 0.0173 | W14: 0.0173 | X14: 0.0173 | Y14: 0.0173
A15: D&A & CAPEX
A16: Depreciation & Amortization ($mm) | B16: 0.751 | C16: 8.547 | D16: 8.649 | E16: 8.736 | F16: 0.968 | G16: 7 | H16: 7.3 | I16: 7.6 | J16: 8.2 | K16: 9 | L16: 9.5 | M16: 10.9 | N16: 11.6 | O16: 12.1 | P16: 12.8 | Q16: 13.5 | R16: 13.5 | S16: 13.5 | T16: 13.5 | U16: 13.5 | V16: 13.5 | W16: 13.5 | X16: 13.5 | Y16: 13.5
A17: Capital Expenditures ($mm) | B17: -11.025 | C17: -10.746 | D17: -9.885 | E17: -7.987 | F17: -8.175 | G17: -2.631 | H17: -14.72 | I17: -92.945 | J17: -13.983 | K17: -44.3 | L17: -27.536 | M17: -32.7 | N17: -22.678 | O17: -32.27 | P17: -21.221 | Q17: -80.278 | R17: -80.3 | S17: -80.3 | T17: -80.3 | U17: -80.3 | V17: -80.3 | W17: -80.3 | X17: -80.3 | Y17: -80.3
A18: Capex % of Revenue | B18: 0.0067 | C18: 0.0058 | D18: 0.0055 | E18: 0.0062 | F18: 0.0037 | G18: 0.0012 | H18: 0.004 | I18: 0.0241 | J18: 0.0026 | K18: 0.0075 | L18: 0.0048 | M18: 0.0071 | N18: 0.0039 | O18: 0.0064 | P18: 0.0017 | Q18: 0.0078 | R18: 0.0078 | S18: 0.0078 | T18: 0.0078 | U18: 0.0078 | V18: 0.0078 | W18: 0.0078 | X18: 0.0078 | Y18: 0.0078
A19: OTHER
A20: Stock-Based Compensation ($mm) | B20: 8.884 | C20: 11.014 | D20: 16.981 | E20: 13.652 | F20: 12.786 | G20: 57.379 | H20: 43.061 | I20: 56.107 | J20: 74.96 | K20: 64.014 | L20: 82.122 | M20: 84.704 | N20: 83.612 | O20: 89.139 | P20: 90.485 | Q20: 125.934 | R20: 125.9 | S20: 125.9 | T20: 125.9 | U20: 125.9 | V20: 125.9 | W20: 125.9 | X20: 125.9 | Y20: 125.9
A21: SBC % of Revenue | B21: 0.0054 | C21: 0.0059 | D21: 0.0094 | E21: 0.0106 | F21: 0.0059 | G21: 0.0271 | H21: 0.0117 | I21: 0.0146 | J21: 0.014 | K21: 0.0108 | L21: 0.0145 | M21: 0.0184 | N21: 0.0145 | O21: 0.0178 | P21: 0.0071 | Q21: 0.0123 | R21: 0.0123 | S21: 0.0123 | T21: 0.0123 | U21: 0.0123 | V21: 0.0123 | W21: 0.0123 | X21: 0.0123 | Y21: 0.0123
A22: Interest Income ($mm) | L22: 8.776 | M22: 14.654 | P22: 51.042 | Q22: 45.437 | R22: 43.6 | S22: 41.9 | T22: 40.2 | U22: 38.6 | V22: 37 | W22: 35.6 | X22: 34.1 | Y22: 32.8 | AA22: EST ~$45mm/qtr tapering -4%/qtr as cash deployed
A23: Interest Expense ($mm) | B23: 2.928 | C23: 3.938 | D23: 1.756 | E23: 1.288 | F23: 3.509 | G23: 1.863 | H23: 8.131 | I23: 6.246 | R23: =R53 -> 109.66375 | S23: =S53 -> 109.66375 | T23: =T53 -> 109.66375 | U23: =U53 -> 109.66375 | V23: =V53 -> 109.66375 | W23: =W53 -> 109.66375 | X23: =X53 -> 109.66375 | Y23: =Y53 -> 109.66375
A24: Effective Tax Rate % | B24: 0.15463856 | C24: 0.17431833 | D24: 0.14373967 | E24: 0.11227159 | F24: 0.13919981 | G24: 0.1140737 | H24: 0.17205032 | I24: -0.052246415 | J24: 0.0052174844 | K24: 0.14974582 | L24: 0.15088528 | M24: 0.050977142 | N24: 0.090025692 | O24: 0.1926686 | P24: 0.1984151 | Q24: 0.20791808 | R24: 0.2079 | S24: 0.2079 | T24: 0.2079 | U24: 0.2079 | V24: 0.2079 | W24: 0.2079 | X24: 0.2079 | Y24: 0.2079
A25: SHARES
A26: Diluted Shares (mm) | B26: 529.16 | C26: 550.17 | D26: 561.44 | E26: 562.33 | F26: 550.17 | G26: 571.853 | H26: 580.777 | I26: 614.31 | J26: 641.644 | K26: 639.148 | L26: 636.047 | M26: 621.809 | N26: 616.604 | O26: 663.235 | P26: 693.989 | Q26: 692.189 | R26: 692.2 | S26: 692.2 | T26: 692.2 | U26: 692.2 | V26: 692.2 | W26: 692.2 | X26: 692.2 | Y26: 692.2
A27: QoQ Share Change (mm) | C27: =C26-B26 -> 21.01 | D27: =D26-C26 -> 11.27 | E27: =E26-D26 -> 0.89 | F27: =F26-E26 -> -12.16 | G27: =G26-F26 -> 21.683 | H27: =H26-G26 -> 8.924 | I27: =I26-H26 -> 33.533 | J27: =J26-I26 -> 27.334 | ... Y27: =Y26-X26 -> 0
A28: Basic Shares (mm) | B28: 507.96 | C28: 525.98 | D28: 531.6 | E28: 532.8 | F28: 525.98 | G28: 530.928 | H28: 541.354 | I28: 564.78 | J28: 586.45 | K28: 589.558 | L28: 592.507 | M28: 595.041 | N28: 597.554 | O28: 595.624 | P28: 598.004 | Q28: 600.205 | R28: 600.2 | S28: 600.2 | T28: 600.2 | U28: 600.2 | V28: 600.2 | W28: 600.2 | X28: 600.2 | Y28: 600.2
A29: WORKING CAPITAL DAYS
A30: Days Sales Outstanding | B30: 46.4 | C30: 36.2 | D30: 38.8 | E30: 47.7 | F30: 47.8 | G30: 36.3 | H30: 37.3 | I30: 39 | J30: 46.5 | K30: 41.9 | L30: 49 | M30: 52.3 | N30: 34.8 | O30: 45.8 | P30: 79 | Q30: 74.7 | R30: 58.6 | S30: 58.6 | T30: 58.6 | U30: 58.6 | V30: 58.6 | W30: 58.6 | X30: 58.6 | Y30: 58.6
A31: Inventory Days | B31: 104.3 | C31: 105 | D31: 88.3 | E31: 132.6 | F31: 72.6 | G31: 105.8 | H31: 72.4 | I31: 115.4 | J31: 82 | K31: 86.9 | L31: 65.3 | M31: 84.7 | N31: 81.7 | O31: 114.6 | P31: 81.1 | Q31: 109.5 | R31: 96.7 | S31: 96.7 | T31: 96.7 | U31: 96.7 | V31: 96.7 | W31: 96.7 | X31: 96.7 | Y31: 96.7
A32: Days Payable Outstanding | B32: 44.2 | C32: 47.5 | D32: 34.8 | E32: 55.3 | F32: 39 | G32: 55.9 | H32: 37 | I32: 30.6 | J32: 27.9 | K32: 29.7 | L32: 10 | M32: 14.1 | N32: 22.4 | O32: 25.6 | P32: 105.3 | Q32: 36.4 | R32: 47.4 | S32: 47.4 | T32: 47.4 | U32: 47.4 | V32: 47.4 | W32: 47.4 | X32: 47.4 | Y32: 47.4
A33: DEBT SCHEDULE
A34: Short-term Debt ($mm) | B34: 449.146 | C34: 101.173 | F34: 170.123 | R34: 0 | S34: 0 | T34: 0 | U34: 0 | V34: 0 | W34: 0 | X34: 0 | Y34: 0
A35: Long-term Debt ($mm) | B35: 147.618 | C35: 212.064 | D35: 131.366 | E35: 147.947 | F35: 120.179 | G35: 105.389 | H35: 333.008 | I35: 126.043 | J35: 1771.799 | K35: 2217.124 | L35: 1868.888 | M35: 2452.489 | N35: 4682.593 | O35: 4756.936 | P35: 4859.584 | Q35: 6967.219 | R35: =R49+R50 -> 8773.1 | S35: =S49+S50 -> 8773.1 | T35: =T49+T50 -> 8773.1 | U35: =U49+U50 -> 8773.1 | V35: =V49+V50 -> 8773.1 | W35: =W49+W50 -> 8773.1 | X35: =X49+X50 -> 8773.1 | Y35: =Y49+Y50 -> 8773.1
A36: Total Debt ($mm) | B36: =B34+B35 -> 596.764 | C36: =C34+C35 -> 313.237 | D36: =D34+D35 -> 131.366 | E36: =E34+E35 -> 147.947 | F36: =F34+F35 -> 290.302 | G36: =G34+G35 -> 105.389 | H36: =H34+H35 -> 333.008 | I36: =I34+I35 -> 126.043 | ... Y36: =Y34+Y35 -> 8773.1
A39: --- SMCI BOTTOM-UP REVENUE BUILD (assumptions-architect) ---
A40: Source: SMCI 10-K product disaggregation (Systems vs Subsystems & Accessories). Units & ASP are ANALYST ESTIMATES (SMCI discloses no units); AI-platform mix per company commentary.
A41: Server & Storage Systems - Units (000s) | B41: 135.2971 | C41: 146.882 | D41: 137.4936 | E41: 93.4239 | F41: 148.5705 | G41: 134.4895 | H41: 189.3544 | I41: 189.4638 | J41: 209.7214 | K41: 207.804 | L41: 192.2396 | M41: 167.1891 | N41: 182.3022 | O41: 154.0947 | P41: 254.1783 | Q41: 223.0184 | R41: 229.71 | S41: 236.6 | T41: 243.7 | U41: 251.01 | V41: 258.54 | W41: 266.3 | X41: 274.28 | Y41: 282.51 | AA41: EST units; +3% QoQ vol
A42: Server & Storage Systems - ASP ($000s) | B42: 11 | C42: 11.5 | D42: 12 | E42: 12.5 | F42: 13.5 | G42: 14.5 | H42: 18 | I42: 19 | J42: 24 | K42: 27 | L42: 28 | M42: 26 | N42: 30 | O42: 31 | P42: 48 | Q42: 44 | R42: 44.44 | S42: 44.88 | T42: 45.33 | U42: 45.79 | V42: 46.24 | W42: 46.71 | X42: 47.17 | Y42: 47.65 | AA42: EST blended ASP; +1% QoQ
A43: AI/GPU-platform mix % of systems | B43: 0.1 | C43: 0.12 | D43: 0.15 | E43: 0.18 | F43: 0.22 | G43: 0.28 | H43: 0.4 | I43: 0.48 | J43: 0.55 | K43: 0.6 | L43: 0.62 | M43: 0.58 | N43: 0.65 | O43: 0.68 | P43: 0.78 | Q43: 0.75 | R43: 0.76 | S43: 0.77 | T43: 0.78 | U43: 0.79 | V43: 0.8 | W43: 0.81 | X43: 0.82 | Y43: 0.83 | AA43: EST AI share of systems rev
A44: Server & Storage Systems Revenue ($mm) | B44: 1488.2686 | C44: 1689.1426 | D44: 1649.9234 | E44: 1167.7994 | F44: 2005.7024 | G44: 1950.0982 | H44: 3408.3793 | I44: 3599.8117 | J44: 5033.3137 | K44: 5610.7069 | L44: 5382.708 | M44: 4346.9178 | N44: 5469.0655 | O44: 4776.9361 | P44: 12200.556 | Q44: 9812.8074 | R44: =R41*R42 -> 10208.312 | S44: =S41*S42 -> 10618.608 | T44: =T41*T42 -> 11046.921 | U44: =U41*U42 -> 11493.748 | V44: =V41*V42 -> 11954.89 | W44: =W41*W42 -> 12438.873 | X44: =X41*X42 -> 12937.788 | Y44: =Y41*Y42 -> 13461.601 | AA44: = Units x ASP
A45: Subsystems & Accessories Revenue ($mm) | B45: 147.1914 | C45: 162.9874 | D45: 153.2716 | E45: 115.4966 | F45: 179.1586 | G45: 169.5738 | H45: 256.5447 | I45: 250.2543 | J45: 321.2753 | K45: 326.5491 | L45: 295.254 | M45: 252.9952 | N45: 287.8456 | O45: 240.8539 | P45: 481.9347 | Q45: 430.2066 | R45: =Q45*(1+-0.01) -> 425.90453 | S45: =R45*(1+-0.01) -> 421.64549 | T45: =S45*(1+-0.01) -> 417.42903 | U45: =T45*(1+-0.01) -> 413.25474 | V45: =U45*(1+-0.01) -> 409.1222 | W45: =V45*(1+-0.01) -> 405.03097 | X45: =W45*(1+-0.01) -> 400.98066 | Y45: =X45*(1+-0.01) -> 396.97086 | AA45: = prior x (1+-1.0%) QoQ
A46: Total Revenue - bottom-up ($mm) | B46: 1635.46 | C46: 1852.13 | D46: 1803.195 | E46: 1283.296 | F46: 2184.861 | G46: 2119.672 | H46: 3664.924 | I46: 3850.066 | J46: 5354.589 | K46: 5937.256 | L46: 5677.962 | M46: 4599.913 | N46: 5756.911 | O46: 5017.79 | P46: 12682.491 | Q46: 10243.014 | R46: =R44+R45 -> 10634.217 | S46: =S44+S45 -> 11040.253 | T46: =T44+T45 -> 11464.35 | U46: =U44+U45 -> 11907.003 | V46: =V44+V45 -> 12364.012 | W46: =W44+W45 -> 12843.904 | X46: =X44+X45 -> 13338.768 | Y46: =Y44+Y45 -> 13858.572 | AA46: = Systems + Subsystems
A48: --- DEBT SCHEDULE (bottom-up, refined) ---
A49: Current Portion of LT Debt ($mm) | B49: 449.146 | C49: 37.66 | D49: 38.776 | E49: 39.26 | F49: 170.123 | G49: 40.843 | H49: 42.621 | I49: 41.169 | J49: 402.346 | K49: 41.594 | L49: 40.147 | M49: 39.805 | N49: 75.06 | O49: 18.77 | P49: 18.252 | Q49: 1805.882 | R49: 1805.9 | S49: 1805.9 | T49: 1805.9 | U49: 1805.9 | V49: 1805.9 | W49: 1805.9 | X49: 1805.9 | Y49: 1805.9 | AA49: EST hold latest maturities
A50: Long-term Debt balance ($mm) | B50: 147.618 | C50: 212.064 | D50: 131.366 | E50: 147.947 | F50: 120.179 | G50: 105.389 | H50: 333.008 | I50: 126.043 | J50: 1771.799 | K50: 2217.124 | L50: 1868.888 | M50: 2452.489 | N50: 4682.593 | O50: 4756.936 | P50: 4859.584 | Q50: 6967.219 | R50: 6967.2 | S50: 6967.2 | T50: 6967.2 | U50: 6967.2 | V50: 6967.2 | W50: 6967.2 | X50: 6967.2 | Y50: 6967.2 | AA50: EST hold LT principal flat
A51: Total Debt - bottom-up ($mm) | B51: 1045.91 | C51: 350.897 | D51: 170.142 | E51: 187.207 | F51: 460.425 | G51: 146.232 | H51: 375.629 | I51: 167.212 | J51: 2174.145 | K51: 2258.718 | L51: 1909.035 | M51: 2492.294 | N51: 4757.653 | O51: 4775.706 | P51: 4877.836 | Q51: 8773.101 | R51: =R49+R50 -> 8773.1 | S51: =S49+S50 -> 8773.1 | T51: =T49+T50 -> 8773.1 | U51: =U49+U50 -> 8773.1 | V51: =V49+V50 -> 8773.1 | W51: =W49+W50 -> 8773.1 | X51: =X49+X50 -> 8773.1 | Y51: =Y49+Y50 -> 8773.1 | AA51: = Current + LT balance
A52: Blended interest rate (%/qtr) | R52: 0.0125 | S52: 0.0125 | T52: 0.0125 | U52: 0.0125 | V52: 0.0125 | W52: 0.0125 | X52: 0.0125 | Y52: 0.0125 | AA52: EST ~1.25%/qtr (~5% annualized)
A53: Interest Expense - modeled ($mm) | R53: =R51*R52 -> 109.66375 | S53: =S51*S52 -> 109.66375 | T53: =T51*T52 -> 109.66375 | U53: =U51*U52 -> 109.66375 | V53: =V51*V52 -> 109.66375 | W53: =W51*W52 -> 109.66375 | X53: =X51*X52 -> 109.66375 | Y53: =Y51*Y52 -> 109.66375 | AA53: = Total Debt x rate
