Workbook

Sheet Cover
A1: Snowflake Inc. (SNOW)
A2: Value-Driven EPS and FCF Forecast
A4: Forecast horizon: | B4: FY2027 - FY2032
A5: Currency: | B5: USD
A6: Unit scale: | B6: millions except per share, customers in whole units, ARPU in thousands USD
A7: Validation status: | B7: PASS
A9: Color key
A10: Blue | B10: Hardcoded input. Edit these to change the forecast.
A11: Black | B11: Formula calculated within this sheet.
A12: Green | B12: Cross-sheet link pulling from another tab.
A13: Yellow fill | B13: Assumption flagged MISSING_EVIDENCE or USER_REQUIRED.
A15: Model framework
A16: Revenue is built bottom-up per segment using driver formulas (price x volume, customers x ARPU, etc.).
A17: Cost lines tie to revenue ratios or unit drivers. No CAGR or top-down growth rates are permitted.
A18: EPS and FCF flow from net income through standard non-cash addbacks and working capital changes.
A19: Every input on the Assumptions tab has a source and a one-sentence reason on the Audit tab.
A20: Sensitivities tab stresses the three highest-impact assumptions plus or minus 20 percent.

Sheet Summary
A1: Bottom-Line Forecast
B3: FY2027 | C3: FY2028 | D3: FY2029 | E3: FY2030 | F3: FY2031 | G3: FY2032
A4: Revenue | B4: ='P&L'!B4 -> 6053.6 | C4: ='P&L'!C4 -> 7288 | D4: ='P&L'!D4 -> 8578 | E4: ='P&L'!E4 -> 9831.8 | F4: ='P&L'!F4 -> 10924.2 | G4: ='P&L'!G4 -> 11867
A5: Gross profit | B5: ='P&L'!B10 -> 4116.448 | C5: ='P&L'!C10 -> 5028.72 | D5: ='P&L'!D10 -> 6004.6 | E5: ='P&L'!E10 -> 6980.578 | F5: ='P&L'!F10 -> 7810.803 | G5: ='P&L'!G10 -> 8544.24
A6: EBIT | B6: ='P&L'!B13 -> -1301.524 | C6: ='P&L'!C13 -> -838.12 | D6: ='P&L'!D13 -> -300.23 | E6: ='P&L'!E13 -> 393.272 | F6: ='P&L'!F13 -> 983.178 | G6: ='P&L'!G13 -> 1661.38
A7: Net income | B7: ='P&L'!B21 -> -1106.524 | C7: ='P&L'!C21 -> -658.12 | D7: ='P&L'!D21 -> -140.23 | E7: ='P&L'!E21 -> 488.9448 | F7: ='P&L'!F21 -> 970.23308 | G7: ='P&L'!G21 -> 1477.1316
A8: Diluted shares (millions) | B8: ='P&L'!B26 -> 353 | C8: ='P&L'!C26 -> 346.90909 | D8: ='P&L'!D26 -> 339.83333 | E8: ='P&L'!E26 -> 331.76923 | F8: ='P&L'!F26 -> 323.71429 | G8: ='P&L'!G26 -> 314.66667
A9: EPS | B9: ='P&L'!B27 -> -3.1346289 | C9: ='P&L'!C27 -> -1.8970964 | D9: ='P&L'!D27 -> -0.41264345 | E9: ='P&L'!E27 -> 1.4737497 | F9: ='P&L'!F27 -> 2.9971896 | G9: ='P&L'!G27 -> 4.6942742
A10: Cash flow from operations | B10: ='Cash Flow'!B17 -> 1037.5602 | C10: ='Cash Flow'!C17 -> 1612.6644 | D10: ='Cash Flow'!D17 -> 2261.6718 | E10: ='Cash Flow'!E17 -> 2829.1388 | F10: ='Cash Flow'!F17 -> 3383.8746 | G10: ='Cash Flow'!G17 -> 3959.155
A11: Capex | B11: ='Cash Flow'!B18 -> -200 | C11: ='Cash Flow'!C18 -> -250 | D11: ='Cash Flow'!D18 -> -290 | E11: ='Cash Flow'!E18 -> -320 | F11: ='Cash Flow'!F18 -> -340 | G11: ='Cash Flow'!G18 -> -360
A12: Free cash flow | B12: ='Cash Flow'!B19 -> 837.56021 | C12: ='Cash Flow'!C19 -> 1362.6644 | D12: ='Cash Flow'!D19 -> 1971.6718 | E12: ='Cash Flow'!E19 -> 2509.1388 | F12: ='Cash Flow'!F19 -> 3043.8746 | G12: ='Cash Flow'!G19 -> 3599.155
A13: FCF margin | B13: ='Cash Flow'!B20 -> 0.13835738 | C13: ='Cash Flow'!C20 -> 0.18697371 | D13: ='Cash Flow'!D20 -> 0.22985216 | E13: ='Cash Flow'!E20 -> 0.25520645 | F13: ='Cash Flow'!F20 -> 0.27863593 | G13: ='Cash Flow'!G20 -> 0.30329106

Sheet Assumptions
A1: Assumptions (blue cells are editable inputs)
A3: Driver | B3: FY2027 | C3: FY2028 | D3: FY2029 | E3: FY2030 | F3: FY2031 | G3: FY2032 | H3: Source | I3: Reason | J3: Confidence
A4: Revenue segment 1: Large customers ($1M+ TTM) product revenue (customers_arpu)
A5: Customers | B5: 920 | C5: 1140 | D5: 1390 | E5: 1640 | F5: 1870 | G5: 2080 | H5: Q4 FY26 8-K Feb 25 2026: 733 large customers at FY26 end, +27% YoY. Q1 FY27 release May 27 2026: 779 large customers, +29% YoY. Net adds of ~157 in FY26 plus accelerating run-rate implies ~190 net adds in FY27. | I5: FY27 calibrated to management guide of $5,840M product revenue. Large-customer count growth slowing from 27% to ~26% as base expands. ARPU declines slightly as newer entrants to the $1M+ tier dilute the average; existing large customers still expand at NRR 125% but pace of $1M+ promotions adds lower-ARPU entrants. | J5: High
A6: ARPU | B6: 3.95 | C6: 3.8 | D6: 3.7 | E6: 3.65 | F6: 3.6 | G6: 3.55 | H6: Implied: large customers ~75% of product revenue (calibrated to FY26 product revenue $4,470M and total customers 13,328 with 733 large). $4,470M x 0.75 / 733 = $4.57M average. Large-customer ARPU declines as new $1M+ entrants drag the average down. Cross-checked vs FY27 guide $5,840M product revenue. | I6: FY27 calibrated to management guide of $5,840M product revenue. Large-customer count growth slowing from 27% to ~26% as base expands. ARPU declines slightly as newer entrants to the $1M+ tier dilute the average; existing large customers still expand at NRR 125% but pace of $1M+ promotions adds lower-ARPU entrants. | J6: High
A8: Revenue segment 2: Long-tail customers (sub-$1M TTM) product revenue (customers_arpu)
A9: Customers | B9: 14600 | C9: 16400 | D9: 18000 | E9: 19400 | F9: 20600 | G9: 21700 | H9: FY26 10-K: total customers 13,328 with 733 large = 12,595 long-tail. Net adds 2,332 in FY26 (740 in Q4 alone +40% YoY). FY27 net adds projected at ~2,000. Long-tail = 14,600 (total ~15,520 minus 920 large). | I9: ARPU expansion reflects existing long-tail cohorts consuming more (NRR 125% applies here too). | J9: Medium
A10: ARPU | B10: 0.151 | C10: 0.165 | D10: 0.175 | E10: 0.182 | F10: 0.187 | G10: 0.19 | H10: Calibrated to FY27 product revenue guide of $5,840M (Q1 FY27 release May 27 2026). Large-customer contribution $3,634M (920 x $3.95M); residual long-tail product revenue = $2,206M, implying ARPU of $151K. FY26 implied long-tail ARPU was ~$129K so this represents modest expansion from cohort maturation and AI workload adoption. | I10: ARPU expansion reflects existing long-tail cohorts consuming more (NRR 125% applies here too). | J10: Medium
A12: Revenue segment 3: Professional services and other revenue (customers_arpu)
A13: Customers | B13: 1 | C13: 1 | D13: 1 | E13: 1 | F13: 1 | G13: 1 | H13: Treated as one segment; using customer count = 1 and ARPU as total dollars in millions. | I13: Services revenue scales with implementation needs from new logos. Modest growth. | J13: Medium
A14: ARPU | B14: 215 | C14: 250 | D14: 285 | E14: 315 | F14: 340 | G14: 360 | H14: FY26 actual: $4,684M total revenue minus $4,470M product = $214M professional services and other. Management has indicated services revenue is not a profit center and grows roughly with product. | I14: Services revenue scales with implementation needs from new logos. Modest growth. | J14: Medium
A16: Cost lines
A17: Cost of revenue (percent_of_revenue) | B17: 0.32 | C17: 0.31 | D17: 0.3 | E17: 0.29 | F17: 0.285 | G17: 0.28 | H17: FY26 10-K: total gross margin 67%, so COGS = 33% of revenue. Mgmt guide of 75% non-GAAP product gross margin for FY27 implies GAAP product gross margin ~70%, with services drag holding total GAAP gross margin around 68%. | I17: Slight improvement from scale and hyperscaler cost negotiations. | J17: High
A18: Research and development (percent_of_revenue) | B18: 0.41 | C18: 0.37 | D18: 0.34 | E18: 0.31 | F18: 0.29 | G18: 0.27 | H18: FY26 10-K: R&D $1,980M / $4,684M = 42.3% of revenue. Management has committed to heavy AI investment. FY27 guide of 12.5% non-GAAP op margin implies disciplined opex on revenue base of $6.1B+ (total revenue). | I18: R&D ratio modestly improves as revenue scales faster than headcount additions, but AI investment keeps absolute dollars high. | J18: High
A19: Sales and marketing (percent_of_revenue) | B19: 0.4 | C19: 0.36 | D19: 0.33 | E19: 0.3 | F19: 0.28 | G19: 0.26 | H19: FY26 10-K: S&M roughly 41% of revenue (estimated from total opex of 98% minus R&D 42% minus G&A 9% minus restructuring 2% gives ~45% but adjusting for non-cash items closer to 41%). FY27 mgmt commentary indicates continued investment in enterprise sales motion. | I19: Modest S&M leverage as NRR-driven expansion lowers cost per dollar of revenue. | J19: Medium
A20: General and administrative (percent_of_revenue) | B20: 0.085 | C20: 0.075 | D20: 0.065 | E20: 0.06 | F20: 0.055 | G20: 0.05 | H20: FY26 10-K: G&A ~9% of revenue (estimated). Public company costs scale sub-linearly with revenue. | I20: G&A leverage from scale. | J20: High
A21: Interest income net of interest expense (fixed_amount) | B21: 195 | C21: 180 | D21: 160 | E21: 150 | F21: 145 | G21: 140 | H21: FY26 10-K: cash and investments ~$5B at FY26 end (down from $4.6B peak as buybacks and Observe acquisition consumed cash). Treasury yields ~4.0-4.3%. Less interest expense on convertible notes issued in 2025. | I21: Strong net interest income from cash hoard. | J21: High
A23: Taxes
A24: Cash tax rate | B24: 0.04 | C24: 0.04 | D24: 0.06 | E24: 0.1 | F24: 0.14 | G24: 0.18 | H24: FY26 10-K: $17.1M tax provision on -$1,329M loss. Heavy NOL carryforward shields cash taxes. Some international cash taxes apply. | I24: Minimal cash taxes due to GAAP losses and NOLs. | J24: High
A26: Working capital (days)
A27: DSO (days) | B27: 105 | C27: 105 | D27: 100 | E27: 100 | F27: 100 | G27: 100 | H27: FY26 implied DSO: AR ~$1,320M / $4,684M x 365 = 103 days. AP ~$60M / cost base implies ~15 days. SNOW has zero inventory. | I27: Stable working capital ratios. | J27: Medium
A28: DIO (days) | B28: 0 | C28: 0 | D28: 0 | E28: 0 | F28: 0 | G28: 0
A29: DPO (days) | B29: 18 | C29: 18 | D29: 18 | E29: 18 | F29: 18 | G29: 18
A31: Capex
A32: Maintenance capex | B32: 80 | C32: 100 | D32: 120 | E32: 140 | F32: 160 | G32: 180 | H32: FY26 capex ~$100M (CFO $1,222M minus FCF $1,120M = ~$102M). FY27 expected to step up as Snowflake builds Cortex AI inference infrastructure and acquires Observe-related compute. Mgmt 23% adj FCF margin guide implies ~$200M capex. | I32: Modest capex step-up for AI infrastructure. | J32: High
A33: Growth capex | B33: 120 | C33: 150 | D33: 170 | E33: 180 | F33: 180 | G33: 180
A35: Share count
A36: Starting diluted shares (millions) | B36: 337 | C36: 333 | D36: 327 | E36: 320 | F36: 313 | G36: 305 | H36: FY26 10-K: weighted avg diluted shares 337.5M. SBC dilution: $1.75B SBC / ~$200 share price = ~8.75M from new grants minus vesting net, plus equity awards from Observe; net ~20M. Buybacks: $232.9M in one quarter (Q3 FY26) implies $800M+ annualized. Repurchase price $200 average. FY27 non-GAAP diluted shares guide of 376M reflects different methodology (includes SBC dilutive effect under treasury method but excludes loss-per-share impact). | I36: Net dilution of ~16M shares per year before buybacks. | J36: Medium
A37: SBC dilution shares (millions) | B37: 20 | C37: 18 | D37: 17 | E37: 16 | F37: 15 | G37: 14
A38: Buyback dollars | B38: 800 | C38: 900 | D38: 1000 | E38: 1100 | F38: 1200 | G38: 1300
A39: Repurchase price per share | B39: 200 | C39: 220 | D39: 240 | E39: 260 | F39: 280 | G39: 300
A40: Issuance shares (millions) | B40: 0 | C40: 0 | D40: 0 | E40: 0 | F40: 0 | G40: 0
A42: Non-cash items (added back in CFO)
A43: Depreciation and amortization | B43: 230 | C43: 260 | D43: 290 | E43: 320 | F43: 350 | G43: 380 | H43: FY26 10-K: SBC $1.6B (Macrotrends), D&A approximately $200M including amortization of acquired intangibles from Observe. 'Other non-cash' captures the change in deferred revenue, which is a major tailwind: RPO grew from $6.88B to $9.77B in FY26 (+42%); current deferred revenue change typically contributes $400-700M to CFO annually. Also includes deferred tax movements and accretion. Calibrated against FY26 GAAP CFO of $1,222M reconciled from net loss of -$1,329M + SBC $1.6B + D&A ~$200M + other ~$751M working capital and deferred revenue tailwinds. | I43: Deferred revenue growth from Q4-weighted billings is the dominant CFO contributor beyond SBC; SNOW collects cash well in advance of revenue recognition. | J43: High
A44: Stock-based compensation | B44: 1750 | C44: 1850 | D44: 1900 | E44: 1950 | F44: 2000 | G44: 2050
A45: Other non-cash items | B45: 550 | C45: 500 | D45: 450 | E45: 400 | F45: 350 | G45: 300
A47: Historical base (prior-year working capital)
A48: Accounts receivable (prior year) | B48: 1320
A49: Inventory (prior year) | B49: 0
A50: Accounts payable (prior year) | B50: 60

Sheet Revenue Build
A1: Revenue Build
A3: Segment / driver | B3: FY2027 | C3: FY2028 | D3: FY2029 | E3: FY2030 | F3: FY2031 | G3: FY2032
A4: Large customers ($1M+ TTM) product revenue
A5: Customers | B5: =Assumptions!B5 -> 920 | C5: =Assumptions!C5 -> 1140 | D5: =Assumptions!D5 -> 1390 | E5: =Assumptions!E5 -> 1640 | F5: =Assumptions!F5 -> 1870 | G5: =Assumptions!G5 -> 2080
A6: ARPU | B6: =Assumptions!B6 -> 3.95 | C6: =Assumptions!C6 -> 3.8 | D6: =Assumptions!D6 -> 3.7 | E6: =Assumptions!E6 -> 3.65 | F6: =Assumptions!F6 -> 3.6 | G6: =Assumptions!G6 -> 3.55
A7: Segment revenue | B7: =B5*B6 -> 3634 | C7: =C5*C6 -> 4332 | D7: =D5*D6 -> 5143 | E7: =E5*E6 -> 5986 | F7: =F5*F6 -> 6732 | G7: =G5*G6 -> 7384
A9: Long-tail customers (sub-$1M TTM) product revenue
A10: Customers | B10: =Assumptions!B9 -> 14600 | C10: =Assumptions!C9 -> 16400 | D10: =Assumptions!D9 -> 18000 | E10: =Assumptions!E9 -> 19400 | F10: =Assumptions!F9 -> 20600 | G10: =Assumptions!G9 -> 21700
A11: ARPU | B11: =Assumptions!B10 -> 0.151 | C11: =Assumptions!C10 -> 0.165 | D11: =Assumptions!D10 -> 0.175 | E11: =Assumptions!E10 -> 0.182 | F11: =Assumptions!F10 -> 0.187 | G11: =Assumptions!G10 -> 0.19
A12: Segment revenue | B12: =B10*B11 -> 2204.6 | C12: =C10*C11 -> 2706 | D12: =D10*D11 -> 3150 | E12: =E10*E11 -> 3530.8 | F12: =F10*F11 -> 3852.2 | G12: =G10*G11 -> 4123
A14: Professional services and other revenue
A15: Customers | B15: =Assumptions!B13 -> 1 | C15: =Assumptions!C13 -> 1 | D15: =Assumptions!D13 -> 1 | E15: =Assumptions!E13 -> 1 | F15: =Assumptions!F13 -> 1 | G15: =Assumptions!G13 -> 1
A16: ARPU | B16: =Assumptions!B14 -> 215 | C16: =Assumptions!C14 -> 250 | D16: =Assumptions!D14 -> 285 | E16: =Assumptions!E14 -> 315 | F16: =Assumptions!F14 -> 340 | G16: =Assumptions!G14 -> 360
A17: Segment revenue | B17: =B15*B16 -> 215 | C17: =C15*C16 -> 250 | D17: =D15*D16 -> 285 | E17: =E15*E16 -> 315 | F17: =F15*F16 -> 340 | G17: =G15*G16 -> 360
A19: Total revenue | B19: =B7+B12+B17 -> 6053.6 | C19: =C7+C12+C17 -> 7288 | D19: =D7+D12+D17 -> 8578 | E19: =E7+E12+E17 -> 9831.8 | F19: =F7+F12+F17 -> 10924.2 | G19: =G7+G12+G17 -> 11867

Sheet P&L
A1: Income Statement
A3: Line | B3: FY2027 | C3: FY2028 | D3: FY2029 | E3: FY2030 | F3: FY2031 | G3: FY2032
A4: Revenue | B4: ='Revenue Build'!B19 -> 6053.6 | C4: ='Revenue Build'!C19 -> 7288 | D4: ='Revenue Build'!D19 -> 8578 | E4: ='Revenue Build'!E19 -> 9831.8 | F4: ='Revenue Build'!F19 -> 10924.2 | G4: ='Revenue Build'!G19 -> 11867
A5: Cost of revenue | B5: =B4*Assumptions!B17 -> 1937.152 | C5: =C4*Assumptions!C17 -> 2259.28 | D5: =D4*Assumptions!D17 -> 2573.4 | E5: =E4*Assumptions!E17 -> 2851.222 | F5: =F4*Assumptions!F17 -> 3113.397 | G5: =G4*Assumptions!G17 -> 3322.76
A6: Research and development | B6: =B4*Assumptions!B18 -> 2481.976 | C6: =C4*Assumptions!C18 -> 2696.56 | D6: =D4*Assumptions!D18 -> 2916.52 | E6: =E4*Assumptions!E18 -> 3047.858 | F6: =F4*Assumptions!F18 -> 3168.018 | G6: =G4*Assumptions!G18 -> 3204.09
A7: Sales and marketing | B7: =B4*Assumptions!B19 -> 2421.44 | C7: =C4*Assumptions!C19 -> 2623.68 | D7: =D4*Assumptions!D19 -> 2830.74 | E7: =E4*Assumptions!E19 -> 2949.54 | F7: =F4*Assumptions!F19 -> 3058.776 | G7: =G4*Assumptions!G19 -> 3085.42
A8: General and administrative | B8: =B4*Assumptions!B20 -> 514.556 | C8: =C4*Assumptions!C20 -> 546.6 | D8: =D4*Assumptions!D20 -> 557.57 | E8: =E4*Assumptions!E20 -> 589.908 | F8: =F4*Assumptions!F20 -> 600.831 | G8: =G4*Assumptions!G20 -> 593.35
A9: Interest income net of interest expense | B9: =Assumptions!B21 -> 195 | C9: =Assumptions!C21 -> 180 | D9: =Assumptions!D21 -> 160 | E9: =Assumptions!E21 -> 150 | F9: =Assumptions!F21 -> 145 | G9: =Assumptions!G21 -> 140
A10: Gross Profit | B10: =B4-(B5) -> 4116.448 | C10: =C4-(C5) -> 5028.72 | D10: =D4-(D5) -> 6004.6 | E10: =E4-(E5) -> 6980.578 | F10: =F4-(F5) -> 7810.803 | G10: =G4-(G5) -> 8544.24
A11: Gross margin | B11: =B10/B4 -> 0.68 | C11: =C10/C4 -> 0.69 | D11: =D10/D4 -> 0.7 | E11: =E10/E4 -> 0.71 | F11: =F10/F4 -> 0.715 | G11: =G10/G4 -> 0.72
A12: Total operating expenses | B12: =B6+B7+B8 -> 5417.972 | C12: =C6+C7+C8 -> 5866.84 | D12: =D6+D7+D8 -> 6304.83 | E12: =E6+E7+E8 -> 6587.306 | F12: =F6+F7+F8 -> 6827.625 | G12: =G6+G7+G8 -> 6882.86
A13: EBIT | B13: =B10-B12 -> -1301.524 | C13: =C10-C12 -> -838.12 | D13: =D10-D12 -> -300.23 | E13: =E10-E12 -> 393.272 | F13: =F10-F12 -> 983.178 | G13: =G10-G12 -> 1661.38
A14: EBIT margin | B14: =B13/B4 -> -0.215 | C14: =C13/C4 -> -0.115 | D14: =D13/D4 -> -0.035 | E14: =E13/E4 -> 0.04 | F14: =F13/F4 -> 0.09 | G14: =G13/G4 -> 0.14
A15: Interest income | B15: =B9 -> 195 | C15: =C9 -> 180 | D15: =D9 -> 160 | E15: =E9 -> 150 | F15: =F9 -> 145 | G15: =G9 -> 140
A16: Interest expense | B16: =0 -> 0 | C16: =0 -> 0 | D16: =0 -> 0 | E16: =0 -> 0 | F16: =0 -> 0 | G16: =0 -> 0
A17: Other income/(expense) | B17: =0 -> 0 | C17: =0 -> 0 | D17: =0 -> 0 | E17: =0 -> 0 | F17: =0 -> 0 | G17: =0 -> 0
A18: EBT | B18: =B13+B15-B16+B17 -> -1106.524 | C18: =C13+C15-C16+C17 -> -658.12 | D18: =D13+D15-D16+D17 -> -140.23 | E18: =E13+E15-E16+E17 -> 543.272 | F18: =F13+F15-F16+F17 -> 1128.178 | G18: =G13+G15-G16+G17 -> 1801.38
A19: Cash tax rate | B19: =Assumptions!B24 -> 0.04 | C19: =Assumptions!C24 -> 0.04 | D19: =Assumptions!D24 -> 0.06 | E19: =Assumptions!E24 -> 0.1 | F19: =Assumptions!F24 -> 0.14 | G19: =Assumptions!G24 -> 0.18
A20: Taxes | B20: =MAX(0,B18)*B19 -> 0 | C20: =MAX(0,C18)*C19 -> 0 | D20: =MAX(0,D18)*D19 -> 0 | E20: =MAX(0,E18)*E19 -> 54.3272 | F20: =MAX(0,F18)*F19 -> 157.94492 | G20: =MAX(0,G18)*G19 -> 324.2484
A21: Net income | B21: =B18-B20 -> -1106.524 | C21: =C18-C20 -> -658.12 | D21: =D18-D20 -> -140.23 | E21: =E18-E20 -> 488.9448 | F21: =F18-F20 -> 970.23308 | G21: =G18-G20 -> 1477.1316
A22: Starting diluted shares | B22: =Assumptions!B36 -> 337 | C22: =Assumptions!C36 -> 333 | D22: =Assumptions!D36 -> 327 | E22: =Assumptions!E36 -> 320 | F22: =Assumptions!F36 -> 313 | G22: =Assumptions!G36 -> 305
A23: + SBC dilution | B23: =Assumptions!B37 -> 20 | C23: =Assumptions!C37 -> 18 | D23: =Assumptions!D37 -> 17 | E23: =Assumptions!E37 -> 16 | F23: =Assumptions!F37 -> 15 | G23: =Assumptions!G37 -> 14
A24: + Issuance | B24: =Assumptions!B40 -> 0 | C24: =Assumptions!C40 -> 0 | D24: =Assumptions!D40 -> 0 | E24: =Assumptions!E40 -> 0 | F24: =Assumptions!F40 -> 0 | G24: =Assumptions!G40 -> 0
A25: - Buyback shares (dollars / price) | B25: =Assumptions!B38/Assumptions!B39 -> 4 | C25: =Assumptions!C38/Assumptions!C39 -> 4.0909091 | D25: =Assumptions!D38/Assumptions!D39 -> 4.1666667 | E25: =Assumptions!E38/Assumptions!E39 -> 4.2307692 | F25: =Assumptions!F38/Assumptions!F39 -> 4.2857143 | G25: =Assumptions!G38/Assumptions!G39 -> 4.3333333
A26: Diluted shares | B26: =B22+B23+B24-B25 -> 353 | C26: =C22+C23+C24-C25 -> 346.90909 | D26: =D22+D23+D24-D25 -> 339.83333 | E26: =E22+E23+E24-E25 -> 331.76923 | F26: =F22+F23+F24-F25 -> 323.71429 | G26: =G22+G23+G24-G25 -> 314.66667
A27: EPS | B27: =B21/B26 -> -3.1346289 | C27: =C21/C26 -> -1.8970964 | D27: =D21/D26 -> -0.41264345 | E27: =E21/E26 -> 1.4737497 | F27: =F21/F26 -> 2.9971896 | G27: =G21/G26 -> 4.6942742

Sheet Cash Flow
A1: Cash Flow Statement
A3: Line | B3: FY2027 | C3: FY2028 | D3: FY2029 | E3: FY2030 | F3: FY2031 | G3: FY2032
A4: Net income | B4: ='P&L'!B21 -> -1106.524 | C4: ='P&L'!C21 -> -658.12 | D4: ='P&L'!D21 -> -140.23 | E4: ='P&L'!E21 -> 488.9448 | F4: ='P&L'!F21 -> 970.23308 | G4: ='P&L'!G21 -> 1477.1316
A5: + D&A | B5: =Assumptions!B43 -> 230 | C5: =Assumptions!C43 -> 260 | D5: =Assumptions!D43 -> 290 | E5: =Assumptions!E43 -> 320 | F5: =Assumptions!F43 -> 350 | G5: =Assumptions!G43 -> 380
A6: + Stock-based compensation | B6: =Assumptions!B44 -> 1750 | C6: =Assumptions!C44 -> 1850 | D6: =Assumptions!D44 -> 1900 | E6: =Assumptions!E44 -> 1950 | F6: =Assumptions!F44 -> 2000 | G6: =Assumptions!G44 -> 2050
A7: + Other non-cash | B7: =Assumptions!B45 -> 550 | C7: =Assumptions!C45 -> 500 | D7: =Assumptions!D45 -> 450 | E7: =Assumptions!E45 -> 400 | F7: =Assumptions!F45 -> 350 | G7: =Assumptions!G45 -> 300
A8: DSO (days) | B8: =Assumptions!B27 -> 105 | C8: =Assumptions!C27 -> 105 | D8: =Assumptions!D27 -> 100 | E8: =Assumptions!E27 -> 100 | F8: =Assumptions!F27 -> 100 | G8: =Assumptions!G27 -> 100
A9: DIO (days) | B9: =Assumptions!B28 -> 0 | C9: =Assumptions!C28 -> 0 | D9: =Assumptions!D28 -> 0 | E9: =Assumptions!E28 -> 0 | F9: =Assumptions!F28 -> 0 | G9: =Assumptions!G28 -> 0
A10: DPO (days) | B10: =Assumptions!B29 -> 18 | C10: =Assumptions!C29 -> 18 | D10: =Assumptions!D29 -> 18 | E10: =Assumptions!E29 -> 18 | F10: =Assumptions!F29 -> 18 | G10: =Assumptions!G29 -> 18
A11: Accounts receivable (end of year) | B11: ='P&L'!B4*B8/365 -> 1741.4466 | C11: ='P&L'!C4*C8/365 -> 2096.5479 | D11: ='P&L'!D4*D8/365 -> 2350.137 | E11: ='P&L'!E4*E8/365 -> 2693.6438 | F11: ='P&L'!F4*F8/365 -> 2992.9315 | G11: ='P&L'!G4*G8/365 -> 3251.2329
A12: Inventory (end of year) | B12: =('P&L'!B4-'P&L'!B10)*B9/365 -> 0 | C12: =('P&L'!C4-'P&L'!C10)*C9/365 -> 0 | D12: =('P&L'!D4-'P&L'!D10)*D9/365 -> 0 | E12: =('P&L'!E4-'P&L'!E10)*E9/365 -> 0 | F12: =('P&L'!F4-'P&L'!F10)*F9/365 -> 0 | G12: =('P&L'!G4-'P&L'!G10)*G9/365 -> 0
A13: Accounts payable (end of year) | B13: =('P&L'!B4-'P&L'!B10)*B10/365 -> 95.530784 | C13: =('P&L'!C4-'P&L'!C10)*C10/365 -> 111.41655 | D13: =('P&L'!D4-'P&L'!D10)*D10/365 -> 126.9074 | E13: =('P&L'!E4-'P&L'!E10)*E10/365 -> 140.60821 | F13: =('P&L'!F4-'P&L'!F10)*F10/365 -> 153.53739 | G13: =('P&L'!G4-'P&L'!G10)*G10/365 -> 163.86214
A14: Net working capital | B14: =B11+B12-B13 -> 1645.9158 | C14: =C11+C12-C13 -> 1985.1314 | D14: =D11+D12-D13 -> 2223.2296 | E14: =E11+E12-E13 -> 2553.0356 | F14: =F11+F12-F13 -> 2839.3941 | G14: =G11+G12-G13 -> 3087.3707
A15: Prior year NWC | B15: =Assumptions!B48+Assumptions!B49-Assumptions!B50 -> 1260 | C15: =B14 -> 1645.9158 | D15: =C14 -> 1985.1314 | E15: =D14 -> 2223.2296 | F15: =E14 -> 2553.0356 | G15: =F14 -> 2839.3941
A16: Change in NWC | B16: =B14-B15 -> 385.91579 | C16: =C14-C15 -> 339.21561 | D16: =D14-D15 -> 238.09819 | E16: =E14-E15 -> 329.80604 | F16: =F14-F15 -> 286.35849 | G16: =G14-G15 -> 247.97662
A17: Cash flow from operations (CFO) | B17: =B4+B5+B6+B7-B16 -> 1037.5602 | C17: =C4+C5+C6+C7-C16 -> 1612.6644 | D17: =D4+D5+D6+D7-D16 -> 2261.6718 | E17: =E4+E5+E6+E7-E16 -> 2829.1388 | F17: =F4+F5+F6+F7-F16 -> 3383.8746 | G17: =G4+G5+G6+G7-G16 -> 3959.155
A18: Capex (maintenance + growth) | B18: =-(Assumptions!B32+Assumptions!B33) -> -200 | C18: =-(Assumptions!C32+Assumptions!C33) -> -250 | D18: =-(Assumptions!D32+Assumptions!D33) -> -290 | E18: =-(Assumptions!E32+Assumptions!E33) -> -320 | F18: =-(Assumptions!F32+Assumptions!F33) -> -340 | G18: =-(Assumptions!G32+Assumptions!G33) -> -360
A19: Free cash flow | B19: =B17+B18 -> 837.56021 | C19: =C17+C18 -> 1362.6644 | D19: =D17+D18 -> 1971.6718 | E19: =E17+E18 -> 2509.1388 | F19: =F17+F18 -> 3043.8746 | G19: =G17+G18 -> 3599.155
A20: FCF margin | B20: =B19/'P&L'!B4 -> 0.13835738 | C20: =C19/'P&L'!C4 -> 0.18697371 | D20: =D19/'P&L'!D4 -> 0.22985216 | E20: =E19/'P&L'!E4 -> 0.25520645 | F20: =F19/'P&L'!F4 -> 0.27863593 | G20: =G19/'P&L'!G4 -> 0.30329106
A21: shares | B21: 341 | C21: 341 | D21: 341 | E21: 341 | F21: 341 | G21: 341
A23: Year | B23: 1 | C23: 2 | D23: 3 | E23: 4 | F23: 5 | G23: 6
A24: FCF / Share | B24: =B19/B21 -> 2.4561883 | C24: =C19/C21 -> 3.9960833 | D24: =D19/D21 -> 5.7820288 | E24: =E19/E21 -> 7.3581782 | F24: =F19/F21 -> 8.9263184 | G24: =G19/G21 -> 10.554707
A25: Disc FCF | B25: =B24/(1+$B$29)^B23 -> 2.2742484 | C25: =C24/(1+$B$29)^C23 -> 3.4259973 | D25: =D24/(1+$B$29)^D23 -> 4.5899609 | E25: =E24/(1+$B$29)^E23 -> 5.4084806 | F25: =F24/(1+$B$29)^F23 -> 6.0751023 | G25: =G24/(1+$B$29)^G23 -> 6.6512556
A26: Terminal | G26: =(G24*(1+B30)/(B29-B30))/(1+B29)^G23 -> 113.07134
A27: Total disc CF | B27: =SUM(B25:B26) -> 2.2742484 | C27: =SUM(C25:C26) -> 3.4259973 | D27: =SUM(D25:D26) -> 4.5899609 | E27: =SUM(E25:E26) -> 5.4084806 | F27: =SUM(F25:F26) -> 6.0751023 | G27: =SUM(G25:G26) -> 119.7226
A29: Disc | B29: 0.08
A30: TGR | B30: 0.02
A31: NPV | B31: =SUM(B27:G27) -> 141.49639

Sheet Sensitivities
A1: Sensitivity Analysis (terminal year FY2032)
A3: Scenario | B3: EPS FY2032 | C3: EPS change vs base | D3: FCF FY2032 | E3: FCF change vs base | F3: Revenue FY2032
A4: Base case | B4: 4.6942742 | C4: 0 | D4: 3599.155 | E4: 0 | F4: 11867
A5: Research and development ratio up 20% | B5: 3.0243459 | C5: -1.6699283 | D5: 3073.6842 | E5: -525.47076 | F5: 11867
A6: Research and development ratio down 20% | B6: 6.3642024 | C6: 1.6699283 | D6: 4124.6257 | E6: 525.47076 | F6: 11867
A7: Sales and marketing ratio up 20% | B7: 3.0861951 | C7: -1.6080791 | D7: 3093.1461 | E7: -506.00888 | F7: 11867
A8: Sales and marketing ratio down 20% | B8: 6.3023532 | C8: 1.6080791 | D8: 4105.1639 | E8: 506.00888 | F8: 11867
A9: Segment 1 customers up 20% | B9: 5.2330558 | C9: 0.53878169 | D9: 3734.4342 | E9: 135.27922 | F9: 13343.8
A10: Segment 1 customers down 20% | B10: 4.1554925 | C10: -0.53878169 | D10: 3463.8758 | E10: -135.27922 | F10: 10390.2
A12: Note: Sensitivity values are computed by the engine, not by live formulas. Edit the Assumptions tab and re-run the engine to update.

Sheet Audit
A1: Assumption Audit
A3: Assumption | B3: Model line | C3: Fiscal year | D3: Value | E3: Source | F3: Reason | G3: Confidence | H3: Status
A4: Large customers ($1M+ TTM) product revenue revenue driver | B4: Revenue | C4: 2027 | D4: 3634 | F4: FY27 calibrated to management guide of $5,840M product revenue. Large-customer count growth slowing from 27% to ~26% as base expands. ARPU declines slightly as newer entrants to the $1M+ tier dilute the average; existing large customers still expand at NRR 125% but pace of $1M+ promotions adds lower-ARPU entrants. | G4: High | H4: MISSING_EVIDENCE
A5: Large customers ($1M+ TTM) product revenue revenue driver | B5: Revenue | C5: 2028 | D5: 4332 | F5: Customer count growth decelerates with scale. ARPU declines mildly because new $1M+ entrants enter near the floor. The combination still produces strong dollar growth from this segment. | G5: Medium | H5: MISSING_EVIDENCE
A6: Large customers ($1M+ TTM) product revenue revenue driver | B6: Revenue | C6: 2029 | D6: 5143 | F6: Continued large-customer expansion but at slower pace. ARPU continues to drift down as base broadens. | G6: Medium | H6: MISSING_EVIDENCE
A7: Large customers ($1M+ TTM) product revenue revenue driver | B7: Revenue | C7: 2030 | D7: 5986 | F7: Forbes Global 2000 penetration approaching 50% caps incremental large-customer adds. ARPU stabilizes as AI workloads add per-customer spend. | G7: Medium | H7: MISSING_EVIDENCE
A8: Large customers ($1M+ TTM) product revenue revenue driver | B8: Revenue | C8: 2031 | D8: 6732 | F8: Late-cycle deceleration; international expansion offsets some US saturation. | G8: Low | H8: MISSING_EVIDENCE
A9: Large customers ($1M+ TTM) product revenue revenue driver | B9: Revenue | C9: 2032 | D9: 7384 | F9: Trajectory consistent with mature platform SaaS at ~10% topline growth in large-customer dollar terms. | G9: Low | H9: MISSING_EVIDENCE
A10: Long-tail customers (sub-$1M TTM) product revenue revenue driver | B10: Revenue | C10: 2027 | D10: 2204.6 | F10: ARPU expansion reflects existing long-tail cohorts consuming more (NRR 125% applies here too). | G10: Medium | H10: MISSING_EVIDENCE
A11: Long-tail customers (sub-$1M TTM) product revenue revenue driver | B11: Revenue | C11: 2028 | D11: 2706 | F11: Slower net adds at scale; ARPU expansion sustains long-tail dollar growth. | G11: Medium | H11: MISSING_EVIDENCE
A12: Long-tail customers (sub-$1M TTM) product revenue revenue driver | B12: Revenue | C12: 2029 | D12: 3150 | F12: Continued mid-market penetration at slowing pace. | G12: Low | H12: MISSING_EVIDENCE
A13: Long-tail customers (sub-$1M TTM) product revenue revenue driver | B13: Revenue | C13: 2030 | D13: 3530.8 | F13: Late-stage mid-market saturation. | G13: Low | H13: MISSING_EVIDENCE
A14: Long-tail customers (sub-$1M TTM) product revenue revenue driver | B14: Revenue | C14: 2031 | D14: 3852.2 | F14: Long-tail growth normalizes. | G14: Low | H14: MISSING_EVIDENCE
A15: Long-tail customers (sub-$1M TTM) product revenue revenue driver | B15: Revenue | C15: 2032 | D15: 4123 | F15: Mature long-tail dynamics. | G15: Low | H15: MISSING_EVIDENCE
... A21: Professional services and other revenue revenue driver | B21: Revenue | C21: 2032 | D21: 360 | F21: Mature services scaling. | G21: Low | H21: MISSING_EVIDENCE
A22: Cost of revenue | B22: cogs | C22: 2027 | D22: 1937.152 | E22: FY26 10-K: total gross margin 67%, so COGS = 33% of revenue. Mgmt guide of 75% non-GAAP product gross margin for FY27 implies GAAP product gross margin ~70%, with services drag holding total GAAP gross margin around 68%. | F22: Slight improvement from scale and hyperscaler cost negotiations. | G22: High | H22: SUPPORTED
A23: Research and development | B23: opex | C23: 2027 | D23: 2481.976 | E23: FY26 10-K: R&D $1,980M / $4,684M = 42.3% of revenue. Management has committed to heavy AI investment. FY27 guide of 12.5% non-GAAP op margin implies disciplined opex on revenue base of $6.1B+ (total revenue). | F23: R&D ratio modestly improves as revenue scales faster than headcount additions, but AI investment keeps absolute dollars high. | G23: High | H23: SUPPORTED
A24: Sales and marketing | B24: opex | C24: 2027 | D24: 2421.44 | E24: FY26 10-K: S&M roughly 41% of revenue (estimated from total opex of 98% minus R&D 42% minus G&A 9% minus restructuring 2% gives ~45% but adjusting for non-cash items closer to 41%). FY27 mgmt commentary indicates continued investment in enterprise sales motion. | F24: Modest S&M leverage as NRR-driven expansion lowers cost per dollar of revenue. | G24: Medium | H24: SUPPORTED
A25: General and administrative | B25: opex | C25: 2027 | D25: 514.556 | E25: FY26 10-K: G&A ~9% of revenue (estimated). Public company costs scale sub-linearly with revenue. | F25: G&A leverage from scale. | G25: High | H25: SUPPORTED
A26: Interest income net of interest expense | B26: interest_income | C26: 2027 | D26: 195 | E26: FY26 10-K: cash and investments ~$5B at FY26 end (down from $4.6B peak as buybacks and Observe acquisition consumed cash). Treasury yields ~4.0-4.3%. Less interest expense on convertible notes issued in 2025. | F26: Strong net interest income from cash hoard. | G26: High | H26: SUPPORTED
A27: Cost of revenue | B27: cogs | C27: 2028 | D27: 2259.28 | E27: Run-rate improvement from FY27 guide; hyperscaler discount progression as volume increases. | F27: Continued modest gross margin expansion. | G27: Medium | H27: SUPPORTED
A28: Research and development | B28: opex | C28: 2028 | D28: 2696.56 | E28: Operating leverage on R&D as revenue compounds; mgmt non-GAAP op margin target of 20% by FY29 implies aggressive opex leverage. | F28: Scale benefits on R&D ratio. | G28: Medium | H28: SUPPORTED
A29: Sales and marketing | B29: opex | C29: 2028 | D29: 2623.68 | E29: S&M leverage as installed-base expansion (NRR 120%+) requires less new-logo spend per dollar of revenue growth. | F29: S&M efficiency improves with platform stickiness. | G29: Medium | H29: SUPPORTED
A30: General and administrative | B30: opex | C30: 2028 | D30: 546.6 | E30: Continued G&A leverage. | F30: G&A ratio compresses with scale. | G30: Medium | H30: SUPPORTED
A31: Interest income net of interest expense | B31: interest_income | C31: 2028 | D31: 180 | E31: Cash declines from continued buybacks; rates assumed to drift lower. | F31: Net interest income drifts down with rates and cash drawdown. | G31: Medium | H31: SUPPORTED
A32: Cost of revenue | B32: cogs | C32: 2029 | D32: 2573.4 | E32: Continued scale benefits; AI workload pricing potentially expands margins as Snowflake captures premium for governed AI inference. | F32: Margin expansion plateau approaches. | G32: Medium | H32: SUPPORTED
A33: Research and development | B33: opex | C33: 2029 | D33: 2916.52 | E33: Operating leverage continues; FY29 informal mgmt target of 20% non-GAAP op margin requires meaningful R&D ratio compression. | F33: Material R&D leverage from revenue scale. | G33: Medium | H33: SUPPORTED
... A51: Interest income net of interest expense | B51: interest_income | C51: 2032 | D51: 140 | E51: Steady-state assumption. | F51: Mature treasury operations. | G51: Low | H51: SUPPORTED

Sheet Validation
A1: Validation
A3: Severity | B3: Location | C3: Issue | D3: Fix
A4: PASS | B4: No validation issues found.
