Workbook

Sheet Assumptions
A1: SoFi Technologies, Inc. | C1: Hist | D1: Hist | E1: Hist | F1: Proj | G1: Proj | H1: Proj | I1: Proj | J1: Proj
A2: $ USD (amounts in $mm) | C2: 2023 | D2: 2024 | E2: 2025 | F2: 2026 | G2: 2027 | H2: 2028 | I2: 2029 | J2: 2030
A4: Net Interest Income Drivers (Volume x Rate)
A5: Interest-Earning Assets
B6: Avg interest-earning assets ($mm) | C6: 21447 | D6: 29587 | E6: 37913 | F6: =ROUND((E82+F82)/2+(E86+F86)/2+3000,0) -> 48502 | G6: =ROUND((F82+G82)/2+(F86+G86)/2+3000,0) -> 57833 | H6: =ROUND((G82+H82)/2+(G86+H86)/2+3000,0) -> 66570 | I6: =ROUND((H82+I82)/2+(H86+I86)/2+3000,0) -> 75247 | J6: =ROUND((I82+J82)/2+(I86+J86)/2+3000,0) -> 83533 | K6: Avg loans + avg securities + est. cash deposits at banks (~$3B)
B7: Avg yield on interest-earning assets | C7: 0.0956 | D7: 0.0949 | E7: 0.089 | F7: 0.0855 | G7: 0.0825 | H7: 0.08 | I7: 0.078 | J7: 0.0765 | K7: Declining: rate cuts, mix shift to lower-yield securities
B8: Total interest income ($mm) | C8: =ROUND(C6*C7,0) -> 2050 | D8: =ROUND(D6*D7,0) -> 2808 | E8: =ROUND(E6*E7,0) -> 3374 | F8: =F6*F7 -> 4146.921 | G8: =G6*G7 -> 4771.2225 | H8: =H6*H7 -> 5325.6 | I8: =I6*I7 -> 5869.266 | J8: =J6*J7 -> 6390.2745 | K8: avg iea x avg yield
A10: Interest-Bearing Liabilities
B11: Avg interest-bearing deposits ($mm) | C11: 12655 | D11: 22614 | E11: 29861 | F11: =ROUND((E77+F77)/2,0) -> 43133 | G11: =ROUND((F77+G77)/2,0) -> 53632 | H11: =ROUND((G77+H77)/2,0) -> 62902 | I11: =ROUND((H77+I77)/2,0) -> 71433 | J11: =ROUND((I77+J77)/2,0) -> 79341 | K11: SoFi Money growth, member adds, direct deposit penetration
B12: Avg cost of deposits | C12: 0.0401 | D12: 0.0411 | E12: 0.034 | F12: 0.031 | G12: 0.029 | H12: 0.0275 | I12: 0.026 | J12: 0.025 | K12: Declining: Fed cuts, sticky checking balances at 0% APY
B13: Deposit interest expense ($mm) | C13: =ROUND(C11*C12,0) -> 507 | D13: =ROUND(D11*D12,0) -> 929 | E13: =ROUND(E11*E12,0) -> 1015 | F13: =F11*F12 -> 1337.123 | G13: =G11*G12 -> 1555.328 | H13: =H11*H12 -> 1729.805 | I13: =I11*I12 -> 1857.258 | J13: =J11*J12 -> 1983.525
B14: Avg debt ($mm) | C14: 5533 | D14: 3527 | E14: 3488 | F14: =ROUND((E94+F94)/2,0) -> 1665 | G14: =ROUND((F94+G94)/2,0) -> 1415 | H14: =ROUND((G94+H94)/2,0) -> 1240 | I14: =ROUND((H94+I94)/2,0) -> 1115 | J14: =ROUND((I94+J94)/2,0) -> 1040 | K14: Declining: paying down warehouse/securitization, replacing with deposits
B15: Avg cost of debt | C15: 0.0509 | D15: 0.0457 | E15: 0.0408 | F15: 0.038 | G15: 0.036 | H15: 0.035 | I15: 0.034 | J15: 0.033
B16: Debt interest expense ($mm) | C16: =ROUND(C14*C15,0) -> 282 | D16: =ROUND(D14*D15,0) -> 161 | E16: =ROUND(E14*E15,0) -> 142 | F16: =F14*F15 -> 63.27 | G16: =G14*G15 -> 50.94 | H16: =H14*H15 -> 43.4 | I16: =I14*I15 -> 37.91 | J16: =J14*J15 -> 34.32
B17: Total interest expense ($mm) | C17: =C13+C16 -> 789 | D17: =D13+D16 -> 1090 | E17: =E13+E16 -> 1157 | F17: =F13+F16 -> 1400.393 | G17: =G13+G16 -> 1606.268 | H17: =H13+H16 -> 1773.205 | I17: =I13+I16 -> 1895.168 | J17: =J13+J16 -> 2017.845
B19: Net interest income ($mm) | C19: =C8-C17 -> 1261 | D19: =D8-D17 -> 1718 | E19: =E8-E17 -> 2217 | F19: =F8-F17 -> 2746.528 | G19: =G8-G17 -> 3164.9545 | H19: =H8-H17 -> 3552.395 | I19: =I8-I17 -> 3974.098 | J19: =J8-J17 -> 4372.4295
B20: Net interest margin (NIM) | C20: =C19/C6 -> 0.058796102 | D20: =D19/D6 -> 0.058066043 | E20: =E19/E6 -> 0.058475984 | F20: =F19/F6 -> 0.056627108 | G20: =G19/G6 -> 0.054725753 | H20: =H19/H6 -> 0.053363302 | I20: =I19/I6 -> 0.052814039 | J20: =J19/J6 -> 0.052343738 | K20: nii / avg iea
A22: Noninterest Income Drivers (Activity-Based)
B23: Total members (mm) | C23: 7.5 | D23: 10.1 | E23: 13.6 | F23: 17 | G23: 20.5 | H23: 24 | I23: 27.5 | J23: 31 | K23: Member growth decelerates from 35% toward 13%
B24: Products per member | C24: 1.46 | D24: 1.46 | E24: 1.49 | F24: 1.52 | G24: 1.54 | H24: 1.56 | I24: 1.57 | J24: 1.58 | K24: Cross-sell improving via FSPL strategy
B25: Total products (mm) | C25: =C23*C24 -> 10.95 | D25: =D23*D24 -> 14.746 | E25: =E23*E24 -> 20.264 | F25: =F23*F24 -> 25.84 | G25: =G23*G24 -> 31.57 | H25: =H23*H24 -> 37.44 | I25: =I23*I24 -> 43.175 | J25: =J23*J24 -> 48.98
B27: Loan origination volume ($mm) | C27: 14500 | D27: 17700 | E27: 27700 | F27: 32000 | G27: 36000 | H27: 40000 | I27: 44000 | J27: 47000 | K27: 57% growth in 2025. Decelerating.
B28: Origination fee / gain-on-sale rate (bps of volume) | C28: 282 | D28: 157 | E28: 88 | F28: 66 | G28: 51 | H28: 41 | I28: 34 | J28: 30 | K28: Declining: more LPB (fee) vs balance sheet (gain-on-sale)
B29: Loan origination, sales, securitizations & servicing ($mm) | C29: =ROUND(C27*C28/10000,0) -> 409 | D29: =ROUND(D27*D28/10000,0) -> 278 | E29: =ROUND(E27*E28/10000,0) -> 244 | F29: =ROUND(F27*F28/10000,0) -> 211 | G29: =ROUND(G27*G28/10000,0) -> 184 | H29: =ROUND(H27*H28/10000,0) -> 164 | I29: =ROUND(I27*I28/10000,0) -> 150 | J29: =ROUND(J27*J28/10000,0) -> 141 | K29: volume x bps / 10000
B31: LPB origination volume on behalf of 3rd parties ($mm) | C31: 600 | D31: 3800 | E31: 11000 | F31: 14000 | G31: 16500 | H31: 18500 | I31: 20000 | J31: 21500 | K31: $11B in 2025. Growth decelerates as penetration matures
B32: LPB fee rate (bps) | C32: 567 | D32: 373 | E32: 524 | F32: 536 | G32: 533 | H32: 535 | I32: 540 | J32: 540 | K32: Stabilizing around ~535 bps ($52 per loan avg fee)
B33: Loan platform fees ($mm) | C33: =ROUND(C31*C32/10000,0) -> 34 | D33: =ROUND(D31*D32/10000,0) -> 142 | E33: =ROUND(E31*E32/10000,0) -> 576 | F33: =ROUND(F31*F32/10000,0) -> 750 | G33: =ROUND(G31*G32/10000,0) -> 879 | H33: =ROUND(H31*H32/10000,0) -> 990 | I33: =ROUND(I31*I32/10000,0) -> 1080 | J33: =ROUND(J31*J32/10000,0) -> 1161 | K33: lpb volume x fee rate / 10000
B35: Technology Platform enabled accounts (mm) | C35: 151 | D35: 160 | E35: 128 | F35: 135 | G35: 145 | H35: 158 | I35: 172 | J35: 188 | K35: Post-Chime trough. Rebuilding via brand partnerships
B36: Revenue per enabled account ($) | C36: 2.15 | D36: 2.47 | E36: 3.52 | F36: 2.96 | G36: 3.07 | H36: 3.13 | I36: 3.2 | J36: 3.24 | K36: Declining from 2025 peak (Chime termination fee inflated)
B37: Technology products and solutions ($mm) | C37: =ROUND(C35*C36,0) -> 325 | D37: =ROUND(D35*D36,0) -> 395 | E37: =ROUND(E35*E36,0) -> 451 | F37: =ROUND(F35*F36,0) -> 400 | G37: =ROUND(G35*G36,0) -> 445 | H37: =ROUND(H35*H36,0) -> 495 | I37: =ROUND(I35*I36,0) -> 550 | J37: =ROUND(J35*J36,0) -> 609 | K37: accounts x rev/account
B39: SoFi Money + Credit Card active accounts (mm) | C39: 4 | D39: 5.8 | E39: 8.5 | F39: 11 | G39: 13.5 | H39: 16 | I39: 18.5 | J39: 21 | K39: Interchange driven by card/debit active accounts
B40: Revenue per active account ($) | C40: 32 | D40: 32.4 | E40: 25.3 | F40: 24.1 | G40: 23.7 | H40: 23.4 | I40: 23.2 | J40: 23.1 | K40: Interchange, brokerage, referral fees per active account
B41: Other noninterest income ($mm) | C41: =ROUND(C39*C40,0) -> 128 | D41: =ROUND(D39*D40,0) -> 188 | E41: =ROUND(E39*E40,0) -> 215 | F41: =ROUND(F39*F40,0) -> 265 | G41: =ROUND(G39*G40,0) -> 320 | H41: =ROUND(H39*H40,0) -> 374 | I41: =ROUND(I39*I40,0) -> 429 | J41: =ROUND(J39*J40,0) -> 485 | K41: active accounts (mm) x revenue per account ($))))
B43: Total noninterest income ($mm) | C43: =C29+C37+C33+C41 -> 896 | D43: =D29+D37+D33+D41 -> 1003 | E43: =E29+E37+E33+E41 -> 1486 | F43: =F29+F37+F33+F41 -> 1626 | G43: =G29+G37+G33+G41 -> 1828 | H43: =H29+H37+H33+H41 -> 2023 | I43: =I29+I37+I33+I41 -> 2209 | J43: =J29+J37+J33+J41 -> 2396
B44: Total net revenue ($mm) | C44: =C19+C43 -> 2157 | D44: =D19+D43 -> 2721 | E44: =E19+E43 -> 3703 | F44: =F19+F43 -> 4372.528 | G44: =G19+G43 -> 4992.9545 | H44: =H19+H43 -> 5575.395 | I44: =I19+I43 -> 6183.098 | J44: =J19+J43 -> 6768.4295
A46: Provision for Credit Losses
B47: Total loans at amortized cost ($mm) | C47: =ROUND(C82*C85,0) -> 826 | D47: =ROUND(D82*D85,0) -> 1239 | E47: =ROUND(E82*E85,0) -> 1522 | F47: =ROUND(F82*F85,0) -> 1892 | G47: =ROUND(G82*G85,0) -> 2227 | H47: =ROUND(H82*H85,0) -> 2553 | I47: =ROUND(I82*I85,0) -> 2887 | J47: =ROUND(J82*J85,0) -> 3185 | K47: Only HFI-AC loans carry ACL. Growing with credit card + commercial
B48: NCO rate on AC loans | C48: 0.049 | D48: 0.032 | E48: 0.017 | F48: 0.02 | G48: 0.02 | H48: 0.02 | I48: 0.02 | J48: 0.02 | K48: Normalizing at ~2% after credit card tightening in 2024-25
B49: Provision for credit losses ($mm) | C49: =ROUND(C47*C48,0) -> 40 | D49: =ROUND(D47*D48,0) -> 40 | E49: =ROUND(E47*E48,0) -> 26 | F49: =ROUND(F47*F48,0) -> 38 | G49: =ROUND(G47*G48,0) -> 45 | H49: =ROUND(H47*H48,0) -> 51 | I49: =ROUND(I47*I48,0) -> 58 | J49: =ROUND(J47*J48,0) -> 64 | K49: ac loans x nco RATE(simplified)
A51: Noninterest Expense Drivers (Unit Economics)
B52: Total employees | C52: 6300 | D52: 7000 | E52: 8100 | F52: 9200 | G52: 10200 | H52: 11100 | I52: 11900 | J52: 12600 | K52: Growing with business complexity. ~11% CAGR decelerating
B53: Avg comp + benefits per employee ($K) | C53: 126 | D53: 126 | E53: 134 | F53: 139 | G53: 143 | H53: 147 | I53: 151 | J53: 155 | K53: ~3% annual inflation on per-head cost
B54: Total compensation & benefits ($mm) | C54: =ROUND(C52*C53/1000,0) -> 794 | D54: =ROUND(D52*D53/1000,0) -> 882 | E54: =ROUND(E52*E53/1000,0) -> 1085 | F54: =ROUND(F52*F53/1000,0) -> 1279 | G54: =ROUND(G52*G53/1000,0) -> 1459 | H54: =ROUND(H52*H53/1000,0) -> 1632 | I54: =ROUND(I52*I53/1000,0) -> 1797 | J54: =ROUND(J52*J53/1000,0) -> 1953 | K54: employees x avg comp / 1000
B55: Marketing spend per new member acquired ($) | C55: 60 | D55: 56 | E55: 76 | F55: 72 | G55: 68 | H55: 65 | I55: 63 | J55: 62 | K55: CAC. Elevated in 2025 for brand. Normalizing.
B56: New members added (mm) | C56: 1.7 | D56: =D23-C23 -> 2.6 | E56: =E23-D23 -> 3.5 | F56: =F23-E23 -> 3.4 | G56: =G23-F23 -> 3.5 | H56: =H23-G23 -> 3.5 | I56: =I23-H23 -> 3.5 | J56: =J23-I23 -> 3.5 | K56: current members - prior members
B57: Total marketing spend ($mm) | C57: =ROUND(C56*C55,0) -> 102 | D57: =ROUND(D56*D55,0) -> 146 | E57: =ROUND(E56*E55,0) -> 266 | F57: =ROUND(F56*F55,0) -> 245 | G57: =ROUND(G56*G55,0) -> 238 | H57: =ROUND(H56*H55,0) -> 228 | I57: =ROUND(I56*I55,0) -> 221 | J57: =ROUND(J56*J55,0) -> 217 | K57: new members x cac
B58: Brand & other S&M ($mm) | C58: 617 | D58: 650 | E58: 829 | F58: 900 | G58: 960 | H58: 1010 | I58: 1050 | J58: 1085 | K58: Stadium naming, national campaigns. Growing but decelerating.
B59: Total sales & marketing ($mm) | C59: =C57+C58 -> 719 | D59: =D57+D58 -> 796 | E59: =E57+E58 -> 1095 | F59: =F57+F58 -> 1145 | G59: =G57+G58 -> 1198 | H59: =H57+H58 -> 1238 | I59: =I57+I58 -> 1271 | J59: =J57+J58 -> 1302 | K59: direct acquisition + brand/other s&m
B60: Processing cost per product ($) | C60: 18.5 | D60: 16.5 | E60: 15.5 | F60: 14.5 | G60: 13.8 | H60: 13.2 | I60: 12.7 | J60: 12.3 | K60: Cost of ops per product. Declining with scale.
B61: Cost of operations ($mm) | C61: =ROUND(C25*C60,0) -> 203 | D61: =ROUND(D25*D60,0) -> 243 | E61: =ROUND(E25*E60,0) -> 314 | F61: =ROUND(F25*F60,0) -> 375 | G61: =ROUND(G25*G60,0) -> 436 | H61: =ROUND(H25*H60,0) -> 494 | I61: =ROUND(I25*I60,0) -> 548 | J61: =ROUND(J25*J60,0) -> 602 | K61: total products (mm) x processing cost/product
B62: Compliance, legal, infrastructure ($mm) | C62: 417 | D62: 434 | E62: 490 | F62: 520 | G62: 545 | H62: 570 | I62: 595 | J62: 620 | K62: Fixed cost base. Growing with regulatory complexity.
B63: Total G&A ($mm) | C63: =C62+ROUND(C54*0.15,0) -> 536 | D63: =D62+ROUND(D54*0.15,0) -> 566 | E63: =E62+ROUND(E54*0.15,0) -> 653 | F63: =F62+ROUND(F54*0.15,0) -> 712 | G63: =G62+ROUND(G54*0.15,0) -> 764 | H63: =H62+ROUND(H54*0.15,0) -> 815 | I63: =I62+ROUND(I54*0.15,0) -> 865 | J63: =J62+ROUND(J54*0.15,0) -> 913 | K63: compliance/infra + 15% of comp (g&a headcount allocation)
B64: Tech & product development ($mm) | C64: =ROUND(C54*0.3,0)+C89 -> 439 | D64: =ROUND(D54*0.3,0)+D89 -> 468 | E64: =ROUND(E54*0.3,0)+E89 -> 560 | F64: =ROUND(F54*0.3,0)+F89 -> 644 | G64: =ROUND(G54*0.3,0)+G89 -> 728 | H64: =ROUND(H54*0.3,0)+H89 -> 805 | I64: =ROUND(I54*0.3,0)+I89 -> 879 | J64: =ROUND(J54*0.3,0)+J89 -> 951 | K64: 30% of comp (eng allocation) + d&a (software amortization)
B65: Goodwill impairment ($mm) | C65: 247 | D65: 0 | E65: 0 | F65: 0 | G65: 0 | H65: 0 | I65: 0 | J65: 0
B66: Total noninterest expense ($mm) | C66: =C64+C59+C61+C63+C65 -> 2144 | D66: =D64+D59+D61+D63+D65 -> 2073 | E66: =E64+E59+E61+E63+E65 -> 2622 | F66: =F64+F59+F61+F63+F65 -> 2876 | G66: =G64+G59+G61+G63+G65 -> 3126 | H66: =H64+H59+H61+H63+H65 -> 3352 | I66: =I64+I59+I61+I63+I65 -> 3563 | J66: =J64+J59+J61+J63+J65 -> 3768 | K66: tech + s&m + cost of ops + g&a + impairment
B67: Implied efficiency ratio | C67: =C66/C44 -> 0.99397311 | D67: =D66/D44 -> 0.76185226 | E67: =E66/E44 -> 0.70807453 | F67: =F66/F44 -> 0.65774307 | G67: =G66/G44 -> 0.62608221 | H67: =H66/H44 -> 0.60121301 | I67: =I66/I44 -> 0.57624835 | J67: =J66/J44 -> 0.55670226 | K67: Total opex / total revenue
B68: Revenue per employee ($K) | C68: =ROUND(C44/C52*1000,0) -> 342 | D68: =ROUND(D44/D52*1000,0) -> 389 | E68: =ROUND(E44/E52*1000,0) -> 457 | F68: =ROUND(F44/F52*1000,0) -> 475 | G68: =ROUND(G44/G52*1000,0) -> 490 | H68: =ROUND(H44/H52*1000,0) -> 502 | I68: =ROUND(I44/I52*1000,0) -> 520 | J68: =ROUND(J44/J52*1000,0) -> 537 | K68: Productivity metric
B69: Opex per member ($) | C69: =ROUND(C66/C23,0) -> 286 | D69: =ROUND(D66/D23,0) -> 205 | E69: =ROUND(E66/E23,0) -> 193 | F69: =ROUND(F66/F23,0) -> 169 | G69: =ROUND(G66/G23,0) -> 152 | H69: =ROUND(H66/H23,0) -> 140 | I69: =ROUND(I66/I23,0) -> 130 | J69: =ROUND(J66/J23,0) -> 122 | K69: Declining with member growth
A71: Income Taxes & Shares
B72: Effective tax rate | C72: -0.001 | D72: -1.137 | E72: 0.085 | F72: 0.22 | G72: 0.23 | H72: 0.24 | I72: 0.25 | J72: 0.25 | K72: 2024 distorted by DTA release. Normalizing to 22-25%
B73: Diluted WASO (mm) | C73: 945 | D73: 1101.4 | E73: 1251.8 | F73: 1290 | G73: 1330 | H73: 1370 | I73: 1410 | J73: 1450 | K73: SBC dilution ~3% annually. No buyback assumed.
A75: Balance Sheet Drivers
A76: Assets
B77: End-of-period deposits ($mm) | C77: =ROUND(C23*C78,0) -> 18623 | D77: =ROUND(D23*D78,0) -> 25977 | E77: =ROUND(E23*E78,0) -> 37509 | F77: =ROUND(F23*F78,0) -> 48756 | G77: =ROUND(G23*G78,0) -> 58507 | H77: =ROUND(H23*H78,0) -> 67296 | I77: =ROUND(I23*I78,0) -> 75570 | J77: =ROUND(J23*J78,0) -> 83111 | K77: members (mm) x deposits per member
B78: Deposits per member ($) | C78: 2483 | D78: 2572 | E78: 2758 | F78: 2868 | G78: 2854 | H78: 2804 | I78: 2748 | J78: 2681 | K78: Plateaus as new lower-balance members dilute avg
B79: On-balance-sheet originations ($mm) | E79: 16700 | F79: =F27-F31 -> 18000 | G79: =G27-G31 -> 19500 | H79: =H27-H31 -> 21500 | I79: =I27-I31 -> 24000 | J79: =J27-J31 -> 25500 | K79: total originations - lpb originations (off-bs)
B80: Loan principal runoff rate (% of beg balance) | E80: 0.225 | F80: 0.23 | G80: 0.235 | H80: 0.24 | I80: 0.245 | J80: 0.25 | K80: Paydowns, refinancings, sales, charge-offs. Rising with maturity.
B81: Beginning loans ($mm) | E81: 27528 | F81: =E82 -> 38038 | G81: =F82 -> 47289 | H81: =G82 -> 55676 | I81: =H82 -> 63814 | J81: =I82 -> 72180
B82: Ending total loans ($mm) | C82: 22958 | D82: 27528 | E82: 38038 | F82: =F81+F79-ROUND(F81*F80,0) -> 47289 | G82: =G81+G79-ROUND(G81*G80,0) -> 55676 | H82: =H81+H79-ROUND(H81*H80,0) -> 63814 | I82: =I81+I79-ROUND(I81*I80,0) -> 72180 | J82: =J81+J79-ROUND(J81*J80,0) -> 79635 | K82: beg loans + on-bs originations - runoff
B83: Loans HFS % of total | C83: 0.671 | D83: 0.642 | E83: 0.601 | F83: 0.58 | G83: 0.56 | H83: 0.545 | I83: 0.53 | J83: 0.52 | K83: Declining: shifting more to HFI for NII
B84: Loans HFI FV % of total | C84: 0.293 | D84: 0.312 | E84: 0.359 | F84: 0.38 | G84: 0.4 | H84: 0.415 | I84: 0.43 | J84: 0.44 | K84: Growing: personal/student loans held longer
B85: Loans HFI AC % of total | C85: 0.036 | D85: 0.045 | E85: 0.04 | F85: 0.04 | G85: 0.04 | H85: 0.04 | I85: 0.04 | J85: 0.04 | K85: Credit card + commercial. Stable share.
B86: Investment securities ($mm) | C86: 702 | D86: 1896 | E86: 2576 | F86: 3100 | G86: 3600 | H86: 4050 | I86: 4450 | J86: 4800 | K86: Deploying excess liquidity into AFS securities
B87: Servicing rights ($mm) | C87: 180 | D87: 342 | E87: 378 | F87: 420 | G87: 465 | H87: 510 | I87: 555 | J87: 600 | K87: Growing with LPB volume (servicing retained)
B88: CAPEX ($mm) | C88: 121 | D88: 163 | E88: 251 | F88: 280 | G88: 300 | H88: 315 | I88: 330 | J88: 345 | K88: Tech platform, office buildout, Galileo/Technisys
B89: D&A ($mm) | C89: 201 | D89: 203 | E89: 234 | F89: 260 | G89: 290 | H89: 315 | I89: 340 | J89: 365 | K89: Growing with cumulative capex. Software ~3yr amort.
B90: Goodwill ($mm) | C90: 1394 | D90: 1394 | E90: 1394 | F90: 1394 | G90: 1394 | H90: 1394 | I90: 1394 | J90: 1394 | K90: Galileo + Technisys. No impairment assumed.
B91: Intangible assets ($mm) | C91: 364 | D91: 298 | E91: 232 | F91: 170 | G91: 115 | H91: 70 | I91: 35 | J91: 10 | K91: Amortizing Technisys/Galileo acquired intangibles
B92: Restricted cash ($mm) | C92: 531 | D92: 171 | E92: 427 | F92: 350 | G92: 350 | H92: 350 | I92: 350 | J92: 350
A93: Liabilities
B94: Debt ending balance ($mm) | C94: 5233 | D94: 3093 | E94: 1815 | F94: =E94+F95 -> 1515 | G94: =F94+G95 -> 1315 | H94: =G94+H95 -> 1165 | I94: =H94+I95 -> 1065 | J94: =I94+J95 -> 1015 | K94: Continued paydown. Deposits replacing warehouse debt
B95: Debt repayment ($mm) | C95: -593 | D95: -2985 | E95: -1278 | F95: -300 | G95: -200 | H95: -150 | I95: -100 | J95: -50 | K95: Convertibles retired. Remaining is term/revolver
A97: Equity
B98: SBC expense ($mm) | C98: 271 | D98: 246 | E98: 262 | F98: 285 | G98: 310 | H98: 335 | I98: 360 | J98: 385 | K98: Growing with headcount. ~7-8% of revenue.
B99: Dividend payout % | C99: 0 | D99: 0 | E99: 0 | F99: 0 | G99: 0 | H99: 0 | I99: 0 | J99: 0 | K99: No dividend expected through 2030.
B100: Operating lease ROU assets ($mm) | C100: 90 | D100: 81 | E100: 94 | F100: 90 | G100: 85 | H100: 80 | I100: 75 | J100: 70 | K100: General operating lease commitments
B101: Other assets ($mm) | C101: 554 | D101: 1715 | E101: 2177 | F101: 2500 | G101: 2850 | H101: 3200 | I101: 3550 | J101: 3900 | K101: DTA + other. Growing with deferred tax asset utilization
B102: AP, accruals & other liabilities ($mm) | C102: 550 | D102: 557 | E102: 744 | F102: 850 | G102: 960 | H102: 1070 | I102: 1180 | J102: 1290
B103: Operating lease liabilities ($mm) | C103: 109 | D103: 97 | E103: 106 | F103: 100 | G103: 95 | H103: 90 | I103: 85 | J103: 80
B104: APIC ($mm) | C104: 7040 | D104: 7839 | E104: 11303 | F104: =E104+F98 -> 11588 | G104: =F104+G98 -> 11898 | H104: =G104+H98 -> 12233 | I104: =H104+I98 -> 12593 | J104: =I104+J98 -> 12978 | K104: Prior APIC + SBC expense (simplified)
B105: AOCI ($mm) | C105: -1 | D105: -8 | E105: 11 | F105: 11 | G105: 11 | H105: 11 | I105: 11 | J105: 11

Sheet Revenue NII Buildout
A1: SoFi Technologies, Inc. | C1: Hist | D1: Hist | E1: Hist | F1: Proj | G1: Proj | H1: Proj | I1: Proj | J1: Proj
A2: $ USD (amounts in $mm) | C2: 2023 | D2: 2024 | E2: 2025 | F2: 2026 | G2: 2027 | H2: 2028 | I2: 2029 | J2: 2030
A4: Net Interest Income Build (Volume x Rate)
B5: Avg interest-earning assets ($mm) | C5: 21447 | D5: 29587 | E5: 37913 | F5: =Assumptions!F6 -> 48502 | G5: =Assumptions!G6 -> 57833 | H5: =Assumptions!H6 -> 66570 | I5: =Assumptions!I6 -> 75247 | J5: =Assumptions!J6 -> 83533
B6: Avg yield on IEA | C6: 0.0956 | D6: 0.0949 | E6: 0.089 | F6: =Assumptions!F7 -> 0.0855 | G6: =Assumptions!G7 -> 0.0825 | H6: =Assumptions!H7 -> 0.08 | I6: =Assumptions!I7 -> 0.078 | J6: =Assumptions!J7 -> 0.0765
B7: Total interest income | C7: 2051 | D7: 2808 | E7: 3375 | F7: =F5*F6 -> 4146.921 | G7: =G5*G6 -> 4771.2225 | H7: =H5*H6 -> 5325.6 | I7: =I5*I6 -> 5869.266 | J7: =J5*J6 -> 6390.2745
B8: Total interest expense | C8: 789 | D8: 1091 | E8: 1156 | F8: =Assumptions!F17 -> 1400.393 | G8: =Assumptions!G17 -> 1606.268 | H8: =Assumptions!H17 -> 1773.205 | I8: =Assumptions!I17 -> 1895.168 | J8: =Assumptions!J17 -> 2017.845
B9: Net interest income | C9: 1262 | D9: 1716 | E9: 2219 | F9: =F7-F8 -> 2746.528 | G9: =G7-G8 -> 3164.9545 | H9: =H7-H8 -> 3552.395 | I9: =I7-I8 -> 3974.098 | J9: =J7-J8 -> 4372.4295
B10: NIM | C10: 0.0588 | D10: 0.058 | E10: 0.0585 | F10: =F9/F5 -> 0.056627108 | G10: =G9/G5 -> 0.054725753 | H10: =H9/H5 -> 0.053363302 | I10: =I9/I5 -> 0.052814039 | J10: =J9/J5 -> 0.052343738
A12: Noninterest Income Build (Activity x Price)
B13: Loan orig, sales, securitizations & servicing | C13: 409 | D13: 278 | E13: 243 | F13: =Assumptions!F29 -> 211 | G13: =Assumptions!G29 -> 184 | H13: =Assumptions!H29 -> 164 | I13: =Assumptions!I29 -> 150 | J13: =Assumptions!J29 -> 141
B14: Technology products and solutions | C14: 324 | D14: 351 | E14: 361 | F14: =Assumptions!F37 -> 400 | G14: =Assumptions!G37 -> 445 | H14: =Assumptions!H37 -> 495 | I14: =Assumptions!I37 -> 550 | J14: =Assumptions!J37 -> 609
B15: Loan platform fees | C15: 34 | D15: 142 | E15: 576 | F15: =Assumptions!F33 -> 750 | G15: =Assumptions!G33 -> 879 | H15: =Assumptions!H33 -> 990 | I15: =Assumptions!I33 -> 1080 | J15: =Assumptions!J33 -> 1161
B16: Other noninterest income | C16: 128 | D16: 188 | E16: 215 | F16: =Assumptions!F41 -> 265 | G16: =Assumptions!G41 -> 320 | H16: =Assumptions!H41 -> 374 | I16: =Assumptions!I41 -> 429 | J16: =Assumptions!J41 -> 485
B17: Total noninterest income | C17: 861 | D17: 958 | E17: 1394 | F17: =F13+F14+F15+F16 -> 1626 | G17: =G13+G14+G15+G16 -> 1828 | H17: =H13+H14+H15+H16 -> 2023 | I17: =I13+I14+I15+I16 -> 2209 | J17: =J13+J14+J15+J16 -> 2396
B19: Total net revenue | C19: 2123 | D19: 2675 | E19: 3613 | F19: =F9+F17 -> 4372.528 | G19: =G9+G17 -> 4992.9545 | H19: =H9+H17 -> 5575.395 | I19: =I9+I17 -> 6183.098 | J19: =J9+J17 -> 6768.4295
B20: YoY growth | D20: 0.26 | E20: 0.351 | F20: =F19/E19-1 -> 0.21022087 | G20: =G19/F19-1 -> 0.14189194 | H20: =H19/G19-1 -> 0.11665248 | I20: =I19/H19-1 -> 0.1089973 | J20: =J19/I19-1 -> 0.094666379
A22: Revenue Segment Allocation
B23: Lending | C23: 1371 | D23: 1485 | E23: 1849 | F23: 2164 | G23: 2484 | H23: 2806 | I23: 3134 | J23: 3447
B24: Technology Platform | C24: 352 | D24: 395 | E24: 450 | F24: 513 | G24: 577 | H24: 642 | I24: 706 | J24: 770
B25: Financial Services | C25: 437 | D25: 822 | E25: 1542 | F25: 1958 | G25: 2368 | H25: 2770 | I25: 3148 | J25: 3513
B26: Total (segment) | C26: 2160 | D26: 2702 | E26: 3841 | F26: =F23+F24+F25 -> 4635 | G26: =G23+G24+G25 -> 5429 | H26: =H23+H24+H25 -> 6218 | I26: =I23+I24+I25 -> 6988 | J26: =J23+J24+J25 -> 7730

Sheet Calcs
A1: SoFi Technologies, Inc. | C1: Hist | D1: Hist | E1: Hist | F1: Proj | G1: Proj | H1: Proj | I1: Proj | J1: Proj
A2: $ USD (amounts in $mm) | C2: 2023 | D2: 2024 | E2: 2025 | F2: 2026 | G2: 2027 | H2: 2028 | I2: 2029 | J2: 2030
A4: PP&E Schedule
B5: Beginning | F5: 416 | G5: =F8 -> 436 | H5: =G8 -> 446 | I5: =H8 -> 446 | J5: =I8 -> 436
B6: Depreciation | F6: =Assumptions!F89 -> 260 | G6: =Assumptions!G89 -> 290 | H6: =Assumptions!H89 -> 315 | I6: =Assumptions!I89 -> 340 | J6: =Assumptions!J89 -> 365
B7: CapEx | F7: =Assumptions!F88 -> 280 | G7: =Assumptions!G88 -> 300 | H7: =Assumptions!H88 -> 315 | I7: =Assumptions!I88 -> 330 | J7: =Assumptions!J88 -> 345
B8: Ending | E8: 416 | F8: =F5-F6+F7 -> 436 | G8: =G5-G6+G7 -> 446 | H8: =H5-H6+H7 -> 446 | I8: =I5-I6+I7 -> 436 | J8: =J5-J6+J7 -> 416
A10: Retained Earnings (Accumulated Deficit) Schedule
B11: Beginning | F11: -824 | G11: =F14 -> 314 | H11: =G14 -> 1717 | I11: =H14 -> 3368 | J11: =I14 -> 5290
B12: Dividends | F12: 0 | G12: 0 | H12: 0 | I12: 0 | J12: 0
B13: Net Income | F13: =ROUND((Assumptions!F44-Assumptions!F49-Assumptions!F66)*(1-Assumptions!F72),0) -> 1138 | G13: =ROUND((Assumptions!G44-Assumptions!G49-Assumptions!G66)*(1-Assumptions!G72),0) -> 1403 | H13: =ROUND((Assumptions!H44-Assumptions!H49-Assumptions!H66)*(1-Assumptions!H72),0) -> 1651 | I13: =ROUND((Assumptions!I44-Assumptions!I49-Assumptions!I66)*(1-Assumptions!I72),0) -> 1922 | J13: =ROUND((Assumptions!J44-Assumptions!J49-Assumptions!J66)*(1-Assumptions!J72),0) -> 2202 | K13: Linked from IS forecast output
B14: Ending | E14: -824 | F14: =F11+F13-F12 -> 314 | G14: =G11+G13-G12 -> 1717 | H14: =H11+H13-H12 -> 3368 | I14: =I11+I13-I12 -> 5290 | J14: =J11+J13-J12 -> 7492
A16: Debt Schedule
B17: Beginning | F17: 1815 | G17: =F20 -> 1515 | H17: =G20 -> 1315 | I17: =H20 -> 1165 | J17: =I20 -> 1065
B18: New issuance | F18: 0 | G18: 0 | H18: 0 | I18: 0 | J18: 0
B19: Repayment | F19: =Assumptions!F95 -> -300 | G19: =Assumptions!G95 -> -200 | H19: =Assumptions!H95 -> -150 | I19: =Assumptions!I95 -> -100 | J19: =Assumptions!J95 -> -50
B20: Ending | E20: 1815 | F20: =F17+F18+F19 -> 1515 | G20: =G17+G18+G19 -> 1315 | H20: =H17+H18+H19 -> 1165 | I20: =I17+I18+I19 -> 1065 | J20: =J17+J18+J19 -> 1015
A22: Interest Expense Build
B23: Avg deposits ($mm) | F23: =Assumptions!F11 -> 43133 | G23: =Assumptions!G11 -> 53632 | H23: =Assumptions!H11 -> 62902 | I23: =Assumptions!I11 -> 71433 | J23: =Assumptions!J11 -> 79341
B24: Cost of deposits | F24: =Assumptions!F12 -> 0.031 | G24: =Assumptions!G12 -> 0.029 | H24: =Assumptions!H12 -> 0.0275 | I24: =Assumptions!I12 -> 0.026 | J24: =Assumptions!J12 -> 0.025
B25: Deposit interest expense | F25: =F23*F24 -> 1337.123 | G25: =G23*G24 -> 1555.328 | H25: =H23*H24 -> 1729.805 | I25: =I23*I24 -> 1857.258 | J25: =J23*J24 -> 1983.525
B26: Avg debt ($mm) | F26: =Assumptions!F14 -> 1665 | G26: =Assumptions!G14 -> 1415 | H26: =Assumptions!H14 -> 1240 | I26: =Assumptions!I14 -> 1115 | J26: =Assumptions!J14 -> 1040
B27: Cost of debt | F27: =Assumptions!F15 -> 0.038 | G27: =Assumptions!G15 -> 0.036 | H27: =Assumptions!H15 -> 0.035 | I27: =Assumptions!I15 -> 0.034 | J27: =Assumptions!J15 -> 0.033
B28: Debt interest expense | F28: =F26*F27 -> 63.27 | G28: =G26*G27 -> 50.94 | H28: =H26*H27 -> 43.4 | I28: =I26*I27 -> 37.91 | J28: =J26*J27 -> 34.32
B29: Total interest expense | F29: =F28+F25 -> 1400.393 | G29: =G28+G25 -> 1606.268 | H29: =H28+H25 -> 1773.205 | I29: =I28+I25 -> 1895.168 | J29: =J28+J25 -> 2017.845

Sheet Income Statement
A1: SoFi Technologies, Inc.
A2: Consolidated Statements of Operations ($mm) | B2: 2021 | C2: 2022 | D2: 2023 | E2: 2024 | F2: 2025
A4: Interest Income
A5: Loans and securitizations | B5: 352 | C5: 760 | D5: 1944 | E5: 2602 | F5: 3146
A6: Other interest income | B6: 3 | C6: 14 | D6: 107 | E6: 206 | F6: 229
A7: Total interest income | B7: 355 | C7: 773 | D7: 2051 | E7: 2808 | F7: 3375
A9: Interest Expense
A10: Securitizations and warehouses | B10: 90 | C10: 110 | D10: 244 | E10: 112 | F10: 96
A11: Deposits | B11: 0 | C11: 60 | D11: 508 | E11: 930 | F11: 1014
A12: Corporate borrowings | B12: 10 | C12: 18 | D12: 37 | E12: 48 | F12: 46
A13: Other interest expense | B13: 2 | C13: 1 | D13: 0 | E13: 0 | F13: 1
A14: Total interest expense | B14: 103 | C14: 189 | D14: 789 | E14: 1091 | F14: 1156
A16: Net interest income | B16: 252 | C16: 584 | D16: 1262 | E16: 1716 | F16: 2219
A18: Noninterest Income
A19: Loan origination, sales, securitizations and servicing | B19: 480 | C19: 609 | D19: 409 | E19: 278 | F19: 243
A20: Technology products and solutions | B20: 192 | C20: 305 | D20: 324 | E20: 351 | F20: 361
A21: Loan platform fees | B21: 0 | C21: 0 | D21: 34 | E21: 142 | F21: 576
A22: Other noninterest income | B22: 60 | C22: 76 | D22: 128 | E22: 188 | F22: 215
A23: Total noninterest income | B23: 733 | C23: 989 | D23: 861 | E23: 958 | F23: 1394
A25: Total net revenue | B25: 985 | C25: 1574 | D25: 2123 | E25: 2675 | F25: 3613
A27: Provision for credit losses | B27: 8 | C27: 54 | D27: 55 | E27: 32 | F27: 30
A29: Noninterest Expense
A30: Technology and product development | B30: 276 | C30: 405 | D30: 511 | E30: 552 | F30: 648
A31: Sales and marketing | B31: 427 | C31: 618 | D31: 719 | E31: 796 | F31: 1095
A32: Cost of operations | B32: 257 | C32: 313 | D32: 380 | E32: 462 | F32: 609
A33: General and administrative | B33: 499 | C33: 502 | D33: 511 | E33: 600 | F33: 704
A34: Goodwill impairment | B34: 0 | C34: 0 | D34: 247 | E34: 0 | F34: 0
A35: Total noninterest expense | B35: 1458 | C35: 1838 | D35: 2369 | E35: 2410 | F35: 3057
A37: Income (loss) before income taxes | B37: -481 | C37: -319 | D37: -301 | E37: 233 | F37: 526
A38: Income tax (expense) benefit | B38: -3 | C38: -2 | D38: 0 | E38: 265 | F38: -45
A39: Net income (loss) | B39: -484 | C39: -320 | D39: -301 | E39: 499 | F39: 481
A41: Other Comprehensive Income (Loss)
A42: Unrealized gains (losses) on AFS securities, net | B42: -1 | C42: -7 | D42: 6 | E42: -7 | F42: 20
A43: Foreign currency translation adjustments, net | B43: 0 | C43: 0 | D43: 1 | E43: 0 | F43: 0
A44: Total other comprehensive income (loss) | B44: -1 | C44: -7 | D44: 7 | E44: -7 | F44: 19
A45: Comprehensive income (loss) | B45: -485 | C45: -327 | D45: -294 | E45: 492 | F45: 501
A47: Per Share Data
A48: EPS - basic | B48: -1 | C48: -0.4 | D48: -0.36 | E48: 0.46 | F48: 0.42
A49: EPS - diluted | B49: -1 | C49: -0.4 | D49: -0.36 | E49: 0.39 | F49: 0.39
A50: Weighted avg shares outstanding - basic (mm) | B50: 526.7 | C50: 900.9 | D50: 945 | E50: 1050.2 | F50: 1150.1
A51: Weighted avg shares outstanding - diluted (mm) | B51: 526.7 | C51: 900.9 | D51: 945 | E51: 1101.4 | F51: 1251.8

Sheet Balance Sheet
A1: SoFi Technologies, Inc.
A2: Consolidated Balance Sheets ($mm) | B2: 2022 | C2: 2023 | D2: 2024 | E2: 2025
A4: Assets
A5: Cash and cash equivalents | B5: 1422 | C5: 3085 | D5: 2538 | E5: 4929
A6: Restricted cash and restricted cash equivalents | B6: 424 | C6: 531 | D6: 171 | E6: 427
A7: Investment securities | B7: 397 | C7: 702 | D7: 1896 | E7: 2576
A8: Loans held for sale | B8: 13557 | C8: 15397 | D8: 17685 | E8: 22863
A9: Loans held for investment, at fair value | B9: 0 | C9: 6725 | D9: 8597 | E9: 13658
A10: Loans held for investment, at amortized cost | B10: 308 | C10: 836 | D10: 1246 | E10: 1517
A11: Servicing rights | B11: 150 | C11: 180 | D11: 342 | E11: 378
A12: Property, equipment and software | B12: 170 | C12: 217 | D12: 288 | E12: 416
A13: Goodwill | B13: 1623 | C13: 1394 | D13: 1394 | E13: 1394
A14: Intangible assets | B14: 442 | C14: 364 | D14: 298 | E14: 232
A15: Operating lease right-of-use assets | B15: 97 | C15: 90 | D15: 81 | E15: 94
A16: Other assets | B16: 417 | C16: 554 | D16: 1715 | E16: 2177
A17: Total assets | B17: 19008 | C17: 30075 | D17: 36251 | E17: 50660
A19: Liabilities
A20: Interest-bearing deposits | B20: 7266 | C20: 18569 | D20: 25861 | E20: 37387
A21: Noninterest-bearing deposits | B21: 77 | C21: 52 | D21: 117 | E21: 118
A22: Total deposits | B22: 7342 | C22: 18621 | D22: 25978 | E22: 37505
A23: Accounts payable, accruals and other liabilities | B23: 516 | C23: 550 | D23: 557 | E23: 744
A24: Operating lease liabilities | B24: 118 | C24: 109 | D24: 97 | E24: 106
A25: Debt | B25: 5486 | C25: 5233 | D25: 3093 | E25: 1815
A26: Residual interests classified as debt | B26: 17 | C26: 7 | D26: 1 | E26: 1
A27: Total liabilities | B27: 13479 | C27: 24520 | D27: 29726 | E27: 40171
A29: Temporary Equity
A30: Redeemable preferred stock | B30: 320 | C30: 320 | D30: 0 | E30: 0
A32: Permanent Equity
A33: Common stock | B33: 0 | C33: 0 | D33: 0 | E33: 0
A34: Additional paid-in capital | B34: 6720 | C34: 7040 | D34: 7839 | E34: 11303
A35: Accumulated other comprehensive income (loss) | B35: -8 | C35: -1 | D35: -8 | E35: 11
A36: Accumulated deficit | B36: -1504 | C36: -1804 | D36: -1306 | E36: -824
A37: Total permanent equity | B37: 5208 | C37: 5235 | D37: 6525 | E37: 10489
A38: Total liabilities and equity | B38: 19008 | C38: 30075 | D38: 36251 | E38: 50660

Sheet Cash Flow Statement
A1: SoFi Technologies, Inc.
A2: Consolidated Statements of Cash Flows ($mm) | B2: 2021 | C2: 2022 | D2: 2023 | E2: 2024 | F2: 2025
A4: Operating Activities
A5: Net income (loss) | B5: -484 | C5: -320 | D5: -301 | E5: 499 | F5: 481
A6: Share-based compensation expense | B6: 239 | C6: 306 | D6: 271 | E6: 246 | F6: 262
A7: Depreciation and amortization | B7: 102 | C7: 151 | D7: 201 | E7: 203 | F7: 234
A8: Goodwill impairment | B8: 0 | C8: 0 | D8: 247 | E8: 0 | F8: 0
A9: Deferred debt issuance and discount expense | B9: 18 | C9: 18 | D9: 20 | E9: 13 | F9: 11
A10: Gain on extinguishment of convertible debt | B10: 0 | C10: 0 | D10: -15 | E10: -63 | F10: 0
A11: Provision for credit losses | B11: 8 | C11: 54 | D11: 55 | E11: 32 | F11: 30
A12: Deferred income taxes | B12: 1 | C12: -3 | D12: -16 | E12: -287 | F12: 16
A13: Fair value changes in loans held for investment | B13: 0 | C13: 0 | D13: -44 | E13: -158 | F13: -351
A14: Fair value changes in securitization investments | B14: -7 | C14: 14 | D14: 0 | E14: -3 | F14: -2
A15: Fair value changes in warrant liabilities | B15: 107 | C15: 0 | D15: 0 | E15: 0 | F15: 0
A16: Fair value changes in residual interests classified as debt | B16: 23 | C16: 7 | D16: 0 | E16: 0 | F16: 0
... A24: Net cash used in operating activities | B24: -1350 | C24: -7256 | D24: -7227 | E24: -1120 | F24: -3742
A26: Investing Activities
A27: Purchases of property, equipment and software | B27: -52 | C27: -93 | D27: -111 | E27: -154 | F27: -242
A28: Capitalized software development costs | B28: 0 | C28: -11 | D28: -10 | E28: -9 | F28: -9
A29: Purchases of AFS investments | B29: -246 | C29: -45 | D29: -801 | E29: -2191 | F29: -1668
A30: Proceeds from sales of AFS investments | B30: 53 | C30: 23 | D30: 266 | E30: 186 | F30: 522
A31: Proceeds from maturities/paydowns of AFS investments | B31: 5 | C31: 15 | D31: 154 | E31: 808 | F31: 550
A32: Purchases of loans held for investment | B32: 0 | C32: 0 | D32: 0 | E32: 0 | F32: -2083
A33: Proceeds from sales of loans held for investment | B33: 0 | C33: 0 | D33: 0 | E33: 678 | F33: 393
A34: Other changes in loans held for investment, net | B34: 0 | C34: -174 | D34: -1362 | E34: -4183 | F34: -4199
A35: Proceeds from securitization investments | B35: 247 | C35: 119 | D35: 108 | E35: 80 | F35: 78
A36: Proceeds from non-securitization investments | B36: 110 | C36: 0 | D36: 5 | E36: 4 | F36: 42
A37: Purchases of non-securitization investments | B37: -22 | C37: 0 | D37: -67 | E37: -38 | F37: -102
A38: Acquisition of businesses, net of cash acquired | B38: 0 | C38: 59 | D38: -72 | E38: 0 | F38: 0
... A40: Net cash used in investing activities | B40: 110 | C40: -106 | D40: -1890 | E40: -4821 | F40: -6719
A42: Financing Activities
A43: Net change in deposits | B43: 0 | C43: 7153 | D43: 11232 | E43: 6954 | F43: 11249
A44: Proceeds from issuance of common stock | B44: 0 | C44: 0 | D44: 0 | E44: 0 | F44: 3186
A45: Payment of common stock issuance costs | B45: 0 | C45: 0 | D45: 0 | E45: 0 | F45: -3
A46: Net change in debt facilities | B46: -1187 | C46: 1418 | D46: 181 | E46: -1983 | F46: -1257
A47: Proceeds from other debt issuances | B47: 1192 | C47: 440 | D47: 340 | E47: 845 | F47: 0
A48: Repayment of other debt | B48: -913 | C48: -516 | D48: -800 | E48: -353 | F48: -29
A49: Payment of debt issuance costs | B49: -9 | C49: -8 | D49: -12 | E49: -8 | F49: -3
A50: Purchase of capped calls | B50: -114 | C50: 0 | D50: 0 | E50: -91 | F50: 0
A51: Unwind of capped calls | B51: 0 | C51: 0 | D51: 0 | E51: 10 | F51: 0
A52: Taxes paid related to net share settlement | B52: -43 | C52: -9 | D52: -15 | E52: -23 | F52: -65
A53: Proceeds from stock option exercises | B53: 25 | C53: 3 | D53: 1 | E53: 21 | F53: 7
A54: Proceeds from issuance of common stock under ESPP | B54: 0 | C54: 0 | D54: 0 | E54: 0 | F54: 26
... A63: Cash, restricted cash at end of period | B63: 768 | C63: 1846 | D63: 3616 | E63: 2709 | F63: 5357
A65: Supplemental Information
A66: Interest paid | B66: 95 | C66: 151 | D66: 720 | E66: 1118 | F66: 1146
A67: Income taxes paid, net | B67: 2 | C67: 3 | D67: 14 | E67: 27 | F67: 29

Sheet KPIs & Segments
A1: SoFi Technologies, Inc.
A2: Key Performance Indicators & Segment Information ($mm) | B2: 2021 | C2: 2022 | D2: 2023 | E2: 2024 | F2: 2025
A4: Segment Revenue ($mm)
A5: Lending | B5: 0 | C5: 0 | D5: 1371 | E5: 1485 | F5: 1849
A6: Technology Platform | B6: 0 | C6: 0 | D6: 352 | E6: 395 | F6: 450
A7: Financial Services | B7: 0 | C7: 0 | D7: 437 | E7: 822 | F7: 1542
A9: Segment Contribution Profit ($mm)
A10: Lending | B10: 0 | C10: 0 | D10: 823 | E10: 891 | F10: 1017
A11: Technology Platform | B11: 0 | C11: 0 | D11: 95 | E11: 127 | F11: 144
A12: Financial Services | B12: 0 | C12: 0 | D12: 0 | E12: 307 | F12: 793
A14: Segment Contribution Margin
A15: Lending | B15: 0 | C15: 0 | D15: 0.601 | E15: 0.6 | F15: 0.55
A16: Technology Platform | B16: 0 | C16: 0 | D16: 0.269 | E16: 0.321 | F16: 0.321
A17: Financial Services | B17: 0 | C17: 0 | D17: 0 | E17: 0.374 | F17: 0.514
A19: Non-GAAP Measures ($mm)
A20: Adjusted net revenue | B20: 0 | C20: 0 | D20: 2074 | E20: 2606 | F20: 3591
A22: Member & Product Metrics
A23: Total members (mm) | B23: 0 | C23: 0 | D23: 0 | E23: 10.1 | F23: 13.6
A24: Total products (mm) | B24: 0 | C24: 0 | D24: 0 | E24: 14.7 | F24: 20.2
A26: Technology Platform Metrics
A27: Total enabled accounts (mm) | B27: 0 | C27: 0 | D27: 0 | E27: 168 | F27: 128
A29: Balance Sheet Metrics ($mm)
A30: Total deposits | B30: 0 | C30: 7342 | D30: 18621 | E30: 25978 | F30: 37505
A31: Total loans (HFS + HFI) | B31: 0 | C31: 13865 | D31: 22958 | E31: 27529 | F31: 38037
A33: Key Ratios
A34: Net interest margin | B34: 0 | C34: 0 | D34: 0.0588 | E34: 0.058 | F34: 0.0585
A35: Total risk-based capital ratio (SoFi Technologies) | B35: 0 | C35: 0 | D35: 0 | E35: 0.162 | F35: 0.229
A36: Total risk-based capital ratio (SoFi Bank) | B36: 0 | C36: 0 | D36: 0 | E36: 0.175 | F36: 0.166
A38: Origination Volume ($mm)
A39: Personal loans | B39: 0 | C39: 0 | D39: 0 | E39: 0 | F39: 0
A40: Student loans | B40: 0 | C40: 0 | D40: 0 | E40: 0 | F40: 0
A41: Home loans | B41: 0 | C41: 0 | D41: 0 | E41: 0 | F41: 0
A43: Credit Quality
A44: Personal loan NCO ratio | B44: 0 | C44: 0 | D44: 0.0342 | E44: 0.0354 | F44: 0.0286
A45: Student loan NCO ratio | B45: 0 | C45: 0 | D45: 0.0044 | E45: 0.0064 | F45: 0.0072
A46: Credit card NCO ratio | B46: 0 | C46: 0 | D46: 0.1716 | E46: 0.1446 | F46: 0.0715
A47: Total loan NCO ratio | B47: 0 | C47: 0 | D47: 0.0266 | E47: 0.0263 | F47: 0.0207
A49: Share Information
A50: Shares outstanding (mm) | B50: 0 | C50: 933.9 | D50: 975.9 | E50: 1095.4 | F50: 1270.6
